Workbook
Name Eno_TM: #REF!
Name Eno_Tons: #REF!
Name Sum_T2: #REF!
Name Sum_TTM: #REF!
Name ti_tbl_50: #REF!
Name ti_tbl_69: #REF!

Sheet About
A1: SYVbT Start Year Vehicles by Technology
A3: Sources: | B3: LDVs, HDVs, Motorbikes
B4: BPS (Statistics Indonesia)
B5: Land Transportation Statistics 2019
B6: https://www.bps.go.id/publication/2020/11/20/ddce434c92536777bf07605d/statistik-transportasi-darat-2019.html
B7: Number of Cars, Buses, Trucks, Motorcycles by Province 2015-2019
B8: Table 3.3 and Appendix 8-12
B10: Aircraft
B11: BPS (Statistics Indonesia)
B12: Air Transportation Statistics 2019
B13: https://www.bps.go.id/publication/2020/11/20/231373341461207b51910a4a/statistik-transportasi-udara-2019.html
B14: The Number of Civil Aircraft Registered by Air Operator Certificate
B15: Table 3.9
B17: Ministry of Transportation
... B101: Page 9
A102: Notes
A103: BPS data only provide the number of motor vehicles by types, does not include fuel technology used
A104: Ministry of Transportation data also does not mention fuel technology used, except for trains
A105: Start year 2018

Sheet BPS LTS 2019
A1: Perkembangan Jumlah Kendaraan Bermotor Menurut Jenisnya
A2: The number of Motor Vehicles by Types
A3: Jenis Kendaraan Bermotor | B3: 2015 | C3: 2016 | D3: 2017 | E3: 2018 | F3: 2019
A4: Mobil penumpang (passenger car) | B4: 14304221 | C4: 14142958 | D4: 15968202 | E4: 16830698 | F4: 17592419 | G4: diesel/gasoline ration unknown
A5: Mobil bus (passenger bus) | B5: 296309 | C5: 304512 | D5: 313359 | E5: 322872 | F5: 331569 | G5: diesel
A6: Mobil barang (freight/truck) | B6: 4145857 | C6: 4326731 | D6: 4540902 | E6: 4797254 | F6: 5021888 | G6: diesel
A7: Sepeda motor (motorcycles) | B7: 88656931 | C7: 94531510 | D7: 100200245 | E7: 106657952 | F7: 112771136 | G7: gasoline
A8: Jumlah | B8: =SUM(B4:B7) -> 107403318 | C8: =SUM(C4:C7) -> 113305711 | D8: =SUM(D4:D7) -> 121022708 | E8: =SUM(E4:E7) -> 128608776 | F8: =SUM(F4:F7) -> 135717012
A10: Sumber | B10: Kepolisian Republik Indonesia
A11: Source | B11: Indonesian State Police

Sheet KCI Annual Report 2018
B2: Jumlah rangkaian yang beroperasi
B3: number of trainset operated
B4: 97 | C4: units
B5: (EMU: electric multiple unit)

Sheet Transjakarta Statistics
B2: Perkembangan armada bus transjakarta yang beroperasi tahun 2016-2019
B3: Number of transjakarta fleets operated 2016-2019
B5: Jenis Layanan | C5: 2016 | D5: 2017 | E5: 2018 | F5: 2019
B6: BRT | C6: 524 | D6: 581 | E6: 750 | F6: 783
B7: Mikrotrans | C7: 0 | D7: 445 | E7: 530 | F7: 1368
B8: Angkutan umum integrasi | C8: 225 | D8: 310 | E8: 480 | F8: 602
B9: Transjabodetabek | C9: 113 | D9: 106 | E9: 132 | F9: 193
B10: Rusun | C10: 14 | D10: 33 | E10: 45 | F10: 47
B11: Royaltrans | C11: 0 | D11: 0 | E11: 19 | F11: 82
B12: Bus wisata | C12: 15 | D12: 17 | E12: 21 | F12: 25
B13: Angkutan umum lain | C13: 5 | D13: 21 | E13: 6 | F13: 31
B14: Transjakarta cares | C14: 0 | D14: 7 | E14: 20 | F14: 18
B15: Total | C15: =SUM(C6:C13) -> 896 | D15: =SUM(D6:D13) -> 1513 | E15: =SUM(E6:E13) -> 1983 | F15: =SUM(F6:F13) -> 3131

Sheet EV
B2: Number of Electric Vehicles
B4: No | C4: Jenis | D4: Tahun / year
B5: No | C5: Type | D5: 2019
B6: 1 | C6: two-wheelers | D6: 0
B7: 2 | C7: three-wheelers | D7: 0
B8: 3 | C8: four-wheelers | D8: 0
B9: 4 | C9: Bus | D9: 0

Sheet BUKU IT 2019 & Statistik Transp
B1: Transportasi Jalan
B2: Land Transportatiom
B3: Jumlah Angkutan antar kota antar provinsi (AKAP) dan Pariwisata
B4: The Number of Inter city coach bus and tour bus
B5: Tabel / Table | C5: A.1.4.02 | D5: Page 1-18
B7: Tahun | C7: AKAP | D7: Pariwisata | E7: Total
B8: year | C8: inter city, inter province | D8: tour bus
B9: 2014 | C9: 22544 | D9: 19841 | E9: =D9+C9 -> 42385
B10: 2015 | C10: 23464 | D10: 21277 | E10: =D10+C10 -> 44741
B11: 2016 | C11: 22742 | D11: 22971 | E11: =D11+C11 -> 45713
B12: 2017 | C12: 16238 | D12: 24524 | E12: =D12+C12 -> 40762
B13: 2018 | C13: 16353 | D13: 24679 | E13: =D13+C13 -> 41032
B14: 2019 | C14: 12367 | D14: 12961 | E14: =D14+C14 -> 25328
B16: Jumlah Kendaraan Angkutan Alat Berat, B3, Antar-Jemput Antar Provinsi, Sewa dan Taksi Bandara
B17: Number of Heavy Equipment, Dangerous Goods Transport, Inter-provincial Shuttle Services, and Carter and Airports Taxi Service Operators
B18: Tabel / Table | C18: A.1.4.06 | D18: Page 1-21
B20: No | C20: Uraian | D20: Satuan | E20: 2014 | F20: 2015 | G20: 2016 | H20: 2017 | I20: 2018 | J20: 2019
C21: Description | D21: Unit
B22: 1 | C22: Alat Berat | D22: Unit | E22: 109 | F22: 1087 | G22: 1129 | H22: 1158 | I22: 1341 | J22: 229 | L22: passenger car | M22: =SUM(J26:J28) -> 1344
C23: Heavy Equipment | D23: Units
B24: 2 | C24: Bahan Berbahaya dan Beracun | D24: Unit | E24: 2716 | F24: 10130 | G24: 11942 | H24: 13332 | I24: 18825 | J24: 8984
C25: Dangerous Goods | D25: Units
B26: 3 | C26: Antar Jemput antar Provinsi | D26: Unit | E26: 2681 | F26: 2811 | G26: 1886 | H26: 2539 | I26: 3078 | J26: 937
C27: inter-provincial shuttle | D27: Units
B28: 4 | C28: Sewa | D28: Unit | E28: 0 | F28: 0 | G28: 0 | H28: 2341 | I28: 2495 | J28: 407
C29: Rent Services | D29: Units
B33: Jumlah Bus dan Truk Siap Operasi Perum Damri 2014-2018
B34: Number of Available-for-operation Buses & Trucks of Perum Damri 2014-2018
B35: Tabel / Table | C35: A.1.4.07 | D35: Page 1-22
B37: No | C37: Uraian | D37: Satuan | E37: 2014 | F37: 2015 | G37: 2016 | H37: 2017 | I37: 2018 | J37: 2019 | L37: freight | M37: =J51 -> 57
D38: Unit | L38: passenger | M38: =SUM(J39:J49) -> 1782
B39: 1 | C39: Bus Kota | D39: Unit | E39: 422 | F39: 405 | G39: 565 | H39: 201 | I39: 451 | J39: 436
C40: City Bus | D40: Units
B41: 2 | C41: Bus Antar Kota | D41: Unit | E41: 378 | F41: 378 | G41: 395 | H41: 406 | I41: 360 | J41: 385
C42: Intercity Bus | D42: Units
B43: 3 | C43: Bus Antar Negara | D43: Unit | E43: 11 | F43: 11 | G43: 12 | H43: 11 | I43: 8 | J43: 12
C44: Intercontinental Bus | D44: Units
B45: 4 | C45: Bus Wisata | D45: Unit | E45: 31 | F45: 26 | G45: 27 | H45: 7 | I45: 5 | J45: 15
C46: Tour Bus | D46: Units
B47: 5 | C47: Bus Perintis | D47: Unit | E47: 356 | F47: 367 | G47: 388 | H47: 741 | I47: 479 | J47: 461
C48: pioneer bus | D48: Units
B49: 6 | C49: Bus Bandar Udara | D49: Unit | E49: 392 | F49: 406 | G49: 423 | H49: 430 | I49: 445 | J49: 473
C50: airport bus | D50: Units
B51: 7 | C51: Truk Boks | D51: Unit | E51: 68 | F51: 68 | G51: 51 | H51: 54 | I51: 63 | J51: 57
C52: container trucks | D52: Units
B54: Transportasi Laut
B55: Sea Transport
B56: Jumlah Armada Angkutan Penyeberangan
B57: Number of Ferry Boat
B58: Tabel / Table | C58: A.1.4.14 | D58: Page 1-27
B60: No | C60: Uraian | D60: Satuan | E60: 2014 | F60: 2015 | G60: 2016 | H60: 2017 | I60: 2018 | J60: 2019
C61: Description | D61: Unit
C62: Kapal / Boats | D62: Units | E62: =SUM(E63:E64) -> 267 | F62: =SUM(F63:F64) -> 345 | G62: =SUM(G63:G64) -> 354 | H62: =SUM(H63:H64) -> 380 | I62: =SUM(I63:I64) -> 392 | J62: =SUM(J63:J64) -> 412 | K62: Ferry boat is assumed to be used for freight only
B63: 1 | C63: RoRo | D63: Units | E63: 265 | F63: 331 | G63: 354 | H63: 380 | I63: 392 | J63: 412
B64: 2 | C64: LCT | D64: Units | E64: 2 | F64: 14 | G64: 0 | H64: 0 | I64: 0 | J64: 0
B67: Jumlah Armada Angkatan Laut menurut Kepemilikan
B68: Number of Ocean Liners Ownership
B69: Tabel/Table | C69: A.2.1.01 | D69: Page 2-1
B71: No | C71: Uraian | D71: Satuan | E71: 2014 | F71: 2015 | G71: 2016 | H71: 2017 | I71: 2018 | J71: 2019
C72: Description | D72: Unit
B73: 1 | C73: Kapal Nasional | D73: Unit | E73: 14156 | F73: 16142 | G73: 24046 | H73: 23823 | I73: 25559 | J73: 32634 | K73: identical to A.2.1.02 below
C74: National Ship | D74: Units
B75: 2 | C75: Armada Charter Asing | D75: Unit | E75: 295 | F75: 182 | G75: 233 | H75: 63 | I75: 92 | J75: 51
C76: Foreign Charter Ship | D76: Units
B77: 3 | C77: Kapal Keagenan Asing | D77: Unit | E77: 4320 | F77: 4284 | G77: 9191 | H77: 9122 | I77: 7612 | J77: 8237
C78: Ship of Foreign Agent | D78: Units
B79: Total | D79: Unit | E79: =SUM(E73:E78) -> 18771 | F79: =SUM(F73:F78) -> 20608 | G79: =SUM(G73:G78) -> 33470 | H79: =SUM(H73:H78) -> 33008 | I79: =SUM(I73:I78) -> 33263 | J79: =SUM(J73:J78) -> 40922
B82: Jumlah Armada Angkatan Laut Menurut Jenis Pelayaran
B83: Number of Ocean Liners by Type of Service
B84: Tabel/table | C84: A.2.1.02 | D84: Page 2-2
B86: No | C86: Uraian | D86: Satuan | E86: 2014 | F86: 2015 | G86: 2016 | H86: 2017 | I86: 2018 | J86: 2019
C87: Description | D87: Unit | L87: freight | M87: =J88+J94 -> 30825
B88: 1 | C88: Angkatan Laut (Pelayaran) | D88: Unit | E88: 12300 | F88: 14231 | G88: 21866 | H88: 21644 | I88: 23622 | J88: 27367 | L88: passenger | M88: =J90+J92 -> 1809
C89: Shipping | D89: Units
B90: 2 | C90: Pelayaran Rakyat | D90: Unit | E90: 1357 | F90: 1371 | G90: 1384 | H90: 1516 | I90: 1516 | J90: 1649
C91: Traditional Fleet | D91: Units
B92: 3 | C92: Perintis | D92: Unit | E92: 86 | F92: 60 | G92: 68 | H92: 89 | I92: 160 | J92: 160
C93: Pioneer | D93: Units
B94: 4 | C94: Angkatan Laut Khusus | D94: Unit | E94: 1856 | F94: 1911 | G94: 2180 | H94: 2179 | I94: 1937 | J94: 3458
C95: Special Shipping | D95: Units
B96: Total | D96: Unit | E96: =SUM(E88:E95) -> 15599 | F96: =SUM(F88:F95) -> 17573 | G96: =SUM(G88:G95) -> 25498 | H96: =SUM(H88:H95) -> 25428 | I96: =SUM(I88:I95) -> 27235 | J96: =SUM(J88:J95) -> 32634
B99: Jumlah Armada Angkutan Laut menurut Perusahaan Pelayaran BUMN
B100: Number of Ships by State Owned Shipping Agents Enterprises Liners
B101: Tabel/Table | C101: A.2.1.03 | D101: Page 2-3
B103: No | C103: Uraian | D103: Satuan | E103: 2014 | F103: 2015 | G103: 2016 | H103: 2017 | I103: 2018 | J103: 2019
C104: Description | D104: Unit | L104: freight | M104: =J108+J111+J114 -> 39
B105: 1 | C105: PT Pelni | L105: passenger | M105: =J106 -> 26
C106: Kapal Penumpang | D106: Unit | E106: 25 | F106: 25 | G106: 26 | H106: 26 | I106: 26 | J106: 26
C107: Passenger Fleet | D107: Units
C108: Kapal Barang | D108: Unit | E108: 3 | F108: 3 | G108: 8 | H108: 8 | I108: 8 | J108: 8
C109: Goods Fleet | D109: Units
B110: 2 | C110: PT Djakarta Lloyd
C111: Kapal barang | D111: Unit | E111: 16 | F111: 16 | G111: 17 | H111: 17 | I111: 17 | J111: 18
C112: Goods Fleet | D112: Units
B113: 3 | C113: PT Bahtera Adhiguna
C114: Kapal barang | D114: Unit | E114: 8 | F114: 8 | G114: 24 | H114: 19 | I114: 13 | J114: 13
C115: Goods Fleet | D115: Units
B116: Total | D116: Unit | E116: =SUM(E105:E113) -> 44 | F116: =SUM(F105:F113) -> 44 | G116: =SUM(G105:G113) -> 51 | H116: =SUM(H105:H113) -> 51 | I116: =SUM(I105:I113) -> 51 | J116: =SUM(J105:J113) -> 52
B119: Jumlah dan Jenis Kapal Pengerukan Alur Pelayaran / Kolam Pelabuhan dari Dana APBN
B120: Number and Type of Dredging Vessels Funded by Government
...

Sheet SYVbT-passenger
A1: Number of Vehicles | B1: battery electric vehicle | C1: natural gas vehicle | D1: gasoline vehicle | E1: diesel vehicle | F1: plugin hybrid vehicle | G1: LPG vehicle | H1: hydrogen vehicle
A2: LDVs | B2: =EV!D8 -> 0 | C2: 0 | D2: ='BPS LTS 2019'!F4 -> 17592419 | E2: 0 | F2: 0 | G2: 0 | H2: 0
A3: HDVs | B3: 0 | C3: 0 | D3: 0 | E3: ='BPS LTS 2019'!F5 -> 331569 | F3: 0 | G3: 0 | H3: 0
A4: aircraft | B4: 0 | C4: 0 | D4: ='BUKU IT 2019 & Statistik Transp'!I174 -> 1197 | E4: 0 | F4: 0 | G4: 0 | H4: 0
A5: rail | B5: ='KCI Annual Report 2018'!B4 -> 97 | C5: 0 | D5: 0 | E5: ='BUKU IT 2019 & Statistik Transp'!J198+'BUKU IT 2019 & Statistik Transp'!J253+'BUKU IT 2019 & Statistik Transp'!J267+'BUKU IT 2019 & Statistik Transp'!J275 -> 667 | F5: 0 | G5: 0 | H5: 0
A6: ships | B6: 0 | C6: 0 | D6: 0 | E6: ='BUKU IT 2019 & Statistik Transp'!J149+'BUKU IT 2019 & Statistik Transp'!M105+'BUKU IT 2019 & Statistik Transp'!M88 -> 2222 | F6: 0 | G6: 0 | H6: 0
A7: motorbikes | B7: =EV!D6 -> 0 | C7: 0 | D7: ='BPS LTS 2019'!F7 -> 112771136 | E7: 0 | F7: 0 | G7: 0 | H7: 0

Sheet SYVbT-freight
A1: Number of Vehicles | B1: battery electric vehicle | C1: natural gas vehicle | D1: gasoline vehicle | E1: diesel vehicle | F1: plugin hybrid vehicle | G1: LPG vehicle | H1: hydrogen vehicle
A2: LDVs | B2: 0 | C2: 0 | D2: 0 | E2: 0 | F2: 0 | G2: 0 | H2: 0
A3: HDVs | B3: 0 | C3: 0 | D3: 0 | E3: ='BPS LTS 2019'!F6 -> 5021888 | F3: 0 | G3: 0 | H3: 0
A4: aircraft | B4: 0 | C4: 0 | D4: 0 | E4: 0 | F4: 0 | G4: 0 | H4: 0
A5: rail | B5: 0 | C5: 0 | D5: 0 | E5: 0 | F5: 0 | G5: 0 | H5: 0
A6: ships | B6: 0 | C6: 0 | D6: 0 | E6: ='BUKU IT 2019 & Statistik Transp'!J62+'BUKU IT 2019 & Statistik Transp'!J88+'BUKU IT 2019 & Statistik Transp'!J108+'BUKU IT 2019 & Statistik Transp'!J111+'BUKU IT 2019 & Statistik Transp'!J114 -> 27818 | F6: 0 | G6: 0 | H6: 0
A7: motorbikes | B7: 0 | C7: 0 | D7: 0 | E7: 0 | F7: 0 | G7: 0 | H7: 0

Sheet AEO 7
B1: ref2019.d111618a | C1: 2017 | D1: 2018 | E1: 2019 | F1: 2020 | G1: 2021 | H1: 2022 | I1: 2023 | J1: 2024 | K1: 2025 | L1: 2026 | M1: 2027 | N1: 2028 | O1: 2029 | P1: 2030 | Q1: 2031 | R1: 2032 | S1: 2033 | T1: 2034 | U1: 2035 | V1: 2036 | W1: 2037 | X1: 2038 | Y1: 2039 | Z1: 2040 | AA1: 2041 | AB1: 2042 | AC1: 2043 | AD1: 2044 | AE1: 2045 | AF1: 2046 | AG1: 2047 | AH1: 2048 | AI1: 2049 | AJ1: 2050
C3: Report | D3: Annual Energy Outlook 2019
C4: Scenario | D4: ref2019 | G4: Reference case
C5: Datekey | D5: d111618a
C6: Release Date | E6: January 2019
A10: TKI000 | B10: 7. Transportation Sector Key Indicators and Delivered Energy Consumption
AK12: 2018-
B13: Key Indicators and Consumption | C13: 2017 | D13: 2018 | E13: 2019 | F13: 2020 | G13: 2021 | H13: 2022 | I13: 2023 | J13: 2024 | K13: 2025 | L13: 2026 | M13: 2027 | N13: 2028 | O13: 2029 | P13: 2030 | Q13: 2031 | R13: 2032 | S13: 2033 | T13: 2034 | U13: 2035 | V13: 2036 | W13: 2037 | X13: 2038 | Y13: 2039 | Z13: 2040 | AA13: 2041 | AB13: 2042 | AC13: 2043 | AD13: 2044 | AE13: 2045 | AF13: 2046 | AG13: 2047 | AH13: 2048 | AI13: 2049 | AJ13: 2050 | AK13: 2050
B15: Key Indicators
B16: Travel Indicators
B17: (billion vehicle miles traveled)
A18: TKI000:ba_Light-DutyVeh | B18: Light-Duty Vehicles less than 8,501 pounds | C18: 2835.9963 | D18: 2883.0076 | E18: 2922.0107 | F18: 2951.3701 | G18: 2973.1135 | H18: 2990.5669 | I18: 3001.8533 | J18: 3009.8223 | K18: 3017.5295 | L18: 3036.9685 | M18: 3057.3228 | N18: 3077.249 | O18: 3092.1702 | P18: 3107.1677 | Q18: 3121.2544 | R18: 3134.6589 | S18: 3147.7898 | T18: 3160.5212 | U18: 3171.6843 | V18: 3188.4839 | W18: 3207.2163 | X18: 3227.2656 | Y18: 3247.8088 | Z18: 3268.6482 | AA18: 3289.6279 | AB18: 3310.8071 | AC18: 3332.4702 | AD18: 3354.2253 | AE18: 3375.4978 | AF18: 3397.093 | AG18: 3417.8025 | AH18: 3436.7725 | AI18: 3455.405 | AJ18: 3472.6509 | AK18: 0.005832
A19: TKI000:ba_CommercialLig | B19: Commercial Light Trucks 1/ | C19: 97.025139 | D19: 99.47998 | E19: 101.74947 | F19: 103.4052 | G19: 104.64126 | H19: 105.86214 | I19: 107.08696 | J19: 108.28252 | K19: 109.68753 | L19: 111.26117 | M19: 112.82363 | N19: 114.57213 | O19: 116.06745 | P19: 117.52844 | Q19: 119.13098 | R19: 120.71562 | S19: 122.31748 | T19: 123.99625 | U19: 125.76493 | V19: 127.5814 | W19: 129.47594 | X19: 131.41042 | Y19: 133.23712 | Z19: 135.04831 | AA19: 136.89467 | AB19: 138.72411 | AC19: 140.66197 | AD19: 142.69688 | AE19: 144.86681 | AF19: 147.03716 | AG19: 149.26863 | AH19: 151.51474 | AI19: 153.70024 | AJ19: 155.92755 | AK19: 0.014144
A20: TKI000:ba_FreightTrucks | B20: Freight Trucks greater than 10,000 pounds | C20: 289.55078 | D20: 297.04279 | E20: 305.55014 | F20: 309.82758 | G20: 312.85162 | H20: 316.75717 | I20: 320.85107 | J20: 324.86124 | K20: 329.14508 | L20: 333.67548 | M20: 337.54114 | N20: 341.87463 | O20: 345.66849 | P20: 349.52676 | Q20: 353.97122 | R20: 358.05899 | S20: 362.21085 | T20: 366.77152 | U20: 371.79031 | V20: 376.70877 | W20: 381.89111 | X20: 387.09091 | Y20: 391.7778 | Z20: 396.25085 | AA20: 400.73352 | AB20: 405.11423 | AC20: 409.46503 | AD20: 414.23755 | AE20: 419.31766 | AF20: 424.31128 | AG20: 429.53677 | AH20: 434.97501 | AI20: 440.03778 | AJ20: 445.35059 | AK20: 0.012736
A21: TKI000:buspassmiles | B21: (billion passenger miles traveled)
A22: TKI000:railpassmiles | B22: Bus Transportation | C22: 205.3141 | D22: 206.33447 | E22: 207.28133 | F22: 208.21898 | G22: 209.15999 | H22: 210.08101 | I22: 210.95932 | J22: 211.85976 | K22: 212.84192 | L22: 213.80716 | M22: 214.7581 | N22: 215.72217 | O22: 216.6627 | P22: 217.55475 | Q22: 218.4193 | R22: 219.26325 | S22: 220.02628 | T22: 220.74793 | U22: 221.43126 | V22: 222.08023 | W22: 222.69884 | X22: 223.28966 | Y22: 223.85547 | Z22: 224.39857 | AA22: 224.92021 | AB22: 225.42384 | AC22: 225.91266 | AD22: 226.39052 | AE22: 226.8633 | AF22: 227.33708 | AG22: 227.81938 | AH22: 228.31657 | AI22: 228.83379 | AJ22: 229.37569 | AK22: 0.003314
B23: Passenger Rail | C23: 39.645065 | D23: 39.896538 | E23: 40.432911 | F23: 40.870899 | G23: 41.314678 | H23: 41.73423 | I23: 42.149014 | J23: 42.569008 | K23: 43.00835 | L23: 43.455452 | M23: 43.862602 | N23: 44.347565 | O23: 44.702797 | P23: 45.127457 | Q23: 45.522034 | R23: 45.91967 | S23: 46.329922 | T23: 46.726559 | U23: 47.114132 | V23: 47.480175 | W23: 47.866169 | X23: 48.231972 | Y23: 48.586067 | Z23: 48.930767 | AA23: 49.274044 | AB23: 49.600204 | AC23: 49.935272 | AD23: 50.266663 | AE23: 50.58802 | AF23: 50.906265 | AG23: 51.242321 | AH23: 51.570972 | AI23: 51.911625 | AJ23: 52.242622 | AK23: 0.008461
A24: TKI000:ba_Air | B24: (billion seat miles available)
B25: Air | C25: 1173.5535 | D25: 1188.8688 | E25: 1213.5831 | F25: 1235.7582 | G25: 1255.5334 | H25: 1273.8647 | I25: 1293.121 | J25: 1313.7976 | K25: 1336.5613 | L25: 1360.6853 | M25: 1384.1838 | N25: 1413.3251 | O25: 1439.0891 | P25: 1464.7561 | Q25: 1491.2557 | R25: 1517.9093 | S25: 1544.9697 | T25: 1572.8766 | U25: 1600.8291 | V25: 1628.6422 | W25: 1656.9591 | X25: 1686.0646 | Y25: 1715.3379 | Z25: 1745.1476 | AA25: 1774.89 | AB25: 1805.4565 | AC25: 1836.7898 | AD25: 1868.7915 | AE25: 1901.8862 | AF25: 1935.8136 | AG25: 1970.7146 | AH25: 2005.9568 | AI25: 2040.9736 | AJ25: 2075.53 | AK25: 0.017565
A26: TKI000:ba_Rail | B26: (billion ton miles traveled)
A27: TKI000:ba_DomesticShipp | B27: Rail | C27: 1787.5374 | D27: 1788.7363 | E27: 1812.1239 | F27: 1776.697 | G27: 1769.3909 | H27: 1761.3311 | I27: 1760.6548 | J27: 1779.4348 | K27: 1793.8669 | L27: 1809.7041 | M27: 1816.5015 | N27: 1828.6771 | O27: 1865.3177 | P27: 1893.7076 | Q27: 1898.4255 | R27: 1901.764 | S27: 1914.6235 | T27: 1915.7354 | U27: 1929.5085 | V27: 1945.8417 | W27: 1957.7838 | X27: 1973.6379 | Y27: 1989.265 | Z27: 2003.4233 | AA27: 2016.8127 | AB27: 2027.808 | AC27: 2037.5172 | AD27: 2052.5413 | AE27: 2069.3689 | AF27: 2081.4026 | AG27: 2096.3093 | AH27: 2113.6646 | AI27: 2130.5164 | AJ27: 2149.3511 | AK27: 0.005756
B28: Domestic Shipping | C28: 447.72595 | D28: 444.52057 | E28: 435.79327 | F28: 426.55743 | G28: 415.90875 | H28: 407.28922 | I28: 397.98157 | J28: 387.66037 | K28: 377.81396 | L28: 368.69983 | M28: 359.4342 | N28: 349.28803 | O28: 339.07843 | P28: 328.70654 | Q28: 324.04404 | R28: 318.92053 | S28: 314.1752 | T28: 309.60535 | U28: 305.29675 | V28: 300.71558 | W28: 296.95438 | X28: 292.93774 | Y28: 288.72516 | Z28: 284.26468 | AA28: 282.85895 | AB28: 281.43481 | AC28: 279.57016 | AD28: 278.13324 | AE28: 276.71732 | AF28: 275.62259 | AG28: 274.33264 | AH28: 273.4216 | AI28: 271.81381 | AJ28: 270.6106 | AK28: -0.01539
B30: Energy Efficiency Indicators
A31: TKI000:ca_AvgCAFEStand | B31: (miles per gallon)
A32: TKI000:ca_CarCAFEStand | B32: New Light-Duty Vehicle CAFE Standard 2/ | C32: 33.231037 | D32: 33.824409 | E32: 34.663242 | F32: 36.011749 | G32: 37.960045 | H32: 39.711666 | I32: 41.675518 | J32: 43.356022 | K32: 45.640671 | L32: 45.687145 | M32: 45.835239 | N32: 45.955185 | O32: 46.097694 | P32: 46.204849 | Q32: 46.309845 | R32: 46.409691 | S32: 46.480145 | T32: 46.55238 | U32: 46.617996 | V32: 46.679771 | W32: 46.724213 | X32: 46.772335 | Y32: 46.816681 | Z32: 46.858173 | AA32: 46.889629 | AB32: 46.931118 | AC32: 46.960442 | AD32: 46.978397 | AE32: 46.999207 | AF32: 47.003643 | AG32: 47.005432 | AH32: 47.012489 | AI32: 47.006405 | AJ32: 46.994553 | AK32: 0.010329
A33: TKI000:ca_TwukCAFEStand | B33: New Car 2/ | C33: 38.552597 | D33: 39.421032 | E33: 40.955711 | F33: 42.739193 | G33: 44.647316 | H33: 46.77142 | I33: 49.107544 | J33: 50.479019 | K33: 53.163414 | L33: 53.165295 | M33: 53.182201 | N33: 53.182201 | O33: 53.192871 | P33: 53.192871 | Q33: 53.19289 | R33: 53.192928 | S33: 53.19294 | T33: 53.193012 | U33: 53.19305 | V33: 53.193115 | W33: 53.193115 | X33: 53.193176 | Y33: 53.194641 | Z33: 53.19503 | AA33: 53.195042 | AB33: 53.197578 | AC33: 53.197578 | AD33: 53.197578 | AE33: 53.197632 | AF33: 53.197948 | AG33: 53.19817 | AH33: 53.200935 | AI33: 53.200935 | AJ33: 53.200947 | AK33: 0.009412
A34: TKI000:ca_NewVehCred | B34: New Light Truck 2/ | C34: 28.836378 | D34: 29.179739 | E34: 29.623194 | F34: 30.619411 | G34: 32.520454 | H34: 33.934437 | I34: 35.478027 | J34: 37.151321 | K34: 38.954666 | L34: 38.965858 | M34: 38.966263 | N34: 38.96772 | O34: 38.967854 | P34: 38.969234 | Q34: 38.96973 | R34: 38.970463 | S34: 38.971207 | T34: 38.971207 | U34: 38.97168 | V34: 38.972107 | W34: 38.972855 | X34: 38.973167 | Y34: 38.973568 | Z34: 38.97398 | AA34: 38.974487 | AB34: 38.974743 | AC34: 38.975323 | AD34: 38.975731 | AE34: 38.976013 | AF34: 38.976311 | AG34: 38.976658 | AH34: 38.97686 | AI34: 38.977299 | AJ34: 38.977531 | AK34: 0.009088
A35: TKI000:ca_NewCarCred | B35: Compliance New Light-Duty Vehicle 3/ | C35: 33.453663 | D35: 33.999165 | E35: 34.852367 | F35: 36.294296 | G35: 38.366337 | H35: 40.360031 | I35: 42.344337 | J35: 43.980865 | K35: 46.242016 | L35: 46.369415 | M35: 46.563313 | N35: 46.693798 | O35: 46.881443 | P35: 47.023907 | Q35: 47.195477 | R35: 47.396988 | S35: 47.630604 | T35: 47.772404 | U35: 47.898392 | V35: 48.021744 | W35: 48.10815 | X35: 48.228577 | Y35: 48.328503 | Z35: 48.415863 | AA35: 48.528599 | AB35: 48.589287 | AC35: 48.621609 | AD35: 48.628242 | AE35: 48.712502 | AF35: 48.731789 | AG35: 48.745567 | AH35: 48.774223 | AI35: 48.780106 | AJ35: 48.78289 | AK35: 0.011346
A36: TKI000:ca_NewTwukCred | B36: New Car 3/ | C36: 39.21965 | D36: 40.208176 | E36: 41.560863 | F36: 43.481544 | G36: 45.514778 | H36: 47.57579 | I36: 49.836277 | J36: 51.162941 | K36: 53.624893 | L36: 53.706425 | M36: 53.805222 | N36: 53.878506 | O36: 54.057693 | P36: 54.205578 | Q36: 54.410496 | R36: 54.644573 | S36: 54.846699 | T36: 55.040737 | U36: 55.223377 | V36: 55.398727 | W36: 55.53233 | X36: 55.66367 | Y36: 55.798275 | Z36: 55.916218 | AA36: 55.95874 | AB36: 56.004444 | AC36: 56.03677 | AD36: 56.041607 | AE36: 56.047878 | AF36: 56.084099 | AG36: 56.117535 | AH36: 56.169254 | AI36: 56.202084 | AJ36: 56.231964 | AK36: 0.010537
A37: TKI000:ca_TestedNewVeh | B37: New Light Truck 3/ | C37: 28.781832 | D37: 28.981468 | E37: 29.56732 | F37: 30.629837 | G37: 32.641251 | H37: 34.464329 | I37: 36.083229 | J37: 37.714725 | K37: 39.624859 | L37: 39.715786 | M37: 39.738346 | N37: 39.70694 | O37: 39.659554 | P37: 39.607239 | Q37: 39.559658 | R37: 39.545506 | S37: 39.663071 | T37: 39.61974 | U37: 39.567665 | V37: 39.521477 | W37: 39.476704 | X37: 39.484936 | Y37: 39.461704 | Z37: 39.433529 | AA37: 39.534775 | AB37: 39.520966 | AC37: 39.49025 | AD37: 39.460434 | AE37: 39.564434 | AF37: 39.558979 | AG37: 39.551521 | AH37: 39.546413 | AI37: 39.541836 | AJ37: 39.546425 | AK37: 0.00976
A38: TKI000:ca_TestedNewCar | B38: Tested New Light-Duty Vehicle 4/ | C38: 32.92057 | D38: 33.597721 | E38: 34.642803 | F38: 36.290867 | G38: 38.362621 | H38: 40.356014 | I38: 42.339863 | J38: 43.975994 | K38: 46.236908 | L38: 46.364128 | M38: 46.557949 | N38: 46.688419 | O38: 46.876041 | P38: 47.018448 | Q38: 47.189926 | R38: 47.391357 | S38: 47.624954 | T38: 47.766644 | U38: 47.892525 | V38: 48.015766 | W38: 48.102093 | X38: 48.222412 | Y38: 48.322189 | Z38: 48.409386 | AA38: 48.522015 | AB38: 48.582489 | AC38: 48.614666 | AD38: 48.621155 | AE38: 48.705265 | AF38: 48.724365 | AG38: 48.737965 | AH38: 48.766415 | AI38: 48.772102 | AJ38: 48.774681 | AK38: 0.011717
A39: TKI000:ca_TestedNewTwuk | B39: New Car 4/ | C39: 38.844189 | D39: 39.84222 | E39: 41.359097 | F39: 43.479668 | G39: 45.512585 | H39: 47.573315 | I39: 49.833408 | J39: 51.159718 | K39: 53.621464 | L39: 53.702938 | M39: 53.80172 | N39: 53.874981 | O39: 54.05426 | P39: 54.202103 | Q39: 54.407009 | R39: 54.641037 | S39: 54.843136 | T39: 55.03714 | U39: 55.219742 | V39: 55.395058 | W39: 55.528614 | X39: 55.659931 | Y39: 55.794483 | Z39: 55.912376 | AA39: 55.95483 | AB39: 56.000454 | AC39: 56.032734 | AD39: 56.03751 | AE39: 56.043736 | AF39: 56.079899 | AG39: 56.113274 | AH39: 56.164932 | AI39: 56.197685 | AJ39: 56.227493 | AK39: 0.010823
A40: TKI000:ca_OnRoadNewVeh | B40: New Light Truck 4/ | C40: 28.17654 | D40: 28.57621 | E40: 29.362612 | F40: 30.6257 | G40: 32.636818 | H40: 34.45956 | I40: 36.077965 | J40: 37.708981 | K40: 39.618832 | L40: 39.709496 | M40: 39.731888 | N40: 39.700436 | O40: 39.652912 | P40: 39.600517 | Q40: 39.552765 | R40: 39.538483 | S40: 39.656025 | T40: 39.612507 | U40: 39.560276 | V40: 39.513908 | W40: 39.469017 | X40: 39.477066 | Y40: 39.453606 | Z40: 39.425179 | AA40: 39.526264 | AB40: 39.512119 | AC40: 39.481171 | AD40: 39.451141 | AE40: 39.554874 | AF40: 39.549133 | AG40: 39.541401 | AH40: 39.535969 | AI40: 39.531124 | AJ40: 39.535419 | AK40: 0.010196
A41: TKI000:ca_OnRoadNewCar | B41: On-Road New Light-Duty Vehicle 5/ | C41: 26.860435 | D41: 27.412979 | E41: 28.265438 | F41: 29.610132 | G41: 31.300692 | H41: 32.927387 | I41: 34.546352 | J41: 35.881912 | K41: 37.727074 | L41: 37.831051 | M41: 37.989754 | N41: 38.09668 | O41: 38.250278 | P41: 38.366863 | Q41: 38.507156 | R41: 38.671864 | S41: 38.86277 | T41: 38.978622 | U41: 39.081562 | V41: 39.182323 | W41: 39.252899 | X41: 39.351257 | Y41: 39.432819 | Z41: 39.504112 | AA41: 39.596188 | AB41: 39.645687 | AC41: 39.672047 | AD41: 39.67741 | AE41: 39.746174 | AF41: 39.761765 | AG41: 39.772858 | AH41: 39.796085 | AI41: 39.800686 | AJ41: 39.802731 | AK41: 0.011722
A42: TKI000:ca_OnRoadNewTwuk | B42: New Car 5/ | C42: 31.720737 | D42: 32.535744 | E42: 33.774448 | F42: 35.506138 | G42: 37.166248 | H42: 38.849072 | I42: 40.694695 | J42: 41.777779 | K42: 43.788078 | L42: 43.85461 | M42: 43.935276 | N42: 43.995106 | O42: 44.141506 | P42: 44.262238 | Q42: 44.429565 | R42: 44.620678 | S42: 44.785713 | T42: 44.944141 | U42: 45.093254 | V42: 45.23642 | W42: 45.345486 | X42: 45.452721 | Y42: 45.562599 | Z42: 45.658871 | AA42: 45.693539 | AB42: 45.730797 | AC42: 45.757156 | AD42: 45.761059 | AE42: 45.76614 | AF42: 45.795673 | AG42: 45.822926 | AH42: 45.865112 | AI42: 45.891857 | AJ42: 45.916199 | AK42: 0.010823
A43: TKI000:ca_Light-DutySto | B43: New Light Truck 5/ | C43: 22.973969 | D43: 23.299843 | E43: 23.941042 | F43: 24.970911 | G43: 26.610691 | H43: 28.09688 | I43: 29.416458 | J43: 30.746321 | K43: 32.303532 | L43: 32.377457 | M43: 32.395714 | N43: 32.370068 | O43: 32.331322 | P43: 32.288601 | Q43: 32.249664 | R43: 32.238018 | S43: 32.333858 | T43: 32.298374 | U43: 32.255791 | V43: 32.217983 | W43: 32.181381 | X43: 32.187943 | Y43: 32.168816 | Z43: 32.145638 | AA43: 32.228058 | AB43: 32.216526 | AC43: 32.191292 | AD43: 32.166805 | AE43: 32.251385 | AF43: 32.246704 | AG43: 32.240398 | AH43: 32.23597 | AI43: 32.232021 | AJ43: 32.235523 | AK43: 0.010196
... A46: TKI000:ca_FreightTruck | B46: Stock Commercial Light Truck 1/ | C46: 13.680938 | D46: 13.806588 | E46: 13.931844 | F46: 14.097829 | G46: 14.271951 | H46: 14.463296 | I46: 14.661203 | J46: 14.868921 | K46: 15.04772 | L46: 15.250485 | M46: 15.469141 | N46: 15.679131 | O46: 15.881999 | P46: 16.080351 | Q46: 16.25989 | R46: 16.421648 | S46: 16.55814 | T46: 16.673365 | U46: 16.775356 | V46: 16.865324 | W46: 16.940193 | X46: 17.005682 | Y46: 17.071365 | Z46: 17.127596 | AA46: 17.18157 | AB46: 17.229876 | AC46: 17.27033 | AD46: 17.306684 | AE46: 17.334562 | AF46: 17.348494 | AG46: 17.368992 | AH46: 17.406809 | AI46: 17.437517 | AJ46: 17.471701 | AK46: 0.007385
B47: Freight Truck | C47: 7.133016 | D47: 7.234839 | E47: 7.335194 | F47: 7.434534 | G47: 7.53856 | H47: 7.643671 | I47: 7.754342 | J47: 7.873028 | K47: 8.002402 | L47: 8.144583 | M47: 8.300921 | N47: 8.463225 | O47: 8.630606 | P47: 8.802323 | Q47: 8.97359 | R47: 9.139458 | S47: 9.299235 | T47: 9.442711 | U47: 9.568296 | V47: 9.682433 | W47: 9.784242 | X47: 9.877921 | Y47: 9.96206 | Z47: 10.051148 | AA47: 10.121845 | AB47: 10.185764 | AC47: 10.238789 | AD47: 10.28496 | AE47: 10.331643 | AF47: 10.376075 | AG47: 10.415617 | AH47: 10.453134 | AI47: 10.495623 | AJ47: 10.53261 | AK47: 0.011806
A48: TKI000:ca_Aircraft | B48: (seat miles per gallon)
B49: Aircraft | C49: 68.402603 | D49: 68.732193 | E49: 69.062111 | F49: 69.384827 | G49: 69.710152 | H49: 70.043472 | I49: 70.380814 | J49: 70.734665 | K49: 71.079346 | L49: 71.468315 | M49: 71.879921 | N49: 72.329201 | O49: 72.806061 | P49: 73.26902 | Q49: 73.724205 | R49: 74.190994 | S49: 74.669258 | T49: 75.136513 | U49: 75.61467 | V49: 76.099602 | W49: 76.587379 | X49: 77.079155 | Y49: 77.586296 | Z49: 78.09967 | AA49: 78.597786 | AB49: 79.095818 | AC49: 79.574516 | AD49: 80.036766 | AE49: 80.496498 | AF49: 80.955223 | AG49: 81.4114 | AH49: 81.874283 | AI49: 82.320076 | AJ49: 82.757706 | AK49: 0.00582
A50: TKI000:ca_Rail | B50: (ton miles/thousand Btu)
A51: TKI000:ca_DomesticShipp | B51: Rail | C51: 3.422345 | D51: 3.444543 | E51: 3.466884 | F51: 3.489371 | G51: 3.512003 | H51: 3.534782 | I51: 3.55771 | J51: 3.580785 | K51: 3.60401 | L51: 3.627386 | M51: 3.650914 | N51: 3.674594 | O51: 3.698428 | P51: 3.722416 | Q51: 3.74656 | R51: 3.77086 | S51: 3.795318 | T51: 3.819935 | U51: 3.844712 | V51: 3.869649 | W51: 3.894748 | X51: 3.920009 | Y51: 3.945435 | Z51: 3.971025 | AA51: 3.996782 | AB51: 4.022705 | AC51: 4.048797 | AD51: 4.075058 | AE51: 4.101489 | AF51: 4.128091 | AG51: 4.154866 | AH51: 4.181815 | AI51: 4.208939 | AJ51: 4.236238 | AK51: 0.006486
B52: Domestic Shipping | C52: 4.756678 | D52: 4.784937 | E52: 4.813365 | F52: 4.84196 | G52: 4.870726 | H52: 4.899663 | I52: 4.928772 | J52: 4.958054 | K52: 4.987509 | L52: 5.01714 | M52: 5.046947 | N52: 5.076931 | O52: 5.107092 | P52: 5.137434 | Q52: 5.167955 | R52: 5.198658 | S52: 5.229543 | T52: 5.260611 | U52: 5.291864 | V52: 5.323303 | W52: 5.354929 | X52: 5.386742 | Y52: 5.418745 | Z52: 5.450938 | AA52: 5.483322 | AB52: 5.515898 | AC52: 5.548667 | AD52: 5.581632 | AE52: 5.614792 | AF52: 5.64815 | AG52: 5.681705 | AH52: 5.71546 | AI52: 5.749416 | AJ52: 5.783573 | AK52: 0.005941
B54: Energy Use by Mode
A55: TKI000:da_Light-DutyVeh | B55: (quadrillion Btu)
A56: TKI000:da_CommercialLig | B56: Light-Duty Vehicles | C56: 15.428981 | D56: 15.405498 | E56: 15.323709 | F56: 15.159972 | G56: 14.917847 | H56: 14.628936 | I56: 14.292074 | J56: 13.935912 | K56: 13.565999 | L56: 13.277204 | M56: 13.019745 | N56: 12.784966 | O56: 12.550358 | P56: 12.335548 | Q56: 12.134972 | R56: 11.949124 | S56: 11.778061 | T56: 11.621789 | U56: 11.477596 | V56: 11.370868 | W56: 11.287215 | X56: 11.223202 | Y56: 11.175605 | Z56: 11.142943 | AA56: 11.12225 | AB56: 11.112763 | AC56: 11.114813 | AD56: 11.125956 | AE56: 11.141642 | AF56: 11.164968 | AG56: 11.191122 | AH56: 11.216116 | AI56: 11.244189 | AJ56: 11.271485 | AK56: -0.009717
A57: TKI000:da_BusTransporta | B57: Commercial Light Trucks 1/ | C57: 0.887006 | D57: 0.901172 | E57: 0.913443 | F57: 0.917378 | G57: 0.917018 | H57: 0.915444 | I57: 0.913535 | J57: 0.910829 | K57: 0.911685 | L57: 0.912469 | M57: 0.912204 | N57: 0.913935 | O57: 0.914036 | P57: 0.914125 | Q57: 0.916358 | R57: 0.919401 | S57: 0.923922 | T57: 0.93013 | U57: 0.937661 | V57: 0.94613 | W57: 0.955936 | X57: 0.966482 | Y57: 0.976147 | Z57: 0.986168 | AA57: 0.99651 | AB57: 1.006997 | AC57: 1.018671 | AD57: 1.031238 | AE57: 1.045235 | AF57: 1.060043 | AG57: 1.07486 | AH57: 1.088664 | AI57: 1.102422 | AJ57: 1.11621 | AK57: 0.00671
A58: TKI000:da_FreightTrucks | B58: Bus Transportation | C58: 0.236778 | D58: 0.237636 | E58: 0.238408 | F58: 0.239163 | G58: 0.239921 | H58: 0.240654 | I58: 0.241333 | J58: 0.242039 | K58: 0.242841 | L58: 0.243624 | M58: 0.244393 | N58: 0.245183 | O58: 0.245948 | P58: 0.246627 | Q58: 0.247273 | R58: 0.247895 | S58: 0.24841 | T58: 0.24887 | U58: 0.249278 | V58: 0.249639 | W58: 0.249957 | X58: 0.25023 | Y58: 0.250457 | Z58: 0.250637 | AA58: 0.250765 | AB58: 0.250847 | AC58: 0.250888 | AD58: 0.250892 | AE58: 0.250873 | AF58: 0.250846 | AG58: 0.250834 | AH58: 0.250861 | AI58: 0.250946 | AJ58: 0.25111 | AK58: 0.001725
A59: TKI000:da_Rail,Passenge | B59: Freight Trucks | C59: 5.649382 | D59: 5.722904 | E59: 5.814896 | F59: 5.825496 | G59: 5.808636 | H59: 5.806846 | I59: 5.804241 | J59: 5.792575 | K59: 5.777115 | L59: 5.7594 | M59: 5.720149 | N59: 5.686709 | O59: 5.642106 | P59: 5.597387 | Q59: 5.564857 | R59: 5.532156 | S59: 5.504872 | T59: 5.492891 | U59: 5.499219 | V59: 5.510053 | W59: 5.531815 | X59: 5.557973 | Y59: 5.583206 | Z59: 5.602642 | AA59: 5.634213 | AB59: 5.66795 | AC59: 5.708614 | AD59: 5.758537 | AE59: 5.812732 | AF59: 5.871642 | AG59: 5.939038 | AH59: 6.007619 | AI59: 6.063802 | AJ59: 6.126197 | AK59: 0.00213
A60: TKI000:da_Rail,Freight | B60: Rail, Passenger | C60: 0.046543 | D60: 0.046796 | E60: 0.04753 | F60: 0.048112 | G60: 0.048722 | H60: 0.049294 | I60: 0.049854 | J60: 0.050421 | K60: 0.051026 | L60: 0.051644 | M60: 0.052196 | N60: 0.052875 | O60: 0.053353 | P60: 0.053961 | Q60: 0.054524 | R60: 0.055095 | S60: 0.055691 | T60: 0.056268 | U60: 0.056839 | V60: 0.05738 | W60: 0.057962 | X60: 0.058515 | Y60: 0.059056 | Z60: 0.05959 | AA60: 0.060133 | AB60: 0.060653 | AC60: 0.061199 | AD60: 0.061745 | AE60: 0.062278 | AF60: 0.062804 | AG60: 0.063347 | AH60: 0.063863 | AI60: 0.064386 | AJ60: 0.064878 | AK60: 0.010262
A61: TKI000:da_Shipping,Dome | B61: Rail, Freight | C61: 0.522313 | D61: 0.519296 | E61: 0.522695 | F61: 0.509174 | G61: 0.503812 | H61: 0.498286 | I61: 0.494884 | J61: 0.49694 | K61: 0.497742 | L61: 0.4989 | M61: 0.497547 | N61: 0.497654 | O61: 0.504354 | P61: 0.508731 | Q61: 0.506712 | R61: 0.504332 | S61: 0.50447 | T61: 0.50151 | U61: 0.50186 | V61: 0.502847 | W61: 0.502673 | X61: 0.503478 | Y61: 0.504194 | Z61: 0.50451 | AA61: 0.504609 | AB61: 0.504091 | AC61: 0.50324 | AD61: 0.503684 | AE61: 0.504541 | AF61: 0.504205 | AG61: 0.504543 | AH61: 0.505442 | AI61: 0.506188 | AJ61: 0.507373 | AK61: -0.000726
A62: TKI000:da_Shipping,Inte | B62: Shipping, Domestic | C62: 0.094505 | D62: 0.093176 | E62: 0.091311 | F62: 0.088601 | G62: 0.085677 | H62: 0.083393 | I62: 0.080994 | J62: 0.078417 | K62: 0.075963 | L62: 0.073684 | M62: 0.071399 | N62: 0.068965 | O62: 0.066546 | P62: 0.064121 | Q62: 0.062829 | R62: 0.061462 | S62: 0.060182 | T62: 0.058948 | U62: 0.057777 | V62: 0.056568 | W62: 0.055523 | X62: 0.054441 | Y62: 0.053333 | Z62: 0.052192 | AA62: 0.051627 | AB62: 0.051064 | AC62: 0.050426 | AD62: 0.04987 | AE62: 0.049323 | AF62: 0.048838 | AG62: 0.048322 | AH62: 0.047877 | AI62: 0.047314 | AJ62: 0.046826 | AK62: -0.021272
A63: TKI000:da_RecreationalB | B63: Shipping, International | C63: 0.960147 | D63: 0.917648 | E63: 1.03994 | F63: 0.861388 | G63: 0.864633 | H63: 0.921436 | I63: 0.932806 | J63: 0.938772 | K63: 0.944178 | L63: 0.94026 | M63: 0.93702 | N63: 0.93539 | O63: 0.937245 | P63: 0.929832 | Q63: 0.929154 | R63: 0.928998 | S63: 0.929023 | T63: 0.928191 | U63: 0.914269 | V63: 0.913769 | W63: 0.910804 | X63: 0.910243 | Y63: 0.909776 | Z63: 0.909511 | AA63: 0.9089 | AB63: 0.907319 | AC63: 0.914151 | AD63: 0.907852 | AE63: 0.908362 | AF63: 0.905308 | AG63: 0.905439 | AH63: 0.905901 | AI63: 0.907053 | AJ63: 0.90721 | AK63: -0.000357
A64: TKI000:da_Air | B64: Recreational Boats | C64: 0.242865 | D64: 0.242798 | E64: 0.243499 | F64: 0.243798 | G64: 0.244158 | H64: 0.244395 | I64: 0.244576 | J64: 0.244721 | K64: 0.244897 | L64: 0.245087 | M64: 0.245121 | N64: 0.245347 | O64: 0.24531 | P64: 0.245288 | Q64: 0.245216 | R64: 0.245077 | S64: 0.244893 | T64: 0.244693 | U64: 0.244411 | V64: 0.244051 | W64: 0.243704 | X64: 0.243288 | Y64: 0.242823 | Z64: 0.242324 | AA64: 0.241793 | AB64: 0.241213 | AC64: 0.24063 | AD64: 0.240038 | AE64: 0.239407 | AF64: 0.238783 | AG64: 0.238148 | AH64: 0.237453 | AI64: 0.236735 | AJ64: 0.235959 | AK64: -0.000893
A65: TKI000:da_MilitaryUse | B65: Air | C65: 2.523884 | D65: 2.543482 | E65: 2.581435 | F65: 2.61451 | G65: 2.639638 | H65: 2.662873 | I65: 2.688826 | J65: 2.716387 | K65: 2.747756 | L65: 2.778921 | M65: 2.807338 | N65: 2.84509 | O65: 2.875095 | P65: 2.905722 | Q65: 2.937704 | R65: 2.968971 | S65: 3.000346 | T65: 3.033164 | U65: 3.065069 | V65: 3.096148 | W65: 3.127663 | X65: 3.159908 | Y65: 3.191287 | Z65: 3.22304 | AA65: 3.254714 | AB65: 3.286702 | AC65: 3.321468 | AD65: 3.356642 | AE65: 3.394192 | AF65: 3.431655 | AG65: 3.47079 | AH65: 3.50973 | AI65: 3.548421 | AJ65: 3.586297 | AK65: 0.010795
A66: TKI000:da_Lubricants | B66: Military Use | C66: 0.535696 | D66: 0.557784 | E66: 0.587657 | F66: 0.589987 | G66: 0.581883 | H66: 0.575975 | I66: 0.559007 | J66: 0.548075 | K66: 0.546878 | L66: 0.545983 | M66: 0.546442 | N66: 0.550222 | O66: 0.551223 | P66: 0.55183 | Q66: 0.552408 | R66: 0.552958 | S66: 0.553483 | T66: 0.553986 | U66: 0.554465 | V66: 0.554935 | W66: 0.555392 | X66: 0.555837 | Y66: 0.556271 | Z66: 0.556691 | AA66: 0.557098 | AB66: 0.557492 | AC66: 0.557874 | AD66: 0.558238 | AE66: 0.558589 | AF66: 0.558925 | AG66: 0.559245 | AH66: 0.559551 | AI66: 0.55927 | AJ66: 0.559034 | AK66: 7e-05
A67: TKI000:da_PipelineFuel | B67: Lubricants | C67: 0.135318 | D67: 0.134279 | E67: 0.133617 | F67: 0.133109 | G67: 0.132632 | H67: 0.131976 | I67: 0.131403 | J67: 0.130875 | K67: 0.130328 | L67: 0.129819 | M67: 0.129337 | N67: 0.128918 | O67: 0.128549 | P67: 0.128273 | Q67: 0.128138 | R67: 0.127991 | S67: 0.127887 | T67: 0.127904 | U67: 0.127907 | V67: 0.127899 | W67: 0.127922 | X67: 0.127961 | Y67: 0.127983 | Z67: 0.128017 | AA67: 0.128052 | AB67: 0.128127 | AC67: 0.128199 | AD67: 0.128312 | AE67: 0.128432 | AF67: 0.128539 | AG67: 0.128607 | AH67: 0.128636 | AI67: 0.128677 | AJ67: 0.128711 | AK67: -0.001323
A68: TKI000:da_Total | B68: Pipeline Fuel | C68: 0.679154 | D68: 0.704264 | E68: 0.690707 | F68: 0.673192 | G68: 0.660012 | H68: 0.647853 | I68: 0.640445 | J68: 0.641466 | K68: 0.653295 | L68: 0.657333 | M68: 0.664647 | N68: 0.673619 | O68: 0.680862 | P68: 0.682965 | Q68: 0.685364 | R68: 0.692495 | S68: 0.693112 | T68: 0.696353 | U68: 0.697718 | V68: 0.700136 | W68: 0.700379 | X68: 0.703284 | Y68: 0.706421 | Z68: 0.71111 | AA68: 0.715578 | AB68: 0.721452 | AC68: 0.725308 | AD68: 0.731309 | AE68: 0.736503 | AF68: 0.740353 | AG68: 0.745328 | AH68: 0.75128 | AI68: 0.757931 | AJ68: 0.764318 | AK68: 0.00256
B69: Total | C69: 27.94257 | D69: 28.026735 | E69: 28.228846 | F69: 27.903879 | G69: 27.644588 | H69: 27.407358 | I69: 27.073978 | J69: 26.727428 | K69: 26.389702 | L69: 26.114326 | M69: 25.847538 | N69: 25.628876 | O69: 25.394987 | P69: 25.164408 | Q69: 24.965509 | R69: 24.785954 | S69: 24.624353 | T69: 24.494696 | U69: 24.384068 | V69: 24.330423 | W69: 24.306944 | X69: 24.314842 | Y69: 24.336559 | Z69: 24.369379 | AA69: 24.426243 | AB69: 24.496666 | AC69: 24.595482 | AD69: 24.704313 | AE69: 24.832108 | AF69: 24.966904 | AG69: 25.119625 | AH69: 25.272991 | AI69: 25.417336 | AJ69: 25.565609 | AK69: -0.002868
A71: TKI000:ea_Light-DutyVeh | B71: (million barrels per day oil equivalent)
A72: TKI000:ea_CommercialLig | B72: Light-Duty Vehicles | C72: 8.357067 | D72: 8.353935 | E72: 8.307609 | F72: 8.218623 | G72: 8.089526 | H72: 7.936023 | I72: 7.75667 | J72: 7.56909 | K72: 7.376121 | L72: 7.218821 | M72: 7.082164 | N72: 6.956802 | O72: 6.831923 | P72: 6.717787 | Q72: 6.609073 | R72: 6.507457 | S72: 6.414566 | T72: 6.331388 | U72: 6.253195 | V72: 6.196048 | W72: 6.15119 | X72: 6.116357 | Y72: 6.089727 | Z72: 6.071071 | AA72: 6.057342 | AB72: 6.049935 | AC72: 6.047934 | AD72: 6.052037 | AE72: 6.059132 | AF72: 6.066707 | AG72: 6.074933 | AH72: 6.085821 | AI72: 6.103084 | AJ72: 6.116785 | AK72: -0.009693
A73: TKI000:ea_BusTransporta | B73: Commercial Light Trucks 1/ | C73: 0.461895 | D73: 0.469845 | E73: 0.476047 | F73: 0.478148 | G73: 0.478209 | H73: 0.477642 | I73: 0.476961 | J73: 0.476543 | K73: 0.478605 | L73: 0.479371 | M73: 0.480239 | N73: 0.482105 | O73: 0.483313 | P73: 0.484769 | Q73: 0.486632 | R73: 0.488957 | S73: 0.492202 | T73: 0.496821 | U73: 0.501744 | V73: 0.507346 | W73: 0.513656 | X73: 0.520187 | Y73: 0.526096 | Z73: 0.532049 | AA73: 0.537721 | AB73: 0.543461 | AC73: 0.549298 | AD73: 0.556021 | AE73: 0.563677 | AF73: 0.570107 | AG73: 0.57578 | AH73: 0.582052 | AI73: 0.590257 | AJ73: 0.598357 | AK73: 0.007584
A74: TKI000:ea_FreightTrucks | B74: Bus Transportation | C74: 0.114317 | D74: 0.11476 | E74: 0.115139 | F74: 0.115529 | G74: 0.115889 | H74: 0.116242 | I74: 0.116598 | J74: 0.11692 | K74: 0.117326 | L74: 0.117693 | M74: 0.118046 | N74: 0.118423 | O74: 0.118812 | P74: 0.119135 | Q74: 0.119446 | R74: 0.119745 | S74: 0.119972 | T74: 0.120209 | U74: 0.120407 | V74: 0.120587 | W74: 0.120737 | X74: 0.120871 | Y74: 0.120983 | Z74: 0.121072 | AA74: 0.121135 | AB74: 0.12118 | AC74: 0.121198 | AD74: 0.121207 | AE74: 0.121198 | AF74: 0.12119 | AG74: 0.121191 | AH74: 0.121209 | AI74: 0.121258 | AJ74: 0.121337 | AK74: 0.001743
A75: TKI000:ea_Rail,Passenge | B75: Freight Trucks | C75: 2.716007 | D75: 2.751489 | E75: 2.795627 | F75: 2.801202 | G75: 2.793341 | H75: 2.792572 | I75: 2.792328 | J75: 2.786532 | K75: 2.779877 | L75: 2.771582 | M75: 2.752661 | N75: 2.737045 | O75: 2.716828 | P75: 2.695718 | Q75: 2.680891 | R75: 2.665842 | S75: 2.652959 | T75: 2.648333 | U75: 2.652082 | V75: 2.658186 | W75: 2.66927 | X75: 2.682786 | Y75: 2.695746 | Z75: 2.706168 | AA75: 2.722346 | AB75: 2.73974 | AC75: 2.760433 | AD75: 2.785677 | AE75: 2.812876 | AF75: 2.842768 | AG75: 2.877009 | AH75: 2.911673 | AI75: 2.940098 | AJ75: 2.971311 | AK75: 0.002405
A76: TKI000:ea_Rail,Freight | B76: Rail, Passenger | C76: 0.022033 | D76: 0.022153 | E76: 0.022502 | F76: 0.022779 | G76: 0.023067 | H76: 0.023337 | I76: 0.023605 | J76: 0.023871 | K76: 0.024159 | L76: 0.024451 | M76: 0.024709 | N76: 0.02503 | O76: 0.02526 | P76: 0.025547 | Q76: 0.025814 | R76: 0.026085 | S76: 0.026365 | T76: 0.026641 | U76: 0.026911 | V76: 0.027168 | W76: 0.027444 | X76: 0.027706 | Y76: 0.027962 | Z76: 0.028215 | AA76: 0.028473 | AB76: 0.02872 | AC76: 0.028978 | AD76: 0.029238 | AE76: 0.02949 | AF76: 0.02974 | AG76: 0.029998 | AH76: 0.030243 | AI76: 0.030491 | AJ76: 0.030725 | AK76: 0.010273
A77: TKI000:ea_Shipping,Dome | B77: Rail, Freight | C77: 0.247806 | D77: 0.24641 | E77: 0.248031 | F77: 0.241643 | G77: 0.239089 | H77: 0.236438 | I77: 0.234871 | J77: 0.235787 | K77: 0.236205 | L77: 0.236713 | M77: 0.236007 | N77: 0.236031 | O77: 0.239233 | P77: 0.241282 | Q77: 0.240304 | R77: 0.239157 | S77: 0.239167 | T77: 0.237781 | U77: 0.237928 | V77: 0.238387 | W77: 0.238277 | X77: 0.238642 | Y77: 0.238966 | Z77: 0.239099 | AA77: 0.239128 | AB77: 0.238871 | AC77: 0.238445 | AD77: 0.238648 | AE77: 0.239036 | AF77: 0.238864 | AG77: 0.239014 | AH77: 0.239428 | AI77: 0.23977 | AJ77: 0.24032 | AK77: -0.000782
A78: TKI000:ea_Shipping,Inte | B78: Shipping, Domestic | C78: 0.044738 | D78: 0.044124 | E78: 0.043217 | F78: 0.041955 | G78: 0.040583 | H78: 0.0395 | I78: 0.038375 | J78: 0.037148 | K78: 0.035996 | L78: 0.034914 | M78: 0.033826 | N78: 0.032674 | O78: 0.031536 | P78: 0.030389 | Q78: 0.029779 | R78: 0.029134 | S78: 0.028524 | T78: 0.027947 | U78: 0.027394 | V78: 0.026823 | W78: 0.026329 | X78: 0.025818 | Y78: 0.025295 | Z78: 0.024756 | AA78: 0.024488 | AB78: 0.024221 | AC78: 0.023918 | AD78: 0.023655 | AE78: 0.023396 | AF78: 0.023166 | AG78: 0.022922 | AH78: 0.022711 | AI78: 0.022445 | AJ78: 0.022214 | AK78: -0.021218
A79: TKI000:ea_RecreationalB | B79: Shipping, International | C79: 0.429439 | D79: 0.411176 | E79: 0.468182 | F79: 0.395185 | G79: 0.393832 | H79: 0.415271 | I79: 0.419638 | J79: 0.421896 | K79: 0.424006 | L79: 0.422547 | M79: 0.421323 | N79: 0.420746 | O79: 0.421521 | P79: 0.418769 | Q79: 0.418558 | R79: 0.418546 | S79: 0.418579 | T79: 0.418339 | U79: 0.413132 | V79: 0.412994 | W79: 0.411918 | X79: 0.411754 | Y79: 0.411625 | Z79: 0.411575 | AA79: 0.411393 | AB79: 0.410841 | AC79: 0.413474 | AD79: 0.411156 | AE79: 0.411408 | AF79: 0.410308 | AG79: 0.410416 | AH79: 0.410648 | AI79: 0.411143 | AJ79: 0.411262 | AK79: 7e-06
A80: TKI000:ea_Air | B80: Recreational Boats | C80: 0.131586 | D80: 0.131586 | E80: 0.131948 | F80: 0.132101 | G80: 0.13232 | H80: 0.132502 | I80: 0.132666 | J80: 0.132766 | K80: 0.132875 | L80: 0.132989 | M80: 0.13302 | N80: 0.133153 | O80: 0.133145 | P80: 0.133131 | Q80: 0.133111 | R80: 0.133046 | S80: 0.132952 | T80: 0.132859 | U80: 0.132724 | V80: 0.132549 | W80: 0.132382 | X80: 0.132178 | Y80: 0.131954 | Z80: 0.131713 | AA80: 0.131459 | AB80: 0.131178 | AC80: 0.130904 | AD80: 0.130624 | AE80: 0.130325 | AF80: 0.130035 | AG80: 0.129751 | AH80: 0.12944 | AI80: 0.129123 | AJ80: 0.1287 | AK80: -0.000693
A81: TKI000:ea_MilitaryUse | B81: Air | C81: 1.220852 | D81: 1.230324 | E81: 1.24866 | F81: 1.26464 | G81: 1.276783 | H81: 1.288014 | I81: 1.30056 | J81: 1.313879 | K81: 1.329037 | L81: 1.344096 | M81: 1.357828 | N81: 1.37607 | O81: 1.39057 | P81: 1.405368 | Q81: 1.420823 | R81: 1.435932 | S81: 1.451093 | T81: 1.466952 | U81: 1.48237 | V81: 1.497389 | W81: 1.512619 | X81: 1.528201 | Y81: 1.543366 | Z81: 1.558712 | AA81: 1.57402 | AB81: 1.58948 | AC81: 1.606283 | AD81: 1.623282 | AE81: 1.64143 | AF81: 1.659537 | AG81: 1.678453 | AH81: 1.697275 | AI81: 1.715977 | AJ81: 1.734279 | AK81: 0.010786
A82: TKI000:ea_Lubricants | B82: Military Use | C82: 0.257023 | D82: 0.267681 | E82: 0.281707 | F82: 0.282962 | G82: 0.279199 | H82: 0.276358 | I82: 0.268228 | J82: 0.26297 | K82: 0.262406 | L82: 0.261971 | M82: 0.26218 | N82: 0.263992 | O82: 0.264483 | P82: 0.264774 | Q82: 0.265051 | R82: 0.265316 | S82: 0.265559 | T82: 0.26581 | U82: 0.266041 | V82: 0.266269 | W82: 0.266486 | X82: 0.266701 | Y82: 0.26691 | Z82: 0.267112 | AA82: 0.267307 | AB82: 0.267498 | AC82: 0.26768 | AD82: 0.267857 | AE82: 0.268026 | AF82: 0.268188 | AG82: 0.268344 | AH82: 0.268491 | AI82: 0.268358 | AJ82: 0.268247 | AK82: 6.6e-05
A83: TKI000:ea_PipelineFuel | B83: Lubricants | C83: 0.06392 | D83: 0.063429 | E83: 0.063116 | F83: 0.062876 | G83: 0.062651 | H83: 0.062341 | I83: 0.06207 | J83: 0.061821 | K83: 0.061562 | L83: 0.061322 | M83: 0.061094 | N83: 0.060897 | O83: 0.060722 | P83: 0.060592 | Q83: 0.060528 | R83: 0.060458 | S83: 0.06041 | T83: 0.060417 | U83: 0.060419 | V83: 0.060415 | W83: 0.060426 | X83: 0.060445 | Y83: 0.060455 | Z83: 0.060471 | AA83: 0.060488 | AB83: 0.060523 | AC83: 0.060557 | AD83: 0.06061 | AE83: 0.060667 | AF83: 0.060717 | AG83: 0.06075 | AH83: 0.060763 | AI83: 0.060783 | AJ83: 0.060799 | AK83: -0.001323
A84: TKI000:ea_Total | B84: Pipeline Fuel | C84: 0.320809 | D84: 0.332671 | E84: 0.326267 | F84: 0.317993 | G84: 0.311768 | H84: 0.306024 | I84: 0.302525 | J84: 0.303007 | K84: 0.308595 | L84: 0.310502 | M84: 0.313957 | N84: 0.318195 | O84: 0.321616 | P84: 0.32261 | Q84: 0.323743 | R84: 0.327112 | S84: 0.327403 | T84: 0.328934 | U84: 0.329578 | V84: 0.330721 | W84: 0.330835 | X84: 0.332208 | Y84: 0.33369 | Z84: 0.335905 | AA84: 0.338015 | AB84: 0.34079 | AC84: 0.342611 | AD84: 0.345446 | AE84: 0.347899 | AF84: 0.349718 | AG84: 0.352068 | AH84: 0.35488 | AI84: 0.358021 | AJ84: 0.361038 | AK84: 0.00256
B85: Total | C85: 14.387494 | D85: 14.439582 | E85: 14.528051 | F85: 14.375638 | G85: 14.236258 | H85: 14.102266 | I85: 13.925094 | J85: 13.742229 | K85: 13.56677 | L85: 13.41697 | M85: 13.277055 | N85: 13.161164 | O85: 13.038962 | P85: 12.91987 | Q85: 12.813753 | R85: 12.716784 | S85: 12.629751 | T85: 12.562429 | U85: 12.503926 | V85: 12.474881 | W85: 12.461569 | X85: 12.463853 | Y85: 12.472775 | Z85: 12.487917 | AA85: 12.513312 | AB85: 12.546439 | AC85: 12.591713 | AD85: 12.645458 | AE85: 12.708559 | AF85: 12.771045 | AG85: 12.840629 | AH85: 12.914635 | AI85: 12.990807 | AJ85: 13.065372 | AK85: -0.00312
B87: 1/ Commercial trucks 8,501 to 10,000 pounds gross vehicle weight rating.
B88: 2/ CAFE standard based on projected new vehicle sales.
B89: 3/ Includes CAFE credits for alternative fueled vehicle sales and credit banking.
B90: 4/ U.S. Environmental Protection Agency rated miles per gallon.
B91: 5/ Tested new vehicle efficiency revised for on-road performance.
B92: 6/ Combined "on-the-road" estimate for all cars and light trucks.
B93: CAFE = Corporate average fuel economy.
B94: Btu = British thermal unit.
B95: Note: Totals may not equal sum of components due to independent rounding. Data for 2017
B96: are model results and may differ from official EIA data reports.
B97: Sources: 2017: U.S. Energy Information Administration (EIA), Monthly Energy Review, September 2018;
B98: EIA, Alternatives to Traditional Transportation Fuels 2009 (Part II - User and Fuel Data); EIA, State Energy Data System 2016;
... B107: Projections: EIA, AEO2019 National Energy Modeling System run ref2019.d111618a.

Sheet AEO 37
B1: ref2019.d111618a | C1: 2017 | D1: 2018 | E1: 2019 | F1: 2020 | G1: 2021 | H1: 2022 | I1: 2023 | J1: 2024 | K1: 2025 | L1: 2026 | M1: 2027 | N1: 2028 | O1: 2029 | P1: 2030 | Q1: 2031 | R1: 2032 | S1: 2033 | T1: 2034 | U1: 2035 | V1: 2036 | W1: 2037 | X1: 2038 | Y1: 2039 | Z1: 2040 | AA1: 2041 | AB1: 2042 | AC1: 2043 | AD1: 2044 | AE1: 2045 | AF1: 2046 | AG1: 2047 | AH1: 2048 | AI1: 2049 | AJ1: 2050
C3: Report | D3: Annual Energy Outlook 2019
C4: Scenario | D4: ref2019 | G4: Reference case
C5: Datekey | D5: d111618a
C6: Release Date | E6: January 2019
A10: TEF000 | B10: 37. Transportation Sector Energy Use by Fuel Type Within a Mode
B11: (trillion Btu)
AK12: 2018-
B13: Mode and Type | C13: 2017 | D13: 2018 | E13: 2019 | F13: 2020 | G13: 2021 | H13: 2022 | I13: 2023 | J13: 2024 | K13: 2025 | L13: 2026 | M13: 2027 | N13: 2028 | O13: 2029 | P13: 2030 | Q13: 2031 | R13: 2032 | S13: 2033 | T13: 2034 | U13: 2035 | V13: 2036 | W13: 2037 | X13: 2038 | Y13: 2039 | Z13: 2040 | AA13: 2041 | AB13: 2042 | AC13: 2043 | AD13: 2044 | AE13: 2045 | AF13: 2046 | AG13: 2047 | AH13: 2048 | AI13: 2049 | AJ13: 2050 | AK13: 2050
A15: TEF000:ba_Total | B15: Light-Duty Vehicle | C15: 15428.98 | D15: 15405.497 | E15: 15323.709 | F15: 15159.972 | G15: 14917.846 | H15: 14628.936 | I15: 14292.073 | J15: 13935.911 | K15: 13565.998 | L15: 13277.203 | M15: 13019.744 | N15: 12784.966 | O15: 12550.357 | P15: 12335.548 | Q15: 12134.971 | R15: 11949.124 | S15: 11778.061 | T15: 11621.788 | U15: 11477.596 | V15: 11370.867 | W15: 11287.215 | X15: 11223.201 | Y15: 11175.604 | Z15: 11142.942 | AA15: 11122.249 | AB15: 11112.763 | AC15: 11114.812 | AD15: 11125.955 | AE15: 11141.641 | AF15: 11164.967 | AG15: 11191.121 | AH15: 11216.115 | AI15: 11244.188 | AJ15: 11271.484 | AK15: -0.009717
A16: TEF000:ba_MotorGasoline | B16: Motor Gasoline excluding E85 1/ | C16: 15335.15 | D16: 15269.456 | E16: 15169.746 | F16: 14974.812 | G16: 14696.188 | H16: 14372.849 | I16: 14004.568 | J16: 13595.412 | K16: 13161.478 | L16: 12844.558 | M16: 12544.258 | N16: 12271.508 | O16: 11997.812 | P16: 11740.968 | Q16: 11512.418 | R16: 11302.258 | S16: 11104.021 | T16: 10915.162 | U16: 10746.73 | V16: 10612.404 | W16: 10502.844 | X16: 10416.009 | Y16: 10350.128 | Z16: 10299.68 | AA16: 10269.91 | AB16: 10251.455 | AC16: 10250.534 | AD16: 10253.911 | AE16: 10260.729 | AF16: 10292.284 | AG16: 10333.274 | AH16: 10360.222 | AI16: 10370.963 | AJ16: 10381.07 | AK16: -0.011986
A17: TEF000:ba_Ethanol | B17: E85 1/ | C17: 9.156984 | D17: 43.012703 | E17: 44.298954 | F17: 52.46595 | G17: 63.491283 | H17: 71.578003 | I17: 77.357468 | J17: 104.8816 | K17: 143.47879 | L17: 146.33054 | M17: 164.73543 | N17: 178.72351 | O17: 194.28662 | P17: 212.83853 | Q17: 217.02878 | R17: 218.70625 | S17: 224.12753 | T17: 235.0433 | U17: 238.4245 | V17: 244.75336 | W17: 249.60796 | X17: 251.68942 | Y17: 249.4218 | Z17: 246.1485 | AA17: 234.97339 | AB17: 224.71127 | AC17: 208.83667 | AD17: 198.04375 | AE17: 188.86974 | AF17: 162.43597 | AG17: 129.59372 | AH17: 109.98878 | AI17: 109.85819 | AJ17: 110.01675 | AK17: 0.029783
A18: TEF000:ba_Distillate(di | B18: Distillate Fuel Oil (diesel) | C18: 60.85392 | D18: 63.207066 | E18: 68.963806 | F18: 77.644913 | G18: 85.732368 | H18: 93.502289 | I18: 100.80137 | J18: 107.59821 | K18: 113.81428 | L18: 120.60284 | M18: 127.2694 | N18: 134.14171 | O18: 140.60814 | P18: 147.05969 | Q18: 153.66434 | R18: 159.30063 | S18: 164.19002 | T18: 168.79712 | U18: 172.64732 | V18: 176.17078 | W18: 179.40422 | X18: 182.19275 | Y18: 184.53606 | Z18: 187.16952 | AA18: 189.24709 | AB18: 190.37964 | AC18: 191.2065 | AD18: 191.81207 | AE18: 192.10318 | AF18: 192.42505 | AG18: 192.6785 | AH18: 192.67921 | AI18: 192.53387 | AJ18: 192.14185 | AK18: 0.035355
A19: TEF000:ba_CompressedNat | B19: Compressed/Liquefied Natural Gas | C19: 8.077009 | D19: 6.996272 | E19: 5.800754 | F19: 5.330829 | G19: 5.01966 | H19: 4.717643 | I19: 4.430637 | J19: 4.154118 | K19: 3.903601 | L19: 3.681341 | M19: 3.496768 | N19: 3.33005 | O19: 3.180697 | P19: 3.046438 | Q19: 2.936251 | R19: 2.852098 | S19: 2.782017 | T19: 2.743955 | U19: 2.715444 | V19: 2.698159 | W19: 2.68419 | X19: 2.679098 | Y19: 2.678147 | Z19: 2.679404 | AA19: 2.692208 | AB19: 2.707715 | AC19: 2.721627 | AD19: 2.735777 | AE19: 2.752394 | AF19: 2.769456 | AG19: 2.786568 | AH19: 2.804905 | AI19: 2.818092 | AJ19: 2.830572 | AK19: -0.027882
A20: TEF000:ba_LiquefiedPetr | B20: Propane | C20: 3.931244 | D20: 4.326501 | E20: 4.062418 | F20: 3.951213 | G20: 3.675384 | H20: 3.393915 | I20: 3.18454 | J20: 2.967552 | K20: 2.772993 | L20: 2.595296 | M20: 2.482469 | N20: 2.360416 | O20: 2.268101 | P20: 2.162544 | Q20: 2.067465 | R20: 2.005832 | S20: 1.952856 | T20: 1.926577 | U20: 1.90532 | V20: 1.898456 | W20: 1.891649 | X20: 1.898957 | Y20: 1.910733 | Z20: 1.925213 | AA20: 1.952184 | AB20: 1.989794 | AC20: 2.022425 | AD20: 2.056158 | AE20: 2.094924 | AF20: 2.138347 | AG20: 2.182739 | AH20: 2.232311 | AI20: 2.279563 | AJ20: 2.328814 | AK20: -0.01917
A21: TEF000:ba_Electricity | B21: Electricity | C21: 11.537136 | D21: 17.900618 | E21: 29.66337 | F21: 43.69154 | G21: 60.113934 | H21: 77.17585 | I21: 94.003891 | J21: 111.05218 | K21: 128.48337 | L21: 145.28534 | M21: 161.43393 | N21: 177.16246 | O21: 192.89389 | P21: 208.73148 | Q21: 224.82224 | R21: 240.96106 | S21: 257.17175 | T21: 273.62857 | U21: 290.11511 | V21: 307.36252 | W21: 324.78742 | X21: 342.39038 | Y21: 360.27219 | Z21: 378.38275 | AA21: 396.28464 | AB21: 414.11939 | AC21: 431.90869 | AD21: 449.65247 | AE21: 467.21533 | AF21: 484.91217 | AG21: 502.46365 | AH21: 519.88464 | AI21: 537.25446 | AJ21: 554.41638 | AK21: 0.11325
A22: TEF000:ba_LiquidHydroge | B22: Hydrogen | C22: 0.27376 | D22: 0.598766 | E22: 1.173962 | F22: 2.074811 | G22: 3.62372 | H22: 5.720049 | I22: 7.726999 | J22: 9.844712 | K22: 12.067842 | L22: 14.150493 | M22: 16.068527 | N22: 17.740499 | O22: 19.306999 | P22: 20.741417 | Q22: 22.034424 | R22: 23.0404 | S22: 23.813354 | T22: 24.48613 | U22: 25.056366 | V22: 25.579964 | W22: 25.995058 | X22: 26.341858 | Y22: 26.657215 | Z22: 26.95709 | AA22: 27.189186 | AB22: 27.399199 | AC22: 27.583216 | AD22: 27.742733 | AE22: 27.874962 | AF22: 28.002413 | AG22: 28.14126 | AH22: 28.302532 | AI22: 28.480495 | AJ22: 28.679655 | AK22: 0.128522
A24: TEF000:ca_CommercialLig | B24: Commercial Light Trucks 2/ | C24: 886.89825 | D24: 901.04919 | E24: 913.30731 | F24: 917.23218 | G24: 916.86462 | H24: 915.2868 | I24: 913.37457 | J24: 910.66724 | K24: 911.52051 | L24: 912.30298 | M24: 912.03674 | N24: 913.76532 | O24: 913.86469 | P24: 913.95062 | Q24: 916.18103 | R24: 919.2193 | S24: 923.73584 | T24: 929.93817 | U24: 937.46362 | V24: 945.92535 | W24: 955.72406 | X24: 966.26245 | Y24: 975.91791 | Z24: 985.93042 | AA24: 996.26337 | AB24: 1006.7398 | AC24: 1018.405 | AD24: 1030.9612 | AE24: 1044.9469 | AF24: 1059.7432 | AG24: 1074.549 | AH24: 1088.3407 | AI24: 1102.0864 | AJ24: 1115.8612 | AK24: 0.006704
A25: TEF000:clt_MotorGas | B25: Motor Gasoline excluding E85 1/ | C25: 606.36536 | D25: 605.30756 | E25: 607.94952 | F25: 604.1377 | G25: 596.90875 | H25: 589.81464 | I25: 582.98096 | J25: 571.22607 | K25: 558.56311 | L25: 555.41858 | M25: 547.30902 | N25: 541.48975 | O25: 534.28339 | P25: 526.78314 | Q25: 523.7121 | R25: 523.11548 | S25: 521.3371 | T25: 519.05609 | U25: 520.57098 | V25: 521.24829 | W25: 524.30823 | X25: 529.17877 | Y25: 536.13806 | Z25: 543.30438 | AA25: 554.95044 | AB25: 565.55859 | AC25: 579.68866 | AD25: 591.68262 | AE25: 603.7323 | AF25: 627.19488 | AG25: 656.53931 | AH25: 678.30609 | AI25: 686.05109 | AJ25: 693.75092 | AK25: 0.004271
A26: TEF000:clt_e85 | B26: E85 1/ | C26: 1.269456 | D26: 6.800088 | E26: 7.848506 | F26: 10.106414 | G26: 13.157337 | H26: 15.64352 | I26: 17.898479 | J26: 25.584816 | K26: 37.09631 | L26: 39.877831 | M26: 47.133904 | N26: 53.779694 | O26: 61.241974 | P26: 70.29538 | Q26: 74.829681 | R26: 79.007698 | S26: 84.767647 | T26: 93.049576 | U26: 98.679581 | V26: 105.63017 | W26: 112.19795 | X26: 117.53334 | Y26: 121.15105 | Z26: 124.08399 | AA26: 123.46315 | AB26: 123.15036 | AC26: 119.42245 | AD26: 118.49369 | AE26: 118.73388 | AF26: 107.51099 | AG26: 90.537163 | AH26: 81.026688 | AI26: 85.247459 | AJ26: 89.920685 | AK26: 0.084032
A27: TEF000:clt_Diesel | B27: Distillate Fuel Oil (diesel) | C27: 278.04269 | D27: 287.6564 | E27: 296.22836 | F27: 301.69147 | G27: 305.41623 | H27: 308.36707 | I27: 310.91235 | J27: 312.15439 | K27: 314.06976 | L27: 315.12363 | M27: 315.64606 | N27: 316.47168 | O27: 316.24033 | P27: 314.69565 | Q27: 315.3865 | R27: 314.75931 | S27: 315.19653 | T27: 315.28622 | U27: 315.54571 | V27: 316.2467 | W27: 316.27335 | X27: 316.45166 | Y27: 315.36044 | Z27: 315.10004 | AA27: 314.21469 | AB27: 314.19943 | AC27: 315.25479 | AD27: 316.50549 | AE27: 317.94644 | AF27: 320.25555 | AG27: 322.41006 | AH27: 323.64139 | AI27: 325.08737 | AJ27: 326.11346 | AK27: 0.003929
... A29: TEF000:clt_natural_gas | B29: Compressed/Liquefied Natural Gas | C29: 1.219097 | D29: 1.190767 | E29: 1.092497 | F29: 0.954232 | G29: 0.894892 | H29: 0.832107 | I29: 0.81816 | J29: 0.805134 | K29: 0.787249 | L29: 0.773612 | M29: 0.752692 | N29: 0.739955 | O29: 0.730588 | P29: 0.720062 | Q29: 0.713187 | R29: 0.708915 | S29: 0.717549 | T29: 0.734263 | U29: 0.759474 | V29: 0.791415 | W29: 0.829726 | X29: 0.877413 | Y29: 0.934525 | Z29: 0.998199 | AA29: 1.073186 | AB29: 1.155634 | AC29: 1.24983 | AD29: 1.368331 | AE29: 1.49507 | AF29: 1.610998 | AG29: 1.760768 | AH29: 1.920488 | AI29: 2.110897 | AJ29: 2.328216 | AK29: 0.021174
A30: TEF000:clt_electricity | B30: Electricity | C30: 0 | D30: 0 | E30: 0 | F30: 0.063651 | G30: 0.124021 | H30: 0.182401 | I30: 0.23847 | J30: 0.293579 | K30: 0.348081 | L30: 0.402068 | M30: 0.438809 | N30: 0.476974 | O30: 0.513499 | P30: 0.551586 | Q30: 0.58777 | R30: 0.625829 | S30: 0.664104 | T30: 0.704511 | U30: 0.745161 | V30: 0.787404 | W30: 0.831684 | X30: 0.875624 | Y30: 0.921643 | Z30: 0.966855 | AA30: 1.015562 | AB30: 1.063054 | AC30: 1.110935 | AD30: 1.162578 | AE30: 1.217335 | AF30: 1.273639 | AG30: 1.330102 | AH30: 1.391987 | AI30: 1.453642 | AJ30: 1.518894 | AK30: - -
A31: TEF000:clt_hydrogen | B31: Hydrogen | C31: 0 | D31: 0 | E31: 0 | F31: 0 | G31: 0 | H31: 0 | I31: 0 | J31: 0 | K31: 0 | L31: 0 | M31: 0 | N31: 0 | O31: 0 | P31: 0 | Q31: 0 | R31: 0 | S31: 0 | T31: 0 | U31: 0 | V31: 0 | W31: 0 | X31: 0 | Y31: 0 | Z31: 0 | AA31: 0 | AB31: 0 | AC31: 0 | AD31: 0 | AE31: 0 | AF31: 0 | AG31: 0 | AH31: 0 | AI31: 0 | AJ31: 0 | AK31: - -
A33: TEF000:da_Total | B33: Freight Trucks 3/ | C33: 5649.7139 | D33: 5725.2593 | E33: 5818.2104 | F33: 5830.04 | G33: 5814.6382 | H33: 5814.2666 | I33: 5813.0493 | J33: 5804.3057 | K33: 5792.9771 | L33: 5777.2124 | M33: 5741.1816 | N33: 5710.9766 | O33: 5669.7437 | P33: 5629.2808 | Q33: 5599.5835 | R33: 5569.5664 | S33: 5545.6562 | T33: 5537.8218 | U33: 5547.3721 | V33: 5561.834 | W33: 5587.002 | X33: 5616.1782 | Y33: 5643.7476 | Z33: 5665.542 | AA33: 5698.0361 | AB33: 5732.9048 | AC33: 5773.4688 | AD33: 5824.3999 | AE33: 5880.1401 | AF33: 5936.2446 | AG33: 5998.6572 | AH33: 6065.2212 | AI33: 6124.8315 | AJ33: 6190.8994 | AK33: 0.002447
A34: TEF000:da_MotorGasoline | B34: Motor Gasoline | C34: 524.6004 | D34: 526.05066 | E34: 531.52698 | F34: 534.25391 | G34: 536.1546 | H34: 538.6864 | I34: 542.30347 | J34: 545.79401 | K34: 547.48041 | L34: 552.80963 | M34: 555.23926 | N34: 559.45953 | O34: 565.21631 | P34: 567.23321 | Q34: 575.14087 | R34: 580.8081 | S34: 587.01581 | T34: 595.185 | U34: 604.73083 | V34: 615.77203 | W34: 626.92511 | X34: 641.21844 | Y34: 653.27844 | Z34: 668.64557 | AA34: 683.95618 | AB34: 700.56818 | AC34: 719.54102 | AD34: 737.58557 | AE34: 756.44464 | AF34: 780.32105 | AG34: 807.35449 | AH34: 832.86005 | AI34: 852.19983 | AJ34: 872.95386 | AK34: 0.015954
A35: TEF000:da_Distillate(di | B35: Distillate Fuel Oil (diesel) | C35: 5085.1343 | D35: 5153.1602 | E35: 5236.2329 | F35: 5242.0928 | G35: 5222.1313 | H35: 5216.7358 | I35: 5209.6865 | J35: 5193.999 | K35: 5176.458 | L35: 5153.0332 | M35: 5111.042 | N35: 5072.7847 | O35: 5021.7363 | P35: 4973.9824 | Q35: 4932.1289 | R35: 4891.77 | S35: 4855.564 | T35: 4831.9932 | U35: 4824.6523 | V35: 4819.5981 | W35: 4824.5913 | X35: 4829.9502 | Y35: 4835.8374 | Z35: 4831.5806 | AA35: 4838.6494 | AB35: 4845.7031 | AC35: 4856.3198 | AD35: 4875.8486 | AE35: 4897.5234 | AF35: 4917.9126 | AG35: 4942.8105 | AH35: 4969.4038 | AI35: 4989.3945 | AJ35: 5013.7705 | AK35: -0.000857
A36: TEF000:da_CompressedNat | B36: Compressed/Liquefied Natural Gas | C36: 38.148582 | D36: 41.969742 | E36: 45.182625 | F36: 47.002907 | G36: 48.040394 | H36: 48.9674 | I36: 49.663395 | J36: 50.090134 | K36: 50.380482 | L36: 50.671726 | M36: 50.900291 | N36: 51.443798 | O36: 52.070354 | P36: 53.034073 | Q36: 54.41201 | R36: 56.326271 | S36: 58.96563 | T36: 62.304535 | U36: 66.323441 | V36: 71.053864 | W36: 76.538681 | X36: 82.900162 | Y36: 90.034897 | Z36: 98.194077 | AA36: 107.21453 | AB36: 117.10681 | AC36: 128.00066 | AD36: 140.15523 | AE36: 153.60005 | AF36: 168.01939 | AG36: 183.19897 | AH36: 199.47244 | AI36: 216.06509 | AJ36: 233.0426 | AK36: 0.055032
A37: TEF000:da_LiquefiedPetr | B37: Propane | C37: 1.498156 | D37: 1.723063 | E37: 1.953256 | F37: 2.146609 | G37: 2.308614 | H37: 2.456173 | I37: 2.587135 | J37: 2.692057 | K37: 2.796156 | L37: 2.884792 | M37: 2.967321 | N37: 3.020453 | O37: 3.082369 | P37: 3.136817 | Q37: 3.175739 | R37: 3.251039 | S37: 3.326449 | T37: 3.408438 | U37: 3.512938 | V37: 3.628821 | W37: 3.759349 | X37: 3.904456 | Y37: 4.055053 | Z37: 4.221842 | AA37: 4.393282 | AB37: 4.570858 | AC37: 4.752207 | AD37: 4.947835 | AE37: 5.162933 | AF37: 5.388875 | AG37: 5.673164 | AH37: 5.882715 | AI37: 6.142014 | AJ37: 6.42971 | AK37: 0.042009
A38: TEF000:ft_eeeeeeeeeee85 | B38: E85 | C38: 0.3246 | D38: 1.628295 | E38: 1.872856 | F38: 2.416724 | G38: 3.209185 | H38: 3.917608 | I38: 4.594587 | J38: 6.818443 | K38: 10.255258 | L38: 11.512392 | M38: 14.055236 | N38: 16.588409 | O38: 19.274384 | P38: 22.838697 | Q38: 24.972017 | R38: 26.948196 | S38: 29.578747 | T38: 32.954845 | U38: 35.372707 | V38: 38.156052 | W38: 40.699623 | X38: 42.81509 | Y38: 44.225113 | Z38: 45.58128 | AA38: 45.490234 | AB38: 45.583302 | AC38: 44.42683 | AD38: 44.31554 | AE38: 44.65398 | AF38: 40.59256 | AG38: 34.289951 | AH38: 30.860264 | AI38: 32.801682 | AJ38: 34.905605 | AK38: 0.100522
A39: TEF000:ft_electricity | B39: Electricity | C39: 0.008046 | D39: 0.485918 | E39: 0.942142 | F39: 1.38731 | G39: 1.822418 | H39: 2.277648 | I39: 2.732923 | J39: 3.178591 | K39: 3.617856 | L39: 4.051343 | M39: 4.468708 | N39: 4.900696 | O39: 5.316817 | P39: 5.733423 | Q39: 6.151682 | R39: 6.574346 | S39: 7.017518 | T39: 7.477695 | U39: 7.960401 | V39: 8.470009 | W39: 8.990575 | X39: 9.533933 | Y39: 10.09076 | Z39: 10.693088 | AA39: 11.297967 | AB39: 11.913041 | AC39: 12.533807 | AD39: 13.190311 | AE39: 13.898199 | AF39: 14.634829 | AG39: 15.407668 | AH39: 16.235731 | AI39: 17.10915 | AJ39: 18.033409 | AK39: 0.11956
A40: TEF000:ft_hydrogen | B40: Hydrogen | C40: 0 | D40: 0.241363 | E40: 0.50012 | F40: 0.739795 | G40: 0.971506 | H40: 1.225471 | I40: 1.481001 | J40: 1.733284 | K40: 1.988616 | L40: 2.24914 | M40: 2.508825 | N40: 2.778879 | O40: 3.047051 | P40: 3.322155 | Q40: 3.602406 | R40: 3.888457 | S40: 4.187833 | T40: 4.498079 | U40: 4.81976 | V40: 5.155106 | W40: 5.497069 | X40: 5.856051 | Y40: 6.226105 | Z40: 6.626019 | AA40: 7.035265 | AB40: 7.459069 | AC40: 7.894515 | AD40: 8.357041 | AE40: 8.856513 | AF40: 9.375849 | AG40: 9.922225 | AH40: 10.505863 | AI40: 11.11958 | AJ40: 11.763825 | AK40: 0.129136
A43: TEF000:ea_Total | B43: Freight Rail 4/ | C43: 522.31348 | D43: 519.29571 | E43: 522.69519 | F43: 509.17395 | G43: 503.81244 | H43: 498.28558 | I43: 494.88437 | J43: 496.93982 | K43: 497.74182 | L43: 498.90024 | M43: 497.54709 | N43: 497.65418 | O43: 504.35425 | P43: 508.7308 | Q43: 506.71164 | R43: 504.3316 | S43: 504.46985 | T43: 501.50995 | U43: 501.86041 | V43: 502.84714 | W43: 502.67279 | X43: 503.47784 | Y43: 504.19418 | Z43: 504.51038 | AA43: 504.60919 | AB43: 504.09064 | AC43: 503.24023 | AD43: 503.68399 | AE43: 504.54095 | AF43: 504.20459 | AG43: 504.54315 | AH43: 505.44183 | AI43: 506.18845 | AJ43: 507.37259 | AK43: -0.000726
A44: TEF000:ea_Distillate(di | B44: Distillate Fuel Oil (diesel) | C44: 522.31348 | D44: 519.29571 | E44: 522.69519 | F44: 508.62906 | G44: 502.19608 | H44: 495.09235 | I44: 489.60803 | J44: 489.01086 | K44: 485.47165 | L44: 480.60495 | M44: 471.72385 | N44: 462.72113 | O44: 458.26724 | P44: 451.69775 | Q44: 439.62549 | R44: 427.54874 | S44: 417.86636 | T44: 405.88205 | U44: 396.84537 | V44: 388.50128 | W44: 379.45471 | X44: 371.34112 | Y44: 363.33615 | Z44: 355.22128 | AA44: 347.13797 | AB44: 338.82364 | AC44: 330.49014 | AD44: 323.1911 | AE44: 316.31207 | AF44: 308.8476 | AG44: 301.96307 | AH44: 295.55945 | AI44: 289.20377 | AJ44: 283.22842 | AK44: -0.018766
A45: TEF000:ea_ResidualOil | B45: Residual Fuel Oil | C45: 0 | D45: 0 | E45: 0 | F45: 0 | G45: 0 | H45: 0 | I45: 0 | J45: 0 | K45: 0 | L45: 0 | M45: 0 | N45: 0 | O45: 0 | P45: 0 | Q45: 0 | R45: 0 | S45: 0 | T45: 0 | U45: 0 | V45: 0 | W45: 0 | X45: 0 | Y45: 0 | Z45: 0 | AA45: 0 | AB45: 0 | AC45: 0 | AD45: 0 | AE45: 0 | AF45: 0 | AG45: 0 | AH45: 0 | AI45: 0 | AJ45: 0 | AK45: - -
A46: TEF000:ea_SeeEnGee | B46: Compressed Natural Gas | C46: 0 | D46: 0 | E46: 0 | F46: 0 | G46: 0 | H46: 0 | I46: 0 | J46: 0 | K46: 0 | L46: 0 | M46: 0 | N46: 0 | O46: 0 | P46: 0 | Q46: 0 | R46: 0 | S46: 0 | T46: 0 | U46: 0 | V46: 0 | W46: 0 | X46: 0 | Y46: 0 | Z46: 0 | AA46: 0 | AB46: 0 | AC46: 0 | AD46: 0 | AE46: 0 | AF46: 0 | AG46: 0 | AH46: 0 | AI46: 0 | AJ46: 0 | AK46: - -
A47: TEF000:ea_LiquidNG | B47: Liquefied Natural Gas | C47: 0 | D47: 0 | E47: 0 | F47: 0.544906 | G47: 1.616351 | H47: 3.193248 | I47: 5.27633 | J47: 7.928961 | K47: 12.270179 | L47: 18.2953 | M47: 25.823233 | N47: 34.933044 | O47: 46.087021 | P47: 57.033062 | Q47: 67.086143 | R47: 76.782883 | S47: 86.6035 | T47: 95.627899 | U47: 105.01504 | V47: 114.34585 | W47: 123.21808 | X47: 132.13673 | Y47: 140.85803 | Z47: 149.28909 | AA47: 157.47122 | AB47: 165.26701 | AC47: 172.75009 | AD47: 180.49289 | AE47: 188.22887 | AF47: 195.35698 | AG47: 202.58008 | AH47: 209.88238 | AI47: 216.98468 | AJ47: 224.14416 | AK47: - -
A49: TEF000:fa_Total | B49: Domestic Shipping | C49: 94.504654 | D49: 93.176033 | E49: 91.310684 | F49: 88.600655 | G49: 85.676697 | H49: 83.393082 | I49: 80.994202 | J49: 78.416794 | K49: 75.963287 | L49: 73.684006 | M49: 71.398972 | N49: 68.965057 | O49: 66.545532 | P49: 64.120544 | Q49: 62.829025 | R49: 61.462147 | S49: 60.181702 | T49: 58.948166 | U49: 57.776997 | V49: 56.567589 | W49: 55.52335 | X49: 54.441166 | Y49: 53.333256 | Z49: 52.192039 | AA49: 51.627144 | AB49: 51.063759 | AC49: 50.425755 | AD49: 49.870197 | AE49: 49.323185 | AF49: 48.837811 | AG49: 48.322044 | AH49: 47.877007 | AI49: 47.314251 | AJ49: 46.826477 | AK49: -0.021272
A50: TEF000:fa_Distillate(di | B50: Distillate Fuel Oil (diesel) | C50: 91.653206 | D50: 90.538925 | E50: 88.023674 | F50: 85.752136 | G50: 83.230179 | H50: 81.042969 | I50: 78.741394 | J50: 76.263206 | K50: 73.903214 | L50: 71.708344 | M50: 69.507538 | N50: 67.160042 | O50: 64.824844 | P50: 62.484051 | Q50: 61.24757 | R50: 59.936172 | S50: 58.708778 | T50: 57.525631 | U50: 56.401947 | V50: 55.237507 | W50: 54.235291 | X50: 53.197945 | Y50: 52.136215 | Z50: 51.012058 | AA50: 50.399712 | AB50: 49.786072 | AC50: 49.096878 | AD50: 48.484997 | AE50: 47.878189 | AF50: 47.327675 | AG50: 46.743977 | AH50: 46.224663 | AI50: 45.587563 | AJ50: 45.018429 | AK50: -0.021598
A51: TEF000:fa_ResidualOil | B51: Residual Oil | C51: 2.544341 | D51: 2.271792 | E51: 2.870655 | F51: 2.386124 | G51: 1.943896 | H51: 1.809858 | I51: 1.679463 | J51: 1.553509 | K51: 1.435882 | L51: 1.33319 | M51: 1.23104 | N51: 1.131057 | O51: 1.03578 | P51: 0.941132 | Q51: 0.86363 | R51: 0.788976 | S51: 0.716119 | T51: 0.647817 | U51: 0.583952 | V51: 0.528795 | W51: 0.472587 | X51: 0.410933 | Y51: 0.347049 | Z51: 0.29089 | AA51: 0.287727 | AB51: 0.284581 | AC51: 0.281012 | AD51: 0.277905 | AE51: 0.274842 | AF51: 0.272139 | AG51: 0.269256 | AH51: 0.266773 | AI51: 0.263622 | AJ51: 0.260896 | AK51: -0.065395
A52: TEF000:fa_MotorGasoline | B52: Compressed Natural Gas | C52: 0 | D52: 0 | E52: 0 | F52: 0 | G52: 0 | H52: 0 | I52: 0 | J52: 0 | K52: 0 | L52: 0 | M52: 0 | N52: 0 | O52: 0 | P52: 0 | Q52: 0 | R52: 0 | S52: 0 | T52: 0 | U52: 0 | V52: 0 | W52: 0 | X52: 0 | Y52: 0 | Z52: 0 | AA52: 0 | AB52: 0 | AC52: 0 | AD52: 0 | AE52: 0 | AF52: 0 | AG52: 0 | AH52: 0 | AI52: 0 | AJ52: 0 | AK52: - -
A53: TEF000:fa_LiquidNG | B53: Liquefied Natural Gas | C53: 0.307103 | D53: 0.365315 | E53: 0.416356 | F53: 0.462398 | G53: 0.502621 | H53: 0.540256 | I53: 0.573342 | J53: 0.600075 | K53: 0.624195 | L53: 0.642473 | M53: 0.660393 | N53: 0.673955 | O53: 0.684908 | P53: 0.695363 | Q53: 0.717825 | R53: 0.737001 | S53: 0.756804 | T53: 0.774719 | U53: 0.791095 | V53: 0.801283 | W53: 0.815472 | X53: 0.832288 | Y53: 0.849992 | Z53: 0.889093 | AA53: 0.939703 | AB53: 0.993105 | AC53: 1.047864 | AD53: 1.107296 | AE53: 1.170156 | AF53: 1.237994 | AG53: 1.308813 | AH53: 1.385572 | AI53: 1.463067 | AJ53: 1.547155 | AK53: 0.046139
A55: TEF000:ga_Total | B55: International Shipping | C55: 960.14685 | D55: 917.64832 | E55: 1039.9399 | F55: 861.3877 | G55: 864.63275 | H55: 921.43585 | I55: 932.80646 | J55: 938.77173 | K55: 944.17798 | L55: 940.25952 | M55: 937.01996 | N55: 935.38959 | O55: 937.24493 | P55: 929.83154 | Q55: 929.15436 | R55: 928.9978 | S55: 929.02295 | T55: 928.19122 | U55: 914.26904 | V55: 913.76849 | W55: 910.80359 | X55: 910.24292 | Y55: 909.77551 | Z55: 909.51111 | AA55: 908.90015 | AB55: 907.31934 | AC55: 914.15082 | AD55: 907.85168 | AE55: 908.362 | AF55: 905.30817 | AG55: 905.43854 | AH55: 905.901 | AI55: 907.05341 | AJ55: 907.21014 | AK55: -0.000357
A56: TEF000:ga_Distillate(di | B56: Distillate Fuel Oil (diesel) | C56: 285.26331 | D56: 284.82602 | E56: 373.9689 | F56: 494.09885 | G56: 391.50769 | H56: 314.95715 | I56: 296.20209 | J56: 285.24069 | K56: 278.03177 | L56: 281.65076 | M56: 280.63135 | N56: 281.7113 | O56: 280.3064 | P56: 288.04791 | Q56: 286.99866 | R56: 286.33151 | S56: 286.49921 | T56: 287.07068 | U56: 301.2489 | V56: 300.15228 | W56: 303.86438 | X56: 303.56253 | Y56: 302.87805 | Z56: 303.27158 | AA56: 303.63648 | AB56: 303.44531 | AC56: 298.36987 | AD56: 307.66925 | AE56: 309.14441 | AF56: 315.04559 | AG56: 317.74377 | AH56: 321.20062 | AI56: 323.9339 | AJ56: 326.75662 | AK56: 0.004301
A57: TEF000:ga_ResidualOil | B57: Residual Oil | C57: 674.88355 | D57: 625.86169 | E57: 652.02741 | F57: 349.82703 | G57: 422.30859 | H57: 564.66162 | I57: 591.87238 | J57: 605.63672 | K57: 618.08344 | L57: 607.13556 | M57: 597.92908 | N57: 592.59442 | O57: 596.05402 | P57: 575.94141 | Q57: 572.93042 | R57: 571.26422 | S57: 570.04895 | T57: 566.61694 | U57: 530.08911 | V57: 527.55548 | W57: 518.73828 | X57: 516.01593 | Y57: 513.54736 | Z57: 511.54697 | AA57: 508.67346 | AB57: 503.50537 | AC57: 519.27527 | AD57: 502.11008 | AE57: 501.87503 | AF57: 492.98715 | AG57: 492.03061 | AH57: 491.98279 | AI57: 493.63382 | AJ57: 492.72684 | AK57: -0.007446
A58: TEF000:ga_SeeEnGee | B58: Compressed Natural Gas | C58: 0 | D58: 0 | E58: 0 | F58: 0 | G58: 0 | H58: 0 | I58: 0 | J58: 0 | K58: 0 | L58: 0 | M58: 0 | N58: 0 | O58: 0 | P58: 0 | Q58: 0 | R58: 0 | S58: 0 | T58: 0 | U58: 0 | V58: 0 | W58: 0 | X58: 0 | Y58: 0 | Z58: 0 | AA58: 0 | AB58: 0 | AC58: 0 | AD58: 0 | AE58: 0 | AF58: 0 | AG58: 0 | AH58: 0 | AI58: 0 | AJ58: 0 | AK58: - -
A59: TEF000:ga_LiquidNG | B59: Liquefied Natural Gas | C59: 0 | D59: 6.960556 | E59: 13.943656 | F59: 17.461792 | G59: 50.816452 | H59: 41.817055 | I59: 44.731972 | J59: 47.894318 | K59: 48.062717 | L59: 51.473217 | M59: 58.459518 | N59: 61.083858 | O59: 60.884529 | P59: 65.842255 | Q59: 69.225288 | R59: 71.402107 | S59: 72.474823 | T59: 74.503609 | U59: 82.931046 | V59: 86.06073 | W59: 88.200905 | X59: 90.664413 | Y59: 93.350128 | Z59: 94.692589 | AA59: 96.590179 | AB59: 100.36864 | AC59: 96.505661 | AD59: 98.072403 | AE59: 97.342567 | AF59: 97.275436 | AG59: 95.664139 | AH59: 92.717598 | AI59: 89.485657 | AJ59: 87.726692 | AK59: 0.082406
A61: TEF000:ha_Total | B61: Air Transportation | C61: 2523.8835 | D61: 2543.4819 | E61: 2581.4346 | F61: 2614.51 | G61: 2639.6379 | H61: 2662.8723 | I61: 2688.8262 | J61: 2716.3872 | K61: 2747.7563 | L61: 2778.9209 | M61: 2807.3381 | N61: 2845.0901 | O61: 2875.0952 | P61: 2905.7217 | Q61: 2937.7036 | R61: 2968.9705 | S61: 3000.3457 | T61: 3033.1636 | U61: 3065.0688 | V61: 3096.1477 | W61: 3127.6626 | X61: 3159.9075 | Y61: 3191.2871 | Z61: 3223.0403 | AA61: 3254.7139 | AB61: 3286.7017 | AC61: 3321.4683 | AD61: 3356.6418 | AE61: 3394.1917 | AF61: 3431.6545 | AG61: 3470.7896 | AH61: 3509.7302 | AI61: 3548.4204 | AJ61: 3586.2966 | AK61: 0.010795
A62: TEF000:ha_JetFuel | B62: Jet Fuel | C62: 2501.3616 | D62: 2520.9883 | E62: 2558.9644 | F62: 2592.0591 | G62: 2617.2031 | H62: 2640.4507 | I62: 2666.4155 | J62: 2693.9856 | K62: 2725.3623 | L62: 2756.5332 | M62: 2784.9556 | N62: 2822.7117 | O62: 2852.7202 | P62: 2883.3496 | Q62: 2915.334 | R62: 2946.6028 | S62: 2977.9797 | T62: 3010.7991 | U62: 3042.7053 | V62: 3073.7852 | W62: 3105.3008 | X62: 3137.5464 | Y62: 3168.9265 | Z62: 3200.6802 | AA62: 3232.3542 | AB62: 3264.3423 | AC62: 3299.1091 | AD62: 3334.283 | AE62: 3371.8328 | AF62: 3409.2959 | AG62: 3448.4309 | AH62: 3487.3718 | AI62: 3526.062 | AJ62: 3563.9382 | AK62: 0.010878
A63: TEF000:ha_AviationGasol | B63: Aviation Gasoline | C63: 22.522085 | D63: 22.493759 | E63: 22.470324 | F63: 22.450933 | G63: 22.434891 | H63: 22.421618 | I63: 22.410635 | J63: 22.401548 | K63: 22.394032 | L63: 22.387812 | M63: 22.382666 | N63: 22.378407 | O63: 22.374884 | P63: 22.371969 | Q63: 22.369558 | R63: 22.367563 | S63: 22.365911 | T63: 22.364546 | U63: 22.363417 | V63: 22.36248 | W63: 22.361708 | X63: 22.361067 | Y63: 22.360538 | Z63: 22.3601 | AA63: 22.359737 | AB63: 22.359438 | AC63: 22.35919 | AD63: 22.358984 | AE63: 22.358814 | AF63: 22.358673 | AG63: 22.358557 | AH63: 22.358461 | AI63: 22.358381 | AJ63: 22.358315 | AK63: -0.000189
A65: TEF000:ia_Total | B65: Military Use | C65: 535.69592 | D65: 557.78418 | E65: 587.65662 | F65: 589.98645 | G65: 581.88269 | H65: 575.9754 | I65: 559.00671 | J65: 548.07452 | K65: 546.87756 | L65: 545.98315 | M65: 546.44183 | N65: 550.2215 | O65: 551.22302 | P65: 551.82996 | Q65: 552.4079 | R65: 552.95776 | S65: 553.48303 | T65: 553.98566 | U65: 554.46497 | V65: 554.93469 | W65: 555.39172 | X65: 555.83734 | Y65: 556.27051 | Z65: 556.69116 | AA65: 557.09833 | AB65: 557.49182 | AC65: 557.87427 | AD65: 558.23792 | AE65: 558.58929 | AF65: 558.92456 | AG65: 559.24536 | AH65: 559.55066 | AI65: 559.27002 | AJ65: 559.03436 | AK65: 7e-05
A66: TEF000:ia_JetFuel | B66: Jet Fuel and Aviation Gasoline | C66: 411.78094 | D66: 429.67706 | E66: 447.25525 | F66: 451.31705 | G66: 447.31091 | H66: 442.75149 | I66: 429.70361 | J66: 421.29785 | K66: 420.37631 | L66: 419.68909 | M66: 420.04205 | N66: 422.94763 | O66: 423.71698 | P66: 424.18457 | Q66: 424.62885 | R66: 425.05142 | S66: 425.45496 | T66: 425.84116 | U66: 426.2124 | V66: 426.5733 | W66: 426.92502 | X66: 427.26752 | Y66: 427.6004 | Z66: 427.92352 | AA66: 428.23648 | AB66: 428.53906 | AC66: 428.83099 | AD66: 429.11194 | AE66: 429.38171 | AF66: 429.64002 | AG66: 429.88657 | AH66: 430.12119 | AI66: 429.90521 | AJ66: 429.72415 | AK66: 3e-06
A67: TEF000:ia_ResidualFuel | B67: Residual Fuel Oil | C67: 19.091375 | D67: 18.727859 | E67: 26.547354 | F67: 23.781448 | G67: 20.703632 | H67: 20.51643 | I67: 19.917072 | J67: 19.530453 | K67: 19.489599 | L67: 19.457396 | M67: 19.473238 | N67: 19.607624 | O67: 19.644047 | P67: 19.664268 | Q67: 19.684889 | R67: 19.704618 | S67: 19.723619 | T67: 19.741726 | U67: 19.755281 | V67: 19.772219 | W67: 19.788031 | X67: 19.803955 | Y67: 19.819462 | Z67: 19.834751 | AA67: 19.8493 | AB67: 19.863184 | AC67: 19.879412 | AD67: 19.890583 | AE67: 19.90353 | AF67: 19.914705 | AG67: 19.926201 | AH67: 19.93713 | AI67: 19.92745 | AJ67: 19.918989 | AK67: 0.001929
A68: TEF000:ia_Distillate | B68: Distillates and Diesel | C68: 104.82359 | D68: 109.37927 | E68: 113.854 | F68: 114.88797 | G68: 113.86816 | H68: 112.7075 | I68: 109.386 | J68: 107.24623 | K68: 107.01163 | L68: 106.8367 | M68: 106.92654 | N68: 107.66621 | O68: 107.86203 | P68: 107.98108 | Q68: 108.09415 | R68: 108.20174 | S68: 108.30444 | T68: 108.40277 | U68: 108.49728 | V68: 108.58915 | W68: 108.6787 | X68: 108.76587 | Y68: 108.85062 | Z68: 108.93288 | AA68: 109.01253 | AB68: 109.08955 | AC68: 109.16388 | AD68: 109.23538 | AE68: 109.30406 | AF68: 109.36983 | AG68: 109.43259 | AH68: 109.49231 | AI68: 109.43733 | AJ68: 109.39125 | AK68: 3e-06
A70: TEF000:ja_Total | B70: Bus Transportation | C70: 236.259 | D70: 237.06056 | E70: 237.76503 | F70: 238.43889 | G70: 239.09854 | H70: 239.71158 | I70: 240.24525 | J70: 240.77428 | K70: 241.35846 | L70: 241.87195 | M70: 242.30301 | N70: 242.66446 | O70: 242.87593 | P70: 242.82253 | Q70: 242.45755 | R70: 241.58321 | S70: 239.52969 | T70: 238.89334 | U70: 239.29054 | V70: 239.64343 | W70: 239.95526 | X70: 240.22556 | Y70: 240.4541 | Z70: 240.64004 | AA70: 240.77985 | AB70: 240.87923 | AC70: 240.94214 | AD70: 240.97382 | AE70: 240.98682 | AF70: 240.9958 | AG70: 241.02161 | AH70: 241.08539 | AI70: 241.20442 | AJ70: 241.39595 | AK70: 0.000566
A71: TEF000:bus_transit_tot | B71: Transit Bus | C71: 99.369827 | D71: 99.438713 | E71: 99.472229 | F71: 99.505585 | G71: 99.526344 | H71: 99.541695 | I71: 99.557747 | J71: 99.547966 | K71: 99.476646 | L71: 99.396362 | M71: 99.302658 | N71: 99.182693 | O71: 99.0485 | P71: 98.863533 | Q71: 98.658394 | R71: 98.430016 | S71: 98.194893 | T71: 97.939285 | U71: 97.662361 | V71: 97.363182 | W71: 97.038231 | X71: 96.68071 | Y71: 96.284088 | Z71: 95.842407 | AA71: 95.347618 | AB71: 94.802689 | AC71: 94.208138 | AD71: 93.565514 | AE71: 92.884491 | AF71: 92.177803 | AG71: 91.466164 | AH71: 90.772598 | AI71: 90.117622 | AJ71: 89.522926 | AK71: -0.003277
A72: TEF000:ja_TransitBus(mo | B72: Motor Gasoline | C72: 11.445287 | D72: 11.466092 | E72: 11.482542 | F72: 11.498786 | G72: 11.513481 | H72: 11.527476 | I72: 11.541475 | J72: 11.552413 | K72: 11.556156 | L72: 11.558803 | M72: 11.55983 | N72: 11.557747 | O72: 11.553973 | P72: 11.544259 | Q72: 11.532174 | R72: 11.517338 | S72: 11.501655 | T72: 11.483509 | U72: 11.4628 | V72: 11.439426 | W72: 11.412994 | X72: 11.382687 | Y72: 11.347727 | Z72: 11.307388 | AA72: 11.260698 | AB72: 11.207987 | AC72: 11.149298 | AD72: 11.084787 | AE72: 11.015581 | AF72: 10.943103 | AG72: 10.869602 | AH72: 10.797935 | AI72: 10.730744 | AJ72: 10.670596 | AK72: -0.002244
A73: TEF000:bus_transit_e85 | B73: E85 | C73: 0.014615 | D73: 0.014637 | E73: 0.014656 | F73: 0.014678 | G73: 0.014699 | H73: 0.01472 | I73: 0.014742 | J73: 0.014761 | K73: 0.01477 | L73: 0.014778 | M73: 0.014784 | N73: 0.014785 | O73: 0.014783 | P73: 0.014774 | Q73: 0.014761 | R73: 0.014744 | S73: 0.014725 | T73: 0.014703 | U73: 0.014677 | V73: 0.014647 | W73: 0.014613 | X73: 0.014574 | Y73: 0.014528 | Z73: 0.014474 | AA73: 0.014412 | AB73: 0.014341 | AC73: 0.014262 | AD73: 0.014175 | AE73: 0.014081 | AF73: 0.013983 | AG73: 0.013886 | AH73: 0.013792 | AI73: 0.013705 | AJ73: 0.013628 | AK73: -0.002229
... A79: TEF000:bus_inter_total | B79: Intercity Bus | C79: 32.039715 | D79: 32.314651 | E79: 32.579014 | F79: 32.846046 | G79: 33.110317 | H79: 33.374207 | I79: 33.639603 | J79: 33.897377 | K79: 34.139076 | L79: 34.378258 | M79: 34.613281 | N79: 34.839771 | O79: 35.061768 | P79: 35.280872 | Q79: 35.495045 | R79: 35.703171 | S79: 35.912952 | T79: 36.119308 | U79: 36.321995 | V79: 36.520729 | W79: 36.715229 | X79: 36.905312 | Y79: 37.090851 | Z79: 37.271832 | AA79: 37.44838 | AB79: 37.620724 | AC79: 37.78907 | AD79: 37.953735 | AE79: 38.115044 | AF79: 38.273403 | AG79: 38.429111 | AH79: 38.582664 | AI79: 38.734631 | AJ79: 38.885582 | AK79: 0.005801
A80: TEF000:bus_inter_motor | B80: Motor Gasoline | C80: 0 | D80: 0 | E80: 0 | F80: 0 | G80: 0 | H80: 0 | I80: 0 | J80: 0 | K80: 0 | L80: 0 | M80: 0 | N80: 0 | O80: 0 | P80: 0 | Q80: 0 | R80: 0 | S80: 0 | T80: 0 | U80: 0 | V80: 0 | W80: 0 | X80: 0 | Y80: 0 | Z80: 0 | AA80: 0 | AB80: 0 | AC80: 0 | AD80: 0 | AE80: 0 | AF80: 0 | AG80: 0 | AH80: 0 | AI80: 0 | AJ80: 0 | AK80: - -
A81: TEF000:bus_inter_e85 | B81: E85 | C81: 0 | D81: 0 | E81: 0 | F81: 0 | G81: 0 | H81: 0 | I81: 0 | J81: 0 | K81: 0 | L81: 0 | M81: 0 | N81: 0 | O81: 0 | P81: 0 | Q81: 0 | R81: 0 | S81: 0 | T81: 0 | U81: 0 | V81: 0 | W81: 0 | X81: 0 | Y81: 0 | Z81: 0 | AA81: 0 | AB81: 0 | AC81: 0 | AD81: 0 | AE81: 0 | AF81: 0 | AG81: 0 | AH81: 0 | AI81: 0 | AJ81: 0 | AK81: - -
A82: TEF000:ja_IntercityBus( | B82: Distillate Fuel Oil (diesel) | C82: 32.039715 | D82: 32.314651 | E82: 32.579014 | F82: 32.846046 | G82: 33.110317 | H82: 33.374207 | I82: 33.639603 | J82: 33.897377 | K82: 34.139076 | L82: 34.378258 | M82: 34.613281 | N82: 34.839771 | O82: 35.061768 | P82: 35.280872 | Q82: 35.495045 | R82: 35.703171 | S82: 35.912952 | T82: 36.119308 | U82: 36.321995 | V82: 36.520729 | W82: 36.715229 | X82: 36.905312 | Y82: 37.090851 | Z82: 37.271832 | AA82: 37.44838 | AB82: 37.620724 | AC82: 37.78907 | AD82: 37.953735 | AE82: 38.115044 | AF82: 38.273403 | AG82: 38.429111 | AH82: 38.582664 | AI82: 38.734631 | AJ82: 38.885582 | AK82: 0.005801
A83: TEF000:bus_inter_CNG | B83: Compressed/Liquefied Natural Gas | C83: 0 | D83: 0 | E83: 0 | F83: 0 | G83: 0 | H83: 0 | I83: 0 | J83: 0 | K83: 0 | L83: 0 | M83: 0 | N83: 0 | O83: 0 | P83: 0 | Q83: 0 | R83: 0 | S83: 0 | T83: 0 | U83: 0 | V83: 0 | W83: 0 | X83: 0 | Y83: 0 | Z83: 0 | AA83: 0 | AB83: 0 | AC83: 0 | AD83: 0 | AE83: 0 | AF83: 0 | AG83: 0 | AH83: 0 | AI83: 0 | AJ83: 0 | AK83: - -
A84: TEF000:bus_inter_LPG | B84: Propane | C84: 0 | D84: 0 | E84: 0 | F84: 0 | G84: 0 | H84: 0 | I84: 0 | J84: 0 | K84: 0 | L84: 0 | M84: 0 | N84: 0 | O84: 0 | P84: 0 | Q84: 0 | R84: 0 | S84: 0 | T84: 0 | U84: 0 | V84: 0 | W84: 0 | X84: 0 | Y84: 0 | Z84: 0 | AA84: 0 | AB84: 0 | AC84: 0 | AD84: 0 | AE84: 0 | AF84: 0 | AG84: 0 | AH84: 0 | AI84: 0 | AJ84: 0 | AK84: - -
A85: TEF000:bus_inter_elec | B85: Electricity | C85: 0 | D85: 0 | E85: 0 | F85: 0 | G85: 0 | H85: 0 | I85: 0 | J85: 0 | K85: 0 | L85: 0 | M85: 0 | N85: 0 | O85: 0 | P85: 0 | Q85: 0 | R85: 0 | S85: 0 | T85: 0 | U85: 0 | V85: 0 | W85: 0 | X85: 0 | Y85: 0 | Z85: 0 | AA85: 0 | AB85: 0 | AC85: 0 | AD85: 0 | AE85: 0 | AF85: 0 | AG85: 0 | AH85: 0 | AI85: 0 | AJ85: 0 | AK85: - -
A86: TEF000:bus_inter_hydrog | B86: Hydrogen | C86: 0 | D86: 0 | E86: 0 | F86: 0 | G86: 0 | H86: 0 | I86: 0 | J86: 0 | K86: 0 | L86: 0 | M86: 0 | N86: 0 | O86: 0 | P86: 0 | Q86: 0 | R86: 0 | S86: 0 | T86: 0 | U86: 0 | V86: 0 | W86: 0 | X86: 0 | Y86: 0 | Z86: 0 | AA86: 0 | AB86: 0 | AC86: 0 | AD86: 0 | AE86: 0 | AF86: 0 | AG86: 0 | AH86: 0 | AI86: 0 | AJ86: 0 | AK86: - -
A87: TEF000:bus_school_total | B87: School Bus | C87: 105.3689 | D87: 105.88293 | E87: 106.35699 | F87: 106.81185 | G87: 107.28474 | H87: 107.73774 | I87: 108.13515 | J87: 108.59365 | K87: 109.22512 | L87: 109.84963 | M87: 110.47736 | N87: 111.16074 | O87: 111.83788 | P87: 112.48278 | Q87: 113.11958 | R87: 113.76159 | S87: 114.30199 | T87: 114.81098 | U87: 115.29339 | V87: 115.75518 | W87: 116.20332 | X87: 116.64357 | Y87: 117.0817 | Z87: 117.52226 | AA87: 117.96869 | AB87: 118.42373 | AC87: 118.89056 | AD87: 119.37257 | AE87: 119.87326 | AF87: 120.39498 | AG87: 120.93901 | AH87: 121.5056 | AI87: 122.09392 | AJ87: 122.70192 | AK87: 0.004618
A88: TEF000:ja_SchoolBus(mot | B88: Motor Gasoline | C88: 11.694694 | D88: 11.751745 | E88: 11.804358 | F88: 11.854843 | G88: 11.90733 | H88: 11.957606 | I88: 12.001713 | J88: 12.052602 | K88: 12.122687 | L88: 12.192 | M88: 12.261673 | N88: 12.337517 | O88: 12.412673 | P88: 12.484251 | Q88: 12.554927 | R88: 12.626182 | S88: 12.686161 | T88: 12.742651 | U88: 12.796194 | V88: 12.847446 | W88: 12.897185 | X88: 12.946047 | Y88: 12.994674 | Z88: 13.043573 | AA88: 13.093121 | AB88: 13.143623 | AC88: 13.195437 | AD88: 13.248935 | AE88: 13.304506 | AF88: 13.36241 | AG88: 13.422791 | AH88: 13.485676 | AI88: 13.550972 | AJ88: 13.618452 | AK88: 0.004618
A89: TEF000:bus_school_e85 | B89: E85 | C89: 0 | D89: 0 | E89: 0 | F89: 0 | G89: 0 | H89: 0 | I89: 0 | J89: 0 | K89: 0 | L89: 0 | M89: 0 | N89: 0 | O89: 0 | P89: 0 | Q89: 0 | R89: 0 | S89: 0 | T89: 0 | U89: 0 | V89: 0 | W89: 0 | X89: 0 | Y89: 0 | Z89: 0 | AA89: 0 | AB89: 0 | AC89: 0 | AD89: 0 | AE89: 0 | AF89: 0 | AG89: 0 | AH89: 0 | AI89: 0 | AJ89: 0 | AK89: - -
A90: TEF000:ja_SchoolBus(die | B90: Distillate Fuel Oil (diesel) | C90: 92.708397 | D90: 93.13887 | E90: 93.535439 | F90: 93.910034 | G90: 94.299271 | H90: 94.670967 | I90: 94.992752 | J90: 95.366325 | K90: 95.890762 | L90: 96.408051 | M90: 96.925148 | N90: 97.489685 | O90: 98.050026 | P90: 98.580727 | Q90: 99.103241 | R90: 99.62883 | S90: 100.06416 | T90: 100.47111 | U90: 100.85349 | V90: 101.21626 | W90: 101.56695 | X90: 101.90958 | Y90: 102.24928 | Z90: 102.59026 | AA90: 102.93573 | AB90: 103.28775 | AC90: 103.64975 | AD90: 104.02515 | AE90: 104.41649 | AF90: 104.82635 | AG90: 105.25599 | AH90: 105.70495 | AI90: 106.17307 | AJ90: 106.65813 | AK90: 0.004245
A91: TEF000:bus_school_CNG | B91: Compressed/Liquefied Natural Gas | C91: 0.875552 | D91: 0.901618 | E91: 0.926087 | F91: 0.955482 | G91: 0.986248 | H91: 1.016881 | I91: 1.048062 | J91: 1.081704 | K91: 1.11811 | L91: 1.155488 | M91: 1.195917 | N91: 1.238321 | O91: 1.279385 | P91: 1.32146 | Q91: 1.364525 | R91: 1.409136 | S91: 1.45376 | T91: 1.498877 | U91: 1.544955 | V91: 1.59232 | W91: 1.639645 | X91: 1.688031 | Y91: 1.737454 | Z91: 1.787768 | AA91: 1.838789 | AB91: 1.890926 | AC91: 1.943532 | AD91: 1.99625 | AE91: 2.049592 | AF91: 2.103099 | AG91: 2.156643 | AH91: 2.2109 | AI91: 2.265298 | AJ91: 2.320227 | AK91: 0.029979
A92: TEF000:bus_school_LPG | B92: Propane | C92: 0.090253 | D92: 0.090693 | E92: 0.091099 | F92: 0.091489 | G92: 0.091894 | H92: 0.092282 | I92: 0.092622 | J92: 0.093015 | K92: 0.093556 | L92: 0.094091 | M92: 0.094629 | N92: 0.095214 | O92: 0.095794 | P92: 0.096346 | Q92: 0.096892 | R92: 0.097442 | S92: 0.097905 | T92: 0.098341 | U92: 0.098754 | V92: 0.099149 | W92: 0.099533 | X92: 0.09991 | Y92: 0.100286 | Z92: 0.100663 | AA92: 0.101045 | AB92: 0.101435 | AC92: 0.101835 | AD92: 0.102248 | AE92: 0.102677 | AF92: 0.103124 | AG92: 0.10359 | AH92: 0.104075 | AI92: 0.104579 | AJ92: 0.105099 | AK92: 0.004618
A93: TEF000:bus_school_elec | B93: Electricity | C93: 0 | D93: 0 | E93: 0 | F93: 0 | G93: 0 | H93: 0 | I93: 0 | J93: 0 | K93: 0 | L93: 0 | M93: 0 | N93: 0 | O93: 0 | P93: 0 | Q93: 0 | R93: 0 | S93: 0 | T93: 0 | U93: 0 | V93: 0 | W93: 0 | X93: 0 | Y93: 0 | Z93: 0 | AA93: 0 | AB93: 0 | AC93: 0 | AD93: 0 | AE93: 0 | AF93: 0 | AG93: 0 | AH93: 0 | AI93: 0 | AJ93: 0 | AK93: - -
A94: TEF000:bus_school_hydro | B94: Hydrogen | C94: 0 | D94: 0 | E94: 0 | F94: 0 | G94: 0 | H94: 0 | I94: 0 | J94: 0 | K94: 0 | L94: 0 | M94: 0 | N94: 0 | O94: 0 | P94: 0 | Q94: 0 | R94: 0 | S94: 0 | T94: 0 | U94: 0 | V94: 0 | W94: 0 | X94: 0 | Y94: 0 | Z94: 0 | AA94: 0 | AB94: 0 | AC94: 0 | AD94: 0 | AE94: 0 | AF94: 0 | AG94: 0 | AH94: 0 | AI94: 0 | AJ94: 0 | AK94: - -
A95: TEF000:ma_Total | B95: Rail Transportation | C95: 46.543182 | D95: 46.795616 | E95: 47.529716 | F95: 48.111797 | G95: 48.721863 | H95: 49.29406 | I95: 49.853828 | J95: 50.42131 | K95: 51.025574 | L95: 51.643791 | M95: 52.195736 | N95: 52.874577 | O95: 53.353012 | P95: 53.960861 | Q95: 54.52364 | R95: 55.095329 | S95: 55.691116 | T95: 56.268394 | U95: 56.838783 | V95: 57.379852 | W95: 57.961891 | X95: 58.514736 | Y95: 59.056 | Z95: 59.589581 | AA95: 60.132507 | AB95: 60.652596 | AC95: 61.198776 | AD95: 61.74498 | AE95: 62.277622 | AF95: 62.803745 | AG95: 63.347012 | AH95: 63.862675 | AI95: 64.386002 | AJ95: 64.878014 | AK95: 0.010262
A96: TEF000:ka_IntercityRail | B96: Intercity Rail | C96: 10.186204 | D96: 10.297213 | E96: 10.405301 | F96: 10.514687 | G96: 10.623635 | H96: 10.732909 | I96: 10.843113 | J96: 10.951307 | K96: 11.054737 | L96: 11.157768 | M96: 11.25986 | N96: 11.359583 | O96: 11.458236 | P96: 11.556338 | Q96: 11.653212 | R96: 11.74848 | S96: 11.844672 | T96: 11.940115 | U96: 12.034717 | V96: 12.128381 | W96: 12.221003 | X96: 12.312513 | Y96: 12.40286 | Z96: 12.492033 | AA96: 12.580064 | AB96: 12.667017 | AC96: 12.752957 | AD96: 12.837978 | AE96: 12.92219 | AF96: 13.005719 | AG96: 13.088661 | AH96: 13.171181 | AI96: 13.25347 | AJ96: 13.335722 | AK96: 0.008113
A97: TEF000:ka_InterElect | B97: Electricity | C97: 1.679244 | D97: 1.697544 | E97: 1.715364 | F97: 1.733397 | G97: 1.751357 | H97: 1.769371 | I97: 1.787539 | J97: 1.805375 | K97: 1.822426 | L97: 1.839412 | M97: 1.856241 | N97: 1.872682 | O97: 1.888945 | P97: 1.905117 | Q97: 1.921087 | R97: 1.936793 | S97: 1.952651 | T97: 1.968385 | U97: 1.98398 | V97: 1.999421 | W97: 2.01469 | X97: 2.029777 | Y97: 2.04467 | Z97: 2.059371 | AA97: 2.073883 | AB97: 2.088218 | AC97: 2.102386 | AD97: 2.116402 | AE97: 2.130284 | AF97: 2.144054 | AG97: 2.157728 | AH97: 2.171332 | AI97: 2.184897 | AJ97: 2.198458 | AK97: 0.008113
A98: TEF000:la_InterDiesel | B98: Diesel | C98: 8.50696 | D98: 8.599669 | E98: 8.689938 | F98: 8.78129 | G98: 8.872278 | H98: 8.963538 | I98: 9.055574 | J98: 9.145932 | K98: 9.232311 | L98: 9.318357 | M98: 9.403619 | N98: 9.486901 | O98: 9.569291 | P98: 9.651221 | Q98: 9.732124 | R98: 9.811687 | S98: 9.892021 | T98: 9.97173 | U98: 10.050736 | V98: 10.12896 | W98: 10.206312 | X98: 10.282737 | Y98: 10.35819 | Z98: 10.432662 | AA98: 10.506181 | AB98: 10.578799 | AC98: 10.650572 | AD98: 10.721577 | AE98: 10.791905 | AF98: 10.861665 | AG98: 10.930933 | AH98: 10.999848 | AI98: 11.068573 | AJ98: 11.137264 | AK98: 0.008113
A99: TEF000:la_InterCNG | B99: Compressed Natural Gas | C99: 0 | D99: 0 | E99: 0 | F99: 0 | G99: 0 | H99: 0 | I99: 0 | J99: 0 | K99: 0 | L99: 0 | M99: 0 | N99: 0 | O99: 0 | P99: 0 | Q99: 0 | R99: 0 | S99: 0 | T99: 0 | U99: 0 | V99: 0 | W99: 0 | X99: 0 | Y99: 0 | Z99: 0 | AA99: 0 | AB99: 0 | AC99: 0 | AD99: 0 | AE99: 0 | AF99: 0 | AG99: 0 | AH99: 0 | AI99: 0 | AJ99: 0 | AK99: - -
A100: TEF000:la_InterLNG | B100: Liquefied Natural Gas | C100: 0 | D100: 0 | E100: 0 | F100: 0 | G100: 0 | H100: 0 | I100: 0 | J100: 0 | K100: 0 | L100: 0 | M100: 0 | N100: 0 | O100: 0 | P100: 0 | Q100: 0 | R100: 0 | S100: 0 | T100: 0 | U100: 0 | V100: 0 | W100: 0 | X100: 0 | Y100: 0 | Z100: 0 | AA100: 0 | AB100: 0 | AC100: 0 | AD100: 0 | AE100: 0 | AF100: 0 | AG100: 0 | AH100: 0 | AI100: 0 | AJ100: 0 | AK100: - -
A101: TEF000:la_TransitRail | B101: Transit Rail | C101: 15.999097 | D101: 16.130722 | E101: 16.316534 | F101: 16.481346 | G101: 16.641085 | H101: 16.795181 | I101: 16.949228 | J101: 17.103592 | K101: 17.257421 | L101: 17.411604 | M101: 17.557076 | N101: 17.719833 | O101: 17.849571 | P101: 17.987839 | Q101: 18.116646 | R101: 18.243845 | S101: 18.372829 | T101: 18.497709 | U101: 18.617874 | V101: 18.729818 | W101: 18.843767 | X101: 18.949032 | Y101: 19.047655 | Z101: 19.140423 | AA101: 19.22575 | AB101: 19.303459 | AC101: 19.379301 | AD101: 19.45117 | AE101: 19.519167 | AF101: 19.590424 | AG101: 19.67058 | AH101: 19.757105 | AI101: 19.856714 | AJ101: 19.965975 | AK101: 0.006688
A102: TEF000:la_TransitElect | B102: Electricity | C102: 15.999097 | D102: 16.130722 | E102: 16.316534 | F102: 16.481346 | G102: 16.641085 | H102: 16.795181 | I102: 16.949228 | J102: 17.103592 | K102: 17.257421 | L102: 17.411604 | M102: 17.557076 | N102: 17.719833 | O102: 17.849571 | P102: 17.987839 | Q102: 18.116646 | R102: 18.243845 | S102: 18.372829 | T102: 18.497709 | U102: 18.617874 | V102: 18.729818 | W102: 18.843767 | X102: 18.949032 | Y102: 19.047655 | Z102: 19.140423 | AA102: 19.22575 | AB102: 19.303459 | AC102: 19.379301 | AD102: 19.45117 | AE102: 19.519167 | AF102: 19.590424 | AG102: 19.67058 | AH102: 19.757105 | AI102: 19.856714 | AJ102: 19.965975 | AK102: 0.006688
A103: TEF000:ma_CommuterRail | B103: Commuter Rail | C103: 20.357882 | D103: 20.36768 | E103: 20.807882 | F103: 21.115765 | G103: 21.457144 | H103: 21.76597 | I103: 22.061487 | J103: 22.366409 | K103: 22.713413 | L103: 23.074417 | M103: 23.378798 | N103: 23.795158 | O103: 24.045202 | P103: 24.416687 | Q103: 24.75378 | R103: 25.103004 | S103: 25.473616 | T103: 25.830566 | U103: 26.186192 | V103: 26.521656 | W103: 26.897118 | X103: 27.253191 | Y103: 27.605484 | Z103: 27.957125 | AA103: 28.326696 | AB103: 28.682119 | AC103: 29.066517 | AD103: 29.455832 | AE103: 29.836266 | AF103: 30.207603 | AG103: 30.587774 | AH103: 30.934389 | AI103: 31.275814 | AJ103: 31.576313 | AK103: 0.013796
A104: TEF000:ma_CommuteElect | B104: Electricity | C104: 6.143769 | D104: 6.18303 | E104: 6.28751 | F104: 6.367311 | G104: 6.44553 | H104: 6.51592 | I104: 6.58683 | J104: 6.66125 | K104: 6.744179 | L104: 6.829462 | M104: 6.906077 | N104: 7.003094 | O104: 7.084211 | P104: 7.167954 | Q104: 7.248398 | R104: 7.328752 | S104: 7.411416 | T104: 7.492105 | U104: 7.570178 | V104: 7.645185 | W104: 7.724296 | X104: 7.801973 | Y104: 7.878188 | Z104: 7.954695 | AA104: 8.033718 | AB104: 8.111521 | AC104: 8.191443 | AD104: 8.27075 | AE104: 8.348461 | AF104: 8.424042 | AG104: 8.501192 | AH104: 8.573233 | AI104: 8.64048 | AJ104: 8.697745 | AK104: 0.010721
A105: TEF000:ma_CommuteDiesel | B105: Diesel | C105: 14.214112 | D105: 14.184649 | E105: 14.520372 | F105: 14.748454 | G105: 15.011614 | H105: 15.250051 | I105: 15.474657 | J105: 15.70516 | K105: 15.969234 | L105: 16.244955 | M105: 16.472721 | N105: 16.792065 | O105: 16.960991 | P105: 17.248732 | Q105: 17.505383 | R105: 17.774252 | S105: 18.062201 | T105: 18.338461 | U105: 18.616014 | V105: 18.876471 | W105: 19.172823 | X105: 19.451218 | Y105: 19.727297 | Z105: 20.00243 | AA105: 20.292978 | AB105: 20.570599 | AC105: 20.875072 | AD105: 21.185081 | AE105: 21.487804 | AF105: 21.783562 | AG105: 22.086582 | AH105: 22.361156 | AI105: 22.635334 | AJ105: 22.878569 | AK105: 0.015051
A106: TEF000:ma_CommuteCNG | B106: Compressed Natural Gas | C106: 0 | D106: 0 | E106: 0 | F106: 0 | G106: 0 | H106: 0 | I106: 0 | J106: 0 | K106: 0 | L106: 0 | M106: 0 | N106: 0 | O106: 0 | P106: 0 | Q106: 0 | R106: 0 | S106: 0 | T106: 0 | U106: 0 | V106: 0 | W106: 0 | X106: 0 | Y106: 0 | Z106: 0 | AA106: 0 | AB106: 0 | AC106: 0 | AD106: 0 | AE106: 0 | AF106: 0 | AG106: 0 | AH106: 0 | AI106: 0 | AJ106: 0 | AK106: - -
A107: TEF000:ma_CommuteLNG | B107: Liquefied Natural Gas | C107: 0 | D107: 0 | E107: 0 | F107: 0 | G107: 0 | H107: 0 | I107: 0 | J107: 0 | K107: 0 | L107: 0 | M107: 0 | N107: 0 | O107: 0 | P107: 0 | Q107: 0 | R107: 0 | S107: 0 | T107: 0 | U107: 0 | V107: 0 | W107: 0 | X107: 0 | Y107: 0 | Z107: 0 | AA107: 0 | AB107: 0 | AC107: 0 | AD107: 0 | AE107: 0 | AF107: 0 | AG107: 0 | AH107: 0 | AI107: 0 | AJ107: 0 | AK107: - -
A109: TEF000:na_RecreationBoa | B109: Recreational Boats | C109: 242.86507 | D109: 242.79819 | E109: 243.49927 | F109: 243.79782 | G109: 244.15794 | H109: 244.39502 | I109: 244.57638 | J109: 244.72051 | K109: 244.89648 | L109: 245.08664 | M109: 245.12131 | N109: 245.3465 | O109: 245.31044 | P109: 245.28795 | Q109: 245.21646 | R109: 245.07678 | S109: 244.89252 | T109: 244.69249 | U109: 244.41064 | V109: 244.05093 | W109: 243.7038 | X109: 243.28809 | Y109: 242.82324 | Z109: 242.32367 | AA109: 241.79251 | AB109: 241.21249 | AC109: 240.62975 | AD109: 240.03799 | AE109: 239.40691 | AF109: 238.78275 | AG109: 238.1481 | AH109: 237.45334 | AI109: 236.73523 | AJ109: 235.95892 | AK109: -0.000893
A110: TEF000:na_RecreateGas | B110: Gasoline | C110: 191.36455 | D110: 190.83237 | E110: 190.20715 | F110: 189.55968 | G110: 188.87769 | H110: 188.15933 | I110: 187.40134 | J110: 186.60229 | K110: 185.7618 | L110: 184.88086 | M110: 183.95613 | N110: 182.98595 | O110: 181.96875 | P110: 180.90401 | Q110: 179.79146 | R110: 178.63126 | S110: 177.42419 | T110: 176.17131 | U110: 174.87384 | V110: 173.53328 | W110: 172.15123 | X110: 170.7294 | Y110: 169.26956 | Z110: 167.77354 | AA110: 166.24324 | AB110: 164.68083 | AC110: 163.08829 | AD110: 161.46796 | AE110: 159.82219 | AF110: 158.15314 | AG110: 156.46228 | AH110: 154.75143 | AI110: 153.02231 | AJ110: 151.27631 | AK110: -0.007233
A111: TEF000:na_RecreateDies | B111: Distillate Fuel Oil (diesel) | C111: 51.500519 | D111: 51.965816 | E111: 53.292122 | F111: 54.238152 | G111: 55.280254 | H111: 56.235687 | I111: 57.175053 | J111: 58.11821 | K111: 59.134693 | L111: 60.205788 | M111: 61.165173 | N111: 62.360554 | O111: 63.341694 | P111: 64.383942 | Q111: 65.425003 | R111: 66.445526 | S111: 67.46833 | T111: 68.521179 | U111: 69.536812 | V111: 70.517662 | W111: 71.552567 | X111: 72.558678 | Y111: 73.55368 | Z111: 74.550117 | AA111: 75.549271 | AB111: 76.531662 | AC111: 77.541458 | AD111: 78.570045 | AE111: 79.584717 | AF111: 80.629601 | AG111: 81.685829 | AH111: 82.701912 | AI111: 83.712914 | AJ111: 84.682617 | AK111: 0.015377
A113: TEF000:na_Lubricants | B113: Lubricants | C113: 135.3177 | D113: 134.27882 | E113: 133.61671 | F113: 133.10899 | G113: 132.63217 | H113: 131.97607 | I113: 131.4025 | J113: 130.87509 | K113: 130.32767 | L113: 129.81949 | M113: 129.33656 | N113: 128.91829 | O113: 128.54936 | P113: 128.27327 | Q113: 128.13788 | R113: 127.99053 | S113: 127.88733 | T113: 127.90371 | U113: 127.90703 | V113: 127.89866 | W113: 127.92197 | X113: 127.96122 | Y113: 127.98297 | Z113: 128.01708 | AA113: 128.05205 | AB113: 128.12657 | AC113: 128.19894 | AD113: 128.31226 | AE113: 128.43161 | AF113: 128.53868 | AG113: 128.60692 | AH113: 128.63573 | AI113: 128.6767 | AJ113: 128.71118 | AK113: -0.001323
A114: TEF000:na_PipelineFuelN | B114: Pipeline Fuel Natural Gas | C114: 679.1535 | D114: 704.26373 | E114: 690.70654 | F114: 673.19165 | G114: 660.01245 | H114: 647.85309 | I114: 640.44488 | J114: 641.46558 | K114: 653.29547 | L114: 657.33301 | M114: 664.64691 | N114: 673.61926 | O114: 680.86157 | P114: 682.96491 | Q114: 685.36377 | R114: 692.49524 | S114: 693.11206 | T114: 696.35352 | U114: 697.71765 | V114: 700.13562 | W114: 700.37878 | X114: 703.28394 | Y114: 706.42126 | Z114: 711.11011 | AA114: 715.578 | AB114: 721.45178 | AC114: 725.30786 | AD114: 731.30902 | AE114: 736.50281 | AF114: 740.3529 | AG114: 745.32843 | AH114: 751.28027 | AI114: 757.93085 | AJ114: 764.31818 | AK114: 0.00256
A116: TEF000:pa_TotalConsumpt | B116: Total Consumption | C116: 27942.273 | D116: 28028.387 | E116: 28231.379 | F116: 27907.551 | G116: 27649.613 | H116: 27413.68 | I116: 27081.539 | J116: 26737.729 | K116: 26403.916 | L116: 26130.223 | M116: 25866.311 | N116: 25650.449 | O116: 25419.377 | P116: 25192.322 | Q116: 24995.238 | R116: 24816.873 | S116: 24656.07 | T116: 24529.459 | U116: 24422.037 | V116: 24372.002 | W116: 24351.914 | X116: 24362.824 | Y116: 24386.867 | Z116: 24422.039 | AA116: 24479.832 | AB116: 24551.398 | AC116: 24650.125 | AD116: 24759.98 | AE116: 24889.34 | AF116: 25021.359 | AG116: 25169.119 | AH116: 25320.494 | AI116: 25468.285 | AJ116: 25620.25 | AK116: -0.002803
B118: 1/ E85 refers to a blend of 85 percent ethanol (renewable) and 15 percent motor gasoline (nonrenewable). To address cold starting issues,
B119: the percentage of ethanol varies seasonally. The annual average ethanol content of 74 percent is used for these projections.
B120: 2/ Commercial trucks from 8,501 to 10,000 pounds.
B121: 3/ Does not include military distillate. Does not include commercial buses.
B122: 4/ Does not include passenger rail.
B123: Btu = British thermal unit.
B124: - - = Not applicable.
...

Sheet AEO 40
B1: ref2019.d111618a | C1: 2017 | D1: 2018 | E1: 2019 | F1: 2020 | G1: 2021 | H1: 2022 | I1: 2023 | J1: 2024 | K1: 2025 | L1: 2026 | M1: 2027 | N1: 2028 | O1: 2029 | P1: 2030 | Q1: 2031 | R1: 2032 | S1: 2033 | T1: 2034 | U1: 2035 | V1: 2036 | W1: 2037 | X1: 2038 | Y1: 2039 | Z1: 2040 | AA1: 2041 | AB1: 2042 | AC1: 2043 | AD1: 2044 | AE1: 2045 | AF1: 2046 | AG1: 2047 | AH1: 2048 | AI1: 2049 | AJ1: 2050
C3: Report | D3: Annual Energy Outlook 2019
C4: Scenario | D4: ref2019 | G4: Reference case
C5: Datekey | D5: d111618a
C6: Release Date | E6: January 2019
A10: TSK000 | B10: 40. Light-Duty Vehicle Stock by Technology Type
B11: (millions)
AK12: 2018-
B13: Technology Type | C13: 2017 | D13: 2018 | E13: 2019 | F13: 2020 | G13: 2021 | H13: 2022 | I13: 2023 | J13: 2024 | K13: 2025 | L13: 2026 | M13: 2027 | N13: 2028 | O13: 2029 | P13: 2030 | Q13: 2031 | R13: 2032 | S13: 2033 | T13: 2034 | U13: 2035 | V13: 2036 | W13: 2037 | X13: 2038 | Y13: 2039 | Z13: 2040 | AA13: 2041 | AB13: 2042 | AC13: 2043 | AD13: 2044 | AE13: 2045 | AF13: 2046 | AG13: 2047 | AH13: 2048 | AI13: 2049 | AJ13: 2050 | AK13: 2050
B15: Car Stock 1/
B16: Conventional Cars
A17: TSK000:ba_GasolineICEVe | B17: Gasoline ICE Vehicles | C17: 122.71139 | D17: 123.13561 | E17: 123.25343 | F17: 123.22289 | G17: 123.05553 | H17: 122.71806 | I17: 122.45892 | J17: 122.26625 | K17: 122.13725 | L17: 122.02596 | M17: 121.91326 | N17: 121.73737 | O17: 121.48992 | P17: 121.22288 | Q17: 121.01881 | R17: 120.82484 | S17: 120.67058 | T17: 120.57618 | U17: 120.54005 | V17: 120.56654 | W17: 120.67582 | X17: 120.89253 | Y17: 121.17606 | Z17: 121.52527 | AA17: 121.93285 | AB17: 122.37875 | AC17: 122.83848 | AD17: 123.32587 | AE17: 123.81905 | AF17: 124.2961 | AG17: 124.71469 | AH17: 125.05521 | AI17: 125.33985 | AJ17: 125.55564 | AK17: 0.000608
A18: TSK000:ba_TDIDieselICE | B18: TDI Diesel ICE | C18: 0.803633 | D18: 0.777678 | E18: 0.766264 | F18: 0.770079 | G18: 0.778114 | H18: 0.792951 | I18: 0.816763 | J18: 0.849333 | K18: 0.893797 | L18: 0.952299 | M18: 1.026648 | N18: 1.123837 | O18: 1.23531 | P18: 1.363965 | Q18: 1.498988 | R18: 1.636628 | S18: 1.771043 | T18: 1.910757 | U18: 2.043822 | V18: 2.168493 | W18: 2.287811 | X18: 2.399066 | Y18: 2.501343 | Z18: 2.594395 | AA18: 2.677506 | AB18: 2.748384 | AC18: 2.807142 | AD18: 2.85537 | AE18: 2.891941 | AF18: 2.920111 | AG18: 2.939851 | AH18: 2.950457 | AI18: 2.953688 | AJ18: 2.949322 | AK18: 0.042537
A19: TSK000:ba_TotalConventi | B19: Total Conventional Cars | C19: 123.51502 | D19: 123.91329 | E19: 124.01969 | F19: 123.99297 | G19: 123.83364 | H19: 123.51101 | I19: 123.27568 | J19: 123.11558 | K19: 123.03105 | L19: 122.97826 | M19: 122.93991 | N19: 122.86121 | O19: 122.72523 | P19: 122.58684 | Q19: 122.51779 | R19: 122.46146 | S19: 122.44162 | T19: 122.48694 | U19: 122.58387 | V19: 122.73503 | W19: 122.96363 | X19: 123.2916 | Y19: 123.67741 | Z19: 124.11967 | AA19: 124.61036 | AB19: 125.12713 | AC19: 125.64562 | AD19: 126.18124 | AE19: 126.71098 | AF19: 127.21622 | AG19: 127.65454 | AH19: 128.00566 | AI19: 128.29353 | AJ19: 128.50496 | AK19: 0.001138
B21: Alternative-Fuel Cars
A22: TSK000:ca_Ethanol-FlexF | B22: Ethanol-Flex Fuel ICE | C22: 4.813383 | D22: 4.927487 | E22: 5.0174 | F22: 5.086414 | G22: 5.130294 | H22: 5.146977 | I22: 5.139135 | J22: 5.10922 | K22: 5.056395 | L22: 4.980655 | M22: 4.887201 | N22: 4.788911 | O22: 4.689025 | P22: 4.60491 | Q22: 4.539237 | R22: 4.489612 | S22: 4.458049 | T22: 4.454955 | U22: 4.46902 | V22: 4.498343 | W22: 4.548336 | X22: 4.609901 | Y22: 4.674325 | Z22: 4.739589 | AA22: 4.797886 | AB22: 4.846465 | AC22: 4.880943 | AD22: 4.905231 | AE22: 4.919268 | AF22: 4.911937 | AG22: 4.890924 | AH22: 4.860886 | AI22: 4.825336 | AJ22: 4.78445 | AK22: -0.00092
A23: TSK000:ca_100mileEV | B23: 100 Mile Electric Vehicle | C23: 0.195882 | D23: 0.208961 | E23: 0.260034 | F23: 0.313793 | G23: 0.372325 | H23: 0.440716 | I23: 0.513588 | J23: 0.595387 | K23: 0.680871 | L23: 0.760109 | M23: 0.837168 | N23: 0.906489 | O23: 0.972457 | P23: 1.033574 | Q23: 1.092179 | R23: 1.143182 | S23: 1.191302 | T23: 1.236534 | U23: 1.278813 | V23: 1.317466 | W23: 1.351504 | X23: 1.382852 | Y23: 1.412077 | Z23: 1.439353 | AA23: 1.463613 | AB23: 1.486122 | AC23: 1.507143 | AD23: 1.527547 | AE23: 1.547346 | AF23: 1.566476 | AG23: 1.585167 | AH23: 1.604149 | AI23: 1.623101 | AJ23: 1.642135 | AK23: 0.066546
A24: TSK000:ca_ElectricVehic | B24: 200 Mile Electric Vehicle | C24: 0.134602 | D24: 0.1797 | E24: 0.346257 | F24: 0.556082 | G24: 0.776677 | H24: 1.003166 | I24: 1.249311 | J24: 1.523463 | K24: 1.820851 | L24: 2.114036 | M24: 2.406856 | N24: 2.700799 | O24: 3.004122 | P24: 3.305918 | Q24: 3.623039 | R24: 3.954119 | S24: 4.301428 | T24: 4.665046 | U24: 5.042279 | V24: 5.432127 | W24: 5.833308 | X24: 6.250597 | Y24: 6.684587 | Z24: 7.137063 | AA24: 7.591192 | AB24: 8.045319 | AC24: 8.497761 | AD24: 8.949951 | AE24: 9.400811 | AF24: 9.849263 | AG24: 10.290888 | AH24: 10.725594 | AI24: 11.15103 | AJ24: 11.564273 | AK24: 0.138985
A25: TSK000:ea_FuelCellGasol | B25: 300 Mile Electric Vehicle | C25: 0.03085 | D25: 0.166121 | E25: 0.382303 | F25: 0.664127 | G25: 1.020759 | H25: 1.3958 | I25: 1.793634 | J25: 2.201296 | K25: 2.613906 | L25: 3.02542 | M25: 3.444076 | N25: 3.875262 | O25: 4.321768 | P25: 4.798095 | Q25: 5.305131 | R25: 5.836092 | S25: 6.386522 | T25: 6.950972 | U25: 7.521293 | V25: 8.09045 | W25: 8.655412 | X25: 9.212337 | Y25: 9.756588 | Z25: 10.286201 | AA25: 10.80535 | AB25: 11.314354 | AC25: 11.817442 | AD25: 12.315123 | AE25: 12.804375 | AF25: 13.284403 | AG25: 13.750421 | AH25: 14.200466 | AI25: 14.636414 | AJ25: 15.054511 | AK25: 0.151235
A26: TSK000:ca_Plug-inGasoli | B26: Plug-in 10 Gasoline Hybrid | C26: 0.166916 | D26: 0.194989 | E26: 0.225908 | F26: 0.261096 | G26: 0.311727 | H26: 0.370292 | I26: 0.432608 | J26: 0.498413 | K26: 0.568857 | L26: 0.63855 | M26: 0.707152 | N26: 0.773436 | O26: 0.836693 | P26: 0.896938 | Q26: 0.954492 | R26: 1.009833 | S26: 1.062623 | T26: 1.113106 | U26: 1.160533 | V26: 1.205132 | W26: 1.246999 | X26: 1.284144 | Y26: 1.318235 | Z26: 1.349379 | AA26: 1.377192 | AB26: 1.401889 | AC26: 1.423813 | AD26: 1.443546 | AE26: 1.46105 | AF26: 1.476283 | AG26: 1.489851 | AH26: 1.502311 | AI26: 1.513587 | AJ26: 1.524038 | AK26: 0.066365
A27: TSK000:ca_Plug-in40Hybd | B27: Plug-in 40 Gasoline Hybrid | C27: 0.157999 | D27: 0.264722 | E27: 0.376923 | F27: 0.493695 | G27: 0.601855 | H27: 0.699711 | I27: 0.792376 | J27: 0.88319 | K27: 0.969069 | L27: 1.054026 | M27: 1.140216 | N27: 1.227819 | O27: 1.322794 | P27: 1.419631 | Q27: 1.517574 | R27: 1.615744 | S27: 1.712074 | T27: 1.807249 | U27: 1.900304 | V27: 1.993035 | W27: 2.085741 | X27: 2.179276 | Y27: 2.273645 | Z27: 2.369363 | AA27: 2.463845 | AB27: 2.557444 | AC27: 2.649464 | AD27: 2.739549 | AE27: 2.826879 | AF27: 2.910505 | AG27: 2.989496 | AH27: 3.064125 | AI27: 3.133706 | AJ27: 3.198083 | AK27: 0.080975
A28: TSK000:ca_Electric-Dies | B28: Electric-Diesel Hybrid | C28: 0 | D28: 0 | E28: 0 | F28: 0 | G28: 0 | H28: 0 | I28: 0 | J28: 0 | K28: 0 | L28: 0 | M28: 0 | N28: 0 | O28: 0 | P28: 0.001106 | Q28: 0.006045 | R28: 0.014296 | S28: 0.024435 | T28: 0.035563 | U28: 0.047097 | V28: 0.058716 | W28: 0.070455 | X28: 0.08217 | Y28: 0.093822 | Z28: 0.105484 | AA28: 0.117164 | AB28: 0.128677 | AC28: 0.139957 | AD28: 0.15096 | AE28: 0.161474 | AF28: 0.171426 | AG28: 0.180641 | AH28: 0.188912 | AI28: 0.196291 | AJ28: 0.202719 | AK28: - -
A29: TSK000:ca_Electric-Gaso | B29: Electric-Gasoline Hybrid | C29: 3.706463 | D29: 4.135645 | E29: 4.549326 | F29: 4.944612 | G29: 5.317537 | H29: 5.665772 | I29: 6.013466 | J29: 6.364937 | K29: 6.703647 | L29: 7.046333 | M29: 7.395318 | N29: 7.749272 | O29: 8.110472 | P29: 8.47981 | Q29: 8.859372 | R29: 9.236145 | S29: 9.608261 | T29: 9.971205 | U29: 10.323838 | V29: 10.665428 | W29: 10.998904 | X29: 11.323565 | Y29: 11.633993 | Z29: 11.931743 | AA29: 12.21639 | AB29: 12.484378 | AC29: 12.734292 | AD29: 12.967894 | AE29: 13.183614 | AF29: 13.379957 | AG29: 13.55348 | AH29: 13.70423 | AI29: 13.834745 | AJ29: 13.944232 | AK29: 0.038713
A30: TSK000:ca_CompressedNat | B30: Natural Gas ICE | C30: 0.029741 | D30: 0.024521 | E30: 0.019041 | F30: 0.017268 | G30: 0.01633 | H30: 0.015496 | I30: 0.014768 | J30: 0.014121 | K30: 0.013533 | L30: 0.013041 | M30: 0.012605 | N30: 0.012236 | O30: 0.011926 | P30: 0.011697 | Q30: 0.011563 | R30: 0.01148 | S30: 0.011457 | T30: 0.011497 | U30: 0.011577 | V30: 0.011685 | W30: 0.011779 | X30: 0.011888 | Y30: 0.012001 | Z30: 0.012114 | AA30: 0.01227 | AB30: 0.012376 | AC30: 0.012532 | AD30: 0.012681 | AE30: 0.012822 | AF30: 0.012952 | AG30: 0.01307 | AH30: 0.013175 | AI30: 0.013271 | AJ30: 0.013357 | AK30: -0.018804
A31: TSK000:da_CompressedNat | B31: Natural Gas Bi-fuel | C31: 0.048749 | D31: 0.047325 | E31: 0.046074 | F31: 0.044931 | G31: 0.043953 | H31: 0.043008 | I31: 0.042172 | J31: 0.041302 | K31: 0.040327 | L31: 0.039335 | M31: 0.038347 | N31: 0.037448 | O31: 0.036694 | P31: 0.036111 | Q31: 0.03575 | R31: 0.035506 | S31: 0.035422 | T31: 0.0355 | U31: 0.035655 | V31: 0.03586 | W31: 0.036056 | X31: 0.036274 | Y31: 0.036511 | Z31: 0.036762 | AA31: 0.03711 | AB31: 0.037473 | AC31: 0.037821 | AD31: 0.038169 | AE31: 0.038505 | AF31: 0.038822 | AG31: 0.039101 | AH31: 0.03934 | AI31: 0.039555 | AJ31: 0.039738 | AK31: -0.005445
A32: TSK000:da_LiquefiedPetr | B32: Propane ICE | C32: 0.004394 | D32: 0.00445 | E32: 0.004533 | F32: 0.004636 | G32: 0.004761 | H32: 0.004867 | I32: 0.004983 | J32: 0.005108 | K32: 0.005233 | L32: 0.005365 | M32: 0.005504 | N32: 0.005646 | O32: 0.005792 | P32: 0.005943 | Q32: 0.006101 | R32: 0.006253 | S32: 0.006407 | T32: 0.006562 | U32: 0.006711 | V32: 0.006855 | W32: 0.006998 | X32: 0.007137 | Y32: 0.007276 | Z32: 0.007419 | AA32: 0.007529 | AB32: 0.007673 | AC32: 0.007825 | AD32: 0.007982 | AE32: 0.008141 | AF32: 0.008301 | AG32: 0.00846 | AH32: 0.008615 | AI32: 0.008772 | AJ32: 0.008927 | AK32: 0.021997
A33: TSK000:ea_LiquefiedPetr | B33: Propane Bi-fuel | C33: 0.008613 | D33: 0.008585 | E33: 0.008586 | F33: 0.008629 | G33: 0.008718 | H33: 0.008786 | I33: 0.008874 | J33: 0.008972 | K33: 0.009068 | L33: 0.00917 | M33: 0.009277 | N33: 0.009386 | O33: 0.009503 | P33: 0.009624 | Q33: 0.00976 | R33: 0.009892 | S33: 0.010033 | T33: 0.010184 | U33: 0.010331 | V33: 0.010471 | W33: 0.010604 | X33: 0.010731 | Y33: 0.010855 | Z33: 0.01098 | AA33: 0.011036 | AB33: 0.011147 | AC33: 0.011264 | AD33: 0.011381 | AE33: 0.011495 | AF33: 0.011603 | AG33: 0.011702 | AH33: 0.011789 | AI33: 0.011869 | AJ33: 0.01194 | AK33: 0.010362
A34: TSK000:ea_FuelCellMetha | B34: Fuel Cell Methanol | C34: 0 | D34: 0 | E34: 0 | F34: 0 | G34: 0 | H34: 0 | I34: 0 | J34: 0 | K34: 0 | L34: 0 | M34: 0 | N34: 0 | O34: 0 | P34: 0 | Q34: 0 | R34: 0 | S34: 0 | T34: 0 | U34: 0 | V34: 0 | W34: 0 | X34: 0 | Y34: 0 | Z34: 0 | AA34: 0 | AB34: 0 | AC34: 0 | AD34: 0 | AE34: 0 | AF34: 0 | AG34: 0 | AH34: 0 | AI34: 0 | AJ34: 0 | AK34: - -
A35: TSK000:ea_FuelCellHydro | B35: Fuel Cell Hydrogen | C35: 0.00282 | D35: 0.005543 | E35: 0.010657 | F35: 0.019237 | G35: 0.034423 | H35: 0.056417 | I35: 0.079184 | J35: 0.104646 | K35: 0.132151 | L35: 0.159071 | M35: 0.185275 | N35: 0.209316 | O35: 0.232766 | P35: 0.255124 | Q35: 0.276566 | R35: 0.294879 | S35: 0.311813 | T35: 0.327609 | U35: 0.342043 | V35: 0.355095 | W35: 0.365934 | X35: 0.375168 | Y35: 0.38295 | Z35: 0.389479 | AA35: 0.394693 | AB35: 0.398869 | AC35: 0.402282 | AD35: 0.405169 | AE35: 0.407599 | AF35: 0.409628 | AG35: 0.411494 | AH35: 0.4135 | AI35: 0.415589 | AJ35: 0.417831 | AK35: 0.144627
A36: TSK000:ea_TotalAlternat | B36: Total Alternative Cars | C36: 9.300412 | D36: 10.168049 | E36: 11.247043 | F36: 12.414519 | G36: 13.639361 | H36: 14.851009 | I36: 16.084099 | J36: 17.350054 | K36: 18.613907 | L36: 19.84511 | M36: 21.068996 | N36: 22.296021 | O36: 23.55401 | P36: 24.858482 | Q36: 26.236809 | R36: 27.65703 | S36: 29.119825 | T36: 30.625978 | U36: 32.149498 | V36: 33.680664 | W36: 35.222031 | X36: 36.766041 | Y36: 38.296867 | Z36: 39.81493 | AA36: 41.295269 | AB36: 42.732185 | AC36: 44.12254 | AD36: 45.475185 | AE36: 46.783379 | AF36: 48.031551 | AG36: 49.214695 | AH36: 50.337093 | AI36: 51.403259 | AJ36: 52.406235 | AK36: 0.052579
A38: TSK000:fa_TotalNewCarSa | B38: Total Car Stock | C38: 132.81543 | D38: 134.08134 | E38: 135.26674 | F38: 136.40749 | G38: 137.47301 | H38: 138.36202 | I38: 139.35977 | J38: 140.46564 | K38: 141.64496 | L38: 142.82338 | M38: 144.00891 | N38: 145.15723 | O38: 146.27925 | P38: 147.44533 | Q38: 148.75461 | R38: 150.1185 | S38: 151.56145 | T38: 153.11291 | U38: 154.73337 | V38: 156.41569 | W38: 158.18567 | X38: 160.05763 | Y38: 161.97427 | Z38: 163.9346 | AA38: 165.90562 | AB38: 167.85931 | AC38: 169.76816 | AD38: 171.65643 | AE38: 173.49435 | AF38: 175.24777 | AG38: 176.86923 | AH38: 178.34276 | AI38: 179.69679 | AJ38: 180.91119 | AK38: 0.009405
B40: Light Truck Stock 1/
B41: Conventional Light Trucks
A42: TSK000:ga_GasolineICEVe | B42: Gasoline ICE Vehicles | C42: 105.13951 | D42: 105.25349 | E42: 105.41277 | F42: 105.55881 | G42: 105.75748 | H42: 105.86691 | I42: 106.05436 | J42: 106.25108 | K42: 106.37717 | L42: 106.48899 | M42: 106.44029 | N42: 106.24216 | O42: 105.84392 | P42: 105.32433 | Q42: 104.76894 | R42: 104.12988 | S42: 103.45435 | T42: 102.71626 | U42: 101.89417 | V42: 100.99657 | W42: 100.06853 | X42: 99.134407 | Y42: 98.203331 | Z42: 97.292336 | AA42: 96.440727 | AB42: 95.633842 | AC42: 94.880959 | AD42: 94.20182 | AE42: 93.576584 | AF42: 93.036606 | AG42: 92.53817 | AH42: 92.052879 | AI42: 91.603561 | AJ42: 91.180695 | AK42: -0.004475
A43: TSK000:ga_TDIDieselICE | B43: TDI Diesel ICE | C43: 0.429247 | D43: 0.494202 | E43: 0.61249 | F43: 0.777353 | G43: 0.943354 | H43: 1.108745 | I43: 1.274453 | J43: 1.436772 | K43: 1.594936 | L43: 1.745153 | M43: 1.879648 | N43: 2.000192 | O43: 2.104411 | P43: 2.194759 | Q43: 2.274534 | R43: 2.339217 | S43: 2.389884 | T43: 2.42916 | U43: 2.456599 | V43: 2.473171 | W43: 2.482533 | X43: 2.484463 | Y43: 2.479049 | Z43: 2.467787 | AA43: 2.452773 | AB43: 2.433501 | AC43: 2.411256 | AD43: 2.388016 | AE43: 2.363396 | AF43: 2.340392 | AG43: 2.318142 | AH43: 2.295082 | AI43: 2.271864 | AJ43: 2.248193 | AK43: 0.04848
A44: TSK000:ga_TotalConventi | B44: Total Conventional Light Trucks | C44: 105.56876 | D44: 105.7477 | E44: 106.02526 | F44: 106.33616 | G44: 106.70083 | H44: 106.97566 | I44: 107.32881 | J44: 107.68786 | K44: 107.97211 | L44: 108.23415 | M44: 108.31994 | N44: 108.24236 | O44: 107.94833 | P44: 107.51909 | Q44: 107.04347 | R44: 106.4691 | S44: 105.84424 | T44: 105.14542 | U44: 104.35077 | V44: 103.46974 | W44: 102.55106 | X44: 101.61887 | Y44: 100.68238 | Z44: 99.760124 | AA44: 98.893501 | AB44: 98.067345 | AC44: 97.292213 | AD44: 96.589836 | AE44: 95.93998 | AF44: 95.376999 | AG44: 94.856316 | AH44: 94.347961 | AI44: 93.875427 | AJ44: 93.428886 | AK44: -0.003863
B46: Alternative-Fuel Light Trucks
A47: TSK000:ha_Ethanol-FlexF | B47: Ethanol-Flex Fuel ICE | C47: 14.63013 | D47: 14.801981 | E47: 14.933042 | F47: 15.002501 | G47: 15.005728 | H47: 14.935081 | I47: 14.811186 | J47: 14.627807 | K47: 14.400931 | L47: 14.151474 | M47: 13.899592 | N47: 13.675066 | O47: 13.478799 | P47: 13.334288 | Q47: 13.2085 | R47: 13.089256 | S47: 12.990664 | T47: 12.925666 | U47: 12.876668 | V47: 12.851568 | W47: 12.851306 | X47: 12.860449 | Y47: 12.872561 | Z47: 12.882545 | AA47: 12.869473 | AB47: 12.829853 | AC47: 12.755886 | AD47: 12.661153 | AE47: 12.546265 | AF47: 12.388064 | AG47: 12.208497 | AH47: 12.017945 | AI47: 11.825339 | AJ47: 11.632048 | AK47: -0.007503
A48: TSK000:ha_100mileEV | B48: 100 Mile Electric Vehicle | C48: 0.004057 | D48: 0.009334 | E48: 0.031371 | F48: 0.061464 | G48: 0.10489 | H48: 0.161669 | I48: 0.219542 | J48: 0.282775 | K48: 0.350063 | L48: 0.416434 | M48: 0.481525 | N48: 0.542539 | O48: 0.602825 | P48: 0.661339 | Q48: 0.718898 | R48: 0.770852 | S48: 0.821481 | T48: 0.871826 | U48: 0.922183 | V48: 0.973333 | W48: 1.024417 | X48: 1.077613 | Y48: 1.133643 | Z48: 1.193458 | AA48: 1.256843 | AB48: 1.324353 | AC48: 1.396715 | AD48: 1.475077 | AE48: 1.559884 | AF48: 1.652368 | AG48: 1.753064 | AH48: 1.863072 | AI48: 1.98331 | AJ48: 2.114828 | AK48: 0.184676
A49: TSK000:ha_ElectricVehic | B49: 200 Mile Electric Vehicle | C49: 0.002434 | D49: 0.005456 | E49: 0.011627 | F49: 0.021976 | G49: 0.040388 | H49: 0.067036 | I49: 0.094706 | J49: 0.125752 | K49: 0.159603 | L49: 0.193028 | M49: 0.225858 | N49: 0.25657 | O49: 0.286841 | P49: 0.316105 | Q49: 0.344484 | R49: 0.369321 | S49: 0.392724 | T49: 0.414984 | U49: 0.435888 | V49: 0.455562 | W49: 0.473378 | X49: 0.490042 | Y49: 0.505681 | Z49: 0.520434 | AA49: 0.534049 | AB49: 0.546629 | AC49: 0.558308 | AD49: 0.56926 | AE49: 0.579469 | AF49: 0.589008 | AG49: 0.598045 | AH49: 0.606768 | AI49: 0.615205 | AJ49: 0.623517 | AK49: 0.159608
A50: TSK000:ja_FuelCellGasol | B50: 300 Mile Electric Vehicle | C50: 0.001352 | D50: 0.003896 | E50: 0.009249 | F50: 0.018109 | G50: 0.033702 | H50: 0.056246 | I50: 0.079689 | J50: 0.106024 | K50: 0.134805 | L50: 0.163316 | M50: 0.19142 | N50: 0.217875 | O50: 0.244055 | P50: 0.2695 | Q50: 0.294302 | R50: 0.3163 | S50: 0.337132 | T50: 0.357021 | U50: 0.375756 | V50: 0.393411 | W50: 0.409473 | X50: 0.424476 | Y50: 0.4385 | Z50: 0.451641 | AA50: 0.4637 | AB50: 0.474739 | AC50: 0.48487 | AD50: 0.494231 | AE50: 0.50279 | AF50: 0.510604 | AG50: 0.517805 | AH50: 0.524536 | AI50: 0.530819 | AJ50: 0.536774 | AK50: 0.166408
A51: TSK000:ha_Plug-inGasoli | B51: Plug-in 10 Gasoline Hybrid | C51: 0.025121 | D51: 0.049594 | E51: 0.082252 | F51: 0.119889 | G51: 0.17269 | H51: 0.232925 | I51: 0.296285 | J51: 0.362306 | K51: 0.432146 | L51: 0.500502 | M51: 0.566867 | N51: 0.629824 | O51: 0.690987 | P51: 0.750032 | Q51: 0.806795 | R51: 0.861263 | S51: 0.9135 | T51: 0.963907 | U51: 1.012438 | V51: 1.059738 | W51: 1.106577 | X51: 1.151102 | Y51: 1.195494 | Z51: 1.240289 | AA51: 1.285596 | AB51: 1.331576 | AC51: 1.378832 | AD51: 1.428152 | AE51: 1.479411 | AF51: 1.533245 | AG51: 1.590075 | AH51: 1.650259 | AI51: 1.714203 | AJ51: 1.782442 | AK51: 0.118438
A52: TSK000:ha_Plug-in40Hybd | B52: Plug-in 40 Gasoline Hybrid | C52: 0.007578 | D52: 0.022682 | E52: 0.042734 | F52: 0.066282 | G52: 0.09864 | H52: 0.135015 | I52: 0.172974 | J52: 0.212365 | K52: 0.25395 | L52: 0.294536 | M52: 0.333853 | N52: 0.370999 | O52: 0.406912 | P52: 0.441305 | Q52: 0.473907 | R52: 0.504603 | S52: 0.533447 | T52: 0.560693 | U52: 0.586273 | V52: 0.61053 | W52: 0.633866 | X52: 0.655196 | Y52: 0.675623 | Z52: 0.695525 | AA52: 0.714875 | AB52: 0.733798 | AC52: 0.752582 | AD52: 0.771576 | AE52: 0.790698 | AF52: 0.810149 | AG52: 0.830216 | AH52: 0.851125 | AI52: 0.872993 | AJ52: 0.896106 | AK52: 0.12175
A53: TSK000:ha_Electric-Dies | B53: Electric-Diesel Hybrid | C53: 0 | D53: 0 | E53: 0 | F53: 0 | G53: 0 | H53: 0 | I53: 0 | J53: 0 | K53: 0 | L53: 1.3e-05 | M53: 3e-05 | N53: 5.1e-05 | O53: 7.8e-05 | P53: 0.00012 | Q53: 0.000178 | R53: 0.000248 | S53: 0.000331 | T53: 0.000429 | U53: 0.000542 | V53: 0.000672 | W53: 0.000821 | X53: 0.000987 | Y53: 0.001171 | Z53: 0.00137 | AA53: 0.001583 | AB53: 0.001805 | AC53: 0.002034 | AD53: 0.002268 | AE53: 0.002503 | AF53: 0.002738 | AG53: 0.00297 | AH53: 0.003194 | AI53: 0.003412 | AJ53: 0.003621 | AK53: - -
A54: TSK000:ha_Electric-Gaso | B54: Electric-Gasoline Hybrid | C54: 0.506487 | D54: 0.539762 | E54: 0.572327 | F54: 0.606526 | G54: 0.640358 | H54: 0.674769 | I54: 0.712139 | J54: 0.752646 | K54: 0.792561 | L54: 0.834705 | M54: 0.876724 | N54: 0.919064 | O54: 0.962289 | P54: 1.005662 | Q54: 1.052056 | R54: 1.100582 | S54: 1.151416 | T54: 1.204037 | U54: 1.257612 | V54: 1.311985 | W54: 1.367049 | X54: 1.423124 | Y54: 1.480276 | Z54: 1.538538 | AA54: 1.598278 | AB54: 1.659007 | AC54: 1.721175 | AD54: 1.785705 | AE54: 1.85247 | AF54: 1.922612 | AG54: 1.995738 | AH54: 2.07186 | AI54: 2.152038 | AJ54: 2.23657 | AK54: 0.045426
A55: TSK000:ha_CompressedNat | B55: Natural Gas ICE | C55: 0.025414 | D55: 0.020526 | E55: 0.015344 | F55: 0.013883 | G55: 0.013241 | H55: 0.012693 | I55: 0.012275 | J55: 0.011974 | K55: 0.011714 | L55: 0.011549 | M55: 0.011433 | N55: 0.011358 | O55: 0.011244 | P55: 0.011219 | Q55: 0.011226 | R55: 0.011243 | S55: 0.011265 | T55: 0.01134 | U55: 0.0114 | V55: 0.011462 | W55: 0.01152 | X55: 0.011574 | Y55: 0.011616 | Z55: 0.011641 | AA55: 0.011698 | AB55: 0.011717 | AC55: 0.011769 | AD55: 0.011818 | AE55: 0.011861 | AF55: 0.011902 | AG55: 0.011938 | AH55: 0.011968 | AI55: 0.011996 | AJ55: 0.012023 | AK55: -0.016576
A56: TSK000:ia_CompressedNat | B56: Natural Gas Bi-fuel | C56: 0.037657 | D56: 0.037763 | E56: 0.037749 | F56: 0.037562 | G56: 0.037274 | H56: 0.036737 | I56: 0.03616 | J56: 0.035561 | K56: 0.034924 | L56: 0.034356 | M56: 0.033773 | N56: 0.033226 | O56: 0.032631 | P56: 0.032126 | Q56: 0.0317 | R56: 0.031297 | S56: 0.030935 | T56: 0.030711 | U56: 0.030468 | V56: 0.030249 | W56: 0.030057 | X56: 0.029884 | Y56: 0.029693 | Z56: 0.029485 | AA56: 0.029313 | AB56: 0.029135 | AC56: 0.028972 | AD56: 0.028844 | AE56: 0.028737 | AF56: 0.028656 | AG56: 0.028588 | AH56: 0.028518 | AI56: 0.028472 | AJ56: 0.028441 | AK56: -0.00882
A57: TSK000:ia_LiquefiedPetr | B57: Propane ICE | C57: 0.016439 | D57: 0.016369 | E57: 0.016401 | F57: 0.016532 | G57: 0.016698 | H57: 0.016816 | I57: 0.016973 | J57: 0.017155 | K57: 0.017334 | L57: 0.017568 | M57: 0.017809 | N57: 0.018048 | O57: 0.018274 | P57: 0.018489 | Q57: 0.018709 | R57: 0.018916 | S57: 0.019118 | T57: 0.019393 | U57: 0.01966 | V57: 0.019943 | W57: 0.02023 | X57: 0.020524 | Y57: 0.020816 | Z57: 0.021112 | AA57: 0.02146 | AB57: 0.021848 | AC57: 0.022256 | AD57: 0.022689 | AE57: 0.023143 | AF57: 0.023629 | AG57: 0.024139 | AH57: 0.024673 | AI57: 0.025235 | AJ57: 0.025822 | AK57: 0.014347
A58: TSK000:ja_LiquefiedPetr | B58: Propane Bi-fuel | C58: 0.075659 | D58: 0.070139 | E58: 0.065111 | F58: 0.060407 | G58: 0.055988 | H58: 0.051641 | I58: 0.047573 | J58: 0.043779 | K58: 0.040234 | L58: 0.037015 | M58: 0.034067 | N58: 0.031424 | O58: 0.029003 | P58: 0.026832 | Q58: 0.024958 | R58: 0.023343 | S58: 0.021951 | T58: 0.021011 | U58: 0.020158 | V58: 0.01949 | W58: 0.018944 | X58: 0.018491 | Y58: 0.018052 | Z58: 0.017574 | AA58: 0.017481 | AB58: 0.017372 | AC58: 0.017269 | AD58: 0.017187 | AE58: 0.017118 | AF58: 0.017064 | AG58: 0.017018 | AH58: 0.01697 | AI58: 0.016936 | AJ58: 0.016912 | AK58: -0.043478
A59: TSK000:ja_FuelCellMetha | B59: Fuel Cell Methanol | C59: 0 | D59: 0 | E59: 0 | F59: 0 | G59: 0 | H59: 0 | I59: 0 | J59: 0 | K59: 0 | L59: 0 | M59: 0 | N59: 0 | O59: 0 | P59: 0 | Q59: 0 | R59: 0 | S59: 0 | T59: 0 | U59: 0 | V59: 0 | W59: 0 | X59: 0 | Y59: 0 | Z59: 0 | AA59: 0 | AB59: 0 | AC59: 0 | AD59: 0 | AE59: 0 | AF59: 0 | AG59: 0 | AH59: 0 | AI59: 0 | AJ59: 0 | AK59: - -
A60: TSK000:ja_FuelCellHydro | B60: Fuel Cell Hydrogen | C60: 0.001352 | D60: 0.003896 | E60: 0.00882 | F60: 0.017229 | G60: 0.032227 | H60: 0.054024 | I60: 0.076592 | J60: 0.101827 | K60: 0.129074 | L60: 0.155678 | M60: 0.181485 | N60: 0.205033 | O60: 0.227814 | P60: 0.249241 | Q60: 0.26943 | R60: 0.285988 | S60: 0.300819 | T60: 0.314237 | U60: 0.326155 | V60: 0.336766 | W60: 0.345483 | X60: 0.353093 | Y60: 0.359811 | Z60: 0.365811 | AA60: 0.370954 | AB60: 0.375428 | AC60: 0.37937 | AD60: 0.382905 | AE60: 0.386052 | AF60: 0.388876 | AG60: 0.391553 | AH60: 0.394253 | AI60: 0.396936 | AJ60: 0.39972 | AK60: 0.155712
A61: TSK000:ja_TotalAlternat | B61: Total Alternative Light Trucks | C61: 15.333682 | D61: 15.5814 | E61: 15.826027 | F61: 16.04236 | G61: 16.251823 | H61: 16.434652 | I61: 16.576094 | J61: 16.679972 | K61: 16.757339 | L61: 16.810177 | M61: 16.854437 | N61: 16.911076 | O61: 16.991753 | P61: 17.116259 | Q61: 17.255146 | R61: 17.383211 | S61: 17.524782 | T61: 17.695255 | U61: 17.875202 | V61: 18.074707 | W61: 18.293119 | X61: 18.516556 | Y61: 18.742935 | Z61: 18.969421 | AA61: 19.175301 | AB61: 19.357256 | AC61: 19.510038 | AD61: 19.650866 | AE61: 19.780399 | AF61: 19.878918 | AG61: 19.969648 | AH61: 20.065142 | AI61: 20.176891 | AJ61: 20.308823 | AK61: 0.008315
A63: TSK000:ka_TotalNewTruck | B63: Total Light Truck Stock | C63: 120.90243 | D63: 121.32909 | E63: 121.85129 | F63: 122.37852 | G63: 122.95265 | H63: 123.41031 | I63: 123.90491 | J63: 124.36783 | K63: 124.72945 | L63: 125.04433 | M63: 125.17438 | N63: 125.15343 | O63: 124.94009 | P63: 124.63535 | Q63: 124.29861 | R63: 123.85231 | S63: 123.36902 | T63: 122.84067 | U63: 122.22597 | V63: 121.54445 | W63: 120.84418 | X63: 120.13543 | Y63: 119.42532 | Z63: 118.72955 | AA63: 118.0688 | AB63: 117.4246 | AC63: 116.80225 | AD63: 116.2407 | AE63: 115.72038 | AF63: 115.25592 | AG63: 114.82597 | AH63: 114.4131 | AI63: 114.05232 | AJ63: 113.73771 | AK63: -0.002017
A65: TSK000:la_TotalVehicleS | B65: Total Stock | C65: 253.71786 | D65: 255.41043 | E65: 257.11804 | F65: 258.78601 | G65: 260.42566 | H65: 261.77234 | I65: 263.26468 | J65: 264.83347 | K65: 266.37439 | L65: 267.86771 | M65: 269.18329 | N65: 270.31067 | O65: 271.21933 | P65: 272.08069 | Q65: 273.05322 | R65: 273.97082 | S65: 274.93048 | T65: 275.95358 | U65: 276.95935 | V65: 277.96014 | W65: 279.02985 | X65: 280.19305 | Y65: 281.3996 | Z65: 282.66415 | AA65: 283.97443 | AB65: 285.28391 | AC65: 286.5704 | AD65: 287.89713 | AE65: 289.21472 | AF65: 290.50369 | AG65: 291.69519 | AH65: 292.75586 | AI65: 293.74912 | AJ65: 294.64889 | AK65: 0.004476
B67: 1/ Includes personal and fleet vehicles.
B68: ICE = Internal combustion engine.
B69: - - = Not applicable.
B70: Note: Totals may not equal sum of components due to independent rounding.
B71: Sources: 2017 values derived using: Energy Information Administration (EIA), Describing Current and Potential
B72: Markets for Alternative-Fuel Vehicles, 1996; EIA, Alternatives to Traditional Transportation Fuels 2009 (Part II - User and Fuel Data); Federal Highway
B73: Administration, Highway Statistics 2016; Oak Ridge National Laboratory, Transportation Energy Data Book: Edition 36;
B74: IHS Markit Polk, National Vehicle Population Profile, various years; IHS Markit Polk, Trucking Industry Profile, various years; and
B75: EIA, AEO2019 National Energy Modeling System run ref2019.d111618a. 2018 and projections: EIA, AEO2019 National Energy
B76: Modeling System run ref2019.d111618a.

Sheet AEO 46
A1: ref2019.d111618a | B1: 2017 | C1: 2018 | D1: 2019 | E1: 2020 | F1: 2021 | G1: 2022 | H1: 2023 | I1: 2024 | J1: 2025 | K1: 2026 | L1: 2027 | M1: 2028 | N1: 2029 | O1: 2030 | P1: 2031 | Q1: 2032 | R1: 2033 | S1: 2034 | T1: 2035 | U1: 2036 | V1: 2037 | W1: 2038 | X1: 2039 | Y1: 2040 | Z1: 2041 | AA1: 2042 | AB1: 2043 | AC1: 2044 | AD1: 2045 | AE1: 2046 | AF1: 2047 | AG1: 2048 | AH1: 2049 | AI1: 2050
B3: Report | C3: Annual Energy Outlook 2019
B4: Scenario | C4: ref2019 | F4: Reference case
B5: Datekey | C5: d111618a
B6: Release Date | D6: January 2019
A10: 46. Transportation Fleet Car and Truck Stock by Type and Technology
A11: (thousands)
AJ12: 2018-
A13: Technology Type | B13: 2017 | C13: 2018 | D13: 2019 | E13: 2020 | F13: 2021 | G13: 2022 | H13: 2023 | I13: 2024 | J13: 2025 | K13: 2026 | L13: 2027 | M13: 2028 | N13: 2029 | O13: 2030 | P13: 2031 | Q13: 2032 | R13: 2033 | S13: 2034 | T13: 2035 | U13: 2036 | V13: 2037 | W13: 2038 | X13: 2039 | Y13: 2040 | Z13: 2041 | AA13: 2042 | AB13: 2043 | AC13: 2044 | AD13: 2045 | AE13: 2046 | AF13: 2047 | AG13: 2048 | AH13: 2049 | AI13: 2050 | AJ13: 2050
A15: Car Stock 1/
A16: Conventional Cars
A17: Gasoline ICE Vehicles | B17: 7371.9702 | C17: 7080.1284 | D17: 6829.1465 | E17: 6601.2847 | F17: 6353.937 | G17: 6067.2627 | H17: 5844.3706 | I17: 5649.4609 | J17: 5455.2925 | K17: 5284.8516 | L17: 5145.4556 | M17: 5037.1123 | N17: 4944.9087 | O17: 4872.5464 | P17: 4831.9937 | Q17: 4803.5083 | R17: 4789.1768 | S17: 4794.8574 | T17: 4802.4829 | U17: 4807.3721 | V17: 4816.5205 | W17: 4831.4565 | X17: 4845.2734 | Y17: 4861.3164 | Z17: 4875.7949 | AA17: 4906.9985 | AB17: 4938.2998 | AC17: 4975.7329 | AD17: 5014.7568 | AE17: 5050.2017 | AF17: 5075.9468 | AG17: 5092.0063 | AH17: 5108.1768 | AI17: 5119.502 | AJ17: -0.010081
A18: TDI Diesel ICE | B18: 36.27449 | C18: 34.634598 | D18: 33.361244 | E18: 32.168747 | F18: 31.07633 | G18: 30.188026 | H18: 29.550236 | I18: 29.274616 | J18: 29.323959 | K18: 29.752871 | L18: 30.607014 | M18: 32.005032 | N18: 33.928902 | O18: 36.285336 | P18: 39.100269 | Q18: 42.410435 | R18: 45.892429 | S18: 49.415874 | T18: 52.90453 | U18: 56.316933 | V18: 59.591991 | W18: 62.733749 | X18: 65.506279 | Y18: 68.342262 | Z18: 71.43277 | AA18: 74.275612 | AB18: 76.890846 | AC18: 79.383583 | AD18: 81.697388 | AE18: 83.770638 | AF18: 85.548279 | AG18: 87.061745 | AH18: 88.426216 | AI18: 89.601013 | AJ18: 0.030149
A19: Total Conventional Cars | B19: 7408.2446 | C19: 7114.7632 | D19: 6862.5078 | E19: 6633.4536 | F19: 6385.0132 | G19: 6097.4507 | H19: 5873.9209 | I19: 5678.7354 | J19: 5484.6162 | K19: 5314.6045 | L19: 5176.0625 | M19: 5069.1172 | N19: 4978.8374 | O19: 4908.8315 | P19: 4871.0938 | Q19: 4845.9189 | R19: 4835.0693 | S19: 4844.2734 | T19: 4855.3872 | U19: 4863.689 | V19: 4876.1123 | W19: 4894.1904 | X19: 4910.7798 | Y19: 4929.6587 | Z19: 4947.2275 | AA19: 4981.2739 | AB19: 5015.1904 | AC19: 5055.1167 | AD19: 5096.4541 | AE19: 5133.9722 | AF19: 5161.4951 | AG19: 5179.0679 | AH19: 5196.603 | AI19: 5209.103 | AJ19: -0.009695
A21: Alternative-Fuel Cars
A22: Ethanol-Flex Fuel ICE | B22: 511.11575 | C22: 478.4639 | D22: 449.45297 | E22: 424.69723 | F22: 402.7432 | G22: 382.87866 | H22: 366.9158 | I22: 353.37149 | J22: 339.53934 | K22: 326.47366 | L22: 314.8378 | M22: 304.31476 | N22: 295.27283 | O22: 287.59778 | P22: 281.00632 | Q22: 275.71219 | R22: 268.42645 | S22: 264.54257 | T22: 261.50461 | U22: 257.21893 | V22: 255.83353 | W22: 256.27121 | X22: 256.02445 | Y22: 256.04959 | Z22: 257.86188 | AA22: 259.80475 | AB22: 261.60953 | AC22: 263.68195 | AD22: 265.73526 | AE22: 267.46735 | AF22: 268.6315 | AG22: 269.34265 | AH22: 270.06937 | AI22: 270.60083 | AJ22: -0.017653
A23: 100 Mile Electric Vehicle | B23: 16.729153 | C23: 20.657087 | D23: 27.360132 | E23: 38.507462 | F23: 58.855564 | G23: 86.71801 | H23: 107.62179 | I23: 127.79937 | J23: 147.58066 | K23: 162.45522 | L23: 174.36815 | M23: 182.75604 | N23: 191.37201 | O23: 199.05635 | P23: 205.8624 | Q23: 207.29237 | R23: 207.92168 | S23: 208.54768 | T23: 208.94153 | U23: 209.33638 | V23: 208.28656 | W23: 207.10809 | X23: 206.08806 | Y23: 205.28021 | Z23: 204.17252 | AA23: 202.87694 | AB23: 201.63252 | AC23: 200.49289 | AD23: 199.1879 | AE23: 197.60823 | AF23: 195.93048 | AG23: 194.64279 | AH23: 193.49214 | AI23: 192.65204 | AJ23: 0.072268
A24: 200 Mile Electric Vehicle | B24: 17.607058 | C24: 20.49828 | D24: 25.010633 | E24: 31.898012 | F24: 44.304337 | G24: 61.18219 | H24: 74.254997 | I24: 87.112717 | J24: 100.44286 | K24: 111.06916 | L24: 120.25794 | M24: 127.65694 | N24: 135.4994 | O24: 143.17464 | P24: 150.68356 | Q24: 155.95601 | R24: 160.96884 | S24: 166.03836 | T24: 170.896 | U24: 175.66332 | V24: 179.67787 | W24: 183.31981 | X24: 186.70941 | Y24: 189.95123 | Z24: 192.71831 | AA24: 195.2159 | AB24: 197.51125 | AC24: 199.68571 | AD24: 201.55768 | AE24: 203.00758 | AF24: 204.09113 | AG24: 205.10698 | AH24: 206.00127 | AI24: 206.85379 | AJ24: 0.074913
A25: 300 Mile Electric Vehicle | B25: 2.020338 | C25: 4.600814 | D25: 8.512125 | E25: 14.281381 | F25: 24.641897 | G25: 38.877815 | H25: 50.024136 | I25: 61.108116 | J25: 72.797729 | K25: 82.364006 | L25: 90.874657 | M25: 98.077515 | N25: 105.81053 | O25: 113.55384 | P25: 121.27568 | Q25: 127.24423 | R25: 133.0864 | S25: 139.00803 | T25: 144.75154 | U25: 150.38074 | V25: 155.38297 | W25: 160.11112 | X25: 164.5421 | Y25: 168.77954 | Z25: 172.54979 | AA25: 175.83978 | AB25: 178.83517 | AC25: 181.65036 | AD25: 184.12148 | AE25: 186.15418 | AF25: 187.78633 | AG25: 189.27425 | AH25: 190.5903 | AI25: 191.79889 | AJ25: 0.123635
A26: Plug-in 10 Gasoline Hybrid | B26: 27.493435 | C26: 47.756512 | D26: 61.921108 | E26: 73.892128 | F26: 98.197983 | G26: 124.74712 | H26: 148.60919 | I26: 170.45541 | J26: 192.13013 | K26: 208.81935 | L26: 222.19539 | M26: 232.89069 | N26: 243.50195 | O26: 253.57402 | P26: 262.39972 | Q26: 270.02524 | R26: 276.50989 | S26: 282.25479 | T26: 287.14035 | U26: 291.69144 | V26: 296.22598 | W26: 298.35107 | X26: 300.17789 | Y26: 302.00104 | Z26: 303.1915 | AA26: 304.06268 | AB26: 304.74264 | AC26: 305.47452 | AD26: 305.90945 | AE26: 305.80582 | AF26: 305.64023 | AG26: 305.70505 | AH26: 305.78055 | AI26: 306.11719 | AJ26: 0.059776
A27: Plug-in 40 Gasoline Hybrid | B27: 15.178844 | C27: 27.388926 | D27: 35.88583 | E27: 42.959641 | F27: 57.462017 | G27: 73.360611 | H27: 87.718491 | I27: 100.9425 | J27: 114.15194 | K27: 124.47277 | L27: 132.92837 | M27: 139.91069 | N27: 146.98042 | O27: 153.86223 | P27: 160.12592 | Q27: 165.7659 | R27: 170.79997 | S27: 175.45233 | T27: 179.62088 | U27: 183.54805 | V27: 187.45822 | W27: 190.0601 | X27: 192.47464 | Y27: 194.85782 | Z27: 196.83073 | AA27: 198.45822 | AB27: 199.88356 | AC27: 201.26941 | AD27: 202.39781 | AE27: 203.1165 | AF27: 203.7048 | AG27: 204.34178 | AH27: 204.91388 | AI27: 205.57222 | AJ27: 0.065015
A28: Electric-Diesel Hybrid | B28: 0 | C28: 0 | D28: 0 | E28: 0 | F28: 0 | G28: 0 | H28: 0 | I28: 0 | J28: 0 | K28: 0 | L28: 0 | M28: 0 | N28: 0 | O28: 0.007167 | P28: 0.015645 | Q28: 0.026059 | R28: 0.039258 | S28: 0.056256 | T28: 0.078018 | U28: 0.105416 | V28: 0.139576 | W28: 0.18164 | X28: 0.232373 | Y28: 0.292635 | Z28: 0.36273 | AA28: 0.442267 | AB28: 0.530564 | AC28: 0.626972 | AD28: 0.729612 | AE28: 0.836213 | AF28: 0.944087 | AG28: 1.051181 | AH28: 1.156428 | AI28: 1.257915 | AJ28: - -
A29: Electric-Gasoline Hybrid | B29: 285.89841 | C29: 287.20181 | D29: 288.25821 | E29: 292.28683 | F29: 296.58084 | G29: 300.03003 | H29: 304.36774 | I29: 309.33283 | J29: 314.59247 | K29: 320.09226 | L29: 326.94891 | M29: 335.58908 | N29: 346.04965 | O29: 358.24457 | P29: 373.54474 | Q29: 389.16043 | R29: 405.82108 | S29: 423.89911 | T29: 441.21945 | U29: 458.556 | V29: 475.06921 | W29: 490.70993 | X29: 505.6023 | Y29: 519.73822 | Z29: 533.2926 | AA29: 546.32794 | AB29: 558.32428 | AC29: 569.76526 | AD29: 580.37707 | AE29: 589.86658 | AF29: 597.92194 | AG29: 604.65308 | AH29: 610.65796 | AI29: 615.71661 | AJ29: 0.024118
A30: Natural Gas ICE | B30: 24.762091 | C30: 19.656492 | D30: 14.278668 | E30: 12.589105 | F30: 11.704149 | G30: 10.891492 | H30: 10.134369 | I30: 9.413951 | J30: 8.7405 | K30: 8.157124 | L30: 7.639833 | M30: 7.178278 | N30: 6.781656 | O30: 6.435264 | P30: 6.155359 | Q30: 5.904707 | R30: 5.715197 | S30: 5.574745 | T30: 5.470803 | U30: 5.395168 | V30: 5.300972 | W30: 5.238197 | X30: 5.193787 | Y30: 5.166048 | Z30: 5.195061 | AA30: 5.185341 | AB30: 5.235277 | AC30: 5.285192 | AD30: 5.333377 | AE30: 5.378386 | AF30: 5.418141 | AG30: 5.451933 | AH30: 5.482228 | AI30: 5.507849 | AJ30: -0.038977
A31: Natural Gas Bi-fuel | B31: 43.051434 | C31: 41.769711 | D31: 40.663792 | E31: 39.66666 | F31: 38.835835 | G31: 38.053776 | H31: 37.38752 | I31: 36.694813 | J31: 35.9048 | K31: 35.101032 | L31: 34.315048 | M31: 33.600487 | N31: 33.026081 | O31: 32.582989 | P31: 32.328655 | Q31: 32.158268 | R31: 32.142292 | S31: 32.262882 | T31: 32.444241 | U31: 32.659702 | V31: 32.842983 | W31: 33.045158 | X31: 33.261688 | Y31: 33.490185 | Z31: 33.811455 | AA31: 34.1446 | AB31: 34.45948 | AC31: 34.771133 | AD31: 35.070194 | AE31: 35.347095 | AF31: 35.586945 | AG31: 35.786407 | AH31: 35.963493 | AI31: 36.109707 | AJ31: -0.00454
A32: Propane ICE | B32: 4.254695 | C32: 4.171724 | D32: 4.110635 | E32: 4.072934 | F32: 4.060987 | G32: 4.040604 | H32: 4.035384 | I32: 4.038661 | J32: 4.046723 | K32: 4.062395 | L32: 4.084833 | M32: 4.109815 | N32: 4.139592 | O32: 4.172641 | P32: 4.21277 | Q32: 4.253407 | R32: 4.30149 | S32: 4.357242 | T32: 4.412648 | U32: 4.466545 | V32: 4.518507 | W32: 4.568696 | X32: 4.618726 | Y32: 4.670463 | Z32: 4.686111 | AA32: 4.73194 | AB32: 4.780472 | AC32: 4.829637 | AD32: 4.87748 | AE32: 4.922688 | AF32: 4.96362 | AG32: 4.999352 | AH32: 5.031749 | AI32: 5.059905 | AJ32: 0.00605
A33: Propane Bi-fuel | B33: 8.543881 | C33: 8.445667 | D33: 8.378443 | E33: 8.354096 | F33: 8.378883 | G33: 8.387218 | H33: 8.417918 | I33: 8.458485 | J33: 8.500422 | K33: 8.548801 | L33: 8.603531 | M33: 8.66216 | N33: 8.729722 | O33: 8.803678 | P33: 8.894547 | Q33: 8.985997 | R33: 9.091739 | S33: 9.213204 | T33: 9.334698 | U33: 9.452297 | V33: 9.566059 | W33: 9.675813 | X33: 9.783573 | Y33: 9.894577 | Z33: 9.935765 | AA33: 10.03303 | AB33: 10.13458 | AC33: 10.237174 | AD33: 10.336849 | AE33: 10.430822 | AF33: 10.515491 | AG33: 10.58902 | AH33: 10.655549 | AI33: 10.713072 | AJ33: 0.007459
A34: Fuel Cell Methanol | B34: 0 | C34: 0 | D34: 0 | E34: 0 | F34: 0 | G34: 0 | H34: 0 | I34: 0 | J34: 0 | K34: 0 | L34: 0 | M34: 0 | N34: 0 | O34: 0 | P34: 0 | Q34: 0 | R34: 0 | S34: 0 | T34: 0 | U34: 0 | V34: 0 | W34: 0 | X34: 0 | Y34: 0 | Z34: 0 | AA34: 0 | AB34: 0 | AC34: 0 | AD34: 0 | AE34: 0 | AF34: 0 | AG34: 0 | AH34: 0 | AI34: 0 | AJ34: - -
A35: Fuel Cell Hydrogen | B35: 1.791733 | C35: 3.913028 | D35: 7.341292 | E35: 12.716816 | F35: 22.484205 | G35: 35.895599 | H35: 46.042435 | I35: 55.843388 | J35: 65.458496 | K35: 72.712524 | L35: 78.662712 | M35: 82.673927 | N35: 86.785347 | O35: 90.392159 | P35: 93.543633 | Q35: 94.070488 | R35: 94.196999 | S35: 94.297371 | T35: 94.282639 | U35: 94.309196 | V35: 93.646759 | W35: 92.970856 | X35: 92.361786 | Y35: 91.901337 | Z35: 91.26194 | AA35: 90.529808 | AB35: 89.833 | AC35: 89.196915 | AD35: 88.489784 | AE35: 87.662338 | AF35: 86.80146 | AG35: 86.140152 | AH35: 85.552406 | AI35: 85.122894 | AJ35: 0.101027
A36: Total Alternative Cars | B36: 958.44678 | C36: 964.52405 | D36: 971.17383 | E36: 995.92236 | F36: 1068.2499 | G36: 1165.0632 | H36: 1245.53 | I36: 1324.5719 | J36: 1403.8861 | K36: 1464.3284 | L36: 1515.7173 | M36: 1557.4203 | N36: 1603.9493 | O36: 1651.4575 | P36: 1700.0487 | Q36: 1736.5552 | R36: 1769.0215 | S36: 1805.5046 | T36: 1840.0974 | U36: 1872.7832 | V36: 1903.9492 | W36: 1931.6117 | X36: 1957.071 | Y36: 1982.0728 | Z36: 2005.8704 | AA36: 2027.6533 | AB36: 2047.5123 | AC36: 2066.967 | AD36: 2084.1238 | AE36: 2097.6038 | AF36: 2107.9363 | AG36: 2117.0847 | AH36: 2125.3472 | AI36: 2133.0828 | AJ36: 0.025113
A38: Total Car Stock | B38: 8366.6914 | C38: 8079.2871 | D38: 7833.6816 | E38: 7629.376 | F38: 7453.2632 | G38: 7262.5137 | H38: 7119.4512 | I38: 7003.3071 | J38: 6888.5024 | K38: 6778.9326 | L38: 6691.7798 | M38: 6626.5376 | N38: 6582.7866 | O38: 6560.2891 | P38: 6571.1426 | Q38: 6582.4741 | R38: 6604.0908 | S38: 6649.7783 | T38: 6695.4844 | U38: 6736.4722 | V38: 6780.0615 | W38: 6825.8022 | X38: 6867.8506 | Y38: 6911.7314 | Z38: 6953.0977 | AA38: 7008.9272 | AB38: 7062.7026 | AC38: 7122.084 | AD38: 7180.5781 | AE38: 7231.5762 | AF38: 7269.4316 | AG38: 7296.1523 | AH38: 7321.9502 | AI38: 7342.1855 | AJ38: -0.002985
A40: Light Truck Stock 1/
A41: Conventional Light Trucks
A42: Gasoline ICE Vehicles | B42: 7246.3936 | C42: 6918.1567 | D42: 6671.7886 | E42: 6446.0137 | F42: 6195.5532 | G42: 5901.5933 | H42: 5643.6831 | I42: 5403.4282 | J42: 5170.8062 | K42: 4977.8223 | L42: 4794.5034 | M42: 4631.8896 | N42: 4467.5825 | O42: 4316.231 | P42: 4183.9937 | Q42: 4067.7192 | R42: 3960.1584 | S42: 3878.3804 | T42: 3794.8823 | U42: 3716.855 | V42: 3650.8701 | W42: 3595.4575 | X42: 3539.1741 | Y42: 3482.2898 | Z42: 3430.4377 | AA42: 3392.5439 | AB42: 3359.0134 | AC42: 3333.2415 | AD42: 3312.3496 | AE42: 3296.7739 | AF42: 3283.009 | AG42: 3268.0139 | AH42: 3257.6108 | AI42: 3249.4812 | AJ42: -0.023338
A43: TDI Diesel ICE | B43: 41.382172 | C43: 42.698997 | D43: 44.364071 | E43: 46.25771 | F43: 48.453228 | G43: 50.588619 | H43: 52.864319 | I43: 55.209023 | J43: 57.750847 | K43: 60.522007 | L43: 63.331169 | M43: 66.269981 | N43: 69.269203 | O43: 72.408432 | P43: 75.742447 | Q43: 79.010193 | R43: 82.312454 | S43: 85.648613 | T43: 88.872925 | U43: 91.93029 | V43: 94.908356 | W43: 97.827019 | X43: 100.33254 | Y43: 102.56605 | Z43: 104.83514 | AA43: 106.98048 | AB43: 108.93513 | AC43: 110.80037 | AD43: 112.49923 | AE43: 114.05725 | AF43: 115.42042 | AG43: 116.55399 | AH43: 117.59268 | AI43: 118.52371 | AJ43: 0.032419
A44: Total Conventional Light Trucks | B44: 7287.7759 | C44: 6960.856 | D44: 6716.1528 | E44: 6492.2715 | F44: 6244.0063 | G44: 5952.1816 | H44: 5696.5474 | I44: 5458.6372 | J44: 5228.5571 | K44: 5038.3442 | L44: 4857.8345 | M44: 4698.1597 | N44: 4536.8516 | O44: 4388.6392 | P44: 4259.7363 | Q44: 4146.7295 | R44: 4042.4709 | S44: 3964.0291 | T44: 3883.7554 | U44: 3808.7852 | V44: 3745.7786 | W44: 3693.2844 | X44: 3639.5066 | Y44: 3584.856 | Z44: 3535.2729 | AA44: 3499.5244 | AB44: 3467.9485 | AC44: 3444.0417 | AD44: 3424.8489 | AE44: 3410.8311 | AF44: 3398.4294 | AG44: 3384.5679 | AH44: 3375.2036 | AI44: 3368.0049 | AJ44: -0.022431
A46: Alternative-Fuel Light Trucks
A47: Ethanol-Flex Fuel ICE | B47: 1808.5121 | C47: 1728.7035 | D47: 1672.0482 | E47: 1623.0906 | F47: 1576.2102 | G47: 1524.9993 | H47: 1474.2567 | I47: 1422.1147 | J47: 1367.8939 | K47: 1316.5366 | L47: 1259.8173 | M47: 1202.9429 | N47: 1148.3228 | O47: 1097.4196 | P47: 1051.811 | Q47: 1005.3876 | R47: 965.19415 | S47: 932.59174 | T47: 902.03296 | U47: 873.16699 | V47: 850.17322 | W47: 827.33911 | X47: 809.15546 | Y47: 800.29822 | Z47: 793.341 | AA47: 787.93701 | AB47: 783.10162 | AC47: 779.93683 | AD47: 777.37531 | AE47: 775.46582 | AF47: 773.56653 | AG47: 771.20447 | AH47: 769.79889 | AI47: 769.04468 | AJ47: -0.024994
A48: 100 Mile Electric Vehicle | B48: 4.057117 | C48: 7.67889 | D48: 14.070018 | E48: 24.976068 | F48: 44.970486 | G48: 72.269539 | H48: 92.483612 | I48: 111.88062 | J48: 130.70831 | K48: 144.36259 | L48: 155.05455 | M48: 161.60667 | N48: 168.39708 | O48: 174.41203 | P48: 179.93607 | Q48: 180.46211 | R48: 180.88585 | S48: 181.65399 | T48: 182.36263 | U48: 183.13924 | V48: 182.33774 | W48: 181.30347 | X48: 180.21935 | Y48: 179.28389 | Z48: 177.8891 | AA48: 176.22923 | AB48: 174.59746 | AC48: 173.06953 | AD48: 171.41809 | AE48: 169.65439 | AF48: 167.91901 | AG48: 166.46619 | AH48: 165.19115 | AI48: 164.29925 | AJ48: 0.100457
A49: 200 Mile Electric Vehicle | B49: 2.43427 | C49: 4.471943 | D49: 8.314238 | E49: 14.72496 | F49: 26.464836 | G49: 42.443066 | H49: 54.360237 | I49: 65.881615 | J49: 77.334953 | K49: 85.901169 | L49: 92.813156 | M49: 97.58902 | N49: 102.62863 | O49: 107.43253 | P49: 112.12183 | Q49: 114.1814 | R49: 116.3084 | S49: 118.71592 | T49: 121.10313 | U49: 123.50376 | V49: 125.07166 | W49: 126.44485 | X49: 127.67958 | Y49: 128.89487 | Z49: 129.75551 | AA49: 130.3186 | AB49: 130.78622 | AC49: 131.25943 | AD49: 131.56918 | AE49: 131.72771 | AF49: 131.79062 | AG49: 131.88904 | AH49: 132.02506 | AI49: 132.30925 | AJ49: 0.111659
A50: 300 Mile Electric Vehicle | B50: 1.352372 | C50: 3.34874 | D50: 7.074019 | E50: 12.658982 | F50: 22.601164 | G50: 36.133232 | H50: 46.284462 | I50: 56.144249 | J50: 66.014328 | K50: 73.503098 | L50: 79.635849 | M50: 84.048904 | N50: 88.723389 | O50: 93.254089 | P50: 97.724304 | Q50: 100.10778 | R50: 102.5341 | S50: 105.16822 | T50: 107.73817 | U50: 110.26399 | V50: 112.07724 | W50: 113.66599 | X50: 115.07415 | Y50: 116.41019 | Z50: 117.40196 | AA50: 118.09177 | AB50: 118.66124 | AC50: 119.20481 | AD50: 119.58237 | AE50: 119.81186 | AF50: 119.93391 | AG50: 120.05804 | AH50: 120.20051 | AI50: 120.45497 | AJ50: 0.118467
A51: Plug-in 10 Gasoline Hybrid | B51: 14.059927 | C51: 33.867481 | D51: 47.501087 | E51: 58.779976 | F51: 82.123283 | G51: 107.60622 | H51: 130.12676 | I51: 150.64883 | J51: 170.97136 | K51: 186.24289 | L51: 198.08401 | M51: 207.17303 | N51: 216.18996 | O51: 224.81606 | P51: 232.44833 | Q51: 239.21669 | R51: 245.17603 | S51: 250.57281 | T51: 255.19775 | U51: 259.50043 | V51: 263.80853 | W51: 265.55875 | X51: 266.98157 | Y51: 268.37714 | Z51: 269.27859 | AA51: 269.76038 | AB51: 270.16495 | AC51: 270.63492 | AD51: 270.81329 | AE51: 270.60458 | AF51: 270.33124 | AG51: 270.08505 | AH51: 269.83285 | AI51: 269.88742 | AJ51: 0.067011
A52: Plug-in 40 Gasoline Hybrid | B52: 6.644185 | C52: 18.527199 | D52: 26.711494 | E52: 33.417397 | F52: 47.392609 | G52: 62.689999 | H52: 76.27478 | I52: 88.734482 | J52: 101.15466 | K52: 110.63201 | L52: 118.13947 | M52: 124.08516 | N52: 130.06711 | O52: 135.8921 | P52: 141.19124 | Q52: 146.01523 | R52: 150.39111 | S52: 154.44998 | T52: 158.04373 | U52: 161.42624 | V52: 164.79024 | W52: 166.70668 | X52: 168.36157 | Y52: 169.93559 | Z52: 171.19951 | AA52: 172.1079 | AB52: 172.90096 | AC52: 173.68683 | AD52: 174.24731 | AE52: 174.53111 | AF52: 174.72813 | AG52: 174.89192 | AH52: 175.0172 | AI52: 175.29256 | AJ52: 0.07275
A53: Electric-Diesel Hybrid | B53: 0 | C53: 0 | D53: 0 | E53: 0 | F53: 0 | G53: 0 | H53: 0 | I53: 0 | J53: 0 | K53: 0.012101 | L53: 0.025291 | M53: 0.040602 | N53: 0.058852 | O53: 0.081396 | P53: 0.109568 | Q53: 0.144001 | R53: 0.186379 | S53: 0.237917 | T53: 0.299146 | U53: 0.370459 | V53: 0.452593 | W53: 0.544832 | X53: 0.64543 | Y53: 0.752954 | Z53: 0.865568 | AA53: 0.979833 | AB53: 1.094407 | AC53: 1.209086 | AD53: 1.321344 | AE53: 1.430449 | AF53: 1.534381 | AG53: 1.631786 | AH53: 1.724057 | AI53: 1.810606 | AJ53: - -
A54: Electric-Gasoline Hybrid | B54: 57.52943 | C54: 53.278786 | D54: 48.866955 | E54: 48.736362 | F54: 49.752323 | G54: 50.991116 | H54: 52.687664 | I54: 54.92543 | J54: 57.783882 | K54: 61.491402 | L54: 65.798157 | M54: 70.799385 | N54: 76.350189 | O54: 82.484444 | P54: 88.848526 | Q54: 95.576172 | R54: 101.97135 | S54: 108.70105 | T54: 115.2231 | U54: 121.56199 | V54: 127.61434 | W54: 133.27622 | X54: 138.44199 | Y54: 143.11162 | Z54: 147.26765 | AA54: 150.86446 | AB54: 154.08945 | AC54: 157.1566 | AD54: 159.92186 | AE54: 162.44159 | AF54: 164.61801 | AG54: 166.39664 | AH54: 168.04581 | AI54: 169.53815 | AJ54: 0.036835
A55: Natural Gas ICE | B55: 24.724743 | C55: 19.859348 | D55: 14.680317 | E55: 13.18959 | F55: 12.465335 | G55: 11.756211 | H55: 11.083871 | I55: 10.455625 | J55: 9.843993 | K55: 9.305326 | L55: 8.820227 | M55: 8.390126 | N55: 7.940099 | O55: 7.595423 | P55: 7.292424 | Q55: 7.020234 | R55: 6.775842 | S55: 6.600845 | T55: 6.433057 | U55: 6.29117 | V55: 6.169653 | W55: 6.065895 | X55: 5.965441 | Y55: 5.862265 | Z55: 5.807958 | AA55: 5.725763 | AB55: 5.689218 | AC55: 5.659315 | AD55: 5.633512 | AE55: 5.612592 | AF55: 5.594244 | AG55: 5.575975 | AH55: 5.562133 | AI55: 5.551663 | AJ55: -0.039048
A56: Natural Gas Bi-fuel | B56: 37.19714 | C56: 37.315529 | D56: 37.309807 | E56: 37.126621 | F56: 36.839725 | G56: 36.304241 | H56: 35.724079 | I56: 35.119129 | J56: 34.47345 | K56: 33.892124 | L56: 33.293274 | M56: 32.730461 | N56: 32.119881 | O56: 31.600567 | P56: 31.160404 | Q56: 30.744526 | R56: 30.370613 | S56: 30.134914 | T56: 29.880434 | U56: 29.649422 | V56: 29.446999 | W56: 29.263313 | X56: 29.062243 | Y56: 28.842033 | Z56: 28.658337 | AA56: 28.468006 | AB56: 28.292097 | AC56: 28.150133 | AD56: 28.028652 | AE56: 27.932308 | AF56: 27.847996 | AG56: 27.762222 | AH56: 27.698891 | AI56: 27.652334 | AJ56: -0.009322
A57: Propane ICE | B57: 15.536107 | C57: 14.459949 | D57: 13.504262 | E57: 12.644981 | F57: 11.871395 | G57: 11.127613 | H57: 10.45 | I57: 9.828161 | J57: 9.253678 | K57: 8.738051 | L57: 8.263955 | M57: 7.838923 | N57: 7.443721 | O57: 7.085744 | P57: 6.773302 | Q57: 6.497639 | R57: 6.252445 | S57: 6.084557 | T57: 5.923894 | U57: 5.790704 | V57: 5.676636 | W57: 5.577735 | X57: 5.478998 | Y57: 5.374598 | Z57: 5.321282 | AA57: 5.281228 | AB57: 5.246207 | AC57: 5.217097 | AD57: 5.191752 | AE57: 5.170716 | AF57: 5.152221 | AG57: 5.134222 | AH57: 5.120206 | AI57: 5.109301 | AJ57: -0.031987
A58: Propane Bi-fuel | B58: 75.654488 | C58: 70.127174 | D58: 65.092728 | E58: 60.381432 | F58: 55.956242 | G58: 51.602642 | H58: 47.528503 | I58: 43.728642 | J58: 40.178066 | K58: 36.954609 | L58: 34.001389 | M58: 31.354206 | N58: 28.929304 | O58: 26.754398 | P58: 24.876833 | Q58: 23.259001 | R58: 21.86487 | S58: 20.921804 | T58: 20.067417 | U58: 19.397001 | V58: 18.849516 | W58: 18.395195 | X58: 17.954615 | Y58: 17.475426 | Z58: 17.380531 | AA58: 17.269787 | AB58: 17.165451 | AC58: 17.082088 | AD58: 17.011189 | AE58: 16.955887 | AF58: 16.907574 | AG58: 16.857616 | AH58: 16.821451 | AI58: 16.795465 | AJ58: -0.04368
A59: Fuel Cell Methanol | B59: 0 | C59: 0 | D59: 0 | E59: 0 | F59: 0 | G59: 0 | H59: 0 | I59: 0 | J59: 0 | K59: 0 | L59: 0 | M59: 0 | N59: 0 | O59: 0 | P59: 0 | Q59: 0 | R59: 0 | S59: 0 | T59: 0 | U59: 0 | V59: 0 | W59: 0 | X59: 0 | Y59: 0 | Z59: 0 | AA59: 0 | AB59: 0 | AC59: 0 | AD59: 0 | AE59: 0 | AF59: 0 | AG59: 0 | AH59: 0 | AI59: 0 | AJ59: - -
A60: Fuel Cell Hydrogen | B60: 1.352372 | C60: 3.34874 | D60: 6.645105 | E60: 11.891937 | F60: 21.463959 | G60: 34.547173 | H60: 44.213631 | I60: 53.464401 | J60: 62.412399 | K60: 68.83017 | L60: 73.786804 | M60: 76.675613 | N60: 79.645332 | O60: 82.186638 | P60: 84.451271 | Q60: 84.202934 | R60: 83.88533 | S60: 83.718788 | T60: 83.521248 | U60: 83.362885 | V60: 82.41629 | W60: 81.377609 | X60: 80.342957 | Y60: 79.408035 | Z60: 78.279625 | AA60: 77.059868 | AB60: 75.885643 | AC60: 74.786491 | AD60: 73.655838 | AE60: 72.496574 | AF60: 71.381332 | AG60: 70.435013 | AH60: 69.59729 | AI60: 68.967674 | AJ60: 0.099145
A61: Total Alternative Light Trucks | B61: 2049.0544 | C61: 1994.9873 | D61: 1961.8184 | E61: 1951.6189 | F61: 1988.1116 | G61: 2042.4701 | H61: 2075.4741 | I61: 2102.9258 | J61: 2128.0229 | K61: 2136.4019 | L61: 2127.5334 | M61: 2105.2751 | N61: 2086.8164 | O61: 2071.0149 | P61: 2058.7451 | Q61: 2032.8154 | R61: 2011.7964 | S61: 1999.5526 | T61: 1987.8269 | U61: 1977.4244 | V61: 1968.8848 | W61: 1955.5195 | X61: 1945.3633 | Y61: 1944.027 | Z61: 1942.4468 | AA61: 1940.0939 | AB61: 1937.6748 | AC61: 1937.0531 | AD61: 1935.77 | AE61: 1933.8357 | AF61: 1931.3053 | AG61: 1928.3882 | AH61: 1926.6354 | AI61: 1926.7131 | AJ61: -0.001088
A63: Total Light Truck Stock | B63: 9336.8301 | C63: 8955.8438 | D63: 8677.9707 | E63: 8443.8906 | F63: 8232.1182 | G63: 7994.6519 | H63: 7772.0215 | I63: 7561.563 | J63: 7356.5801 | K63: 7174.7461 | L63: 6985.3682 | M63: 6803.4346 | N63: 6623.668 | O63: 6459.6543 | P63: 6318.4814 | Q63: 6179.5449 | R63: 6054.2676 | S63: 5963.5815 | T63: 5871.582 | U63: 5786.2095 | V63: 5714.6631 | W63: 5648.8037 | X63: 5584.8701 | Y63: 5528.8828 | Z63: 5477.7197 | AA63: 5439.6182 | AB63: 5405.623 | AC63: 5381.0947 | AD63: 5360.6191 | AE63: 5344.667 | AF63: 5329.7349 | AG63: 5312.9561 | AH63: 5301.8389 | AI63: 5294.7178 | AJ63: -0.016291
A65: Total Fleet Vehicles | B65: 17703.521 | C65: 17035.131 | D65: 16511.652 | E65: 16073.267 | F65: 15685.381 | G65: 15257.166 | H65: 14891.473 | I65: 14564.87 | J65: 14245.082 | K65: 13953.679 | L65: 13677.148 | M65: 13429.973 | N65: 13206.455 | O65: 13019.943 | P65: 12889.624 | Q65: 12762.02 | R65: 12658.358 | S65: 12613.359 | T65: 12567.066 | U65: 12522.682 | V65: 12494.725 | W65: 12474.605 | X65: 12452.721 | Y65: 12440.614 | Z65: 12430.817 | AA65: 12448.545 | AB65: 12468.326 | AC65: 12503.179 | AD65: 12541.197 | AE65: 12576.243 | AF65: 12599.166 | AG65: 12609.108 | AH65: 12623.789 | AI65: 12636.903 | AJ65: -0.00929
A67: Commercial Light Truck Stock 2/
A68: Motor Gasoline | B68: 7719.5703 | C68: 7388.231 | D68: 7087.6426 | E68: 6865.1406 | F68: 6654.2314 | G68: 6436.3604 | H68: 6240.0571 | I68: 6086.2959 | J68: 5945.1089 | K68: 5840.4575 | L68: 5739.895 | M68: 5606.6079 | N68: 5527.8784 | O68: 5411.7368 | P68: 5354.6982 | Q68: 5272.438 | R68: 5186.1616 | S68: 5093.2339 | T68: 5030.626 | U68: 4935.1714 | V68: 4839.9873 | W68: 4775.5127 | X68: 4677.2441 | Y68: 4609.8877 | Z68: 4512.2568 | AA68: 4424.7725 | AB68: 4376.5547 | AC68: 4307.479 | AD68: 4217.9302 | AE68: 4134.1152 | AF68: 4040.6431 | AG68: 3938.7502 | AH68: 3834.2427 | AI68: 3716.6846 | AJ68: -0.021242
A69: Diesel | B69: 4734.8306 | C69: 4869.4165 | D69: 4994.8984 | E69: 5136.4126 | F69: 5280.9341 | G69: 5411.8301 | H69: 5541.6504 | I69: 5665.4834 | J69: 5786.7778 | K69: 5888.1128 | L69: 5994.6206 | M69: 6081.5439 | N69: 6182.769 | O69: 6187.3179 | P69: 6329.3394 | Q69: 6366.8569 | R69: 6439.7314 | S69: 6462.2378 | T69: 6492.1421 | U69: 6513.8418 | V69: 6488.876 | W69: 6496.8198 | X69: 6427.4121 | Y69: 6421.8926 | Z69: 6360.7798 | AA69: 6373.4692 | AB69: 6429.1484 | AC69: 6454.4072 | AD69: 6465.8506 | AE69: 6491.5835 | AF69: 6548.5474 | AG69: 6545.8237 | AH69: 6568.458 | AI69: 6566.4033 | AJ69: 0.009387
A70: Propane | B70: 0.041408 | C70: 0.701373 | D70: 1.415488 | E70: 2.169564 | F70: 2.948441 | G70: 3.736746 | H70: 4.551395 | I70: 5.383721 | J70: 6.229667 | K70: 7.092832 | L70: 7.970722 | M70: 8.871048 | N70: 9.79502 | O70: 10.737355 | P70: 11.706683 | Q70: 12.689833 | R70: 13.689785 | S70: 14.709307 | T70: 15.742059 | U70: 16.785549 | V70: 17.843605 | W70: 18.916348 | X70: 19.998865 | Y70: 21.093317 | Z70: 22.199602 | AA70: 23.312925 | AB70: 24.43572 | AC70: 25.576822 | AD70: 26.733946 | AE70: 27.907084 | AF70: 29.09054 | AG70: 30.282028 | AH70: 31.489689 | AI70: 32.866543 | AJ70: 0.12775
A71: Compressed/Liquefied Natural Gas | B71: 11.380197 | C71: 11.59199 | D71: 11.791846 | E71: 11.972598 | F71: 12.129579 | G71: 12.254408 | H71: 12.358032 | I71: 12.450001 | J71: 12.501683 | K71: 12.644959 | L71: 12.585588 | M71: 12.631204 | N71: 12.793311 | O71: 12.801377 | P71: 12.897332 | Q71: 12.829887 | R71: 12.896102 | S71: 13.000175 | T71: 13.198858 | U71: 13.460276 | V71: 13.745989 | W71: 14.203264 | X71: 14.751233 | Y71: 15.396377 | Z71: 16.143673 | AA71: 17.000696 | AB71: 18.02986 | AC71: 19.46607 | AD71: 20.841642 | AE71: 21.642704 | AF71: 23.187176 | AG71: 24.523056 | AH71: 26.456913 | AI71: 28.691246 | AJ71: 0.028726
A72: Ethanol-Flex Fuel | B72: 1302.9929 | C72: 1582.9817 | D72: 1863.9946 | E72: 2139.0833 | F72: 2403.6533 | G72: 2651.4192 | H72: 2889.0645 | I72: 3115.6584 | J72: 3330.8794 | K72: 3537.4927 | L72: 3737.2483 | M72: 3936.6465 | N72: 4138.1143 | O72: 4340.3223 | P72: 4546.0874 | Q72: 4752.5361 | R72: 4961.334 | S72: 5173.3618 | T72: 5387.3042 | U72: 5603.0229 | V72: 5821.9697 | W72: 6044.5913 | X72: 6269.9937 | Y72: 6499.1191 | Z72: 6732.5562 | AA72: 6985.0469 | AB72: 7225.9043 | AC72: 7461.1777 | AD72: 7716.9854 | AE72: 7959.8721 | AF72: 8247.3818 | AG72: 8476.3047 | AH72: 8733.7236 | AI72: 8985.9668 | AJ72: 0.05576
A73: Electric | B73: 0 | C73: 0 | D73: 0 | E73: 0.950456 | F73: 1.933605 | G73: 2.927428 | H73: 3.955451 | I73: 5.010197 | J73: 6.088058 | K73: 7.193323 | L73: 8.321522 | M73: 9.481894 | N73: 10.678308 | O73: 11.902115 | P73: 13.163356 | Q73: 14.44487 | R73: 15.75213 | S73: 17.086782 | T73: 18.440033 | U73: 19.808685 | V73: 21.197168 | W73: 22.605139 | X73: 24.026016 | Y73: 25.462082 | Z73: 26.912809 | AA73: 28.371765 | AB73: 29.841652 | AC73: 31.333256 | AD73: 32.843403 | AE73: 34.371765 | AF73: 35.911068 | AG73: 37.458168 | AH73: 39.023144 | AI73: 40.603519 | AJ73: - -
A74: Plug-in Gasoline Hybrid | B74: 0 | C74: 0 | D74: 0 | E74: 1.064342 | F74: 2.165294 | G74: 3.278199 | H74: 4.429402 | I74: 5.61053 | J74: 6.817543 | K74: 8.055242 | L74: 9.318625 | M74: 10.618035 | N74: 11.957807 | O74: 13.328256 | P74: 14.740617 | Q74: 16.175695 | R74: 17.639584 | S74: 19.134169 | T74: 20.649557 | U74: 22.182213 | V74: 23.737061 | W74: 25.313745 | X74: 26.904867 | Y74: 28.51302 | Z74: 30.137558 | AA74: 31.771341 | AB74: 33.417362 | AC74: 35.087681 | AD74: 36.778759 | AE74: 38.490276 | AF74: 40.213997 | AG74: 41.946503 | AH74: 43.698997 | AI74: 45.468727 | AJ74: - -
A75: Plug-in Diesel Hybrid | B75: 0 | C75: 0 | D75: 0 | E75: 1.038787 | F75: 2.113305 | G75: 3.199491 | H75: 4.323053 | I75: 5.475821 | J75: 6.653853 | K75: 7.861836 | L75: 9.094882 | M75: 10.363097 | N75: 11.670701 | O75: 13.008245 | P75: 14.386697 | Q75: 15.787313 | R75: 17.216061 | S75: 18.674757 | T75: 20.153763 | U75: 21.649628 | V75: 23.167133 | W75: 24.705961 | X75: 26.258873 | Y75: 27.828411 | Z75: 29.413963 | AA75: 31.008499 | AB75: 32.615009 | AC75: 34.245224 | AD75: 35.895702 | AE75: 37.566124 | AF75: 39.248489 | AG75: 40.939388 | AH75: 42.649796 | AI75: 44.377026 | AJ75: - -
A76: Fuel Cell | B76: 0 | C76: 0 | D76: 0 | E76: 0 | F76: 0 | G76: 0 | H76: 0 | I76: 0 | J76: 0 | K76: 0 | L76: 0 | M76: 0 | N76: 0 | O76: 0 | P76: 0 | Q76: 0 | R76: 0 | S76: 0 | T76: 0 | U76: 0 | V76: 0 | W76: 0 | X76: 0 | Y76: 0 | Z76: 0 | AA76: 0 | AB76: 0 | AC76: 0 | AD76: 0 | AE76: 0 | AF76: 0 | AG76: 0 | AH76: 0 | AI76: 0 | AJ76: - -
A77: Total Commercial Light Truck Stock | B77: 13768.814 | C77: 13852.922 | D77: 13959.742 | E77: 14157.832 | F77: 14360.109 | G77: 14525.006 | H77: 14700.39 | I77: 14901.367 | J77: 15101.058 | K77: 15308.912 | L77: 15519.055 | M77: 15676.764 | N77: 15905.657 | O77: 16001.154 | P77: 16297.019 | Q77: 16463.76 | R77: 16664.42 | S77: 16811.438 | T77: 16998.258 | U77: 17145.922 | V77: 17250.523 | W77: 17422.668 | X77: 17486.59 | Y77: 17649.195 | Z77: 17730.398 | AA77: 17914.752 | AB77: 18169.949 | AC77: 18368.775 | AD77: 18553.863 | AE77: 18745.549 | AF77: 19004.225 | AG77: 19136.029 | AH77: 19319.744 | AI77: 19461.062 | AJ77: 0.010679
A79: 1/ Includes all fleets of 10 or more.
A80: 2/ Commercial trucks from 8,501 to 10,000 pounds.
A81: ICE = Internal combustion engine.
A82: - - = Not applicable.
A83: Note: Totals may not equal sum of components due to independent rounding.
A84: Sources: 2017 values derived using: Publishing Company, Fleet Fact Book, various issues; Federal Highway
A85: Administration, Highway Statistics 2016; and U.S. Energy Information Administration (EIA), Describing Current and Potential
A86: Markets for Alternative-Fuel Vehicles, 1996; and EIA, AEO2019 National Energy Modeling System run ref2019.d111618a.
A87: 2018 and projections: EIA, AEO2019 National Energy Modeling System run ref2019.d111618a.

Sheet AEO 49
B1: ref2019.d111618a | C1: 2017 | D1: 2018 | E1: 2019 | F1: 2020 | G1: 2021 | H1: 2022 | I1: 2023 | J1: 2024 | K1: 2025 | L1: 2026 | M1: 2027 | N1: 2028 | O1: 2029 | P1: 2030 | Q1: 2031 | R1: 2032 | S1: 2033 | T1: 2034 | U1: 2035 | V1: 2036 | W1: 2037 | X1: 2038 | Y1: 2039 | Z1: 2040 | AA1: 2041 | AB1: 2042 | AC1: 2043 | AD1: 2044 | AE1: 2045 | AF1: 2046 | AG1: 2047 | AH1: 2048 | AI1: 2049 | AJ1: 2050
C3: Report | D3: Annual Energy Outlook 2019
C4: Scenario | D4: ref2019 | G4: Reference case
C5: Datekey | D5: d111618a
C6: Release Date | E6: January 2019
A10: ATS000 | B10: 49. Aircraft Stock
AK12: 2018-
B13: Stock | C13: 2017 | D13: 2018 | E13: 2019 | F13: 2020 | G13: 2021 | H13: 2022 | I13: 2023 | J13: 2024 | K13: 2025 | L13: 2026 | M13: 2027 | N13: 2028 | O13: 2029 | P13: 2030 | Q13: 2031 | R13: 2032 | S13: 2033 | T13: 2034 | U13: 2035 | V13: 2036 | W13: 2037 | X13: 2038 | Y13: 2039 | Z13: 2040 | AA13: 2041 | AB13: 2042 | AC13: 2043 | AD13: 2044 | AE13: 2045 | AF13: 2046 | AG13: 2047 | AH13: 2048 | AI13: 2049 | AJ13: 2050 | AK13: 2050
B15: Aircraft Stock
A16: ATS000:stk_U.S.Total | B16: United States | C16: 8556.9023 | D16: 8782.752 | E16: 9019.627 | F16: 9262.3252 | G16: 9501.46 | H16: 9729.5791 | I16: 9969.7881 | J16: 10204.913 | K16: 10430.27 | L16: 10648.474 | M16: 10852.224 | N16: 11042.507 | O16: 11223.458 | P16: 11390.76 | Q16: 11531.974 | R16: 11661.18 | S16: 11786.006 | T16: 11908.087 | U16: 12029.012 | V16: 12151.535 | W16: 12270.73 | X16: 12380.965 | Y16: 12484.449 | Z16: 12586.021 | AA16: 12693.679 | AB16: 12808.978 | AC16: 12934.625 | AD16: 13066.677 | AE16: 13197.98 | AF16: 13335.504 | AG16: 13474.515 | AH16: 13582.81 | AI16: 13686.998 | AJ16: 13793.74 | AK16: 0.014207
A17: ATS000:stk_USNarrowBody | B17: Narrow Body Aircraft | C17: 4405.7471 | D17: 4580.6211 | E17: 4767.1191 | F17: 4954.376 | G17: 5137.874 | H17: 5314.2446 | I17: 5481.6172 | J17: 5641.0352 | K17: 5793.4424 | L17: 5942.5723 | M17: 6081.3491 | N17: 6208.0654 | O17: 6332.166 | P17: 6447.1357 | Q17: 6548.4849 | R17: 6642.4722 | S17: 6735.1372 | T17: 6826.0552 | U17: 6919.5889 | V17: 7013.2285 | W17: 7104.6143 | X17: 7191.4741 | Y17: 7275.2056 | Z17: 7358.6494 | AA17: 7447.1685 | AB17: 7542.9023 | AC17: 7648.9717 | AD17: 7762.8101 | AE17: 7883.0073 | AF17: 8006.3335 | AG17: 8131.9058 | AH17: 8258.0645 | AI17: 8382.7822 | AJ17: 8503.1768 | AK17: 0.019519
A18: ATS000:stk_USWideBody | B18: Wide Body Aircraft | C18: 1249.9583 | D18: 1226.3086 | E18: 1211.7889 | F18: 1204.8491 | G18: 1200.5604 | H18: 1196.7437 | I18: 1210.2567 | J18: 1227.4249 | K18: 1246.342 | L18: 1266.6892 | M18: 1287.3787 | N18: 1311.4264 | O18: 1333.6724 | P18: 1355.8521 | Q18: 1380.2045 | R18: 1404.7987 | S18: 1429.8125 | T18: 1455.4954 | U18: 1481.3813 | V18: 1507.3611 | W18: 1533.8206 | X18: 1560.9368 | Y18: 1588.354 | Z18: 1616.2996 | AA18: 1643.5125 | AB18: 1671.4509 | AC18: 1700.0862 | AD18: 1729.3638 | AE18: 1759.5537 | AF18: 1790.5027 | AG18: 1822.3066 | AH18: 1854.5723 | AI18: 1886.944 | AJ18: 1919.1038 | AK18: 0.014094
A19: ATS000:stk_USRegional | B19: Regional Jets | C19: 2901.1973 | D19: 2975.8225 | E19: 3040.7183 | F19: 3103.1001 | G19: 3163.0254 | H19: 3218.5908 | I19: 3277.9138 | J19: 3336.4534 | K19: 3390.4858 | L19: 3439.2117 | M19: 3483.4963 | N19: 3523.0149 | O19: 3557.6196 | P19: 3587.7715 | Q19: 3603.2839 | R19: 3613.9089 | S19: 3621.0562 | T19: 3626.5359 | U19: 3628.041 | V19: 3630.9458 | W19: 3632.2961 | X19: 3628.5542 | Y19: 3620.8892 | Z19: 3611.0718 | AA19: 3602.9983 | AB19: 3594.6243 | AC19: 3585.5674 | AD19: 3574.5032 | AE19: 3555.4194 | AF19: 3538.668 | AG19: 3520.3015 | AH19: 3470.1729 | AI19: 3417.272 | AJ19: 3371.46 | AK19: 0.003908
A20: ATS000:stk_Canada | B20: Canada | C20: 943.51129 | D20: 955.47821 | E20: 965.6842 | F20: 975.39331 | G20: 983.724 | H20: 991.57068 | I20: 998.42816 | J20: 1005.6929 | K20: 1013.0767 | L20: 1020.3723 | M20: 1028.2203 | N20: 1036.288 | O20: 1044.5876 | P20: 1053.4701 | Q20: 1066.4026 | R20: 1080.832 | S20: 1096.2681 | T20: 1113.4138 | U20: 1132.0181 | V20: 1151.4303 | W20: 1171.6893 | X20: 1192.0835 | Y20: 1213.3651 | Z20: 1234.8871 | AA20: 1256.5039 | AB20: 1278.2723 | AC20: 1302.1448 | AD20: 1326.2328 | AE20: 1350.6509 | AF20: 1376.5986 | AG20: 1403.0471 | AH20: 1430.3584 | AI20: 1458.2212 | AJ20: 1486.978 | AK20: 0.013917
A21: ATS000:stk_Canada-nb | B21: Narrow Body Aircraft | C21: 347.49164 | D21: 351.68677 | E21: 355.52121 | F21: 359.29712 | G21: 363.10364 | H21: 366.97638 | I21: 371.09192 | J21: 375.79825 | K21: 380.30652 | L21: 384.65927 | M21: 389.5 | N21: 394.54034 | O21: 399.6622 | P21: 404.95084 | Q21: 413.44174 | R21: 422.31045 | S21: 430.98636 | T21: 440.59253 | U21: 450.60236 | V21: 460.68811 | W21: 471.09949 | X21: 481.92071 | Y21: 492.66946 | Z21: 503.30917 | AA21: 514.15027 | AB21: 525.20074 | AC21: 536.42438 | AD21: 547.72559 | AE21: 559.30627 | AF21: 571.11621 | AG21: 583.00989 | AH21: 595.11346 | AI21: 607.55225 | AJ21: 620.11359 | AK21: 0.017882
A22: ATS000:stk_Canada-wb | B22: Wide Body Aircraft | C22: 133.45897 | D22: 137.45016 | E22: 140.91112 | F22: 144.76733 | G22: 148.60454 | H22: 152.51004 | I22: 155.28857 | J22: 158.88928 | K22: 163.17535 | L22: 167.45708 | M22: 172.07141 | N22: 176.88242 | O22: 181.83641 | P22: 186.9868 | Q22: 192.68434 | R22: 198.66829 | S22: 205.06383 | T22: 211.78491 | U22: 218.69899 | V22: 225.74147 | W22: 233.07916 | X22: 240.76822 | Y22: 248.52847 | Z22: 256.55908 | AA22: 264.60687 | AB22: 272.90585 | AC22: 281.43686 | AD22: 290.14291 | AE22: 299.15225 | AF22: 308.43719 | AG22: 317.90781 | AH22: 327.64639 | AI22: 337.73715 | AJ22: 348.04156 | AK22: 0.029459
A23: ATS000:stk_Canada-rj | B23: Regional Jets | C23: 462.56067 | D23: 466.34128 | E23: 469.25186 | F23: 471.32886 | G23: 472.01581 | H23: 472.08426 | I23: 472.04767 | J23: 471.0054 | K23: 469.59482 | L23: 468.25592 | M23: 466.64889 | N23: 464.86523 | O23: 463.08902 | P23: 461.5325 | Q23: 460.27652 | R23: 459.85321 | S23: 460.2179 | T23: 461.03632 | U23: 462.71674 | V23: 465.00073 | W23: 467.51068 | X23: 469.39453 | Y23: 472.16715 | Z23: 475.01877 | AA23: 477.7467 | AB23: 480.16574 | AC23: 484.2836 | AD23: 488.36429 | AE23: 492.19238 | AF23: 497.0452 | AG23: 502.12933 | AH23: 507.59851 | AI23: 512.93176 | AJ23: 518.82288 | AK23: 0.003338
A24: ATS000:stk_Central_Am | B24: Central America | C24: 796.98584 | D24: 839.57764 | E24: 884.27136 | F24: 930.29309 | G24: 977.94812 | H24: 1026.4446 | I24: 1075.5314 | J24: 1125.2771 | K24: 1175.0249 | L24: 1224.7755 | M24: 1274.9265 | N24: 1325.4113 | O24: 1376.3717 | P24: 1427.9666 | Q24: 1481.3638 | R24: 1536.0007 | S24: 1593.1343 | T24: 1651.739 | U24: 1711.9142 | V24: 1773.0913 | W24: 1835.2092 | X24: 1897.5298 | Y24: 1959.7639 | Z24: 2026.4385 | AA24: 2091.6047 | AB24: 2156.7302 | AC24: 2222.123 | AD24: 2287.3015 | AE24: 2351.8916 | AF24: 2416.4614 | AG24: 2480.9341 | AH24: 2545.7693 | AI24: 2611.0967 | AJ24: 2676.4121 | AK24: 0.036893
A25: ATS000:stk_Central_Am-n | B25: Narrow Body Aircraft | C25: 464.09076 | D25: 491.81036 | E25: 520.07007 | F25: 549.21631 | G25: 579.80005 | H25: 610.90906 | I25: 642.51501 | J25: 674.6015 | K25: 706.95032 | L25: 739.44824 | M25: 772.18939 | N25: 805.01386 | O25: 838.0271 | P25: 871.44025 | Q25: 905.85419 | R25: 941.25348 | S25: 978.48938 | T25: 1016.6234 | U25: 1055.9716 | V25: 1096.1637 | W25: 1136.7012 | X25: 1177.1818 | Y25: 1217.7656 | Z25: 1257.4083 | AA25: 1297.9845 | AB25: 1338.2178 | AC25: 1378.3802 | AD25: 1418.2329 | AE25: 1457.3353 | AF25: 1495.8237 | AG25: 1534.2672 | AH25: 1572.7728 | AI25: 1611.2152 | AJ25: 1649.3124 | AK25: 0.038537
A26: ATS000:stk_Central_Am-w | B26: Wide Body Aircraft | C26: 43.643806 | D26: 47.312588 | E26: 52.574127 | F26: 58.302418 | G26: 64.243317 | H26: 70.490555 | I26: 76.814865 | J26: 83.313896 | K26: 89.580978 | L26: 95.76664 | M26: 102.16319 | N26: 108.8357 | O26: 115.78057 | P26: 122.89415 | Q26: 130.72154 | R26: 138.69106 | S26: 147.13983 | T26: 155.97531 | U26: 164.90103 | V26: 173.93506 | W26: 183.14485 | X26: 192.67659 | Y26: 202.08794 | Z26: 216.99188 | AA26: 228.00755 | AB26: 239.18527 | AC26: 250.58801 | AD26: 262.04852 | AE26: 273.75885 | AF26: 285.66186 | AG26: 297.50311 | AH26: 309.62491 | AI26: 322.23169 | AJ26: 335.08298 | AK26: 0.063085
A27: ATS000:stk_Central_Am-r | B27: Regional Jets | C27: 289.25128 | D27: 300.45474 | E27: 311.6272 | F27: 322.77432 | G27: 333.90479 | H27: 345.04495 | I27: 356.20148 | J27: 367.36163 | K27: 378.49359 | L27: 389.56058 | M27: 400.57391 | N27: 411.56171 | O27: 422.56406 | P27: 433.63217 | Q27: 444.78805 | R27: 456.05615 | S27: 467.5051 | T27: 479.14032 | U27: 491.04166 | V27: 502.99252 | W27: 515.36316 | X27: 527.67133 | Y27: 539.91034 | Z27: 552.03827 | AA27: 565.61261 | AB27: 579.32721 | AC27: 593.15472 | AD27: 607.01996 | AE27: 620.79736 | AF27: 634.97595 | AG27: 649.16376 | AH27: 663.37152 | AI27: 677.64984 | AJ27: 692.01672 | AK27: 0.026415
... A68: ATS000:stk_WorldTotal | B68: Total World | C68: 32124.422 | D68: 33618.664 | E68: 35167.789 | F68: 36763.273 | G68: 38394.297 | H68: 40043.477 | I68: 41718.086 | J68: 43413.48 | K68: 45146.004 | L68: 46903.328 | M68: 48678.066 | N68: 50460.926 | O68: 52281.98 | P68: 54129.762 | Q68: 56000.223 | R68: 57900.887 | S68: 59849.574 | T68: 61837.207 | U68: 63874.227 | V68: 65943.094 | W68: 68060.688 | X68: 70194.734 | Y68: 72370.672 | Z68: 74584.688 | AA68: 76856.195 | AB68: 79190.625 | AC68: 81574.43 | AD68: 83992.68 | AE68: 86456.539 | AF68: 88962.789 | AG68: 91495.164 | AH68: 94039.414 | AI68: 96632.516 | AJ68: 99265.992 | AK68: 0.034414
B71: Aircraft Active Stock
A72: ATS000:act_U.S.Total | B72: United States | C72: 6585.1777 | D72: 6869.1514 | E72: 7151.0146 | F72: 7430.0967 | G72: 7708.7568 | H72: 7980.7686 | I72: 8247.6445 | J72: 8508.8633 | K72: 8762.3271 | L72: 9006.0576 | M72: 9244.0537 | N72: 9482.1318 | O72: 9708.2012 | P72: 9926.1172 | Q72: 10107.3 | R72: 10264.901 | S72: 10419.205 | T72: 10565.258 | U72: 10701.797 | V72: 10840.538 | W72: 10975.748 | X72: 11104.815 | Y72: 11228.18 | Z72: 11351.535 | AA72: 11479.031 | AB72: 11614.234 | AC72: 11760.216 | AD72: 11918.266 | AE72: 12076.584 | AF72: 12241.539 | AG72: 12408.065 | AH72: 12549.944 | AI72: 12682.85 | AJ72: 12812.458 | AK72: 0.019672
A73: ATS000:act_USNarrowBody | B73: Narrow Body Aircraft | C73: 3740.6677 | D73: 3931.6379 | E73: 4130.478 | F73: 4332.0688 | G73: 4532.647 | H73: 4729.6509 | I73: 4916.6099 | J73: 5097.1836 | K73: 5272.5513 | L73: 5441.4946 | M73: 5608.9844 | N73: 5777.1743 | O73: 5939.2246 | P73: 6096.6875 | Q73: 6229.1753 | R73: 6341.9175 | S73: 6452.4365 | T73: 6555.3545 | U73: 6649.8882 | V73: 6747.5278 | W73: 6842.8364 | X73: 6932.7734 | Y73: 7018.5049 | Z73: 7104.9487 | AA73: 7196.4678 | AB73: 7294.2017 | AC73: 7400.271 | AD73: 7515.1094 | AE73: 7636.3066 | AF73: 7763.6328 | AG73: 7889.2051 | AH73: 8016.3643 | AI73: 8142.2197 | AJ73: 8263.4766 | AK73: 0.023484
A74: ATS000:act_USWideBody | B74: Wide Body Aircraft | C74: 558.34662 | D74: 574.38983 | E74: 589.75049 | F74: 601.60193 | G74: 615.95227 | H74: 630.98523 | I74: 646.51715 | J74: 662.84186 | K74: 680.35443 | L74: 698.66956 | M74: 716.68512 | N74: 737.96454 | O74: 757.40314 | P74: 776.85681 | Q74: 798.31958 | R74: 820.02032 | S74: 842.11035 | T74: 864.85461 | U74: 887.78748 | V74: 910.79913 | W74: 934.27576 | X74: 958.39429 | Y74: 982.79889 | Z74: 1007.7165 | AA74: 1031.8866 | AB74: 1056.767 | AC74: 1082.3289 | AD74: 1108.5176 | AE74: 1135.6034 | AF74: 1163.4325 | AG74: 1192.1011 | AH74: 1221.2157 | AI74: 1250.4207 | AJ74: 1279.3978 | AK74: 0.025342
A75: ATS000:act_USRegional | B75: Regional Jets | C75: 2286.1633 | D75: 2363.1233 | E75: 2430.7859 | F75: 2496.426 | G75: 2560.1577 | H75: 2620.1321 | I75: 2684.5181 | J75: 2748.8379 | K75: 2809.4214 | L75: 2865.8933 | M75: 2918.3843 | N75: 2966.9934 | O75: 3011.5728 | P75: 3052.573 | Q75: 3079.8049 | R75: 3102.9636 | S75: 3124.6577 | T75: 3145.0483 | U75: 3164.1213 | V75: 3182.2107 | W75: 3198.6362 | X75: 3213.6477 | Y75: 3226.876 | Z75: 3238.8704 | AA75: 3250.6765 | AB75: 3263.2654 | AC75: 3277.6165 | AD75: 3294.6387 | AE75: 3304.6738 | AF75: 3314.4734 | AG75: 3326.7585 | AH75: 3312.364 | AI75: 3290.2087 | AJ75: 3269.5842 | AK75: 0.010198
A76: ATS000:act_Canada | B76: Canada | C76: 831.02661 | D76: 844.64673 | E76: 856.37653 | F76: 867.89764 | G76: 878.3169 | H76: 888.19971 | I76: 897.91412 | J76: 908.0401 | K76: 917.65155 | L76: 926.95288 | M76: 937.07483 | N76: 947.53345 | O76: 958.44434 | P76: 970.09821 | Q76: 985.8794 | R76: 1003.0903 | S76: 1022.1118 | T76: 1042.4332 | U76: 1063.6691 | V76: 1085.1941 | W76: 1107.2771 | X76: 1129.972 | Y76: 1152.2288 | Z76: 1174.4995 | AA76: 1197.0626 | AB76: 1220.3166 | AC76: 1244.2725 | AD76: 1269.1729 | AE76: 1295.0936 | AF76: 1321.6194 | AG76: 1348.3125 | AH76: 1375.6776 | AI76: 1403.9718 | AJ76: 1432.8024 | AK76: 0.016652
A77: ATS000:act_Canada-nb | B77: Narrow Body Aircraft | C77: 317.742 | D77: 323.27188 | E77: 328.06216 | F77: 332.85101 | G77: 337.1698 | H77: 341.45642 | I77: 345.91107 | J77: 350.89123 | K77: 355.6174 | L77: 360.14102 | M77: 365.1138 | N77: 370.25467 | O77: 375.45196 | P77: 380.79633 | Q77: 389.32782 | R77: 398.22565 | S77: 407.6994 | T77: 417.57932 | U77: 427.62094 | V77: 437.7067 | W77: 448.11807 | X77: 458.9393 | Y77: 469.68805 | Z77: 480.32776 | AA77: 491.16882 | AB77: 502.21933 | AC77: 513.44293 | AD77: 524.74414 | AE77: 536.32483 | AF77: 548.13477 | AG77: 560.02844 | AH77: 572.13202 | AI77: 584.5708 | AJ77: 597.13214 | AK77: 0.019361
A78: ATS000:act_Canada-wb | B78: Wide Body Aircraft | C78: 121.25897 | D78: 125.04616 | E78: 128.29904 | F78: 131.94301 | G78: 135.56374 | H78: 139.24841 | I78: 143.09023 | J78: 147.17268 | K78: 151.22443 | L78: 155.26714 | M78: 159.63766 | N78: 164.2 | O78: 168.90034 | P78: 173.79201 | Q78: 179.22566 | R78: 184.94043 | S78: 191.06142 | T78: 197.50246 | U78: 204.13088 | V78: 210.882 | W78: 217.9225 | X78: 225.30843 | Y78: 232.75948 | Z78: 240.47472 | AA78: 248.20082 | AB78: 256.17166 | AC78: 264.36798 | AD78: 272.73267 | AE78: 281.3938 | AF78: 290.32358 | AG78: 299.43192 | AH78: 308.801 | AI78: 318.51483 | AJ78: 328.43481 | AK78: 0.030637
A79: ATS000:act_Canada-rj | B79: Regional Jets | C79: 392.02567 | D79: 396.32864 | E79: 400.01532 | F79: 403.10364 | G79: 405.58334 | H79: 407.49484 | I79: 408.91284 | J79: 409.9762 | K79: 410.80972 | L79: 411.54474 | M79: 412.3234 | N79: 413.0788 | O79: 414.09207 | P79: 415.50989 | Q79: 417.32593 | R79: 419.92429 | S79: 423.35098 | T79: 427.35144 | U79: 431.91721 | V79: 436.60538 | W79: 441.23654 | X79: 445.72433 | Y79: 449.78125 | Z79: 453.69702 | AA79: 457.69296 | AB79: 461.92572 | AC79: 466.46152 | AD79: 471.69598 | AE79: 477.375 | AF79: 483.16101 | AG79: 488.85211 | AH79: 494.7446 | AI79: 500.88614 | AJ79: 507.23538 | AK79: 0.00774
A80: ATS000:act_Central_Am | B80: Central America | C80: 702.85095 | D80: 748.06812 | E80: 794.45789 | F80: 842.16773 | G80: 890.77869 | H80: 940.50085 | I80: 991.15662 | J80: 1042.9216 | K80: 1095.2371 | L80: 1148.1951 | M80: 1202.1555 | N80: 1257.2156 | O80: 1312.9758 | P80: 1370.0897 | Q80: 1428.0952 | R80: 1487.2062 | S80: 1546.9843 | T80: 1607.5775 | U80: 1669.3416 | V80: 1731.9247 | W80: 1795.2633 | X80: 1858.9271 | Y80: 1922.5984 | Z80: 1992.1769 | AA80: 2058.6616 | AB80: 2124.4026 | AC80: 2190.1062 | AD80: 2255.4507 | AE80: 2320.0786 | AF80: 2384.3643 | AG80: 2448.5471 | AH80: 2513.0867 | AI80: 2578.1125 | AJ80: 2643.1204 | AK80: 0.040233
A81: ATS000:act_Central_Am-n | B81: Narrow Body Aircraft | C81: 412.42426 | D81: 441.55624 | E81: 471.28247 | F81: 501.94794 | G81: 533.37549 | H81: 565.57227 | I81: 598.51282 | J81: 632.26636 | K81: 666.68939 | L81: 701.73798 | M81: 737.45514 | N81: 773.84131 | O81: 810.65454 | P81: 848.40125 | Q81: 886.185 | R81: 924.84924 | S81: 963.47723 | T81: 1002.484 | U81: 1042.3359 | V81: 1082.764 | W81: 1123.4222 | X81: 1163.9812 | Y81: 1204.6182 | Z81: 1245.5341 | AA81: 1286.9023 | AB81: 1327.2152 | AC81: 1367.3777 | AD81: 1407.2303 | AE81: 1446.3328 | AF81: 1484.8212 | AG81: 1523.2646 | AH81: 1561.7703 | AI81: 1600.2126 | AJ81: 1638.3098 | AK81: 0.041823
A82: ATS000:act_Central_Am-w | B82: Wide Body Aircraft | C82: 33.974438 | D82: 38.619946 | E82: 43.849991 | F82: 49.503132 | G82: 55.333782 | H82: 61.44339 | I82: 67.609375 | J82: 73.93515 | K82: 80.018837 | L82: 86.014282 | M82: 92.215935 | N82: 98.689903 | O82: 105.43185 | P82: 112.33846 | Q82: 119.95474 | R82: 127.70891 | S82: 135.93805 | T82: 144.54948 | U82: 153.24669 | V82: 162.04764 | W82: 171.01968 | X82: 180.30891 | Y82: 189.4729 | Z82: 204.12456 | AA82: 214.88287 | AB82: 225.79811 | AC82: 236.93311 | AD82: 248.12051 | AE82: 259.55228 | AF82: 271.17117 | AG82: 282.7226 | AH82: 294.54877 | AI82: 306.85403 | AJ82: 319.39777 | AK82: 0.068249
A83: ATS000:act_Central_Am-r | B83: Regional Jets | C83: 256.45227 | D83: 267.89197 | E83: 279.32541 | F83: 290.7167 | G83: 302.06943 | H83: 313.4852 | I83: 325.03439 | J83: 336.72009 | K83: 348.52881 | L83: 360.44278 | M83: 372.48447 | N83: 384.68442 | O83: 396.88934 | P83: 409.35007 | Q83: 421.95538 | R83: 434.64804 | S83: 447.56897 | T83: 460.54407 | U83: 473.75897 | V83: 487.11307 | W83: 500.82141 | X83: 514.63696 | Y83: 528.50738 | Z83: 542.51831 | AA83: 556.87634 | AB83: 571.38928 | AC83: 585.79547 | AD83: 600.09973 | AE83: 614.19348 | AF83: 628.37207 | AG83: 642.55988 | AH83: 656.76764 | AI83: 671.04596 | AJ83: 685.41284 | AK83: 0.029793
... A124: ATS000:act_WorldTotal | B124: Total World | C124: 27286.984 | D124: 28895.17 | E124: 30545.375 | F124: 32233.766 | G124: 33958.285 | H124: 35717.887 | I124: 37483.66 | J124: 39273.066 | K124: 41091.621 | L124: 42937.395 | M124: 44812.414 | N124: 46723.988 | O124: 48668.508 | P124: 50635.883 | Q124: 52601.336 | R124: 54582.543 | S124: 56602.023 | T124: 58659.738 | U124: 60744.734 | V124: 62872.895 | W124: 65032.891 | X124: 67219.383 | Y124: 69435.219 | Z124: 71687.148 | AA124: 73992.508 | AB124: 76348.188 | AC124: 78747.75 | AD124: 81190.648 | AE124: 83672.078 | AF124: 86194.688 | AG124: 88746.539 | AH124: 91326.336 | AI124: 93932.742 | AJ124: 96572.211 | AK124: 0.038427
B127: Aircraft Parked Stock
A128: ATS000:prk_U.S.Total | B128: United States | C128: 1035.2216 | D128: 1002.7459 | E128: 973.12213 | F128: 945.41016 | G128: 913.68115 | H128: 870.97369 | I128: 841.91065 | J128: 813.14374 | K128: 783.31671 | L128: 756.04034 | M128: 723.95721 | N128: 683.40381 | O128: 638.41986 | P128: 584.97217 | Q128: 543.10895 | R128: 512.85181 | S128: 481.51669 | T128: 457.67697 | U128: 442.37338 | V128: 425.20105 | W128: 406.23703 | X128: 385.85748 | Y128: 363.65613 | Z128: 339.60345 | AA128: 317.10352 | AB128: 295.47885 | AC128: 273.40704 | AD128: 245.30504 | AE128: 216.23228 | AF128: 187.24876 | AG128: 157.66948 | AH128: 123.06326 | AI128: 93.428741 | AJ128: 69.248314 | AK128: -0.080132
A129: ATS000:prk_USNarrowBody | B129: Narrow Body Aircraft | C129: 387.07929 | D129: 374.97305 | E129: 362.63138 | F129: 348.45212 | G129: 332.59317 | H129: 315.19086 | I129: 295.93652 | J129: 274.90228 | K129: 253.03149 | L129: 234.24078 | M129: 210.52785 | N129: 179.14865 | O129: 144.19858 | P129: 101.70534 | Q129: 71.566696 | R129: 53.853916 | S129: 36 | T129: 26 | U129: 26 | V129: 23 | W129: 19.077349 | X129: 17 | Y129: 15 | Z129: 12 | AA129: 9 | AB129: 8 | AC129: 8 | AD129: 7 | AE129: 6 | AF129: 3 | AG129: 3 | AH129: 2 | AI129: 0.861858 | AJ129: 0 | AK129: - -
A130: ATS000:prk_USWideBody | B130: Wide Body Aircraft | C130: 85.108284 | D130: 67.073547 | E130: 52.558323 | F130: 42.283905 | G130: 30.220236 | H130: 9.32402 | I130: 4.578397 | J130: 2.626037 | K130: 1.220694 | L130: 0.428814 | M130: 0.264833 | N130: 0.181054 | O130: 0.121984 | P130: 0.015895 | Q130: 0.01065 | R130: 0 | S130: 0 | T130: 0 | U130: 0 | V130: 0 | W130: 0 | X130: 0 | Y130: 0 | Z130: 0 | AA130: 0 | AB130: 0 | AC130: 0 | AD130: 0 | AE130: 0 | AF130: 0 | AG130: 0 | AH130: 0 | AI130: 0 | AJ130: 0 | AK130: - -
A131: ATS000:prk_USRegional | B131: Regional Jets | C131: 563.034 | D131: 560.69922 | E131: 557.93243 | F131: 554.67413 | G131: 550.86774 | H131: 546.4588 | I131: 541.39575 | J131: 535.61542 | K131: 529.06451 | L131: 521.37073 | M131: 513.16455 | N131: 504.0741 | O131: 494.0993 | P131: 483.25092 | Q131: 471.53159 | R131: 458.99789 | S131: 445.51669 | T131: 431.67697 | U131: 416.37338 | V131: 402.20105 | W131: 387.15967 | X131: 368.85748 | Y131: 348.65613 | Z131: 327.60345 | AA131: 308.10352 | AB131: 287.47885 | AC131: 265.40704 | AD131: 238.30504 | AE131: 210.23228 | AF131: 184.24876 | AG131: 154.66948 | AH131: 121.06326 | AI131: 92.566879 | AJ131: 69.248314 | AK131: -0.063269
A132: ATS000:prk_Canada | B132: Canada | C132: 65.284637 | D132: 63.427544 | E132: 61.695587 | F132: 59.671333 | G132: 57.452938 | H132: 55.273556 | I132: 53.191319 | J132: 50.163567 | K132: 47.759018 | L132: 45.51424 | M132: 42.996506 | N132: 40.356922 | O132: 37.492012 | P132: 34.461933 | Q132: 31.371628 | R132: 28.320883 | S132: 24.469107 | T132: 21.060804 | U132: 18.179544 | V132: 15.775371 | W132: 13.654145 | X132: 11.15905 | Y132: 9.874762 | Z132: 8.810604 | AA132: 7.598513 | AB132: 5.946968 | AC132: 5.529007 | AD132: 4.433164 | AE132: 3.582251 | AF132: 2.679178 | AG132: 2.100659 | AH132: 1.687145 | AI132: 0.948312 | AJ132: 0.523048 | AK132: -0.139238
A133: ATS000:prk_Canada-nb | B133: Narrow Body Aircraft | C133: 6.749637 | D133: 5.414897 | E133: 4.459055 | F133: 3.44611 | G133: 2.933837 | H133: 2.519951 | I133: 2.180832 | J133: 1.907005 | K133: 1.689108 | L133: 1.518238 | M133: 1.386199 | N133: 1.285664 | O133: 1.210243 | P133: 1.154501 | Q133: 1.113921 | R133: 1.084822 | S133: 0.295059 | T133: 0.021299 | U133: 0 | V133: 0 | W133: 0 | X133: 0 | Y133: 0 | Z133: 0 | AA133: 0 | AB133: 0 | AC133: 0 | AD133: 0 | AE133: 0 | AF133: 0 | AG133: 0 | AH133: 0 | AI133: 0 | AJ133: 0 | AK133: - -
A134: ATS000:prk_Canada-wb | B134: Wide Body Aircraft | C134: 1 | D134: 1 | E134: 1 | F134: 1 | G134: 1 | H134: 1 | I134: 0.711488 | J134: 0 | K134: 0 | L134: 0 | M134: 0 | N134: 0 | O134: 0 | P134: 0 | Q134: 0 | R134: 0 | S134: 0 | T134: 0 | U134: 0 | V134: 0 | W134: 0 | X134: 0 | Y134: 0 | Z134: 0 | AA134: 0 | AB134: 0 | AC134: 0 | AD134: 0 | AE134: 0 | AF134: 0 | AG134: 0 | AH134: 0 | AI134: 0 | AJ134: 0 | AK134: - -
A135: ATS000:prk_Canada-rj | B135: Regional Jets | C135: 57.535 | D135: 57.012646 | E135: 56.23653 | F135: 55.225224 | G135: 53.5191 | H135: 51.753605 | I135: 50.299 | J135: 48.256561 | K135: 46.069912 | L135: 43.996002 | M135: 41.610306 | N135: 39.071259 | O135: 36.281769 | P135: 33.30743 | Q135: 30.257708 | R135: 27.236061 | S135: 24.174047 | T135: 21.039505 | U135: 18.179544 | V135: 15.775371 | W135: 13.654145 | X135: 11.15905 | Y135: 9.874762 | Z135: 8.810604 | AA135: 7.598513 | AB135: 5.946968 | AC135: 5.529007 | AD135: 4.433164 | AE135: 3.582251 | AF135: 2.679178 | AG135: 2.100659 | AH135: 1.687145 | AI135: 0.948312 | AJ135: 0.523048 | AK135: -0.136365
A136: ATS000:prk_Central_Am | B136: Central America | C136: 64.974884 | D136: 62.516327 | E136: 60.982719 | F136: 59.42712 | G136: 58.298141 | H136: 56.895691 | I136: 55.146603 | J136: 52.943474 | K136: 50.1884 | L136: 46.835854 | M136: 42.833069 | N136: 38.079624 | O136: 33.185364 | P136: 27.601475 | Q136: 22.920439 | R136: 18.589325 | S136: 15.749455 | T136: 13.628861 | U136: 11.872077 | V136: 10.281026 | W136: 8.828255 | X136: 7.28997 | Y136: 5.704282 | Z136: 3.710838 | AA136: 2.135045 | AB136: 1.283386 | AC136: 0.704694 | AD136: 0.276795 | AE136: 0 | AF136: 0 | AG136: 0 | AH136: 0 | AI136: 0 | AJ136: 0 | AK136: - -
A137: ATS000:prk_Central_Am-n | B137: Narrow Body Aircraft | C137: 37.666512 | D137: 36.584106 | E137: 35.446449 | F137: 34.229668 | G137: 33.38588 | H137: 32.298065 | I137: 30.963507 | J137: 29.296461 | K137: 27.222218 | L137: 24.717661 | M137: 21.74334 | N137: 18.202337 | O137: 14.510663 | P137: 10.319381 | Q137: 7.087763 | R137: 4.181204 | S137: 2.81333 | T137: 2.031227 | U137: 1.588004 | V137: 1.370385 | W137: 1.249581 | X137: 1.171257 | Y137: 1.118136 | Z137: 0.845435 | AA137: 0.053342 | AB137: 0 | AC137: 0 | AD137: 0 | AE137: 0 | AF137: 0 | AG137: 0 | AH137: 0 | AI137: 0 | AJ137: 0 | AK137: - -
A138: ATS000:prk_Central_Am-w | B138: Wide Body Aircraft | C138: 1.50937 | D138: 0.369442 | E138: 0.234469 | F138: 0.139827 | G138: 0.076891 | H138: 0.037864 | I138: 0.01601 | J138: 0.00547 | K138: 0.001403 | L138: 0.000404 | M138: 0.00027 | N138: 0 | O138: 0 | P138: 0 | Q138: 0 | R138: 0 | S138: 0 | T138: 0 | U138: 0 | V138: 0 | W138: 0 | X138: 0 | Y138: 0 | Z138: 0 | AA138: 0 | AB138: 0 | AC138: 0 | AD138: 0 | AE138: 0 | AF138: 0 | AG138: 0 | AH138: 0 | AI138: 0 | AJ138: 0 | AK138: - -
A139: ATS000:prk_Central_Am-r | B139: Regional Jets | C139: 25.799 | D139: 25.562777 | E139: 25.301802 | F139: 25.057625 | G139: 24.835371 | H139: 24.559763 | I139: 24.167086 | J139: 23.641544 | K139: 22.964781 | L139: 22.117786 | M139: 21.089458 | N139: 19.877287 | O139: 18.6747 | P139: 17.282093 | Q139: 15.832675 | R139: 14.408121 | S139: 12.936125 | T139: 11.597634 | U139: 10.284073 | V139: 8.910641 | W139: 7.578673 | X139: 6.118713 | Y139: 4.586146 | Z139: 2.865403 | AA139: 2.081702 | AB139: 1.283386 | AC139: 0.704694 | AD139: 0.276795 | AE139: 0 | AF139: 0 | AG139: 0 | AH139: 0 | AI139: 0 | AJ139: 0 | AK139: - -
A140: ATS000:prk_South_Am | B140: South America | C140: 140.024 | D140: 133.45694 | E140: 128.10489 | F140: 122.99267 | G140: 117.67668 | H140: 112.69033 | I140: 106.35902 | J140: 102.41994 | K140: 98.970253 | L140: 97.174576 | M140: 94.83374 | N140: 91.983139 | O140: 89.416534 | P140: 86.238907 | Q140: 83.070366 | R140: 80.212212 | S140: 77.463211 | T140: 74.199333 | U140: 70.3965 | V140: 66.839478 | W140: 64.775375 | X140: 60.229652 | Y140: 58.396713 | Z140: 51.557251 | AA140: 44.717781 | AB140: 37.453896 | AC140: 33.937466 | AD140: 25.06539 | AE140: 23.047768 | AF140: 23.034437 | AG140: 19.024496 | AH140: 17.017189 | AI140: 15.009647 | AJ140: 13.006657 | AK140: -0.070176
A141: ATS000:prk_South_Am-nb | B141: Narrow Body Aircraft | C141: 54.922001 | D141: 49.656872 | E141: 45.535065 | F141: 41.174618 | G141: 36.551254 | H141: 32.339775 | I141: 27.003897 | J141: 23.585306 | K141: 21.04422 | L141: 20.263906 | M141: 19.168129 | N141: 17.485888 | O141: 16.168325 | P141: 14.497519 | Q141: 13.419774 | R141: 13.327424 | S141: 13.246987 | T141: 12.191608 | U141: 12.143706 | V141: 12.106342 | W141: 12.07763 | X141: 12.055894 | Y141: 12.039684 | Z141: 11.02778 | AA141: 10.50773 | AB141: 8.013034 | AC141: 6.991151 | AD141: 4 | AE141: 4 | AF141: 4 | AG141: 4 | AH141: 4 | AI141: 3 | AJ141: 1 | AK141: -0.114883
A142: ATS000:prk_South_Am-wb | B142: Wide Body Aircraft | C142: 13.26 | D142: 12.202678 | E142: 11.292742 | F142: 10.92113 | G142: 10.672549 | H142: 10.384254 | I142: 10.209257 | J142: 10.107836 | K142: 9.746656 | L142: 9.415969 | M142: 9.000761 | N142: 8.811992 | O142: 8.691354 | P142: 8.472711 | Q142: 7.831967 | R142: 6.753472 | S142: 6.129421 | T142: 5.757256 | U142: 5.625729 | V142: 5.511062 | W142: 5.412519 | X142: 5.32903 | Y142: 5.125089 | Z142: 4.298353 | AA142: 2.840748 | AB142: 1.094134 | AC142: 0.088349 | AD142: 0.065389 | AE142: 0.047769 | AF142: 0.034438 | AG142: 0.024496 | AH142: 0.017189 | AI142: 0.009647 | AJ142: 0.006656 | AK142: -0.209277
A143: ATS000:prk_South_Am-rj | B143: Regional Jets | C143: 71.842003 | D143: 71.597382 | E143: 71.277092 | F143: 70.896919 | G143: 70.452873 | H143: 69.966301 | I143: 69.145874 | J143: 68.726791 | K143: 68.179375 | L143: 67.494705 | M143: 66.664848 | N143: 65.685257 | O143: 64.556854 | P143: 63.268681 | Q143: 61.818623 | R143: 60.131313 | S143: 58.086807 | T143: 56.250469 | U143: 52.627068 | V143: 49.222069 | W143: 47.285229 | X143: 42.844727 | Y143: 41.231941 | Z143: 36.231117 | AA143: 31.369303 | AB143: 28.346727 | AC143: 26.857965 | AD143: 21 | AE143: 19 | AF143: 19 | AG143: 15 | AH143: 13 | AI143: 12 | AJ143: 12 | AK143: -0.054288
A144: ATS000:prk_Europe | B144: Europe | C144: 392.03213 | D144: 381.48117 | E144: 370.10193 | F144: 357.3902 | G144: 342.45956 | H144: 324.4942 | I144: 305.58502 | J144: 288.35535 | K144: 272.53851 | L144: 254.10641 | M144: 234.11314 | N144: 215.3324 | O144: 193.98096 | P144: 175.17982 | Q144: 160.6554 | R144: 136.96423 | S144: 115.20644 | T144: 96.950409 | U144: 83.455887 | V144: 68.691109 | W144: 57.359905 | X144: 48.68861 | Y144: 42.04356 | Z144: 38.628593 | AA144: 31.542427 | AB144: 22.983791 | AC144: 15.457098 | AD144: 13 | AE144: 13 | AF144: 10 | AG144: 6 | AH144: 6 | AI144: 6 | AJ144: 5 | AK144: -0.126683
A145: ATS000:prk_Europe-nb | B145: Narrow Body Aircraft | C145: 127.3186 | D145: 124.55893 | E145: 120.76537 | F145: 116.56065 | G145: 111.68264 | H145: 105.8444 | I145: 101.33463 | J145: 99.4254 | K145: 96.427895 | L145: 89.499123 | M145: 83.447357 | N145: 77.101784 | O145: 67.479294 | P145: 61.089233 | Q145: 57.895863 | R145: 50.872482 | S145: 48 | T145: 47 | U145: 47 | V145: 47 | W145: 41 | X145: 40 | Y145: 37.04356 | Z145: 34 | AA145: 28.324408 | AB145: 21 | AC145: 14.990871 | AD145: 13 | AE145: 13 | AF145: 10 | AG145: 6 | AH145: 6 | AI145: 6 | AJ145: 5 | AK145: -0.095596
A146: ATS000:prk_Europe-wb | B146: Wide Body Aircraft | C146: 94.819504 | D146: 91.80407 | E146: 89.542007 | F146: 87.125381 | G146: 84.222641 | H146: 80.064476 | I146: 74.83847 | J146: 68.930603 | K146: 65.419983 | L146: 64.110329 | M146: 61.170689 | N146: 59.323227 | O146: 56.698067 | P146: 53.395706 | Q146: 51.617603 | R146: 44.617393 | S146: 34.066418 | T146: 24.427061 | U146: 16.760612 | V146: 7.397914 | W146: 7 | X146: 2.597784 | Y146: 0 | Z146: 0 | AA146: 0 | AB146: 0 | AC146: 0 | AD146: 0 | AE146: 0 | AF146: 0 | AG146: 0 | AH146: 0 | AI146: 0 | AJ146: 0 | AK146: - -
A147: ATS000:prk_Europe-rj | B147: Regional Jets | C147: 169.89403 | D147: 165.11816 | E147: 159.79454 | F147: 153.70415 | G147: 146.55429 | H147: 138.58533 | I147: 129.41194 | J147: 119.99935 | K147: 110.69066 | L147: 100.49696 | M147: 89.495102 | N147: 78.907372 | O147: 69.803589 | P147: 60.694889 | Q147: 51.141937 | R147: 41.474365 | S147: 33.140018 | T147: 25.52335 | U147: 19.695276 | V147: 14.293196 | W147: 9.359905 | X147: 6.090823 | Y147: 5 | Z147: 4.628594 | AA147: 3.218019 | AB147: 1.983791 | AC147: 0.466227 | AD147: 0 | AE147: 0 | AF147: 0 | AG147: 0 | AH147: 0 | AI147: 0 | AJ147: 0 | AK147: - -
A148: ATS000:prk_Africa | B148: Africa | C148: 174.27515 | D148: 159.39632 | E148: 141.75122 | F148: 121.74418 | G148: 99.447266 | H148: 78.722672 | I148: 69.864784 | J148: 61.25481 | K148: 53.444874 | L148: 45.908894 | M148: 39.264336 | N148: 31.57378 | O148: 23.285351 | P148: 14.525385 | Q148: 11.116631 | R148: 9.629894 | S148: 8.232439 | T148: 7.727801 | U148: 7.31131 | V148: 6.044627 | W148: 4 | X148: 4 | Y148: 3.764473 | Z148: 3.419249 | AA148: 3.140162 | AB148: 3 | AC148: 2.450733 | AD148: 1.213568 | AE148: 0 | AF148: 0 | AG148: 0 | AH148: 0 | AI148: 0 | AJ148: 0 | AK148: - -
A149: ATS000:prk_Africa-nb | B149: Narrow Body Aircraft | C149: 80.593658 | D149: 67.628799 | E149: 53.771397 | F149: 38.422081 | G149: 20.953762 | H149: 5.723207 | I149: 3.013431 | J149: 1.679904 | K149: 0.985687 | L149: 0.612582 | M149: 0.401401 | N149: 0.151718 | O149: 0 | P149: 0 | Q149: 0 | R149: 0 | S149: 0 | T149: 0 | U149: 0 | V149: 0 | W149: 0 | X149: 0 | Y149: 0 | Z149: 0 | AA149: 0 | AB149: 0 | AC149: 0 | AD149: 0 | AE149: 0 | AF149: 0 | AG149: 0 | AH149: 0 | AI149: 0 | AJ149: 0 | AK149: - -
A150: ATS000:prk_Africa-wb | B150: Wide Body Aircraft | C150: 23.547937 | D150: 22.645319 | E150: 20.968094 | F150: 20.038393 | G150: 18.918077 | H150: 17.780966 | I150: 16.523275 | J150: 15.189061 | K150: 13.597528 | L150: 12.117215 | M150: 11.34734 | N150: 10.009257 | O150: 8.462185 | P150: 7.293347 | Q150: 6.364127 | R150: 5.658347 | S150: 5.234598 | T150: 5.125743 | U150: 5.033429 | V150: 4.521914 | W150: 4 | X150: 4 | Y150: 3.764473 | Z150: 3.419249 | AA150: 3.140162 | AB150: 3 | AC150: 2.450733 | AD150: 1.213568 | AE150: 0 | AF150: 0 | AG150: 0 | AH150: 0 | AI150: 0 | AJ150: 0 | AK150: - -
A151: ATS000:prk_Africa-rj | B151: Regional Jets | C151: 70.133553 | D151: 69.1222 | E151: 67.011734 | F151: 63.283707 | G151: 59.575424 | H151: 55.218498 | I151: 50.328075 | J151: 44.385845 | K151: 38.86166 | L151: 33.179096 | M151: 27.515593 | N151: 21.412806 | O151: 14.823165 | P151: 7.232038 | Q151: 4.752504 | R151: 3.971547 | S151: 2.997841 | T151: 2.602057 | U151: 2.277882 | V151: 1.522713 | W151: 0 | X151: 0 | Y151: 0 | Z151: 0 | AA151: 0 | AB151: 0 | AC151: 0 | AD151: 0 | AE151: 0 | AF151: 0 | AG151: 0 | AH151: 0 | AI151: 0 | AJ151: 0 | AK151: - -
A152: ATS000:prk_Mideast | B152: Mideast | C152: 114.58019 | D152: 109.84749 | E152: 104.44011 | F152: 98.985321 | G152: 95.645271 | H152: 90.355492 | I152: 83.793205 | J152: 78.624565 | K152: 69.908096 | L152: 64.741272 | M152: 61.345631 | N152: 57.569881 | O152: 52.735565 | P152: 49.534203 | Q152: 46.265919 | R152: 43.30349 | S152: 39.751614 | T152: 35.656052 | U152: 31.698065 | V152: 27.058376 | W152: 22.340071 | X152: 17.559746 | Y152: 15.327183 | Z152: 14.263629 | AA152: 12.970339 | AB152: 12.447514 | AC152: 11.134189 | AD152: 9.849737 | AE152: 9.587763 | AF152: 9.279154 | AG152: 8.697452 | AH152: 8.068181 | AI152: 7.49008 | AJ152: 7.319295 | AK152: -0.08116
A153: ATS000:prk_Mideast-nb | B153: Narrow Body Aircraft | C153: 59.219997 | D153: 57.561943 | E153: 56.157204 | F153: 54.053074 | G153: 51.91114 | H153: 49.188168 | I153: 46.895565 | J153: 44.526718 | K153: 42.154507 | L153: 39.748779 | M153: 37.720848 | N153: 35.455929 | O153: 33.032127 | P153: 30.764385 | Q153: 28.405638 | R153: 26.274298 | S153: 23.457966 | T153: 20.171152 | U153: 17.055717 | V153: 13.215076 | W153: 9.831625 | X153: 6.326939 | Y153: 4.674884 | Z153: 4.20268 | AA153: 4.12812 | AB153: 4.08584 | AC153: 4 | AD153: 3 | AE153: 3 | AF153: 3 | AG153: 3 | AH153: 3 | AI153: 3 | AJ153: 3 | AK153: -0.088187
A154: ATS000:prk_Mideast-wb | B154: Wide Body Aircraft | C154: 37.440197 | D154: 34.443752 | E154: 30.538019 | F154: 27.312593 | G154: 26.267569 | H154: 23.879082 | I154: 19.808479 | J154: 17.226786 | K154: 11.126843 | L154: 8.621367 | M154: 7.797786 | N154: 6.518455 | O154: 4.370973 | P154: 3.738022 | Q154: 3.17441 | R154: 2.653471 | S154: 2.208212 | T154: 1.804498 | U154: 1.469441 | V154: 1.178987 | W154: 0.936573 | X154: 0.735373 | Y154: 0.570066 | Z154: 0.436237 | AA154: 0.329478 | AB154: 0.245562 | AC154: 0.180572 | AD154: 0.130982 | AE154: 0.093706 | AF154: 0.066105 | AG154: 0.045975 | AH154: 0.031516 | AI154: 0.021291 | AJ154: 0.00793 | AK154: -0.230307
A155: ATS000:prk_Mideast-rj | B155: Regional Jets | C155: 17.92 | D155: 17.841801 | E155: 17.74489 | F155: 17.61965 | G155: 17.466558 | H155: 17.288244 | I155: 17.089165 | J155: 16.871061 | K155: 16.626747 | L155: 16.371124 | M155: 15.826997 | N155: 15.595498 | O155: 15.332464 | P155: 15.031796 | Q155: 14.685872 | R155: 14.375721 | S155: 14.085435 | T155: 13.6804 | U155: 13.172907 | V155: 12.664312 | W155: 11.571873 | X155: 10.497434 | Y155: 10.082233 | Z155: 9.624712 | AA155: 8.512741 | AB155: 8.116112 | AC155: 6.953617 | AD155: 6.718755 | AE155: 6.494057 | AF155: 6.213049 | AG155: 5.651477 | AH155: 5.036664 | AI155: 4.468789 | AJ155: 4.311365 | AK155: -0.043414
A156: ATS000:prk_Russia | B156: Commonwealth of Independent States | C156: 366.73007 | D156: 362.16339 | E156: 358.04761 | F156: 354.54102 | G156: 350.94769 | H156: 343.39807 | I156: 330.47455 | J156: 311.83542 | K156: 301.13846 | L156: 286.7088 | M156: 266.04059 | N156: 237.13159 | O156: 214.09508 | P156: 199.14362 | Q156: 187.73914 | R156: 179.78481 | S156: 170.89932 | T156: 158.15863 | U156: 148.52387 | V156: 131.19772 | W156: 122.19182 | X156: 103.1752 | Y156: 88.192566 | Z156: 70.151779 | AA156: 59.081429 | AB156: 56.756973 | AC156: 53.399414 | AD156: 48.075943 | AE156: 43.529442 | AF156: 38.032219 | AG156: 32.949371 | AH156: 21.919571 | AI156: 15.942092 | AJ156: 12.260004 | AK156: -0.1004
A157: ATS000:prk_Russia-nb | B157: Narrow Body Aircraft | C157: 248.06346 | D157: 245.62065 | E157: 243.89261 | F157: 242.56723 | G157: 241.1729 | H157: 236.26675 | I157: 226.26807 | J157: 210.24043 | K157: 203.2178 | L157: 193.17552 | M157: 178.11615 | N157: 156.07417 | O157: 142.05565 | P157: 130.03525 | Q157: 120.03561 | R157: 113.02367 | S157: 106.01903 | T157: 96.02182 | U157: 90.015007 | V157: 84.004944 | W157: 77.005486 | X157: 61.012421 | Y157: 49.02243 | Z157: 32.997028 | AA157: 21.966448 | AB157: 20.584732 | AC157: 19.264738 | AD157: 16.904213 | AE157: 13.395275 | AF157: 10.860992 | AG157: 7.815695 | AH157: 2.748837 | AI157: 0.808925 | AJ157: 0.089814 | AK157: -0.219098
A158: ATS000:prk_Russia-wb | B158: Wide Body Aircraft | C158: 37.542263 | D158: 35.530003 | E158: 33.320023 | F158: 31.385118 | G158: 29.505762 | H158: 27.264032 | I158: 24.835173 | J158: 22.830784 | K158: 19.910578 | L158: 16.465288 | M158: 12.263511 | N158: 7.280735 | O158: 2.028505 | P158: 0.359903 | Q158: 0.203005 | R158: 0.142662 | S158: 0.104994 | T158: 0.076284 | U158: 0.054706 | V158: 0.038716 | W158: 0.024097 | X158: 0.014158 | Y158: 0.009769 | Z158: 0.006643 | AA158: 0.004451 | AB158: 0 | AC158: 0 | AD158: 0 | AE158: 0 | AF158: 0 | AG158: 0 | AH158: 0 | AI158: 0 | AJ158: 0 | AK158: - -
A159: ATS000:prk_Russia-rj | B159: Regional Jets | C159: 81.124359 | D159: 81.012726 | E159: 80.834969 | F159: 80.588654 | G159: 80.269051 | H159: 79.867279 | I159: 79.3713 | J159: 78.764198 | K159: 78.010078 | L159: 77.067978 | M159: 75.660919 | N159: 73.77668 | O159: 70.010925 | P159: 68.748459 | Q159: 67.500534 | R159: 66.618477 | S159: 64.775291 | T159: 62.06052 | U159: 58.454155 | V159: 47.15406 | W159: 45.162231 | X159: 42.148628 | Y159: 39.160362 | Z159: 37.148109 | AA159: 37.110531 | AB159: 36.172241 | AC159: 34.134674 | AD159: 31.171728 | AE159: 30.134165 | AF159: 27.171227 | AG159: 25.133677 | AH159: 19.170732 | AI159: 15.133166 | AJ159: 12.17019 | AK159: -0.057518
A160: ATS000:prk_China | B160: China | C160: 62.964748 | D160: 51.990917 | E160: 43.564812 | F160: 38.621552 | G160: 36.381851 | H160: 32.528572 | I160: 27.776388 | J160: 25.689106 | K160: 24.017309 | L160: 20.541899 | M160: 19.258728 | N160: 18.158752 | O160: 17.229206 | P160: 16.454754 | Q160: 15.818563 | R160: 15.303254 | S160: 14.891682 | T160: 12.567548 | U160: 12.315842 | V160: 12.123116 | W160: 11.977623 | X160: 11.869335 | Y160: 11.789881 | Z160: 11.728744 | AA160: 10.670171 | AB160: 10.631293 | AC160: 10.622499 | AD160: 10.613349 | AE160: 10.609655 | AF160: 9.603394 | AG160: 7.603394 | AH160: 0 | AI160: 0 | AJ160: 0 | AK160: - -
A161: ATS000:prk_China-nb | B161: Narrow Body Aircraft | C161: 18.649 | D161: 18.165144 | E161: 17.480015 | F161: 17 | G161: 16.904232 | H161: 16.190647 | I161: 13.832685 | J161: 12.394759 | K161: 11.117878 | L161: 8.001068 | M161: 7.038759 | N161: 6.221759 | O161: 5.538242 | P161: 4.974702 | Q161: 4.516809 | R161: 4.15014 | S161: 3.860776 | T161: 2.635734 | U161: 2.463268 | V161: 2.33303 | W161: 2.236128 | X161: 2.1651 | Y161: 2.113814 | Z161: 2.07367 | AA161: 1.034123 | AB161: 1.006643 | AC161: 1.004451 | AD161: 1 | AE161: 1 | AF161: 0 | AG161: 0 | AH161: 0 | AI161: 0 | AJ161: 0 | AK161: - -
A162: ATS000:prk_China-wb | B162: Wide Body Aircraft | C162: 15.8 | D162: 13.547635 | E162: 11.544699 | F162: 10.072722 | G162: 8.291219 | H162: 5.734534 | I162: 3.340309 | J162: 2.690954 | K162: 2.296038 | L162: 1.937437 | M162: 1.616575 | N162: 1.333601 | O162: 1.087572 | P162: 0.876659 | Q162: 0.698362 | R162: 0.549721 | S162: 0.427512 | T162: 0.32842 | U162: 0.24918 | V162: 0.186693 | W162: 0.138101 | X162: 0.100841 | Y162: 0.072673 | Z162: 0.05168 | AA162: 0.032655 | AB162: 0.021257 | AC162: 0.014654 | AD162: 0.009956 | AE162: 0.006262 | AF162: 0 | AG162: 0 | AH162: 0 | AI162: 0 | AJ162: 0 | AK162: - -
A163: ATS000:prk_China-rj | B163: Regional Jets | C163: 28.515747 | D163: 20.278137 | E163: 14.5401 | F163: 11.548828 | G163: 11.186401 | H163: 10.603394 | I163: 10.603394 | J163: 10.603394 | K163: 10.603394 | L163: 10.603394 | M163: 10.603394 | N163: 10.603394 | O163: 10.603394 | P163: 10.603394 | Q163: 10.603394 | R163: 10.603394 | S163: 10.603394 | T163: 9.603394 | U163: 9.603394 | V163: 9.603394 | W163: 9.603394 | X163: 9.603394 | Y163: 9.603394 | Z163: 9.603394 | AA163: 9.603394 | AB163: 9.603394 | AC163: 9.603394 | AD163: 9.603394 | AE163: 9.603394 | AF163: 9.603394 | AG163: 7.603394 | AH163: 0 | AI163: 0 | AJ163: 0 | AK163: - -
A164: ATS000:prk_NE_Asia | B164: Northeast Asia | C164: 13.798964 | D164: 12.826821 | E164: 12.183221 | F164: 11.265993 | G164: 10.709548 | H164: 10.070929 | I164: 8.96828 | J164: 8.715976 | K164: 8.454715 | L164: 8.076572 | M164: 7.730955 | N164: 7.491329 | O164: 6.806841 | P164: 6.217837 | Q164: 6.105443 | R164: 6.071034 | S164: 6.009087 | T164: 6.006088 | U164: 6 | V164: 6 | W164: 6 | X164: 5.689813 | Y164: 5.026877 | Z164: 5 | AA164: 5 | AB164: 5 | AC164: 4 | AD164: 4 | AE164: 4 | AF164: 4 | AG164: 4 | AH164: 4 | AI164: 3.643515 | AJ164: 3 | AK164: -0.044389
A165: ATS000:prk_NE_Asia-nb | B165: Narrow Body Aircraft | C165: 7.958963 | D165: 7.879904 | E165: 7.77362 | F165: 7.610173 | G165: 7.339084 | H165: 6.778262 | I165: 5.74 | J165: 5.5402 | K165: 5.321125 | L165: 4.97638 | M165: 4.656813 | N165: 4.437205 | O165: 4.289001 | P165: 4.190169 | Q165: 4.086076 | R165: 4.057671 | S165: 4 | T165: 4 | U165: 4 | V165: 4 | W165: 4 | X165: 3.689813 | Y165: 3.026878 | Z165: 3 | AA165: 3 | AB165: 3 | AC165: 3 | AD165: 3 | AE165: 3 | AF165: 3 | AG165: 3 | AH165: 3 | AI165: 2.643515 | AJ165: 2 | AK165: -0.041944
