Workbook
Name asdf: About!#REF!
Name cpi_2010to2012: About!#REF!
Name cpi_2013to2012: About!#REF!
Name cpi_2014to2012: About!#REF!
Name cpi_2016to2012: About!#REF!
Name cpi_2017to2012: About!#REF!
Name cpi_2018to2012: About!#REF!
Name cpi_2019to2012: About!#REF!
Name cpi_2020to2012: About!#REF!
Name cpi_2021to2012: About!#REF!
Name H2_kg_to_MMBtu: [1]Constants!$D$7
Name kWh_to_Btu: [1]Constants!$D$4
Name US_salestax: About!#REF!

Sheet About
A1: BNVP BAU New Vehicle Price
A4: Source: | B4: Exchange Rates
B5: 2019
B6: https://www.exchangerates.org.uk/USD-IDR-spot-exchange-rates-history-2019.html
B8: Indonesia - Investments
B9: Import tariff (CBU vehicles)
B10: 2016
B11: https://www.indonesia-investments.com/news/todays-headlines/indonesian-demand-for-imported-cbu-cars-still-strong/item6501?
B13: Global Fleet
B14: VAT (PPN)
B15: 2025
B16: https://www.globalfleet.com/en/taxation-and-legislation/asia-pacific/analysis/tax-turbulence-guiding-fleets-through-indonesias-vat-storm?a=YHE11&t%5B0%5D=Indonesia&t%5B1%5D=Taxation&curl=1
B18: Global Fleet
B19: Luxury goods tax (PPnBM)
B20: 2025
B21: https://www.globalfleet.com/en/taxation-and-legislation/asia-pacific/analysis/tax-turbulence-guiding-fleets-through-indonesias-vat-storm?a=YHE11&t%5B0%5D=Indonesia&t%5B1%5D=Taxation&curl=1
B23: Mordor Intellligence
B24: Dealer margin & logistics
B25: 2024
B26: https://www.mordorintelligence.com/industry-reports/indonesia-freight-logistics-market
B28: World Bank
B29: Final Consumption Expenditure
B30: 2010-2023
B31: https://databank.worldbank.org/reports.aspx?source=2&series=NE.CON.TOTL.CD&country=
A34: Currency Year
A35: The figures from the Center for Automotive Research come from a 2010 Automotive Yearbook
A36: and therefore are likely in 2010 dollars.
A37: The figures from TruckerToTrucker were collected in early 2015 and therefore use 2015 | B37: 2014 to 2012, for TruckerToTrucker
A38: dollars, but because we don't have a 2015 annual CPI-U figure available yet, we use 2014. | B38: 2013 to 2012, for American Public Transit Association
A39: 0.987 | B39: 2013 to 2012
A40: 0.953 | B40: 2016 to 2012
A41: 0.9366596 | B41: 2017 to 2012
A42: 0.914 | B42: 2018 to 2012
A43: 0.89805482 | B43: 2019 to 2012
A44: 0.88711067 | B44: 2020 to 2012
A45: 0.84730413 | B45: 2021 to 2012
A46: See "cpi.xlsx" in the InputData folder for source information.
A50: Note: | B50: To estimate the adjusted vehicle price for Indonesia based on a U.S. vehicle price, we compute an adjustment factor that combines two key elements: the FCE-based scaling and a correction factor accounting for country-specific cost components. First, we calculate the ratio of Final Consumption Expenditure (FCE) per capita between Indonesia and the U.S. to reflect differences in purchasing power and spending capacity. This gives a base scaling factor. Then, apply a correction factor to capture additional costs associated with importing vehicles into Indonesia. This correction factor is the sum of typical vehicle-related costs, such as import tariffs on completely built-up (CBU) vehicles, value-added tax (VAT or PPN), luxury goods tax (PPnBM), and dealer margins or logistics fees. For passenger cars, instead of using FCE, we directly estimate the scaling by comparing average Indonesian passenger car prices to U.S. passenger vehicle prices.

Sheet NVP-Indonesia
A1: Year | B1: 2011 | C1: 2012 | D1: 2013 | E1: 2014 | F1: 2015 | G1: 2016 | H1: 2017 | I1: 2018 | J1: 2019 | K1: 2020 | L1: 2021 | M1: 2022 | N1: 2023
A2: Average new car price (million Rupiah) | B2: 193 | C2: =ROUNDUP(($B$2+(($N$2-$B$2)/($N$1-$B$1))*(C1-$B$1)),0) -> 206 | D2: =ROUNDUP(($B$2+(($N$2-$B$2)/($N$1-$B$1))*(D1-$B$1)),0) -> 219 | E2: =ROUNDUP(($B$2+(($N$2-$B$2)/($N$1-$B$1))*(E1-$B$1)),0) -> 232 | F2: =ROUNDUP(($B$2+(($N$2-$B$2)/($N$1-$B$1))*(F1-$B$1)),0) -> 245 | G2: =ROUNDUP(($B$2+(($N$2-$B$2)/($N$1-$B$1))*(G1-$B$1)),0) -> 258 | H2: =ROUNDUP(($B$2+(($N$2-$B$2)/($N$1-$B$1))*(H1-$B$1)),0) -> 270 | I2: =ROUNDUP(($B$2+(($N$2-$B$2)/($N$1-$B$1))*(I1-$B$1)),0) -> 283 | J2: =ROUNDUP(($B$2+(($N$2-$B$2)/($N$1-$B$1))*(J1-$B$1)),0) -> 296 | ... M2: =ROUNDUP(($B$2+(($N$2-$B$2)/($N$1-$B$1))*(M1-$B$1)),0) -> 335 | N2: 347
A3: Million Rupiah to Rupiah | B3: 1000000
A4: 1 USD to Rupiah (2019) | B4: 14135.41
A5: 1 Rupiah to USD (2019) | B5: =1/B4 -> 7.0744322e-05
A6: Average new car price (USD) | B6: =ROUNDUP(B2*$B$3*$B$5,0) -> 13654 | C6: =ROUNDUP(C2*$B$3*$B$5,0) -> 14574 | D6: =ROUNDUP(D2*$B$3*$B$5,0) -> 15494 | E6: =ROUNDUP(E2*$B$3*$B$5,0) -> 16413 | F6: =ROUNDUP(F2*$B$3*$B$5,0) -> 17333 | G6: =ROUNDUP(G2*$B$3*$B$5,0) -> 18253 | H6: =ROUNDUP(H2*$B$3*$B$5,0) -> 19101 | I6: =ROUNDUP(I2*$B$3*$B$5,0) -> 20021 | ... N6: =ROUNDUP(N2*$B$3*$B$5,0) -> 24549
A8: Percentage increase overtime | B8: 0.05
A10: Year | B10: 2020 | C10: 2021 | D10: 2022 | E10: 2023 | F10: 2024 | G10: 2025 | H10: 2026 | I10: 2027 | J10: 2028 | K10: 2029 | L10: 2030 | M10: 2031 | N10: 2032 | O10: 2033 | P10: 2034 | Q10: 2035 | R10: 2036 | S10: 2037 | T10: 2038 | U10: 2039 | V10: 2040 | W10: 2041 | X10: 2042 | Y10: 2043 | Z10: 2044 | AA10: 2045 | AB10: 2046 | AC10: 2047 | AD10: 2048 | AE10: 2049 | AF10: 2050 | AG10: 2051 | AH10: 2052 | AI10: 2053 | AJ10: 2054 | AK10: 2055 | AL10: 2056 | AM10: 2057 | AN10: 2058 | AO10: 2059 | AP10: 2060 | AQ10: 2061 | AR10: 2062 | AS10: 2063 | AT10: 2064 | AU10: 2065 | AV10: 2066 | AW10: 2067 | AX10: 2068 | AY10: 2069 | AZ10: 2070
A11: Average new car price (2012 USD) - Percentage Increase | B11: =K6 -> 21860 | C11: =L6 -> 22780 | D11: =M6 -> 23700 | E11: =N6 -> 24549 | F11: =ROUNDUP(E11+E11*$B$8, 0) -> 25777 | G11: =ROUNDUP(F11+F11*$B$8, 0) -> 27066 | H11: =ROUNDUP(G11+G11*$B$8, 0) -> 28420 | I11: =ROUNDUP(H11+H11*$B$8, 0) -> 29841 | J11: =ROUNDUP(I11+I11*$B$8, 0) -> 31334 | K11: =ROUNDUP(J11+J11*$B$8, 0) -> 32901 | L11: =ROUNDUP(K11+K11*$B$8, 0) -> 34547 | M11: =ROUNDUP(L11+L11*$B$8, 0) -> 36275 | ... AZ11: =ROUNDUP(AY11+AY11*$B$8, 0) -> 243261
A12: Average new car price (2012 USD) - Linear Forecast | B12: =B11 -> 21860 | C12: =C11 -> 22780 | D12: =D11 -> 23700 | E12: =E11 -> 24549 | F12: =ROUNDUP(_xlfn.FORECAST.LINEAR(F10,$B$12:$E$12,$B$10:$E$10), 0) -> 25469 | G12: =ROUNDUP(_xlfn.FORECAST.LINEAR(G10,$B$12:$E$12,$B$10:$E$10), 0) -> 26368 | H12: =ROUNDUP(_xlfn.FORECAST.LINEAR(H10,$B$12:$E$12,$B$10:$E$10), 0) -> 27267 | I12: =ROUNDUP(_xlfn.FORECAST.LINEAR(I10,$B$12:$E$12,$B$10:$E$10), 0) -> 28166 | J12: =ROUNDUP(_xlfn.FORECAST.LINEAR(J10,$B$12:$E$12,$B$10:$E$10), 0) -> 29064 | K12: =ROUNDUP(_xlfn.FORECAST.LINEAR(K10,$B$12:$E$12,$B$10:$E$10), 0) -> 29963 | L12: =ROUNDUP(_xlfn.FORECAST.LINEAR(L10,$B$12:$E$12,$B$10:$E$10), 0) -> 30862 | M12: =ROUNDUP(_xlfn.FORECAST.LINEAR(M10,$B$12:$E$12,$B$10:$E$10), 0) -> 31760 | ... AZ12: =ROUNDUP(_xlfn.FORECAST.LINEAR(AZ10,$B$12:$E$12,$B$10:$E$10), 0) -> 66810
A14: US New Vehicle Price
A15: BNVP-LDVs-psgr
A16: Price ($/vehicle) | B16: 2020 | C16: 2021 | D16: 2022 | E16: 2023 | F16: 2024 | G16: 2025 | H16: 2026 | I16: 2027 | J16: 2028 | K16: 2029 | L16: 2030 | M16: 2031 | N16: 2032 | O16: 2033 | P16: 2034 | Q16: 2035 | R16: 2036 | S16: 2037 | T16: 2038 | U16: 2039 | V16: 2040 | W16: 2041 | X16: 2042 | Y16: 2043 | Z16: 2044 | AA16: 2045 | AB16: 2046 | AC16: 2047 | AD16: 2048 | AE16: 2049 | AF16: 2050 | AG16: 2051 | AH16: 2052 | AI16: 2053 | AJ16: 2054 | AK16: 2055 | AL16: 2056 | AM16: 2057 | AN16: 2058 | AO16: 2059 | AP16: 2060 | AQ16: 2061 | AR16: 2062 | AS16: 2063 | AT16: 2064 | AU16: 2065 | AV16: 2066 | AW16: 2067 | AX16: 2068 | AY16: 2069 | AZ16: 2070
A17: battery electric vehicle | B17: 49825.128 | C17: 44974.651 | D17: 44014.219 | E17: 42953.309 | F17: 42057.542 | G17: 41521.193 | H17: 40991.55 | I17: 40480.256 | J17: 40050.501 | K17: 39618.7 | L17: 39193.065 | M17: 38851.711 | N17: 38445.374 | O17: 38068.778 | P17: 37707.033 | Q17: 37365.394 | R17: 37011.736 | S17: 36641.185 | T17: 36270.533 | U17: 35909.696 | V17: 35548.372 | W17: 35209.229 | X17: 34885.052 | Y17: 34557.402 | Z17: 34243.998 | AA17: 33954.038 | AB17: 33631.495 | AC17: 33320.219 | AD17: 33037.653 | AE17: 32722.528 | AF17: 32420.62 | AG17: 31015.295 | AH17: 30583.827 | AI17: 30152.359 | AJ17: 29720.891 | AK17: 29289.424 | AL17: 28857.956 | AM17: 28426.488 | AN17: 27995.02 | AO17: 27563.552 | AP17: 27132.085 | AQ17: 26700.617 | AR17: 26269.149 | AS17: 25837.681 | AT17: 25406.213 | AU17: 24974.746 | AV17: 24543.278 | AW17: 24111.81 | AX17: 23680.342 | AY17: 23248.875 | AZ17: 22817.407
A18: natural gas vehicle | B18: 36759.75 | C18: 36495.301 | D18: 36652.899 | E18: 36898.855 | F18: 37088.42 | G18: 37274.214 | H18: 37445.623 | I18: 37600.873 | J18: 37766.33 | K18: 37923.877 | L18: 38069.817 | M18: 38227.33 | N18: 38348.863 | O18: 38510.498 | P18: 38604.697 | Q18: 38681.121 | R18: 38748.487 | S18: 38814.705 | T18: 38876.265 | U18: 38939.471 | V18: 38983.894 | W18: 39034.301 | X18: 39076.492 | Y18: 39111.674 | Z18: 39147.674 | AA18: 39181.697 | AB18: 39212.991 | AC18: 39245.837 | AD18: 39278.913 | AE18: 39308.052 | AF18: 39337.439 | AG18: 39864.611 | AH18: 39959.684 | AI18: 40054.758 | AJ18: 40149.832 | AK18: 40244.906 | AL18: 40339.979 | AM18: 40435.053 | AN18: 40530.127 | AO18: 40625.2 | AP18: 40720.274 | AQ18: 40815.348 | AR18: 40910.422 | AS18: 41005.495 | AT18: 41100.569 | AU18: 41195.643 | AV18: 41290.717 | AW18: 41385.79 | AX18: 41480.864 | AY18: 41575.938 | AZ18: 41671.011
A19: gasoline vehicle | B19: 32342.636 | C19: 31217.363 | D19: 31436.447 | E19: 31582.449 | F19: 31757.9 | G19: 31937.089 | H19: 32051.631 | I19: 32113.77 | J19: 32185.62 | K19: 32243.903 | L19: 32274.622 | M19: 32331.769 | N19: 32347.685 | O19: 32381.444 | P19: 32396.375 | Q19: 32409.373 | R19: 32401.629 | S19: 32380.855 | T19: 32354.526 | U19: 32332.246 | V19: 32299.489 | W19: 32277.911 | X19: 32262.981 | Y19: 32240.582 | Z19: 32222.923 | AA19: 32218.675 | AB19: 32189.558 | AC19: 32165.915 | AD19: 32160.914 | AE19: 32130.598 | AF19: 32106.973 | AG19: 32390.103 | AH19: 32404.896 | AI19: 32419.689 | AJ19: 32434.482 | AK19: 32449.275 | AL19: 32464.068 | AM19: 32478.861 | AN19: 32493.654 | AO19: 32508.447 | AP19: 32523.24 | AQ19: 32538.033 | AR19: 32552.826 | AS19: 32567.619 | AT19: 32582.412 | AU19: 32597.205 | AV19: 32611.998 | AW19: 32626.791 | AX19: 32641.584 | AY19: 32656.377 | AZ19: 32671.17
A20: diesel vehicle | B20: 35443.546 | C20: 34572.73 | D20: 34849.204 | E20: 34983.821 | F20: 35151.364 | G20: 35326.619 | H20: 35410.191 | I20: 35435.494 | J20: 35474.588 | K20: 35499.908 | L20: 35487.978 | M20: 35511.964 | N20: 35480.242 | O20: 35474.108 | P20: 35461.937 | Q20: 35455.995 | R20: 35422.177 | S20: 35366.464 | T20: 35302.941 | U20: 35244.577 | V20: 35170.962 | W20: 35114.649 | X20: 35067.006 | Y20: 35011.117 | Z20: 34962.564 | AA20: 34932.466 | AB20: 34867.704 | AC20: 34811.011 | AD20: 34778.001 | AE20: 34711.17 | AF20: 34656.058 | AG20: 34943.404 | AH20: 34928.902 | AI20: 34914.4 | AJ20: 34899.898 | AK20: 34885.396 | AL20: 34870.893 | AM20: 34856.391 | AN20: 34841.889 | AO20: 34827.387 | AP20: 34812.885 | AQ20: 34798.383 | AR20: 34783.881 | AS20: 34769.379 | AT20: 34754.877 | AU20: 34740.375 | AV20: 34725.873 | AW20: 34711.371 | AX20: 34696.868 | AY20: 34682.366 | AZ20: 34667.864
A21: plugin hybrid vehicle | B21: 36885.812 | C21: 37390.063 | D21: 37336.116 | E21: 37519.774 | F21: 37560.849 | G21: 37672.814 | H21: 37718.564 | I21: 37744.624 | J21: 37799.089 | K21: 37869.295 | L21: 37947.783 | M21: 38048.195 | N21: 38134.621 | O21: 38250.401 | P21: 38309.624 | Q21: 38356.758 | R21: 38399.036 | S21: 38433.322 | T21: 38455.444 | U21: 38471.88 | V21: 38470.609 | W21: 38476.534 | X21: 38473.613 | Y21: 38464.26 | Z21: 38454.964 | AA21: 38445.041 | AB21: 38433.395 | AC21: 38423.684 | AD21: 38414.275 | AE21: 38406.062 | AF21: 38395.608 | AG21: 38782.846 | AH21: 38825.399 | AI21: 38867.951 | AJ21: 38910.504 | AK21: 38953.056 | AL21: 38995.609 | AM21: 39038.162 | AN21: 39080.714 | AO21: 39123.267 | AP21: 39165.82 | AQ21: 39208.372 | AR21: 39250.925 | AS21: 39293.478 | AT21: 39336.03 | AU21: 39378.583 | AV21: 39421.136 | AW21: 39463.688 | AX21: 39506.241 | AY21: 39548.794 | AZ21: 39591.346
A22: LPG vehicle | B22: 35929.333 | C22: 36517.782 | D22: 36483.97 | E22: 36547.532 | F22: 36633.721 | G22: 36794.3 | H22: 36928.46 | I22: 36997.316 | J22: 37058.276 | K22: 37124.274 | L22: 37186.148 | M22: 37247.67 | N22: 37300.144 | O22: 37363.114 | P22: 37405.731 | Q22: 37444.211 | R22: 37483.983 | S22: 37524.069 | T22: 37561.633 | U22: 37601.442 | V22: 37635.684 | W22: 37670.003 | X22: 37704.042 | Y22: 37736.312 | Z22: 37769.703 | AA22: 37804.107 | AB22: 37838.223 | AC22: 37873.503 | AD22: 37908.731 | AE22: 37944.389 | AF22: 37966.872 | AG22: 38189.454 | AH22: 38243.665 | AI22: 38297.875 | AJ22: 38352.086 | AK22: 38406.296 | AL22: 38460.507 | AM22: 38514.717 | AN22: 38568.928 | AO22: 38623.138 | AP22: 38677.349 | AQ22: 38731.559 | AR22: 38785.77 | AS22: 38839.98 | AT22: 38894.191 | AU22: 38948.401 | AV22: 39002.612 | AW22: 39056.822 | AX22: 39111.032 | AY22: 39165.243 | AZ22: 39219.453
A23: hydrogen vehicle | B23: 65082.118 | C23: 65067.963 | D23: 63660.552 | E23: 62421.595 | F23: 61170.116 | G23: 59874.757 | H23: 58736.772 | I23: 57689.483 | J23: 56690.542 | K23: 55738.719 | L23: 54831.315 | M23: 53967.601 | N23: 53140.492 | O23: 52357.768 | P23: 51589.549 | Q23: 50852.967 | R23: 50151.391 | S23: 49482.28 | T23: 48844.264 | U23: 48236.533 | V23: 47655.606 | W23: 47102.665 | X23: 46575.275 | Y23: 46072.297 | Z23: 45593.078 | AA23: 45136.282 | AB23: 44700.604 | AC23: 44285.587 | AD23: 43889.741 | AE23: 43512.798 | AF23: 43136.219 | AG23: 40253.789 | AH23: 39509.072 | AI23: 38764.355 | AJ23: 38019.639 | AK23: 37274.922 | AL23: 36530.205 | AM23: 35785.489 | AN23: 35040.772 | AO23: 34296.055 | AP23: 33551.339 | AQ23: 32806.622 | AR23: 32061.905 | AS23: 31317.189 | AT23: 30572.472 | AU23: 29827.755 | AV23: 29083.039 | AW23: 28338.322 | AX23: 27593.605 | AY23: 26848.889 | AZ23: 26104.172
A25: BNVP-LDVs-frgt
A26: Price ($/vehicle) | B26: 2020 | C26: 2021 | D26: 2022 | E26: 2023 | F26: 2024 | G26: 2025 | H26: 2026 | I26: 2027 | J26: 2028 | K26: 2029 | L26: 2030 | M26: 2031 | N26: 2032 | O26: 2033 | P26: 2034 | Q26: 2035 | R26: 2036 | S26: 2037 | T26: 2038 | U26: 2039 | V26: 2040 | W26: 2041 | X26: 2042 | Y26: 2043 | Z26: 2044 | AA26: 2045 | AB26: 2046 | AC26: 2047 | AD26: 2048 | AE26: 2049 | AF26: 2050 | AG26: 2051 | AH26: 2052 | AI26: 2053 | AJ26: 2054 | AK26: 2055 | AL26: 2056 | AM26: 2057 | AN26: 2058 | AO26: 2059 | AP26: 2060 | AQ26: 2061 | AR26: 2062 | AS26: 2063 | AT26: 2064 | AU26: 2065 | AV26: 2066 | AW26: 2067 | AX26: 2068 | AY26: 2069 | AZ26: 2070
A27: battery electric vehicle | B27: 74481.202 | C27: 74481.202 | D27: 74481.202 | E27: 74481.202 | F27: 74481.202 | G27: 74481.202 | H27: 74481.202 | I27: 74481.202 | J27: 74481.202 | K27: 74481.202 | L27: 74481.202 | M27: 74481.202 | N27: 74481.202 | O27: 74481.202 | P27: 74481.202 | Q27: 74481.202 | R27: 74481.202 | S27: 74481.202 | T27: 74481.202 | U27: 74481.202 | V27: 74481.202 | W27: 74481.202 | X27: 74481.202 | Y27: 74481.202 | Z27: 74481.202 | AA27: 74481.202 | AB27: 74481.202 | AC27: 74481.202 | AD27: 74481.202 | AE27: 74481.202 | AF27: 74481.202 | AG27: 74481.202 | AH27: 74481.202 | AI27: 74481.202 | AJ27: 74481.202 | AK27: 74481.202 | AL27: 74481.202 | AM27: 74481.202 | AN27: 74481.202 | AO27: 74481.202 | AP27: 74481.202 | AQ27: 74481.202 | AR27: 74481.202 | AS27: 74481.202 | AT27: 74481.202 | AU27: 74481.202 | AV27: 74481.202 | AW27: 74481.202 | AX27: 74481.202 | AY27: 74481.202 | AZ27: 74481.202
A28: natural gas vehicle | B28: 51983.088 | C28: 51609.123 | D28: 51831.988 | E28: 52179.801 | F28: 52447.871 | G28: 52710.607 | H28: 52953.003 | I28: 53172.546 | J28: 53406.524 | K28: 53629.316 | L28: 53835.695 | M28: 54058.438 | N28: 54230.301 | O28: 54458.874 | P28: 54592.084 | Q28: 54700.157 | R28: 54795.422 | S28: 54889.063 | T28: 54976.117 | U28: 55065.499 | V28: 55128.319 | W28: 55199.6 | X28: 55259.265 | Y28: 55309.016 | Z28: 55359.925 | AA28: 55408.038 | AB28: 55452.292 | AC28: 55498.74 | AD28: 55545.514 | AE28: 55586.72 | AF28: 55628.278 | AG28: 56373.767 | AH28: 56508.214 | AI28: 56642.66 | AJ28: 56777.107 | AK28: 56911.554 | AL28: 57046 | AM28: 57180.447 | AN28: 57314.894 | AO28: 57449.34 | AP28: 57583.787 | AQ28: 57718.234 | AR28: 57852.68 | AS28: 57987.127 | AT28: 58121.574 | AU28: 58256.02 | AV28: 58390.467 | AW28: 58524.914 | AX28: 58659.36 | AY28: 58793.807 | AZ28: 58928.254
A29: gasoline vehicle | B29: 45736.713 | C29: 45736.713 | D29: 45736.713 | E29: 45736.713 | F29: 45736.713 | G29: 45736.713 | H29: 45736.713 | I29: 45736.713 | J29: 45736.713 | K29: 45736.713 | L29: 45736.713 | M29: 45736.713 | N29: 45736.713 | O29: 45736.713 | P29: 45736.713 | Q29: 45736.713 | R29: 45736.713 | S29: 45736.713 | T29: 45736.713 | U29: 45736.713 | V29: 45736.713 | W29: 45736.713 | X29: 45736.713 | Y29: 45736.713 | Z29: 45736.713 | AA29: 45736.713 | AB29: 45736.713 | AC29: 45736.713 | AD29: 45736.713 | AE29: 45736.713 | AF29: 45736.713 | AG29: 45736.713 | AH29: 45736.713 | AI29: 45736.713 | AJ29: 45736.713 | AK29: 45736.713 | AL29: 45736.713 | AM29: 45736.713 | AN29: 45736.713 | AO29: 45736.713 | AP29: 45736.713 | AQ29: 45736.713 | AR29: 45736.713 | AS29: 45736.713 | AT29: 45736.713 | AU29: 45736.713 | AV29: 45736.713 | AW29: 45736.713 | AX29: 45736.713 | AY29: 45736.713 | AZ29: 45736.713
A30: diesel vehicle | B30: 50818.57 | C30: 50818.57 | D30: 50818.57 | E30: 50818.57 | F30: 50818.57 | G30: 50818.57 | H30: 50818.57 | I30: 50818.57 | J30: 50818.57 | K30: 50818.57 | L30: 50818.57 | M30: 50818.57 | N30: 50818.57 | O30: 50818.57 | P30: 50818.57 | Q30: 50818.57 | R30: 50818.57 | S30: 50818.57 | T30: 50818.57 | U30: 50818.57 | V30: 50818.57 | W30: 50818.57 | X30: 50818.57 | Y30: 50818.57 | Z30: 50818.57 | AA30: 50818.57 | AB30: 50818.57 | AC30: 50818.57 | AD30: 50818.57 | AE30: 50818.57 | AF30: 50818.57 | AG30: 50818.57 | AH30: 50818.57 | AI30: 50818.57 | AJ30: 50818.57 | AK30: 50818.57 | AL30: 50818.57 | AM30: 50818.57 | AN30: 50818.57 | AO30: 50818.57 | AP30: 50818.57 | AQ30: 50818.57 | AR30: 50818.57 | AS30: 50818.57 | AT30: 50818.57 | AU30: 50818.57 | AV30: 50818.57 | AW30: 50818.57 | AX30: 50818.57 | AY30: 50818.57 | AZ30: 50818.57
A31: plugin hybrid vehicle | B31: 52161.357 | C31: 52874.433 | D31: 52798.145 | E31: 53057.862 | F31: 53115.947 | G31: 53274.28 | H31: 53338.977 | I31: 53375.829 | J31: 53452.85 | K31: 53552.129 | L31: 53663.122 | M31: 53805.119 | N31: 53927.335 | O31: 54091.064 | P31: 54174.813 | Q31: 54241.466 | R31: 54301.253 | S31: 54349.738 | T31: 54381.021 | U31: 54404.263 | V31: 54402.467 | W31: 54410.845 | X31: 54406.715 | Y31: 54393.489 | Z31: 54380.342 | AA31: 54366.31 | AB31: 54349.841 | AC31: 54336.108 | AD31: 54322.803 | AE31: 54311.189 | AF31: 54296.405 | AG31: 54844.01 | AH31: 54904.185 | AI31: 54964.36 | AJ31: 55024.535 | AK31: 55084.71 | AL31: 55144.885 | AM31: 55205.06 | AN31: 55265.235 | AO31: 55325.41 | AP31: 55385.585 | AQ31: 55445.76 | AR31: 55505.935 | AS31: 55566.11 | AT31: 55626.285 | AU31: 55686.46 | AV31: 55746.635 | AW31: 55806.81 | AX31: 55866.985 | AY31: 55927.16 | AZ31: 55987.335
A32: LPG vehicle | B32: 50808.77 | C32: 51640.914 | D32: 51593.1 | E32: 51682.984 | F32: 51804.867 | G32: 52031.947 | H32: 52221.667 | I32: 52319.038 | J32: 52405.243 | K32: 52498.573 | L32: 52586.071 | M32: 52673.071 | N32: 52747.277 | O32: 52836.324 | P32: 52896.59 | Q32: 52951.005 | R32: 53007.249 | S32: 53063.936 | T32: 53117.056 | U32: 53173.35 | V32: 53221.773 | W32: 53270.305 | X32: 53318.44 | Y32: 53364.075 | Z32: 53411.295 | AA32: 53459.946 | AB32: 53508.19 | AC32: 53558.081 | AD32: 53607.897 | AE32: 53658.322 | AF32: 53690.117 | AG32: 54004.877 | AH32: 54081.538 | AI32: 54158.198 | AJ32: 54234.859 | AK32: 54311.52 | AL32: 54388.181 | AM32: 54464.841 | AN32: 54541.502 | AO32: 54618.163 | AP32: 54694.823 | AQ32: 54771.484 | AR32: 54848.145 | AS32: 54924.806 | AT32: 55001.466 | AU32: 55078.127 | AV32: 55154.788 | AW32: 55231.448 | AX32: 55308.109 | AY32: 55384.77 | AZ32: 55461.43
A33: hydrogen vehicle | B33: 93314.03 | C33: 93293.735 | D33: 91275.805 | E33: 89499.402 | F33: 87705.045 | G33: 85847.774 | H33: 84216.142 | I33: 82714.551 | J33: 81282.281 | K33: 79917.567 | L33: 78616.541 | M33: 77378.157 | N33: 76192.258 | O33: 75069.996 | P33: 73968.533 | Q33: 72912.43 | R33: 71906.517 | S33: 70947.153 | T33: 70032.372 | U33: 69161.015 | V33: 68328.087 | W33: 67535.288 | X33: 66779.121 | Y33: 66057.957 | Z33: 65370.857 | AA33: 64715.909 | AB33: 64091.238 | AC33: 63496.192 | AD33: 62928.631 | AE33: 62388.175 | AF33: 61848.24 | AG33: 57715.443 | AH33: 56647.677 | AI33: 55579.91 | AJ33: 54512.143 | AK33: 53444.377 | AL33: 52376.61 | AM33: 51308.843 | AN33: 50241.077 | AO33: 49173.31 | AP33: 48105.543 | AQ33: 47037.777 | AR33: 45970.01 | AS33: 44902.243 | AT33: 43834.477 | AU33: 42766.71 | AV33: 41698.943 | AW33: 40631.177 | AX33: 39563.41 | AY33: 38495.643 | AZ33: 37427.877
A35: BNVP-HDVs-psgr
A36: Price ($/vehicle) | B36: 2020 | C36: 2021 | D36: 2022 | E36: 2023 | F36: 2024 | G36: 2025 | H36: 2026 | I36: 2027 | J36: 2028 | K36: 2029 | L36: 2030 | M36: 2031 | N36: 2032 | O36: 2033 | P36: 2034 | Q36: 2035 | R36: 2036 | S36: 2037 | T36: 2038 | U36: 2039 | V36: 2040 | W36: 2041 | X36: 2042 | Y36: 2043 | Z36: 2044 | AA36: 2045 | AB36: 2046 | AC36: 2047 | AD36: 2048 | AE36: 2049 | AF36: 2050 | AG36: 2051 | AH36: 2052 | AI36: 2053 | AJ36: 2054 | AK36: 2055 | AL36: 2056 | AM36: 2057 | AN36: 2058 | AO36: 2059 | AP36: 2060 | AQ36: 2061 | AR36: 2062 | AS36: 2063 | AT36: 2064 | AU36: 2065 | AV36: 2066 | AW36: 2067 | AX36: 2068 | AY36: 2069 | AZ36: 2070
A37: battery electric vehicle | B37: 787140.4 | C37: 787140.4 | D37: 787140.4 | E37: 787140.4 | F37: 787140.4 | G37: 787140.4 | H37: 787140.4 | I37: 787140.4 | J37: 787140.4 | K37: 787140.4 | L37: 787140.4 | M37: 787140.4 | N37: 787140.4 | O37: 787140.4 | P37: 787140.4 | Q37: 787140.4 | R37: 787140.4 | S37: 787140.4 | T37: 787140.4 | U37: 787140.4 | V37: 787140.4 | W37: 787140.4 | X37: 787140.4 | Y37: 787140.4 | Z37: 787140.4 | AA37: 787140.4 | AB37: 787140.4 | AC37: 787140.4 | AD37: 787140.4 | AE37: 787140.4 | AF37: 787140.4 | AG37: 787140.4 | AH37: 787140.4 | AI37: 787140.4 | AJ37: 787140.4 | AK37: 787140.4 | AL37: 787140.4 | AM37: 787140.4 | AN37: 787140.4 | AO37: 787140.4 | AP37: 787140.4 | AQ37: 787140.4 | AR37: 787140.4 | AS37: 787140.4 | AT37: 787140.4 | AU37: 787140.4 | AV37: 787140.4 | AW37: 787140.4 | AX37: 787140.4 | AY37: 787140.4 | AZ37: 787140.4
A38: natural gas vehicle | B38: 543571.43 | C38: 539660.99 | D38: 541991.42 | E38: 545628.4 | F38: 548431.52 | G38: 551178.88 | H38: 553713.53 | I38: 556009.23 | J38: 558455.87 | K38: 560785.54 | L38: 562943.58 | M38: 565272.73 | N38: 567069.86 | O38: 569459.98 | P38: 570852.91 | Q38: 571983 | R38: 572979.15 | S38: 573958.33 | T38: 574868.62 | U38: 575803.27 | V38: 576460.15 | W38: 577205.52 | X38: 577829.42 | Y38: 578349.65 | Z38: 578881.99 | AA38: 579385.1 | AB38: 579847.85 | AC38: 580333.54 | AD38: 580822.64 | AE38: 581253.52 | AF38: 581688.07 | AG38: 589483.43 | AH38: 590889.3 | AI38: 592295.17 | AJ38: 593701.03 | AK38: 595106.9 | AL38: 596512.77 | AM38: 597918.64 | AN38: 599324.51 | AO38: 600730.38 | AP38: 602136.24 | AQ38: 603542.11 | AR38: 604947.98 | AS38: 606353.85 | AT38: 607759.72 | AU38: 609165.58 | AV38: 610571.45 | AW38: 611977.32 | AX38: 613383.19 | AY38: 614789.06 | AZ38: 616194.93
A39: gasoline vehicle | B39: 425813.12 | C39: 425813.12 | D39: 425813.12 | E39: 425813.12 | F39: 425813.12 | G39: 425813.12 | H39: 425813.12 | I39: 425813.12 | J39: 425813.12 | K39: 425813.12 | L39: 425813.12 | M39: 425813.12 | N39: 425813.12 | O39: 425813.12 | P39: 425813.12 | Q39: 425813.12 | R39: 425813.12 | S39: 425813.12 | T39: 425813.12 | U39: 425813.12 | V39: 425813.12 | W39: 425813.12 | X39: 425813.12 | Y39: 425813.12 | Z39: 425813.12 | AA39: 425813.12 | AB39: 425813.12 | AC39: 425813.12 | AD39: 425813.12 | AE39: 425813.12 | AF39: 425813.12 | AG39: 425813.12 | AH39: 425813.12 | AI39: 425813.12 | AJ39: 425813.12 | AK39: 425813.12 | AL39: 425813.12 | AM39: 425813.12 | AN39: 425813.12 | AO39: 425813.12 | AP39: 425813.12 | AQ39: 425813.12 | AR39: 425813.12 | AS39: 425813.12 | AT39: 425813.12 | AU39: 425813.12 | AV39: 425813.12 | AW39: 425813.12 | AX39: 425813.12 | AY39: 425813.12 | AZ39: 425813.12
A40: diesel vehicle | B40: 425813.12 | C40: 425813.12 | D40: 425813.12 | E40: 425813.12 | F40: 425813.12 | G40: 425813.12 | H40: 425813.12 | I40: 425813.12 | J40: 425813.12 | K40: 425813.12 | L40: 425813.12 | M40: 425813.12 | N40: 425813.12 | O40: 425813.12 | P40: 425813.12 | Q40: 425813.12 | R40: 425813.12 | S40: 425813.12 | T40: 425813.12 | U40: 425813.12 | V40: 425813.12 | W40: 425813.12 | X40: 425813.12 | Y40: 425813.12 | Z40: 425813.12 | AA40: 425813.12 | AB40: 425813.12 | AC40: 425813.12 | AD40: 425813.12 | AE40: 425813.12 | AF40: 425813.12 | AG40: 425813.12 | AH40: 425813.12 | AI40: 425813.12 | AJ40: 425813.12 | AK40: 425813.12 | AL40: 425813.12 | AM40: 425813.12 | AN40: 425813.12 | AO40: 425813.12 | AP40: 425813.12 | AQ40: 425813.12 | AR40: 425813.12 | AS40: 425813.12 | AT40: 425813.12 | AU40: 425813.12 | AV40: 425813.12 | AW40: 425813.12 | AX40: 425813.12 | AY40: 425813.12 | AZ40: 425813.12
A41: plugin hybrid vehicle | B41: 616714.29 | C41: 625145.13 | D41: 624243.15 | E41: 627313.84 | F41: 628000.59 | G41: 629872.59 | H41: 630637.52 | I41: 631073.23 | J41: 631983.87 | K41: 633157.67 | L41: 634469.96 | M41: 636148.81 | N41: 637593.8 | O41: 639529.6 | P41: 640519.78 | Q41: 641307.83 | R41: 642014.7 | S41: 642587.95 | T41: 642957.82 | U41: 643232.62 | V41: 643211.38 | W41: 643310.43 | X41: 643261.6 | Y41: 643105.23 | Z41: 642949.79 | AA41: 642783.89 | AB41: 642589.17 | AC41: 642426.81 | AD41: 642269.5 | AE41: 642132.18 | AF41: 641957.39 | AG41: 648431.84 | AH41: 649143.3 | AI41: 649854.76 | AJ41: 650566.22 | AK41: 651277.68 | AL41: 651989.14 | AM41: 652700.6 | AN41: 653412.06 | AO41: 654123.53 | AP41: 654834.99 | AQ41: 655546.45 | AR41: 656257.91 | AS41: 656969.37 | AT41: 657680.83 | AU41: 658392.29 | AV41: 659103.75 | AW41: 659815.22 | AX41: 660526.68 | AY41: 661238.14 | AZ41: 661949.6
A42: LPG vehicle | B42: 556134.73 | C42: 565243.08 | D42: 564719.73 | E42: 565703.57 | F42: 567037.66 | G42: 569523.2 | H42: 571599.8 | I42: 572665.59 | J42: 573609.15 | K42: 574630.71 | L42: 575588.44 | M42: 576540.71 | N42: 577352.94 | O42: 578327.62 | P42: 578987.27 | Q42: 579582.88 | R42: 580198.5 | S42: 580818.97 | T42: 581400.42 | U42: 582016.59 | V42: 582546.61 | W42: 583077.82 | X42: 583604.69 | Y42: 584104.19 | Z42: 584621.04 | AA42: 585153.56 | AB42: 585681.63 | AC42: 586227.71 | AD42: 586772.99 | AE42: 587324.92 | AF42: 587672.93 | AG42: 591118.18 | AH42: 591957.28 | AI42: 592796.38 | AJ42: 593635.49 | AK42: 594474.59 | AL42: 595313.69 | AM42: 596152.79 | AN42: 596991.89 | AO42: 597830.99 | AP42: 598670.09 | AQ42: 599509.19 | AR42: 600348.29 | AS42: 601187.39 | AT42: 602026.49 | AU42: 602865.6 | AV42: 603704.7 | AW42: 604543.8 | AX42: 605382.9 | AY42: 606222 | AZ42: 607061.1
A43: hydrogen vehicle | B43: 856850.98 | C43: 856664.62 | D43: 838135.09 | E43: 821823.37 | F43: 805346.78 | G43: 788292.49 | H43: 773310.12 | I43: 759521.84 | J43: 746370.1 | K43: 733838.69 | L43: 721892.09 | M43: 710520.7 | N43: 699631.24 | O43: 689326.14 | P43: 679212.01 | Q43: 669514.4 | R43: 660277.66 | S43: 651468.36 | T43: 643068.43 | U43: 635067.24 | V43: 627418.93 | W43: 620139.09 | X43: 613195.62 | Y43: 606573.58 | Z43: 600264.33 | AA43: 594250.29 | AB43: 588514.29 | AC43: 583050.31 | AD43: 577838.72 | AE43: 572876.01 | AF43: 567918.08 | AG43: 529968.9 | AH43: 520164.19 | AI43: 510359.48 | AJ43: 500554.78 | AK43: 490750.07 | AL43: 480945.36 | AM43: 471140.65 | AN43: 461335.94 | AO43: 451531.23 | AP43: 441726.52 | AQ43: 431921.81 | AR43: 422117.1 | AS43: 412312.4 | AT43: 402507.69 | AU43: 392702.98 | AV43: 382898.27 | AW43: 373093.56 | AX43: 363288.85 | AY43: 353484.14 | AZ43: 343679.43
A45: BNVP-HDVs-frgt
A46: Price ($/vehicle) | B46: 2020 | C46: 2021 | D46: 2022 | E46: 2023 | F46: 2024 | G46: 2025 | H46: 2026 | I46: 2027 | J46: 2028 | K46: 2029 | L46: 2030 | M46: 2031 | N46: 2032 | O46: 2033 | P46: 2034 | Q46: 2035 | R46: 2036 | S46: 2037 | T46: 2038 | U46: 2039 | V46: 2040 | W46: 2041 | X46: 2042 | Y46: 2043 | Z46: 2044 | AA46: 2045 | AB46: 2046 | AC46: 2047 | AD46: 2048 | AE46: 2049 | AF46: 2050 | AG46: 2051 | AH46: 2052 | AI46: 2053 | AJ46: 2054 | AK46: 2055 | AL46: 2056 | AM46: 2057 | AN46: 2058 | AO46: 2059 | AP46: 2060 | AQ46: 2061 | AR46: 2062 | AS46: 2063 | AT46: 2064 | AU46: 2065 | AV46: 2066 | AW46: 2067 | AX46: 2068 | AY46: 2069 | AZ46: 2070
A47: battery electric vehicle | B47: 212323.26 | C47: 212323.26 | D47: 212323.26 | E47: 212323.26 | F47: 212323.26 | G47: 212323.26 | H47: 212323.26 | I47: 212323.26 | J47: 212323.26 | K47: 212323.26 | L47: 212323.26 | M47: 212323.26 | N47: 212323.26 | O47: 212323.26 | P47: 212323.26 | Q47: 212323.26 | R47: 212323.26 | S47: 212323.26 | T47: 212323.26 | U47: 212323.26 | V47: 212323.26 | W47: 212323.26 | X47: 212323.26 | Y47: 212323.26 | Z47: 212323.26 | AA47: 212323.26 | AB47: 212323.26 | AC47: 212323.26 | AD47: 212323.26 | AE47: 212323.26 | AF47: 212323.26 | AG47: 212323.26 | AH47: 212323.26 | AI47: 212323.26 | AJ47: 212323.26 | AK47: 212323.26 | AL47: 212323.26 | AM47: 212323.26 | AN47: 212323.26 | AO47: 212323.26 | AP47: 212323.26 | AQ47: 212323.26 | AR47: 212323.26 | AS47: 212323.26 | AT47: 212323.26 | AU47: 212323.26 | AV47: 212323.26 | AW47: 212323.26 | AX47: 212323.26 | AY47: 212323.26 | AZ47: 212323.26
A48: natural gas vehicle | B48: 169081.01 | C48: 167864.65 | D48: 168589.54 | E48: 169720.85 | F48: 170592.77 | G48: 171447.35 | H48: 172235.77 | I48: 172949.86 | J48: 173710.9 | K48: 174435.56 | L48: 175106.83 | M48: 175831.33 | N48: 176390.34 | O48: 177133.8 | P48: 177567.08 | Q48: 177918.6 | R48: 178228.46 | S48: 178533.03 | T48: 178816.19 | U48: 179106.91 | V48: 179311.24 | W48: 179543.09 | X48: 179737.16 | Y48: 179898.98 | Z48: 180064.57 | AA48: 180221.06 | AB48: 180365 | AC48: 180516.08 | AD48: 180668.22 | AE48: 180802.25 | AF48: 180937.41 | AG48: 183362.21 | AH48: 183799.51 | AI48: 184236.81 | AJ48: 184674.12 | AK48: 185111.42 | AL48: 185548.72 | AM48: 185986.03 | AN48: 186423.33 | AO48: 186860.63 | AP48: 187297.94 | AQ48: 187735.24 | AR48: 188172.54 | AS48: 188609.85 | AT48: 189047.15 | AU48: 189484.45 | AV48: 189921.76 | AW48: 190359.06 | AX48: 190796.36 | AY48: 191233.67 | AZ48: 191670.97
A49: gasoline vehicle | B49: 116533.08 | C49: 116533.08 | D49: 116533.08 | E49: 116533.08 | F49: 116533.08 | G49: 116533.08 | H49: 116533.08 | I49: 116533.08 | J49: 116533.08 | K49: 116533.08 | L49: 116533.08 | M49: 116533.08 | N49: 116533.08 | O49: 116533.08 | P49: 116533.08 | Q49: 116533.08 | R49: 116533.08 | S49: 116533.08 | T49: 116533.08 | U49: 116533.08 | V49: 116533.08 | W49: 116533.08 | X49: 116533.08 | Y49: 116533.08 | Z49: 116533.08 | AA49: 116533.08 | AB49: 116533.08 | AC49: 116533.08 | AD49: 116533.08 | AE49: 116533.08 | AF49: 116533.08 | AG49: 116533.08 | AH49: 116533.08 | AI49: 116533.08 | AJ49: 116533.08 | AK49: 116533.08 | AL49: 116533.08 | AM49: 116533.08 | AN49: 116533.08 | AO49: 116533.08 | AP49: 116533.08 | AQ49: 116533.08 | AR49: 116533.08 | AS49: 116533.08 | AT49: 116533.08 | AU49: 116533.08 | AV49: 116533.08 | AW49: 116533.08 | AX49: 116533.08 | AY49: 116533.08 | AZ49: 116533.08
A50: diesel vehicle | B50: 116533.08 | C50: 116533.08 | D50: 116533.08 | E50: 116533.08 | F50: 116533.08 | G50: 116533.08 | H50: 116533.08 | I50: 116533.08 | J50: 116533.08 | K50: 116533.08 | L50: 116533.08 | M50: 116533.08 | N50: 116533.08 | O50: 116533.08 | P50: 116533.08 | Q50: 116533.08 | R50: 116533.08 | S50: 116533.08 | T50: 116533.08 | U50: 116533.08 | V50: 116533.08 | W50: 116533.08 | X50: 116533.08 | Y50: 116533.08 | Z50: 116533.08 | AA50: 116533.08 | AB50: 116533.08 | AC50: 116533.08 | AD50: 116533.08 | AE50: 116533.08 | AF50: 116533.08 | AG50: 116533.08 | AH50: 116533.08 | AI50: 116533.08 | AJ50: 116533.08 | AK50: 116533.08 | AL50: 116533.08 | AM50: 116533.08 | AN50: 116533.08 | AO50: 116533.08 | AP50: 116533.08 | AQ50: 116533.08 | AR50: 116533.08 | AS50: 116533.08 | AT50: 116533.08 | AU50: 116533.08 | AV50: 116533.08 | AW50: 116533.08 | AX50: 116533.08 | AY50: 116533.08 | AZ50: 116533.08
A51: plugin hybrid vehicle | B51: 292717.2 | C51: 296718.81 | D51: 296290.7 | E51: 297748.17 | F51: 298074.13 | G51: 298962.66 | H51: 299325.72 | I51: 299532.53 | J51: 299964.75 | K51: 300521.89 | L51: 301144.75 | M51: 301941.6 | N51: 302627.45 | O51: 303546.26 | P51: 304016.24 | Q51: 304390.28 | R51: 304725.79 | S51: 304997.87 | T51: 305173.43 | U51: 305303.86 | V51: 305293.78 | W51: 305340.79 | X51: 305317.62 | Y51: 305243.4 | Z51: 305169.62 | AA51: 305090.87 | AB51: 304998.45 | AC51: 304921.39 | AD51: 304846.72 | AE51: 304781.55 | AF51: 304698.59 | AG51: 307771.62 | AH51: 308109.3 | AI51: 308446.99 | AJ51: 308784.68 | AK51: 309122.37 | AL51: 309460.05 | AM51: 309797.74 | AN51: 310135.43 | AO51: 310473.12 | AP51: 310810.81 | AQ51: 311148.49 | AR51: 311486.18 | AS51: 311823.87 | AT51: 312161.56 | AU51: 312499.25 | AV51: 312836.93 | AW51: 313174.62 | AX51: 313512.31 | AY51: 313850 | AZ51: 314187.69
A52: LPG vehicle | B52: 165261.41 | C52: 167968.05 | D52: 167812.53 | E52: 168104.89 | F52: 168501.33 | G52: 169239.93 | H52: 169857.02 | I52: 170173.73 | J52: 170454.12 | K52: 170757.69 | L52: 171042.29 | M52: 171325.26 | N52: 171566.63 | O52: 171856.26 | P52: 172052.29 | Q52: 172229.28 | R52: 172412.22 | S52: 172596.6 | T52: 172769.38 | U52: 172952.48 | V52: 173109.98 | W52: 173267.84 | X52: 173424.4 | Y52: 173572.83 | Z52: 173726.42 | AA52: 173884.67 | AB52: 174041.59 | AC52: 174203.86 | AD52: 174365.89 | AE52: 174529.91 | AF52: 174633.32 | AG52: 175657.12 | AH52: 175906.46 | AI52: 176155.81 | AJ52: 176405.16 | AK52: 176654.51 | AL52: 176903.86 | AM52: 177153.2 | AN52: 177402.55 | AO52: 177651.9 | AP52: 177901.25 | AQ52: 178150.59 | AR52: 178399.94 | AS52: 178649.29 | AT52: 178898.64 | AU52: 179147.99 | AV52: 179397.33 | AW52: 179646.68 | AX52: 179896.03 | AY52: 180145.38 | AZ52: 180394.73
A53: hydrogen vehicle | B53: 356070.43 | C53: 355992.99 | D53: 348292.91 | E53: 341514.46 | F53: 334667.5 | G53: 327580.47 | H53: 321354.44 | I53: 315624.63 | J53: 310159.33 | K53: 304951.81 | L53: 299987.32 | M53: 295261.86 | N53: 290736.67 | O53: 286454.31 | P53: 282251.31 | Q53: 278221.4 | R53: 274383.01 | S53: 270722.24 | T53: 267231.6 | U53: 263906.64 | V53: 260728.33 | W53: 257703.15 | X53: 254817.74 | Y53: 252065.91 | Z53: 249444.05 | AA53: 246944.88 | AB53: 244561.24 | AC53: 242290.65 | AD53: 240124.93 | AE53: 238062.64 | AF53: 236002.34 | AG53: 220232.29 | AH53: 216157.88 | AI53: 212083.46 | AJ53: 208009.05 | AK53: 203934.63 | AL53: 199860.22 | AM53: 195785.8 | AN53: 191711.38 | AO53: 187636.97 | AP53: 183562.55 | AQ53: 179488.14 | AR53: 175413.72 | AS53: 171339.31 | AT53: 167264.89 | AU53: 163190.48 | AV53: 159116.06 | AW53: 155041.64 | AX53: 150967.23 | AY53: 146892.81 | AZ53: 142818.4
A55: BNVP-aircraft-psgr
A56: Price ($/vehicle) | B56: 2020 | C56: 2021 | D56: 2022 | E56: 2023 | F56: 2024 | G56: 2025 | H56: 2026 | I56: 2027 | J56: 2028 | K56: 2029 | L56: 2030 | M56: 2031 | N56: 2032 | O56: 2033 | P56: 2034 | Q56: 2035 | R56: 2036 | S56: 2037 | T56: 2038 | U56: 2039 | V56: 2040 | W56: 2041 | X56: 2042 | Y56: 2043 | Z56: 2044 | AA56: 2045 | AB56: 2046 | AC56: 2047 | AD56: 2048 | AE56: 2049 | AF56: 2050 | AG56: 2051 | AH56: 2052 | AI56: 2053 | AJ56: 2054 | AK56: 2055 | AL56: 2056 | AM56: 2057 | AN56: 2058 | AO56: 2059 | AP56: 2060 | AQ56: 2061 | AR56: 2062 | AS56: 2063 | AT56: 2064 | AU56: 2065 | AV56: 2066 | AW56: 2067 | AX56: 2068 | AY56: 2069 | AZ56: 2070
A57: battery electric vehicle | B57: 1.198482e+08 | C57: 1.198482e+08 | D57: 1.198482e+08 | E57: 1.198482e+08 | F57: 1.198482e+08 | G57: 1.198482e+08 | H57: 1.198482e+08 | I57: 1.198482e+08 | J57: 1.198482e+08 | K57: 1.198482e+08 | L57: 1.198482e+08 | M57: 1.198482e+08 | N57: 1.198482e+08 | O57: 1.198482e+08 | P57: 1.198482e+08 | Q57: 1.198482e+08 | R57: 1.198482e+08 | S57: 1.198482e+08 | T57: 1.198482e+08 | U57: 1.198482e+08 | V57: 1.198482e+08 | W57: 1.198482e+08 | X57: 1.198482e+08 | Y57: 1.198482e+08 | Z57: 1.198482e+08 | AA57: 1.198482e+08 | AB57: 1.198482e+08 | AC57: 1.198482e+08 | AD57: 1.198482e+08 | AE57: 1.198482e+08 | AF57: 1.198482e+08 | AG57: 1.198482e+08 | AH57: 1.198482e+08 | AI57: 1.198482e+08 | AJ57: 1.198482e+08 | AK57: 1.198482e+08 | AL57: 1.198482e+08 | AM57: 1.198482e+08 | AN57: 1.198482e+08 | AO57: 1.198482e+08 | AP57: 1.198482e+08 | AQ57: 1.198482e+08 | AR57: 1.198482e+08 | AS57: 1.198482e+08 | AT57: 1.198482e+08 | AU57: 1.198482e+08 | AV57: 1.198482e+08 | AW57: 1.198482e+08 | AX57: 1.198482e+08 | AY57: 1.198482e+08 | AZ57: 1.198482e+08
A58: natural gas vehicle | B58: 0 | C58: 0 | D58: 0 | E58: 0 | F58: 0 | G58: 0 | H58: 0 | I58: 0 | J58: 0 | K58: 0 | L58: 0 | M58: 0 | N58: 0 | O58: 0 | P58: 0 | Q58: 0 | R58: 0 | S58: 0 | T58: 0 | U58: 0 | V58: 0 | W58: 0 | X58: 0 | Y58: 0 | Z58: 0 | AA58: 0 | AB58: 0 | AC58: 0 | AD58: 0 | AE58: 0 | AF58: 0 | AG58: 0 | AH58: 0 | AI58: 0 | AJ58: 0 | AK58: 0 | AL58: 0 | AM58: 0 | AN58: 0 | AO58: 0 | AP58: 0 | AQ58: 0 | AR58: 0 | AS58: 0 | AT58: 0 | AU58: 0 | AV58: 0 | AW58: 0 | AX58: 0 | AY58: 0 | AZ58: 0
A59: gasoline vehicle | B59: 0 | C59: 0 | D59: 0 | E59: 0 | F59: 0 | G59: 0 | H59: 0 | I59: 0 | J59: 0 | K59: 0 | L59: 0 | M59: 0 | N59: 0 | O59: 0 | P59: 0 | Q59: 0 | R59: 0 | S59: 0 | T59: 0 | U59: 0 | V59: 0 | W59: 0 | X59: 0 | Y59: 0 | Z59: 0 | AA59: 0 | AB59: 0 | AC59: 0 | AD59: 0 | AE59: 0 | AF59: 0 | AG59: 0 | AH59: 0 | AI59: 0 | AJ59: 0 | AK59: 0 | AL59: 0 | AM59: 0 | AN59: 0 | AO59: 0 | AP59: 0 | AQ59: 0 | AR59: 0 | AS59: 0 | AT59: 0 | AU59: 0 | AV59: 0 | AW59: 0 | AX59: 0 | AY59: 0 | AZ59: 0
A60: diesel vehicle | B60: 64833333 | C60: 64833333 | D60: 64833333 | E60: 64833333 | F60: 64833333 | G60: 64833333 | H60: 64833333 | I60: 64833333 | J60: 64833333 | K60: 64833333 | L60: 64833333 | M60: 64833333 | N60: 64833333 | O60: 64833333 | P60: 64833333 | Q60: 64833333 | R60: 64833333 | S60: 64833333 | T60: 64833333 | U60: 64833333 | V60: 64833333 | W60: 64833333 | X60: 64833333 | Y60: 64833333 | Z60: 64833333 | AA60: 64833333 | AB60: 64833333 | AC60: 64833333 | AD60: 64833333 | AE60: 64833333 | AF60: 64833333 | AG60: 64833333 | AH60: 64833333 | AI60: 64833333 | AJ60: 64833333 | AK60: 64833333 | AL60: 64833333 | AM60: 64833333 | AN60: 64833333 | AO60: 64833333 | AP60: 64833333 | AQ60: 64833333 | AR60: 64833333 | AS60: 64833333 | AT60: 64833333 | AU60: 64833333 | AV60: 64833333 | AW60: 64833333 | AX60: 64833333 | AY60: 64833333 | AZ60: 64833333
A61: plugin hybrid vehicle | B61: 0 | C61: 0 | D61: 0 | E61: 0 | F61: 0 | G61: 0 | H61: 0 | I61: 0 | J61: 0 | K61: 0 | L61: 0 | M61: 0 | N61: 0 | O61: 0 | P61: 0 | Q61: 0 | R61: 0 | S61: 0 | T61: 0 | U61: 0 | V61: 0 | W61: 0 | X61: 0 | Y61: 0 | Z61: 0 | AA61: 0 | AB61: 0 | AC61: 0 | AD61: 0 | AE61: 0 | AF61: 0 | AG61: 0 | AH61: 0 | AI61: 0 | AJ61: 0 | AK61: 0 | AL61: 0 | AM61: 0 | AN61: 0 | AO61: 0 | AP61: 0 | AQ61: 0 | AR61: 0 | AS61: 0 | AT61: 0 | AU61: 0 | AV61: 0 | AW61: 0 | AX61: 0 | AY61: 0 | AZ61: 0
A62: LPG vehicle | B62: 0 | C62: 0 | D62: 0 | E62: 0 | F62: 0 | G62: 0 | H62: 0 | I62: 0 | J62: 0 | K62: 0 | L62: 0 | M62: 0 | N62: 0 | O62: 0 | P62: 0 | Q62: 0 | R62: 0 | S62: 0 | T62: 0 | U62: 0 | V62: 0 | W62: 0 | X62: 0 | Y62: 0 | Z62: 0 | AA62: 0 | AB62: 0 | AC62: 0 | AD62: 0 | AE62: 0 | AF62: 0 | AG62: 0 | AH62: 0 | AI62: 0 | AJ62: 0 | AK62: 0 | AL62: 0 | AM62: 0 | AN62: 0 | AO62: 0 | AP62: 0 | AQ62: 0 | AR62: 0 | AS62: 0 | AT62: 0 | AU62: 0 | AV62: 0 | AW62: 0 | AX62: 0 | AY62: 0 | AZ62: 0
A63: hydrogen vehicle | B63: 1.3046217e+08 | C63: 1.304338e+08 | D63: 1.2761253e+08 | E63: 1.2512895e+08 | F63: 1.2262026e+08 | G63: 1.2002361e+08 | H63: 1.1774243e+08 | I63: 1.1564306e+08 | J63: 1.1364061e+08 | K63: 1.117326e+08 | L63: 1.0991364e+08 | M63: 1.0818226e+08 | N63: 1.0652426e+08 | O63: 1.0495522e+08 | P63: 1.0341527e+08 | Q63: 1.0193873e+08 | R63: 1.0053237e+08 | S63: 99191084 | T63: 97912130 | U63: 96693887 | V63: 95529373 | W63: 94420961 | X63: 93363765 | Y63: 92355508 | Z63: 91394875 | AA63: 90479192 | AB63: 89605842 | AC63: 88773909 | AD63: 87980403 | AE63: 87224793 | AF63: 86469910 | AG63: 80691855 | AH63: 79199012 | AI63: 77706169 | AJ63: 76213327 | AK63: 74720484 | AL63: 73227642 | AM63: 71734799 | AN63: 70241956 | AO63: 68749114 | AP63: 67256271 | AQ63: 65763429 | AR63: 64270586 | AS63: 62777744 | AT63: 61284901 | AU63: 59792058 | AV63: 58299216 | AW63: 56806373 | AX63: 55313531 | AY63: 53820688 | AZ63: 52327845
A65: BNVP-rail-psgr
A66: Price ($/vehicle) | B66: 2020 | C66: 2021 | D66: 2022 | E66: 2023 | F66: 2024 | G66: 2025 | H66: 2026 | I66: 2027 | J66: 2028 | K66: 2029 | L66: 2030 | M66: 2031 | N66: 2032 | O66: 2033 | P66: 2034 | Q66: 2035 | R66: 2036 | S66: 2037 | T66: 2038 | U66: 2039 | V66: 2040 | W66: 2041 | X66: 2042 | Y66: 2043 | Z66: 2044 | AA66: 2045 | AB66: 2046 | AC66: 2047 | AD66: 2048 | AE66: 2049 | AF66: 2050 | AG66: 2051 | AH66: 2052 | AI66: 2053 | AJ66: 2054 | AK66: 2055 | AL66: 2056 | AM66: 2057 | AN66: 2058 | AO66: 2059 | AP66: 2060 | AQ66: 2061 | AR66: 2062 | AS66: 2063 | AT66: 2064 | AU66: 2065 | AV66: 2066 | AW66: 2067 | AX66: 2068 | AY66: 2069 | AZ66: 2070
A67: battery electric vehicle | B67: 4166666.7 | C67: 4166666.7 | D67: 4166666.7 | E67: 4166666.7 | F67: 4166666.7 | G67: 4166666.7 | H67: 4166666.7 | I67: 4166666.7 | J67: 4166666.7 | K67: 4166666.7 | L67: 4166666.7 | M67: 4166666.7 | N67: 4166666.7 | O67: 4166666.7 | P67: 4166666.7 | Q67: 4166666.7 | R67: 4166666.7 | S67: 4166666.7 | T67: 4166666.7 | U67: 4166666.7 | V67: 4166666.7 | W67: 4166666.7 | X67: 4166666.7 | Y67: 4166666.7 | Z67: 4166666.7 | AA67: 4166666.7 | AB67: 4166666.7 | AC67: 4166666.7 | AD67: 4166666.7 | AE67: 4166666.7 | AF67: 4166666.7 | AG67: 4166666.7 | AH67: 4166666.7 | AI67: 4166666.7 | AJ67: 4166666.7 | AK67: 4166666.7 | AL67: 4166666.7 | AM67: 4166666.7 | AN67: 4166666.7 | AO67: 4166666.7 | AP67: 4166666.7 | AQ67: 4166666.7 | AR67: 4166666.7 | AS67: 4166666.7 | AT67: 4166666.7 | AU67: 4166666.7 | AV67: 4166666.7 | AW67: 4166666.7 | AX67: 4166666.7 | AY67: 4166666.7 | AZ67: 4166666.7
A68: natural gas vehicle | B68: 0 | C68: 0 | D68: 0 | E68: 0 | F68: 0 | G68: 0 | H68: 0 | I68: 0 | J68: 0 | K68: 0 | L68: 0 | M68: 0 | N68: 0 | O68: 0 | P68: 0 | Q68: 0 | R68: 0 | S68: 0 | T68: 0 | U68: 0 | V68: 0 | W68: 0 | X68: 0 | Y68: 0 | Z68: 0 | AA68: 0 | AB68: 0 | AC68: 0 | AD68: 0 | AE68: 0 | AF68: 0 | AG68: 0 | AH68: 0 | AI68: 0 | AJ68: 0 | AK68: 0 | AL68: 0 | AM68: 0 | AN68: 0 | AO68: 0 | AP68: 0 | AQ68: 0 | AR68: 0 | AS68: 0 | AT68: 0 | AU68: 0 | AV68: 0 | AW68: 0 | AX68: 0 | AY68: 0 | AZ68: 0
A69: gasoline vehicle | B69: 0 | C69: 0 | D69: 0 | E69: 0 | F69: 0 | G69: 0 | H69: 0 | I69: 0 | J69: 0 | K69: 0 | L69: 0 | M69: 0 | N69: 0 | O69: 0 | P69: 0 | Q69: 0 | R69: 0 | S69: 0 | T69: 0 | U69: 0 | V69: 0 | W69: 0 | X69: 0 | Y69: 0 | Z69: 0 | AA69: 0 | AB69: 0 | AC69: 0 | AD69: 0 | AE69: 0 | AF69: 0 | AG69: 0 | AH69: 0 | AI69: 0 | AJ69: 0 | AK69: 0 | AL69: 0 | AM69: 0 | AN69: 0 | AO69: 0 | AP69: 0 | AQ69: 0 | AR69: 0 | AS69: 0 | AT69: 0 | AU69: 0 | AV69: 0 | AW69: 0 | AX69: 0 | AY69: 0 | AZ69: 0
A70: diesel vehicle | B70: 2245137 | C70: 2245137 | D70: 2245137 | E70: 2245137 | F70: 2245137 | G70: 2245137 | H70: 2245137 | I70: 2245137 | J70: 2245137 | K70: 2245137 | L70: 2245137 | M70: 2245137 | N70: 2245137 | O70: 2245137 | P70: 2245137 | Q70: 2245137 | R70: 2245137 | S70: 2245137 | T70: 2245137 | U70: 2245137 | V70: 2245137 | W70: 2245137 | X70: 2245137 | Y70: 2245137 | Z70: 2245137 | AA70: 2245137 | AB70: 2245137 | AC70: 2245137 | AD70: 2245137 | AE70: 2245137 | AF70: 2245137 | AG70: 2245137 | AH70: 2245137 | AI70: 2245137 | AJ70: 2245137 | AK70: 2245137 | AL70: 2245137 | AM70: 2245137 | AN70: 2245137 | AO70: 2245137 | AP70: 2245137 | AQ70: 2245137 | AR70: 2245137 | AS70: 2245137 | AT70: 2245137 | AU70: 2245137 | AV70: 2245137 | AW70: 2245137 | AX70: 2245137 | AY70: 2245137 | AZ70: 2245137
A71: plugin hybrid vehicle | B71: 0 | C71: 0 | D71: 0 | E71: 0 | F71: 0 | G71: 0 | H71: 0 | I71: 0 | J71: 0 | K71: 0 | L71: 0 | M71: 0 | N71: 0 | O71: 0 | P71: 0 | Q71: 0 | R71: 0 | S71: 0 | T71: 0 | U71: 0 | V71: 0 | W71: 0 | X71: 0 | Y71: 0 | Z71: 0 | AA71: 0 | AB71: 0 | AC71: 0 | AD71: 0 | AE71: 0 | AF71: 0 | AG71: 0 | AH71: 0 | AI71: 0 | AJ71: 0 | AK71: 0 | AL71: 0 | AM71: 0 | AN71: 0 | AO71: 0 | AP71: 0 | AQ71: 0 | AR71: 0 | AS71: 0 | AT71: 0 | AU71: 0 | AV71: 0 | AW71: 0 | AX71: 0 | AY71: 0 | AZ71: 0
A72: LPG vehicle | B72: 0 | C72: 0 | D72: 0 | E72: 0 | F72: 0 | G72: 0 | H72: 0 | I72: 0 | J72: 0 | K72: 0 | L72: 0 | M72: 0 | N72: 0 | O72: 0 | P72: 0 | Q72: 0 | R72: 0 | S72: 0 | T72: 0 | U72: 0 | V72: 0 | W72: 0 | X72: 0 | Y72: 0 | Z72: 0 | AA72: 0 | AB72: 0 | AC72: 0 | AD72: 0 | AE72: 0 | AF72: 0 | AG72: 0 | AH72: 0 | AI72: 0 | AJ72: 0 | AK72: 0 | AL72: 0 | AM72: 0 | AN72: 0 | AO72: 0 | AP72: 0 | AQ72: 0 | AR72: 0 | AS72: 0 | AT72: 0 | AU72: 0 | AV72: 0 | AW72: 0 | AX72: 0 | AY72: 0 | AZ72: 0
A73: hydrogen vehicle | B73: 2963580.9 | C73: 2962936.3 | D73: 2898848.4 | E73: 2842431.3 | F73: 2785443.9 | G73: 2726458.4 | H73: 2674639.1 | I73: 2626949.7 | J73: 2581461.9 | K73: 2538119.7 | L73: 2496800.1 | M73: 2457470 | N73: 2419806.7 | O73: 2384164.6 | P73: 2349183 | Q73: 2315642 | R73: 2283694.9 | S73: 2253226.3 | T73: 2224173.6 | U73: 2196499.9 | V73: 2170046.8 | W73: 2144868.1 | X73: 2120852.8 | Y73: 2097949.3 | Z73: 2076127.5 | AA73: 2055326.8 | AB73: 2035487.8 | AC73: 2016589.6 | AD73: 1998564.3 | AE73: 1981399.8 | AF73: 1964251.9 | AG73: 1832997.5 | AH73: 1799086.1 | AI73: 1765174.6 | AJ73: 1731263.2 | AK73: 1697351.8 | AL73: 1663440.3 | AM73: 1629528.9 | AN73: 1595617.4 | AO73: 1561706 | AP73: 1527794.6 | AQ73: 1493883.1 | AR73: 1459971.7 | AS73: 1426060.3 | AT73: 1392148.8 | AU73: 1358237.4 | AV73: 1324326 | AW73: 1290414.5 | AX73: 1256503.1 | AY73: 1222591.6 | AZ73: 1188680.2
A75: BNVP-aircraft-frgt
A76: Price ($/vehicle) | B76: 2020 | C76: 2021 | D76: 2022 | E76: 2023 | F76: 2024 | G76: 2025 | H76: 2026 | I76: 2027 | J76: 2028 | K76: 2029 | L76: 2030 | M76: 2031 | N76: 2032 | O76: 2033 | P76: 2034 | Q76: 2035 | R76: 2036 | S76: 2037 | T76: 2038 | U76: 2039 | V76: 2040 | W76: 2041 | X76: 2042 | Y76: 2043 | Z76: 2044 | AA76: 2045 | AB76: 2046 | AC76: 2047 | AD76: 2048 | AE76: 2049 | AF76: 2050 | AG76: 2051 | AH76: 2052 | AI76: 2053 | AJ76: 2054 | AK76: 2055 | AL76: 2056 | AM76: 2057 | AN76: 2058 | AO76: 2059 | AP76: 2060 | AQ76: 2061 | AR76: 2062 | AS76: 2063 | AT76: 2064 | AU76: 2065 | AV76: 2066 | AW76: 2067 | AX76: 2068 | AY76: 2069 | AZ76: 2070
A77: battery electric vehicle | B77: 1.198482e+08 | C77: 1.198482e+08 | D77: 1.198482e+08 | E77: 1.198482e+08 | F77: 1.198482e+08 | G77: 1.198482e+08 | H77: 1.198482e+08 | I77: 1.198482e+08 | J77: 1.198482e+08 | K77: 1.198482e+08 | L77: 1.198482e+08 | M77: 1.198482e+08 | N77: 1.198482e+08 | O77: 1.198482e+08 | P77: 1.198482e+08 | Q77: 1.198482e+08 | R77: 1.198482e+08 | S77: 1.198482e+08 | T77: 1.198482e+08 | U77: 1.198482e+08 | V77: 1.198482e+08 | W77: 1.198482e+08 | X77: 1.198482e+08 | Y77: 1.198482e+08 | Z77: 1.198482e+08 | AA77: 1.198482e+08 | AB77: 1.198482e+08 | AC77: 1.198482e+08 | AD77: 1.198482e+08 | AE77: 1.198482e+08 | AF77: 1.198482e+08 | AG77: 1.198482e+08 | AH77: 1.198482e+08 | AI77: 1.198482e+08 | AJ77: 1.198482e+08 | AK77: 1.198482e+08 | AL77: 1.198482e+08 | AM77: 1.198482e+08 | AN77: 1.198482e+08 | AO77: 1.198482e+08 | AP77: 1.198482e+08 | AQ77: 1.198482e+08 | AR77: 1.198482e+08 | AS77: 1.198482e+08 | AT77: 1.198482e+08 | AU77: 1.198482e+08 | AV77: 1.198482e+08 | AW77: 1.198482e+08 | AX77: 1.198482e+08 | AY77: 1.198482e+08 | AZ77: 1.198482e+08
A78: natural gas vehicle | B78: 0 | C78: 0 | D78: 0 | E78: 0 | F78: 0 | G78: 0 | H78: 0 | I78: 0 | J78: 0 | K78: 0 | L78: 0 | M78: 0 | N78: 0 | O78: 0 | P78: 0 | Q78: 0 | R78: 0 | S78: 0 | T78: 0 | U78: 0 | V78: 0 | W78: 0 | X78: 0 | Y78: 0 | Z78: 0 | AA78: 0 | AB78: 0 | AC78: 0 | AD78: 0 | AE78: 0 | AF78: 0 | AG78: 0 | AH78: 0 | AI78: 0 | AJ78: 0 | AK78: 0 | AL78: 0 | AM78: 0 | AN78: 0 | AO78: 0 | AP78: 0 | AQ78: 0 | AR78: 0 | AS78: 0 | AT78: 0 | AU78: 0 | AV78: 0 | AW78: 0 | AX78: 0 | AY78: 0 | AZ78: 0
A79: gasoline vehicle | B79: 0 | C79: 0 | D79: 0 | E79: 0 | F79: 0 | G79: 0 | H79: 0 | I79: 0 | J79: 0 | K79: 0 | L79: 0 | M79: 0 | N79: 0 | O79: 0 | P79: 0 | Q79: 0 | R79: 0 | S79: 0 | T79: 0 | U79: 0 | V79: 0 | W79: 0 | X79: 0 | Y79: 0 | Z79: 0 | AA79: 0 | AB79: 0 | AC79: 0 | AD79: 0 | AE79: 0 | AF79: 0 | AG79: 0 | AH79: 0 | AI79: 0 | AJ79: 0 | AK79: 0 | AL79: 0 | AM79: 0 | AN79: 0 | AO79: 0 | AP79: 0 | AQ79: 0 | AR79: 0 | AS79: 0 | AT79: 0 | AU79: 0 | AV79: 0 | AW79: 0 | AX79: 0 | AY79: 0 | AZ79: 0
A80: diesel vehicle | B80: 64833333 | C80: 64833333 | D80: 64833333 | E80: 64833333 | F80: 64833333 | G80: 64833333 | H80: 64833333 | I80: 64833333 | J80: 64833333 | K80: 64833333 | L80: 64833333 | M80: 64833333 | N80: 64833333 | O80: 64833333 | P80: 64833333 | Q80: 64833333 | R80: 64833333 | S80: 64833333 | T80: 64833333 | U80: 64833333 | V80: 64833333 | W80: 64833333 | X80: 64833333 | Y80: 64833333 | Z80: 64833333 | AA80: 64833333 | AB80: 64833333 | AC80: 64833333 | AD80: 64833333 | AE80: 64833333 | AF80: 64833333 | AG80: 64833333 | AH80: 64833333 | AI80: 64833333 | AJ80: 64833333 | AK80: 64833333 | AL80: 64833333 | AM80: 64833333 | AN80: 64833333 | AO80: 64833333 | AP80: 64833333 | AQ80: 64833333 | AR80: 64833333 | AS80: 64833333 | AT80: 64833333 | AU80: 64833333 | AV80: 64833333 | AW80: 64833333 | AX80: 64833333 | AY80: 64833333 | AZ80: 64833333
A81: plugin hybrid vehicle | B81: 0 | C81: 0 | D81: 0 | E81: 0 | F81: 0 | G81: 0 | H81: 0 | I81: 0 | J81: 0 | K81: 0 | L81: 0 | M81: 0 | N81: 0 | O81: 0 | P81: 0 | Q81: 0 | R81: 0 | S81: 0 | T81: 0 | U81: 0 | V81: 0 | W81: 0 | X81: 0 | Y81: 0 | Z81: 0 | AA81: 0 | AB81: 0 | AC81: 0 | AD81: 0 | AE81: 0 | AF81: 0 | AG81: 0 | AH81: 0 | AI81: 0 | AJ81: 0 | AK81: 0 | AL81: 0 | AM81: 0 | AN81: 0 | AO81: 0 | AP81: 0 | AQ81: 0 | AR81: 0 | AS81: 0 | AT81: 0 | AU81: 0 | AV81: 0 | AW81: 0 | AX81: 0 | AY81: 0 | AZ81: 0
A82: LPG vehicle | B82: 0 | C82: 0 | D82: 0 | E82: 0 | F82: 0 | G82: 0 | H82: 0 | I82: 0 | J82: 0 | K82: 0 | L82: 0 | M82: 0 | N82: 0 | O82: 0 | P82: 0 | Q82: 0 | R82: 0 | S82: 0 | T82: 0 | U82: 0 | V82: 0 | W82: 0 | X82: 0 | Y82: 0 | Z82: 0 | AA82: 0 | AB82: 0 | AC82: 0 | AD82: 0 | AE82: 0 | AF82: 0 | AG82: 0 | AH82: 0 | AI82: 0 | AJ82: 0 | AK82: 0 | AL82: 0 | AM82: 0 | AN82: 0 | AO82: 0 | AP82: 0 | AQ82: 0 | AR82: 0 | AS82: 0 | AT82: 0 | AU82: 0 | AV82: 0 | AW82: 0 | AX82: 0 | AY82: 0 | AZ82: 0
A83: hydrogen vehicle | B83: 1.3046217e+08 | C83: 1.304338e+08 | D83: 1.2761253e+08 | E83: 1.2512895e+08 | F83: 1.2262026e+08 | G83: 1.2002361e+08 | H83: 1.1774243e+08 | I83: 1.1564306e+08 | J83: 1.1364061e+08 | K83: 1.117326e+08 | L83: 1.0991364e+08 | M83: 1.0818226e+08 | N83: 1.0652426e+08 | O83: 1.0495522e+08 | P83: 1.0341527e+08 | Q83: 1.0193873e+08 | R83: 1.0053237e+08 | S83: 99191084 | T83: 97912130 | U83: 96693887 | V83: 95529373 | W83: 94420961 | X83: 93363765 | Y83: 92355508 | Z83: 91394875 | AA83: 90479192 | AB83: 89605842 | AC83: 88773909 | AD83: 87980403 | AE83: 87224793 | AF83: 86469910 | AG83: 80691855 | AH83: 79199012 | AI83: 77706169 | AJ83: 76213327 | AK83: 74720484 | AL83: 73227642 | AM83: 71734799 | AN83: 70241956 | AO83: 68749114 | AP83: 67256271 | AQ83: 65763429 | AR83: 64270586 | AS83: 62777744 | AT83: 61284901 | AU83: 59792058 | AV83: 58299216 | AW83: 56806373 | AX83: 55313531 | AY83: 53820688 | AZ83: 52327845
A85: BNVP-rail-frgt
A86: Price ($/vehicle) | B86: 2020 | C86: 2021 | D86: 2022 | E86: 2023 | F86: 2024 | G86: 2025 | H86: 2026 | I86: 2027 | J86: 2028 | K86: 2029 | L86: 2030 | M86: 2031 | N86: 2032 | O86: 2033 | P86: 2034 | Q86: 2035 | R86: 2036 | S86: 2037 | T86: 2038 | U86: 2039 | V86: 2040 | W86: 2041 | X86: 2042 | Y86: 2043 | Z86: 2044 | AA86: 2045 | AB86: 2046 | AC86: 2047 | AD86: 2048 | AE86: 2049 | AF86: 2050 | AG86: 2051 | AH86: 2052 | AI86: 2053 | AJ86: 2054 | AK86: 2055 | AL86: 2056 | AM86: 2057 | AN86: 2058 | AO86: 2059 | AP86: 2060 | AQ86: 2061 | AR86: 2062 | AS86: 2063 | AT86: 2064 | AU86: 2065 | AV86: 2066 | AW86: 2067 | AX86: 2068 | AY86: 2069 | AZ86: 2070
A87: battery electric vehicle | B87: 5000000 | C87: 5000000 | D87: 5000000 | E87: 5000000 | F87: 5000000 | G87: 5000000 | H87: 5000000 | I87: 5000000 | J87: 5000000 | K87: 5000000 | L87: 5000000 | M87: 5000000 | N87: 5000000 | O87: 5000000 | P87: 5000000 | Q87: 5000000 | R87: 5000000 | S87: 5000000 | T87: 5000000 | U87: 5000000 | V87: 5000000 | W87: 5000000 | X87: 5000000 | Y87: 5000000 | Z87: 5000000 | AA87: 5000000 | AB87: 5000000 | AC87: 5000000 | AD87: 5000000 | AE87: 5000000 | AF87: 5000000 | AG87: 5000000 | AH87: 5000000 | AI87: 5000000 | AJ87: 5000000 | AK87: 5000000 | AL87: 5000000 | AM87: 5000000 | AN87: 5000000 | AO87: 5000000 | AP87: 5000000 | AQ87: 5000000 | AR87: 5000000 | AS87: 5000000 | AT87: 5000000 | AU87: 5000000 | AV87: 5000000 | AW87: 5000000 | AX87: 5000000 | AY87: 5000000 | AZ87: 5000000
A88: natural gas vehicle | B88: 0 | C88: 0 | D88: 0 | E88: 0 | F88: 0 | G88: 0 | H88: 0 | I88: 0 | J88: 0 | K88: 0 | L88: 0 | M88: 0 | N88: 0 | O88: 0 | P88: 0 | Q88: 0 | R88: 0 | S88: 0 | T88: 0 | U88: 0 | V88: 0 | W88: 0 | X88: 0 | Y88: 0 | Z88: 0 | AA88: 0 | AB88: 0 | AC88: 0 | AD88: 0 | AE88: 0 | AF88: 0 | AG88: 0 | AH88: 0 | AI88: 0 | AJ88: 0 | AK88: 0 | AL88: 0 | AM88: 0 | AN88: 0 | AO88: 0 | AP88: 0 | AQ88: 0 | AR88: 0 | AS88: 0 | AT88: 0 | AU88: 0 | AV88: 0 | AW88: 0 | AX88: 0 | AY88: 0 | AZ88: 0
A89: gasoline vehicle | B89: 0 | C89: 0 | D89: 0 | E89: 0 | F89: 0 | G89: 0 | H89: 0 | I89: 0 | J89: 0 | K89: 0 | L89: 0 | M89: 0 | N89: 0 | O89: 0 | P89: 0 | Q89: 0 | R89: 0 | S89: 0 | T89: 0 | U89: 0 | V89: 0 | W89: 0 | X89: 0 | Y89: 0 | Z89: 0 | AA89: 0 | AB89: 0 | AC89: 0 | AD89: 0 | AE89: 0 | AF89: 0 | AG89: 0 | AH89: 0 | AI89: 0 | AJ89: 0 | AK89: 0 | AL89: 0 | AM89: 0 | AN89: 0 | AO89: 0 | AP89: 0 | AQ89: 0 | AR89: 0 | AS89: 0 | AT89: 0 | AU89: 0 | AV89: 0 | AW89: 0 | AX89: 0 | AY89: 0 | AZ89: 0
A90: diesel vehicle | B90: 2694164.4 | C90: 2694164.4 | D90: 2694164.4 | E90: 2694164.4 | F90: 2694164.4 | G90: 2694164.4 | H90: 2694164.4 | I90: 2694164.4 | J90: 2694164.4 | K90: 2694164.4 | L90: 2694164.4 | M90: 2694164.4 | N90: 2694164.4 | O90: 2694164.4 | P90: 2694164.4 | Q90: 2694164.4 | R90: 2694164.4 | S90: 2694164.4 | T90: 2694164.4 | U90: 2694164.4 | V90: 2694164.4 | W90: 2694164.4 | X90: 2694164.4 | Y90: 2694164.4 | Z90: 2694164.4 | AA90: 2694164.4 | AB90: 2694164.4 | AC90: 2694164.4 | AD90: 2694164.4 | AE90: 2694164.4 | AF90: 2694164.4 | AG90: 2694164.4 | AH90: 2694164.4 | AI90: 2694164.4 | AJ90: 2694164.4 | AK90: 2694164.4 | AL90: 2694164.4 | AM90: 2694164.4 | AN90: 2694164.4 | AO90: 2694164.4 | AP90: 2694164.4 | AQ90: 2694164.4 | AR90: 2694164.4 | AS90: 2694164.4 | AT90: 2694164.4 | AU90: 2694164.4 | AV90: 2694164.4 | AW90: 2694164.4 | AX90: 2694164.4 | AY90: 2694164.4 | AZ90: 2694164.4
A91: plugin hybrid vehicle | B91: 0 | C91: 0 | D91: 0 | E91: 0 | F91: 0 | G91: 0 | H91: 0 | I91: 0 | J91: 0 | K91: 0 | L91: 0 | M91: 0 | N91: 0 | O91: 0 | P91: 0 | Q91: 0 | R91: 0 | S91: 0 | T91: 0 | U91: 0 | V91: 0 | W91: 0 | X91: 0 | Y91: 0 | Z91: 0 | AA91: 0 | AB91: 0 | AC91: 0 | AD91: 0 | AE91: 0 | AF91: 0 | AG91: 0 | AH91: 0 | AI91: 0 | AJ91: 0 | AK91: 0 | AL91: 0 | AM91: 0 | AN91: 0 | AO91: 0 | AP91: 0 | AQ91: 0 | AR91: 0 | AS91: 0 | AT91: 0 | AU91: 0 | AV91: 0 | AW91: 0 | AX91: 0 | AY91: 0 | AZ91: 0
A92: LPG vehicle | B92: 0 | C92: 0 | D92: 0 | E92: 0 | F92: 0 | G92: 0 | H92: 0 | I92: 0 | J92: 0 | K92: 0 | L92: 0 | M92: 0 | N92: 0 | O92: 0 | P92: 0 | Q92: 0 | R92: 0 | S92: 0 | T92: 0 | U92: 0 | V92: 0 | W92: 0 | X92: 0 | Y92: 0 | Z92: 0 | AA92: 0 | AB92: 0 | AC92: 0 | AD92: 0 | AE92: 0 | AF92: 0 | AG92: 0 | AH92: 0 | AI92: 0 | AJ92: 0 | AK92: 0 | AL92: 0 | AM92: 0 | AN92: 0 | AO92: 0 | AP92: 0 | AQ92: 0 | AR92: 0 | AS92: 0 | AT92: 0 | AU92: 0 | AV92: 0 | AW92: 0 | AX92: 0 | AY92: 0 | AZ92: 0
A93: hydrogen vehicle | B93: 8351909.8 | C93: 8350093.3 | D93: 8169482 | E93: 8010488.2 | F93: 7849887.3 | G93: 7683655.5 | H93: 7537619.2 | I93: 7403221.8 | J93: 7275029 | K93: 7152882.7 | L93: 7036436.6 | M93: 6925597.2 | N93: 6819455.4 | O93: 6719009.3 | P93: 6620424.7 | Q93: 6525900.1 | R93: 6435867.6 | S93: 6350001.4 | T93: 6268125.5 | U93: 6190136.2 | V93: 6115586.5 | W93: 6044628.3 | X93: 5976948.9 | Y93: 5912402.4 | Z93: 5850904.8 | AA93: 5792284.7 | AB93: 5736374.7 | AC93: 5683116.1 | AD93: 5632317.5 | AE93: 5583945 | AF93: 5535619 | AG93: 5165720.2 | AH93: 5070151.6 | AI93: 4974583.1 | AJ93: 4879014.5 | AK93: 4783445.9 | AL93: 4687877.3 | AM93: 4592308.7 | AN93: 4496740.1 | AO93: 4401171.5 | AP93: 4305602.9 | AQ93: 4210034.3 | AR93: 4114465.7 | AS93: 4018897.1 | AT93: 3923328.5 | AU93: 3827759.9 | AV93: 3732191.3 | AW93: 3636622.7 | AX93: 3541054.1 | AY93: 3445485.5 | AZ93: 3349916.9
A95: BNVP-ships-psgr
A96: Price ($/vehicle) | B96: 2020 | C96: 2021 | D96: 2022 | E96: 2023 | F96: 2024 | G96: 2025 | H96: 2026 | I96: 2027 | J96: 2028 | K96: 2029 | L96: 2030 | M96: 2031 | N96: 2032 | O96: 2033 | P96: 2034 | Q96: 2035 | R96: 2036 | S96: 2037 | T96: 2038 | U96: 2039 | V96: 2040 | W96: 2041 | X96: 2042 | Y96: 2043 | Z96: 2044 | AA96: 2045 | AB96: 2046 | AC96: 2047 | AD96: 2048 | AE96: 2049 | AF96: 2050 | AG96: 2051 | AH96: 2052 | AI96: 2053 | AJ96: 2054 | AK96: 2055 | AL96: 2056 | AM96: 2057 | AN96: 2058 | AO96: 2059 | AP96: 2060 | AQ96: 2061 | AR96: 2062 | AS96: 2063 | AT96: 2064 | AU96: 2065 | AV96: 2066 | AW96: 2067 | AX96: 2068 | AY96: 2069 | AZ96: 2070
A97: battery electric vehicle | B97: 55456.75 | C97: 55456.75 | D97: 55456.75 | E97: 55456.75 | F97: 55456.75 | G97: 55456.75 | H97: 55456.75 | I97: 55456.75 | J97: 55456.75 | K97: 55456.75 | L97: 55456.75 | M97: 55456.75 | N97: 55456.75 | O97: 55456.75 | P97: 55456.75 | Q97: 55456.75 | R97: 55456.75 | S97: 55456.75 | T97: 55456.75 | U97: 55456.75 | V97: 55456.75 | W97: 55456.75 | X97: 55456.75 | Y97: 55456.75 | Z97: 55456.75 | AA97: 55456.75 | AB97: 55456.75 | AC97: 55456.75 | AD97: 55456.75 | AE97: 55456.75 | AF97: 55456.75 | AG97: 55456.75 | AH97: 55456.75 | AI97: 55456.75 | AJ97: 55456.75 | AK97: 55456.75 | AL97: 55456.75 | AM97: 55456.75 | AN97: 55456.75 | AO97: 55456.75 | AP97: 55456.75 | AQ97: 55456.75 | AR97: 55456.75 | AS97: 55456.75 | AT97: 55456.75 | AU97: 55456.75 | AV97: 55456.75 | AW97: 55456.75 | AX97: 55456.75 | AY97: 55456.75 | AZ97: 55456.75
A98: natural gas vehicle | B98: 0 | C98: 0 | D98: 0 | E98: 0 | F98: 0 | G98: 0 | H98: 0 | I98: 0 | J98: 0 | K98: 0 | L98: 0 | M98: 0 | N98: 0 | O98: 0 | P98: 0 | Q98: 0 | R98: 0 | S98: 0 | T98: 0 | U98: 0 | V98: 0 | W98: 0 | X98: 0 | Y98: 0 | Z98: 0 | AA98: 0 | AB98: 0 | AC98: 0 | AD98: 0 | AE98: 0 | AF98: 0 | AG98: 0 | AH98: 0 | AI98: 0 | AJ98: 0 | AK98: 0 | AL98: 0 | AM98: 0 | AN98: 0 | AO98: 0 | AP98: 0 | AQ98: 0 | AR98: 0 | AS98: 0 | AT98: 0 | AU98: 0 | AV98: 0 | AW98: 0 | AX98: 0 | AY98: 0 | AZ98: 0
A99: gasoline vehicle | B99: 30000 | C99: 30000 | D99: 30000 | E99: 30000 | F99: 30000 | G99: 30000 | H99: 30000 | I99: 30000 | J99: 30000 | K99: 30000 | L99: 30000 | M99: 30000 | N99: 30000 | O99: 30000 | P99: 30000 | Q99: 30000 | R99: 30000 | S99: 30000 | T99: 30000 | U99: 30000 | V99: 30000 | W99: 30000 | X99: 30000 | Y99: 30000 | Z99: 30000 | AA99: 30000 | AB99: 30000 | AC99: 30000 | AD99: 30000 | AE99: 30000 | AF99: 30000 | AG99: 30000 | AH99: 30000 | AI99: 30000 | AJ99: 30000 | AK99: 30000 | AL99: 30000 | AM99: 30000 | AN99: 30000 | AO99: 30000 | AP99: 30000 | AQ99: 30000 | AR99: 30000 | AS99: 30000 | AT99: 30000 | AU99: 30000 | AV99: 30000 | AW99: 30000 | AX99: 30000 | AY99: 30000 | AZ99: 30000
A100: diesel vehicle | B100: 30000 | C100: 30000 | D100: 30000 | E100: 30000 | F100: 30000 | G100: 30000 | H100: 30000 | I100: 30000 | J100: 30000 | K100: 30000 | L100: 30000 | M100: 30000 | N100: 30000 | O100: 30000 | P100: 30000 | Q100: 30000 | R100: 30000 | S100: 30000 | T100: 30000 | U100: 30000 | V100: 30000 | W100: 30000 | X100: 30000 | Y100: 30000 | Z100: 30000 | AA100: 30000 | AB100: 30000 | AC100: 30000 | AD100: 30000 | AE100: 30000 | AF100: 30000 | AG100: 30000 | AH100: 30000 | AI100: 30000 | AJ100: 30000 | AK100: 30000 | AL100: 30000 | AM100: 30000 | AN100: 30000 | AO100: 30000 | AP100: 30000 | AQ100: 30000 | AR100: 30000 | AS100: 30000 | AT100: 30000 | AU100: 30000 | AV100: 30000 | AW100: 30000 | AX100: 30000 | AY100: 30000 | AZ100: 30000
A101: plugin hybrid vehicle | B101: 0 | C101: 0 | D101: 0 | E101: 0 | F101: 0 | G101: 0 | H101: 0 | I101: 0 | J101: 0 | K101: 0 | L101: 0 | M101: 0 | N101: 0 | O101: 0 | P101: 0 | Q101: 0 | R101: 0 | S101: 0 | T101: 0 | U101: 0 | V101: 0 | W101: 0 | X101: 0 | Y101: 0 | Z101: 0 | AA101: 0 | AB101: 0 | AC101: 0 | AD101: 0 | AE101: 0 | AF101: 0 | AG101: 0 | AH101: 0 | AI101: 0 | AJ101: 0 | AK101: 0 | AL101: 0 | AM101: 0 | AN101: 0 | AO101: 0 | AP101: 0 | AQ101: 0 | AR101: 0 | AS101: 0 | AT101: 0 | AU101: 0 | AV101: 0 | AW101: 0 | AX101: 0 | AY101: 0 | AZ101: 0
A102: LPG vehicle | B102: 0 | C102: 0 | D102: 0 | E102: 0 | F102: 0 | G102: 0 | H102: 0 | I102: 0 | J102: 0 | K102: 0 | L102: 0 | M102: 0 | N102: 0 | O102: 0 | P102: 0 | Q102: 0 | R102: 0 | S102: 0 | T102: 0 | U102: 0 | V102: 0 | W102: 0 | X102: 0 | Y102: 0 | Z102: 0 | AA102: 0 | AB102: 0 | AC102: 0 | AD102: 0 | AE102: 0 | AF102: 0 | AG102: 0 | AH102: 0 | AI102: 0 | AJ102: 0 | AK102: 0 | AL102: 0 | AM102: 0 | AN102: 0 | AO102: 0 | AP102: 0 | AQ102: 0 | AR102: 0 | AS102: 0 | AT102: 0 | AU102: 0 | AV102: 0 | AW102: 0 | AX102: 0 | AY102: 0 | AZ102: 0
A103: hydrogen vehicle | B103: 60368.101 | C103: 60354.971 | D103: 59049.502 | E103: 57900.285 | F103: 56739.452 | G103: 55537.919 | H103: 54482.36 | I103: 53510.928 | J103: 52584.343 | K103: 51701.461 | L103: 50859.782 | M103: 50058.629 | N103: 49291.429 | O103: 48565.399 | P103: 47852.824 | Q103: 47169.594 | R103: 46518.834 | S103: 45898.188 | T103: 45306.384 | U103: 44742.673 | V103: 44203.823 | W103: 43690.933 | X103: 43201.742 | Y103: 42735.197 | Z103: 42290.688 | AA103: 41866.978 | AB103: 41462.857 | AC103: 41077.901 | AD103: 40710.726 | AE103: 40361.087 | AF103: 40011.784 | AG103: 37338.133 | AH103: 36647.358 | AI103: 35956.582 | AJ103: 35265.807 | AK103: 34575.031 | AL103: 33884.256 | AM103: 33193.48 | AN103: 32502.705 | AO103: 31811.929 | AP103: 31121.154 | AQ103: 30430.378 | AR103: 29739.603 | AS103: 29048.827 | AT103: 28358.052 | AU103: 27667.276 | AV103: 26976.501 | AW103: 26285.725 | AX103: 25594.95 | AY103: 24904.174 | AZ103: 24213.399
A105: BNVP-ships-frgt
A106: Price ($/vehicle) | B106: 2020 | C106: 2021 | D106: 2022 | E106: 2023 | F106: 2024 | G106: 2025 | H106: 2026 | I106: 2027 | J106: 2028 | K106: 2029 | L106: 2030 | M106: 2031 | N106: 2032 | O106: 2033 | P106: 2034 | Q106: 2035 | R106: 2036 | S106: 2037 | T106: 2038 | U106: 2039 | V106: 2040 | W106: 2041 | X106: 2042 | Y106: 2043 | Z106: 2044 | AA106: 2045 | AB106: 2046 | AC106: 2047 | AD106: 2048 | AE106: 2049 | AF106: 2050 | AG106: 2051 | AH106: 2052 | AI106: 2053 | AJ106: 2054 | AK106: 2055 | AL106: 2056 | AM106: 2057 | AN106: 2058 | AO106: 2059 | AP106: 2060 | AQ106: 2061 | AR106: 2062 | AS106: 2063 | AT106: 2064 | AU106: 2065 | AV106: 2066 | AW106: 2067 | AX106: 2068 | AY106: 2069 | AZ106: 2070
A107: battery electric vehicle | B107: 18485583 | C107: 18485583 | D107: 18485583 | E107: 18485583 | F107: 18485583 | G107: 18485583 | H107: 18485583 | I107: 18485583 | J107: 18485583 | K107: 18485583 | L107: 18485583 | M107: 18485583 | N107: 18485583 | O107: 18485583 | P107: 18485583 | Q107: 18485583 | R107: 18485583 | S107: 18485583 | T107: 18485583 | U107: 18485583 | V107: 18485583 | W107: 18485583 | X107: 18485583 | Y107: 18485583 | Z107: 18485583 | AA107: 18485583 | AB107: 18485583 | AC107: 18485583 | AD107: 18485583 | AE107: 18485583 | AF107: 18485583 | AG107: 18485583 | AH107: 18485583 | AI107: 18485583 | AJ107: 18485583 | AK107: 18485583 | AL107: 18485583 | AM107: 18485583 | AN107: 18485583 | AO107: 18485583 | AP107: 18485583 | AQ107: 18485583 | AR107: 18485583 | AS107: 18485583 | AT107: 18485583 | AU107: 18485583 | AV107: 18485583 | AW107: 18485583 | AX107: 18485583 | AY107: 18485583 | AZ107: 18485583
A108: natural gas vehicle | B108: 0 | C108: 0 | D108: 0 | E108: 0 | F108: 0 | G108: 0 | H108: 0 | I108: 0 | J108: 0 | K108: 0 | L108: 0 | M108: 0 | N108: 0 | O108: 0 | P108: 0 | Q108: 0 | R108: 0 | S108: 0 | T108: 0 | U108: 0 | V108: 0 | W108: 0 | X108: 0 | Y108: 0 | Z108: 0 | AA108: 0 | AB108: 0 | AC108: 0 | AD108: 0 | AE108: 0 | AF108: 0 | AG108: 0 | AH108: 0 | AI108: 0 | AJ108: 0 | AK108: 0 | AL108: 0 | AM108: 0 | AN108: 0 | AO108: 0 | AP108: 0 | AQ108: 0 | AR108: 0 | AS108: 0 | AT108: 0 | AU108: 0 | AV108: 0 | AW108: 0 | AX108: 0 | AY108: 0 | AZ108: 0
A109: gasoline vehicle | B109: 0 | C109: 0 | D109: 0 | E109: 0 | F109: 0 | G109: 0 | H109: 0 | I109: 0 | J109: 0 | K109: 0 | L109: 0 | M109: 0 | N109: 0 | O109: 0 | P109: 0 | Q109: 0 | R109: 0 | S109: 0 | T109: 0 | U109: 0 | V109: 0 | W109: 0 | X109: 0 | Y109: 0 | Z109: 0 | AA109: 0 | AB109: 0 | AC109: 0 | AD109: 0 | AE109: 0 | AF109: 0 | AG109: 0 | AH109: 0 | AI109: 0 | AJ109: 0 | AK109: 0 | AL109: 0 | AM109: 0 | AN109: 0 | AO109: 0 | AP109: 0 | AQ109: 0 | AR109: 0 | AS109: 0 | AT109: 0 | AU109: 0 | AV109: 0 | AW109: 0 | AX109: 0 | AY109: 0 | AZ109: 0
A110: diesel vehicle | B110: 10000000 | C110: 10000000 | D110: 10000000 | E110: 10000000 | F110: 10000000 | G110: 10000000 | H110: 10000000 | I110: 10000000 | J110: 10000000 | K110: 10000000 | L110: 10000000 | M110: 10000000 | N110: 10000000 | O110: 10000000 | P110: 10000000 | Q110: 10000000 | R110: 10000000 | S110: 10000000 | T110: 10000000 | U110: 10000000 | V110: 10000000 | W110: 10000000 | X110: 10000000 | Y110: 10000000 | Z110: 10000000 | AA110: 10000000 | AB110: 10000000 | AC110: 10000000 | AD110: 10000000 | AE110: 10000000 | AF110: 10000000 | AG110: 10000000 | AH110: 10000000 | AI110: 10000000 | AJ110: 10000000 | AK110: 10000000 | AL110: 10000000 | AM110: 10000000 | AN110: 10000000 | AO110: 10000000 | AP110: 10000000 | AQ110: 10000000 | AR110: 10000000 | AS110: 10000000 | AT110: 10000000 | AU110: 10000000 | AV110: 10000000 | AW110: 10000000 | AX110: 10000000 | AY110: 10000000 | AZ110: 10000000
A111: plugin hybrid vehicle | B111: 0 | C111: 0 | D111: 0 | E111: 0 | F111: 0 | G111: 0 | H111: 0 | I111: 0 | J111: 0 | K111: 0 | L111: 0 | M111: 0 | N111: 0 | O111: 0 | P111: 0 | Q111: 0 | R111: 0 | S111: 0 | T111: 0 | U111: 0 | V111: 0 | W111: 0 | X111: 0 | Y111: 0 | Z111: 0 | AA111: 0 | AB111: 0 | AC111: 0 | AD111: 0 | AE111: 0 | AF111: 0 | AG111: 0 | AH111: 0 | AI111: 0 | AJ111: 0 | AK111: 0 | AL111: 0 | AM111: 0 | AN111: 0 | AO111: 0 | AP111: 0 | AQ111: 0 | AR111: 0 | AS111: 0 | AT111: 0 | AU111: 0 | AV111: 0 | AW111: 0 | AX111: 0 | AY111: 0 | AZ111: 0
A112: LPG vehicle | B112: 0 | C112: 0 | D112: 0 | E112: 0 | F112: 0 | G112: 0 | H112: 0 | I112: 0 | J112: 0 | K112: 0 | L112: 0 | M112: 0 | N112: 0 | O112: 0 | P112: 0 | Q112: 0 | R112: 0 | S112: 0 | T112: 0 | U112: 0 | V112: 0 | W112: 0 | X112: 0 | Y112: 0 | Z112: 0 | AA112: 0 | AB112: 0 | AC112: 0 | AD112: 0 | AE112: 0 | AF112: 0 | AG112: 0 | AH112: 0 | AI112: 0 | AJ112: 0 | AK112: 0 | AL112: 0 | AM112: 0 | AN112: 0 | AO112: 0 | AP112: 0 | AQ112: 0 | AR112: 0 | AS112: 0 | AT112: 0 | AU112: 0 | AV112: 0 | AW112: 0 | AX112: 0 | AY112: 0 | AZ112: 0
...

Sheet BNVP-LDVs-psgr
A1: Price ($/vehicle) | B1: 2020 | C1: 2021 | D1: 2022 | E1: 2023 | F1: 2024 | G1: 2025 | H1: 2026 | I1: 2027 | J1: 2028 | K1: 2029 | L1: 2030 | M1: 2031 | N1: 2032 | O1: 2033 | P1: 2034 | Q1: 2035 | R1: 2036 | S1: 2037 | T1: 2038 | U1: 2039 | V1: 2040 | W1: 2041 | X1: 2042 | Y1: 2043 | Z1: 2044 | AA1: 2045 | AB1: 2046 | AC1: 2047 | AD1: 2048 | AE1: 2049 | AF1: 2050 | AG1: 2051 | AH1: 2052 | AI1: 2053 | AJ1: 2054 | AK1: 2055 | AL1: 2056 | AM1: 2057 | AN1: 2058 | AO1: 2059 | AP1: 2060 | AQ1: 2061 | AR1: 2062 | AS1: 2063 | AT1: 2064 | AU1: 2065 | AV1: 2066 | AW1: 2067 | AX1: 2068 | AY1: 2069 | AZ1: 2070
A2: battery electric vehicle | B2: =('NVP-Indonesia'!$B$12+'NVP-Indonesia'!$B$12*'NVP-Indonesia'!$B140) -> 21521.202 | C2: =(B2+B2*'NVP-Indonesia'!$B140) -> 21187.654 | D2: =(C2+C2*'NVP-Indonesia'!$B140) -> 20859.276 | E2: =(D2+D2*'NVP-Indonesia'!$B140) -> 20535.987 | F2: =(E2+E2*'NVP-Indonesia'!$B140) -> 20217.709 | G2: =(F2+F2*'NVP-Indonesia'!$B140) -> 19904.364 | H2: =(G2+G2*'NVP-Indonesia'!$B140) -> 19595.875 | I2: =(H2+H2*'NVP-Indonesia'!$B140) -> 19292.167 | J2: =(I2+I2*'NVP-Indonesia'!$B140) -> 18993.166 | ... AZ2: =(AY2+AY2*'NVP-Indonesia'!$B140) -> 9855.6297
A3: natural gas vehicle | B3: =('NVP-Indonesia'!$B$12+'NVP-Indonesia'!$B$12*'NVP-Indonesia'!$B141) -> 21914.895 | C3: =(B3+B3*'NVP-Indonesia'!$B141) -> 21969.927 | D3: =(C3+C3*'NVP-Indonesia'!$B141) -> 22025.098 | E3: =(D3+D3*'NVP-Indonesia'!$B141) -> 22080.407 | F3: =(E3+E3*'NVP-Indonesia'!$B141) -> 22135.855 | G3: =(F3+F3*'NVP-Indonesia'!$B141) -> 22191.443 | H3: =(G3+G3*'NVP-Indonesia'!$B141) -> 22247.17 | I3: =(H3+H3*'NVP-Indonesia'!$B141) -> 22303.037 | J3: =(I3+I3*'NVP-Indonesia'!$B141) -> 22359.044 | ... AZ3: =(AY3+AY3*'NVP-Indonesia'!$B141) -> 24842.82
A4: gasoline vehicle | B4: =('NVP-Indonesia'!$B$12+'NVP-Indonesia'!$B$12*'NVP-Indonesia'!$B142) -> 21864.419 | C4: =(B4+B4*'NVP-Indonesia'!$B142) -> 21868.839 | D4: =(C4+C4*'NVP-Indonesia'!$B142) -> 21873.26 | E4: =(D4+D4*'NVP-Indonesia'!$B142) -> 21877.682 | F4: =(E4+E4*'NVP-Indonesia'!$B142) -> 21882.104 | G4: =(F4+F4*'NVP-Indonesia'!$B142) -> 21886.528 | H4: =(G4+G4*'NVP-Indonesia'!$B142) -> 21890.952 | I4: =(H4+H4*'NVP-Indonesia'!$B142) -> 21895.378 | J4: =(I4+I4*'NVP-Indonesia'!$B142) -> 21899.804 | ... AZ4: =(AY4+AY4*'NVP-Indonesia'!$B142) -> 22086.516
A5: diesel vehicle | B5: =('NVP-Indonesia'!$B$12+'NVP-Indonesia'!$B$12*'NVP-Indonesia'!$B143) -> 21850.328 | C5: =(B5+B5*'NVP-Indonesia'!$B143) -> 21840.66 | D5: =(C5+C5*'NVP-Indonesia'!$B143) -> 21830.996 | E5: =(D5+D5*'NVP-Indonesia'!$B143) -> 21821.337 | F5: =(E5+E5*'NVP-Indonesia'!$B143) -> 21811.682 | G5: =(F5+F5*'NVP-Indonesia'!$B143) -> 21802.031 | H5: =(G5+G5*'NVP-Indonesia'!$B143) -> 21792.384 | I5: =(H5+H5*'NVP-Indonesia'!$B143) -> 21782.742 | J5: =(I5+I5*'NVP-Indonesia'!$B143) -> 21773.104 | ... AZ5: =(AY5+AY5*'NVP-Indonesia'!$B143) -> 21372.133
A6: plugin hybrid vehicle | B6: =('NVP-Indonesia'!$B$12+'NVP-Indonesia'!$B$12*'NVP-Indonesia'!$B144) -> 21890.968 | C6: =(B6+B6*'NVP-Indonesia'!$B144) -> 21921.981 | D6: =(C6+C6*'NVP-Indonesia'!$B144) -> 21953.037 | E6: =(D6+D6*'NVP-Indonesia'!$B144) -> 21984.137 | F6: =(E6+E6*'NVP-Indonesia'!$B144) -> 22015.282 | G6: =(F6+F6*'NVP-Indonesia'!$B144) -> 22046.47 | H6: =(G6+G6*'NVP-Indonesia'!$B144) -> 22077.703 | I6: =(H6+H6*'NVP-Indonesia'!$B144) -> 22108.98 | J6: =(I6+I6*'NVP-Indonesia'!$B144) -> 22140.301 | ... AZ6: =(AY6+AY6*'NVP-Indonesia'!$B144) -> 23496.647
A7: LPG vehicle | B7: =('NVP-Indonesia'!$B$12+'NVP-Indonesia'!$B$12*'NVP-Indonesia'!$B145) -> 21898.341 | C7: =(B7+B7*'NVP-Indonesia'!$B145) -> 21936.748 | D7: =(C7+C7*'NVP-Indonesia'!$B145) -> 21975.224 | E7: =(D7+D7*'NVP-Indonesia'!$B145) -> 22013.766 | F7: =(E7+E7*'NVP-Indonesia'!$B145) -> 22052.376 | G7: =(F7+F7*'NVP-Indonesia'!$B145) -> 22091.054 | H7: =(G7+G7*'NVP-Indonesia'!$B145) -> 22129.8 | I7: =(H7+H7*'NVP-Indonesia'!$B145) -> 22168.614 | J7: =(I7+I7*'NVP-Indonesia'!$B145) -> 22207.496 | ... AZ7: =(AY7+AY7*'NVP-Indonesia'!$B145) -> 23903.615
A8: hydrogen vehicle | B8: =('NVP-Indonesia'!$B$12+'NVP-Indonesia'!$B$12*'NVP-Indonesia'!$B146) -> 21464.221 | C8: =(B8+B8*'NVP-Indonesia'!$B146) -> 21075.607 | D8: =(C8+C8*'NVP-Indonesia'!$B146) -> 20694.029 | E8: =(D8+D8*'NVP-Indonesia'!$B146) -> 20319.36 | F8: =(E8+E8*'NVP-Indonesia'!$B146) -> 19951.474 | G8: =(F8+F8*'NVP-Indonesia'!$B146) -> 19590.249 | H8: =(G8+G8*'NVP-Indonesia'!$B146) -> 19235.563 | I8: =(H8+H8*'NVP-Indonesia'!$B146) -> 18887.3 | J8: =(I8+I8*'NVP-Indonesia'!$B146) -> 18545.342 | ... AZ8: =(AY8+AY8*'NVP-Indonesia'!$B146) -> 8609.2113

Sheet BNVP-LDVs-frgt
A1: Price ($/vehicle) | B1: 2020 | C1: 2021 | D1: 2022 | E1: 2023 | F1: 2024 | G1: 2025 | H1: 2026 | I1: 2027 | J1: 2028 | K1: 2029 | L1: 2030 | M1: 2031 | N1: 2032 | O1: 2033 | P1: 2034 | Q1: 2035 | R1: 2036 | S1: 2037 | T1: 2038 | U1: 2039 | V1: 2040 | W1: 2041 | X1: 2042 | Y1: 2043 | Z1: 2044 | AA1: 2045 | AB1: 2046 | AC1: 2047 | AD1: 2048 | AE1: 2049 | AF1: 2050 | AG1: 2051 | AH1: 2052 | AI1: 2053 | AJ1: 2054 | AK1: 2055 | AL1: 2056 | AM1: 2057 | AN1: 2058 | AO1: 2059 | AP1: 2060 | AQ1: 2061 | AR1: 2062 | AS1: 2063 | AT1: 2064 | AU1: 2065 | AV1: 2066 | AW1: 2067 | AX1: 2068 | AY1: 2069 | AZ1: 2070
A2: battery electric vehicle | B2: ='NVP-Indonesia'!B27*'NVP-Indonesia'!$B$176 -> 58095.337 | C2: ='NVP-Indonesia'!C27*'NVP-Indonesia'!$B$176 -> 58095.337 | D2: ='NVP-Indonesia'!D27*'NVP-Indonesia'!$B$176 -> 58095.337 | E2: ='NVP-Indonesia'!E27*'NVP-Indonesia'!$B$176 -> 58095.337 | F2: ='NVP-Indonesia'!F27*'NVP-Indonesia'!$B$176 -> 58095.337 | G2: ='NVP-Indonesia'!G27*'NVP-Indonesia'!$B$176 -> 58095.337 | H2: ='NVP-Indonesia'!H27*'NVP-Indonesia'!$B$176 -> 58095.337 | I2: ='NVP-Indonesia'!I27*'NVP-Indonesia'!$B$176 -> 58095.337 | ... AZ2: ='NVP-Indonesia'!AZ27*'NVP-Indonesia'!$B$176 -> 58095.337
A3: natural gas vehicle | B3: ='NVP-Indonesia'!B28*'NVP-Indonesia'!$B$176 -> 40546.809 | C3: ='NVP-Indonesia'!C28*'NVP-Indonesia'!$B$176 -> 40255.116 | D3: ='NVP-Indonesia'!D28*'NVP-Indonesia'!$B$176 -> 40428.95 | E3: ='NVP-Indonesia'!E28*'NVP-Indonesia'!$B$176 -> 40700.245 | F3: ='NVP-Indonesia'!F28*'NVP-Indonesia'!$B$176 -> 40909.339 | G3: ='NVP-Indonesia'!G28*'NVP-Indonesia'!$B$176 -> 41114.274 | H3: ='NVP-Indonesia'!H28*'NVP-Indonesia'!$B$176 -> 41303.342 | I3: ='NVP-Indonesia'!I28*'NVP-Indonesia'!$B$176 -> 41474.586 | ... AZ3: ='NVP-Indonesia'!AZ28*'NVP-Indonesia'!$B$176 -> 45964.038
A4: gasoline vehicle | B4: ='NVP-Indonesia'!B29*'NVP-Indonesia'!$B$176 -> 35674.636 | C4: ='NVP-Indonesia'!C29*'NVP-Indonesia'!$B$176 -> 35674.636 | D4: ='NVP-Indonesia'!D29*'NVP-Indonesia'!$B$176 -> 35674.636 | E4: ='NVP-Indonesia'!E29*'NVP-Indonesia'!$B$176 -> 35674.636 | F4: ='NVP-Indonesia'!F29*'NVP-Indonesia'!$B$176 -> 35674.636 | G4: ='NVP-Indonesia'!G29*'NVP-Indonesia'!$B$176 -> 35674.636 | H4: ='NVP-Indonesia'!H29*'NVP-Indonesia'!$B$176 -> 35674.636 | I4: ='NVP-Indonesia'!I29*'NVP-Indonesia'!$B$176 -> 35674.636 | ... AZ4: ='NVP-Indonesia'!AZ29*'NVP-Indonesia'!$B$176 -> 35674.636
A5: diesel vehicle | B5: ='NVP-Indonesia'!B30*'NVP-Indonesia'!$B$176 -> 39638.484 | C5: ='NVP-Indonesia'!C30*'NVP-Indonesia'!$B$176 -> 39638.484 | D5: ='NVP-Indonesia'!D30*'NVP-Indonesia'!$B$176 -> 39638.484 | E5: ='NVP-Indonesia'!E30*'NVP-Indonesia'!$B$176 -> 39638.484 | F5: ='NVP-Indonesia'!F30*'NVP-Indonesia'!$B$176 -> 39638.484 | G5: ='NVP-Indonesia'!G30*'NVP-Indonesia'!$B$176 -> 39638.484 | H5: ='NVP-Indonesia'!H30*'NVP-Indonesia'!$B$176 -> 39638.484 | I5: ='NVP-Indonesia'!I30*'NVP-Indonesia'!$B$176 -> 39638.484 | ... AZ5: ='NVP-Indonesia'!AZ30*'NVP-Indonesia'!$B$176 -> 39638.484
A6: plugin hybrid vehicle | B6: ='NVP-Indonesia'!B31*'NVP-Indonesia'!$B$176 -> 40685.859 | C6: ='NVP-Indonesia'!C31*'NVP-Indonesia'!$B$176 -> 41242.058 | D6: ='NVP-Indonesia'!D31*'NVP-Indonesia'!$B$176 -> 41182.553 | E6: ='NVP-Indonesia'!E31*'NVP-Indonesia'!$B$176 -> 41385.132 | F6: ='NVP-Indonesia'!F31*'NVP-Indonesia'!$B$176 -> 41430.439 | G6: ='NVP-Indonesia'!G31*'NVP-Indonesia'!$B$176 -> 41553.938 | H6: ='NVP-Indonesia'!H31*'NVP-Indonesia'!$B$176 -> 41604.402 | I6: ='NVP-Indonesia'!I31*'NVP-Indonesia'!$B$176 -> 41633.147 | ... AZ6: ='NVP-Indonesia'!AZ31*'NVP-Indonesia'!$B$176 -> 43670.122
A7: LPG vehicle | B7: ='NVP-Indonesia'!B32*'NVP-Indonesia'!$B$176 -> 39630.84 | C7: ='NVP-Indonesia'!C32*'NVP-Indonesia'!$B$176 -> 40279.913 | D7: ='NVP-Indonesia'!D32*'NVP-Indonesia'!$B$176 -> 40242.618 | E7: ='NVP-Indonesia'!E32*'NVP-Indonesia'!$B$176 -> 40312.727 | F7: ='NVP-Indonesia'!F32*'NVP-Indonesia'!$B$176 -> 40407.796 | G7: ='NVP-Indonesia'!G32*'NVP-Indonesia'!$B$176 -> 40584.919 | H7: ='NVP-Indonesia'!H32*'NVP-Indonesia'!$B$176 -> 40732.9 | I7: ='NVP-Indonesia'!I32*'NVP-Indonesia'!$B$176 -> 40808.85 | ... AZ7: ='NVP-Indonesia'!AZ32*'NVP-Indonesia'!$B$176 -> 43259.916
A8: hydrogen vehicle | B8: ='NVP-Indonesia'!B33*'NVP-Indonesia'!$B$176 -> 72784.944 | C8: ='NVP-Indonesia'!C33*'NVP-Indonesia'!$B$176 -> 72769.113 | D8: ='NVP-Indonesia'!D33*'NVP-Indonesia'!$B$176 -> 71195.128 | E8: ='NVP-Indonesia'!E33*'NVP-Indonesia'!$B$176 -> 69809.534 | F8: ='NVP-Indonesia'!F33*'NVP-Indonesia'!$B$176 -> 68409.935 | G8: ='NVP-Indonesia'!G33*'NVP-Indonesia'!$B$176 -> 66961.263 | H8: ='NVP-Indonesia'!H33*'NVP-Indonesia'!$B$176 -> 65688.591 | I8: ='NVP-Indonesia'!I33*'NVP-Indonesia'!$B$176 -> 64517.35 | ... AZ8: ='NVP-Indonesia'!AZ33*'NVP-Indonesia'!$B$176 -> 29193.744

Sheet BNVP-HDVs-psgr
A1: Price ($/vehicle) | B1: 2020 | C1: 2021 | D1: 2022 | E1: 2023 | F1: 2024 | G1: 2025 | H1: 2026 | I1: 2027 | J1: 2028 | K1: 2029 | L1: 2030 | M1: 2031 | N1: 2032 | O1: 2033 | P1: 2034 | Q1: 2035 | R1: 2036 | S1: 2037 | T1: 2038 | U1: 2039 | V1: 2040 | W1: 2041 | X1: 2042 | Y1: 2043 | Z1: 2044 | AA1: 2045 | AB1: 2046 | AC1: 2047 | AD1: 2048 | AE1: 2049 | AF1: 2050 | AG1: 2051 | AH1: 2052 | AI1: 2053 | AJ1: 2054 | AK1: 2055 | AL1: 2056 | AM1: 2057 | AN1: 2058 | AO1: 2059 | AP1: 2060 | AQ1: 2061 | AR1: 2062 | AS1: 2063 | AT1: 2064 | AU1: 2065 | AV1: 2066 | AW1: 2067 | AX1: 2068 | AY1: 2069 | AZ1: 2070
A2: battery electric vehicle | B2: ='NVP-Indonesia'!$B$12+'NVP-Indonesia'!$B$12*'NVP-Indonesia'!B151 -> 21860 | C2: =B2+B2*'NVP-Indonesia'!B151 -> 21860 | D2: =C2+C2*'NVP-Indonesia'!C151 -> 21860 | E2: =D2+D2*'NVP-Indonesia'!D151 -> 21860 | F2: =E2+E2*'NVP-Indonesia'!E151 -> 21860 | G2: =F2+F2*'NVP-Indonesia'!F151 -> 21860 | H2: =G2+G2*'NVP-Indonesia'!G151 -> 21860 | I2: =H2+H2*'NVP-Indonesia'!H151 -> 21860 | J2: =I2+I2*'NVP-Indonesia'!I151 -> 21860 | ... AZ2: =AY2+AY2*'NVP-Indonesia'!AY151 -> 21860
A3: natural gas vehicle | B3: ='NVP-Indonesia'!$B$12+'NVP-Indonesia'!$B$12*'NVP-Indonesia'!B152 -> 21914.895 | C3: =B3+B3*'NVP-Indonesia'!B152 -> 21969.927 | D3: =C3+C3*'NVP-Indonesia'!C152 -> 21969.927 | E3: =D3+D3*'NVP-Indonesia'!D152 -> 21969.927 | F3: =E3+E3*'NVP-Indonesia'!E152 -> 21969.927 | G3: =F3+F3*'NVP-Indonesia'!F152 -> 21969.927 | H3: =G3+G3*'NVP-Indonesia'!G152 -> 21969.927 | I3: =H3+H3*'NVP-Indonesia'!H152 -> 21969.927 | J3: =I3+I3*'NVP-Indonesia'!I152 -> 21969.927 | ... AZ3: =AY3+AY3*'NVP-Indonesia'!AY152 -> 21969.927
A4: gasoline vehicle | B4: ='NVP-Indonesia'!$B$12+'NVP-Indonesia'!$B$12*'NVP-Indonesia'!B153 -> 21860 | C4: =B4+B4*'NVP-Indonesia'!B153 -> 21860 | D4: =C4+C4*'NVP-Indonesia'!C153 -> 21860 | E4: =D4+D4*'NVP-Indonesia'!D153 -> 21860 | F4: =E4+E4*'NVP-Indonesia'!E153 -> 21860 | G4: =F4+F4*'NVP-Indonesia'!F153 -> 21860 | H4: =G4+G4*'NVP-Indonesia'!G153 -> 21860 | I4: =H4+H4*'NVP-Indonesia'!H153 -> 21860 | J4: =I4+I4*'NVP-Indonesia'!I153 -> 21860 | ... AZ4: =AY4+AY4*'NVP-Indonesia'!AY153 -> 21860
A5: diesel vehicle | B5: ='NVP-Indonesia'!$B$12+'NVP-Indonesia'!$B$12*'NVP-Indonesia'!B154 -> 21860 | C5: =B5+B5*'NVP-Indonesia'!B154 -> 21860 | D5: =C5+C5*'NVP-Indonesia'!C154 -> 21860 | E5: =D5+D5*'NVP-Indonesia'!D154 -> 21860 | F5: =E5+E5*'NVP-Indonesia'!E154 -> 21860 | G5: =F5+F5*'NVP-Indonesia'!F154 -> 21860 | H5: =G5+G5*'NVP-Indonesia'!G154 -> 21860 | I5: =H5+H5*'NVP-Indonesia'!H154 -> 21860 | J5: =I5+I5*'NVP-Indonesia'!I154 -> 21860 | ... AZ5: =AY5+AY5*'NVP-Indonesia'!AY154 -> 21860
A6: plugin hybrid vehicle | B6: ='NVP-Indonesia'!$B$12+'NVP-Indonesia'!$B$12*'NVP-Indonesia'!B155 -> 21890.968 | C6: =B6+B6*'NVP-Indonesia'!B155 -> 21921.981 | D6: =C6+C6*'NVP-Indonesia'!C155 -> 21921.981 | E6: =D6+D6*'NVP-Indonesia'!D155 -> 21921.981 | F6: =E6+E6*'NVP-Indonesia'!E155 -> 21921.981 | G6: =F6+F6*'NVP-Indonesia'!F155 -> 21921.981 | H6: =G6+G6*'NVP-Indonesia'!G155 -> 21921.981 | I6: =H6+H6*'NVP-Indonesia'!H155 -> 21921.981 | J6: =I6+I6*'NVP-Indonesia'!I155 -> 21921.981 | ... AZ6: =AY6+AY6*'NVP-Indonesia'!AY155 -> 21921.981
A7: LPG vehicle | B7: ='NVP-Indonesia'!$B$12+'NVP-Indonesia'!$B$12*'NVP-Indonesia'!B156 -> 21898.341 | C7: =B7+B7*'NVP-Indonesia'!B156 -> 21936.748 | D7: =C7+C7*'NVP-Indonesia'!C156 -> 21936.748 | E7: =D7+D7*'NVP-Indonesia'!D156 -> 21936.748 | F7: =E7+E7*'NVP-Indonesia'!E156 -> 21936.748 | G7: =F7+F7*'NVP-Indonesia'!F156 -> 21936.748 | H7: =G7+G7*'NVP-Indonesia'!G156 -> 21936.748 | I7: =H7+H7*'NVP-Indonesia'!H156 -> 21936.748 | J7: =I7+I7*'NVP-Indonesia'!I156 -> 21936.748 | ... AZ7: =AY7+AY7*'NVP-Indonesia'!AY156 -> 21936.748
A8: hydrogen vehicle | B8: ='NVP-Indonesia'!$B$12+'NVP-Indonesia'!$B$12*'NVP-Indonesia'!B157 -> 21464.221 | C8: =B8+B8*'NVP-Indonesia'!B157 -> 21075.607 | D8: =C8+C8*'NVP-Indonesia'!C157 -> 21075.607 | E8: =D8+D8*'NVP-Indonesia'!D157 -> 21075.607 | F8: =E8+E8*'NVP-Indonesia'!E157 -> 21075.607 | G8: =F8+F8*'NVP-Indonesia'!F157 -> 21075.607 | H8: =G8+G8*'NVP-Indonesia'!G157 -> 21075.607 | I8: =H8+H8*'NVP-Indonesia'!H157 -> 21075.607 | J8: =I8+I8*'NVP-Indonesia'!I157 -> 21075.607 | ... AZ8: =AY8+AY8*'NVP-Indonesia'!AY157 -> 21075.607

Sheet BNVP-HDVs-frgt
A1: Price ($/vehicle) | B1: 2020 | C1: 2021 | D1: 2022 | E1: 2023 | F1: 2024 | G1: 2025 | H1: 2026 | I1: 2027 | J1: 2028 | K1: 2029 | L1: 2030 | M1: 2031 | N1: 2032 | O1: 2033 | P1: 2034 | Q1: 2035 | R1: 2036 | S1: 2037 | T1: 2038 | U1: 2039 | V1: 2040 | W1: 2041 | X1: 2042 | Y1: 2043 | Z1: 2044 | AA1: 2045 | AB1: 2046 | AC1: 2047 | AD1: 2048 | AE1: 2049 | AF1: 2050 | AG1: 2051 | AH1: 2052 | AI1: 2053 | AJ1: 2054 | AK1: 2055 | AL1: 2056 | AM1: 2057 | AN1: 2058 | AO1: 2059 | AP1: 2060 | AQ1: 2061 | AR1: 2062 | AS1: 2063 | AT1: 2064 | AU1: 2065 | AV1: 2066 | AW1: 2067 | AX1: 2068 | AY1: 2069 | AZ1: 2070
A2: battery electric vehicle | B2: ='NVP-Indonesia'!B47*'NVP-Indonesia'!$B$176 -> 165612.15 | C2: ='NVP-Indonesia'!C47*'NVP-Indonesia'!$B$176 -> 165612.15 | D2: ='NVP-Indonesia'!D47*'NVP-Indonesia'!$B$176 -> 165612.15 | E2: ='NVP-Indonesia'!E47*'NVP-Indonesia'!$B$176 -> 165612.15 | F2: ='NVP-Indonesia'!F47*'NVP-Indonesia'!$B$176 -> 165612.15 | G2: ='NVP-Indonesia'!G47*'NVP-Indonesia'!$B$176 -> 165612.15 | H2: ='NVP-Indonesia'!H47*'NVP-Indonesia'!$B$176 -> 165612.15 | I2: ='NVP-Indonesia'!I47*'NVP-Indonesia'!$B$176 -> 165612.15 | ... AZ2: ='NVP-Indonesia'!AZ47*'NVP-Indonesia'!$B$176 -> 165612.15
A3: natural gas vehicle | B3: ='NVP-Indonesia'!B48*'NVP-Indonesia'!$B$176 -> 131883.19 | C3: ='NVP-Indonesia'!C48*'NVP-Indonesia'!$B$176 -> 130934.43 | D3: ='NVP-Indonesia'!D48*'NVP-Indonesia'!$B$176 -> 131499.84 | E3: ='NVP-Indonesia'!E48*'NVP-Indonesia'!$B$176 -> 132382.26 | F3: ='NVP-Indonesia'!F48*'NVP-Indonesia'!$B$176 -> 133062.36 | G3: ='NVP-Indonesia'!G48*'NVP-Indonesia'!$B$176 -> 133728.94 | H3: ='NVP-Indonesia'!H48*'NVP-Indonesia'!$B$176 -> 134343.9 | I3: ='NVP-Indonesia'!I48*'NVP-Indonesia'!$B$176 -> 134900.89 | ... AZ3: ='NVP-Indonesia'!AZ48*'NVP-Indonesia'!$B$176 -> 149503.36
A4: gasoline vehicle | B4: ='NVP-Indonesia'!B49*'NVP-Indonesia'!$B$176 -> 90895.799 | C4: ='NVP-Indonesia'!C49*'NVP-Indonesia'!$B$176 -> 90895.799 | D4: ='NVP-Indonesia'!D49*'NVP-Indonesia'!$B$176 -> 90895.799 | E4: ='NVP-Indonesia'!E49*'NVP-Indonesia'!$B$176 -> 90895.799 | F4: ='NVP-Indonesia'!F49*'NVP-Indonesia'!$B$176 -> 90895.799 | G4: ='NVP-Indonesia'!G49*'NVP-Indonesia'!$B$176 -> 90895.799 | H4: ='NVP-Indonesia'!H49*'NVP-Indonesia'!$B$176 -> 90895.799 | I4: ='NVP-Indonesia'!I49*'NVP-Indonesia'!$B$176 -> 90895.799 | ... AZ4: ='NVP-Indonesia'!AZ49*'NVP-Indonesia'!$B$176 -> 90895.799
A5: diesel vehicle | B5: ='NVP-Indonesia'!B50*'NVP-Indonesia'!$B$176 -> 90895.799 | C5: ='NVP-Indonesia'!C50*'NVP-Indonesia'!$B$176 -> 90895.799 | D5: ='NVP-Indonesia'!D50*'NVP-Indonesia'!$B$176 -> 90895.799 | E5: ='NVP-Indonesia'!E50*'NVP-Indonesia'!$B$176 -> 90895.799 | F5: ='NVP-Indonesia'!F50*'NVP-Indonesia'!$B$176 -> 90895.799 | G5: ='NVP-Indonesia'!G50*'NVP-Indonesia'!$B$176 -> 90895.799 | H5: ='NVP-Indonesia'!H50*'NVP-Indonesia'!$B$176 -> 90895.799 | I5: ='NVP-Indonesia'!I50*'NVP-Indonesia'!$B$176 -> 90895.799 | ... AZ5: ='NVP-Indonesia'!AZ50*'NVP-Indonesia'!$B$176 -> 90895.799
A6: plugin hybrid vehicle | B6: ='NVP-Indonesia'!B51*'NVP-Indonesia'!$B$176 -> 228319.42 | C6: ='NVP-Indonesia'!C51*'NVP-Indonesia'!$B$176 -> 231440.68 | D6: ='NVP-Indonesia'!D51*'NVP-Indonesia'!$B$176 -> 231106.75 | E6: ='NVP-Indonesia'!E51*'NVP-Indonesia'!$B$176 -> 232243.57 | F6: ='NVP-Indonesia'!F51*'NVP-Indonesia'!$B$176 -> 232497.82 | G6: ='NVP-Indonesia'!G51*'NVP-Indonesia'!$B$176 -> 233190.87 | H6: ='NVP-Indonesia'!H51*'NVP-Indonesia'!$B$176 -> 233474.06 | I6: ='NVP-Indonesia'!I51*'NVP-Indonesia'!$B$176 -> 233635.37 | ... AZ6: ='NVP-Indonesia'!AZ51*'NVP-Indonesia'!$B$176 -> 245066.39
A7: LPG vehicle | B7: ='NVP-Indonesia'!B52*'NVP-Indonesia'!$B$176 -> 128903.9 | C7: ='NVP-Indonesia'!C52*'NVP-Indonesia'!$B$176 -> 131015.08 | D7: ='NVP-Indonesia'!D52*'NVP-Indonesia'!$B$176 -> 130893.78 | E7: ='NVP-Indonesia'!E52*'NVP-Indonesia'!$B$176 -> 131121.81 | F7: ='NVP-Indonesia'!F52*'NVP-Indonesia'!$B$176 -> 131431.04 | G7: ='NVP-Indonesia'!G52*'NVP-Indonesia'!$B$176 -> 132007.15 | H7: ='NVP-Indonesia'!H52*'NVP-Indonesia'!$B$176 -> 132488.47 | I7: ='NVP-Indonesia'!I52*'NVP-Indonesia'!$B$176 -> 132735.51 | ... AZ7: ='NVP-Indonesia'!AZ52*'NVP-Indonesia'!$B$176 -> 140707.89
A8: hydrogen vehicle | B8: ='NVP-Indonesia'!B53*'NVP-Indonesia'!$B$176 -> 277734.94 | C8: ='NVP-Indonesia'!C53*'NVP-Indonesia'!$B$176 -> 277674.53 | D8: ='NVP-Indonesia'!D53*'NVP-Indonesia'!$B$176 -> 271668.47 | E8: ='NVP-Indonesia'!E53*'NVP-Indonesia'!$B$176 -> 266381.28 | F8: ='NVP-Indonesia'!F53*'NVP-Indonesia'!$B$176 -> 261040.65 | G8: ='NVP-Indonesia'!G53*'NVP-Indonesia'!$B$176 -> 255512.77 | H8: ='NVP-Indonesia'!H53*'NVP-Indonesia'!$B$176 -> 250656.47 | I8: ='NVP-Indonesia'!I53*'NVP-Indonesia'!$B$176 -> 246187.21 | ... AZ8: ='NVP-Indonesia'!AZ53*'NVP-Indonesia'!$B$176 -> 111398.35

Sheet BNVP-aircraft-psgr
A1: Price ($/vehicle) | B1: 2020 | C1: 2021 | D1: 2022 | E1: 2023 | F1: 2024 | G1: 2025 | H1: 2026 | I1: 2027 | J1: 2028 | K1: 2029 | L1: 2030 | M1: 2031 | N1: 2032 | O1: 2033 | P1: 2034 | Q1: 2035 | R1: 2036 | S1: 2037 | T1: 2038 | U1: 2039 | V1: 2040 | W1: 2041 | X1: 2042 | Y1: 2043 | Z1: 2044 | AA1: 2045 | AB1: 2046 | AC1: 2047 | AD1: 2048 | AE1: 2049 | AF1: 2050 | AG1: 2051 | AH1: 2052 | AI1: 2053 | AJ1: 2054 | AK1: 2055 | AL1: 2056 | AM1: 2057 | AN1: 2058 | AO1: 2059 | AP1: 2060 | AQ1: 2061 | AR1: 2062 | AS1: 2063 | AT1: 2064 | AU1: 2065 | AV1: 2066 | AW1: 2067 | AX1: 2068 | AY1: 2069 | AZ1: 2070
A2: battery electric vehicle | B2: ='NVP-Indonesia'!B57*'NVP-Indonesia'!$B$176 -> 93481595 | C2: =B2 -> 93481595 | D2: =C2 -> 93481595 | E2: =D2 -> 93481595 | F2: =E2 -> 93481595 | G2: =F2 -> 93481595 | H2: =G2 -> 93481595 | I2: =H2 -> 93481595 | J2: =I2 -> 93481595 | ... AF2: =AE2 -> 93481595 | AG2: =_xlfn.FORECAST.LINEAR(AG$1,$B2:$AF2,$B$1:$AF$1) -> 93481595 | AH2: =_xlfn.FORECAST.LINEAR(AH$1,$B2:$AF2,$B$1:$AF$1) -> 93481595 | AI2: =_xlfn.FORECAST.LINEAR(AI$1,$B2:$AF2,$B$1:$AF$1) -> 93481595 | AJ2: =_xlfn.FORECAST.LINEAR(AJ$1,$B2:$AF2,$B$1:$AF$1) -> 93481595 | AK2: =_xlfn.FORECAST.LINEAR(AK$1,$B2:$AF2,$B$1:$AF$1) -> 93481595 | AL2: =_xlfn.FORECAST.LINEAR(AL$1,$B2:$AF2,$B$1:$AF$1) -> 93481595 | AM2: =_xlfn.FORECAST.LINEAR(AM$1,$B2:$AF2,$B$1:$AF$1) -> 93481595 | AN2: =_xlfn.FORECAST.LINEAR(AN$1,$B2:$AF2,$B$1:$AF$1) -> 93481595 | ... AZ2: =_xlfn.FORECAST.LINEAR(AZ$1,$B2:$AF2,$B$1:$AF$1) -> 93481595
A3: natural gas vehicle | B3: 999999999 | C3: 999999999 | D3: 999999999 | E3: 999999999 | F3: 999999999 | G3: 999999999 | H3: 999999999 | I3: 999999999 | J3: 999999999 | K3: 999999999 | L3: 999999999 | M3: 999999999 | N3: 999999999 | O3: 999999999 | P3: 999999999 | Q3: 999999999 | R3: 999999999 | S3: 999999999 | T3: 999999999 | U3: 999999999 | V3: 999999999 | W3: 999999999 | X3: 999999999 | Y3: 999999999 | Z3: 999999999 | AA3: 999999999 | AB3: 999999999 | AC3: 999999999 | AD3: 999999999 | AE3: 999999999 | AF3: 999999999 | AG3: 999999999 | AH3: 999999999 | AI3: 999999999 | AJ3: 999999999 | AK3: 999999999 | AL3: 999999999 | AM3: 999999999 | AN3: 999999999 | AO3: 999999999 | AP3: 999999999 | AQ3: 999999999 | AR3: 999999999 | AS3: 999999999 | AT3: 999999999 | AU3: 999999999 | AV3: 999999999 | AW3: 999999999 | AX3: 999999999 | AY3: 999999999 | AZ3: 999999999
A4: gasoline vehicle | B4: 999999999 | C4: 999999999 | D4: 999999999 | E4: 999999999 | F4: 999999999 | G4: 999999999 | H4: 999999999 | I4: 999999999 | J4: 999999999 | K4: 999999999 | L4: 999999999 | M4: 999999999 | N4: 999999999 | O4: 999999999 | P4: 999999999 | Q4: 999999999 | R4: 999999999 | S4: 999999999 | T4: 999999999 | U4: 999999999 | V4: 999999999 | W4: 999999999 | X4: 999999999 | Y4: 999999999 | Z4: 999999999 | AA4: 999999999 | AB4: 999999999 | AC4: 999999999 | AD4: 999999999 | AE4: 999999999 | AF4: 999999999 | AG4: 999999999 | AH4: 999999999 | AI4: 999999999 | AJ4: 999999999 | AK4: 999999999 | AL4: 999999999 | AM4: 999999999 | AN4: 999999999 | AO4: 999999999 | AP4: 999999999 | AQ4: 999999999 | AR4: 999999999 | AS4: 999999999 | AT4: 999999999 | AU4: 999999999 | AV4: 999999999 | AW4: 999999999 | AX4: 999999999 | AY4: 999999999 | AZ4: 999999999
A5: diesel vehicle | B5: ='NVP-Indonesia'!B60*'NVP-Indonesia'!$B$176 -> 50570000 | C5: =$B5 -> 50570000 | D5: =$B5 -> 50570000 | E5: =$B5 -> 50570000 | F5: =$B5 -> 50570000 | G5: =$B5 -> 50570000 | H5: =$B5 -> 50570000 | I5: =$B5 -> 50570000 | J5: =$B5 -> 50570000 | ... AF5: =$B5 -> 50570000 | AG5: =_xlfn.FORECAST.LINEAR(AG$1,$B5:$AF5,$B$1:$AF$1) -> 50570000 | AH5: =_xlfn.FORECAST.LINEAR(AH$1,$B5:$AF5,$B$1:$AF$1) -> 50570000 | AI5: =_xlfn.FORECAST.LINEAR(AI$1,$B5:$AF5,$B$1:$AF$1) -> 50570000 | AJ5: =_xlfn.FORECAST.LINEAR(AJ$1,$B5:$AF5,$B$1:$AF$1) -> 50570000 | AK5: =_xlfn.FORECAST.LINEAR(AK$1,$B5:$AF5,$B$1:$AF$1) -> 50570000 | AL5: =_xlfn.FORECAST.LINEAR(AL$1,$B5:$AF5,$B$1:$AF$1) -> 50570000 | AM5: =_xlfn.FORECAST.LINEAR(AM$1,$B5:$AF5,$B$1:$AF$1) -> 50570000 | AN5: =_xlfn.FORECAST.LINEAR(AN$1,$B5:$AF5,$B$1:$AF$1) -> 50570000 | ... AZ5: =_xlfn.FORECAST.LINEAR(AZ$1,$B5:$AF5,$B$1:$AF$1) -> 50570000
A6: plugin hybrid vehicle | B6: 999999999 | C6: 999999999 | D6: 999999999 | E6: 999999999 | F6: 999999999 | G6: 999999999 | H6: 999999999 | I6: 999999999 | J6: 999999999 | K6: 999999999 | L6: 999999999 | M6: 999999999 | N6: 999999999 | O6: 999999999 | P6: 999999999 | Q6: 999999999 | R6: 999999999 | S6: 999999999 | T6: 999999999 | U6: 999999999 | V6: 999999999 | W6: 999999999 | X6: 999999999 | Y6: 999999999 | Z6: 999999999 | AA6: 999999999 | AB6: 999999999 | AC6: 999999999 | AD6: 999999999 | AE6: 999999999 | AF6: 999999999 | AG6: 999999999 | AH6: 999999999 | AI6: 999999999 | AJ6: 999999999 | AK6: 999999999 | AL6: 999999999 | AM6: 999999999 | AN6: 999999999 | AO6: 999999999 | AP6: 999999999 | AQ6: 999999999 | AR6: 999999999 | AS6: 999999999 | AT6: 999999999 | AU6: 999999999 | AV6: 999999999 | AW6: 999999999 | AX6: 999999999 | AY6: 999999999 | AZ6: 999999999
A7: LPG vehicle | B7: 999999999 | C7: 999999999 | D7: 999999999 | E7: 999999999 | F7: 999999999 | G7: 999999999 | H7: 999999999 | I7: 999999999 | J7: 999999999 | K7: 999999999 | L7: 999999999 | M7: 999999999 | N7: 999999999 | O7: 999999999 | P7: 999999999 | Q7: 999999999 | R7: 999999999 | S7: 999999999 | T7: 999999999 | U7: 999999999 | V7: 999999999 | W7: 999999999 | X7: 999999999 | Y7: 999999999 | Z7: 999999999 | AA7: 999999999 | AB7: 999999999 | AC7: 999999999 | AD7: 999999999 | AE7: 999999999 | AF7: 999999999 | AG7: 999999999 | AH7: 999999999 | AI7: 999999999 | AJ7: 999999999 | AK7: 999999999 | AL7: 999999999 | AM7: 999999999 | AN7: 999999999 | AO7: 999999999 | AP7: 999999999 | AQ7: 999999999 | AR7: 999999999 | AS7: 999999999 | AT7: 999999999 | AU7: 999999999 | AV7: 999999999 | AW7: 999999999 | AX7: 999999999 | AY7: 999999999 | AZ7: 999999999
A8: hydrogen vehicle | B8: ='NVP-Indonesia'!B63*'NVP-Indonesia'!$B$176 -> 1.017605e+08 | C8: =C$5*('BNVP-HDVs-psgr'!C$8/'BNVP-HDVs-psgr'!C$5) -> 48755418 | D8: =D$5*('BNVP-HDVs-psgr'!D$8/'BNVP-HDVs-psgr'!D$5) -> 48755418 | E8: =E$5*('BNVP-HDVs-psgr'!E$8/'BNVP-HDVs-psgr'!E$5) -> 48755418 | F8: =F$5*('BNVP-HDVs-psgr'!F$8/'BNVP-HDVs-psgr'!F$5) -> 48755418 | G8: =G$5*('BNVP-HDVs-psgr'!G$8/'BNVP-HDVs-psgr'!G$5) -> 48755418 | H8: =H$5*('BNVP-HDVs-psgr'!H$8/'BNVP-HDVs-psgr'!H$5) -> 48755418 | I8: =I$5*('BNVP-HDVs-psgr'!I$8/'BNVP-HDVs-psgr'!I$5) -> 48755418 | J8: =J$5*('BNVP-HDVs-psgr'!J$8/'BNVP-HDVs-psgr'!J$5) -> 48755418 | ... AF8: =AF$5*('BNVP-HDVs-psgr'!AF$8/'BNVP-HDVs-psgr'!AF$5) -> 48755418 | AG8: =_xlfn.FORECAST.LINEAR(AG$1,$B8:$AF8,$B$1:$AF$1) -> 45335736 | AH8: =_xlfn.FORECAST.LINEAR(AH$1,$B8:$AF8,$B$1:$AF$1) -> 45015140 | AI8: =_xlfn.FORECAST.LINEAR(AI$1,$B8:$AF8,$B$1:$AF$1) -> 44694545 | AJ8: =_xlfn.FORECAST.LINEAR(AJ$1,$B8:$AF8,$B$1:$AF$1) -> 44373950 | AK8: =_xlfn.FORECAST.LINEAR(AK$1,$B8:$AF8,$B$1:$AF$1) -> 44053355 | AL8: =_xlfn.FORECAST.LINEAR(AL$1,$B8:$AF8,$B$1:$AF$1) -> 43732759 | AM8: =_xlfn.FORECAST.LINEAR(AM$1,$B8:$AF8,$B$1:$AF$1) -> 43412164 | AN8: =_xlfn.FORECAST.LINEAR(AN$1,$B8:$AF8,$B$1:$AF$1) -> 43091569 | ... AZ8: =_xlfn.FORECAST.LINEAR(AZ$1,$B8:$AF8,$B$1:$AF$1) -> 39244426

Sheet BNVP-rail-psgr
A1: Price ($/vehicle) | B1: 2020 | C1: 2021 | D1: 2022 | E1: 2023 | F1: 2024 | G1: 2025 | H1: 2026 | I1: 2027 | J1: 2028 | K1: 2029 | L1: 2030 | M1: 2031 | N1: 2032 | O1: 2033 | P1: 2034 | Q1: 2035 | R1: 2036 | S1: 2037 | T1: 2038 | U1: 2039 | V1: 2040 | W1: 2041 | X1: 2042 | Y1: 2043 | Z1: 2044 | AA1: 2045 | AB1: 2046 | AC1: 2047 | AD1: 2048 | AE1: 2049 | AF1: 2050 | AG1: 2051 | AH1: 2052 | AI1: 2053 | AJ1: 2054 | AK1: 2055 | AL1: 2056 | AM1: 2057 | AN1: 2058 | AO1: 2059 | AP1: 2060 | AQ1: 2061 | AR1: 2062 | AS1: 2063 | AT1: 2064 | AU1: 2065 | AV1: 2066 | AW1: 2067 | AX1: 2068 | AY1: 2069 | AZ1: 2070
A2: battery electric vehicle | B2: ='NVP-Indonesia'!B67*'NVP-Indonesia'!$B$176 -> 3250000 | C2: =B2 -> 3250000 | D2: =C2 -> 3250000 | E2: =D2 -> 3250000 | F2: =E2 -> 3250000 | G2: =F2 -> 3250000 | H2: =G2 -> 3250000 | I2: =H2 -> 3250000 | J2: =I2 -> 3250000 | ... AF2: =AE2 -> 3250000 | AG2: =_xlfn.FORECAST.LINEAR(AG$1,$B2:$AF2,$B$1:$AF$1) -> 3250000 | AH2: =_xlfn.FORECAST.LINEAR(AH$1,$B2:$AF2,$B$1:$AF$1) -> 3250000 | AI2: =_xlfn.FORECAST.LINEAR(AI$1,$B2:$AF2,$B$1:$AF$1) -> 3250000 | AJ2: =_xlfn.FORECAST.LINEAR(AJ$1,$B2:$AF2,$B$1:$AF$1) -> 3250000 | AK2: =_xlfn.FORECAST.LINEAR(AK$1,$B2:$AF2,$B$1:$AF$1) -> 3250000 | AL2: =_xlfn.FORECAST.LINEAR(AL$1,$B2:$AF2,$B$1:$AF$1) -> 3250000 | AM2: =_xlfn.FORECAST.LINEAR(AM$1,$B2:$AF2,$B$1:$AF$1) -> 3250000 | AN2: =_xlfn.FORECAST.LINEAR(AN$1,$B2:$AF2,$B$1:$AF$1) -> 3250000 | ... AZ2: =_xlfn.FORECAST.LINEAR(AZ$1,$B2:$AF2,$B$1:$AF$1) -> 3250000
A3: natural gas vehicle | B3: 999999999 | C3: 999999999 | D3: 999999999 | E3: 999999999 | F3: 999999999 | G3: 999999999 | H3: 999999999 | I3: 999999999 | J3: 999999999 | K3: 999999999 | L3: 999999999 | M3: 999999999 | N3: 999999999 | O3: 999999999 | P3: 999999999 | Q3: 999999999 | R3: 999999999 | S3: 999999999 | T3: 999999999 | U3: 999999999 | V3: 999999999 | W3: 999999999 | X3: 999999999 | Y3: 999999999 | Z3: 999999999 | AA3: 999999999 | AB3: 999999999 | AC3: 999999999 | AD3: 999999999 | AE3: 999999999 | AF3: 999999999 | AG3: 999999999 | AH3: 999999999 | AI3: 999999999 | AJ3: 999999999 | AK3: 999999999 | AL3: 999999999 | AM3: 999999999 | AN3: 999999999 | AO3: 999999999 | AP3: 999999999 | AQ3: 999999999 | AR3: 999999999 | AS3: 999999999 | AT3: 999999999 | AU3: 999999999 | AV3: 999999999 | AW3: 999999999 | AX3: 999999999 | AY3: 999999999 | AZ3: 999999999
A4: gasoline vehicle | B4: 999999999 | C4: 999999999 | D4: 999999999 | E4: 999999999 | F4: 999999999 | G4: 999999999 | H4: 999999999 | I4: 999999999 | J4: 999999999 | K4: 999999999 | L4: 999999999 | M4: 999999999 | N4: 999999999 | O4: 999999999 | P4: 999999999 | Q4: 999999999 | R4: 999999999 | S4: 999999999 | T4: 999999999 | U4: 999999999 | V4: 999999999 | W4: 999999999 | X4: 999999999 | Y4: 999999999 | Z4: 999999999 | AA4: 999999999 | AB4: 999999999 | AC4: 999999999 | AD4: 999999999 | AE4: 999999999 | AF4: 999999999 | AG4: 999999999 | AH4: 999999999 | AI4: 999999999 | AJ4: 999999999 | AK4: 999999999 | AL4: 999999999 | AM4: 999999999 | AN4: 999999999 | AO4: 999999999 | AP4: 999999999 | AQ4: 999999999 | AR4: 999999999 | AS4: 999999999 | AT4: 999999999 | AU4: 999999999 | AV4: 999999999 | AW4: 999999999 | AX4: 999999999 | AY4: 999999999 | AZ4: 999999999
A5: diesel vehicle | B5: ='NVP-Indonesia'!B70*'NVP-Indonesia'!$B$176 -> 1751206.9 | C5: =$B5 -> 1751206.9 | D5: =$B5 -> 1751206.9 | E5: =$B5 -> 1751206.9 | F5: =$B5 -> 1751206.9 | G5: =$B5 -> 1751206.9 | H5: =$B5 -> 1751206.9 | I5: =$B5 -> 1751206.9 | J5: =$B5 -> 1751206.9 | ... AF5: =$B5 -> 1751206.9 | AG5: =_xlfn.FORECAST.LINEAR(AG$1,$B5:$AF5,$B$1:$AF$1) -> 1751206.9 | AH5: =_xlfn.FORECAST.LINEAR(AH$1,$B5:$AF5,$B$1:$AF$1) -> 1751206.9 | AI5: =_xlfn.FORECAST.LINEAR(AI$1,$B5:$AF5,$B$1:$AF$1) -> 1751206.9 | AJ5: =_xlfn.FORECAST.LINEAR(AJ$1,$B5:$AF5,$B$1:$AF$1) -> 1751206.9 | AK5: =_xlfn.FORECAST.LINEAR(AK$1,$B5:$AF5,$B$1:$AF$1) -> 1751206.9 | AL5: =_xlfn.FORECAST.LINEAR(AL$1,$B5:$AF5,$B$1:$AF$1) -> 1751206.9 | AM5: =_xlfn.FORECAST.LINEAR(AM$1,$B5:$AF5,$B$1:$AF$1) -> 1751206.9 | AN5: =_xlfn.FORECAST.LINEAR(AN$1,$B5:$AF5,$B$1:$AF$1) -> 1751206.9 | ... AZ5: =_xlfn.FORECAST.LINEAR(AZ$1,$B5:$AF5,$B$1:$AF$1) -> 1751206.9
A6: plugin hybrid vehicle | B6: 999999999 | C6: 999999999 | D6: 999999999 | E6: 999999999 | F6: 999999999 | G6: 999999999 | H6: 999999999 | I6: 999999999 | J6: 999999999 | K6: 999999999 | L6: 999999999 | M6: 999999999 | N6: 999999999 | O6: 999999999 | P6: 999999999 | Q6: 999999999 | R6: 999999999 | S6: 999999999 | T6: 999999999 | U6: 999999999 | V6: 999999999 | W6: 999999999 | X6: 999999999 | Y6: 999999999 | Z6: 999999999 | AA6: 999999999 | AB6: 999999999 | AC6: 999999999 | AD6: 999999999 | AE6: 999999999 | AF6: 999999999 | AG6: 999999999 | AH6: 999999999 | AI6: 999999999 | AJ6: 999999999 | AK6: 999999999 | AL6: 999999999 | AM6: 999999999 | AN6: 999999999 | AO6: 999999999 | AP6: 999999999 | AQ6: 999999999 | AR6: 999999999 | AS6: 999999999 | AT6: 999999999 | AU6: 999999999 | AV6: 999999999 | AW6: 999999999 | AX6: 999999999 | AY6: 999999999 | AZ6: 999999999
A7: LPG vehicle | B7: 999999999 | C7: 999999999 | D7: 999999999 | E7: 999999999 | F7: 999999999 | G7: 999999999 | H7: 999999999 | I7: 999999999 | J7: 999999999 | K7: 999999999 | L7: 999999999 | M7: 999999999 | N7: 999999999 | O7: 999999999 | P7: 999999999 | Q7: 999999999 | R7: 999999999 | S7: 999999999 | T7: 999999999 | U7: 999999999 | V7: 999999999 | W7: 999999999 | X7: 999999999 | Y7: 999999999 | Z7: 999999999 | AA7: 999999999 | AB7: 999999999 | AC7: 999999999 | AD7: 999999999 | AE7: 999999999 | AF7: 999999999 | AG7: 999999999 | AH7: 999999999 | AI7: 999999999 | AJ7: 999999999 | AK7: 999999999 | AL7: 999999999 | AM7: 999999999 | AN7: 999999999 | AO7: 999999999 | AP7: 999999999 | AQ7: 999999999 | AR7: 999999999 | AS7: 999999999 | AT7: 999999999 | AU7: 999999999 | AV7: 999999999 | AW7: 999999999 | AX7: 999999999 | AY7: 999999999 | AZ7: 999999999
A8: hydrogen vehicle | B8: ='NVP-Indonesia'!B73*'NVP-Indonesia'!$B$176 -> 2311593.1 | C8: =$B$8*'BNVP-HDVs-frgt'!C8/'BNVP-HDVs-frgt'!$B$8 -> 2311090.3 | D8: =$B$8*'BNVP-HDVs-frgt'!D8/'BNVP-HDVs-frgt'!$B$8 -> 2261101.8 | E8: =$B$8*'BNVP-HDVs-frgt'!E8/'BNVP-HDVs-frgt'!$B$8 -> 2217096.4 | F8: =$B$8*'BNVP-HDVs-frgt'!F8/'BNVP-HDVs-frgt'!$B$8 -> 2172646.2 | G8: =$B$8*'BNVP-HDVs-frgt'!G8/'BNVP-HDVs-frgt'!$B$8 -> 2126637.6 | H8: =$B$8*'BNVP-HDVs-frgt'!H8/'BNVP-HDVs-frgt'!$B$8 -> 2086218.5 | I8: =$B$8*'BNVP-HDVs-frgt'!I8/'BNVP-HDVs-frgt'!$B$8 -> 2049020.8 | J8: =$B$8*'BNVP-HDVs-frgt'!J8/'BNVP-HDVs-frgt'!$B$8 -> 2013540.3 | ... AF8: =$B$8*'BNVP-HDVs-frgt'!AF8/'BNVP-HDVs-frgt'!$B$8 -> 1532116.5 | AG8: =_xlfn.FORECAST.LINEAR(AG$1,$B8:$AF8,$B$1:$AF$1) -> 1429738.1 | AH8: =_xlfn.FORECAST.LINEAR(AH$1,$B8:$AF8,$B$1:$AF$1) -> 1403287.1 | AI8: =_xlfn.FORECAST.LINEAR(AI$1,$B8:$AF8,$B$1:$AF$1) -> 1376836.2 | AJ8: =_xlfn.FORECAST.LINEAR(AJ$1,$B8:$AF8,$B$1:$AF$1) -> 1350385.3 | AK8: =_xlfn.FORECAST.LINEAR(AK$1,$B8:$AF8,$B$1:$AF$1) -> 1323934.4 | AL8: =_xlfn.FORECAST.LINEAR(AL$1,$B8:$AF8,$B$1:$AF$1) -> 1297483.5 | AM8: =_xlfn.FORECAST.LINEAR(AM$1,$B8:$AF8,$B$1:$AF$1) -> 1271032.5 | AN8: =_xlfn.FORECAST.LINEAR(AN$1,$B8:$AF8,$B$1:$AF$1) -> 1244581.6 | ... AZ8: =_xlfn.FORECAST.LINEAR(AZ$1,$B8:$AF8,$B$1:$AF$1) -> 927170.56

Sheet BNVP-aircraft-frgt
A1: Price ($/vehicle) | B1: 2020 | C1: 2021 | D1: 2022 | E1: 2023 | F1: 2024 | G1: 2025 | H1: 2026 | I1: 2027 | J1: 2028 | K1: 2029 | L1: 2030 | M1: 2031 | N1: 2032 | O1: 2033 | P1: 2034 | Q1: 2035 | R1: 2036 | S1: 2037 | T1: 2038 | U1: 2039 | V1: 2040 | W1: 2041 | X1: 2042 | Y1: 2043 | Z1: 2044 | AA1: 2045 | AB1: 2046 | AC1: 2047 | AD1: 2048 | AE1: 2049 | AF1: 2050 | AG1: 2051 | AH1: 2052 | AI1: 2053 | AJ1: 2054 | AK1: 2055 | AL1: 2056 | AM1: 2057 | AN1: 2058 | AO1: 2059 | AP1: 2060 | AQ1: 2061 | AR1: 2062 | AS1: 2063 | AT1: 2064 | AU1: 2065 | AV1: 2066 | AW1: 2067 | AX1: 2068 | AY1: 2069 | AZ1: 2070
A2: battery electric vehicle | B2: ='NVP-Indonesia'!B77*'NVP-Indonesia'!$B$176 -> 93481595 | C2: =B2 -> 93481595 | D2: =C2 -> 93481595 | E2: =D2 -> 93481595 | F2: =E2 -> 93481595 | G2: =F2 -> 93481595 | H2: =G2 -> 93481595 | I2: =H2 -> 93481595 | J2: =I2 -> 93481595 | ... AF2: =AE2 -> 93481595 | AG2: =_xlfn.FORECAST.LINEAR(AG$1,$B2:$AF2,$B$1:$AF$1) -> 93481595 | AH2: =_xlfn.FORECAST.LINEAR(AH$1,$B2:$AF2,$B$1:$AF$1) -> 93481595 | AI2: =_xlfn.FORECAST.LINEAR(AI$1,$B2:$AF2,$B$1:$AF$1) -> 93481595 | AJ2: =_xlfn.FORECAST.LINEAR(AJ$1,$B2:$AF2,$B$1:$AF$1) -> 93481595 | AK2: =_xlfn.FORECAST.LINEAR(AK$1,$B2:$AF2,$B$1:$AF$1) -> 93481595 | AL2: =_xlfn.FORECAST.LINEAR(AL$1,$B2:$AF2,$B$1:$AF$1) -> 93481595 | AM2: =_xlfn.FORECAST.LINEAR(AM$1,$B2:$AF2,$B$1:$AF$1) -> 93481595 | AN2: =_xlfn.FORECAST.LINEAR(AN$1,$B2:$AF2,$B$1:$AF$1) -> 93481595 | ... AZ2: =_xlfn.FORECAST.LINEAR(AZ$1,$B2:$AF2,$B$1:$AF$1) -> 93481595
A3: natural gas vehicle | B3: 999999999 | C3: 999999999 | D3: 999999999 | E3: 999999999 | F3: 999999999 | G3: 999999999 | H3: 999999999 | I3: 999999999 | J3: 999999999 | K3: 999999999 | L3: 999999999 | M3: 999999999 | N3: 999999999 | O3: 999999999 | P3: 999999999 | Q3: 999999999 | R3: 999999999 | S3: 999999999 | T3: 999999999 | U3: 999999999 | V3: 999999999 | W3: 999999999 | X3: 999999999 | Y3: 999999999 | Z3: 999999999 | AA3: 999999999 | AB3: 999999999 | AC3: 999999999 | AD3: 999999999 | AE3: 999999999 | AF3: 999999999 | AG3: 999999999 | AH3: 999999999 | AI3: 999999999 | AJ3: 999999999 | AK3: 999999999 | AL3: 999999999 | AM3: 999999999 | AN3: 999999999 | AO3: 999999999 | AP3: 999999999 | AQ3: 999999999 | AR3: 999999999 | AS3: 999999999 | AT3: 999999999 | AU3: 999999999 | AV3: 999999999 | AW3: 999999999 | AX3: 999999999 | AY3: 999999999 | AZ3: 999999999
A4: gasoline vehicle | B4: 999999999 | C4: 999999999 | D4: 999999999 | E4: 999999999 | F4: 999999999 | G4: 999999999 | H4: 999999999 | I4: 999999999 | J4: 999999999 | K4: 999999999 | L4: 999999999 | M4: 999999999 | N4: 999999999 | O4: 999999999 | P4: 999999999 | Q4: 999999999 | R4: 999999999 | S4: 999999999 | T4: 999999999 | U4: 999999999 | V4: 999999999 | W4: 999999999 | X4: 999999999 | Y4: 999999999 | Z4: 999999999 | AA4: 999999999 | AB4: 999999999 | AC4: 999999999 | AD4: 999999999 | AE4: 999999999 | AF4: 999999999 | AG4: 999999999 | AH4: 999999999 | AI4: 999999999 | AJ4: 999999999 | AK4: 999999999 | AL4: 999999999 | AM4: 999999999 | AN4: 999999999 | AO4: 999999999 | AP4: 999999999 | AQ4: 999999999 | AR4: 999999999 | AS4: 999999999 | AT4: 999999999 | AU4: 999999999 | AV4: 999999999 | AW4: 999999999 | AX4: 999999999 | AY4: 999999999 | AZ4: 999999999
A5: diesel vehicle | B5: ='NVP-Indonesia'!B80*'NVP-Indonesia'!$B$176 -> 50570000 | C5: =$B5 -> 50570000 | D5: =$B5 -> 50570000 | E5: =$B5 -> 50570000 | F5: =$B5 -> 50570000 | G5: =$B5 -> 50570000 | H5: =$B5 -> 50570000 | I5: =$B5 -> 50570000 | J5: =$B5 -> 50570000 | ... AF5: =$B5 -> 50570000 | AG5: =_xlfn.FORECAST.LINEAR(AG$1,$B5:$AF5,$B$1:$AF$1) -> 50570000 | AH5: =_xlfn.FORECAST.LINEAR(AH$1,$B5:$AF5,$B$1:$AF$1) -> 50570000 | AI5: =_xlfn.FORECAST.LINEAR(AI$1,$B5:$AF5,$B$1:$AF$1) -> 50570000 | AJ5: =_xlfn.FORECAST.LINEAR(AJ$1,$B5:$AF5,$B$1:$AF$1) -> 50570000 | AK5: =_xlfn.FORECAST.LINEAR(AK$1,$B5:$AF5,$B$1:$AF$1) -> 50570000 | AL5: =_xlfn.FORECAST.LINEAR(AL$1,$B5:$AF5,$B$1:$AF$1) -> 50570000 | AM5: =_xlfn.FORECAST.LINEAR(AM$1,$B5:$AF5,$B$1:$AF$1) -> 50570000 | AN5: =_xlfn.FORECAST.LINEAR(AN$1,$B5:$AF5,$B$1:$AF$1) -> 50570000 | ... AZ5: =_xlfn.FORECAST.LINEAR(AZ$1,$B5:$AF5,$B$1:$AF$1) -> 50570000
A6: plugin hybrid vehicle | B6: 999999999 | C6: 999999999 | D6: 999999999 | E6: 999999999 | F6: 999999999 | G6: 999999999 | H6: 999999999 | I6: 999999999 | J6: 999999999 | K6: 999999999 | L6: 999999999 | M6: 999999999 | N6: 999999999 | O6: 999999999 | P6: 999999999 | Q6: 999999999 | R6: 999999999 | S6: 999999999 | T6: 999999999 | U6: 999999999 | V6: 999999999 | W6: 999999999 | X6: 999999999 | Y6: 999999999 | Z6: 999999999 | AA6: 999999999 | AB6: 999999999 | AC6: 999999999 | AD6: 999999999 | AE6: 999999999 | AF6: 999999999 | AG6: 999999999 | AH6: 999999999 | AI6: 999999999 | AJ6: 999999999 | AK6: 999999999 | AL6: 999999999 | AM6: 999999999 | AN6: 999999999 | AO6: 999999999 | AP6: 999999999 | AQ6: 999999999 | AR6: 999999999 | AS6: 999999999 | AT6: 999999999 | AU6: 999999999 | AV6: 999999999 | AW6: 999999999 | AX6: 999999999 | AY6: 999999999 | AZ6: 999999999
A7: LPG vehicle | B7: 999999999 | C7: 999999999 | D7: 999999999 | E7: 999999999 | F7: 999999999 | G7: 999999999 | H7: 999999999 | I7: 999999999 | J7: 999999999 | K7: 999999999 | L7: 999999999 | M7: 999999999 | N7: 999999999 | O7: 999999999 | P7: 999999999 | Q7: 999999999 | R7: 999999999 | S7: 999999999 | T7: 999999999 | U7: 999999999 | V7: 999999999 | W7: 999999999 | X7: 999999999 | Y7: 999999999 | Z7: 999999999 | AA7: 999999999 | AB7: 999999999 | AC7: 999999999 | AD7: 999999999 | AE7: 999999999 | AF7: 999999999 | AG7: 999999999 | AH7: 999999999 | AI7: 999999999 | AJ7: 999999999 | AK7: 999999999 | AL7: 999999999 | AM7: 999999999 | AN7: 999999999 | AO7: 999999999 | AP7: 999999999 | AQ7: 999999999 | AR7: 999999999 | AS7: 999999999 | AT7: 999999999 | AU7: 999999999 | AV7: 999999999 | AW7: 999999999 | AX7: 999999999 | AY7: 999999999 | AZ7: 999999999
A8: hydrogen vehicle | B8: ='NVP-Indonesia'!B83*'NVP-Indonesia'!$B$176 -> 1.017605e+08 | C8: =C$5*('BNVP-HDVs-psgr'!C$8/'BNVP-HDVs-psgr'!C$5) -> 48755418 | D8: =D$5*('BNVP-HDVs-psgr'!D$8/'BNVP-HDVs-psgr'!D$5) -> 48755418 | E8: =E$5*('BNVP-HDVs-psgr'!E$8/'BNVP-HDVs-psgr'!E$5) -> 48755418 | F8: =F$5*('BNVP-HDVs-psgr'!F$8/'BNVP-HDVs-psgr'!F$5) -> 48755418 | G8: =G$5*('BNVP-HDVs-psgr'!G$8/'BNVP-HDVs-psgr'!G$5) -> 48755418 | H8: =H$5*('BNVP-HDVs-psgr'!H$8/'BNVP-HDVs-psgr'!H$5) -> 48755418 | I8: =I$5*('BNVP-HDVs-psgr'!I$8/'BNVP-HDVs-psgr'!I$5) -> 48755418 | J8: =J$5*('BNVP-HDVs-psgr'!J$8/'BNVP-HDVs-psgr'!J$5) -> 48755418 | ... AF8: =AF$5*('BNVP-HDVs-psgr'!AF$8/'BNVP-HDVs-psgr'!AF$5) -> 48755418 | AG8: =_xlfn.FORECAST.LINEAR(AG$1,$B8:$AF8,$B$1:$AF$1) -> 45335736 | AH8: =_xlfn.FORECAST.LINEAR(AH$1,$B8:$AF8,$B$1:$AF$1) -> 45015140 | AI8: =_xlfn.FORECAST.LINEAR(AI$1,$B8:$AF8,$B$1:$AF$1) -> 44694545 | AJ8: =_xlfn.FORECAST.LINEAR(AJ$1,$B8:$AF8,$B$1:$AF$1) -> 44373950 | AK8: =_xlfn.FORECAST.LINEAR(AK$1,$B8:$AF8,$B$1:$AF$1) -> 44053355 | AL8: =_xlfn.FORECAST.LINEAR(AL$1,$B8:$AF8,$B$1:$AF$1) -> 43732759 | AM8: =_xlfn.FORECAST.LINEAR(AM$1,$B8:$AF8,$B$1:$AF$1) -> 43412164 | AN8: =_xlfn.FORECAST.LINEAR(AN$1,$B8:$AF8,$B$1:$AF$1) -> 43091569 | ... AZ8: =_xlfn.FORECAST.LINEAR(AZ$1,$B8:$AF8,$B$1:$AF$1) -> 39244426

Sheet BNVP-rail-frgt
A1: Price ($/vehicle) | B1: 2020 | C1: 2021 | D1: 2022 | E1: 2023 | F1: 2024 | G1: 2025 | H1: 2026 | I1: 2027 | J1: 2028 | K1: 2029 | L1: 2030 | M1: 2031 | N1: 2032 | O1: 2033 | P1: 2034 | Q1: 2035 | R1: 2036 | S1: 2037 | T1: 2038 | U1: 2039 | V1: 2040 | W1: 2041 | X1: 2042 | Y1: 2043 | Z1: 2044 | AA1: 2045 | AB1: 2046 | AC1: 2047 | AD1: 2048 | AE1: 2049 | AF1: 2050 | AG1: 2051 | AH1: 2052 | AI1: 2053 | AJ1: 2054 | AK1: 2055 | AL1: 2056 | AM1: 2057 | AN1: 2058 | AO1: 2059 | AP1: 2060 | AQ1: 2061 | AR1: 2062 | AS1: 2063 | AT1: 2064 | AU1: 2065 | AV1: 2066 | AW1: 2067 | AX1: 2068 | AY1: 2069 | AZ1: 2070
A2: battery electric vehicle | B2: ='NVP-Indonesia'!B87*'NVP-Indonesia'!$B$176 -> 3900000 | C2: =B2 -> 3900000 | D2: =C2 -> 3900000 | E2: =D2 -> 3900000 | F2: =E2 -> 3900000 | G2: =F2 -> 3900000 | H2: =G2 -> 3900000 | I2: =H2 -> 3900000 | J2: =I2 -> 3900000 | ... AF2: =AE2 -> 3900000 | AG2: =_xlfn.FORECAST.LINEAR(AG$1,$B2:$AF2,$B$1:$AF$1) -> 3900000 | AH2: =_xlfn.FORECAST.LINEAR(AH$1,$B2:$AF2,$B$1:$AF$1) -> 3900000 | AI2: =_xlfn.FORECAST.LINEAR(AI$1,$B2:$AF2,$B$1:$AF$1) -> 3900000 | AJ2: =_xlfn.FORECAST.LINEAR(AJ$1,$B2:$AF2,$B$1:$AF$1) -> 3900000 | AK2: =_xlfn.FORECAST.LINEAR(AK$1,$B2:$AF2,$B$1:$AF$1) -> 3900000 | AL2: =_xlfn.FORECAST.LINEAR(AL$1,$B2:$AF2,$B$1:$AF$1) -> 3900000 | AM2: =_xlfn.FORECAST.LINEAR(AM$1,$B2:$AF2,$B$1:$AF$1) -> 3900000 | AN2: =_xlfn.FORECAST.LINEAR(AN$1,$B2:$AF2,$B$1:$AF$1) -> 3900000 | ... AZ2: =_xlfn.FORECAST.LINEAR(AZ$1,$B2:$AF2,$B$1:$AF$1) -> 3900000
A3: natural gas vehicle | B3: 999999999 | C3: 999999999 | D3: 999999999 | E3: 999999999 | F3: 999999999 | G3: 999999999 | H3: 999999999 | I3: 999999999 | J3: 999999999 | K3: 999999999 | L3: 999999999 | M3: 999999999 | N3: 999999999 | O3: 999999999 | P3: 999999999 | Q3: 999999999 | R3: 999999999 | S3: 999999999 | T3: 999999999 | U3: 999999999 | V3: 999999999 | W3: 999999999 | X3: 999999999 | Y3: 999999999 | Z3: 999999999 | AA3: 999999999 | AB3: 999999999 | AC3: 999999999 | AD3: 999999999 | AE3: 999999999 | AF3: 999999999 | AG3: 999999999 | AH3: 999999999 | AI3: 999999999 | AJ3: 999999999 | AK3: 999999999 | AL3: 999999999 | AM3: 999999999 | AN3: 999999999 | AO3: 999999999 | AP3: 999999999 | AQ3: 999999999 | AR3: 999999999 | AS3: 999999999 | AT3: 999999999 | AU3: 999999999 | AV3: 999999999 | AW3: 999999999 | AX3: 999999999 | AY3: 999999999 | AZ3: 999999999
A4: gasoline vehicle | B4: 999999999 | C4: 999999999 | D4: 999999999 | E4: 999999999 | F4: 999999999 | G4: 999999999 | H4: 999999999 | I4: 999999999 | J4: 999999999 | K4: 999999999 | L4: 999999999 | M4: 999999999 | N4: 999999999 | O4: 999999999 | P4: 999999999 | Q4: 999999999 | R4: 999999999 | S4: 999999999 | T4: 999999999 | U4: 999999999 | V4: 999999999 | W4: 999999999 | X4: 999999999 | Y4: 999999999 | Z4: 999999999 | AA4: 999999999 | AB4: 999999999 | AC4: 999999999 | AD4: 999999999 | AE4: 999999999 | AF4: 999999999 | AG4: 999999999 | AH4: 999999999 | AI4: 999999999 | AJ4: 999999999 | AK4: 999999999 | AL4: 999999999 | AM4: 999999999 | AN4: 999999999 | AO4: 999999999 | AP4: 999999999 | AQ4: 999999999 | AR4: 999999999 | AS4: 999999999 | AT4: 999999999 | AU4: 999999999 | AV4: 999999999 | AW4: 999999999 | AX4: 999999999 | AY4: 999999999 | AZ4: 999999999
A5: diesel vehicle | B5: ='NVP-Indonesia'!B90*'NVP-Indonesia'!$B$176 -> 2101448.3 | C5: =$B5 -> 2101448.3 | D5: =$B5 -> 2101448.3 | E5: =$B5 -> 2101448.3 | F5: =$B5 -> 2101448.3 | G5: =$B5 -> 2101448.3 | H5: =$B5 -> 2101448.3 | I5: =$B5 -> 2101448.3 | J5: =$B5 -> 2101448.3 | ... AF5: =$B5 -> 2101448.3 | AG5: =_xlfn.FORECAST.LINEAR(AG$1,$B5:$AF5,$B$1:$AF$1) -> 2101448.3 | AH5: =_xlfn.FORECAST.LINEAR(AH$1,$B5:$AF5,$B$1:$AF$1) -> 2101448.3 | AI5: =_xlfn.FORECAST.LINEAR(AI$1,$B5:$AF5,$B$1:$AF$1) -> 2101448.3 | AJ5: =_xlfn.FORECAST.LINEAR(AJ$1,$B5:$AF5,$B$1:$AF$1) -> 2101448.3 | AK5: =_xlfn.FORECAST.LINEAR(AK$1,$B5:$AF5,$B$1:$AF$1) -> 2101448.3 | AL5: =_xlfn.FORECAST.LINEAR(AL$1,$B5:$AF5,$B$1:$AF$1) -> 2101448.3 | AM5: =_xlfn.FORECAST.LINEAR(AM$1,$B5:$AF5,$B$1:$AF$1) -> 2101448.3 | AN5: =_xlfn.FORECAST.LINEAR(AN$1,$B5:$AF5,$B$1:$AF$1) -> 2101448.3 | ... AZ5: =_xlfn.FORECAST.LINEAR(AZ$1,$B5:$AF5,$B$1:$AF$1) -> 2101448.3
A6: plugin hybrid vehicle | B6: 999999999 | C6: 999999999 | D6: 999999999 | E6: 999999999 | F6: 999999999 | G6: 999999999 | H6: 999999999 | I6: 999999999 | J6: 999999999 | K6: 999999999 | L6: 999999999 | M6: 999999999 | N6: 999999999 | O6: 999999999 | P6: 999999999 | Q6: 999999999 | R6: 999999999 | S6: 999999999 | T6: 999999999 | U6: 999999999 | V6: 999999999 | W6: 999999999 | X6: 999999999 | Y6: 999999999 | Z6: 999999999 | AA6: 999999999 | AB6: 999999999 | AC6: 999999999 | AD6: 999999999 | AE6: 999999999 | AF6: 999999999 | AG6: 999999999 | AH6: 999999999 | AI6: 999999999 | AJ6: 999999999 | AK6: 999999999 | AL6: 999999999 | AM6: 999999999 | AN6: 999999999 | AO6: 999999999 | AP6: 999999999 | AQ6: 999999999 | AR6: 999999999 | AS6: 999999999 | AT6: 999999999 | AU6: 999999999 | AV6: 999999999 | AW6: 999999999 | AX6: 999999999 | AY6: 999999999 | AZ6: 999999999
A7: LPG vehicle | B7: 999999999 | C7: 999999999 | D7: 999999999 | E7: 999999999 | F7: 999999999 | G7: 999999999 | H7: 999999999 | I7: 999999999 | J7: 999999999 | K7: 999999999 | L7: 999999999 | M7: 999999999 | N7: 999999999 | O7: 999999999 | P7: 999999999 | Q7: 999999999 | R7: 999999999 | S7: 999999999 | T7: 999999999 | U7: 999999999 | V7: 999999999 | W7: 999999999 | X7: 999999999 | Y7: 999999999 | Z7: 999999999 | AA7: 999999999 | AB7: 999999999 | AC7: 999999999 | AD7: 999999999 | AE7: 999999999 | AF7: 999999999 | AG7: 999999999 | AH7: 999999999 | AI7: 999999999 | AJ7: 999999999 | AK7: 999999999 | AL7: 999999999 | AM7: 999999999 | AN7: 999999999 | AO7: 999999999 | AP7: 999999999 | AQ7: 999999999 | AR7: 999999999 | AS7: 999999999 | AT7: 999999999 | AU7: 999999999 | AV7: 999999999 | AW7: 999999999 | AX7: 999999999 | AY7: 999999999 | AZ7: 999999999
A8: hydrogen vehicle | B8: ='NVP-Indonesia'!B93*'NVP-Indonesia'!$B$176 -> 6514489.6 | C8: =$B$8*('BNVP-HDVs-frgt'!C8/'BNVP-HDVs-frgt'!$B$8) -> 6513072.8 | D8: =$B$8*('BNVP-HDVs-frgt'!D8/'BNVP-HDVs-frgt'!$B$8) -> 6372195.9 | E8: =$B$8*('BNVP-HDVs-frgt'!E8/'BNVP-HDVs-frgt'!$B$8) -> 6248180.8 | F8: =$B$8*('BNVP-HDVs-frgt'!F8/'BNVP-HDVs-frgt'!$B$8) -> 6122912.1 | G8: =$B$8*('BNVP-HDVs-frgt'!G8/'BNVP-HDVs-frgt'!$B$8) -> 5993251.3 | H8: =$B$8*('BNVP-HDVs-frgt'!H8/'BNVP-HDVs-frgt'!$B$8) -> 5879343 | I8: =$B$8*('BNVP-HDVs-frgt'!I8/'BNVP-HDVs-frgt'!$B$8) -> 5774513 | J8: =$B$8*('BNVP-HDVs-frgt'!J8/'BNVP-HDVs-frgt'!$B$8) -> 5674522.7 | ... AF8: =$B$8*('BNVP-HDVs-frgt'!AF8/'BNVP-HDVs-frgt'!$B$8) -> 4317782.8 | AG8: =_xlfn.FORECAST.LINEAR(AG$1,$B8:$AF8,$B$1:$AF$1) -> 4029261.8 | AH8: =_xlfn.FORECAST.LINEAR(AH$1,$B8:$AF8,$B$1:$AF$1) -> 3954718.3 | AI8: =_xlfn.FORECAST.LINEAR(AI$1,$B8:$AF8,$B$1:$AF$1) -> 3880174.8 | AJ8: =_xlfn.FORECAST.LINEAR(AJ$1,$B8:$AF8,$B$1:$AF$1) -> 3805631.3 | AK8: =_xlfn.FORECAST.LINEAR(AK$1,$B8:$AF8,$B$1:$AF$1) -> 3731087.8 | AL8: =_xlfn.FORECAST.LINEAR(AL$1,$B8:$AF8,$B$1:$AF$1) -> 3656544.3 | AM8: =_xlfn.FORECAST.LINEAR(AM$1,$B8:$AF8,$B$1:$AF$1) -> 3582000.8 | AN8: =_xlfn.FORECAST.LINEAR(AN$1,$B8:$AF8,$B$1:$AF$1) -> 3507457.3 | ... AZ8: =_xlfn.FORECAST.LINEAR(AZ$1,$B8:$AF8,$B$1:$AF$1) -> 2612935.2

Sheet BNVP-ships-psgr
A1: Price ($/vehicle) | B1: 2020 | C1: 2021 | D1: 2022 | E1: 2023 | F1: 2024 | G1: 2025 | H1: 2026 | I1: 2027 | J1: 2028 | K1: 2029 | L1: 2030 | M1: 2031 | N1: 2032 | O1: 2033 | P1: 2034 | Q1: 2035 | R1: 2036 | S1: 2037 | T1: 2038 | U1: 2039 | V1: 2040 | W1: 2041 | X1: 2042 | Y1: 2043 | Z1: 2044 | AA1: 2045 | AB1: 2046 | AC1: 2047 | AD1: 2048 | AE1: 2049 | AF1: 2050 | AG1: 2051 | AH1: 2052 | AI1: 2053 | AJ1: 2054 | AK1: 2055 | AL1: 2056 | AM1: 2057 | AN1: 2058 | AO1: 2059 | AP1: 2060 | AQ1: 2061 | AR1: 2062 | AS1: 2063 | AT1: 2064 | AU1: 2065 | AV1: 2066 | AW1: 2067 | AX1: 2068 | AY1: 2069 | AZ1: 2070
A2: battery electric vehicle | B2: ='NVP-Indonesia'!B97*'NVP-Indonesia'!$B$176 -> 43256.265 | C2: =B2 -> 43256.265 | D2: =C2 -> 43256.265 | E2: =D2 -> 43256.265 | F2: =E2 -> 43256.265 | G2: =F2 -> 43256.265 | H2: =G2 -> 43256.265 | I2: =H2 -> 43256.265 | J2: =I2 -> 43256.265 | ... AF2: =AE2 -> 43256.265 | AG2: =_xlfn.FORECAST.LINEAR(AG$1,$B2:$AF2,$B$1:$AF$1) -> 43256.265 | AH2: =_xlfn.FORECAST.LINEAR(AH$1,$B2:$AF2,$B$1:$AF$1) -> 43256.265 | AI2: =_xlfn.FORECAST.LINEAR(AI$1,$B2:$AF2,$B$1:$AF$1) -> 43256.265 | AJ2: =_xlfn.FORECAST.LINEAR(AJ$1,$B2:$AF2,$B$1:$AF$1) -> 43256.265 | AK2: =_xlfn.FORECAST.LINEAR(AK$1,$B2:$AF2,$B$1:$AF$1) -> 43256.265 | AL2: =_xlfn.FORECAST.LINEAR(AL$1,$B2:$AF2,$B$1:$AF$1) -> 43256.265 | AM2: =_xlfn.FORECAST.LINEAR(AM$1,$B2:$AF2,$B$1:$AF$1) -> 43256.265 | AN2: =_xlfn.FORECAST.LINEAR(AN$1,$B2:$AF2,$B$1:$AF$1) -> 43256.265 | ... AZ2: =_xlfn.FORECAST.LINEAR(AZ$1,$B2:$AF2,$B$1:$AF$1) -> 43256.265
A3: natural gas vehicle | B3: 999999999 | C3: 999999999 | D3: 999999999 | E3: 999999999 | F3: 999999999 | G3: 999999999 | H3: 999999999 | I3: 999999999 | J3: 999999999 | K3: 999999999 | L3: 999999999 | M3: 999999999 | N3: 999999999 | O3: 999999999 | P3: 999999999 | Q3: 999999999 | R3: 999999999 | S3: 999999999 | T3: 999999999 | U3: 999999999 | V3: 999999999 | W3: 999999999 | X3: 999999999 | Y3: 999999999 | Z3: 999999999 | AA3: 999999999 | AB3: 999999999 | AC3: 999999999 | AD3: 999999999 | AE3: 999999999 | AF3: 999999999 | AG3: 999999999 | AH3: 999999999 | AI3: 999999999 | AJ3: 999999999 | AK3: 999999999 | AL3: 999999999 | AM3: 999999999 | AN3: 999999999 | AO3: 999999999 | AP3: 999999999 | AQ3: 999999999 | AR3: 999999999 | AS3: 999999999 | AT3: 999999999 | AU3: 999999999 | AV3: 999999999 | AW3: 999999999 | AX3: 999999999 | AY3: 999999999 | AZ3: 999999999
A4: gasoline vehicle | B4: ='NVP-Indonesia'!B99*'NVP-Indonesia'!$B$176 -> 23400 | C4: =C$5 -> 23400 | D4: =D$5 -> 23400 | E4: =E$5 -> 23400 | F4: =F$5 -> 23400 | G4: =G$5 -> 23400 | H4: =H$5 -> 23400 | I4: =I$5 -> 23400 | J4: =J$5 -> 23400 | ... AF4: =AF$5 -> 23400 | AG4: =_xlfn.FORECAST.LINEAR(AG$1,$B4:$AF4,$B$1:$AF$1) -> 23400 | AH4: =_xlfn.FORECAST.LINEAR(AH$1,$B4:$AF4,$B$1:$AF$1) -> 23400 | AI4: =_xlfn.FORECAST.LINEAR(AI$1,$B4:$AF4,$B$1:$AF$1) -> 23400 | AJ4: =_xlfn.FORECAST.LINEAR(AJ$1,$B4:$AF4,$B$1:$AF$1) -> 23400 | AK4: =_xlfn.FORECAST.LINEAR(AK$1,$B4:$AF4,$B$1:$AF$1) -> 23400 | AL4: =_xlfn.FORECAST.LINEAR(AL$1,$B4:$AF4,$B$1:$AF$1) -> 23400 | AM4: =_xlfn.FORECAST.LINEAR(AM$1,$B4:$AF4,$B$1:$AF$1) -> 23400 | AN4: =_xlfn.FORECAST.LINEAR(AN$1,$B4:$AF4,$B$1:$AF$1) -> 23400 | ... AZ4: =_xlfn.FORECAST.LINEAR(AZ$1,$B4:$AF4,$B$1:$AF$1) -> 23400
A5: diesel vehicle | B5: ='NVP-Indonesia'!B100*'NVP-Indonesia'!$B$176 -> 23400 | C5: =$B5 -> 23400 | D5: =$B5 -> 23400 | E5: =$B5 -> 23400 | F5: =$B5 -> 23400 | G5: =$B5 -> 23400 | H5: =$B5 -> 23400 | I5: =$B5 -> 23400 | J5: =$B5 -> 23400 | ... AF5: =$B5 -> 23400 | AG5: =_xlfn.FORECAST.LINEAR(AG$1,$B5:$AF5,$B$1:$AF$1) -> 23400 | AH5: =_xlfn.FORECAST.LINEAR(AH$1,$B5:$AF5,$B$1:$AF$1) -> 23400 | AI5: =_xlfn.FORECAST.LINEAR(AI$1,$B5:$AF5,$B$1:$AF$1) -> 23400 | AJ5: =_xlfn.FORECAST.LINEAR(AJ$1,$B5:$AF5,$B$1:$AF$1) -> 23400 | AK5: =_xlfn.FORECAST.LINEAR(AK$1,$B5:$AF5,$B$1:$AF$1) -> 23400 | AL5: =_xlfn.FORECAST.LINEAR(AL$1,$B5:$AF5,$B$1:$AF$1) -> 23400 | AM5: =_xlfn.FORECAST.LINEAR(AM$1,$B5:$AF5,$B$1:$AF$1) -> 23400 | AN5: =_xlfn.FORECAST.LINEAR(AN$1,$B5:$AF5,$B$1:$AF$1) -> 23400 | ... AZ5: =_xlfn.FORECAST.LINEAR(AZ$1,$B5:$AF5,$B$1:$AF$1) -> 23400
A6: plugin hybrid vehicle | B6: 999999999 | C6: 999999999 | D6: 999999999 | E6: 999999999 | F6: 999999999 | G6: 999999999 | H6: 999999999 | I6: 999999999 | J6: 999999999 | K6: 999999999 | L6: 999999999 | M6: 999999999 | N6: 999999999 | O6: 999999999 | P6: 999999999 | Q6: 999999999 | R6: 999999999 | S6: 999999999 | T6: 999999999 | U6: 999999999 | V6: 999999999 | W6: 999999999 | X6: 999999999 | Y6: 999999999 | Z6: 999999999 | AA6: 999999999 | AB6: 999999999 | AC6: 999999999 | AD6: 999999999 | AE6: 999999999 | AF6: 999999999 | AG6: 999999999 | AH6: 999999999 | AI6: 999999999 | AJ6: 999999999 | AK6: 999999999 | AL6: 999999999 | AM6: 999999999 | AN6: 999999999 | AO6: 999999999 | AP6: 999999999 | AQ6: 999999999 | AR6: 999999999 | AS6: 999999999 | AT6: 999999999 | AU6: 999999999 | AV6: 999999999 | AW6: 999999999 | AX6: 999999999 | AY6: 999999999 | AZ6: 999999999
A7: LPG vehicle | B7: 999999999 | C7: 999999999 | D7: 999999999 | E7: 999999999 | F7: 999999999 | G7: 999999999 | H7: 999999999 | I7: 999999999 | J7: 999999999 | K7: 999999999 | L7: 999999999 | M7: 999999999 | N7: 999999999 | O7: 999999999 | P7: 999999999 | Q7: 999999999 | R7: 999999999 | S7: 999999999 | T7: 999999999 | U7: 999999999 | V7: 999999999 | W7: 999999999 | X7: 999999999 | Y7: 999999999 | Z7: 999999999 | AA7: 999999999 | AB7: 999999999 | AC7: 999999999 | AD7: 999999999 | AE7: 999999999 | AF7: 999999999 | AG7: 999999999 | AH7: 999999999 | AI7: 999999999 | AJ7: 999999999 | AK7: 999999999 | AL7: 999999999 | AM7: 999999999 | AN7: 999999999 | AO7: 999999999 | AP7: 999999999 | AQ7: 999999999 | AR7: 999999999 | AS7: 999999999 | AT7: 999999999 | AU7: 999999999 | AV7: 999999999 | AW7: 999999999 | AX7: 999999999 | AY7: 999999999 | AZ7: 999999999
A8: hydrogen vehicle | B8: ='NVP-Indonesia'!B103*'NVP-Indonesia'!$B$176 -> 47087.119 | C8: =C$5*('BNVP-HDVs-psgr'!C$8/'BNVP-HDVs-psgr'!C$5) -> 22560.348 | D8: =D$5*('BNVP-HDVs-psgr'!D$8/'BNVP-HDVs-psgr'!D$5) -> 22560.348 | E8: =E$5*('BNVP-HDVs-psgr'!E$8/'BNVP-HDVs-psgr'!E$5) -> 22560.348 | F8: =F$5*('BNVP-HDVs-psgr'!F$8/'BNVP-HDVs-psgr'!F$5) -> 22560.348 | G8: =G$5*('BNVP-HDVs-psgr'!G$8/'BNVP-HDVs-psgr'!G$5) -> 22560.348 | H8: =H$5*('BNVP-HDVs-psgr'!H$8/'BNVP-HDVs-psgr'!H$5) -> 22560.348 | I8: =I$5*('BNVP-HDVs-psgr'!I$8/'BNVP-HDVs-psgr'!I$5) -> 22560.348 | J8: =J$5*('BNVP-HDVs-psgr'!J$8/'BNVP-HDVs-psgr'!J$5) -> 22560.348 | ... AF8: =AF$5*('BNVP-HDVs-psgr'!AF$8/'BNVP-HDVs-psgr'!AF$5) -> 22560.348 | AG8: =_xlfn.FORECAST.LINEAR(AG$1,$B8:$AF8,$B$1:$AF$1) -> 20977.975 | AH8: =_xlfn.FORECAST.LINEAR(AH$1,$B8:$AF8,$B$1:$AF$1) -> 20829.628 | AI8: =_xlfn.FORECAST.LINEAR(AI$1,$B8:$AF8,$B$1:$AF$1) -> 20681.28 | AJ8: =_xlfn.FORECAST.LINEAR(AJ$1,$B8:$AF8,$B$1:$AF$1) -> 20532.933 | AK8: =_xlfn.FORECAST.LINEAR(AK$1,$B8:$AF8,$B$1:$AF$1) -> 20384.586 | AL8: =_xlfn.FORECAST.LINEAR(AL$1,$B8:$AF8,$B$1:$AF$1) -> 20236.238 | AM8: =_xlfn.FORECAST.LINEAR(AM$1,$B8:$AF8,$B$1:$AF$1) -> 20087.891 | AN8: =_xlfn.FORECAST.LINEAR(AN$1,$B8:$AF8,$B$1:$AF$1) -> 19939.543 | ... AZ8: =_xlfn.FORECAST.LINEAR(AZ$1,$B8:$AF8,$B$1:$AF$1) -> 18159.375

Sheet BNVP-ships-frgt
A1: Price ($/vehicle) | B1: 2020 | C1: 2021 | D1: 2022 | E1: 2023 | F1: 2024 | G1: 2025 | H1: 2026 | I1: 2027 | J1: 2028 | K1: 2029 | L1: 2030 | M1: 2031 | N1: 2032 | O1: 2033 | P1: 2034 | Q1: 2035 | R1: 2036 | S1: 2037 | T1: 2038 | U1: 2039 | V1: 2040 | W1: 2041 | X1: 2042 | Y1: 2043 | Z1: 2044 | AA1: 2045 | AB1: 2046 | AC1: 2047 | AD1: 2048 | AE1: 2049 | AF1: 2050 | AG1: 2051 | AH1: 2052 | AI1: 2053 | AJ1: 2054 | AK1: 2055 | AL1: 2056 | AM1: 2057 | AN1: 2058 | AO1: 2059 | AP1: 2060 | AQ1: 2061 | AR1: 2062 | AS1: 2063 | AT1: 2064 | AU1: 2065 | AV1: 2066 | AW1: 2067 | AX1: 2068 | AY1: 2069 | AZ1: 2070
A2: battery electric vehicle | B2: ='NVP-Indonesia'!B107*'NVP-Indonesia'!$B$176 -> 14418755 | C2: =B2 -> 14418755 | D2: =C2 -> 14418755 | E2: =D2 -> 14418755 | F2: =E2 -> 14418755 | G2: =F2 -> 14418755 | H2: =G2 -> 14418755 | I2: =H2 -> 14418755 | J2: =I2 -> 14418755 | ... AF2: =AE2 -> 14418755 | AG2: =_xlfn.FORECAST.LINEAR(AG$1,$B2:$AF2,$B$1:$AF$1) -> 14418755 | AH2: =_xlfn.FORECAST.LINEAR(AH$1,$B2:$AF2,$B$1:$AF$1) -> 14418755 | AI2: =_xlfn.FORECAST.LINEAR(AI$1,$B2:$AF2,$B$1:$AF$1) -> 14418755 | AJ2: =_xlfn.FORECAST.LINEAR(AJ$1,$B2:$AF2,$B$1:$AF$1) -> 14418755 | AK2: =_xlfn.FORECAST.LINEAR(AK$1,$B2:$AF2,$B$1:$AF$1) -> 14418755 | AL2: =_xlfn.FORECAST.LINEAR(AL$1,$B2:$AF2,$B$1:$AF$1) -> 14418755 | AM2: =_xlfn.FORECAST.LINEAR(AM$1,$B2:$AF2,$B$1:$AF$1) -> 14418755 | AN2: =_xlfn.FORECAST.LINEAR(AN$1,$B2:$AF2,$B$1:$AF$1) -> 14418755 | ... AZ2: =_xlfn.FORECAST.LINEAR(AZ$1,$B2:$AF2,$B$1:$AF$1) -> 14418755
A3: natural gas vehicle | B3: 999999999 | C3: 999999999 | D3: 999999999 | E3: 999999999 | F3: 999999999 | G3: 999999999 | H3: 999999999 | I3: 999999999 | J3: 999999999 | K3: 999999999 | L3: 999999999 | M3: 999999999 | N3: 999999999 | O3: 999999999 | P3: 999999999 | Q3: 999999999 | R3: 999999999 | S3: 999999999 | T3: 999999999 | U3: 999999999 | V3: 999999999 | W3: 999999999 | X3: 999999999 | Y3: 999999999 | Z3: 999999999 | AA3: 999999999 | AB3: 999999999 | AC3: 999999999 | AD3: 999999999 | AE3: 999999999 | AF3: 999999999 | AG3: 999999999 | AH3: 999999999 | AI3: 999999999 | AJ3: 999999999 | AK3: 999999999 | AL3: 999999999 | AM3: 999999999 | AN3: 999999999 | AO3: 999999999 | AP3: 999999999 | AQ3: 999999999 | AR3: 999999999 | AS3: 999999999 | AT3: 999999999 | AU3: 999999999 | AV3: 999999999 | AW3: 999999999 | AX3: 999999999 | AY3: 999999999 | AZ3: 999999999
A4: gasoline vehicle | B4: 999999999 | C4: 999999999 | D4: 999999999 | E4: 999999999 | F4: 999999999 | G4: 999999999 | H4: 999999999 | I4: 999999999 | J4: 999999999 | K4: 999999999 | L4: 999999999 | M4: 999999999 | N4: 999999999 | O4: 999999999 | P4: 999999999 | Q4: 999999999 | R4: 999999999 | S4: 999999999 | T4: 999999999 | U4: 999999999 | V4: 999999999 | W4: 999999999 | X4: 999999999 | Y4: 999999999 | Z4: 999999999 | AA4: 999999999 | AB4: 999999999 | AC4: 999999999 | AD4: 999999999 | AE4: 999999999 | AF4: 999999999 | AG4: 999999999 | AH4: 999999999 | AI4: 999999999 | AJ4: 999999999 | AK4: 999999999 | AL4: 999999999 | AM4: 999999999 | AN4: 999999999 | AO4: 999999999 | AP4: 999999999 | AQ4: 999999999 | AR4: 999999999 | AS4: 999999999 | AT4: 999999999 | AU4: 999999999 | AV4: 999999999 | AW4: 999999999 | AX4: 999999999 | AY4: 999999999 | AZ4: 999999999
A5: diesel vehicle | B5: ='NVP-Indonesia'!B110*'NVP-Indonesia'!$B$176 -> 7800000 | C5: =$B5 -> 7800000 | D5: =$B5 -> 7800000 | E5: =$B5 -> 7800000 | F5: =$B5 -> 7800000 | G5: =$B5 -> 7800000 | H5: =$B5 -> 7800000 | I5: =$B5 -> 7800000 | J5: =$B5 -> 7800000 | ... AF5: =$B5 -> 7800000 | AG5: =_xlfn.FORECAST.LINEAR(AG$1,$B5:$AF5,$B$1:$AF$1) -> 7800000 | AH5: =_xlfn.FORECAST.LINEAR(AH$1,$B5:$AF5,$B$1:$AF$1) -> 7800000 | AI5: =_xlfn.FORECAST.LINEAR(AI$1,$B5:$AF5,$B$1:$AF$1) -> 7800000 | AJ5: =_xlfn.FORECAST.LINEAR(AJ$1,$B5:$AF5,$B$1:$AF$1) -> 7800000 | AK5: =_xlfn.FORECAST.LINEAR(AK$1,$B5:$AF5,$B$1:$AF$1) -> 7800000 | AL5: =_xlfn.FORECAST.LINEAR(AL$1,$B5:$AF5,$B$1:$AF$1) -> 7800000 | AM5: =_xlfn.FORECAST.LINEAR(AM$1,$B5:$AF5,$B$1:$AF$1) -> 7800000 | AN5: =_xlfn.FORECAST.LINEAR(AN$1,$B5:$AF5,$B$1:$AF$1) -> 7800000 | ... AZ5: =_xlfn.FORECAST.LINEAR(AZ$1,$B5:$AF5,$B$1:$AF$1) -> 7800000
A6: plugin hybrid vehicle | B6: 999999999 | C6: 999999999 | D6: 999999999 | E6: 999999999 | F6: 999999999 | G6: 999999999 | H6: 999999999 | I6: 999999999 | J6: 999999999 | K6: 999999999 | L6: 999999999 | M6: 999999999 | N6: 999999999 | O6: 999999999 | P6: 999999999 | Q6: 999999999 | R6: 999999999 | S6: 999999999 | T6: 999999999 | U6: 999999999 | V6: 999999999 | W6: 999999999 | X6: 999999999 | Y6: 999999999 | Z6: 999999999 | AA6: 999999999 | AB6: 999999999 | AC6: 999999999 | AD6: 999999999 | AE6: 999999999 | AF6: 999999999 | AG6: 999999999 | AH6: 999999999 | AI6: 999999999 | AJ6: 999999999 | AK6: 999999999 | AL6: 999999999 | AM6: 999999999 | AN6: 999999999 | AO6: 999999999 | AP6: 999999999 | AQ6: 999999999 | AR6: 999999999 | AS6: 999999999 | AT6: 999999999 | AU6: 999999999 | AV6: 999999999 | AW6: 999999999 | AX6: 999999999 | AY6: 999999999 | AZ6: 999999999
A7: LPG vehicle | B7: 999999999 | C7: 999999999 | D7: 999999999 | E7: 999999999 | F7: 999999999 | G7: 999999999 | H7: 999999999 | I7: 999999999 | J7: 999999999 | K7: 999999999 | L7: 999999999 | M7: 999999999 | N7: 999999999 | O7: 999999999 | P7: 999999999 | Q7: 999999999 | R7: 999999999 | S7: 999999999 | T7: 999999999 | U7: 999999999 | V7: 999999999 | W7: 999999999 | X7: 999999999 | Y7: 999999999 | Z7: 999999999 | AA7: 999999999 | AB7: 999999999 | AC7: 999999999 | AD7: 999999999 | AE7: 999999999 | AF7: 999999999 | AG7: 999999999 | AH7: 999999999 | AI7: 999999999 | AJ7: 999999999 | AK7: 999999999 | AL7: 999999999 | AM7: 999999999 | AN7: 999999999 | AO7: 999999999 | AP7: 999999999 | AQ7: 999999999 | AR7: 999999999 | AS7: 999999999 | AT7: 999999999 | AU7: 999999999 | AV7: 999999999 | AW7: 999999999 | AX7: 999999999 | AY7: 999999999 | AZ7: 999999999
A8: hydrogen vehicle | B8: ='NVP-Indonesia'!B113*'NVP-Indonesia'!$B$176 -> 15695706 | C8: =C$5*('BNVP-HDVs-psgr'!C$8/'BNVP-HDVs-psgr'!C$5) -> 7520115.9 | D8: =D$5*('BNVP-HDVs-psgr'!D$8/'BNVP-HDVs-psgr'!D$5) -> 7520115.9 | E8: =E$5*('BNVP-HDVs-psgr'!E$8/'BNVP-HDVs-psgr'!E$5) -> 7520115.9 | F8: =F$5*('BNVP-HDVs-psgr'!F$8/'BNVP-HDVs-psgr'!F$5) -> 7520115.9 | G8: =G$5*('BNVP-HDVs-psgr'!G$8/'BNVP-HDVs-psgr'!G$5) -> 7520115.9 | H8: =H$5*('BNVP-HDVs-psgr'!H$8/'BNVP-HDVs-psgr'!H$5) -> 7520115.9 | I8: =I$5*('BNVP-HDVs-psgr'!I$8/'BNVP-HDVs-psgr'!I$5) -> 7520115.9 | J8: =J$5*('BNVP-HDVs-psgr'!J$8/'BNVP-HDVs-psgr'!J$5) -> 7520115.9 | ... AF8: =AF$5*('BNVP-HDVs-psgr'!AF$8/'BNVP-HDVs-psgr'!AF$5) -> 7520115.9 | AG8: =_xlfn.FORECAST.LINEAR(AG$1,$B8:$AF8,$B$1:$AF$1) -> 6992658.4 | AH8: =_xlfn.FORECAST.LINEAR(AH$1,$B8:$AF8,$B$1:$AF$1) -> 6943209.3 | AI8: =_xlfn.FORECAST.LINEAR(AI$1,$B8:$AF8,$B$1:$AF$1) -> 6893760.2 | AJ8: =_xlfn.FORECAST.LINEAR(AJ$1,$B8:$AF8,$B$1:$AF$1) -> 6844311 | AK8: =_xlfn.FORECAST.LINEAR(AK$1,$B8:$AF8,$B$1:$AF$1) -> 6794861.9 | AL8: =_xlfn.FORECAST.LINEAR(AL$1,$B8:$AF8,$B$1:$AF$1) -> 6745412.8 | AM8: =_xlfn.FORECAST.LINEAR(AM$1,$B8:$AF8,$B$1:$AF$1) -> 6695963.6 | AN8: =_xlfn.FORECAST.LINEAR(AN$1,$B8:$AF8,$B$1:$AF$1) -> 6646514.5 | ... AZ8: =_xlfn.FORECAST.LINEAR(AZ$1,$B8:$AF8,$B$1:$AF$1) -> 6053124.9

Sheet BNVP-motorbikes-psgr
A1: Price ($/vehicle) | B1: 2020 | C1: 2021 | D1: 2022 | E1: 2023 | F1: 2024 | G1: 2025 | H1: 2026 | I1: 2027 | J1: 2028 | K1: 2029 | L1: 2030 | M1: 2031 | N1: 2032 | O1: 2033 | P1: 2034 | Q1: 2035 | R1: 2036 | S1: 2037 | T1: 2038 | U1: 2039 | V1: 2040 | W1: 2041 | X1: 2042 | Y1: 2043 | Z1: 2044 | AA1: 2045 | AB1: 2046 | AC1: 2047 | AD1: 2048 | AE1: 2049 | AF1: 2050 | AG1: 2051 | AH1: 2052 | AI1: 2053 | AJ1: 2054 | AK1: 2055 | AL1: 2056 | AM1: 2057 | AN1: 2058 | AO1: 2059 | AP1: 2060 | AQ1: 2061 | AR1: 2062 | AS1: 2063 | AT1: 2064 | AU1: 2065 | AV1: 2066 | AW1: 2067 | AX1: 2068 | AY1: 2069 | AZ1: 2070
A2: battery electric vehicle | B2: ='NVP-Indonesia'!B117*'NVP-Indonesia'!$B$176 -> 10262.765 | C2: =$B$2 -> 10262.765 | D2: =$B$2 -> 10262.765 | E2: =$B$2 -> 10262.765 | F2: =$B$2 -> 10262.765 | G2: =$B$2 -> 10262.765 | H2: =$B$2 -> 10262.765 | I2: =$B$2 -> 10262.765 | J2: =$B$2 -> 10262.765 | ... AF2: =$B$2 -> 10262.765 | AG2: =_xlfn.FORECAST.LINEAR(AG$1,$B2:$AF2,$B$1:$AF$1) -> 10262.765 | AH2: =_xlfn.FORECAST.LINEAR(AH$1,$B2:$AF2,$B$1:$AF$1) -> 10262.765 | AI2: =_xlfn.FORECAST.LINEAR(AI$1,$B2:$AF2,$B$1:$AF$1) -> 10262.765 | AJ2: =_xlfn.FORECAST.LINEAR(AJ$1,$B2:$AF2,$B$1:$AF$1) -> 10262.765 | AK2: =_xlfn.FORECAST.LINEAR(AK$1,$B2:$AF2,$B$1:$AF$1) -> 10262.765 | AL2: =_xlfn.FORECAST.LINEAR(AL$1,$B2:$AF2,$B$1:$AF$1) -> 10262.765 | AM2: =_xlfn.FORECAST.LINEAR(AM$1,$B2:$AF2,$B$1:$AF$1) -> 10262.765 | AN2: =_xlfn.FORECAST.LINEAR(AN$1,$B2:$AF2,$B$1:$AF$1) -> 10262.765 | ... AZ2: =_xlfn.FORECAST.LINEAR(AZ$1,$B2:$AF2,$B$1:$AF$1) -> 10262.765
A3: natural gas vehicle | B3: 999999999 | C3: 999999999 | D3: 999999999 | E3: 999999999 | F3: 999999999 | G3: 999999999 | H3: 999999999 | I3: 999999999 | J3: 999999999 | K3: 999999999 | L3: 999999999 | M3: 999999999 | N3: 999999999 | O3: 999999999 | P3: 999999999 | Q3: 999999999 | R3: 999999999 | S3: 999999999 | T3: 999999999 | U3: 999999999 | V3: 999999999 | W3: 999999999 | X3: 999999999 | Y3: 999999999 | Z3: 999999999 | AA3: 999999999 | AB3: 999999999 | AC3: 999999999 | AD3: 999999999 | AE3: 999999999 | AF3: 999999999 | AG3: 999999999 | AH3: 999999999 | AI3: 999999999 | AJ3: 999999999 | AK3: 999999999 | AL3: 999999999 | AM3: 999999999 | AN3: 999999999 | AO3: 999999999 | AP3: 999999999 | AQ3: 999999999 | AR3: 999999999 | AS3: 999999999 | AT3: 999999999 | AU3: 999999999 | AV3: 999999999 | AW3: 999999999 | AX3: 999999999 | AY3: 999999999 | AZ3: 999999999
A4: gasoline vehicle | B4: ='NVP-Indonesia'!B119*'NVP-Indonesia'!$B$176 -> 7004.4 | C4: =$B4 -> 7004.4 | D4: =$B4 -> 7004.4 | E4: =$B4 -> 7004.4 | F4: =$B4 -> 7004.4 | G4: =$B4 -> 7004.4 | H4: =$B4 -> 7004.4 | I4: =$B4 -> 7004.4 | J4: =$B4 -> 7004.4 | ... AF4: =$B4 -> 7004.4 | AG4: =_xlfn.FORECAST.LINEAR(AG$1,$B4:$AF4,$B$1:$AF$1) -> 7004.4 | AH4: =_xlfn.FORECAST.LINEAR(AH$1,$B4:$AF4,$B$1:$AF$1) -> 7004.4 | AI4: =_xlfn.FORECAST.LINEAR(AI$1,$B4:$AF4,$B$1:$AF$1) -> 7004.4 | AJ4: =_xlfn.FORECAST.LINEAR(AJ$1,$B4:$AF4,$B$1:$AF$1) -> 7004.4 | AK4: =_xlfn.FORECAST.LINEAR(AK$1,$B4:$AF4,$B$1:$AF$1) -> 7004.4 | AL4: =_xlfn.FORECAST.LINEAR(AL$1,$B4:$AF4,$B$1:$AF$1) -> 7004.4 | AM4: =_xlfn.FORECAST.LINEAR(AM$1,$B4:$AF4,$B$1:$AF$1) -> 7004.4 | AN4: =_xlfn.FORECAST.LINEAR(AN$1,$B4:$AF4,$B$1:$AF$1) -> 7004.4 | ... AZ4: =_xlfn.FORECAST.LINEAR(AZ$1,$B4:$AF4,$B$1:$AF$1) -> 7004.4
A5: diesel vehicle | B5: 999999999 | C5: 999999999 | D5: 999999999 | E5: 999999999 | F5: 999999999 | G5: 999999999 | H5: 999999999 | I5: 999999999 | J5: 999999999 | K5: 999999999 | L5: 999999999 | M5: 999999999 | N5: 999999999 | O5: 999999999 | P5: 999999999 | Q5: 999999999 | R5: 999999999 | S5: 999999999 | T5: 999999999 | U5: 999999999 | V5: 999999999 | W5: 999999999 | X5: 999999999 | Y5: 999999999 | Z5: 999999999 | AA5: 999999999 | AB5: 999999999 | AC5: 999999999 | AD5: 999999999 | AE5: 999999999 | AF5: 999999999 | AG5: 999999999 | AH5: 999999999 | AI5: 999999999 | AJ5: 999999999 | AK5: 999999999 | AL5: 999999999 | AM5: 999999999 | AN5: 999999999 | AO5: 999999999 | AP5: 999999999 | AQ5: 999999999 | AR5: 999999999 | AS5: 999999999 | AT5: 999999999 | AU5: 999999999 | AV5: 999999999 | AW5: 999999999 | AX5: 999999999 | AY5: 999999999 | AZ5: 999999999
A6: plugin hybrid vehicle | B6: 999999999 | C6: 999999999 | D6: 999999999 | E6: 999999999 | F6: 999999999 | G6: 999999999 | H6: 999999999 | I6: 999999999 | J6: 999999999 | K6: 999999999 | L6: 999999999 | M6: 999999999 | N6: 999999999 | O6: 999999999 | P6: 999999999 | Q6: 999999999 | R6: 999999999 | S6: 999999999 | T6: 999999999 | U6: 999999999 | V6: 999999999 | W6: 999999999 | X6: 999999999 | Y6: 999999999 | Z6: 999999999 | AA6: 999999999 | AB6: 999999999 | AC6: 999999999 | AD6: 999999999 | AE6: 999999999 | AF6: 999999999 | AG6: 999999999 | AH6: 999999999 | AI6: 999999999 | AJ6: 999999999 | AK6: 999999999 | AL6: 999999999 | AM6: 999999999 | AN6: 999999999 | AO6: 999999999 | AP6: 999999999 | AQ6: 999999999 | AR6: 999999999 | AS6: 999999999 | AT6: 999999999 | AU6: 999999999 | AV6: 999999999 | AW6: 999999999 | AX6: 999999999 | AY6: 999999999 | AZ6: 999999999
A7: LPG vehicle | B7: 999999999 | C7: 999999999 | D7: 999999999 | E7: 999999999 | F7: 999999999 | G7: 999999999 | H7: 999999999 | I7: 999999999 | J7: 999999999 | K7: 999999999 | L7: 999999999 | M7: 999999999 | N7: 999999999 | O7: 999999999 | P7: 999999999 | Q7: 999999999 | R7: 999999999 | S7: 999999999 | T7: 999999999 | U7: 999999999 | V7: 999999999 | W7: 999999999 | X7: 999999999 | Y7: 999999999 | Z7: 999999999 | AA7: 999999999 | AB7: 999999999 | AC7: 999999999 | AD7: 999999999 | AE7: 999999999 | AF7: 999999999 | AG7: 999999999 | AH7: 999999999 | AI7: 999999999 | AJ7: 999999999 | AK7: 999999999 | AL7: 999999999 | AM7: 999999999 | AN7: 999999999 | AO7: 999999999 | AP7: 999999999 | AQ7: 999999999 | AR7: 999999999 | AS7: 999999999 | AT7: 999999999 | AU7: 999999999 | AV7: 999999999 | AW7: 999999999 | AX7: 999999999 | AY7: 999999999 | AZ7: 999999999
A8: hydrogen vehicle | B8: 999999999 | C8: 999999999 | D8: 999999999 | E8: 999999999 | F8: 999999999 | G8: 999999999 | H8: 999999999 | I8: 999999999 | J8: 999999999 | K8: 999999999 | L8: 999999999 | M8: 999999999 | N8: 999999999 | O8: 999999999 | P8: 999999999 | Q8: 999999999 | R8: 999999999 | S8: 999999999 | T8: 999999999 | U8: 999999999 | V8: 999999999 | W8: 999999999 | X8: 999999999 | Y8: 999999999 | Z8: 999999999 | AA8: 999999999 | AB8: 999999999 | AC8: 999999999 | AD8: 999999999 | AE8: 999999999 | AF8: 999999999 | AG8: 999999999 | AH8: 999999999 | AI8: 999999999 | AJ8: 999999999 | AK8: 999999999 | AL8: 999999999 | AM8: 999999999 | AN8: 999999999 | AO8: 999999999 | AP8: 999999999 | AQ8: 999999999 | AR8: 999999999 | AS8: 999999999 | AT8: 999999999 | AU8: 999999999 | AV8: 999999999 | AW8: 999999999 | AX8: 999999999 | AY8: 999999999 | AZ8: 999999999

Sheet BNVP-motorbikes-frgt
A1: Price ($/vehicle) | B1: 2020 | C1: 2021 | D1: 2022 | E1: 2023 | F1: 2024 | G1: 2025 | H1: 2026 | I1: 2027 | J1: 2028 | K1: 2029 | L1: 2030 | M1: 2031 | N1: 2032 | O1: 2033 | P1: 2034 | Q1: 2035 | R1: 2036 | S1: 2037 | T1: 2038 | U1: 2039 | V1: 2040 | W1: 2041 | X1: 2042 | Y1: 2043 | Z1: 2044 | AA1: 2045 | AB1: 2046 | AC1: 2047 | AD1: 2048 | AE1: 2049 | AF1: 2050 | AG1: 2051 | AH1: 2052 | AI1: 2053 | AJ1: 2054 | AK1: 2055 | AL1: 2056 | AM1: 2057 | AN1: 2058 | AO1: 2059 | AP1: 2060 | AQ1: 2061 | AR1: 2062 | AS1: 2063 | AT1: 2064 | AU1: 2065 | AV1: 2066 | AW1: 2067 | AX1: 2068 | AY1: 2069 | AZ1: 2070
A2: battery electric vehicle | B2: ='NVP-Indonesia'!B127*'NVP-Indonesia'!$B$176 -> 0 | C2: ='NVP-Indonesia'!C127*'NVP-Indonesia'!$B$176 -> 0 | D2: ='NVP-Indonesia'!D127*'NVP-Indonesia'!$B$176 -> 0 | E2: ='NVP-Indonesia'!E127*'NVP-Indonesia'!$B$176 -> 0 | F2: ='NVP-Indonesia'!F127*'NVP-Indonesia'!$B$176 -> 0 | G2: ='NVP-Indonesia'!G127*'NVP-Indonesia'!$B$176 -> 0 | H2: ='NVP-Indonesia'!H127*'NVP-Indonesia'!$B$176 -> 0 | I2: ='NVP-Indonesia'!I127*'NVP-Indonesia'!$B$176 -> 0 | ... AZ2: ='NVP-Indonesia'!AZ127*'NVP-Indonesia'!$B$176 -> 0
A3: natural gas vehicle | B3: 0 | C3: 0 | D3: 0 | E3: 0 | F3: 0 | G3: 0 | H3: 0 | I3: 0 | J3: 0 | K3: 0 | L3: 0 | M3: 0 | N3: 0 | O3: 0 | P3: 0 | Q3: 0 | R3: 0 | S3: 0 | T3: 0 | U3: 0 | V3: 0 | W3: 0 | X3: 0 | Y3: 0 | Z3: 0 | AA3: 0 | AB3: 0 | AC3: 0 | AD3: 0 | AE3: 0 | AF3: 0 | AG3: 0 | AH3: 0 | AI3: 0 | AJ3: 0 | AK3: 0 | AL3: 0 | AM3: 0 | AN3: 0 | AO3: 0 | AP3: 0 | AQ3: 0 | AR3: 0 | AS3: 0 | AT3: 0 | AU3: 0 | AV3: 0 | AW3: 0 | AX3: 0 | AY3: 0 | AZ3: 0
A4: gasoline vehicle | B4: 0 | C4: 0 | D4: 0 | E4: 0 | F4: 0 | G4: 0 | H4: 0 | I4: 0 | J4: 0 | K4: 0 | L4: 0 | M4: 0 | N4: 0 | O4: 0 | P4: 0 | Q4: 0 | R4: 0 | S4: 0 | T4: 0 | U4: 0 | V4: 0 | W4: 0 | X4: 0 | Y4: 0 | Z4: 0 | AA4: 0 | AB4: 0 | AC4: 0 | AD4: 0 | AE4: 0 | AF4: 0 | AG4: 0 | AH4: 0 | AI4: 0 | AJ4: 0 | AK4: 0 | AL4: 0 | AM4: 0 | AN4: 0 | AO4: 0 | AP4: 0 | AQ4: 0 | AR4: 0 | AS4: 0 | AT4: 0 | AU4: 0 | AV4: 0 | AW4: 0 | AX4: 0 | AY4: 0 | AZ4: 0
A5: diesel vehicle | B5: 0 | C5: 0 | D5: 0 | E5: 0 | F5: 0 | G5: 0 | H5: 0 | I5: 0 | J5: 0 | K5: 0 | L5: 0 | M5: 0 | N5: 0 | O5: 0 | P5: 0 | Q5: 0 | R5: 0 | S5: 0 | T5: 0 | U5: 0 | V5: 0 | W5: 0 | X5: 0 | Y5: 0 | Z5: 0 | AA5: 0 | AB5: 0 | AC5: 0 | AD5: 0 | AE5: 0 | AF5: 0 | AG5: 0 | AH5: 0 | AI5: 0 | AJ5: 0 | AK5: 0 | AL5: 0 | AM5: 0 | AN5: 0 | AO5: 0 | AP5: 0 | AQ5: 0 | AR5: 0 | AS5: 0 | AT5: 0 | AU5: 0 | AV5: 0 | AW5: 0 | AX5: 0 | AY5: 0 | AZ5: 0
A6: plugin hybrid vehicle | B6: 0 | C6: 0 | D6: 0 | E6: 0 | F6: 0 | G6: 0 | H6: 0 | I6: 0 | J6: 0 | K6: 0 | L6: 0 | M6: 0 | N6: 0 | O6: 0 | P6: 0 | Q6: 0 | R6: 0 | S6: 0 | T6: 0 | U6: 0 | V6: 0 | W6: 0 | X6: 0 | Y6: 0 | Z6: 0 | AA6: 0 | AB6: 0 | AC6: 0 | AD6: 0 | AE6: 0 | AF6: 0 | AG6: 0 | AH6: 0 | AI6: 0 | AJ6: 0 | AK6: 0 | AL6: 0 | AM6: 0 | AN6: 0 | AO6: 0 | AP6: 0 | AQ6: 0 | AR6: 0 | AS6: 0 | AT6: 0 | AU6: 0 | AV6: 0 | AW6: 0 | AX6: 0 | AY6: 0 | AZ6: 0
A7: LPG vehicle | B7: 0 | C7: 0 | D7: 0 | E7: 0 | F7: 0 | G7: 0 | H7: 0 | I7: 0 | J7: 0 | K7: 0 | L7: 0 | M7: 0 | N7: 0 | O7: 0 | P7: 0 | Q7: 0 | R7: 0 | S7: 0 | T7: 0 | U7: 0 | V7: 0 | W7: 0 | X7: 0 | Y7: 0 | Z7: 0 | AA7: 0 | AB7: 0 | AC7: 0 | AD7: 0 | AE7: 0 | AF7: 0 | AG7: 0 | AH7: 0 | AI7: 0 | AJ7: 0 | AK7: 0 | AL7: 0 | AM7: 0 | AN7: 0 | AO7: 0 | AP7: 0 | AQ7: 0 | AR7: 0 | AS7: 0 | AT7: 0 | AU7: 0 | AV7: 0 | AW7: 0 | AX7: 0 | AY7: 0 | AZ7: 0
A8: hydrogen vehicle | B8: 0 | C8: 0 | D8: 0 | E8: 0 | F8: 0 | G8: 0 | H8: 0 | I8: 0 | J8: 0 | K8: 0 | L8: 0 | M8: 0 | N8: 0 | O8: 0 | P8: 0 | Q8: 0 | R8: 0 | S8: 0 | T8: 0 | U8: 0 | V8: 0 | W8: 0 | X8: 0 | Y8: 0 | Z8: 0 | AA8: 0 | AB8: 0 | AC8: 0 | AD8: 0 | AE8: 0 | AF8: 0 | AG8: 0 | AH8: 0 | AI8: 0 | AJ8: 0 | AK8: 0 | AL8: 0 | AM8: 0 | AN8: 0 | AO8: 0 | AP8: 0 | AQ8: 0 | AR8: 0 | AS8: 0 | AT8: 0 | AU8: 0 | AV8: 0 | AW8: 0 | AX8: 0 | AY8: 0 | AZ8: 0
