Workbook

Sheet About
A1: DCSoCbIC Domestic Content Share of Consumption by ISIC Code
A3: Source: | B3: OECD
B4: 2018
B5: Input-Output Tables 2018 Edition (ISIC Rev. 4)
B6: https://stats.oecd.org/Index.aspx?DataSetCode=IOTSI4_2018
B7: Variables: TTL, ICESHR, CONS_ABR, CONS_NONRES, EXPO, IMPO
B9: ISIC Splits
B10: Exiobase
B11: 2019
B12: Exiobase 3rx, 2016
B13: https://zenodo.org/record/2654460#.YEFjHmhKg2w
B14: Output; imports and exports
B16: World Input Output Database
B17: 2014
B18: Indonesia
B19: http://www.wiod.org/release16
B20: 2014 (multiple data points used to calculate split for output, imports, and exports)
A22: Notes
A23: This variable is used to determine the share of a policy-driven increase in the domestic need
A24: for a type of economic output that is satisfied by increased domestic production rather
A25: than by increased imports.
A27: This variable contains the share of the domestic consumption of goods/services
A28: within each ISIC code that was produced domestically rather than imported.
A29: The calculations appear on the "Calculations" tab and are straightforward to follow
A30: by looking at the formulas in Excel.
A32: Note on ISIC 84 in variable ICESHR
A33: Many non-European countries in the OECD database, in variable ICESHR, omit a value for
A34: ISIC code 84 (Public administration and defence; compulsory social security).
A35: Though this value may be low, it is unlikely to be zero, due to imported content in
... A47: We use EXIOBASE data to apportion ISIC splits for most sectors, and WIOD for apportioning chem/ pharma

Sheet IDN WIOD IO-tables
E1: A01 | F1: A02 | G1: A03 | H1: B | I1: C10-C12 | J1: C13-C15 | K1: C16 | L1: C17 | M1: C18 | N1: C19 | O1: C20 | P1: C21 | Q1: C22 | R1: C23 | S1: C24 | T1: C25 | U1: C26 | V1: C27 | W1: C28 | X1: C29 | Y1: C30 | Z1: C31_C32 | AA1: C33 | AB1: D35 | AC1: E36 | AD1: E37-E39 | AE1: F | AF1: G45 | AG1: G46 | AH1: G47 | AI1: H49 | AJ1: H50 | AK1: H51 | AL1: H52 | AM1: H53 | AN1: I | AO1: J58 | AP1: J59_J60 | AQ1: J61 | AR1: J62_J63 | AS1: K64 | AT1: K65 | AU1: K66 | AV1: L68 | AW1: M69_M70 | AX1: M71 | AY1: M72 | AZ1: M73 | BA1: M74_M75 | BB1: N | BC1: O84 | BD1: P85 | BE1: Q | BF1: R_S | BG1: T | BH1: U | BI1: CONS_h | BJ1: CONS_np | BK1: CONS_g | BL1: GFCF | BM1: INVEN | BN1: EXP | BO1: GO
A2: Year | B2: Code | C2: Description | D2: Origin | E2: Crop and animal production, hunting and related service activities | F2: Forestry and logging | G2: Fishing and aquaculture | H2: Mining and quarrying | I2: Manufacture of food products, beverages and tobacco products | J2: Manufacture of textiles, wearing apparel and leather products | K2: Manufacture of wood and of products of wood and cork, except furniture; manufacture of articles of straw and plaiting materials | L2: Manufacture of paper and paper products | M2: Printing and reproduction of recorded media | N2: Manufacture of coke and refined petroleum products | O2: Manufacture of chemicals and chemical products | P2: Manufacture of basic pharmaceutical products and pharmaceutical preparations | Q2: Manufacture of rubber and plastic products | R2: Manufacture of other non-metallic mineral products | S2: Manufacture of basic metals | T2: Manufacture of fabricated metal products, except machinery and equipment | U2: Manufacture of computer, electronic and optical products | V2: Manufacture of electrical equipment | W2: Manufacture of machinery and equipment n.e.c. | X2: Manufacture of motor vehicles, trailers and semi-trailers | Y2: Manufacture of other transport equipment | Z2: Manufacture of furniture; other manufacturing | AA2: Repair and installation of machinery and equipment | AB2: Electricity, gas, steam and air conditioning supply | AC2: Water collection, treatment and supply | AD2: Sewerage; waste collection, treatment and disposal activities; materials recovery; remediation activities and other waste management services | AE2: Construction | AF2: Wholesale and retail trade and repair of motor vehicles and motorcycles | AG2: Wholesale trade, except of motor vehicles and motorcycles | AH2: Retail trade, except of motor vehicles and motorcycles | AI2: Land transport and transport via pipelines | AJ2: Water transport | AK2: Air transport | AL2: Warehousing and support activities for transportation | AM2: Postal and courier activities | AN2: Accommodation and food service activities | AO2: Publishing activities | AP2: Motion picture, video and television programme production, sound recording and music publishing activities; programming and broadcasting activities | AQ2: Telecommunications | AR2: Computer programming, consultancy and related activities; information service activities | AS2: Financial service activities, except insurance and pension funding | AT2: Insurance, reinsurance and pension funding, except compulsory social security | AU2: Activities auxiliary to financial services and insurance activities | AV2: Real estate activities | AW2: Legal and accounting activities; activities of head offices; management consultancy activities | AX2: Architectural and engineering activities; technical testing and analysis | AY2: Scientific research and development | AZ2: Advertising and market research | BA2: Other professional, scientific and technical activities; veterinary activities | BB2: Administrative and support service activities | BC2: Public administration and defence; compulsory social security | BD2: Education | BE2: Human health and social work activities | BF2: Other service activities | BG2: Activities of households as employers; undifferentiated goods- and services-producing activities of households for own use | BH2: Activities of extraterritorial organizations and bodies | BI2: Final consumption expenditure by households | BJ2: Final consumption expenditure by non-profit organisations serving households (NPISH) | BK2: Final consumption expenditure by government | BL2: Gross fixed capital formation | BM2: Changes in inventories and valuables | BN2: Exports | BO2: Total output
A3: 2000 | B3: A01 | C3: Crop and animal production, hunting and related service activities | D3: Domestic | E3: 1738.7029 | F3: 61.244225 | G3: 78.518394 | H3: 0 | I3: 10304.642 | J3: 889.15223 | K3: 43.297026 | L3: 30.781562 | M3: 0 | N3: 0.0044589355 | O3: 125.23082 | P3: 222.0081 | Q3: 676.01661 | R3: 2.3702082 | S3: 0 | T3: 0.0019256738 | U3: 0.0036510959 | V3: 0.0023068121 | W3: 0.00094889801 | X3: 0.00030199422 | Y3: 0.00020177082 | Z3: 114.60549 | AA3: 0 | AB3: 0 | AC3: 0 | AD3: 0 | AE3: 0 | AF3: 0 | AG3: 2.3320834 | AH3: 1.3539323 | AI3: 0.23653121 | AJ3: 45.488493 | AK3: 0 | AL3: 0 | AM3: 0 | AN3: 1735.0651 | AO3: 0 | AP3: 6.2348461 | AQ3: 0 | AR3: 0 | AS3: 0 | AT3: 0.0020927905 | AU3: 0 | AV3: 0.0063189692 | AW3: 0.52707426 | AX3: 0 | AY3: 0 | AZ3: 0 | BA3: 0 | BB3: 0.60051694 | BC3: 1.0537544 | BD3: 19.90195 | BE3: 346.30088 | BF3: 37.228427 | BG3: 0 | BH3: 0 | BI3: 9325.9433 | BJ3: 0 | BK3: 0 | BL3: 64.967091 | BM3: 347.42898 | BN3: 750.67668 | BO3: 26971.931
A4: 2000 | B4: A02 | C4: Forestry and logging | D4: Domestic | E4: 6.9652888 | F4: 41.638054 | G4: 2.2844019 | H4: 3.8958541 | I4: 1.1383613 | J4: 1.9518573 | K4: 1286.3959 | L4: 95.164413 | M4: 0.0038803349 | N4: 0 | O4: 8.6816439 | P4: 3.1441068 | Q4: 0.0082070271 | R4: 1.3940018 | S4: 0 | T4: 1.5572331 | U4: 3.0416103 | V4: 0.0011101339 | W4: 1.478425 | X4: 0 | Y4: 0.13353632 | Z4: 285.79886 | AA4: 0 | AB4: 0.0012628413 | AC4: 0 | AD4: 0 | AE4: 575.41359 | AF4: 0 | AG4: 0.29944314 | AH4: 0.17384701 | AI4: 0.25349626 | AJ4: 0 | AK4: 0 | AL4: 0 | AM4: 0 | AN4: 4.10538 | AO4: 0 | AP4: 0 | AQ4: 0 | AR4: 0 | AS4: 0 | AT4: 0 | AU4: 0 | AV4: 0 | AW4: 0.014616918 | AX4: 0 | AY4: 0 | AZ4: 0 | BA4: 0 | BB4: 0.016653643 | BC4: 0 | BD4: 0.64073402 | BE4: 0.10693979 | BF4: 7.9676286 | BG4: 0 | BH4: 0 | BI4: 219.59417 | BJ4: 0 | BK4: 0 | BL4: 0 | BM4: 319.57857 | BN4: 78.565025 | BO4: 2951.4081
A5: 2000 | B5: A03 | C5: Fishing and aquaculture | D5: Domestic | E5: 0.15362334 | F5: 0 | G5: 85.311336 | H5: 0 | I5: 872.79681 | J5: 0.36623353 | K5: 0.26842429 | L5: 0 | M5: 0 | N5: 0 | O5: 0.15505851 | P5: 0.17906137 | Q5: 0 | R5: 0 | S5: 0 | T5: 0 | U5: 0 | V5: 0 | W5: 0 | X5: 0 | Y5: 0 | Z5: 15.367126 | AA5: 0 | AB5: 0 | AC5: 0 | AD5: 0 | AE5: 0 | AF5: 0 | AG5: 0 | AH5: 0 | AI5: 0 | AJ5: 6.0370825 | AK5: 0 | AL5: 0 | AM5: 0 | AN5: 217.82579 | AO5: 0 | AP5: 0 | AQ5: 0 | AR5: 0 | AS5: 0 | AT5: 0 | AU5: 0 | AV5: 0 | AW5: 1.2261853 | AX5: 0 | AY5: 0 | AZ5: 0 | BA5: 0 | BB5: 1.3970423 | BC5: 0 | BD5: 0 | BE5: 22.576574 | BF5: 0.00072080141 | BG5: 0 | BH5: 0 | BI5: 1870.9138 | BJ5: 0 | BK5: 0 | BL5: 0 | BM5: 0 | BN5: 334.17957 | BO5: 3428.7544
A6: 2000 | B6: B | C6: Mining and quarrying | D6: Domestic | E6: 0.034538773 | F6: 0 | G6: 0 | H6: 1429.0975 | I6: 10.173221 | J6: 7.2708437 | K6: 3.8548534 | L6: 5.4455964 | M6: 0.00069333339 | N6: 5092.0103 | O6: 1640.9981 | P6: 81.607625 | Q6: 121.66628 | R6: 433.3476 | S6: 1345.9153 | T6: 38.935261 | U6: 0.79690396 | V6: 1.3649958 | W6: 5.3489089 | X6: 0.2364466 | Y6: 0.0022970537 | Z6: 0.91592052 | AA6: 0 | AB6: 1709.0978 | AC6: 0 | AD6: 0 | AE6: 897.16787 | AF6: 0 | AG6: 0.096081157 | AH6: 0.055781616 | AI6: 0.93623241 | AJ6: 0 | AK6: 0 | AL6: 0 | AM6: 0 | AN6: 0.0038069851 | AO6: 0 | AP6: 0 | AQ6: 0 | AR6: 0 | AS6: 0 | AT6: 0 | AU6: 0 | AV6: 0 | AW6: 0.00015394261 | AX6: 0 | AY6: 0 | AZ6: 0 | BA6: 0 | BB6: 0.00017539302 | BC6: 0 | BD6: 30.182922 | BE6: 2.6884533e-05 | BF6: 0 | BG6: 0 | BH6: 0 | BI6: 0.20020276 | BJ6: 0 | BK6: 0 | BL6: 0 | BM6: 850.81483 | BN6: 9792.9465 | BO6: 23500.526
A7: 2000 | B7: C10-C12 | C7: Manufacture of food products, beverages and tobacco products | D7: Domestic | E7: 1641.9543 | F7: 0 | G7: 146.5262 | H7: 0 | I7: 5101.2179 | J7: 179.14639 | K7: 11.077005 | L7: 14.65651 | M7: 0.099857249 | N7: 0 | O7: 38.655515 | P7: 178.77843 | Q7: 0.81588573 | R7: 0.55484337 | S7: 0 | T7: 0.30959965 | U7: 9.7065411 | V7: 0.16505231 | W7: 0.070650432 | X7: 8.2883291e-05 | Y7: 0.00016612997 | Z7: 9.7339571 | AA7: 0 | AB7: 0 | AC7: 0 | AD7: 0 | AE7: 0 | AF7: 0.002314091 | AG7: 7.6574975 | AH7: 4.4456957 | AI7: 3.5092211 | AJ7: 498.48118 | AK7: 21.636882 | AL7: 7.623409 | AM7: 0.011060587 | AN7: 3064.1603 | AO7: 0.072935984 | AP7: 0 | AQ7: 1.1796349 | AR7: 0.061974089 | AS7: 1.6779431 | AT7: 0.021472719 | AU7: 0 | AV7: 14.951936 | AW7: 1.4495009 | AX7: 0 | AY7: 0 | AZ7: 0 | BA7: 0 | BB7: 1.6514748 | BC7: 0 | BD7: 0 | BE7: 252.50583 | BF7: 66.609952 | BG7: 0 | BH7: 0 | BI7: 20033.685 | BJ7: 0 | BK7: 0 | BL7: 0 | BM7: 60.018301 | BN7: 4843.9523 | BO7: 36218.834
A8: 2000 | B8: C13-C15 | C8: Manufacture of textiles, wearing apparel and leather products | D8: Domestic | E8: 2.3735822 | F8: 0.3748167 | G8: 0.63271553 | H8: 2.4217204 | I8: 3.9041407 | J8: 1720.8032 | K8: 2.9594644 | L8: 1.8056222 | M8: 0.039716843 | N8: 0.0025914557 | O8: 3.8434366 | P8: 0.35769008 | Q8: 52.236484 | R8: 0.18703711 | S8: 0.043931216 | T8: 7.5591156 | U8: 7.1933865 | V8: 0.50142918 | W8: 0.52899394 | X8: 1.9855395 | Y8: 0.19540728 | Z8: 19.117718 | AA8: 0 | AB8: 0.27303095 | AC8: 0.029730165 | AD8: 0 | AE8: 9.9196058 | AF8: 33.652107 | AG8: 38.19054 | AH8: 22.172194 | AI8: 4.3602636 | AJ8: 2.5745555 | AK8: 0.72806874 | AL8: 2.8387935 | AM8: 0.01071598 | AN8: 3.3708061 | AO8: 0.070663568 | AP8: 0.31415738 | AQ8: 1.1428818 | AR8: 0.060043204 | AS8: 0.19040761 | AT8: 0.031832013 | AU8: 0 | AV8: 1.8358201 | AW8: 1.8063186 | AX8: 0 | AY8: 0 | AZ8: 0 | BA8: 0 | BB8: 2.0580116 | BC8: 7.8277212 | BD8: 14.52483 | BE8: 1.6148798 | BF8: 44.436667 | BG8: 0 | BH8: 0 | BI8: 1955.5645 | BJ8: 0 | BK8: 0 | BL8: 15.385165 | BM8: 196.94223 | BN8: 10490.505 | BO8: 14681.5
A9: 2000 | B9: C16 | C9: Manufacture of wood and of products of wood and cork, except furniture; manufacture of articles of straw and plaiting materials | D9: Domestic | E9: 1.8443428 | F9: 0 | G9: 0.51665303 | H9: 0.42990628 | I9: 1.482036 | J9: 0.67129321 | K9: 108.30734 | L9: 1.5102648 | M9: 0.003459379 | N9: 0 | O9: 0.4801606 | P9: 0.50768648 | Q9: 0.291364 | R9: 0.84591058 | S9: 0 | T9: 11.348052 | U9: 3.1018898 | V9: 0.1340853 | W9: 0.90638638 | X9: 0.54293564 | Y9: 2.9755676 | Z9: 197.60402 | AA9: 0 | AB9: 0 | AC9: 0 | AD9: 0 | AE9: 225.84168 | AF9: 2.4703235 | AG9: 10.70974 | AH9: 6.217729 | AI9: 0.119033 | AJ9: 0 | AK9: 0.037182861 | AL9: 0.3550284 | AM9: 0.00014172641 | AN9: 0.28007726 | AO9: 0.00093457563 | AP9: 0.0093813148 | AQ9: 0.01511542 | AR9: 0.00079411382 | AS9: 0 | AT9: 0 | AU9: 0 | AV9: 0.10378738 | AW9: 0.0036347181 | AX9: 0 | AY9: 0 | AZ9: 0 | BA9: 0 | BB9: 0.0041411808 | BC9: 0.38721869 | BD9: 1.5159766 | BE9: 0.00157733 | BF9: 0.059535315 | BG9: 0 | BH9: 0 | BI9: 50.667638 | BJ9: 0 | BK9: 0 | BL9: 0 | BM9: 74.37573 | BN9: 3998.6624 | BO9: 4705.3421
A10: 2000 | B10: C17 | C10: Manufacture of paper and paper products | D10: Domestic | E10: 4.6800606 | F10: 2.7511465 | G10: 0.4278826 | H10: 3.585794 | I10: 212.40728 | J10: 42.648637 | K10: 2.2917467 | L10: 2396.0396 | M10: 47.466564 | N10: 0.0034786917 | O10: 17.962231 | P10: 37.405569 | Q10: 24.863346 | R10: 30.704853 | S10: 0.88754397 | T10: 5.4570903 | U10: 77.360839 | V10: 15.828966 | W10: 1.4134329 | X10: 1.7785775 | Y10: 0.10082361 | Z10: 5.9413743 | AA10: 0 | AB10: 1.1137129 | AC10: 0.32027997 | AD10: 0 | AE10: 17.112382 | AF10: 6.7885419 | AG10: 264.52836 | AH10: 153.57662 | AI10: 1.6326567 | AJ10: 3.3980118 | AK10: 0.4179799 | AL10: 0.86509157 | AM10: 0.021960904 | AN10: 2.8375586 | AO10: 0.1448151 | AP10: 0.37520879 | AQ10: 2.3421766 | AR10: 0.12305015 | AS10: 42.904518 | AT10: 1.2462014 | AU10: 0 | AV10: 11.743651 | AW10: 13.289355 | AX10: 0 | AY10: 0 | AZ10: 0 | BA10: 0 | BB10: 15.141097 | BC10: 64.529635 | BD10: 358.63632 | BE10: 0.53966091 | BF10: 4.936586 | BG10: 0 | BH10: 0 | BI10: 477.3965 | BJ10: 0 | BK10: 0 | BL10: 0 | BM10: 213.76532 | BN10: 2889.4323 | BO10: 7481.1664
A11: 2000 | B11: C18 | C11: Printing and reproduction of recorded media | D11: Domestic | E11: 0.059109842 | F11: 0.19000092 | G11: 0.010247852 | H11: 0.12198718 | I11: 1.6474901 | J11: 0.27087183 | K11: 0.033515269 | L11: 0.046129414 | M11: 0.048451767 | N11: 0.00020476914 | O11: 0.90824416 | P11: 0.09019796 | Q11: 0.16098221 | R11: 0.38514624 | S11: 0.041564515 | T11: 0.088688814 | U11: 0.93313379 | V11: 0.023411961 | W11: 0.0069929986 | X11: 0.0026966679 | Y11: 0.00080305217 | Z11: 0.064875956 | AA11: 0 | AB11: 0.52340203 | AC11: 0.051883088 | AD11: 0 | AE11: 1.962387 | AF11: 0.54023919 | AG11: 19.998014 | AH11: 11.610201 | AI11: 0.69526685 | AJ11: 0.34496069 | AK11: 2.7059345 | AL11: 0.14320103 | AM11: 0.016096551 | AN11: 1.0129672 | AO11: 0.10614425 | AP11: 0.029656226 | AQ11: 1.716731 | AR11: 0.090191329 | AS11: 6.8748686 | AT11: 0.2251389 | AU11: 0 | AV11: 0.55228879 | AW11: 0.84242718 | AX11: 0 | AY11: 0 | AZ11: 0 | BA11: 0 | BB11: 0.95981122 | BC11: 7.9593961 | BD11: 91.749714 | BE11: 0.060980917 | BF11: 0.69284536 | BG11: 0 | BH11: 0 | BI11: 49.733814 | BJ11: 0 | BK11: 0 | BL11: 0 | BM11: 1.4129355 | BN11: 2.4721007 | BO11: 210.21835
A12: 2000 | B12: C19 | C12: Manufacture of coke and refined petroleum products | D12: Domestic | E12: 29.621007 | F12: 26.274239 | G12: 63.156356 | H12: 93.594764 | I12: 62.131547 | J12: 156.85054 | K12: 67.564955 | L12: 114.54932 | M12: 2.2801431 | N12: 200.55297 | O12: 75.260962 | P12: 8.0499874 | Q12: 71.542246 | R12: 99.466062 | S12: 137.70203 | T12: 90.571693 | U12: 18.234906 | V12: 17.651031 | W12: 1.7477903 | X12: 13.978886 | Y12: 3.3763205 | Z12: 10.632244 | AA12: 0 | AB12: 287.82391 | AC12: 0.42519713 | AD12: 0 | AE12: 926.88221 | AF12: 7.0689723 | AG12: 174.06958 | AH12: 101.05917 | AI12: 269.91934 | AJ12: 412.74784 | AK12: 255.57785 | AL12: 54.609388 | AM12: 0.081297139 | AN12: 15.607057 | AO12: 0.5360915 | AP12: 1.0377187 | AQ12: 8.670511 | AR12: 0.45551976 | AS12: 7.4208705 | AT12: 6.0239001 | AU12: 0 | AV12: 9.3290415 | AW12: 13.081006 | AX12: 0 | AY12: 0 | AZ12: 0 | BA12: 0 | BB12: 14.903718 | BC12: 90.056379 | BD12: 44.666989 | BE12: 2.4080552 | BF12: 2.5693327 | BG12: 0 | BH12: 0 | BI12: 730.39927 | BJ12: 0 | BK12: 0 | BL12: 0 | BM12: 1068.0526 | BN12: 8555.0653 | BO12: 14425.338
A13: 2000 | B13: C20 | C13: Manufacture of chemicals and chemical products | D13: Domestic | E13: 189.02473 | F13: 0.60885651 | G13: 0.26616903 | H13: 34.581257 | I13: 49.637839 | J13: 386.84243 | K13: 49.388639 | L13: 73.735033 | M13: 2.5131399 | N13: 0.80417436 | O13: 434.42143 | P13: 178.19095 | Q13: 456.06707 | R13: 58.289925 | S13: 94.937093 | T13: 118.21472 | U13: 63.947442 | V13: 158.58825 | W13: 2.1649825 | X13: 8.9595537 | Y13: 1.2366596 | Z13: 30.745881 | AA13: 0 | AB13: 0.91180195 | AC13: 2.3259933 | AD13: 0 | AE13: 51.694446 | AF13: 20.471512 | AG13: 7.9121364 | AH13: 4.5935308 | AI13: 2.9513031 | AJ13: 2.2501676 | AK13: 0.43594603 | AL13: 0.78327798 | AM13: 0.0023629618 | AN13: 1.8704049 | AO13: 0.015581898 | AP13: 5.7651386 | AQ13: 0.25201485 | AR13: 0.013240021 | AS13: 0.1217167 | AT13: 0.050917352 | AU13: 0 | AV13: 0.47291718 | AW13: 5.5133474 | AX13: 0 | AY13: 0 | AZ13: 0 | BA13: 0 | BB13: 6.2815788 | BC13: 16.812735 | BD13: 74.94823 | BE13: 72.068636 | BF13: 8.5059566 | BG13: 0 | BH13: 0 | BI13: 747.16977 | BJ13: 0 | BK13: 0 | BL13: 0 | BM13: 872.10642 | BN13: 3014.281 | BO13: 7313.7483
A14: 2000 | B14: C21 | C14: Manufacture of basic pharmaceutical products and pharmaceutical preparations | D14: Domestic | E14: 0.61721443 | F14: 0 | G14: 0.021170724 | H14: 0.033606639 | I14: 3.5633548 | J14: 6.6985862 | K14: 3.0913991 | L14: 10.028821 | M14: 0.24174704 | N14: 0.0026544465 | O14: 1.2417317 | P14: 68.55918 | Q14: 8.3155867 | R14: 0.24956264 | S14: 1.0901666 | T14: 1.1776105 | U14: 32.225659 | V14: 3.4562557 | W14: 0.18701826 | X14: 0.68024263 | Y14: 0.06861631 | Z14: 0.42150235 | AA14: 0 | AB14: 0 | AC14: 0 | AD14: 0 | AE14: 0 | AF14: 39.667534 | AG14: 39.591618 | AH14: 22.985614 | AI14: 7.435698 | AJ14: 9.7537282 | AK14: 0.57163461 | AL14: 2.8442957 | AM14: 0.0052767136 | AN14: 11.4268 | AO14: 0.034795829 | AP14: 0.61602155 | AQ14: 0.56277261 | AR14: 0.029566198 | AS14: 1.7423611 | AT14: 0.67707589 | AU14: 0 | AV14: 0.59038453 | AW14: 4.4318441 | AX14: 0 | AY14: 0 | AZ14: 0 | BA14: 0 | BB14: 5.0493784 | BC14: 2.0686823 | BD14: 12.254221 | BE14: 7.4841388 | BF14: 125.75452 | BG14: 0 | BH14: 0 | BI14: 2078.3344 | BJ14: 0 | BK14: 0 | BL14: 0 | BM14: 42.274444 | BN14: 252.96317 | BO14: 2811.1216
... A1802: 2014 | B1802: GO | C1802: Output at basic prices | D1802: TOT | E1802: 112492.71 | F1802: 7330.9997 | G1802: 24366.378 | H1802: 119982.65 | I1802: 170838.28 | J1802: 34627.013 | K1802: 15184.876 | L1802: 20002.664 | M1802: 1038.359 | N1802: 59961.825 | O1802: 32288.822 | P1802: 12294.534 | Q1802: 25626.629 | R1802: 18459.576 | S1802: 21745.768 | T1802: 19224.344 | U1802: 21787.842 | V1802: 13990.962 | W1802: 11444.956 | X1802: 33550.657 | Y1802: 2511.627 | Z1802: 10131.811 | AA1802: 0 | AB1802: 41270.371 | AC1802: 805.31332 | AD1802: 0 | AE1802: 255324.62 | AF1802: 36385.303 | AG1802: 88576.867 | AH1802: 51998.845 | AI1802: 39778.667 | AJ1802: 12790.448 | AK1802: 27767.809 | AL1802: 11435.343 | AM1802: 1575.5336 | AN1802: 59848.058 | AO1802: 5567.6029 | AP1802: 5319.8231 | AQ1802: 33331.099 | AR1802: 4428.1372 | AS1802: 37824.207 | AT1802: 9768.3113 | AU1802: 0 | AV1802: 30046.42 | AW1802: 11796.58 | AX1802: 0 | AY1802: 0 | AZ1802: 0 | BA1802: 0 | BB1802: 11919.857 | BC1802: 55001.986 | BD1802: 44541.26 | BE1802: 20753.37 | BF1802: 27603.946 | BG1802: 0 | BH1802: 0 | BI1802: 0 | BJ1802: 0 | BK1802: 0 | BL1802: 0 | BM1802: 0 | BN1802: 0 | BO1802: 0
O1803: =SUM(O1795:O1801) -> 32288.821 | P1803: =SUM(P1795:P1801) -> 12294.534
M1806: Values | N1806: Domestic | O1806: =SUMIFS(O:O, A:A, 2014, D:D, "Domestic") -> 14724.45 | P1806: =SUMIFS(P:P, A:A, 2014, D:D, "Domestic") -> 6471.7435
N1807: Imports | O1807: =SUMIFS(O:O, A:A, 2014, D:D, "Imports") -> 6038.9505 | P1807: =SUMIFS(P:P, A:A, 2014, D:D, "Imports") -> 1530.8002
N1808: Exports | O1808: =SUMIFS(BN:BN, A:A, 2014, B:B, "C20", D:D, "Domestic") -> 11971.035 | P1808: =SUMIFS(BN:BN, A:A, 2014, B:B, "C21", D:D, "Domestic") -> 1818.6057
M1810: Splits | N1810: Domestic | O1810: =O1806/SUM($O1806:$P1806) -> 0.69467425 | P1810: =P1806/SUM($O1806:$P1806) -> 0.30532575
N1811: Imports | O1811: =O1807/SUM($O1807:$P1807) -> 0.79777402 | P1811: =P1807/SUM($O1807:$P1807) -> 0.20222598
N1812: Exports | O1812: =O1808/SUM($O1808:$P1808) -> 0.86811797 | P1812: =P1808/SUM($O1808:$P1808) -> 0.13188203

Sheet EXIOBASE Output
B2: Source: EXIOBASE CountryXSector v2
B3: M.EUR
B4: IDN
B6: ISIC code | C6: Output
B7: 0 | C7: 0
B8: ISIC 01T03 | C8: 121959.75
B9: ISIC 05 | C9: 11483.575
B10: ISIC 06 | C10: 17357.035
B11: ISIC 07T08 | C11: 42493.004
B12: ISIC 10T12 | C12: 122293.28
B13: ISIC 13T15 | C13: 40953.523
B14: ISIC 16 | C14: 19770.902
B15: ISIC 17T18 | C15: 18038.204
B16: ISIC 19 | C16: 19322.691
B17: ISIC 20 | C17: 31282.074
B18: ISIC 22 | C18: 22680.663
B19: ISIC 231 | C19: 2690.1995
... B47: Grand Total | C47: 1249621.6

Sheet EXIOBASE Imports Exports
A1: Source: EXIOBASE Trade data
A2: Units: Million Euros
A3: IDN
A5: Sector | B5: Sector ID | C5: Imports | D5: Exports | E5: ISIC Code
A6: Paddy rice | B6: 1 | C6: 4.9135386 | D6: 0.060647461 | E6: =VLOOKUP(A6,'ISIC Code Mapping'!$A$2:$C$201, 3, FALSE) -> ISIC 01T03
A7: Wheat | B7: 2 | C7: 1831.9716 | D7: 0 | E7: =VLOOKUP(A7,'ISIC Code Mapping'!$A$2:$C$201, 3, FALSE) -> ISIC 01T03
A8: Cereal grains nec | B8: 3 | C8: 805.72429 | D8: 16.028876 | E8: =VLOOKUP(A8,'ISIC Code Mapping'!$A$2:$C$201, 3, FALSE) -> ISIC 01T03
A9: Vegetables, fruit, nuts | B9: 4 | C9: 2113.1957 | D9: 907.36106 | E9: =VLOOKUP(A9,'ISIC Code Mapping'!$A$2:$C$201, 3, FALSE) -> ISIC 01T03
A10: Oil seeds | B10: 5 | C10: 1418.0252 | D10: 93.09923 | E10: =VLOOKUP(A10,'ISIC Code Mapping'!$A$2:$C$201, 3, FALSE) -> ISIC 01T03
A11: Sugar cane, sugar beet | B11: 6 | C11: 0.0053496484 | D11: 0.14131539 | E11: =VLOOKUP(A11,'ISIC Code Mapping'!$A$2:$C$201, 3, FALSE) -> ISIC 01T03
A12: Plant-based fibers | B12: 7 | C12: 1204.0144 | D12: 2.2037404 | E12: =VLOOKUP(A12,'ISIC Code Mapping'!$A$2:$C$201, 3, FALSE) -> ISIC 01T03
A13: Crops nec | B13: 8 | C13: 944.41945 | D13: 7211.7766 | E13: =VLOOKUP(A13,'ISIC Code Mapping'!$A$2:$C$201, 3, FALSE) -> ISIC 01T03
A14: Cattle | B14: 9 | C14: 1306.7228 | D14: 0 | E14: =VLOOKUP(A14,'ISIC Code Mapping'!$A$2:$C$201, 3, FALSE) -> ISIC 01T03
A15: Pigs | B15: 10 | C15: 0.017497093 | D15: 70.90954 | E15: =VLOOKUP(A15,'ISIC Code Mapping'!$A$2:$C$201, 3, FALSE) -> ISIC 01T03
A16: Poultry | B16: 11 | C16: 28.809818 | D16: 0 | E16: =VLOOKUP(A16,'ISIC Code Mapping'!$A$2:$C$201, 3, FALSE) -> ISIC 01T03
A17: Meat animals nec | B17: 12 | C17: 3.529496 | D17: 7.228892 | E17: =VLOOKUP(A17,'ISIC Code Mapping'!$A$2:$C$201, 3, FALSE) -> ISIC 01T03
... A205: Extra-territorial organizations and bodies | B205: 200 | C205: 0 | D205: 0 | E205: =VLOOKUP(A205,'ISIC Code Mapping'!$A$2:$C$201, 3, FALSE) -> 0

Sheet EXIOBASE ISIC SPLITS
C2: Data (M.EUR) | H2: Splits
B3: ='EXIOBASE Output'!B6 -> ISIC code | C3: Output | D3: Imports | E3: Exports | F3: ICESHR | H3: Output | I3: Import | J3: Export
B4: ='EXIOBASE Output'!B9 -> ISIC 05 | C4: =IF(ISERROR(VLOOKUP(B4,'EXIOBASE Output'!$B$8:$C$46,2,FALSE)),"",VLOOKUP(B4,'EXIOBASE Output'!$B$8:$C$46,2,FALSE)) -> 11483.575 | D4: =SUMIFS('EXIOBASE Imports Exports'!C:C, 'EXIOBASE Imports Exports'!E:E, 'EXIOBASE ISIC SPLITS'!B4) -> 158.22152 | E4: =SUMIFS('EXIOBASE Imports Exports'!D:D, 'EXIOBASE Imports Exports'!E:E, 'EXIOBASE ISIC SPLITS'!B4) -> 7339.3975 | F4: =IF(ISERROR(VLOOKUP(B4,'OECD ICESHR'!$B$9:$E$43,4,FALSE)),"",VLOOKUP(B4,'OECD ICESHR'!$B$9:$E$43,4,FALSE)) | H4: =C4/SUM(C$4:C$5) -> 0.39817377 | I4: =D4/SUM(D$4:D$5) -> 0.034856795 | J4: =E4/SUM(E$4:E$5) -> 0.40480346
B5: ='EXIOBASE Output'!B10 -> ISIC 06 | C5: =IF(ISERROR(VLOOKUP(B5,'EXIOBASE Output'!$B$8:$C$46,2,FALSE)),"",VLOOKUP(B5,'EXIOBASE Output'!$B$8:$C$46,2,FALSE)) -> 17357.035 | D5: =SUMIFS('EXIOBASE Imports Exports'!C:C, 'EXIOBASE Imports Exports'!E:E, 'EXIOBASE ISIC SPLITS'!B5) -> 4380.9657 | E5: =SUMIFS('EXIOBASE Imports Exports'!D:D, 'EXIOBASE Imports Exports'!E:E, 'EXIOBASE ISIC SPLITS'!B5) -> 10791.37 | F5: =IF(ISERROR(VLOOKUP(B5,'OECD ICESHR'!$B$9:$E$43,4,FALSE)),"",VLOOKUP(B5,'OECD ICESHR'!$B$9:$E$43,4,FALSE)) | H5: =C5/SUM(C$4:C$5) -> 0.60182623 | I5: =D5/SUM(D$4:D$5) -> 0.96514321 | J5: =E5/SUM(E$4:E$5) -> 0.59519654
B6: ='EXIOBASE Output'!B19 -> ISIC 231 | C6: =IF(ISERROR(VLOOKUP(B6,'EXIOBASE Output'!$B$8:$C$46,2,FALSE)),"",VLOOKUP(B6,'EXIOBASE Output'!$B$8:$C$46,2,FALSE)) -> 2690.1995 | D6: =SUMIFS('EXIOBASE Imports Exports'!C:C, 'EXIOBASE Imports Exports'!E:E, 'EXIOBASE ISIC SPLITS'!B6) -> 452.17343 | E6: =SUMIFS('EXIOBASE Imports Exports'!D:D, 'EXIOBASE Imports Exports'!E:E, 'EXIOBASE ISIC SPLITS'!B6) -> 358.15921 | F6: =IF(ISERROR(VLOOKUP(B6,'OECD ICESHR'!$B$9:$E$43,4,FALSE)),"",VLOOKUP(B6,'OECD ICESHR'!$B$9:$E$43,4,FALSE)) | H6: =C6/SUM(C$6:C$7) -> 0.27109933 | I6: =D6/SUM(D$6:D$7) -> 0.27626225 | J6: =E6/SUM(E$6:E$7) -> 0.36087383
B7: ='EXIOBASE Output'!B20 -> ISIC 239 | C7: =IF(ISERROR(VLOOKUP(B7,'EXIOBASE Output'!$B$8:$C$46,2,FALSE)),"",VLOOKUP(B7,'EXIOBASE Output'!$B$8:$C$46,2,FALSE)) -> 7233.0989 | D7: =SUMIFS('EXIOBASE Imports Exports'!C:C, 'EXIOBASE Imports Exports'!E:E, 'EXIOBASE ISIC SPLITS'!B7) -> 1184.5809 | E7: =SUMIFS('EXIOBASE Imports Exports'!D:D, 'EXIOBASE Imports Exports'!E:E, 'EXIOBASE ISIC SPLITS'!B7) -> 634.31845 | F7: =IF(ISERROR(VLOOKUP(B7,'OECD ICESHR'!$B$9:$E$43,4,FALSE)),"",VLOOKUP(B7,'OECD ICESHR'!$B$9:$E$43,4,FALSE)) | H7: =C7/SUM(C$6:C$7) -> 0.72890067 | I7: =D7/SUM(D$6:D$7) -> 0.72373775 | J7: =E7/SUM(E$6:E$7) -> 0.63912617
B8: ='EXIOBASE Output'!B21 -> ISIC 241 | C8: =IF(ISERROR(VLOOKUP(B8,'EXIOBASE Output'!$B$8:$C$46,2,FALSE)),"",VLOOKUP(B8,'EXIOBASE Output'!$B$8:$C$46,2,FALSE)) -> 10856.266 | D8: =SUMIFS('EXIOBASE Imports Exports'!C:C, 'EXIOBASE Imports Exports'!E:E, 'EXIOBASE ISIC SPLITS'!B8) -> 9339.0799 | E8: =SUMIFS('EXIOBASE Imports Exports'!D:D, 'EXIOBASE Imports Exports'!E:E, 'EXIOBASE ISIC SPLITS'!B8) -> 1503.5145 | F8: =IF(ISERROR(VLOOKUP(B8,'OECD ICESHR'!$B$9:$E$43,4,FALSE)),"",VLOOKUP(B8,'OECD ICESHR'!$B$9:$E$43,4,FALSE)) | H8: =C8/SUM(C$8:C$9) -> 0.42628986 | I8: =D8/SUM(D$8:D$9) -> 0.77046615 | J8: =E8/SUM(E$8:E$9) -> 0.24047436
B9: ='EXIOBASE Output'!B22 -> ISIC 242 | C9: =IF(ISERROR(VLOOKUP(B9,'EXIOBASE Output'!$B$8:$C$46,2,FALSE)),"",VLOOKUP(B9,'EXIOBASE Output'!$B$8:$C$46,2,FALSE)) -> 14610.599 | D9: =SUMIFS('EXIOBASE Imports Exports'!C:C, 'EXIOBASE Imports Exports'!E:E, 'EXIOBASE ISIC SPLITS'!B9) -> 2782.2572 | E9: =SUMIFS('EXIOBASE Imports Exports'!D:D, 'EXIOBASE Imports Exports'!E:E, 'EXIOBASE ISIC SPLITS'!B9) -> 4748.7716 | F9: =IF(ISERROR(VLOOKUP(B9,'OECD ICESHR'!$B$9:$E$43,4,FALSE)),"",VLOOKUP(B9,'OECD ICESHR'!$B$9:$E$43,4,FALSE)) | H9: =C9/SUM(C$8:C$9) -> 0.57371014 | I9: =D9/SUM(D$8:D$9) -> 0.22953385 | J9: =E9/SUM(E$8:E$9) -> 0.75952564
B10: ='EXIOBASE Output'!B30 -> ISIC 351 | C10: =IF(ISERROR(VLOOKUP(B10,'EXIOBASE Output'!$B$8:$C$46,2,FALSE)),"",VLOOKUP(B10,'EXIOBASE Output'!$B$8:$C$46,2,FALSE)) -> 10312.653 | D10: =SUMIFS('EXIOBASE Imports Exports'!C:C, 'EXIOBASE Imports Exports'!E:E, 'EXIOBASE ISIC SPLITS'!B10) -> 0 | E10: =SUMIFS('EXIOBASE Imports Exports'!D:D, 'EXIOBASE Imports Exports'!E:E, 'EXIOBASE ISIC SPLITS'!B10) -> 0 | F10: =IF(ISERROR(VLOOKUP(B10,'OECD ICESHR'!$B$9:$E$43,4,FALSE)),"",VLOOKUP(B10,'OECD ICESHR'!$B$9:$E$43,4,FALSE)) | H10: =C10/SUM(C$10:C$12) -> 0.9716666 | I10: =D10/SUM(D$10:D$12) -> 0 | J10: =IFERROR(E10/SUM(E$10:E$12),0) -> 0
B11: ='EXIOBASE Output'!B31 -> ISIC 352T353 | C11: =IF(ISERROR(VLOOKUP(B11,'EXIOBASE Output'!$B$8:$C$46,2,FALSE)),"",VLOOKUP(B11,'EXIOBASE Output'!$B$8:$C$46,2,FALSE)) -> 300.71274 | D11: =SUMIFS('EXIOBASE Imports Exports'!C:C, 'EXIOBASE Imports Exports'!E:E, 'EXIOBASE ISIC SPLITS'!B11) -> 16.359913 | E11: =SUMIFS('EXIOBASE Imports Exports'!D:D, 'EXIOBASE Imports Exports'!E:E, 'EXIOBASE ISIC SPLITS'!B11) -> 0 | F11: =IF(ISERROR(VLOOKUP(B11,'OECD ICESHR'!$B$9:$E$43,4,FALSE)),"",VLOOKUP(B11,'OECD ICESHR'!$B$9:$E$43,4,FALSE)) | H11: =C11/SUM(C$10:C$12) -> 0.028333399 | I11: =D11/SUM(D$10:D$12) -> 1 | J11: =IFERROR(E11/SUM(E$10:E$12),0) -> 0
B12: ='EXIOBASE Output'!B32 -> ISIC 36T39 | H12: =C12/SUM(C$10:C$12) -> 0 | I12: =D12/SUM(D$10:D$12) -> 0 | J12: =IFERROR(E12/SUM(E$10:E$12),0) -> 0

Sheet OECD ICESHR
C1: =DotStatQuery(D1) -> #NAME? | D1: Sorry, the query is too large to fit into the Excel cell. You will not be able to update your table with the .Stat Populator.
C2: Dataset: Input-Output Tables 2018 edition
C3: Variable | E3: ICESHR: Imports content of exports, as % of exports
C4: Country | E4: IDN: Indonesia
C5: Time | E5: 2015
C6: Unit | E6: Percentage
B7: ISIC | C7: To: (sector in column) | E7: ICESHR: Imports content of exports shares
C8: From: (sector in row)
B9: ="ISIC "&MID(LEFT(C9,FIND(":",C9)-1),FIND("_",C9)+1,LEN(C9)) -> ISIC 01T03 | C9: TTL_01T03: Agriculture, forestry and fishing | E9: 5.55
B10: ="ISIC "&MID(LEFT(C10,FIND(":",C10)-1),FIND("_",C10)+1,LEN(C10)) -> ISIC 05T06 | C10: TTL_05T06: Mining and extraction of energy producing products | E10: 7.78
B11: ="ISIC "&MID(LEFT(C11,FIND(":",C11)-1),FIND("_",C11)+1,LEN(C11)) -> ISIC 07T08 | C11: TTL_07T08: Mining and quarrying of non-energy producing products | E11: 7.23
B12: ="ISIC "&MID(LEFT(C12,FIND(":",C12)-1),FIND("_",C12)+1,LEN(C12)) -> ISIC 09 | C12: TTL_09: Mining support service activities | E12: 9.59
B13: ="ISIC "&MID(LEFT(C13,FIND(":",C13)-1),FIND("_",C13)+1,LEN(C13)) -> ISIC 10T12 | C13: TTL_10T12: Food products, beverages and tobacco | E13: 8.06
B14: ="ISIC "&MID(LEFT(C14,FIND(":",C14)-1),FIND("_",C14)+1,LEN(C14)) -> ISIC 13T15 | C14: TTL_13T15: Textiles, wearing apparel, leather and related products | E14: 22.39
B15: ="ISIC "&MID(LEFT(C15,FIND(":",C15)-1),FIND("_",C15)+1,LEN(C15)) -> ISIC 16 | C15: TTL_16: Wood and of products of wood and cork (except furniture) | E15: 7.74
B16: ="ISIC "&MID(LEFT(C16,FIND(":",C16)-1),FIND("_",C16)+1,LEN(C16)) -> ISIC 17T18 | C16: TTL_17T18: Paper products and printing | E16: 17.69
B17: ="ISIC "&MID(LEFT(C17,FIND(":",C17)-1),FIND("_",C17)+1,LEN(C17)) -> ISIC 19 | C17: TTL_19: Coke and refined petroleum products | E17: 19.14
B18: ="ISIC "&MID(LEFT(C18,FIND(":",C18)-1),FIND("_",C18)+1,LEN(C18)) -> ISIC 20T21 | C18: TTL_20T21: Chemicals and pharmaceutical products | E18: 15.91
B19: ="ISIC "&MID(LEFT(C19,FIND(":",C19)-1),FIND("_",C19)+1,LEN(C19)) -> ISIC 22 | C19: TTL_22: Rubber and plastics products | E19: 28.8
B20: ="ISIC "&MID(LEFT(C20,FIND(":",C20)-1),FIND("_",C20)+1,LEN(C20)) -> ISIC 23 | C20: TTL_23: Other non-metallic mineral products | E20: 7.93
... B28: ="ISIC "&MID(LEFT(C28,FIND(":",C28)-1),FIND("_",C28)+1,LEN(C28)) -> ISIC 31T33 | C28: TTL_31T33: Other manufacturing; repair and installation of machinery and equipment | E28: 18.87
B29: ="ISIC "&MID(LEFT(C29,FIND(":",C29)-1),FIND("_",C29)+1,LEN(C29)) -> ISIC 35T39 | C29: TTL_35T39: Electricity, gas, water supply, sewerage, waste and remediation services | E29: 5.53 | F29: Filling in Indonesia value using value from "Other business sector services" row
B30: ="ISIC "&MID(LEFT(C30,FIND(":",C30)-1),FIND("_",C30)+1,LEN(C30)) -> ISIC 41T43 | C30: TTL_41T43: Construction | E30: 5.53 | F30: Filling in Indonesia value using value from "Other business sector services" row
B31: ="ISIC "&MID(LEFT(C31,FIND(":",C31)-1),FIND("_",C31)+1,LEN(C31)) -> ISIC 45T47 | C31: TTL_45T47: Wholesale and retail trade; repair of motor vehicles | E31: 5.3
B32: ="ISIC "&MID(LEFT(C32,FIND(":",C32)-1),FIND("_",C32)+1,LEN(C32)) -> ISIC 49T53 | C32: TTL_49T53: Transportation and storage | E32: 13.54
B33: ="ISIC "&MID(LEFT(C33,FIND(":",C33)-1),FIND("_",C33)+1,LEN(C33)) -> ISIC 55T56 | C33: TTL_55T56: Accomodation and food services | E33: 7.49
B34: ="ISIC "&MID(LEFT(C34,FIND(":",C34)-1),FIND("_",C34)+1,LEN(C34)) -> ISIC 58T60 | C34: TTL_58T60: Publishing, audiovisual and broadcasting activities | E34: 12.73
B35: ="ISIC "&MID(LEFT(C35,FIND(":",C35)-1),FIND("_",C35)+1,LEN(C35)) -> ISIC 61 | C35: TTL_61: Telecommunications | E35: 5.63
B36: ="ISIC "&MID(LEFT(C36,FIND(":",C36)-1),FIND("_",C36)+1,LEN(C36)) -> ISIC 62T63 | C36: TTL_62T63: IT and other information services | E36: 9.58
B37: ="ISIC "&MID(LEFT(C37,FIND(":",C37)-1),FIND("_",C37)+1,LEN(C37)) -> ISIC 64T66 | C37: TTL_64T66: Financial and insurance activities | E37: 4.99
B38: ="ISIC "&MID(LEFT(C38,FIND(":",C38)-1),FIND("_",C38)+1,LEN(C38)) -> ISIC 68 | C38: TTL_68: Real estate activities | E38: 1.57
B39: ="ISIC "&MID(LEFT(C39,FIND(":",C39)-1),FIND("_",C39)+1,LEN(C39)) -> ISIC 69T82 | C39: TTL_69T82: Other business sector services | E39: 5.53
B40: ="ISIC "&MID(LEFT(C40,FIND(":",C40)-1),FIND("_",C40)+1,LEN(C40)) -> ISIC 84 | C40: TTL_84: Public administration and defence; compulsory social security | E40: 5.53 | F40: Filling in Indonesia value using value from "Other business sector services" row
B41: ="ISIC "&MID(LEFT(C41,FIND(":",C41)-1),FIND("_",C41)+1,LEN(C41)) -> ISIC 85 | C41: TTL_85: Education | E41: 2.41
B42: ="ISIC "&MID(LEFT(C42,FIND(":",C42)-1),FIND("_",C42)+1,LEN(C42)) -> ISIC 86T88 | C42: TTL_86T88: Human health and social work | E42: 7.92
B43: ="ISIC "&MID(LEFT(C43,FIND(":",C43)-1),FIND("_",C43)+1,LEN(C43)) -> ISIC 90T96 | C43: TTL_90T96: Arts, entertainment, recreation and other service activities | E43: 16.52
C44: TOTAL: Total | E44: 13.04

Sheet OECD ICESHR 2018
C1: =DotStatQuery(D1) -> #NAME? | D1: Sorry, the query is too large to fit into the Excel cell. You will not be able to update your table with the .Stat Populator.
C2: Dataset: Input-Output Tables (IOTs) 2021 ed.
C3: Variable | E3: ICESHR: Imports content of exports, as % of exports
C4: Country | E4: IDN: Indonesia
C5: Time | E5: 2018
C6: Unit | E6: Percentage
B7: ISIC | C7: To industry / sector | E7: ICESHR: Imports content of exports shares
C8: From industry / sector | F8: output | G8: percent | H8: combined 01T03
B9: ISIC 01T03 | C9: TTL_01T02: Agriculture, hunting, forestry | E9: 6.48 | F9: {=TRANSPOSE('OECD TTL 2018'!D58:E58)} -> 142726.1 | G9: =F9/SUM($F$9,$F$10) -> 0.82575957 | H9: =SUMPRODUCT(E9:E10,G9:G10) -> 5.7011453 | I9: created weighted avg
B10: ISIC 01T03 | C10: TTL_03: Fishing and aquaculture | E10: 2.01 | F10: 30116.1 | G10: =F10/SUM($F$9,$F$10) -> 0.17424043
B11: ="ISIC "&MID(LEFT(C11,FIND(":",C11)-1),FIND("_",C11)+1,LEN(C11)) -> ISIC 05T06 | C11: TTL_05T06: Mining and quarrying, energy producing products | E11: 13.46
B12: ="ISIC "&MID(LEFT(C12,FIND(":",C12)-1),FIND("_",C12)+1,LEN(C12)) -> ISIC 07T08 | C12: TTL_07T08: Mining and quarrying, non-energy producing products | E12: 8.55
B13: ="ISIC "&MID(LEFT(C13,FIND(":",C13)-1),FIND("_",C13)+1,LEN(C13)) -> ISIC 09 | C13: TTL_09: Mining support service activities | E13: 11.22
B14: ="ISIC "&MID(LEFT(C14,FIND(":",C14)-1),FIND("_",C14)+1,LEN(C14)) -> ISIC 10T12 | C14: TTL_10T12: Food products, beverages and tobacco | E14: 9.55
B15: ="ISIC "&MID(LEFT(C15,FIND(":",C15)-1),FIND("_",C15)+1,LEN(C15)) -> ISIC 13T15 | C15: TTL_13T15: Textiles, textile products, leather and footwear | E15: 19.65
B16: ="ISIC "&MID(LEFT(C16,FIND(":",C16)-1),FIND("_",C16)+1,LEN(C16)) -> ISIC 16 | C16: TTL_16: Wood and products of wood and cork | E16: 13.04
B17: ="ISIC "&MID(LEFT(C17,FIND(":",C17)-1),FIND("_",C17)+1,LEN(C17)) -> ISIC 17T18 | C17: TTL_17T18: Paper products and printing | E17: 18.1
B18: ="ISIC "&MID(LEFT(C18,FIND(":",C18)-1),FIND("_",C18)+1,LEN(C18)) -> ISIC 19 | C18: TTL_19: Coke and refined petroleum products | E18: 20.61
B19: ="ISIC "&MID(LEFT(C19,FIND(":",C19)-1),FIND("_",C19)+1,LEN(C19)) -> ISIC 20 | C19: TTL_20: Chemical and chemical products | E19: 20.9
B20: ="ISIC "&MID(LEFT(C20,FIND(":",C20)-1),FIND("_",C20)+1,LEN(C20)) -> ISIC 21 | C20: TTL_21: Pharmaceuticals, medicinal chemical and botanical products | E20: 16.7
B21: ="ISIC "&MID(LEFT(C21,FIND(":",C21)-1),FIND("_",C21)+1,LEN(C21)) -> ISIC 22 | C21: TTL_22: Rubber and plastics products | E21: 26.58
B22: ="ISIC "&MID(LEFT(C22,FIND(":",C22)-1),FIND("_",C22)+1,LEN(C22)) -> ISIC 23 | C22: TTL_23: Other non-metallic mineral products | E22: 16.25
... B31: ="ISIC "&MID(LEFT(C31,FIND(":",C31)-1),FIND("_",C31)+1,LEN(C31)) -> ISIC 35 | C31: TTL_35: Electricity, gas, steam and air conditioning supply | E31: 13.72
B32: ="ISIC "&MID(LEFT(C32,FIND(":",C32)-1),FIND("_",C32)+1,LEN(C32)) -> ISIC 41T43 | C32: TTL_41T43: Construction | E32: =AVERAGE(E45:E46) -> 6.755 | F32: Filling in Indonesia value using value from "Other business sector services" row
B33: ="ISIC "&MID(LEFT(C33,FIND(":",C33)-1),FIND("_",C33)+1,LEN(C33)) -> ISIC 45T47 | C33: TTL_45T47: Wholesale and retail trade; repair of motor vehicles | E33: 7.49
B34: ="ISIC "&MID(LEFT(C34,FIND(":",C34)-1),FIND("_",C34)+1,LEN(C34)) -> ISIC 49 | C34: TTL_49: Land transport and transport via pipelines | E34: 9.22 | F34: {=TRANSPOSE('OECD TTL 2018'!AD58:AH58)} -> 39272.1 | G34: =F34/SUM($F$34:$F$38) -> 0.4189976 | H34: =SUMPRODUCT(E34:E38,G34:G38) -> 11.687833 | I34: created weighted avg
B35: ="ISIC "&MID(LEFT(C35,FIND(":",C35)-1),FIND("_",C35)+1,LEN(C35)) -> ISIC 50 | C35: TTL_50: Water transport | E35: 19.63 | F35: 12019 | G35: =F35/SUM($F$34:$F$38) -> 0.1282318
B36: ="ISIC "&MID(LEFT(C36,FIND(":",C36)-1),FIND("_",C36)+1,LEN(C36)) -> ISIC 51 | C36: TTL_51: Air transport | E36: 12.42 | F36: 30571.1 | G36: =F36/SUM($F$34:$F$38) -> 0.32616584
B37: ="ISIC "&MID(LEFT(C37,FIND(":",C37)-1),FIND("_",C37)+1,LEN(C37)) -> ISIC 52 | C37: TTL_52: Warehousing and support activities for transportation | E37: 10.01 | F37: 9510.5 | G37: =F37/SUM($F$34:$F$38) -> 0.10146839
B38: ="ISIC "&MID(LEFT(C38,FIND(":",C38)-1),FIND("_",C38)+1,LEN(C38)) -> ISIC 53 | C38: TTL_53: Postal and courier activities | E38: 9.58 | F38: 2356 | G38: =F38/SUM($F$34:$F$38) -> 0.025136378
B39: ="ISIC "&MID(LEFT(C39,FIND(":",C39)-1),FIND("_",C39)+1,LEN(C39)) -> ISIC 55T56 | C39: TTL_55T56: Accommodation and food service activities | E39: 7.65
B40: ="ISIC "&MID(LEFT(C40,FIND(":",C40)-1),FIND("_",C40)+1,LEN(C40)) -> ISIC 58T60 | C40: TTL_58T60: Publishing, audiovisual and broadcasting activities | E40: 13.37
B41: ="ISIC "&MID(LEFT(C41,FIND(":",C41)-1),FIND("_",C41)+1,LEN(C41)) -> ISIC 61 | C41: TTL_61: Telecommunications | E41: 3.98
B42: ="ISIC "&MID(LEFT(C42,FIND(":",C42)-1),FIND("_",C42)+1,LEN(C42)) -> ISIC 62T63 | C42: TTL_62T63: IT and other information services | E42: 9.39
B43: ="ISIC "&MID(LEFT(C43,FIND(":",C43)-1),FIND("_",C43)+1,LEN(C43)) -> ISIC 64T66 | C43: TTL_64T66: Financial and insurance activities | E43: 2.25
B44: ="ISIC "&MID(LEFT(C44,FIND(":",C44)-1),FIND("_",C44)+1,LEN(C44)) -> ISIC 68 | C44: TTL_68: Real estate activities | E44: 3.26
B45: ="ISIC "&MID(LEFT(C45,FIND(":",C45)-1),FIND("_",C45)+1,LEN(C45)) -> ISIC 69T75 | C45: TTL_69T75: Professional, scientific and technical activities | E45: 7.04 | F45: {=TRANSPOSE('OECD TTL 2018'!AO58:AP58)} -> 4483.7 | G45: =F45/SUM($F$45,$F$46) -> 0.18325125 | H45: =SUMPRODUCT(E45:E46,G45:G46) -> 6.5744532 | I45: created weighted avg
B46: ="ISIC "&MID(LEFT(C46,FIND(":",C46)-1),FIND("_",C46)+1,LEN(C46)) -> ISIC 77T82 | C46: TTL_77T82: Administrative and support services | E46: 6.47 | F46: 19983.8 | G46: =F46/SUM($F$45,$F$46) -> 0.81674875
B47: ISIC 84 | C47: TTL_84: Public administration and defence; compulsory social security | E47: =AVERAGE(E45:E46) -> 6.755 | F47: Filling in Indonesia value using value from "Other business sector services" row
B48: ="ISIC "&MID(LEFT(C48,FIND(":",C48)-1),FIND("_",C48)+1,LEN(C48)) -> ISIC 85 | C48: TTL_85: Education | E48: 5.42
B49: ="ISIC "&MID(LEFT(C49,FIND(":",C49)-1),FIND("_",C49)+1,LEN(C49)) -> ISIC 86T88 | C49: TTL_86T88: Human health and social work activities | E49: 11.3
B50: ="ISIC "&MID(LEFT(C50,FIND(":",C50)-1),FIND("_",C50)+1,LEN(C50)) -> ISIC 90T93 | C50: TTL_90T93: Arts, entertainment and recreation | E50: 5.86 | F50: {=TRANSPOSE('OECD TTL 2018'!AT58:AU58)} -> 6790.7 | G50: =F50/SUM($F$50,$F$51) -> 0.32263689 | H50: =SUMPRODUCT(E50:E51,G50:G51) -> 8.2036764 | I50: created weighted avg
B51: ="ISIC "&MID(LEFT(C51,FIND(":",C51)-1),FIND("_",C51)+1,LEN(C51)) -> ISIC 94T96 | C51: TTL_94T96: Other service activities | E51: 9.32 | F51: 14256.8 | G51: =F51/SUM($F$50,$F$51) -> 0.67736311
C52: TOTAL: Total | E52: 14.51
C53: Data extracted on 10 Apr 2023 16:55 UTC (GMT) from OECD.Stat

Sheet OECD TTL 2018
A1: ISIC code | D1: ISIC 01T03 | E1: ISIC 01T03 | F1: ISIC 05T06 | G1: ISIC 07T08 | H1: ISIC 09 | I1: ISIC 10T12 | J1: ISIC 13T15 | K1: ISIC 16 | L1: ISIC 17T18 | M1: ISIC 19 | N1: ISIC 20 | O1: ISIC 21 | P1: ISIC 22 | Q1: ISIC 23 | R1: ISIC 24 | S1: ISIC 25 | T1: ISIC 26 | U1: ISIC 27 | V1: ISIC 28 | W1: ISIC 29 | X1: ISIC 30 | Y1: ISIC 31T33 | Z1: ISIC 35 | AA1: ISIC 36T39 | AB1: ISIC 41T43 | AC1: ISIC 45T47 | AD1: ISIC 49T53 | AE1: ISIC 49T53 | AF1: ISIC 49T53 | AG1: ISIC 49T53 | AH1: ISIC 49T53 | AI1: ISIC 55T56 | AJ1: ISIC 58T60 | AK1: ISIC 61 | AL1: ISIC 62T63 | AM1: ISIC 64T66 | AN1: ISIC 68 | AO1: ISIC 69T82 | AP1: ISIC 69T82 | AQ1: ISIC 84 | AR1: ISIC 85 | AS1: ISIC 86T88 | AT1: ISIC 90T96 | AU1: ISIC 90T96 | AV1: ISIC 97T98
B2: Dataset: Input-Output Tables (IOTs) 2021 ed.
B3: Variable | D3: TTL: Total
B4: Country | D4: IDN: Indonesia
B5: Time | D5: 2018
B6: Unit | D6: US Dollar, Millions
B7: To industry / sector | D7: D01T02: Agriculture, hunting, forestry | E7: D03: Fishing and aquaculture | F7: D05T06: Mining and quarrying, energy producing products | G7: D07T08: Mining and quarrying, non-energy producing products | H7: D09: Mining support service activities | I7: D10T12: Food products, beverages and tobacco | J7: D13T15: Textiles, textile products, leather and footwear | K7: D16: Wood and products of wood and cork | L7: D17T18: Paper products and printing | M7: D19: Coke and refined petroleum products | N7: D20: Chemical and chemical products | O7: D21: Pharmaceuticals, medicinal chemical and botanical products | P7: D22: Rubber and plastics products | Q7: D23: Other non-metallic mineral products | R7: D24: Basic metals | S7: D25: Fabricated metal products | T7: D26: Computer, electronic and optical equipment | U7: D27: Electrical equipment | V7: D28: Machinery and equipment, nec | W7: D29: Motor vehicles, trailers and semi-trailers | X7: D30: Other transport equipment | Y7: D31T33: Manufacturing nec; repair and installation of machinery and equipment | Z7: D35: Electricity, gas, steam and air conditioning supply | AA7: D36T39: Water supply; sewerage, waste management and remediation activities | AB7: D41T43: Construction | AC7: D45T47: Wholesale and retail trade; repair of motor vehicles | AD7: D49: Land transport and transport via pipelines | AE7: D50: Water transport | AF7: D51: Air transport | AG7: D52: Warehousing and support activities for transportation | AH7: D53: Postal and courier activities | AI7: D55T56: Accommodation and food service activities | AJ7: D58T60: Publishing, audiovisual and broadcasting activities | AK7: D61: Telecommunications | AL7: D62T63: IT and other information services | AM7: D64T66: Financial and insurance activities | AN7: D68: Real estate activities | AO7: D69T75: Professional, scientific and technical activities | AP7: D77T82: Administrative and support services | AQ7: D84: Public administration and defence; compulsory social security | AR7: D85: Education | AS7: D86T88: Human health and social work activities | AT7: D90T93: Arts, entertainment and recreation | AU7: D94T96: Other service activities | AV7: D97T98: Activities of households as employers; undifferentiated goods- and services-producing activities of households for own use | AW7: HFCE: Final consumption expenditure of households | AX7: NPISH: Final consumption expenditure of non-profit institutions serving households | AY7: GGFC: Final consumption expenditure of general government | AZ7: GFCF: Gross Fixed Capital Formation | BA7: INVNT: Changes in inventories | BB7: CONS_ABR: Direct purchases abroad by residents (imports) | BC7: CONS_NONRES: Direct purchases by non-residents (exports) | BD7: EXPO: Exports (cross border) | BE7: IMPO: Imports (cross border)
B8: From industry / sector
A9: ISIC 01T03 | B9: TTL_01T02: Agriculture, hunting, forestry | D9: 8726.8 | E9: 7.7 | F9: 17.1 | G9: 1.6 | H9: 0.2 | I9: 57606.9 | J9: 889.3 | K9: 3633.9 | L9: 846.7 | M9: 57.9 | N9: 1080.8 | O9: 423.3 | P9: 5507.4 | Q9: 46.5 | R9: 0.2 | S9: 149 | T9: 2.5 | U9: 0.6 | V9: 134.5 | W9: 0.3 | X9: 36.4 | Y9: 164.8 | Z9: 1.3 | AA9: 1.4 | AB9: 2992 | AC9: 60.8 | AD9: 0.7 | AE9: 42.7 | AF9: 50.9 | AG9: 0.7 | AH9: 0 | AI9: 6931.9 | AJ9: 0.7 | AK9: 0.4 | AL9: 0.2 | AM9: 2.5 | AN9: 0.7 | AO9: 0.1 | AP9: 1 | AQ9: 505.4 | AR9: 25.9 | AS9: 415.2 | AT9: 156.1 | AU9: 60.4 | AV9: 0 | AW9: 38413.8 | AX9: 765.5 | AY9: 1.2 | AZ9: 14190.2 | BA9: -39.6 | BB9: 62 | BC9: 111.7 | BD9: 6745.6 | BE9: -8109.9
A10: ISIC 01T03 | B10: TTL_03: Fishing and aquaculture | D10: 5.2 | E10: 570.1 | F10: 0.1 | G10: 0.1 | H10: 0 | I10: 3438.6 | J10: 0.7 | K10: 0.6 | L10: 0 | M10: 0.1 | N10: 161.2 | O10: 7.6 | P10: 1.8 | Q10: 0 | R10: 0 | S10: 0.1 | T10: 0 | U10: 0 | V10: 0.1 | W10: 0 | X10: 0 | Y10: 65.6 | Z10: 0 | AA10: 1.5 | AB10: 0.3 | AC10: 0.1 | AD10: 0 | AE10: 31 | AF10: 0 | AG10: 0 | AH10: 0 | AI10: 3406.7 | AJ10: 0 | AK10: 0 | AL10: 4 | AM10: 0 | AN10: 0 | AO10: 2 | AP10: 0.1 | AQ10: 23.1 | AR10: 40.9 | AS10: 209 | AT10: 92.7 | AU10: 1.8 | AV10: 0 | AW10: 21544.6 | AX10: 0.4 | AY10: 0.5 | AZ10: 4.7 | BA10: -4.4 | BB10: 4.9 | BC10: 7.7 | BD10: 611 | BE10: -118.9
A11: ISIC 05T06 | B11: TTL_05T06: Mining and quarrying, energy producing products | D11: 10.4 | E11: 4.9 | F11: 10239.9 | G11: 80.9 | H11: 3.2 | I11: 27.3 | J11: 62.9 | K11: 5.5 | L11: 247.1 | M11: 46900.3 | N11: 4320.4 | O11: 1.6 | P11: 49.5 | Q11: 1588.2 | R11: 398.8 | S11: 467.8 | T11: 0.8 | U11: 2.1 | V11: 19.4 | W11: 3.6 | X11: 2.3 | Y11: 12.3 | Z11: 5909 | AA11: 0.5 | AB11: 156.8 | AC11: 96.7 | AD11: 43.4 | AE11: 26 | AF11: 46.2 | AG11: 2.6 | AH11: 1.4 | AI11: 4.8 | AJ11: 2.7 | AK11: 3.1 | AL11: 1 | AM11: 0.5 | AN11: 1.5 | AO11: 2.7 | AP11: 2.6 | AQ11: 16.4 | AR11: 3.5 | AS11: 4.2 | AT11: 0.5 | AU11: 2.8 | AV11: 0 | AW11: 306.6 | AX11: 9.8 | AY11: 0.1 | AZ11: 253.8 | BA11: -179.6 | BB11: 2.5 | BC11: 0 | BD11: 41282.4 | BE11: -12313.2
A12: ISIC 07T08 | B12: TTL_07T08: Mining and quarrying, non-energy producing products | D12: 1.6 | E12: 0.6 | F12: 919.7 | G12: 485.6 | H12: 41.2 | I12: 69.8 | J12: 1.2 | K12: 34.1 | L12: 0.5 | M12: 4544.2 | N12: 892.4 | O12: 25.2 | P12: 61.7 | Q12: 1409.7 | R12: 11740.4 | S12: 5749.6 | T12: 18.8 | U12: 1.7 | V12: 12.4 | W12: 4.4 | X12: 7.5 | Y12: 79.2 | Z12: 0.3 | AA12: 0.4 | AB12: 8597.9 | AC12: 0.9 | AD12: 0.1 | AE12: 0.1 | AF12: 0.1 | AG12: 0.1 | AH12: 0 | AI12: 0.1 | AJ12: 0.2 | AK12: 0.1 | AL12: 0.4 | AM12: 0.1 | AN12: 0.1 | AO12: 2.3 | AP12: 0.1 | AQ12: 4.3 | AR12: 185.9 | AS12: 0.2 | AT12: 0 | AU12: 0.1 | AV12: 0 | AW12: 12.2 | AX12: 0 | AY12: 0.1 | AZ12: 2.2 | BA12: -0.9 | BB12: 1.9 | BC12: 0 | BD12: 4850.7 | BE12: -926.1
A13: ISIC 09 | B13: TTL_09: Mining support service activities | D13: 0.1 | E13: 0 | F13: 3549.8 | G13: 1198.3 | H13: 28.4 | I13: 0.3 | J13: 0 | K13: 0 | L13: 0 | M13: 29.5 | N13: 30.1 | O13: 0 | P13: 5.1 | Q13: 27.6 | R13: 21.8 | S13: 7.7 | T13: 1.1 | U13: 3.7 | V13: 0 | W13: 0.1 | X13: 0 | Y13: 5.7 | Z13: 9.8 | AA13: 0 | AB13: 4 | AC13: 0.1 | AD13: 0 | AE13: 0 | AF13: 0 | AG13: 0 | AH13: 0 | AI13: 0.1 | AJ13: 0 | AK13: 0 | AL13: 0 | AM13: 0 | AN13: 0 | AO13: 23.8 | AP13: 0.1 | AQ13: 0 | AR13: 0 | AS13: 0 | AT13: 0 | AU13: 0 | AV13: 0 | AW13: 0.7 | AX13: 0 | AY13: 0.1 | AZ13: 1479.4 | BA13: 1.8 | BB13: 0.2 | BC13: 0 | BD13: 51.9 | BE13: -63.7
A14: ISIC 10T12 | B14: TTL_10T12: Food products, beverages and tobacco | D14: 5059.8 | E14: 457.8 | F14: 112.6 | G14: 136.1 | H14: 3.8 | I14: 15007.3 | J14: 194 | K14: 53 | L14: 22.6 | M14: 57.7 | N14: 2784.5 | O14: 24.4 | P14: 25.7 | Q14: 39 | R14: 3.9 | S14: 82.1 | T14: 7.9 | U14: 7.2 | V14: 233.9 | W14: 1.4 | X14: 1.5 | Y14: 22.1 | Z14: 14.6 | AA14: 9 | AB14: 25 | AC14: 133.7 | AD14: 56.7 | AE14: 150.5 | AF14: 69.8 | AG14: 48.5 | AH14: 9 | AI14: 12907.3 | AJ14: 83.7 | AK14: 22.2 | AL14: 6.6 | AM14: 69.3 | AN14: 21.1 | AO14: 7.5 | AP14: 45.4 | AQ14: 350.4 | AR14: 195.4 | AS14: 1091.3 | AT14: 124 | AU14: 12 | AV14: 0 | AW14: 89431.5 | AX14: 991.7 | AY14: 1632.7 | AZ14: 19.3 | BA14: 10091.1 | BB14: 255.6 | BC14: 520.4 | BD14: 28260.6 | BE14: -10792.5
A15: ISIC 13T15 | B15: TTL_13T15: Textiles, textile products, leather and footwear | D15: 484.1 | E15: 96 | F15: 39.4 | G15: 20.3 | H15: 5.4 | I15: 154.8 | J15: 20181.4 | K15: 451 | L15: 92.9 | M15: 93.9 | N15: 184.6 | O15: 103.7 | P15: 192.1 | Q15: 87.9 | R15: 89.2 | S15: 256.3 | T15: 14.8 | U15: 125.1 | V15: 58.4 | W15: 54.9 | X15: 53.6 | Y15: 497.9 | Z15: 1.1 | AA15: 8.4 | AB15: 912.8 | AC15: 1219.7 | AD15: 54.1 | AE15: 42.1 | AF15: 84.6 | AG15: 69.2 | AH15: 75.7 | AI15: 162.1 | AJ15: 48.4 | AK15: 22.2 | AL15: 0.8 | AM15: 53 | AN15: 38.2 | AO15: 1.1 | AP15: 91.1 | AQ15: 610.9 | AR15: 541.1 | AS15: 401.9 | AT15: 73.8 | AU15: 109.7 | AV15: 0 | AW15: 14491.3 | AX15: 172.3 | AY15: 1 | AZ15: 679.3 | BA15: 1775.7 | BB15: 171.4 | BC15: 357 | BD15: 15735.2 | BE15: -9103.5
A16: ISIC 16 | B16: TTL_16: Wood and products of wood and cork | D16: 31.9 | E16: 4.5 | F16: 0.5 | G16: 19.3 | H16: 14.2 | I16: 36.1 | J16: 4 | K16: 1625.8 | L16: 72.1 | M16: 331.7 | N16: 20.6 | O16: 0.4 | P16: 13 | Q16: 6.3 | R16: 1.7 | S16: 173.8 | T16: 0.8 | U16: 1.5 | V16: 3.4 | W16: 4.2 | X16: 36.8 | Y16: 519.7 | Z16: 0.1 | AA16: 0.9 | AB16: 8372.2 | AC16: 307.9 | AD16: 1.4 | AE16: 0.2 | AF16: 0.3 | AG16: 10 | AH16: 0.2 | AI16: 7.8 | AJ16: 0.4 | AK16: 0.5 | AL16: 0.1 | AM16: 0.1 | AN16: 0.3 | AO16: 0.1 | AP16: 1 | AQ16: 259 | AR16: 1.1 | AS16: 1.1 | AT16: 1.3 | AU16: 39.4 | AV16: 0 | AW16: 359.2 | AX16: 6.1 | AY16: 0.2 | AZ16: 12.4 | BA16: 27.6 | BB16: 11.5 | BC16: 18.4 | BD16: 3911.2 | BE16: -376.7
A17: ISIC 17T18 | B17: TTL_17T18: Paper products and printing | D17: 85 | E17: 1.2 | F17: 61.5 | G17: 14.2 | H17: 14.9 | I17: 1127.3 | J17: 71.1 | K17: 28.5 | L17: 8484.4 | M17: 292.6 | N17: 277 | O17: 98.8 | P17: 103.5 | Q17: 170.3 | R17: 54.5 | S17: 86.6 | T17: 255.7 | U17: 56.4 | V17: 63.4 | W17: 5.1 | X17: 7.1 | Y17: 87.2 | Z17: 10.5 | AA17: 23.9 | AB17: 346.9 | AC17: 3565.1 | AD17: 156.3 | AE17: 123 | AF17: 138.5 | AG17: 174 | AH17: 32.4 | AI17: 58.4 | AJ17: 1371.6 | AK17: 67.7 | AL17: 3.1 | AM17: 318.2 | AN17: 105 | AO17: 90.7 | AP17: 178.9 | AQ17: 790.5 | AR17: 1141.6 | AS17: 91.3 | AT17: 4.3 | AU17: 15.3 | AV17: 0 | AW17: 1652.3 | AX17: 35.1 | AY17: 1 | AZ17: 10.6 | BA17: 121.9 | BB17: 30.6 | BC17: 50 | BD17: 5774.1 | BE17: -2310.4
A18: ISIC 19 | B18: TTL_19: Coke and refined petroleum products | D18: 1217.7 | E18: 613.8 | F18: 11335.5 | G18: 1287.1 | H18: 282.3 | I18: 762.4 | J18: 246 | K18: 335.1 | L18: 175.8 | M18: 1343.5 | N18: 1869 | O18: 132.7 | P18: 520.8 | Q18: 1257.7 | R18: 561 | S18: 1752.9 | T18: 55.7 | U18: 185.2 | V18: 287.2 | W18: 113.5 | X18: 238.7 | Y18: 160 | Z18: 2889.7 | AA18: 62.1 | AB18: 17957.1 | AC18: 11867.3 | AD18: 5735.9 | AE18: 3329.7 | AF18: 6079.6 | AG18: 261.4 | AH18: 168.4 | AI18: 450.2 | AJ18: 269 | AK18: 344.5 | AL18: 109.5 | AM18: 47.8 | AN18: 178.3 | AO18: 18.1 | AP18: 283.1 | AQ18: 1992.4 | AR18: 382.2 | AS18: 439 | AT18: 47.7 | AU18: 323.2 | AV18: 0 | AW18: 31723.2 | AX18: 591.1 | AY18: 4.8 | AZ18: 13.4 | BA18: 3164.1 | BB18: 118.8 | BC18: 221.3 | BD18: 1831.6 | BE18: -23581
A19: ISIC 20 | B19: TTL_20: Chemical and chemical products | D19: 7120.2 | E19: 17.2 | F19: 634.8 | G19: 622.7 | H19: 97.4 | I19: 1833.3 | J19: 977.7 | K19: 655.4 | L19: 1220.5 | M19: 2865.9 | N19: 6276.3 | O19: 275.2 | P19: 6278.5 | Q19: 535.7 | R19: 182.3 | S19: 554.2 | T19: 738.9 | U19: 1321.8 | V19: 566.8 | W19: 118.2 | X19: 120 | Y19: 369.6 | Z19: 41.6 | AA19: 75.2 | AB19: 1128 | AC19: 836.3 | AD19: 61.9 | AE19: 43.4 | AF19: 92.1 | AG19: 40 | AH19: 1.9 | AI19: 74.2 | AJ19: 388.9 | AK19: 29.7 | AL19: 12.6 | AM19: 28.9 | AN19: 20.5 | AO19: 7.5 | AP19: 56.5 | AQ19: 280.7 | AR19: 254.4 | AS19: 485.8 | AT19: 29.1 | AU19: 48.7 | AV19: 0 | AW19: 10131.9 | AX19: 4 | AY19: 11.1 | AZ19: 29.5 | BA19: 1043.7 | BB19: 41.3 | BC19: 80.1 | BD19: 11918.9 | BE19: -20863.7
A20: ISIC 21 | B20: TTL_21: Pharmaceuticals, medicinal chemical and botanical products | D20: 114.5 | E20: 4.9 | F20: 10 | G20: 5.6 | H20: 0.8 | I20: 18.3 | J20: 4.5 | K20: 3.5 | L20: 29.2 | M20: 9.2 | N20: 43.4 | O20: 79.3 | P20: 21.9 | Q20: 2.5 | R20: 1 | S20: 24.5 | T20: 19.8 | U20: 6.3 | V20: 2.3 | W20: 2.6 | X20: 0.8 | Y20: 3.3 | Z20: 0.8 | AA20: 2.4 | AB20: 10.7 | AC20: 14.4 | AD20: 21.7 | AE20: 14.2 | AF20: 6.8 | AG20: 27.9 | AH20: 0.1 | AI20: 3 | AJ20: 2.8 | AK20: 2.7 | AL20: 1.9 | AM20: 1.3 | AN20: 0.7 | AO20: 0.6 | AP20: 4.8 | AQ20: 35.3 | AR20: 25.4 | AS20: 957.7 | AT20: 0.9 | AU20: 1.9 | AV20: 0 | AW20: 2529.3 | AX20: 134.5 | AY20: 715.2 | AZ20: 20.4 | BA20: 272.4 | BB20: 32.6 | BC20: 62.6 | BD20: 506.7 | BE20: -1246.3
... A56: ISIC INT_FNL | B56: TTL_INT_FNL: Total intermediate consumption at purchasers’ prices | D56: 36328.9 | E56: 3012.3 | F56: 48496.8 | G56: 10584 | H56: 2102.9 | I56: 104470.3 | J56: 30983 | K56: 10905.7 | L56: 16428.8 | M56: 71397 | N56: 26472.8 | O56: 3016.2 | P56: 23677.7 | Q56: 10635.2 | R56: 16916 | S56: 34698.1 | T56: 12152.4 | U56: 8872.6 | V56: 8551.5 | W56: 15661.7 | X56: 7600.6 | Y56: 6915.4 | Z56: 32000.9 | AA56: 761.1 | AB56: 148583.5 | AC56: 60348.9 | AD56: 12764.3 | AE56: 7573.4 | AF56: 13052.3 | AG56: 3410.6 | AH56: 892.1 | AI56: 34187.8 | AJ56: 7132.6 | AK56: 8560.4 | AL56: 3713.2 | AM56: 5200.2 | AN56: 5886.5 | AO56: 1192.3 | AP56: 4433.6 | AQ56: 21984.9 | AR56: 10824.3 | AS56: 10307 | AT56: 1945.2 | AU56: 3998.6 | AV56: 0 | AW56: 579767.3 | AX56: 12668.4 | AY56: 93907.4 | AZ56: 336313 | BA56: 27527.8 | BB56: 6774.3 | BC56: 10144.4 | BD56: 209829.7 | BE56: -234811.5
B57: VALU: Value added at basic prices | D57: 106397.2 | E57: 27103.9 | F57: 51643.4 | G57: 28251.3 | H57: 4315 | I57: 55731.3 | J57: 21256.5 | K57: 4991.8 | L57: 9190 | M57: 20659.9 | N57: 13344.4 | O57: 1557 | P57: 5761.1 | Q57: 5792.4 | R57: 7942.9 | S57: 16608.8 | T57: 6631.4 | U57: 5654.4 | V57: 3019.1 | W57: 17054.6 | X57: 6780.3 | Y57: 5035.3 | Z57: 12406.2 | AA57: 704 | AB57: 109726.4 | AC57: 135679.4 | AD57: 26507.8 | AE57: 4445.6 | AF57: 17518.7 | AG57: 6100 | AH57: 1463.9 | AI57: 28986.3 | AJ57: 7047.3 | AK57: 27133.1 | AL57: 5076 | AM57: 43286.3 | AN57: 28516 | AO57: 3291.4 | AP57: 15550.2 | AQ57: 38068.8 | AR57: 33833.4 | AS57: 11101.4 | AT57: 4845.5 | AU57: 10258.2 | AV57: 3763.2 | AW57: 0 | AX57: 0 | AY57: 0 | AZ57: 0 | BA57: 0 | BB57: 0 | BC57: 0 | BD57: 0 | BE57: 0
B58: OUTPUT: Output at basic prices | D58: 142726.1 | E58: 30116.1 | F58: 100140.2 | G58: 38835.3 | H58: 6417.9 | I58: 160201.6 | J58: 52239.5 | K58: 15897.5 | L58: 25618.8 | M58: 92056.9 | N58: 39817.2 | O58: 4573.2 | P58: 29438.8 | Q58: 16427.7 | R58: 24858.8 | S58: 51306.9 | T58: 18783.8 | U58: 14527 | V58: 11570.6 | W58: 32716.3 | X58: 14380.9 | Y58: 11950.7 | Z58: 44407.1 | AA58: 1465.1 | AB58: 258309.8 | AC58: 196028.3 | AD58: 39272.1 | AE58: 12019 | AF58: 30571.1 | AG58: 9510.5 | AH58: 2356 | AI58: 63174.1 | AJ58: 14179.9 | AK58: 35693.6 | AL58: 8789.2 | AM58: 48486.4 | AN58: 34402.5 | AO58: 4483.7 | AP58: 19983.8 | AQ58: 60053.7 | AR58: 44657.8 | AS58: 21408.4 | AT58: 6790.7 | AU58: 14256.8 | AV58: 3763.2 | AW58: 0 | AX58: 0 | AY58: 0 | AZ58: 0 | BA58: 0 | BB58: 0 | BC58: 0 | BD58: 0 | BE58: 0
B59: Data extracted on 10 Apr 2023 16:51 UTC (GMT) from OECD.Stat

Sheet OECD TTL
A1: ISIC code | D1: ="ISIC "&MID(LEFT(D7,FIND(":",D7)-1),FIND("D",D7)+1,LEN(D7)) -> ISIC 01T03 | E1: ="ISIC "&MID(LEFT(E7,FIND(":",E7)-1),FIND("D",E7)+1,LEN(E7)) -> ISIC 05T06 | F1: ="ISIC "&MID(LEFT(F7,FIND(":",F7)-1),FIND("D",F7)+1,LEN(F7)) -> ISIC 07T08 | G1: ="ISIC "&MID(LEFT(G7,FIND(":",G7)-1),FIND("D",G7)+1,LEN(G7)) -> ISIC 09 | H1: ="ISIC "&MID(LEFT(H7,FIND(":",H7)-1),FIND("D",H7)+1,LEN(H7)) -> ISIC 10T12 | I1: ="ISIC "&MID(LEFT(I7,FIND(":",I7)-1),FIND("D",I7)+1,LEN(I7)) -> ISIC 13T15 | J1: ="ISIC "&MID(LEFT(J7,FIND(":",J7)-1),FIND("D",J7)+1,LEN(J7)) -> ISIC 16 | K1: ="ISIC "&MID(LEFT(K7,FIND(":",K7)-1),FIND("D",K7)+1,LEN(K7)) -> ISIC 17T18 | ... AM1: ="ISIC "&MID(LEFT(AM7,FIND(":",AM7)-1),FIND("D",AM7)+1,LEN(AM7)) -> ISIC 97T98
B2: Dataset: Input-Output Tables 2018 edition
B3: Variable | D3: TTL: Total
B4: Country | D4: IDN: Indonesia
B5: Time | D5: 2015
B6: Unit | D6: US Dollar, Millions
B7: To: (sector in column) | D7: D01T03: Agriculture, forestry and fishing | E7: D05T06: Mining and extraction of energy producing products | F7: D07T08: Mining and quarrying of non-energy producing products | G7: D09: Mining support service activities | H7: D10T12: Food products, beverages and tobacco | I7: D13T15: Textiles, wearing apparel, leather and related products | J7: D16: Wood and products of wood and cork | K7: D17T18: Paper products and printing | L7: D19: Coke and refined petroleum products | M7: D20T21: Chemicals and pharmaceutical products | N7: D22: Rubber and plastic products | O7: D23: Other non-metallic mineral products | P7: D24: Basic metals | Q7: D25: Fabricated metal products | R7: D26: Computer, electronic and optical products | S7: D27: Electrical equipment | T7: D28: Machinery and equipment, nec | U7: D29: Motor vehicles, trailers and semi-trailers | V7: D30: Other transport equipment | W7: D31T33: Other manufacturing; repair and installation of machinery and equipment | X7: D35T39: Electricity, gas, water supply, sewerage, waste and remediation services | Y7: D41T43: Construction | Z7: D45T47: Wholesale and retail trade; repair of motor vehicles | AA7: D49T53: Transportation and storage | AB7: D55T56: Accomodation and food services | AC7: D58T60: Publishing, audiovisual and broadcasting activities | AD7: D61: Telecommunications | AE7: D62T63: IT and other information services | AF7: D64T66: Financial and insurance activities | AG7: D68: Real estate activities | AH7: D69T82: Other business sector services | AI7: D84: Public admin. and defence; compulsory social security | AJ7: D85: Education | AK7: D86T88: Human health and social work | AL7: D90T96: Arts, entertainment, recreation and other service activities | AM7: D97T98: Private households with employed persons | AN7: HFCE: Final consumption expenditure of households | AO7: NPISH: Final consumption expenditure of non-profit institutions serving households | AP7: GGFC: Final consumption expenditure of general government | AQ7: GFCF: Gross Fixed Capital Formation | AR7: INVNT: Changes in inventories | AS7: CONS_ABR: Direct purchases abroad by residents (imports) | AT7: CONS_NONRES: Direct purchases by non-residents (exports) | AU7: EXPO: Exports (cross border) | AV7: IMPO: Imports (cross border)
B8: From: (sector in row)
A9: ="ISIC "&MID(LEFT(B9,FIND(":",B9)-1),FIND("_",B9)+1,LEN(B9)) -> ISIC 01T03 | B9: TTL_01T03: Agriculture, forestry and fishing | D9: 19977.5 | E9: 42.4 | F9: 0.2 | G9: 11.5 | H9: 56883.7 | I9: 2444.9 | J9: 3600.7 | K9: 1393.3 | L9: 0.5 | M9: 509.1 | N9: 710.4 | O9: 4.2 | P9: 0.2 | Q9: 14.9 | R9: 2.6 | S9: 0.1 | T9: 0.3 | U9: 0.2 | V9: 6 | W9: 148.2 | X9: 11.3 | Y9: 521.3 | Z9: 1248.1 | AA9: 72.3 | AB9: 5341.3 | AC9: 12.4 | AD9: 2.1 | AE9: 3.5 | AF9: 4.5 | AG9: 11.6 | AH9: 63.1 | AI9: 231.8 | AJ9: 108.5 | AK9: 91.7 | AL9: 354.5 | AM9: 0 | AN9: 73505.5 | AO9: 0 | AP9: 0.7 | AQ9: 873.4 | AR9: -6.3 | AS9: 43.6 | AT9: 79.2 | AU9: 4954.2 | AV9: -6275.4
A10: ="ISIC "&MID(LEFT(B10,FIND(":",B10)-1),FIND("_",B10)+1,LEN(B10)) -> ISIC 05T06 | B10: TTL_05T06: Mining and extraction of energy producing products | D10: 4.9 | E10: 8053.8 | F10: 91.5 | G10: 646.8 | H10: 336.1 | I10: 144.2 | J10: 32.1 | K10: 307.1 | L10: 29190.9 | M10: 965.4 | N10: 185.4 | O10: 209.4 | P10: 2235.8 | Q10: 74.1 | R10: 11.6 | S10: 0.1 | T10: 1.5 | U10: 0.2 | V10: 0.3 | W10: 7 | X10: 4354.4 | Y10: 6 | Z10: 256 | AA10: 48.6 | AB10: 14.8 | AC10: 7.1 | AD10: 14.5 | AE10: 1.5 | AF10: 8.3 | AG10: 16.3 | AH10: 26.6 | AI10: 0.4 | AJ10: 0.1 | AK10: 93.4 | AL10: 264.9 | AM10: 0 | AN10: 4.3 | AO10: 0 | AP10: 3.6 | AQ10: 541 | AR10: 165.4 | AS10: 0.9 | AT10: 0 | AU10: 32492.1 | AV10: -8336.5
A11: ="ISIC "&MID(LEFT(B11,FIND(":",B11)-1),FIND("_",B11)+1,LEN(B11)) -> ISIC 07T08 | B11: TTL_07T08: Mining and quarrying of non-energy producing products | D11: 0.9 | E11: 0.7 | F11: 3754.3 | G11: 604.2 | H11: 474.3 | I11: 0.7 | J11: 0.1 | K11: 2.4 | L11: 0.4 | M11: 5799.5 | N11: 14.7 | O11: 4791.5 | P11: 4585.4 | Q11: 473.9 | R11: 33.3 | S11: 11.2 | T11: 80.1 | U11: 4 | V11: 5.5 | W11: 5.7 | X11: 220.4 | Y11: 14.3 | Z11: 593.8 | AA11: 0.9 | AB11: 0.2 | AC11: 0.3 | AD11: 4.6 | AE11: 2.6 | AF11: 0.7 | AG11: 183.2 | AH11: 51.4 | AI11: 0.1 | AJ11: 28 | AK11: 7.7 | AL11: 38.6 | AM11: 0 | AN11: 3.9 | AO11: 0 | AP11: 0.4 | AQ11: 1.1 | AR11: 42.8 | AS11: 1.3 | AT11: 0 | AU11: 4442.4 | AV11: -1228.9
A12: ="ISIC "&MID(LEFT(B12,FIND(":",B12)-1),FIND("_",B12)+1,LEN(B12)) -> ISIC 09 | B12: TTL_09: Mining support service activities | D12: 926.2 | E12: 4118.3 | F12: 290.9 | G12: 458.4 | H12: 48.5 | I12: 0 | J12: 4.7 | K12: 23.5 | L12: 41.1 | M12: 8.5 | N12: 65.5 | O12: 3.2 | P12: 4.6 | Q12: 1.1 | R12: 0.1 | S12: 0 | T12: 19.8 | U12: 0.2 | V12: 0.3 | W12: 3.9 | X12: 59.8 | Y12: 883.3 | Z12: 0.5 | AA12: 14 | AB12: 0.2 | AC12: 0 | AD12: 0 | AE12: 0 | AF12: 0.2 | AG12: 0 | AH12: 3.1 | AI12: 20.9 | AJ12: 6.6 | AK12: 0.4 | AL12: 0.4 | AM12: 0 | AN12: 1 | AO12: 0 | AP12: 865.7 | AQ12: 0.4 | AR12: 0.5 | AS12: 0.2 | AT12: 0 | AU12: 63.8 | AV12: -48.3
A13: ="ISIC "&MID(LEFT(B13,FIND(":",B13)-1),FIND("_",B13)+1,LEN(B13)) -> ISIC 10T12 | B13: TTL_10T12: Food products, beverages and tobacco | D13: 6707.8 | E13: 3.4 | F13: 1.1 | G13: 2.2 | H13: 16280.7 | I13: 500.1 | J13: 14.9 | K13: 83.2 | L13: 4.8 | M13: 380.5 | N13: 59.2 | O13: 3.6 | P13: 1.7 | Q13: 8.1 | R13: 8.8 | S13: 2.2 | T13: 2.8 | U13: 1.3 | V13: 1.7 | W13: 11.8 | X13: 16.8 | Y13: 155.5 | Z13: 709.1 | AA13: 77.7 | AB13: 14336.6 | AC13: 20.6 | AD13: 5.4 | AE13: 4.6 | AF13: 34.4 | AG13: 7.7 | AH13: 35.4 | AI13: 342 | AJ13: 0.5 | AK13: 273.2 | AL13: 1563.2 | AM13: 0 | AN13: 94964.8 | AO13: 0.3 | AP13: 2.5 | AQ13: 16.2 | AR13: 76.4 | AS13: 194 | AT13: 341.9 | AU13: 27308.1 | AV13: -7052.6
A14: ="ISIC "&MID(LEFT(B14,FIND(":",B14)-1),FIND("_",B14)+1,LEN(B14)) -> ISIC 13T15 | B14: TTL_13T15: Textiles, wearing apparel, leather and related products | D14: 343.5 | E14: 15.8 | F14: 17.6 | G14: 30 | H14: 59.4 | I14: 20119.7 | J14: 59.8 | K14: 197.1 | L14: 4.2 | M14: 219.9 | N14: 838.4 | O14: 12.9 | P14: 2.3 | Q14: 94 | R14: 97.5 | S14: 23.9 | T14: 70.1 | U14: 212.7 | V14: 75.6 | W14: 432 | X14: 37.1 | Y14: 557 | Z14: 715.8 | AA14: 196.9 | AB14: 407 | AC14: 10.6 | AD14: 22.4 | AE14: 8.4 | AF14: 27.1 | AG14: 5.9 | AH14: 74.1 | AI14: 336.6 | AJ14: 74.6 | AK14: 298.2 | AL14: 2009.2 | AM14: 0 | AN14: 15870.5 | AO14: 0 | AP14: 0.2 | AQ14: 90.1 | AR14: 80.9 | AS14: 124.1 | AT14: 233.6 | AU14: 14696.9 | AV14: -6518.2
A15: ="ISIC "&MID(LEFT(B15,FIND(":",B15)-1),FIND("_",B15)+1,LEN(B15)) -> ISIC 16 | B15: TTL_16: Wood and of products of wood and cork (except furniture) | D15: 121.9 | E15: 0.3 | F15: 0.1 | G15: 7.6 | H15: 74.9 | I15: 63.1 | J15: 1875.3 | K15: 231.7 | L15: 0.3 | M15: 34.8 | N15: 120.3 | O15: 17.8 | P15: 0.3 | Q15: 100.1 | R15: 51.7 | S15: 17.6 | T15: 64.9 | U15: 60.1 | V15: 47.7 | W15: 688.1 | X15: 5.8 | Y15: 5643.1 | Z15: 142.2 | AA15: 26.3 | AB15: 55.5 | AC15: 13.9 | AD15: 5.2 | AE15: 3.3 | AF15: 1.6 | AG15: 63.1 | AH15: 19.4 | AI15: 20.3 | AJ15: 18.5 | AK15: 4.9 | AL15: 250.7 | AM15: 0 | AN15: 823.4 | AO15: 0 | AP15: 0.3 | AQ15: 13.1 | AR15: -46.1 | AS15: 6.4 | AT15: 11.5 | AU15: 3890.2 | AV15: -316.5
A16: ="ISIC "&MID(LEFT(B16,FIND(":",B16)-1),FIND("_",B16)+1,LEN(B16)) -> ISIC 17T18 | B16: TTL_17T18: Paper products and printing | D16: 150.1 | E16: 54.8 | F16: 15.9 | G16: 4.7 | H16: 1570.5 | I16: 325.9 | J16: 94.7 | K16: 5668.9 | L16: 0.8 | M16: 249.1 | N16: 438.8 | O16: 37.3 | P16: 10.3 | Q16: 102.6 | R16: 201.2 | S16: 48.6 | T16: 128.2 | U16: 50.6 | V16: 26.7 | W16: 96.2 | X16: 84.5 | Y16: 334.9 | Z16: 776.8 | AA16: 127.2 | AB16: 376.1 | AC16: 3124.5 | AD16: 99.4 | AE16: 55.8 | AF16: 379.6 | AG16: 21.1 | AH16: 129.7 | AI16: 259.7 | AJ16: 220.5 | AK16: 96.1 | AL16: 629.1 | AM16: 0 | AN16: 3072.4 | AO16: 0.1 | AP16: 0.8 | AQ16: 15.3 | AR16: -0.4 | AS16: 23.1 | AT16: 31.5 | AU16: 4675.5 | AV16: -2218.6
A17: ="ISIC "&MID(LEFT(B17,FIND(":",B17)-1),FIND("_",B17)+1,LEN(B17)) -> ISIC 19 | B17: TTL_19: Coke and refined petroleum products | D17: 7578.5 | E17: 3918.4 | F17: 1701.1 | G17: 507.4 | H17: 1604.5 | I17: 1047.1 | J17: 307.5 | K17: 647.4 | L17: 10972.1 | M17: 3285.4 | N17: 1112 | O17: 339.9 | P17: 944.6 | Q17: 638.1 | R17: 456.5 | S17: 174.4 | T17: 593.9 | U17: 230.7 | V17: 499.8 | W17: 294.3 | X17: 1612.7 | Y17: 11062.3 | Z17: 3913.5 | AA17: 18853.5 | AB17: 1252.5 | AC17: 288.4 | AD17: 298.4 | AE17: 103.7 | AF17: 764.6 | AG17: 167.8 | AH17: 523.1 | AI17: 1382.6 | AJ17: 404.4 | AK17: 358.3 | AL17: 2857.9 | AM17: 0 | AN17: 5481.2 | AO17: 0.1 | AP17: 1 | AQ17: 4.1 | AR17: 21 | AS17: 53.5 | AT17: 66.7 | AU17: 1601.1 | AV17: -14238
A18: ="ISIC "&MID(LEFT(B18,FIND(":",B18)-1),FIND("_",B18)+1,LEN(B18)) -> ISIC 20T21 | B18: TTL_20T21: Chemicals and pharmaceutical products | D18: 3305.8 | E18: 849.9 | F18: 289.5 | G18: 62.9 | H18: 824.1 | I18: 3138.7 | J18: 331.2 | K18: 1251.7 | L18: 1713.2 | M18: 5732 | N18: 10068.9 | O18: 136.1 | P18: 357.8 | Q18: 607.7 | R18: 845.6 | S18: 254.5 | T18: 403.3 | U18: 277.9 | V18: 279.9 | W18: 287.5 | X18: 174.5 | Y18: 2386.1 | Z18: 479.9 | AA18: 227.7 | AB18: 186.7 | AC18: 237.4 | AD18: 13.1 | AE18: 7.3 | AF18: 46.5 | AG18: 44.3 | AH18: 105.8 | AI18: 158.4 | AJ18: 107.9 | AK18: 798.1 | AL18: 1055.3 | AM18: 0 | AN18: 10001.6 | AO18: 0.6 | AP18: 5.2 | AQ18: 109.9 | AR18: 22 | AS18: 45.1 | AT18: 67.6 | AU18: 8813.8 | AV18: -17388.7
A19: ="ISIC "&MID(LEFT(B19,FIND(":",B19)-1),FIND("_",B19)+1,LEN(B19)) -> ISIC 22 | B19: TTL_22: Rubber and plastics products | D19: 295.8 | E19: 4.1 | F19: 1.2 | G19: 38.3 | H19: 1285.2 | I19: 641.3 | J19: 99.4 | K19: 376.5 | L19: 98.3 | M19: 358.4 | N19: 4740.4 | O19: 45 | P19: 71.4 | Q19: 367.7 | R19: 984.4 | S19: 282 | T19: 730.1 | U19: 750.7 | V19: 420.6 | W19: 281.5 | X19: 42.7 | Y19: 4688.7 | Z19: 829.9 | AA19: 423.2 | AB19: 293.8 | AC19: 74.4 | AD19: 79.1 | AE19: 11.8 | AF19: 50.4 | AG19: 21.6 | AH19: 66.8 | AI19: 81.2 | AJ19: 33.8 | AK19: 68.5 | AL19: 783.8 | AM19: 0 | AN19: 10835.8 | AO19: 0.1 | AP19: 0.6 | AQ19: 75.7 | AR19: 35.9 | AS19: 1.4 | AT19: 0 | AU19: 5263 | AV19: -3076.5
A20: ="ISIC "&MID(LEFT(B20,FIND(":",B20)-1),FIND("_",B20)+1,LEN(B20)) -> ISIC 23 | B20: TTL_23: Other non-metallic mineral products | D20: 3.7 | E20: 2.1 | F20: 2.6 | G20: 15.7 | H20: 224.6 | I20: 8 | J20: 48.6 | K20: 1.9 | L20: 2.1 | M20: 75.5 | N20: 162.2 | O20: 255.4 | P20: 1.8 | Q20: 129 | R20: 288.4 | S20: 44.7 | T20: 104.8 | U20: 83 | V20: 35.1 | W20: 36.4 | X20: 17.7 | Y20: 10819.1 | Z20: 124.7 | AA20: 17.2 | AB20: 73.5 | AC20: 5.8 | AD20: 8.4 | AE20: 1.6 | AF20: 3.3 | AG20: 22.2 | AH20: 12.7 | AI20: 29 | AJ20: 18.4 | AK20: 16.2 | AL20: 90.6 | AM20: 0 | AN20: 1176.9 | AO20: 0.1 | AP20: 0.6 | AQ20: 57 | AR20: -12.7 | AS20: 0.8 | AT20: 0 | AU20: 827.8 | AV20: -1442.5
... A47: ="ISIC "&MID(LEFT(B47,FIND(":",B47)-1),FIND("_",B47)+1,LEN(B47)) -> ISIC INT_FNL | B47: TTL_INT_FNL: Total intermediate consumption at purchasers’ prices | D47: 51788.3 | E47: 26973.8 | F47: 9504.8 | G47: 3650.4 | H47: 101546.9 | I47: 39633.7 | J47: 8458.7 | K47: 15091.1 | L47: 49964.7 | M47: 23188.2 | N47: 26192.4 | O47: 7219.8 | P47: 13494.5 | Q47: 14551.1 | R47: 22016.4 | S47: 4608.8 | T47: 14031.9 | U47: 18775.8 | V47: 8280.9 | W47: 5063.4 | X47: 10833.9 | Y47: 85968.5 | Z47: 43712.3 | AA47: 48024.7 | AB47: 32970.3 | AC47: 13439.4 | AD47: 12651.5 | AE47: 2059.4 | AF47: 18817.1 | AG47: 3036.7 | AH47: 5442.7 | AI47: 10929.6 | AJ47: 4494.7 | AK47: 6536.4 | AL47: 38567.6 | AM47: 0 | AN47: 481844.2 | AO47: 9780.4 | AP47: 84163.3 | AQ47: 282595.9 | AR47: -2675.1 | AS47: 5183.3 | AT47: 7304.2 | AU47: 172920.2 | AV47: -179538.6
B48: VALU: Value added at basic prices | D48: 115215.6 | E48: 45507.9 | F48: 15547.8 | G48: 4240.9 | H48: 55967.4 | I48: 12651.7 | J48: 5776 | K48: 6499.4 | L48: 23723 | M48: 15536.5 | N48: 6365.4 | O48: 6174.3 | P48: 6677 | Q48: 5094.3 | R48: 8406.9 | S48: 3286.2 | T48: 2761.4 | U48: 15735.3 | V48: 595.3 | W48: 2873.6 | X48: 12204.1 | Y48: 87172.6 | Z48: 113700.5 | AA48: 42884 | AB48: 25295 | AC48: 5768.9 | AD48: 22051.4 | AE48: 2246.7 | AF48: 34438.5 | AG48: 24261.5 | AH48: 14092.4 | AI48: 33343.4 | AJ48: 28737.6 | AK48: 9103.8 | AL48: 18408.1 | AM48: 1389.2 | AN48: 0 | AO48: 0 | AP48: 0 | AQ48: 0 | AR48: 0 | AS48: 0 | AT48: 0 | AU48: 0 | AV48: 0
B49: OUTPUT: Output at basic prices | D49: 167004 | E49: 72481.8 | F49: 25052.6 | G49: 7891.3 | H49: 157514.3 | I49: 52285.4 | J49: 14234.7 | K49: 21590.5 | L49: 73687.7 | M49: 38724.7 | N49: 32557.8 | O49: 13394.1 | P49: 20171.6 | Q49: 19645.4 | R49: 30423.2 | S49: 7895 | T49: 16793.3 | U49: 34511.2 | V49: 8876.2 | W49: 7937 | X49: 23038 | Y49: 173141.1 | Z49: 157412.8 | AA49: 90908.7 | AB49: 58265.2 | AC49: 19208.4 | AD49: 34702.8 | AE49: 4306.1 | AF49: 53255.6 | AG49: 27298.3 | AH49: 19535.1 | AI49: 44273 | AJ49: 33232.3 | AK49: 15640.2 | AL49: 56975.6 | AM49: 1389.2 | AN49: 0 | AO49: 0 | AP49: 0 | AQ49: 0 | AR49: 0 | AS49: 0 | AT49: 0 | AU49: 0 | AV49: 0
B50: Data extracted on 26 Mar 2021 19:27 UTC (GMT) from OECD.Stat

Sheet Calculations
B2: Split percentages | D2: {=TRANSPOSE('EXIOBASE ISIC SPLITS'!B4:B5)} -> ISIC 05 | E2: ISIC 06 | M2: ISIC 20 | N2: ISIC 21 | P2: {=TRANSPOSE('EXIOBASE ISIC SPLITS'!B6:B7)} -> ISIC 231 | Q2: ISIC 239 | R2: {=TRANSPOSE('EXIOBASE ISIC SPLITS'!B8:B9)} -> ISIC 241 | S2: ISIC 242 | AA2: {=TRANSPOSE('EXIOBASE ISIC SPLITS'!B10:B12)} -> ISIC 351 | AB2: ISIC 352T353 | AC2: ISIC 36T39
B3: {=TRANSPOSE('EXIOBASE ISIC SPLITS'!H3:J3)} -> Output | D3: {=TRANSPOSE('EXIOBASE ISIC SPLITS'!H4:J5)} -> 0.39817377 | E3: 0.60182623 | M3: ='IDN WIOD IO-tables'!O1810 -> 0.69467425 | N3: ='IDN WIOD IO-tables'!P1810 -> 0.30532575 | P3: {=TRANSPOSE('EXIOBASE ISIC SPLITS'!H6:J7)} -> 0.27109933 | Q3: 0.72890067 | R3: {=TRANSPOSE('EXIOBASE ISIC SPLITS'!H8:J9)} -> 0.42628986 | S3: 0.57371014 | AA3: {=TRANSPOSE('EXIOBASE ISIC SPLITS'!H10:J12)} -> 0.9716666 | AB3: 0.028333399 | AC3: 0
B4: Import | D4: 0.034856795 | E4: 0.96514321 | M4: ='IDN WIOD IO-tables'!O1811 -> 0.79777402 | N4: ='IDN WIOD IO-tables'!P1811 -> 0.20222598 | P4: 0.27626225 | Q4: 0.72373775 | R4: 0.77046615 | S4: 0.22953385 | AA4: 0 | AB4: 1 | AC4: 0
B5: Export | D5: 0.40480346 | E5: 0.59519654 | M5: ='IDN WIOD IO-tables'!O1812 -> 0.86811797 | N5: ='IDN WIOD IO-tables'!P1812 -> 0.13188203 | P5: 0.36087383 | Q5: 0.63912617 | R5: 0.24047436 | S5: 0.75952564 | AA5: 0 | AB5: 0 | AC5: 0
B7: Pre ISIC Consolidation | D7: ISIC 05T06 | E7: ISIC 05T06 | P7: ISIC 23 | Q7: ISIC 23 | R7: ISIC 24 | S7: ISIC 24 | AA7: ISIC 35 | AB7: ISIC 35 | AC7: ISIC 35
C8: ISIC 01T03 | D8: ISIC 05 | E8: ISIC 06 | F8: ISIC 07T08 | G8: ISIC 09 | H8: ISIC 10T12 | I8: ISIC 13T15 | J8: ISIC 16 | K8: ISIC 17T18 | L8: ISIC 19 | M8: ISIC 20 | N8: ISIC 21 | O8: ISIC 22 | P8: ISIC 231 | Q8: ISIC 239 | R8: ISIC 241 | S8: ISIC 242 | T8: ISIC 25 | U8: ISIC 26 | V8: ISIC 27 | W8: ISIC 28 | X8: ISIC 29 | Y8: ISIC 30 | Z8: ISIC 31T33 | AA8: ISIC 351 | AB8: ISIC 352T353 | AC8: ISIC 36T39 | AD8: ISIC 41T43 | AE8: ISIC 45T47 | AF8: ISIC 49T53 | AG8: ISIC 55T56 | AH8: ISIC 58T60 | AI8: ISIC 61 | AJ8: ISIC 62T63 | AK8: ISIC 64T66 | AL8: ISIC 68 | AM8: ISIC 69T82 | AN8: ISIC 84 | AO8: ISIC 85 | AP8: ISIC 86T88 | AQ8: ISIC 90T96 | AR8: ISIC 97T98
A9: =SUM(C9:AR9)/SUM('OECD TTL 2018'!D58:AV58) -> 1 | B9: Domestic Production | C9: =SUMIFS('OECD TTL 2018'!$D$58:$BE$58,'OECD TTL 2018'!$D$1:$BE$1,C8) -> 172842.2 | D9: =SUMIFS('OECD TTL 2018'!$D$58:$BE$58,'OECD TTL 2018'!$D$1:$BE$1,D7)*D3 -> 39873.201 | E9: =SUMIFS('OECD TTL 2018'!$D$58:$BE$58,'OECD TTL 2018'!$D$1:$BE$1,E7)*E3 -> 60266.999 | F9: =SUMIFS('OECD TTL 2018'!$D$58:$BE$58,'OECD TTL 2018'!$D$1:$BE$1,F8) -> 38835.3 | G9: =SUMIFS('OECD TTL 2018'!$D$58:$BE$58,'OECD TTL 2018'!$D$1:$BE$1,G8) -> 6417.9 | H9: =SUMIFS('OECD TTL 2018'!$D$58:$BE$58,'OECD TTL 2018'!$D$1:$BE$1,H8) -> 160201.6 | I9: =SUMIFS('OECD TTL 2018'!$D$58:$BE$58,'OECD TTL 2018'!$D$1:$BE$1,I8) -> 52239.5 | J9: =SUMIFS('OECD TTL 2018'!$D$58:$BE$58,'OECD TTL 2018'!$D$1:$BE$1,J8) -> 15897.5 | K9: =SUMIFS('OECD TTL 2018'!$D$58:$BE$58,'OECD TTL 2018'!$D$1:$BE$1,K8) -> 25618.8 | L9: =SUMIFS('OECD TTL 2018'!$D$58:$BE$58,'OECD TTL 2018'!$D$1:$BE$1,L8) -> 92056.9 | M9: =SUMIFS('OECD TTL 2018'!$D$58:$BE$58,'OECD TTL 2018'!$D$1:$BE$1,M8) -> 39817.2 | ... O9: =SUMIFS('OECD TTL 2018'!$D$58:$BE$58,'OECD TTL 2018'!$D$1:$BE$1,O8) -> 29438.8 | P9: =SUMIFS('OECD TTL 2018'!$D$58:$BE$58,'OECD TTL 2018'!$D$1:$BE$1,P7)*P3 -> 4453.5384 | Q9: =SUMIFS('OECD TTL 2018'!$D$58:$BE$58,'OECD TTL 2018'!$D$1:$BE$1,Q7)*Q3 -> 11974.162 | R9: =SUMIFS('OECD TTL 2018'!$D$58:$BE$58,'OECD TTL 2018'!$D$1:$BE$1,R7)*R3 -> 10597.054 | S9: =SUMIFS('OECD TTL 2018'!$D$58:$BE$58,'OECD TTL 2018'!$D$1:$BE$1,S7)*S3 -> 14261.746 | T9: =SUMIFS('OECD TTL 2018'!$D$58:$BE$58,'OECD TTL 2018'!$D$1:$BE$1,T8) -> 51306.9 | U9: =SUMIFS('OECD TTL 2018'!$D$58:$BE$58,'OECD TTL 2018'!$D$1:$BE$1,U8) -> 18783.8 | V9: =SUMIFS('OECD TTL 2018'!$D$58:$BE$58,'OECD TTL 2018'!$D$1:$BE$1,V8) -> 14527 | W9: =SUMIFS('OECD TTL 2018'!$D$58:$BE$58,'OECD TTL 2018'!$D$1:$BE$1,W8) -> 11570.6 | X9: =SUMIFS('OECD TTL 2018'!$D$58:$BE$58,'OECD TTL 2018'!$D$1:$BE$1,X8) -> 32716.3 | Y9: =SUMIFS('OECD TTL 2018'!$D$58:$BE$58,'OECD TTL 2018'!$D$1:$BE$1,Y8) -> 14380.9 | Z9: =SUMIFS('OECD TTL 2018'!$D$58:$BE$58,'OECD TTL 2018'!$D$1:$BE$1,Z8) -> 11950.7 | AA9: =SUMIFS('OECD TTL 2018'!$D$58:$BE$58,'OECD TTL 2018'!$D$1:$BE$1,AA7)*AA3 -> 43148.896 | AB9: =SUMIFS('OECD TTL 2018'!$D$58:$BE$58,'OECD TTL 2018'!$D$1:$BE$1,AB7)*AB3 -> 1258.2041 | AC9: =SUMIFS('OECD TTL 2018'!$D$58:$BE$58,'OECD TTL 2018'!$D$1:$BE$1,AC8) -> 1465.1 | AD9: =SUMIFS('OECD TTL 2018'!$D$58:$BE$58,'OECD TTL 2018'!$D$1:$BE$1,AD8) -> 258309.8 | AE9: =SUMIFS('OECD TTL 2018'!$D$58:$BE$58,'OECD TTL 2018'!$D$1:$BE$1,AE8) -> 196028.3 | AF9: =SUMIFS('OECD TTL 2018'!$D$58:$BE$58,'OECD TTL 2018'!$D$1:$BE$1,AF8) -> 93728.7 | AG9: =SUMIFS('OECD TTL 2018'!$D$58:$BE$58,'OECD TTL 2018'!$D$1:$BE$1,AG8) -> 63174.1 | AH9: =SUMIFS('OECD TTL 2018'!$D$58:$BE$58,'OECD TTL 2018'!$D$1:$BE$1,AH8) -> 14179.9 | AI9: =SUMIFS('OECD TTL 2018'!$D$58:$BE$58,'OECD TTL 2018'!$D$1:$BE$1,AI8) -> 35693.6 | AJ9: =SUMIFS('OECD TTL 2018'!$D$58:$BE$58,'OECD TTL 2018'!$D$1:$BE$1,AJ8) -> 8789.2 | ... AR9: =SUMIFS('OECD TTL 2018'!$D$58:$BE$58,'OECD TTL 2018'!$D$1:$BE$1,AR8) -> 3763.2
A10: =SUM(C10:AR10)/SUM('OECD TTL 2018'!BB9:BB53,-SUM('OECD TTL 2018'!BE9:BE53)) -> 1.0139743 | B10: Imports | C10: =-SUMIFS('OECD TTL 2018'!$BE:$BE,'OECD TTL 2018'!$A:$A,C8)+SUMIFS('OECD TTL 2018'!$BC:$BC,'OECD TTL 2018'!$A:$A,C8) -> 8348.2 | D10: =(-SUMIFS('OECD TTL 2018'!$BE:$BE,'OECD TTL 2018'!$A:$A,D7)+SUMIFS('OECD TTL 2018'!$BC:$BC,'OECD TTL 2018'!$A:$A,D8))*D4 -> 429.19869 | E10: =(-SUMIFS('OECD TTL 2018'!$BE:$BE,'OECD TTL 2018'!$A:$A,E7)+SUMIFS('OECD TTL 2018'!$BC:$BC,'OECD TTL 2018'!$A:$A,E8))*E4 -> 11884.001 | F10: =-SUMIFS('OECD TTL 2018'!$BE:$BE,'OECD TTL 2018'!$A:$A,F8)+SUMIFS('OECD TTL 2018'!$BC:$BC,'OECD TTL 2018'!$A:$A,F8) -> 926.1 | G10: =-SUMIFS('OECD TTL 2018'!$BE:$BE,'OECD TTL 2018'!$A:$A,G8)+SUMIFS('OECD TTL 2018'!$BC:$BC,'OECD TTL 2018'!$A:$A,G8) -> 63.7 | H10: =-SUMIFS('OECD TTL 2018'!$BE:$BE,'OECD TTL 2018'!$A:$A,H8)+SUMIFS('OECD TTL 2018'!$BC:$BC,'OECD TTL 2018'!$A:$A,H8) -> 11312.9 | I10: =-SUMIFS('OECD TTL 2018'!$BE:$BE,'OECD TTL 2018'!$A:$A,I8)+SUMIFS('OECD TTL 2018'!$BC:$BC,'OECD TTL 2018'!$A:$A,I8) -> 9460.5 | J10: =-SUMIFS('OECD TTL 2018'!$BE:$BE,'OECD TTL 2018'!$A:$A,J8)+SUMIFS('OECD TTL 2018'!$BC:$BC,'OECD TTL 2018'!$A:$A,J8) -> 395.1 | K10: =-SUMIFS('OECD TTL 2018'!$BE:$BE,'OECD TTL 2018'!$A:$A,K8)+SUMIFS('OECD TTL 2018'!$BC:$BC,'OECD TTL 2018'!$A:$A,K8) -> 2360.4 | L10: =-SUMIFS('OECD TTL 2018'!$BE:$BE,'OECD TTL 2018'!$A:$A,L8)+SUMIFS('OECD TTL 2018'!$BC:$BC,'OECD TTL 2018'!$A:$A,L8) -> 23802.3 | M10: =-SUMIFS('OECD TTL 2018'!$BE:$BE,'OECD TTL 2018'!$A:$A,M8)+SUMIFS('OECD TTL 2018'!$BC:$BC,'OECD TTL 2018'!$A:$A,M8) -> 20943.8 | ... O10: =-SUMIFS('OECD TTL 2018'!$BE:$BE,'OECD TTL 2018'!$A:$A,O8)+SUMIFS('OECD TTL 2018'!$BC:$BC,'OECD TTL 2018'!$A:$A,O8) -> 4133.3 | P10: =(-SUMIFS('OECD TTL 2018'!$BE:$BE,'OECD TTL 2018'!$A:$A,P7)+SUMIFS('OECD TTL 2018'!$BC:$BC,'OECD TTL 2018'!$A:$A,P7))*P4 -> 478.95586 | Q10: =(-SUMIFS('OECD TTL 2018'!$BE:$BE,'OECD TTL 2018'!$A:$A,Q7)+SUMIFS('OECD TTL 2018'!$BC:$BC,'OECD TTL 2018'!$A:$A,Q7))*Q4 -> 1254.7441 | R10: =(-SUMIFS('OECD TTL 2018'!$BE:$BE,'OECD TTL 2018'!$A:$A,R7)+SUMIFS('OECD TTL 2018'!$BC:$BC,'OECD TTL 2018'!$A:$A,R7))*R4 -> 10769.884 | S10: =(-SUMIFS('OECD TTL 2018'!$BE:$BE,'OECD TTL 2018'!$A:$A,S7)+SUMIFS('OECD TTL 2018'!$BC:$BC,'OECD TTL 2018'!$A:$A,S7))*S4 -> 3208.516 | T10: =-SUMIFS('OECD TTL 2018'!$BE:$BE,'OECD TTL 2018'!$A:$A,T8)+SUMIFS('OECD TTL 2018'!$BC:$BC,'OECD TTL 2018'!$A:$A,T8) -> 5984.6 | U10: =-SUMIFS('OECD TTL 2018'!$BE:$BE,'OECD TTL 2018'!$A:$A,U8)+SUMIFS('OECD TTL 2018'!$BC:$BC,'OECD TTL 2018'!$A:$A,U8) -> 15007.3 | V10: =-SUMIFS('OECD TTL 2018'!$BE:$BE,'OECD TTL 2018'!$A:$A,V8)+SUMIFS('OECD TTL 2018'!$BC:$BC,'OECD TTL 2018'!$A:$A,V8) -> 7916.2 | W10: =-SUMIFS('OECD TTL 2018'!$BE:$BE,'OECD TTL 2018'!$A:$A,W8)+SUMIFS('OECD TTL 2018'!$BC:$BC,'OECD TTL 2018'!$A:$A,W8) -> 18608.9 | X10: =-SUMIFS('OECD TTL 2018'!$BE:$BE,'OECD TTL 2018'!$A:$A,X8)+SUMIFS('OECD TTL 2018'!$BC:$BC,'OECD TTL 2018'!$A:$A,X8) -> 7332.5 | Y10: =-SUMIFS('OECD TTL 2018'!$BE:$BE,'OECD TTL 2018'!$A:$A,Y8)+SUMIFS('OECD TTL 2018'!$BC:$BC,'OECD TTL 2018'!$A:$A,Y8) -> 5573.4 | Z10: =-SUMIFS('OECD TTL 2018'!$BE:$BE,'OECD TTL 2018'!$A:$A,Z8)+SUMIFS('OECD TTL 2018'!$BC:$BC,'OECD TTL 2018'!$A:$A,Z8) -> 3156.3 | AA10: =(-SUMIFS('OECD TTL 2018'!$BE:$BE,'OECD TTL 2018'!$A:$A,AA7)+SUMIFS('OECD TTL 2018'!$BC:$BC,'OECD TTL 2018'!$A:$A,AA7))*AA4 -> 0 | AB10: =(-SUMIFS('OECD TTL 2018'!$BE:$BE,'OECD TTL 2018'!$A:$A,AB7)+SUMIFS('OECD TTL 2018'!$BC:$BC,'OECD TTL 2018'!$A:$A,AB7))*AB4 -> 344.4 | AC10: =-SUMIFS('OECD TTL 2018'!$BE:$BE,'OECD TTL 2018'!$A:$A,AC8)+SUMIFS('OECD TTL 2018'!$BC:$BC,'OECD TTL 2018'!$A:$A,AC8) -> 30.4 | AD10: =-SUMIFS('OECD TTL 2018'!$BE:$BE,'OECD TTL 2018'!$A:$A,AD8)+SUMIFS('OECD TTL 2018'!$BC:$BC,'OECD TTL 2018'!$A:$A,AD8) -> 120.2 | AE10: =-SUMIFS('OECD TTL 2018'!$BE:$BE,'OECD TTL 2018'!$A:$A,AE8)+SUMIFS('OECD TTL 2018'!$BC:$BC,'OECD TTL 2018'!$A:$A,AE8) -> 23861.3 | AF10: =-SUMIFS('OECD TTL 2018'!$BE:$BE,'OECD TTL 2018'!$A:$A,AF8)+SUMIFS('OECD TTL 2018'!$BC:$BC,'OECD TTL 2018'!$A:$A,AF8) -> 18539.5 | AG10: =-SUMIFS('OECD TTL 2018'!$BE:$BE,'OECD TTL 2018'!$A:$A,AG8)+SUMIFS('OECD TTL 2018'!$BC:$BC,'OECD TTL 2018'!$A:$A,AG8) -> 6395.3 | AH10: =-SUMIFS('OECD TTL 2018'!$BE:$BE,'OECD TTL 2018'!$A:$A,AH8)+SUMIFS('OECD TTL 2018'!$BC:$BC,'OECD TTL 2018'!$A:$A,AH8) -> 1811.7 | AI10: =-SUMIFS('OECD TTL 2018'!$BE:$BE,'OECD TTL 2018'!$A:$A,AI8)+SUMIFS('OECD TTL 2018'!$BC:$BC,'OECD TTL 2018'!$A:$A,AI8) -> 772.7 | AJ10: =-SUMIFS('OECD TTL 2018'!$BE:$BE,'OECD TTL 2018'!$A:$A,AJ8)+SUMIFS('OECD TTL 2018'!$BC:$BC,'OECD TTL 2018'!$A:$A,AJ8) -> 3425.5 | ... AR10: =-SUMIFS('OECD TTL 2018'!$BE:$BE,'OECD TTL 2018'!$A:$A,AR8)+SUMIFS('OECD TTL 2018'!$BC:$BC,'OECD TTL 2018'!$A:$A,AR8) -> 0
A11: =SUM(C11:AR11)/SUM('OECD TTL 2018'!BC9:BC53,'OECD TTL 2018'!BD9:BD53) -> 1 | B11: Exports | C11: =SUM(SUMIFS('OECD TTL 2018'!$BC:$BC,'OECD TTL 2018'!$A:$A,C8),SUMIFS('OECD TTL 2018'!$BD:$BD,'OECD TTL 2018'!$A:$A,C8)) -> 7476 | D11: =SUM(SUMIFS('OECD TTL 2018'!$BC:$BC,'OECD TTL 2018'!$A:$A,D7),SUMIFS('OECD TTL 2018'!$BD:$BD,'OECD TTL 2018'!$A:$A,D7))*D5 -> 16711.258 | E11: =SUM(SUMIFS('OECD TTL 2018'!$BC:$BC,'OECD TTL 2018'!$A:$A,E7),SUMIFS('OECD TTL 2018'!$BD:$BD,'OECD TTL 2018'!$A:$A,E7))*E5 -> 24571.142 | F11: =SUM(SUMIFS('OECD TTL 2018'!$BC:$BC,'OECD TTL 2018'!$A:$A,F8),SUMIFS('OECD TTL 2018'!$BD:$BD,'OECD TTL 2018'!$A:$A,F8)) -> 4850.7 | G11: =SUM(SUMIFS('OECD TTL 2018'!$BC:$BC,'OECD TTL 2018'!$A:$A,G8),SUMIFS('OECD TTL 2018'!$BD:$BD,'OECD TTL 2018'!$A:$A,G8)) -> 51.9 | H11: =SUM(SUMIFS('OECD TTL 2018'!$BC:$BC,'OECD TTL 2018'!$A:$A,H8),SUMIFS('OECD TTL 2018'!$BD:$BD,'OECD TTL 2018'!$A:$A,H8)) -> 28781 | I11: =SUM(SUMIFS('OECD TTL 2018'!$BC:$BC,'OECD TTL 2018'!$A:$A,I8),SUMIFS('OECD TTL 2018'!$BD:$BD,'OECD TTL 2018'!$A:$A,I8)) -> 16092.2 | J11: =SUM(SUMIFS('OECD TTL 2018'!$BC:$BC,'OECD TTL 2018'!$A:$A,J8),SUMIFS('OECD TTL 2018'!$BD:$BD,'OECD TTL 2018'!$A:$A,J8)) -> 3929.6 | K11: =SUM(SUMIFS('OECD TTL 2018'!$BC:$BC,'OECD TTL 2018'!$A:$A,K8),SUMIFS('OECD TTL 2018'!$BD:$BD,'OECD TTL 2018'!$A:$A,K8)) -> 5824.1 | L11: =SUM(SUMIFS('OECD TTL 2018'!$BC:$BC,'OECD TTL 2018'!$A:$A,L8),SUMIFS('OECD TTL 2018'!$BD:$BD,'OECD TTL 2018'!$A:$A,L8)) -> 2052.9 | M11: =SUM(SUMIFS('OECD TTL 2018'!$BC:$BC,'OECD TTL 2018'!$A:$A,M8),SUMIFS('OECD TTL 2018'!$BD:$BD,'OECD TTL 2018'!$A:$A,M8)) -> 11999 | ... O11: =SUM(SUMIFS('OECD TTL 2018'!$BC:$BC,'OECD TTL 2018'!$A:$A,O8),SUMIFS('OECD TTL 2018'!$BD:$BD,'OECD TTL 2018'!$A:$A,O8)) -> 5796.8 | P11: =SUM(SUMIFS('OECD TTL 2018'!$BC:$BC,'OECD TTL 2018'!$A:$A,P7),SUMIFS('OECD TTL 2018'!$BD:$BD,'OECD TTL 2018'!$A:$A,P7))*P5 -> 240.41415 | Q11: =SUM(SUMIFS('OECD TTL 2018'!$BC:$BC,'OECD TTL 2018'!$A:$A,Q7),SUMIFS('OECD TTL 2018'!$BD:$BD,'OECD TTL 2018'!$A:$A,Q7))*Q5 -> 425.78585 | R11: =SUM(SUMIFS('OECD TTL 2018'!$BC:$BC,'OECD TTL 2018'!$A:$A,R7),SUMIFS('OECD TTL 2018'!$BD:$BD,'OECD TTL 2018'!$A:$A,R7))*R5 -> 2297.0591 | S11: =SUM(SUMIFS('OECD TTL 2018'!$BC:$BC,'OECD TTL 2018'!$A:$A,S7),SUMIFS('OECD TTL 2018'!$BD:$BD,'OECD TTL 2018'!$A:$A,S7))*S5 -> 7255.1409 | T11: =SUM(SUMIFS('OECD TTL 2018'!$BC:$BC,'OECD TTL 2018'!$A:$A,T8),SUMIFS('OECD TTL 2018'!$BD:$BD,'OECD TTL 2018'!$A:$A,T8)) -> 1699.8 | U11: =SUM(SUMIFS('OECD TTL 2018'!$BC:$BC,'OECD TTL 2018'!$A:$A,U8),SUMIFS('OECD TTL 2018'!$BD:$BD,'OECD TTL 2018'!$A:$A,U8)) -> 7532.4 | V11: =SUM(SUMIFS('OECD TTL 2018'!$BC:$BC,'OECD TTL 2018'!$A:$A,V8),SUMIFS('OECD TTL 2018'!$BD:$BD,'OECD TTL 2018'!$A:$A,V8)) -> 4965.2 | W11: =SUM(SUMIFS('OECD TTL 2018'!$BC:$BC,'OECD TTL 2018'!$A:$A,W8),SUMIFS('OECD TTL 2018'!$BD:$BD,'OECD TTL 2018'!$A:$A,W8)) -> 3422.2 | X11: =SUM(SUMIFS('OECD TTL 2018'!$BC:$BC,'OECD TTL 2018'!$A:$A,X8),SUMIFS('OECD TTL 2018'!$BD:$BD,'OECD TTL 2018'!$A:$A,X8)) -> 5257.6 | Y11: =SUM(SUMIFS('OECD TTL 2018'!$BC:$BC,'OECD TTL 2018'!$A:$A,Y8),SUMIFS('OECD TTL 2018'!$BD:$BD,'OECD TTL 2018'!$A:$A,Y8)) -> 2197.2 | Z11: =SUM(SUMIFS('OECD TTL 2018'!$BC:$BC,'OECD TTL 2018'!$A:$A,Z8),SUMIFS('OECD TTL 2018'!$BD:$BD,'OECD TTL 2018'!$A:$A,Z8)) -> 7826.3 | AA11: =SUM(SUMIFS('OECD TTL 2018'!$BC:$BC,'OECD TTL 2018'!$A:$A,AA7),SUMIFS('OECD TTL 2018'!$BD:$BD,'OECD TTL 2018'!$A:$A,AA7))*AA5 -> 0 | AB11: =SUM(SUMIFS('OECD TTL 2018'!$BC:$BC,'OECD TTL 2018'!$A:$A,AB7),SUMIFS('OECD TTL 2018'!$BD:$BD,'OECD TTL 2018'!$A:$A,AB7))*AB5 -> 0 | AC11: =SUM(SUMIFS('OECD TTL 2018'!$BC:$BC,'OECD TTL 2018'!$A:$A,AC8),SUMIFS('OECD TTL 2018'!$BD:$BD,'OECD TTL 2018'!$A:$A,AC8)) -> 0 | AD11: =SUM(SUMIFS('OECD TTL 2018'!$BC:$BC,'OECD TTL 2018'!$A:$A,AD8),SUMIFS('OECD TTL 2018'!$BD:$BD,'OECD TTL 2018'!$A:$A,AD8)) -> 0 | AE11: =SUM(SUMIFS('OECD TTL 2018'!$BC:$BC,'OECD TTL 2018'!$A:$A,AE8),SUMIFS('OECD TTL 2018'!$BD:$BD,'OECD TTL 2018'!$A:$A,AE8)) -> 17994.3 | AF11: =SUM(SUMIFS('OECD TTL 2018'!$BC:$BC,'OECD TTL 2018'!$A:$A,AF8),SUMIFS('OECD TTL 2018'!$BD:$BD,'OECD TTL 2018'!$A:$A,AF8)) -> 13251.8 | AG11: =SUM(SUMIFS('OECD TTL 2018'!$BC:$BC,'OECD TTL 2018'!$A:$A,AG8),SUMIFS('OECD TTL 2018'!$BD:$BD,'OECD TTL 2018'!$A:$A,AG8)) -> 3916.4 | AH11: =SUM(SUMIFS('OECD TTL 2018'!$BC:$BC,'OECD TTL 2018'!$A:$A,AH8),SUMIFS('OECD TTL 2018'!$BD:$BD,'OECD TTL 2018'!$A:$A,AH8)) -> 1663.1 | AI11: =SUM(SUMIFS('OECD TTL 2018'!$BC:$BC,'OECD TTL 2018'!$A:$A,AI8),SUMIFS('OECD TTL 2018'!$BD:$BD,'OECD TTL 2018'!$A:$A,AI8)) -> 403.5 | AJ11: =SUM(SUMIFS('OECD TTL 2018'!$BC:$BC,'OECD TTL 2018'!$A:$A,AJ8),SUMIFS('OECD TTL 2018'!$BD:$BD,'OECD TTL 2018'!$A:$A,AJ8)) -> 548.5 | ... AR11: =SUM(SUMIFS('OECD TTL 2018'!$BC:$BC,'OECD TTL 2018'!$A:$A,AR8),SUMIFS('OECD TTL 2018'!$BD:$BD,'OECD TTL 2018'!$A:$A,AR8)) -> 0
B12: Domestic Consumption | C12: =C9+C10-C11 -> 173714.4 | D12: =D9+D10-D11 -> 23591.142 | E12: =E9+E10-E11 -> 47579.858 | F12: =F9+F10-F11 -> 34910.7 | G12: =G9+G10-G11 -> 6429.7 | H12: =H9+H10-H11 -> 142733.5 | I12: =I9+I10-I11 -> 45607.8 | J12: =J9+J10-J11 -> 12363 | ... AR12: =AR9+AR10-AR11 -> 3763.2
B13: Imported Content Share of - new | C13: ='OECD ICESHR 2018'!H9/100 -> 0.057011453 | D13: =SUMIFS('OECD ICESHR 2018'!$E:$E,'OECD ICESHR 2018'!$B:$B,D$7)/100 -> 0.1346 | E13: =SUMIFS('OECD ICESHR 2018'!$E:$E,'OECD ICESHR 2018'!$B:$B,E$7)/100 -> 0.1346 | F13: =SUMIFS('OECD ICESHR 2018'!$E:$E,'OECD ICESHR 2018'!$B:$B,F$8)/100 -> 0.0855 | G13: =SUMIFS('OECD ICESHR 2018'!$E:$E,'OECD ICESHR 2018'!$B:$B,G$8)/100 -> 0.1122 | H13: =SUMIFS('OECD ICESHR 2018'!$E:$E,'OECD ICESHR 2018'!$B:$B,H$8)/100 -> 0.0955 | I13: =SUMIFS('OECD ICESHR 2018'!$E:$E,'OECD ICESHR 2018'!$B:$B,I$8)/100 -> 0.1965 | J13: =SUMIFS('OECD ICESHR 2018'!$E:$E,'OECD ICESHR 2018'!$B:$B,J$8)/100 -> 0.1304 | K13: =SUMIFS('OECD ICESHR 2018'!$E:$E,'OECD ICESHR 2018'!$B:$B,K$8)/100 -> 0.181 | L13: =SUMIFS('OECD ICESHR 2018'!$E:$E,'OECD ICESHR 2018'!$B:$B,L$8)/100 -> 0.2061 | M13: =SUMIFS('OECD ICESHR 2018'!$E:$E,'OECD ICESHR 2018'!$B:$B,M$8)/100 -> 0.209 | ... O13: =SUMIFS('OECD ICESHR 2018'!$E:$E,'OECD ICESHR 2018'!$B:$B,O$8)/100 -> 0.2658 | P13: =SUMIFS('OECD ICESHR 2018'!$E:$E,'OECD ICESHR 2018'!$B:$B,P$7)/100 -> 0.1625 | Q13: =SUMIFS('OECD ICESHR 2018'!$E:$E,'OECD ICESHR 2018'!$B:$B,Q$7)/100 -> 0.1625 | R13: =SUMIFS('OECD ICESHR 2018'!$E:$E,'OECD ICESHR 2018'!$B:$B,R$7)/100 -> 0.1087 | S13: =SUMIFS('OECD ICESHR 2018'!$E:$E,'OECD ICESHR 2018'!$B:$B,S$7)/100 -> 0.1087 | T13: =SUMIFS('OECD ICESHR 2018'!$E:$E,'OECD ICESHR 2018'!$B:$B,T$8)/100 -> 0.2428 | U13: =SUMIFS('OECD ICESHR 2018'!$E:$E,'OECD ICESHR 2018'!$B:$B,U$8)/100 -> 0.3005 | V13: =SUMIFS('OECD ICESHR 2018'!$E:$E,'OECD ICESHR 2018'!$B:$B,V$8)/100 -> 0.2697 | W13: =SUMIFS('OECD ICESHR 2018'!$E:$E,'OECD ICESHR 2018'!$B:$B,W$8)/100 -> 0.3358 | X13: =SUMIFS('OECD ICESHR 2018'!$E:$E,'OECD ICESHR 2018'!$B:$B,X$8)/100 -> 0.1546 | Y13: =SUMIFS('OECD ICESHR 2018'!$E:$E,'OECD ICESHR 2018'!$B:$B,Y$8)/100 -> 0.2185 | Z13: =SUMIFS('OECD ICESHR 2018'!$E:$E,'OECD ICESHR 2018'!$B:$B,Z$8)/100 -> 0.2074 | AA13: =SUMIFS('OECD ICESHR 2018'!$E:$E,'OECD ICESHR 2018'!$B:$B,AA$7)/100 -> 0.1372 | AB13: =SUMIFS('OECD ICESHR 2018'!$E:$E,'OECD ICESHR 2018'!$B:$B,AB$7)/100 -> 0.1372 | AC13: =SUMIFS('OECD ICESHR 2018'!$E:$E,'OECD ICESHR 2018'!$B:$B,AC$7)/100 -> 0.1372 | AD13: =SUMIFS('OECD ICESHR 2018'!$E:$E,'OECD ICESHR 2018'!$B:$B,AD$8)/100 -> 0.06755 | AE13: =SUMIFS('OECD ICESHR 2018'!$E:$E,'OECD ICESHR 2018'!$B:$B,AE$8)/100 -> 0.0749 | AF13: ='OECD ICESHR 2018'!H34/100 -> 0.11687833 | AG13: =SUMIFS('OECD ICESHR 2018'!$E:$E,'OECD ICESHR 2018'!$B:$B,AG$8)/100 -> 0.0765 | AH13: =SUMIFS('OECD ICESHR 2018'!$E:$E,'OECD ICESHR 2018'!$B:$B,AH$8)/100 -> 0.1337 | AI13: =SUMIFS('OECD ICESHR 2018'!$E:$E,'OECD ICESHR 2018'!$B:$B,AI$8)/100 -> 0.0398 | AJ13: =SUMIFS('OECD ICESHR 2018'!$E:$E,'OECD ICESHR 2018'!$B:$B,AJ$8)/100 -> 0.0939 | AK13: =SUMIFS('OECD ICESHR 2018'!$E:$E,'OECD ICESHR 2018'!$B:$B,AK$8)/100 -> 0.0225 | AL13: =SUMIFS('OECD ICESHR 2018'!$E:$E,'OECD ICESHR 2018'!$B:$B,AL$8)/100 -> 0.0326 | AM13: ='OECD ICESHR 2018'!H45/100 -> 0.065744532 | AN13: =SUMIFS('OECD ICESHR 2018'!$E:$E,'OECD ICESHR 2018'!$B:$B,AN$8)/100 -> 0.06755 | AO13: =SUMIFS('OECD ICESHR 2018'!$E:$E,'OECD ICESHR 2018'!$B:$B,AO$8)/100 -> 0.0542 | AP13: =SUMIFS('OECD ICESHR 2018'!$E:$E,'OECD ICESHR 2018'!$B:$B,AP$8)/100 -> 0.113 | AQ13: ='OECD ICESHR 2018'!H50/100 -> 0.082036764 | AR13: =SUMIFS('OECD ICESHR 2018'!$E:$E,'OECD ICESHR 2018'!$B:$B,AR$8)/100 -> 0
B14: Imported Content Share of Exports | C14: =C13 -> 0.057011453 | D14: =D13 -> 0.1346 | E14: =E13 -> 0.1346 | F14: =F13 -> 0.0855 | G14: =G13 -> 0.1122 | H14: =H13 -> 0.0955 | I14: =I13 -> 0.1965 | J14: =J13 -> 0.1304 | ... AR14: =AR13 -> 0
B15: Imports Consumed Domestically | C15: =C10*(1-C14) -> 7872.257 | D15: =D10*(1-D14) -> 371.42854 | E15: =E10*(1-E14) -> 10284.415 | F15: =F10*(1-F14) -> 846.91845 | G15: =G10*(1-G14) -> 56.55286 | H15: =H10*(1-H14) -> 10232.518 | I15: =I10*(1-I14) -> 7601.5117 | J15: =J10*(1-J14) -> 343.57896 | ... AR15: =AR10*(1-AR14) -> 0
B16: Domestic Production Consumed Domestically | C16: =C12-C15 -> 165842.14 | D16: =D12-D15 -> 23219.713 | E16: =E12-E15 -> 37295.443 | F16: =F12-F15 -> 34063.782 | G16: =G12-G15 -> 6373.1471 | H16: =H12-H15 -> 132500.98 | I16: =I12-I15 -> 38006.288 | J16: =J12-J15 -> 12019.421 | ... AR16: =AR12-AR15 -> 3763.2
B17: Domestic Content Share of Domestic Consumption | C17: =IF(ISERROR(C16/C12),1,C16/C12) -> 0.95468276 | D17: =IF(ISERROR(D16/D12),1,D16/D12) -> 0.98425559 | E17: =IF(ISERROR(E16/E12),1,E16/E12) -> 0.7838494 | F17: =IF(ISERROR(F16/F12),1,F16/F12) -> 0.97574043 | G17: =IF(ISERROR(G16/G12),1,G16/G12) -> 0.99120443 | H17: =IF(ISERROR(H16/H12),1,H16/H12) -> 0.92831033 | I17: =IF(ISERROR(I16/I12),1,I16/I12) -> 0.83332869 | J17: =IF(ISERROR(J16/J12),1,J16/J12) -> 0.97220909 | ... AR17: =IF(ISERROR(AR16/AR12),1,AR16/AR12) -> 1
B19: ISIC Consolidation
C20: ISIC 01T03 | D20: ISIC 05 | E20: ISIC 06 | F20: ISIC 07T08 | G20: ISIC 09 | H20: ISIC 10T12 | I20: ISIC 13T15 | J20: ISIC 16 | K20: ISIC 17T18 | L20: ISIC 19 | M20: ISIC 20 | N20: ISIC 21 | O20: ISIC 22 | P20: ISIC 231 | Q20: ISIC 239 | R20: ISIC 241 | S20: ISIC 242 | T20: ISIC 25 | U20: ISIC 26 | V20: ISIC 27 | W20: ISIC 28 | X20: ISIC 29 | Y20: ISIC 30 | Z20: ISIC 31T33 | AA20: ISIC 351 | AB20: ISIC 352T353 | AC20: ISIC 36T39 | AD20: ISIC 41T43 | AE20: ISIC 45T47 | AF20: ISIC 49T53 | AG20: ISIC 55T56 | AH20: ISIC 58T60 | AI20: ISIC 61 | AJ20: ISIC 62T63 | AK20: ISIC 64T66 | AL20: ISIC 68 | AM20: ISIC 69T82 | AN20: ISIC 84 | AO20: ISIC 85 | AP20: ISIC 86T88 | AQ20: ISIC 90T96 | AR20: ISIC 97T98
B21: Domestic Production | C21: =SUMIFS(9:9,$32:$32,C$20) -> 172842.2 | D21: =SUMIFS(9:9,$32:$32,D$20) -> 39873.201 | E21: =SUMIFS(9:9,$32:$32,E$20) -> 60266.999 | F21: =SUMIFS(9:9,$32:$32,F$20) -> 38835.3 | G21: =SUMIFS(9:9,$32:$32,G$20) -> 6417.9 | H21: =SUMIFS(9:9,$32:$32,H$20) -> 160201.6 | I21: =SUMIFS(9:9,$32:$32,I$20) -> 52239.5 | J21: =SUMIFS(9:9,$32:$32,J$20) -> 15897.5 | ... AR21: =SUMIFS(9:9,$32:$32,AR$20) -> 3763.2
B22: Imports | C22: =SUMIFS(10:10,$32:$32,C$20) -> 8348.2 | D22: =SUMIFS(10:10,$32:$32,D$20) -> 429.19869 | E22: =SUMIFS(10:10,$32:$32,E$20) -> 11884.001 | F22: =SUMIFS(10:10,$32:$32,F$20) -> 926.1 | G22: =SUMIFS(10:10,$32:$32,G$20) -> 63.7 | H22: =SUMIFS(10:10,$32:$32,H$20) -> 11312.9 | I22: =SUMIFS(10:10,$32:$32,I$20) -> 9460.5 | J22: =SUMIFS(10:10,$32:$32,J$20) -> 395.1 | ... AR22: =SUMIFS(10:10,$32:$32,AR$20) -> 0
B23: Exports | C23: =SUMIFS(11:11,$32:$32,C$20) -> 7476 | D23: =SUMIFS(11:11,$32:$32,D$20) -> 16711.258 | E23: =SUMIFS(11:11,$32:$32,E$20) -> 24571.142 | F23: =SUMIFS(11:11,$32:$32,F$20) -> 4850.7 | G23: =SUMIFS(11:11,$32:$32,G$20) -> 51.9 | H23: =SUMIFS(11:11,$32:$32,H$20) -> 28781 | I23: =SUMIFS(11:11,$32:$32,I$20) -> 16092.2 | J23: =SUMIFS(11:11,$32:$32,J$20) -> 3929.6 | ... AR23: =SUMIFS(11:11,$32:$32,AR$20) -> 0
B24: Domestic Consumption | C24: =SUMIFS(12:12,$32:$32,C$20) -> 173714.4 | D24: =SUMIFS(12:12,$32:$32,D$20) -> 23591.142 | E24: =SUMIFS(12:12,$32:$32,E$20) -> 47579.858 | F24: =SUMIFS(12:12,$32:$32,F$20) -> 34910.7 | G24: =SUMIFS(12:12,$32:$32,G$20) -> 6429.7 | H24: =SUMIFS(12:12,$32:$32,H$20) -> 142733.5 | I24: =SUMIFS(12:12,$32:$32,I$20) -> 45607.8 | J24: =SUMIFS(12:12,$32:$32,J$20) -> 12363 | ... AR24: =SUMIFS(12:12,$32:$32,AR$20) -> 3763.2
B25: Imported Content Share of Exports | C25: =AVERAGEIF($C$32:$AR$32,C8,$C$14:$AR$14) -> 0.057011453 | D25: =AVERAGEIF($C$32:$AR$32,D8,$C$14:$AR$14) -> 0.1346 | E25: =AVERAGEIF($C$32:$AR$32,E8,$C$14:$AR$14) -> 0.1346 | F25: =AVERAGEIF($C$32:$AR$32,F8,$C$14:$AR$14) -> 0.0855 | G25: =AVERAGEIF($C$32:$AR$32,G8,$C$14:$AR$14) -> 0.1122 | H25: =AVERAGEIF($C$32:$AR$32,H8,$C$14:$AR$14) -> 0.0955 | I25: =AVERAGEIF($C$32:$AR$32,I8,$C$14:$AR$14) -> 0.1965 | J25: =AVERAGEIF($C$32:$AR$32,J8,$C$14:$AR$14) -> 0.1304 | ... AR25: =AVERAGEIF($C$32:$AR$32,AR8,$C$14:$AR$14) -> 0
B26: Imports Consumed Domestically | C26: =C22*(1-C25) -> 7872.257 | D26: =D22*(1-D25) -> 371.42854 | E26: =E22*(1-E25) -> 10284.415 | F26: =F22*(1-F25) -> 846.91845 | G26: =G22*(1-G25) -> 56.55286 | H26: =H22*(1-H25) -> 10232.518 | I26: =I22*(1-I25) -> 7601.5117 | J26: =J22*(1-J25) -> 343.57896 | ... AR26: =AR22*(1-AR25) -> 0
B27: Domestic Production Consumed Domestically | C27: =C24-C26 -> 165842.14 | D27: =D24-D26 -> 23219.713 | E27: =E24-E26 -> 37295.443 | F27: =F24-F26 -> 34063.782 | G27: =G24-G26 -> 6373.1471 | H27: =H24-H26 -> 132500.98 | I27: =I24-I26 -> 38006.288 | J27: =J24-J26 -> 12019.421 | ... AR27: =AR24-AR26 -> 3763.2
B28: Domestic Content Share of Domestic Consumption | C28: =IF(ISERROR(C27/C24),1,C27/C24) -> 0.95468276 | D28: =IF(ISERROR(D27/D24),1,D27/D24) -> 0.98425559 | E28: =IF(ISERROR(E27/E24),1,E27/E24) -> 0.7838494 | F28: =IF(ISERROR(F27/F24),1,F27/F24) -> 0.97574043 | G28: =IF(ISERROR(G27/G24),1,G27/G24) -> 0.99120443 | H28: =IF(ISERROR(H27/H24),1,H27/H24) -> 0.92831033 | I28: =IF(ISERROR(I27/I24),1,I27/I24) -> 0.83332869 | J28: =IF(ISERROR(J27/J24),1,J27/J24) -> 0.97220909 | ... AR28: =IF(ISERROR(AR27/AR24),1,AR27/AR24) -> 1
B30: ISIC Consolidation
B31: Default EPS ISIC Groupings | C31: ISIC 01T03 | D31: ISIC 05 | E31: ISIC 06 | F31: ISIC 07T08 | G31: ISIC 09 | H31: ISIC 10T12 | I31: ISIC 13T15 | J31: ISIC 16 | K31: ISIC 17T18 | L31: ISIC 19 | M31: ISIC 20 | N31: ISIC 21 | O31: ISIC 22 | P31: ISIC 231 | Q31: ISIC 239 | R31: ISIC 241 | S31: ISIC 242 | T31: ISIC 25 | U31: ISIC 26 | V31: ISIC 27 | W31: ISIC 28 | X31: ISIC 29 | Y31: ISIC 30 | Z31: ISIC 31T33 | AA31: ISIC 351 | AB31: ISIC 352T353 | AC31: ISIC 36T39 | AD31: ISIC 41T43 | AE31: ISIC 45T47 | AF31: ISIC 49T53 | AG31: ISIC 55T56 | AH31: ISIC 58T60 | AI31: ISIC 61 | AJ31: ISIC 62T63 | AK31: ISIC 64T66 | AL31: ISIC 68 | AM31: ISIC 69T82 | AN31: ISIC 84 | AO31: ISIC 85 | AP31: ISIC 86T88 | AQ31: ISIC 90T96 | AR31: ISIC 97T98
B32: Indonesia ISIC Groupings | C32: ISIC 01T03 | D32: ISIC 05 | E32: ISIC 06 | F32: ISIC 07T08 | G32: ISIC 09 | H32: ISIC 10T12 | I32: ISIC 13T15 | J32: ISIC 16 | K32: ISIC 17T18 | L32: ISIC 19 | M32: ISIC 20 | N32: ISIC 21 | O32: ISIC 31T33 | P32: ISIC 239 | Q32: ISIC 239 | R32: ISIC 241 | S32: ISIC 242 | T32: ISIC 25 | U32: ISIC 25 | V32: ISIC 25 | W32: ISIC 25 | X32: ISIC 29 | Y32: ISIC 29 | Z32: ISIC 31T33 | AA32: ISIC 351 | AB32: ISIC 352T353 | AC32: ISIC 36T39 | AD32: ISIC 41T43 | AE32: ISIC 45T47 | AF32: ISIC 49T53 | AG32: ISIC 55T56 | AH32: ISIC 58T60 | AI32: ISIC 61 | AJ32: ISIC 62T63 | AK32: ISIC 64T66 | AL32: ISIC 68 | AM32: ISIC 69T82 | AN32: ISIC 84 | AO32: ISIC 85 | AP32: ISIC 86T88 | AQ32: ISIC 90T96 | AR32: ISIC 97T98
C34: =C31=C32 -> TRUE | D34: =D31=D32 -> TRUE | E34: =E31=E32 -> TRUE | F34: =F31=F32 -> TRUE | G34: =G31=G32 -> TRUE | H34: =H31=H32 -> TRUE | I34: =I31=I32 -> TRUE | J34: =J31=J32 -> TRUE | ... AR34: =AR31=AR32 -> TRUE
B37: BESoP
B38: Exports share of production | C38: =IFERROR(C23/C21,0) -> 0.043253326 | D38: =IFERROR(D23/D21,0) -> 0.41911002 | E38: =IFERROR(E23/E21,0) -> 0.40770475 | F38: =IFERROR(F23/F21,0) -> 0.1249044 | G38: =IFERROR(G23/G21,0) -> 0.0080867574 | H38: =IFERROR(H23/H21,0) -> 0.17965488 | I38: =IFERROR(I23/I21,0) -> 0.30804659 | J38: =IFERROR(J23/J21,0) -> 0.24718352 | ... AR38: =IFERROR(AR23/AR21,0) -> 0

Sheet isic groups
A1: ISIC used | B1: ISIC Group | E1: bifubc sector used | F1: bifubc sector grouped
A2: ISIC 01T03 | E2: agriculture and forestry 01T03
A3: ISIC 239 | B3: ISIC 231 | E3: cement and other nonmetallic minerals 239 | F3: glass and glass products 231
A4: ISIC 20 | E4: chemicals 20
A5: ISIC 05 | E5: coal mining 05
A6: ISIC 41T43 | E6: construction 41T43
A7: ISIC 352T353 | E7: energy pipelines and gas processing 352T353
A8: ISIC 10T12 | E8: food beverage and tobacco 10T12
A9: ISIC 241 | E9: iron and steel 241
A10: ISIC 25 | B10: ISIC 26 | C10: ISIC 27 | D10: ISIC 28 | E10: metal products except machinery and vehicles 25 | F10: computers and electronics 26 | G10: appliances and electrical equipment 27 | H10: other machinery 28
A11: ISIC 06 | E11: oil and gas extraction 06
A12: ISIC 31T33 | B12: ISIC 22 | E12: other manufacturing 31T33 | F12: rubber and plastic products 22
A13: ISIC 242 | E13: other metals 242
A14: ISIC 07T08 | E14: other mining and quarrying 07T08
A15: ISIC 17T18 | E15: pulp paper and printing 17T18
A16: ISIC 19 | E16: refined petroleum and coke 19
A17: ISIC 29 | B17: ISIC 30 | E17: road vehicles 29 | F17: nonroad vehicles 30
A18: ISIC 13T15 | E18: textiles apparel and leather 13T15
A19: ISIC 16 | E19: wood products 16

Sheet ISIC Code Mapping
B1: Exiobase Sector Code | C1: ISIC Code
A2: Paddy rice | B2: 1 | C2: ISIC 01T03
A3: Wheat | B3: 2 | C3: ISIC 01T03
A4: Cereal grains nec | B4: 3 | C4: ISIC 01T03
A5: Vegetables, fruit, nuts | B5: 4 | C5: ISIC 01T03
A6: Oil seeds | B6: 5 | C6: ISIC 01T03
A7: Sugar cane, sugar beet | B7: 6 | C7: ISIC 01T03
A8: Plant-based fibers | B8: 7 | C8: ISIC 01T03
A9: Crops nec | B9: 8 | C9: ISIC 01T03
A10: Cattle | B10: 9 | C10: ISIC 01T03
A11: Pigs | B11: 10 | C11: ISIC 01T03
A12: Poultry | B12: 11 | C12: ISIC 01T03
A13: Meat animals nec | B13: 12 | C13: ISIC 01T03
... A200: Private households with employed persons (95) | B200: 199 | C200: ISIC 97T98
A201: Extra-territorial organizations and bodies | B201: 200

Sheet BDCSoCbIC
A1: Unit: dimensionless (%) | B1: ISIC 01T03 | C1: ISIC 05 | D1: ISIC 06 | E1: ISIC 07T08 | F1: ISIC 09 | G1: ISIC 10T12 | H1: ISIC 13T15 | I1: ISIC 16 | J1: ISIC 17T18 | K1: ISIC 19 | L1: ISIC 20 | M1: ISIC 21 | N1: ISIC 22 | O1: ISIC 231 | P1: ISIC 239 | Q1: ISIC 241 | R1: ISIC 242 | S1: ISIC 25 | T1: ISIC 26 | U1: ISIC 27 | V1: ISIC 28 | W1: ISIC 29 | X1: ISIC 30 | Y1: ISIC 31T33 | Z1: ISIC 351 | AA1: ISIC 352T353 | AB1: ISIC 36T39 | AC1: ISIC 41T43 | AD1: ISIC 45T47 | AE1: ISIC 49T53 | AF1: ISIC 55T56 | AG1: ISIC 58T60 | AH1: ISIC 61 | AI1: ISIC 62T63 | AJ1: ISIC 64T66 | AK1: ISIC 68 | AL1: ISIC 69T82 | AM1: ISIC 84 | AN1: ISIC 85 | AO1: ISIC 86T88 | AP1: ISIC 90T96 | AQ1: ISIC 97T98
A2: Percent of Consumption that is Domestic Content | B2: =Calculations!C28 -> 0.95468276 | C2: =Calculations!D28 -> 0.98425559 | D2: =Calculations!E28 -> 0.7838494 | E2: =Calculations!F28 -> 0.97574043 | F2: =Calculations!G28 -> 0.99120443 | G2: =Calculations!H28 -> 0.92831033 | H2: =Calculations!I28 -> 0.83332869 | I2: =Calculations!J28 -> 0.97220909 | ... AQ2: =Calculations!AR28 -> 1

Sheet BESoP
A1: Unit: dimensionless (%) | B1: ISIC 01T03 | C1: ISIC 05 | D1: ISIC 06 | E1: ISIC 07T08 | F1: ISIC 09 | G1: ISIC 10T12 | H1: ISIC 13T15 | I1: ISIC 16 | J1: ISIC 17T18 | K1: ISIC 19 | L1: ISIC 20 | M1: ISIC 21 | N1: ISIC 22 | O1: ISIC 231 | P1: ISIC 239 | Q1: ISIC 241 | R1: ISIC 242 | S1: ISIC 25 | T1: ISIC 26 | U1: ISIC 27 | V1: ISIC 28 | W1: ISIC 29 | X1: ISIC 30 | Y1: ISIC 31T33 | Z1: ISIC 351 | AA1: ISIC 352T353 | AB1: ISIC 36T39 | AC1: ISIC 41T43 | AD1: ISIC 45T47 | AE1: ISIC 49T53 | AF1: ISIC 55T56 | AG1: ISIC 58T60 | AH1: ISIC 61 | AI1: ISIC 62T63 | AJ1: ISIC 64T66 | AK1: ISIC 68 | AL1: ISIC 69T82 | AM1: ISIC 84 | AN1: ISIC 85 | AO1: ISIC 86T88 | AP1: ISIC 90T96 | AQ1: ISIC 97T98
A2: Export Share of Production | B2: =SUMIFS(Calculations!$C$38:$AR$38,Calculations!$C$20:$AR$20,BESoP!B1) -> 0.043253326 | C2: =SUMIFS(Calculations!$C$38:$AR$38,Calculations!$C$20:$AR$20,BESoP!C1) -> 0.41911002 | D2: =SUMIFS(Calculations!$C$38:$AR$38,Calculations!$C$20:$AR$20,BESoP!D1) -> 0.40770475 | E2: =SUMIFS(Calculations!$C$38:$AR$38,Calculations!$C$20:$AR$20,BESoP!E1) -> 0.1249044 | F2: =SUMIFS(Calculations!$C$38:$AR$38,Calculations!$C$20:$AR$20,BESoP!F1) -> 0.0080867574 | G2: =SUMIFS(Calculations!$C$38:$AR$38,Calculations!$C$20:$AR$20,BESoP!G1) -> 0.17965488 | H2: =SUMIFS(Calculations!$C$38:$AR$38,Calculations!$C$20:$AR$20,BESoP!H1) -> 0.30804659 | I2: =SUMIFS(Calculations!$C$38:$AR$38,Calculations!$C$20:$AR$20,BESoP!I1) -> 0.24718352 | ... AQ2: =SUMIFS(Calculations!$C$38:$AR$38,Calculations!$C$20:$AR$20,BESoP!AQ1) -> 0
