Workbook
Name asdf: [1]About!$A$113
Name cpi_2010to2012: [2]About!#REF!
Name cpi_2014to2012: [2]About!#REF!
Name cpi_2017to2012: [2]About!$A$120
Name cpi_2018to2012: [2]About!$A$121
Name cpi_2019to2012: [2]About!$A$122
Name cpi_2020to2012: [2]About!$A$123
Name cpi_2021to2012: [2]About!$A$124
Name cpi_2022to2012: [2]About!$A$125
Name H2_kg_to_MMBtu: [3]Constants!$D$7
Name kWh_to_Btu: [3]Constants!$D$4

Sheet About
A1: SYBCbVT Start Year Battery Capacity by Vehicle Type
A3: Sources: | B3: motorbikes (2- and 3-wheelers)
B4: IRENA
B5: 2017
B6: Electricity Storage and Renewables: Costs and Markets to 2030
B7: http://www.irena.org/publications/2017/Oct/Electricity-storage-and-renewables-costs-and-markets
B8: Page 104
B10: All others
B11: Lindon, Henry (CleanTechnica)
B12: 2016
B13: Electric Bus Batteries Could Soon Overtake Consumer Electronic Batteries
B14: https://cleantechnica.com/2016/03/12/electric-bus-batteries-could-soon-overtake-consumer-electronic-batteries/
B15: Paragraph 2
B17: ICCT
B18: (Data on Request)
B19: 2022
B20: Estimated vehicle costs, battery sizes, and fleet distance traveled
B22: Breakdown by class 6/7
B23: Energy Information Administration (Data on Request)
B24: 2024
B25: Estimated freight vehicle miles traveled by vehicle class

Sheet Data
A1: 2- and 3-wheelers
A2: 0.7 | B2: kWh/vehicle
A3: =A2/10^3 -> 0.0007 | B3: MWh/vehicle
A5: buses
A6: 75 | B6: kWh/veh (low end of range)
A7: 300 | B7: kWh/veh (high end of range)
A8: =AVERAGE(A6:A7) -> 187.5 | B8: kWh/veh (avg)
A9: =A8/10^3 -> 0.1875 | B9: MWh/veh
A11: freight trucks
A12: 212 | B12: kWh/vehicle
A13: =A12/10^3 -> 0.212 | B13: MWh/vehicle
A15: battery electric passenger LDVs
A16: 70 | B16: kWh/veh (Tesla Model S, low end)
A17: 90 | B17: kWh/veh (Tesla Model S, high end)
A18: 60 | B18: kWh/veh (Chevy Bolt)
A19: =AVERAGE(A16:A18) -> 73.333333 | B19: kWh/veh (avg)
A20: =A19/10^3 -> 0.073333333 | B20: MWh/vehicle
A22: plug-in hybrid passenger LDVs
A23: 18.4 | B23: kWh/veh (Chevy Volt)
A24: 8.8 | B24: kWh/veh (Toyota Prius Prime)
A25: =AVERAGE(A23:A24) -> 13.6 | B25: kWh/veh (avg)
A26: =A25/10^3 -> 0.0136 | B26: MWh/vehicle

Sheet Pass LDVs
A1: ICE Sales Shares (from the report above, page 14, paragraph 2) | D1: Data here and below from an earlier ICCT 2017 report
A2: car | B2: 0.26967961 | D2: Source: Figure 4, Lutsey & Nicholas (2018) "Electric Vehicle Costs and Consumer Benefits in Colorado in the 2020-2030 Time Frame," International Council on Clean Transportation, https://theicct.org/wp-content/uploads/2021/06/ev_Colorado_cost_2020_20190613.pdf
A3: crossover | B3: 0.35313092
A4: SUV | B4: 0.230751
A5: pickup | B5: 0.14643847
A7: Annual US BEV sales by vehicle class and range
A8: Vehicle Type | B8: 2018 | C8: 2019 | D8: 2020 | E8: 2021 | F8: 2030
A9: Electric car (150 mile) | B9: 14775 | C9: 12365 | D9: 9564 | E9: 14239 | F9: 0
A10: Electric car (200 mile) | B10: 18019 | C10: 16550 | D10: 25173 | E10: 37438 | F10: 0
A11: Electric car (250 mile) | B11: 0 | C11: 0 | D11: 3 | E11: 27140 | F11: 0
A12: Electric car (300 mile) | B12: 164220 | C12: 158253 | D12: 109589 | E12: 164966 | F12: =B2*100 -> 26.967961
A13: Electric car (350 mile) | B13: 0 | C13: 0 | D13: 0 | E13: 0 | F13: 0
A14: Electric car (400 mile) | B14: 0 | C14: 0 | D14: 0 | E14: 125 | F14: 0
A15: Crossover (150 mile) | B15: 0 | C15: 2508 | D15: 2848 | E15: 8717 | F15: 0
A16: Crossover (200 mile) | B16: 0 | C16: 3603 | D16: 3116 | E16: 15328 | F16: 0
A17: Crossover (250 mile) | B17: 0 | C17: 0 | D17: 75400 | E17: 188400 | F17: 0
A18: Crossover (300 mile) | B18: 0 | C18: 0 | D18: 0 | E18: 0 | F18: =B3*100 -> 35.313092
A19: Crossover (350 mile) | B19: 0 | C19: 0 | D19: 0 | E19: 0 | F19: 0
A20: Crossover (400 mile) | B20: 0 | C20: 0 | D20: 0 | E20: 0 | F20: 0
A21: Sport utilty vehicle (150 mile) | B21: 0 | C21: 0 | D21: 0 | E21: 0 | F21: 0
A22: Sport utility vehicle (200 mile) | B22: 393 | C22: 7966 | D22: 8860 | E22: 27388 | F22: 0
A23: Sport utility vehicle (250 mile) | B23: 0 | C23: 0 | D23: 0 | E23: 0 | F23: 0
A24: Sport utility vehicle (300 mile) | B24: 24650 | C24: 18442 | D24: 16650 | E24: 1015 | F24: =B4*100 -> 23.0751
A25: Sport utility vehicle (350 mile) | B25: 0 | C25: 0 | D25: 0 | E25: 0 | F25: 0
A26: Sport utility vehicle (400 mile) | B26: 0 | C26: 0 | D26: 0 | E26: 0 | F26: 0
A27: Pickup (150 mile) | B27: 0 | C27: 0 | D27: 0 | E27: 0 | F27: 0
A28: Pickup (200 mile) | B28: 0 | C28: 0 | D28: 0 | E28: 76 | F28: 0
A29: Pickup (250 mile) | B29: 0 | C29: 0 | D29: 0 | E29: 0 | F29: 0
A30: Pickup (300 mile) | B30: 0 | C30: 0 | D30: 0 | E30: 913 | F30: =B5*100 -> 14.643847
A31: Pickup (350 mile) | B31: 0 | C31: 0 | D31: 0 | E31: 0 | F31: 0
A32: Pickup (400 mile) | B32: 0 | C32: 0 | D32: 0 | E32: 0 | F32: 0
A35: Annual US PHEV sales by vehicle class and range | B35: 2018 | C35: 2019 | D35: 2020 | E35: 2021 | F35: 2030
A36: PHEV car (20 mile) | B36: 51806 | C36: 39780 | D36: 25570 | E36: 39782 | F36: 0
A37: PHEV car (30 mile) | B37: 261 | C37: 42 | D37: 10 | E37: 18 | F37: 0
A38: PHEV car (40 mile) | B38: 18602 | C38: 10758 | D38: 7140 | E38: 30021 | F38: 0
A39: PHEV car (50 mile) | B39: 18306 | C39: 4493 | D39: 43 | E39: 16 | F39: =B2*100 -> 26.967961
A40: PHEV car (60 mile) | B40: 0 | C40: 0 | D40: 0 | E40: 99 | F40: 0
A41: PHEV car (70 mile) | B41: 0 | C41: 0 | D41: 0 | E41: 0 | F41: 0
A42: PHEV crossover (20 mile) | B42: 7892 | C42: 6846 | D42: 8713 | E42: 45098 | F42: 0
A43: PHEV crossover (30 mile) | B43: 0 | C43: 0 | D43: 27 | E43: 7201 | F43: 0
A44: PHEV crossover (40 mile) | B44: 0 | C44: 0 | D44: 0 | E44: 0 | F44: 0
A45: PHEV crossover (50 mile) | B45: 0 | C45: 0 | D45: 0 | E45: 0 | F45: =B3*100 -> 35.313092
A46: PHEV crossover (60 mile) | B46: 0 | C46: 0 | D46: 0 | E46: 0 | F46: 0
A47: PHEV crossover (70 mile) | B47: 0 | C47: 0 | D47: 0 | E47: 0 | F47: 0
A48: PHEV SUV (20 mile) | B48: 0 | C48: 78 | D48: 1843 | E48: 2901 | F48: 0
A49: PHEV SUV (30 mile) | B49: 7062 | C49: 5228 | D49: 5765 | E49: 15321 | F49: 0
A50: PHEV SUV (40 mile) | B50: 0 | C50: 0 | D50: 0 | E50: 0 | F50: 0
A51: PHEV SUV (50 mile) | B51: 0 | C51: 0 | D51: 0 | E51: 0 | F51: =B4*100 -> 23.0751
A52: PHEV SUV (60 mile) | B52: 596 | C52: 2906 | D52: 160 | E52: 0 | F52: 0
A53: PHEV SUV (70 mile) | B53: 0 | C53: 0 | D53: 0 | E53: 0 | F53: 0
A54: PHEV pickup (20 mile) | B54: 0 | C54: 0 | D54: 0 | E54: 0 | F54: 0
A55: PHEV pickup (30 mile) | B55: 0 | C55: 0 | D55: 0 | E55: 0 | F55: 0
A56: PHEV pickup (40 mile) | B56: 0 | C56: 0 | D56: 0 | E56: 0 | F56: 0
A57: PHEV pickup (50 mile) | B57: 0 | C57: 0 | D57: 0 | E57: 0 | F57: =B5*100 -> 14.643847
A58: PHEV pickup (60 mile) | B58: 0 | C58: 0 | D58: 0 | E58: 0 | F58: 0
A59: PHEV pickup (70 mile) | B59: 0 | C59: 0 | D59: 0 | E59: 0 | F59: 0
A61: We map onto historical ICE shares and weight within each group by the mileage share. We maintain the ICE mapping but assume a shift to all 300 mile vehicles by 2030.
A62: BEV Market Shares
C63: 2020 | D63: 2021 | E63: 2022 | F63: 2023 | G63: 2024 | H63: 2025 | I63: 2026 | J63: 2027 | K63: 2028 | L63: 2029 | M63: 2030 | N63: 2031 | O63: 2032 | P63: 2033 | Q63: 2034 | R63: 2035
A64: Electric car (150 mile) | C64: =D9/SUM(D$9:D$14)*$B$2 -> 0.017870392 | D64: =E9/SUM(E$9:E$14)*$B$2 -> 0.01574351 | E64: =($M64-$D64)/($M$63-$D$63)+D64 -> 0.013994231 | F64: =($M64-$D64)/($M$63-$D$63)+E64 -> 0.012244952 | G64: =($M64-$D64)/($M$63-$D$63)+F64 -> 0.010495673 | H64: =($M64-$D64)/($M$63-$D$63)+G64 -> 0.0087463942 | I64: =($M64-$D64)/($M$63-$D$63)+H64 -> 0.0069971154 | J64: =($M64-$D64)/($M$63-$D$63)+I64 -> 0.0052478365 | K64: =($M64-$D64)/($M$63-$D$63)+J64 -> 0.0034985577 | L64: =($M64-$D64)/($M$63-$D$63)+K64 -> 0.0017492788 | M64: =F9/SUM($F$9:$F$14)*$B$2 -> 0 | N64: =M64 -> 0 | O64: =N64 -> 0 | P64: =O64 -> 0 | Q64: =P64 -> 0 | R64: =Q64 -> 0
A65: Electric car (200 mile) | C65: =D10/SUM(D$9:D$14)*$B$2 -> 0.047035902 | D65: =E10/SUM(E$9:E$14)*$B$2 -> 0.041393743 | E65: =($M65-$D65)/($M$63-$D$63)+D65 -> 0.036794439 | F65: =($M65-$D65)/($M$63-$D$63)+E65 -> 0.032195134 | G65: =($M65-$D65)/($M$63-$D$63)+F65 -> 0.027595829 | H65: =($M65-$D65)/($M$63-$D$63)+G65 -> 0.022996524 | I65: =($M65-$D65)/($M$63-$D$63)+H65 -> 0.018397219 | J65: =($M65-$D65)/($M$63-$D$63)+I65 -> 0.013797914 | K65: =($M65-$D65)/($M$63-$D$63)+J65 -> 0.0091986096 | L65: =($M65-$D65)/($M$63-$D$63)+K65 -> 0.0045993048 | M65: =F10/SUM($F$9:$F$14)*$B$2 -> 0 | N65: =M65 -> 0 | O65: =N65 -> 0 | P65: =O65 -> 0 | Q65: =P65 -> 0 | R65: =Q65 -> 0
A66: Electric car (250 mile) | C66: =D11/SUM(D$9:D$14)*$B$2 -> 5.6055181e-06 | D66: =E11/SUM(E$9:E$14)*$B$2 -> 0.030007644 | E66: =($M66-$D66)/($M$63-$D$63)+D66 -> 0.026673462 | F66: =($M66-$D66)/($M$63-$D$63)+E66 -> 0.023339279 | G66: =($M66-$D66)/($M$63-$D$63)+F66 -> 0.020005096 | H66: =($M66-$D66)/($M$63-$D$63)+G66 -> 0.016670914 | I66: =($M66-$D66)/($M$63-$D$63)+H66 -> 0.013336731 | J66: =($M66-$D66)/($M$63-$D$63)+I66 -> 0.010002548 | K66: =($M66-$D66)/($M$63-$D$63)+J66 -> 0.0066683654 | L66: =($M66-$D66)/($M$63-$D$63)+K66 -> 0.0033341827 | M66: =F11/SUM($F$9:$F$14)*$B$2 -> 0 | N66: =M66 -> 0 | O66: =N66 -> 0 | P66: =O66 -> 0 | Q66: =P66 -> 0 | R66: =Q66 -> 0
A67: Electric car (300 mile) | C67: =D12/SUM(D$9:D$14)*$B$2 -> 0.20476771 | D67: =E12/SUM(E$9:E$14)*$B$2 -> 0.1823965 | E67: =($M67-$D67)/($M$63-$D$63)+D67 -> 0.19209463 | F67: =($M67-$D67)/($M$63-$D$63)+E67 -> 0.20179275 | G67: =($M67-$D67)/($M$63-$D$63)+F67 -> 0.21149087 | H67: =($M67-$D67)/($M$63-$D$63)+G67 -> 0.22118899 | I67: =($M67-$D67)/($M$63-$D$63)+H67 -> 0.23088712 | J67: =($M67-$D67)/($M$63-$D$63)+I67 -> 0.24058524 | K67: =($M67-$D67)/($M$63-$D$63)+J67 -> 0.25028336 | L67: =($M67-$D67)/($M$63-$D$63)+K67 -> 0.25998148 | M67: =F12/SUM($F$9:$F$14)*$B$2 -> 0.26967961 | N67: =M67 -> 0.26967961 | O67: =N67 -> 0.26967961 | P67: =O67 -> 0.26967961 | Q67: =P67 -> 0.26967961 | R67: =Q67 -> 0.26967961
A68: Electric car (350 mile) | C68: =D13/SUM(D$9:D$14)*$B$2 -> 0 | D68: =E13/SUM(E$9:E$14)*$B$2 -> 0 | E68: =($M68-$D68)/($M$63-$D$63)+D68 -> 0 | F68: =($M68-$D68)/($M$63-$D$63)+E68 -> 0 | G68: =($M68-$D68)/($M$63-$D$63)+F68 -> 0 | H68: =($M68-$D68)/($M$63-$D$63)+G68 -> 0 | I68: =($M68-$D68)/($M$63-$D$63)+H68 -> 0 | J68: =($M68-$D68)/($M$63-$D$63)+I68 -> 0 | K68: =($M68-$D68)/($M$63-$D$63)+J68 -> 0 | L68: =($M68-$D68)/($M$63-$D$63)+K68 -> 0 | M68: =F13/SUM($F$9:$F$14)*$B$2 -> 0 | N68: =M68 -> 0 | O68: =N68 -> 0 | P68: =O68 -> 0 | Q68: =P68 -> 0 | R68: =Q68 -> 0
A69: Electric car (400 mile) | C69: =D14/SUM(D$9:D$14)*$B$2 -> 0 | D69: =E14/SUM(E$9:E$14)*$B$2 -> 0.00013820765 | E69: =($M69-$D69)/($M$63-$D$63)+D69 -> 0.00012285124 | F69: =($M69-$D69)/($M$63-$D$63)+E69 -> 0.00010749484 | G69: =($M69-$D69)/($M$63-$D$63)+F69 -> 9.2138432e-05 | H69: =($M69-$D69)/($M$63-$D$63)+G69 -> 7.6782027e-05 | I69: =($M69-$D69)/($M$63-$D$63)+H69 -> 6.1425621e-05 | J69: =($M69-$D69)/($M$63-$D$63)+I69 -> 4.6069216e-05 | K69: =($M69-$D69)/($M$63-$D$63)+J69 -> 3.0712811e-05 | L69: =($M69-$D69)/($M$63-$D$63)+K69 -> 1.5356405e-05 | M69: =F14/SUM($F$9:$F$14)*$B$2 -> 0 | N69: =M69 -> 0 | O69: =N69 -> 0 | P69: =O69 -> 0 | Q69: =P69 -> 0 | R69: =Q69 -> 0
A70: Crossover (150 mile) | C70: =D15/SUM(D$15:D$20)*$B$3 -> 0.012360711 | D70: =E15/SUM(E$15:E$20)*$B$3 -> 0.014489596 | E70: =($M70-$D70)/($M$63-$D$63)+D70 -> 0.012879641 | F70: =($M70-$D70)/($M$63-$D$63)+E70 -> 0.011269686 | G70: =($M70-$D70)/($M$63-$D$63)+F70 -> 0.0096597307 | H70: =($M70-$D70)/($M$63-$D$63)+G70 -> 0.0080497756 | I70: =($M70-$D70)/($M$63-$D$63)+H70 -> 0.0064398205 | J70: =($M70-$D70)/($M$63-$D$63)+I70 -> 0.0048298654 | K70: =($M70-$D70)/($M$63-$D$63)+J70 -> 0.0032199102 | L70: =($M70-$D70)/($M$63-$D$63)+K70 -> 0.0016099551 | M70: =F15/SUM($F$15:$F$20)*$B$3 -> 0 | N70: =M70 -> 0 | O70: =N70 -> 0 | P70: =O70 -> 0 | Q70: =P70 -> 0 | R70: =Q70 -> 0
A71: Crossover (200 mile) | C71: =D16/SUM(D$15:D$20)*$B$3 -> 0.013523867 | D71: =E16/SUM(E$15:E$20)*$B$3 -> 0.025478551 | E71: =($M71-$D71)/($M$63-$D$63)+D71 -> 0.022647601 | F71: =($M71-$D71)/($M$63-$D$63)+E71 -> 0.019816651 | G71: =($M71-$D71)/($M$63-$D$63)+F71 -> 0.016985701 | H71: =($M71-$D71)/($M$63-$D$63)+G71 -> 0.014154751 | I71: =($M71-$D71)/($M$63-$D$63)+H71 -> 0.0113238 | J71: =($M71-$D71)/($M$63-$D$63)+I71 -> 0.0084928503 | K71: =($M71-$D71)/($M$63-$D$63)+J71 -> 0.0056619002 | L71: =($M71-$D71)/($M$63-$D$63)+K71 -> 0.0028309501 | M71: =F16/SUM($F$15:$F$20)*$B$3 -> 0 | N71: =M71 -> 0 | O71: =N71 -> 0 | P71: =O71 -> 0 | Q71: =P71 -> 0 | R71: =Q71 -> 0
A72: Crossover (250 mile) | C72: =D17/SUM(D$15:D$20)*$B$3 -> 0.32724634 | D72: =E17/SUM(E$15:E$20)*$B$3 -> 0.31316277 | E72: =($M72-$D72)/($M$63-$D$63)+D72 -> 0.27836691 | F72: =($M72-$D72)/($M$63-$D$63)+E72 -> 0.24357105 | G72: =($M72-$D72)/($M$63-$D$63)+F72 -> 0.20877518 | H72: =($M72-$D72)/($M$63-$D$63)+G72 -> 0.17397932 | I72: =($M72-$D72)/($M$63-$D$63)+H72 -> 0.13918346 | J72: =($M72-$D72)/($M$63-$D$63)+I72 -> 0.10438759 | K72: =($M72-$D72)/($M$63-$D$63)+J72 -> 0.069591728 | L72: =($M72-$D72)/($M$63-$D$63)+K72 -> 0.034795864 | M72: =F17/SUM($F$15:$F$20)*$B$3 -> 0 | N72: =M72 -> 0 | O72: =N72 -> 0 | P72: =O72 -> 0 | Q72: =P72 -> 0 | R72: =Q72 -> 0
A73: Crossover (300 mile) | C73: =D18/SUM(D$15:D$20)*$B$3 -> 0 | D73: =E18/SUM(E$15:E$20)*$B$3 -> 0 | E73: =($M73-$D73)/($M$63-$D$63)+D73 -> 0.039236769 | F73: =($M73-$D73)/($M$63-$D$63)+E73 -> 0.078473538 | G73: =($M73-$D73)/($M$63-$D$63)+F73 -> 0.11771031 | H73: =($M73-$D73)/($M$63-$D$63)+G73 -> 0.15694708 | I73: =($M73-$D73)/($M$63-$D$63)+H73 -> 0.19618384 | J73: =($M73-$D73)/($M$63-$D$63)+I73 -> 0.23542061 | K73: =($M73-$D73)/($M$63-$D$63)+J73 -> 0.27465738 | L73: =($M73-$D73)/($M$63-$D$63)+K73 -> 0.31389415 | M73: =F18/SUM($F$15:$F$20)*$B$3 -> 0.35313092 | N73: =M73 -> 0.35313092 | O73: =N73 -> 0.35313092 | P73: =O73 -> 0.35313092 | Q73: =P73 -> 0.35313092 | R73: =Q73 -> 0.35313092
A74: Crossover (350 mile) | C74: =D19/SUM(D$15:D$20)*$B$3 -> 0 | D74: =E19/SUM(E$15:E$20)*$B$3 -> 0 | E74: =($M74-$D74)/($M$63-$D$63)+D74 -> 0 | F74: =($M74-$D74)/($M$63-$D$63)+E74 -> 0 | G74: =($M74-$D74)/($M$63-$D$63)+F74 -> 0 | H74: =($M74-$D74)/($M$63-$D$63)+G74 -> 0 | I74: =($M74-$D74)/($M$63-$D$63)+H74 -> 0 | J74: =($M74-$D74)/($M$63-$D$63)+I74 -> 0 | K74: =($M74-$D74)/($M$63-$D$63)+J74 -> 0 | L74: =($M74-$D74)/($M$63-$D$63)+K74 -> 0 | M74: =F19/SUM($F$15:$F$20)*$B$3 -> 0 | N74: =M74 -> 0 | O74: =N74 -> 0 | P74: =O74 -> 0 | Q74: =P74 -> 0 | R74: =Q74 -> 0
A75: Crossover (400 mile) | C75: =D20/SUM(D$15:D$20)*$B$3 -> 0 | D75: =E20/SUM(E$15:E$20)*$B$3 -> 0 | E75: =($M75-$D75)/($M$63-$D$63)+D75 -> 0 | F75: =($M75-$D75)/($M$63-$D$63)+E75 -> 0 | G75: =($M75-$D75)/($M$63-$D$63)+F75 -> 0 | H75: =($M75-$D75)/($M$63-$D$63)+G75 -> 0 | I75: =($M75-$D75)/($M$63-$D$63)+H75 -> 0 | J75: =($M75-$D75)/($M$63-$D$63)+I75 -> 0 | K75: =($M75-$D75)/($M$63-$D$63)+J75 -> 0 | L75: =($M75-$D75)/($M$63-$D$63)+K75 -> 0 | M75: =F20/SUM($F$15:$F$20)*$B$3 -> 0 | N75: =M75 -> 0 | O75: =N75 -> 0 | P75: =O75 -> 0 | Q75: =P75 -> 0 | R75: =Q75 -> 0
A76: Sport utilty vehicle (150 mile) | C76: =D21/SUM(D$21:D$26)*$B$4 -> 0 | D76: =E21/SUM(E$21:E$26)*$B$4 -> 0 | E76: =($M76-$D76)/($M$63-$D$63)+D76 -> 0 | F76: =($M76-$D76)/($M$63-$D$63)+E76 -> 0 | G76: =($M76-$D76)/($M$63-$D$63)+F76 -> 0 | H76: =($M76-$D76)/($M$63-$D$63)+G76 -> 0 | I76: =($M76-$D76)/($M$63-$D$63)+H76 -> 0 | J76: =($M76-$D76)/($M$63-$D$63)+I76 -> 0 | K76: =($M76-$D76)/($M$63-$D$63)+J76 -> 0 | L76: =($M76-$D76)/($M$63-$D$63)+K76 -> 0 | M76: =F21/SUM($F$21:$F$26)*$B$4 -> 0 | N76: =M76 -> 0 | O76: =N76 -> 0 | P76: =O76 -> 0 | Q76: =P76 -> 0 | R76: =Q76 -> 0
A77: Sport utility vehicle (200 mile) | C77: =D22/SUM(D$21:D$26)*$B$4 -> 0.080143231 | D77: =E22/SUM(E$21:E$26)*$B$4 -> 0.22250496 | E77: =($M77-$D77)/($M$63-$D$63)+D77 -> 0.19778218 | F77: =($M77-$D77)/($M$63-$D$63)+E77 -> 0.17305941 | G77: =($M77-$D77)/($M$63-$D$63)+F77 -> 0.14833664 | H77: =($M77-$D77)/($M$63-$D$63)+G77 -> 0.12361387 | I77: =($M77-$D77)/($M$63-$D$63)+H77 -> 0.098891092 | J77: =($M77-$D77)/($M$63-$D$63)+I77 -> 0.074168319 | K77: =($M77-$D77)/($M$63-$D$63)+J77 -> 0.049445546 | L77: =($M77-$D77)/($M$63-$D$63)+K77 -> 0.024722773 | M77: =F22/SUM($F$21:$F$26)*$B$4 -> 0 | N77: =M77 -> 0 | O77: =N77 -> 0 | P77: =O77 -> 0 | Q77: =P77 -> 0 | R77: =Q77 -> 0
A78: Sport utility vehicle (250 mile) | C78: =D23/SUM(D$21:D$26)*$B$4 -> 0 | D78: =E23/SUM(E$21:E$26)*$B$4 -> 0 | E78: =($M78-$D78)/($M$63-$D$63)+D78 -> 0 | F78: =($M78-$D78)/($M$63-$D$63)+E78 -> 0 | G78: =($M78-$D78)/($M$63-$D$63)+F78 -> 0 | H78: =($M78-$D78)/($M$63-$D$63)+G78 -> 0 | I78: =($M78-$D78)/($M$63-$D$63)+H78 -> 0 | J78: =($M78-$D78)/($M$63-$D$63)+I78 -> 0 | K78: =($M78-$D78)/($M$63-$D$63)+J78 -> 0 | L78: =($M78-$D78)/($M$63-$D$63)+K78 -> 0 | M78: =F23/SUM($F$21:$F$26)*$B$4 -> 0 | N78: =M78 -> 0 | O78: =N78 -> 0 | P78: =O78 -> 0 | Q78: =P78 -> 0 | R78: =Q78 -> 0
A79: Sport utility vehicle (300 mile) | C79: =D24/SUM(D$21:D$26)*$B$4 -> 0.15060777 | D79: =E24/SUM(E$21:E$26)*$B$4 -> 0.0082460396 | E79: =($M79-$D79)/($M$63-$D$63)+D79 -> 0.032968813 | F79: =($M79-$D79)/($M$63-$D$63)+E79 -> 0.057691586 | G79: =($M79-$D79)/($M$63-$D$63)+F79 -> 0.082414359 | H79: =($M79-$D79)/($M$63-$D$63)+G79 -> 0.10713713 | I79: =($M79-$D79)/($M$63-$D$63)+H79 -> 0.1318599 | J79: =($M79-$D79)/($M$63-$D$63)+I79 -> 0.15658268 | K79: =($M79-$D79)/($M$63-$D$63)+J79 -> 0.18130545 | L79: =($M79-$D79)/($M$63-$D$63)+K79 -> 0.20602822 | M79: =F24/SUM($F$21:$F$26)*$B$4 -> 0.230751 | N79: =M79 -> 0.230751 | O79: =N79 -> 0.230751 | P79: =O79 -> 0.230751 | Q79: =P79 -> 0.230751 | R79: =Q79 -> 0.230751
A80: Sport utility vehicle (350 mile) | C80: =D25/SUM(D$21:D$26)*$B$4 -> 0 | D80: =E25/SUM(E$21:E$26)*$B$4 -> 0 | E80: =($M80-$D80)/($M$63-$D$63)+D80 -> 0 | F80: =($M80-$D80)/($M$63-$D$63)+E80 -> 0 | G80: =($M80-$D80)/($M$63-$D$63)+F80 -> 0 | H80: =($M80-$D80)/($M$63-$D$63)+G80 -> 0 | I80: =($M80-$D80)/($M$63-$D$63)+H80 -> 0 | J80: =($M80-$D80)/($M$63-$D$63)+I80 -> 0 | K80: =($M80-$D80)/($M$63-$D$63)+J80 -> 0 | L80: =($M80-$D80)/($M$63-$D$63)+K80 -> 0 | M80: =F25/SUM($F$21:$F$26)*$B$4 -> 0 | N80: =M80 -> 0 | O80: =N80 -> 0 | P80: =O80 -> 0 | Q80: =P80 -> 0 | R80: =Q80 -> 0
A81: Sport utility vehicle (400 mile) | C81: =D26/SUM(D$21:D$26)*$B$4 -> 0 | D81: =E26/SUM(E$21:E$26)*$B$4 -> 0 | E81: =($M81-$D81)/($M$63-$D$63)+D81 -> 0 | F81: =($M81-$D81)/($M$63-$D$63)+E81 -> 0 | G81: =($M81-$D81)/($M$63-$D$63)+F81 -> 0 | H81: =($M81-$D81)/($M$63-$D$63)+G81 -> 0 | I81: =($M81-$D81)/($M$63-$D$63)+H81 -> 0 | J81: =($M81-$D81)/($M$63-$D$63)+I81 -> 0 | K81: =($M81-$D81)/($M$63-$D$63)+J81 -> 0 | L81: =($M81-$D81)/($M$63-$D$63)+K81 -> 0 | M81: =F26/SUM($F$21:$F$26)*$B$4 -> 0 | N81: =M81 -> 0 | O81: =N81 -> 0 | P81: =O81 -> 0 | Q81: =P81 -> 0 | R81: =Q81 -> 0
A82: Pickup (150 mile) | C82: =D82 -> 0 | D82: =E27/SUM(E$27:E$32)*$B$5 -> 0 | E82: =($M82-$D82)/($M$63-$D$63)+D82 -> 0 | F82: =($M82-$D82)/($M$63-$D$63)+E82 -> 0 | G82: =($M82-$D82)/($M$63-$D$63)+F82 -> 0 | H82: =($M82-$D82)/($M$63-$D$63)+G82 -> 0 | I82: =($M82-$D82)/($M$63-$D$63)+H82 -> 0 | J82: =($M82-$D82)/($M$63-$D$63)+I82 -> 0 | K82: =($M82-$D82)/($M$63-$D$63)+J82 -> 0 | L82: =($M82-$D82)/($M$63-$D$63)+K82 -> 0 | M82: =F27/SUM($F$27:$F$32)*$B$5 -> 0 | N82: =M82 -> 0 | O82: =N82 -> 0 | P82: =O82 -> 0 | Q82: =P82 -> 0 | R82: =Q82 -> 0
A83: Pickup (200 mile) | C83: =D83 -> 0.011253108 | D83: =E28/SUM(E$27:E$32)*$B$5 -> 0.011253108 | E83: =($M83-$D83)/($M$63-$D$63)+D83 -> 0.010002763 | F83: =($M83-$D83)/($M$63-$D$63)+E83 -> 0.0087524175 | G83: =($M83-$D83)/($M$63-$D$63)+F83 -> 0.0075020722 | H83: =($M83-$D83)/($M$63-$D$63)+G83 -> 0.0062517268 | I83: =($M83-$D83)/($M$63-$D$63)+H83 -> 0.0050013815 | J83: =($M83-$D83)/($M$63-$D$63)+I83 -> 0.0037510361 | K83: =($M83-$D83)/($M$63-$D$63)+J83 -> 0.0025006907 | L83: =($M83-$D83)/($M$63-$D$63)+K83 -> 0.0012503454 | M83: =F28/SUM($F$27:$F$32)*$B$5 -> 0 | N83: =M83 -> 0 | O83: =N83 -> 0 | P83: =O83 -> 0 | Q83: =P83 -> 0 | R83: =Q83 -> 0
A84: Pickup (250 mile) | C84: =D84 -> 0 | D84: =E29/SUM(E$27:E$32)*$B$5 -> 0 | E84: =($M84-$D84)/($M$63-$D$63)+D84 -> 0 | F84: =($M84-$D84)/($M$63-$D$63)+E84 -> 0 | G84: =($M84-$D84)/($M$63-$D$63)+F84 -> 0 | H84: =($M84-$D84)/($M$63-$D$63)+G84 -> 0 | I84: =($M84-$D84)/($M$63-$D$63)+H84 -> 0 | J84: =($M84-$D84)/($M$63-$D$63)+I84 -> 0 | K84: =($M84-$D84)/($M$63-$D$63)+J84 -> 0 | L84: =($M84-$D84)/($M$63-$D$63)+K84 -> 0 | M84: =F29/SUM($F$27:$F$32)*$B$5 -> 0 | N84: =M84 -> 0 | O84: =N84 -> 0 | P84: =O84 -> 0 | Q84: =P84 -> 0 | R84: =Q84 -> 0
A85: Pickup (300 mile) | C85: =D85 -> 0.13518537 | D85: =E30/SUM(E$27:E$32)*$B$5 -> 0.13518537 | E85: =($M85-$D85)/($M$63-$D$63)+D85 -> 0.13643571 | F85: =($M85-$D85)/($M$63-$D$63)+E85 -> 0.13768606 | G85: =($M85-$D85)/($M$63-$D$63)+F85 -> 0.1389364 | H85: =($M85-$D85)/($M$63-$D$63)+G85 -> 0.14018675 | I85: =($M85-$D85)/($M$63-$D$63)+H85 -> 0.14143709 | J85: =($M85-$D85)/($M$63-$D$63)+I85 -> 0.14268744 | K85: =($M85-$D85)/($M$63-$D$63)+J85 -> 0.14393778 | L85: =($M85-$D85)/($M$63-$D$63)+K85 -> 0.14518813 | M85: =F30/SUM($F$27:$F$32)*$B$5 -> 0.14643847 | N85: =M85 -> 0.14643847 | O85: =N85 -> 0.14643847 | P85: =O85 -> 0.14643847 | Q85: =P85 -> 0.14643847 | R85: =Q85 -> 0.14643847
A86: Pickup (350 mile) | C86: =D86 -> 0 | D86: =E31/SUM(E$27:E$32)*$B$5 -> 0 | E86: =($M86-$D86)/($M$63-$D$63)+D86 -> 0 | F86: =($M86-$D86)/($M$63-$D$63)+E86 -> 0 | G86: =($M86-$D86)/($M$63-$D$63)+F86 -> 0 | H86: =($M86-$D86)/($M$63-$D$63)+G86 -> 0 | I86: =($M86-$D86)/($M$63-$D$63)+H86 -> 0 | J86: =($M86-$D86)/($M$63-$D$63)+I86 -> 0 | K86: =($M86-$D86)/($M$63-$D$63)+J86 -> 0 | L86: =($M86-$D86)/($M$63-$D$63)+K86 -> 0 | M86: =F31/SUM($F$27:$F$32)*$B$5 -> 0 | N86: =M86 -> 0 | O86: =N86 -> 0 | P86: =O86 -> 0 | Q86: =P86 -> 0 | R86: =Q86 -> 0
A87: Pickup (400 mile) | C87: =D87 -> 0 | D87: =E32/SUM(E$27:E$32)*$B$5 -> 0 | E87: =($M87-$D87)/($M$63-$D$63)+D87 -> 0 | F87: =($M87-$D87)/($M$63-$D$63)+E87 -> 0 | G87: =($M87-$D87)/($M$63-$D$63)+F87 -> 0 | H87: =($M87-$D87)/($M$63-$D$63)+G87 -> 0 | I87: =($M87-$D87)/($M$63-$D$63)+H87 -> 0 | J87: =($M87-$D87)/($M$63-$D$63)+I87 -> 0 | K87: =($M87-$D87)/($M$63-$D$63)+J87 -> 0 | L87: =($M87-$D87)/($M$63-$D$63)+K87 -> 0 | M87: =F32/SUM($F$27:$F$32)*$B$5 -> 0 | N87: =M87 -> 0 | O87: =N87 -> 0 | P87: =O87 -> 0 | Q87: =P87 -> 0 | R87: =Q87 -> 0
A89: We use historical data from 2021 for 2023 and assume that by 2030 100% of PHEVs are 50-mile range matching the historical sales distribution of ICE
A90: PHEV Market Shares
C91: 2020 | D91: 2021 | E91: 2022 | F91: 2023 | G91: 2024 | H91: 2025 | I91: 2026 | J91: 2027 | K91: 2028 | L91: 2029 | M91: 2030 | N91: 2031 | O91: 2032 | P91: 2033 | Q91: 2034 | R91: 2035
A92: PHEV car (20 mile) | C92: =D36/SUM(D$36:D$41)*$B$2 -> 0.21047241 | D92: =E36/SUM(E$36:E$41)*$B$2 -> 0.15340303 | E92: =($M92-$D92)/($M$91-$D$91)+D92 -> 0.13635825 | F92: =($M92-$D92)/($M$91-$D$91)+E92 -> 0.11931347 | G92: =($M92-$D92)/($M$91-$D$91)+F92 -> 0.10226869 | H92: =($M92-$D92)/($M$91-$D$91)+G92 -> 0.085223904 | I92: =($M92-$D92)/($M$91-$D$91)+H92 -> 0.068179123 | J92: =($M92-$D92)/($M$91-$D$91)+I92 -> 0.051134343 | K92: =($M92-$D92)/($M$91-$D$91)+J92 -> 0.034089562 | L92: =($M92-$D92)/($M$91-$D$91)+K92 -> 0.017044781 | M92: =F36/SUM($F$36:$F$41)*$B$2 -> 0 | N92: =M92 -> 0 | O92: =N92 -> 0 | P92: =O92 -> 0 | Q92: =P92 -> 0 | R92: =Q92 -> 0
A93: PHEV car (30 mile) | C93: =D37/SUM(D$36:D$41)*$B$2 -> 8.2312245e-05 | D93: =E37/SUM(E$36:E$41)*$B$2 -> 6.9409645e-05 | E93: =($M93-$D93)/($M$91-$D$91)+D93 -> 6.1697462e-05 | F93: =($M93-$D93)/($M$91-$D$91)+E93 -> 5.3985279e-05 | G93: =($M93-$D93)/($M$91-$D$91)+F93 -> 4.6273097e-05 | H93: =($M93-$D93)/($M$91-$D$91)+G93 -> 3.8560914e-05 | I93: =($M93-$D93)/($M$91-$D$91)+H93 -> 3.0848731e-05 | J93: =($M93-$D93)/($M$91-$D$91)+I93 -> 2.3136548e-05 | K93: =($M93-$D93)/($M$91-$D$91)+J93 -> 1.5424366e-05 | L93: =($M93-$D93)/($M$91-$D$91)+K93 -> 7.7121828e-06 | M93: =F37/SUM($F$36:$F$41)*$B$2 -> 0 | N93: =M93 -> 0 | O93: =N93 -> 0 | P93: =O93 -> 0 | Q93: =P93 -> 0 | R93: =Q93 -> 0
A94: PHEV car (40 mile) | C94: =D38/SUM(D$36:D$41)*$B$2 -> 0.058770943 | D94: =E38/SUM(E$36:E$41)*$B$2 -> 0.11576372 | E94: =($M94-$D94)/($M$91-$D$91)+D94 -> 0.10290108 | F94: =($M94-$D94)/($M$91-$D$91)+E94 -> 0.090038449 | G94: =($M94-$D94)/($M$91-$D$91)+F94 -> 0.077175813 | H94: =($M94-$D94)/($M$91-$D$91)+G94 -> 0.064313178 | I94: =($M94-$D94)/($M$91-$D$91)+H94 -> 0.051450542 | J94: =($M94-$D94)/($M$91-$D$91)+I94 -> 0.038587907 | K94: =($M94-$D94)/($M$91-$D$91)+J94 -> 0.025725271 | L94: =($M94-$D94)/($M$91-$D$91)+K94 -> 0.012862636 | M94: =F38/SUM($F$36:$F$41)*$B$2 -> 0 | N94: =M94 -> 0 | O94: =N94 -> 0 | P94: =O94 -> 0 | Q94: =P94 -> 0 | R94: =Q94 -> 0
A95: PHEV car (50 mile) | C95: =D39/SUM(D$36:D$41)*$B$2 -> 0.00035394265 | D95: =E39/SUM(E$36:E$41)*$B$2 -> 6.1697462e-05 | E95: =($M95-$D95)/($M$91-$D$91)+D95 -> 0.030019243 | F95: =($M95-$D95)/($M$91-$D$91)+E95 -> 0.059976789 | G95: =($M95-$D95)/($M$91-$D$91)+F95 -> 0.089934334 | H95: =($M95-$D95)/($M$91-$D$91)+G95 -> 0.11989188 | I95: =($M95-$D95)/($M$91-$D$91)+H95 -> 0.14984943 | J95: =($M95-$D95)/($M$91-$D$91)+I95 -> 0.17980697 | K95: =($M95-$D95)/($M$91-$D$91)+J95 -> 0.20976452 | L95: =($M95-$D95)/($M$91-$D$91)+K95 -> 0.23972206 | M95: =F39/SUM($F$36:$F$41)*$B$2 -> 0.26967961 | N95: =M95 -> 0.26967961 | O95: =N95 -> 0.26967961 | P95: =O95 -> 0.26967961 | Q95: =P95 -> 0.26967961 | R95: =Q95 -> 0.26967961
A96: PHEV car (60 mile) | C96: =D40/SUM(D$36:D$41)*$B$2 -> 0 | D96: =E40/SUM(E$36:E$41)*$B$2 -> 0.00038175305 | E96: =($M96-$D96)/($M$91-$D$91)+D96 -> 0.00033933604 | F96: =($M96-$D96)/($M$91-$D$91)+E96 -> 0.00029691904 | G96: =($M96-$D96)/($M$91-$D$91)+F96 -> 0.00025450203 | H96: =($M96-$D96)/($M$91-$D$91)+G96 -> 0.00021208503 | I96: =($M96-$D96)/($M$91-$D$91)+H96 -> 0.00016966802 | J96: =($M96-$D96)/($M$91-$D$91)+I96 -> 0.00012725102 | K96: =($M96-$D96)/($M$91-$D$91)+J96 -> 8.4834011e-05 | L96: =($M96-$D96)/($M$91-$D$91)+K96 -> 4.2417005e-05 | M96: =F40/SUM($F$36:$F$41)*$B$2 -> 0 | N96: =M96 -> 0 | O96: =N96 -> 0 | P96: =O96 -> 0 | Q96: =P96 -> 0 | R96: =Q96 -> 0
A97: PHEV car (70 mile) | C97: =D41/SUM(D$36:D$41)*$B$2 -> 0 | D97: =E41/SUM(E$36:E$41)*$B$2 -> 0 | E97: =($M97-$D97)/($M$91-$D$91)+D97 -> 0 | F97: =($M97-$D97)/($M$91-$D$91)+E97 -> 0 | G97: =($M97-$D97)/($M$91-$D$91)+F97 -> 0 | H97: =($M97-$D97)/($M$91-$D$91)+G97 -> 0 | I97: =($M97-$D97)/($M$91-$D$91)+H97 -> 0 | J97: =($M97-$D97)/($M$91-$D$91)+I97 -> 0 | K97: =($M97-$D97)/($M$91-$D$91)+J97 -> 0 | L97: =($M97-$D97)/($M$91-$D$91)+K97 -> 0 | M97: =F41/SUM($F$36:$F$41)*$B$2 -> 0 | N97: =M97 -> 0 | O97: =N97 -> 0 | P97: =O97 -> 0 | Q97: =P97 -> 0 | R97: =Q97 -> 0
A98: PHEV crossover (20 mile) | C98: =D42/SUM(D$42:D$47)*$B$3 -> 0.35204001 | D98: =E42/SUM(E$42:E$47)*$B$3 -> 0.30450866 | E98: =($M98-$D98)/($M$91-$D$91)+D98 -> 0.27067436 | F98: =($M98-$D98)/($M$91-$D$91)+E98 -> 0.23684007 | G98: =($M98-$D98)/($M$91-$D$91)+F98 -> 0.20300577 | H98: =($M98-$D98)/($M$91-$D$91)+G98 -> 0.16917148 | I98: =($M98-$D98)/($M$91-$D$91)+H98 -> 0.13533718 | J98: =($M98-$D98)/($M$91-$D$91)+I98 -> 0.10150289 | K98: =($M98-$D98)/($M$91-$D$91)+J98 -> 0.067668591 | L98: =($M98-$D98)/($M$91-$D$91)+K98 -> 0.033834295 | M98: =F42/SUM($F$42:$F$47)*$B$3 -> 0 | N98: =M98 -> 0 | O98: =N98 -> 0 | P98: =O98 -> 0 | Q98: =P98 -> 0 | R98: =Q98 -> 0
A99: PHEV crossover (30 mile) | C99: =D43/SUM(D$42:D$47)*$B$3 -> 0.0010909079 | D99: =E43/SUM(E$42:E$47)*$B$3 -> 0.048622264 | E99: =($M99-$D99)/($M$91-$D$91)+D99 -> 0.04321979 | F99: =($M99-$D99)/($M$91-$D$91)+E99 -> 0.037817316 | G99: =($M99-$D99)/($M$91-$D$91)+F99 -> 0.032414842 | H99: =($M99-$D99)/($M$91-$D$91)+G99 -> 0.027012369 | I99: =($M99-$D99)/($M$91-$D$91)+H99 -> 0.021609895 | J99: =($M99-$D99)/($M$91-$D$91)+I99 -> 0.016207421 | K99: =($M99-$D99)/($M$91-$D$91)+J99 -> 0.010804947 | L99: =($M99-$D99)/($M$91-$D$91)+K99 -> 0.0054024737 | M99: =F43/SUM($F$42:$F$47)*$B$3 -> 0 | N99: =M99 -> 0 | O99: =N99 -> 0 | P99: =O99 -> 0 | Q99: =P99 -> 0 | R99: =Q99 -> 0
A100: PHEV crossover (40 mile) | C100: =D44/SUM(D$42:D$47)*$B$3 -> 0 | D100: =E44/SUM(E$42:E$47)*$B$3 -> 0 | E100: =($M100-$D100)/($M$91-$D$91)+D100 -> 0 | F100: =($M100-$D100)/($M$91-$D$91)+E100 -> 0 | G100: =($M100-$D100)/($M$91-$D$91)+F100 -> 0 | H100: =($M100-$D100)/($M$91-$D$91)+G100 -> 0 | I100: =($M100-$D100)/($M$91-$D$91)+H100 -> 0 | J100: =($M100-$D100)/($M$91-$D$91)+I100 -> 0 | K100: =($M100-$D100)/($M$91-$D$91)+J100 -> 0 | L100: =($M100-$D100)/($M$91-$D$91)+K100 -> 0 | M100: =F44/SUM($F$42:$F$47)*$B$3 -> 0 | N100: =M100 -> 0 | O100: =N100 -> 0 | P100: =O100 -> 0 | Q100: =P100 -> 0 | R100: =Q100 -> 0
A101: PHEV crossover (50 mile) | C101: =D45/SUM(D$42:D$47)*$B$3 -> 0 | D101: =E45/SUM(E$42:E$47)*$B$3 -> 0 | E101: =($M101-$D101)/($M$91-$D$91)+D101 -> 0.039236769 | F101: =($M101-$D101)/($M$91-$D$91)+E101 -> 0.078473538 | G101: =($M101-$D101)/($M$91-$D$91)+F101 -> 0.11771031 | H101: =($M101-$D101)/($M$91-$D$91)+G101 -> 0.15694708 | I101: =($M101-$D101)/($M$91-$D$91)+H101 -> 0.19618384 | J101: =($M101-$D101)/($M$91-$D$91)+I101 -> 0.23542061 | K101: =($M101-$D101)/($M$91-$D$91)+J101 -> 0.27465738 | L101: =($M101-$D101)/($M$91-$D$91)+K101 -> 0.31389415 | M101: =F45/SUM($F$42:$F$47)*$B$3 -> 0.35313092 | N101: =M101 -> 0.35313092 | O101: =N101 -> 0.35313092 | P101: =O101 -> 0.35313092 | Q101: =P101 -> 0.35313092 | R101: =Q101 -> 0.35313092
A102: PHEV crossover (60 mile) | C102: =D46/SUM(D$42:D$47)*$B$3 -> 0 | D102: =E46/SUM(E$42:E$47)*$B$3 -> 0 | E102: =($M102-$D102)/($M$91-$D$91)+D102 -> 0 | F102: =($M102-$D102)/($M$91-$D$91)+E102 -> 0 | G102: =($M102-$D102)/($M$91-$D$91)+F102 -> 0 | H102: =($M102-$D102)/($M$91-$D$91)+G102 -> 0 | I102: =($M102-$D102)/($M$91-$D$91)+H102 -> 0 | J102: =($M102-$D102)/($M$91-$D$91)+I102 -> 0 | K102: =($M102-$D102)/($M$91-$D$91)+J102 -> 0 | L102: =($M102-$D102)/($M$91-$D$91)+K102 -> 0 | M102: =F46/SUM($F$42:$F$47)*$B$3 -> 0 | N102: =M102 -> 0 | O102: =N102 -> 0 | P102: =O102 -> 0 | Q102: =P102 -> 0 | R102: =Q102 -> 0
A103: PHEV crossover (70 mile) | C103: =D47/SUM(D$42:D$47)*$B$3 -> 0 | D103: =E47/SUM(E$42:E$47)*$B$3 -> 0 | E103: =($M103-$D103)/($M$91-$D$91)+D103 -> 0 | F103: =($M103-$D103)/($M$91-$D$91)+E103 -> 0 | G103: =($M103-$D103)/($M$91-$D$91)+F103 -> 0 | H103: =($M103-$D103)/($M$91-$D$91)+G103 -> 0 | I103: =($M103-$D103)/($M$91-$D$91)+H103 -> 0 | J103: =($M103-$D103)/($M$91-$D$91)+I103 -> 0 | K103: =($M103-$D103)/($M$91-$D$91)+J103 -> 0 | L103: =($M103-$D103)/($M$91-$D$91)+K103 -> 0 | M103: =F47/SUM($F$42:$F$47)*$B$3 -> 0 | N103: =M103 -> 0 | O103: =N103 -> 0 | P103: =O103 -> 0 | Q103: =P103 -> 0 | R103: =Q103 -> 0
A104: PHEV SUV (20 mile) | C104: =D48/SUM(D$48:D$53)*$B$4 -> 0.054746922 | D104: =E48/SUM(E$48:E$53)*$B$4 -> 0.036736288 | E104: =($M104-$D104)/($M$91-$D$91)+D104 -> 0.032654478 | F104: =($M104-$D104)/($M$91-$D$91)+E104 -> 0.028572669 | G104: =($M104-$D104)/($M$91-$D$91)+F104 -> 0.024490859 | H104: =($M104-$D104)/($M$91-$D$91)+G104 -> 0.020409049 | I104: =($M104-$D104)/($M$91-$D$91)+H104 -> 0.016327239 | J104: =($M104-$D104)/($M$91-$D$91)+I104 -> 0.012245429 | K104: =($M104-$D104)/($M$91-$D$91)+J104 -> 0.0081636196 | L104: =($M104-$D104)/($M$91-$D$91)+K104 -> 0.0040818098 | M104: =F48/SUM($F$48:$F$53)*$B$4 -> 0 | N104: =M104 -> 0 | O104: =N104 -> 0 | P104: =O104 -> 0 | Q104: =P104 -> 0 | R104: =Q104 -> 0
A105: PHEV SUV (30 mile) | C105: =D49/SUM(D$48:D$53)*$B$4 -> 0.17125122 | D105: =E49/SUM(E$48:E$53)*$B$4 -> 0.19401471 | E105: =($M105-$D105)/($M$91-$D$91)+D105 -> 0.17245752 | F105: =($M105-$D105)/($M$91-$D$91)+E105 -> 0.15090033 | G105: =($M105-$D105)/($M$91-$D$91)+F105 -> 0.12934314 | H105: =($M105-$D105)/($M$91-$D$91)+G105 -> 0.10778595 | I105: =($M105-$D105)/($M$91-$D$91)+H105 -> 0.086228759 | J105: =($M105-$D105)/($M$91-$D$91)+I105 -> 0.06467157 | K105: =($M105-$D105)/($M$91-$D$91)+J105 -> 0.04311438 | L105: =($M105-$D105)/($M$91-$D$91)+K105 -> 0.02155719 | M105: =F49/SUM($F$48:$F$53)*$B$4 -> 0 | N105: =M105 -> 0 | O105: =N105 -> 0 | P105: =O105 -> 0 | Q105: =P105 -> 0 | R105: =Q105 -> 0
...

Sheet AEO by Class
A1: Total VMT by Class
B2: 2021 | C2: 2022 | D2: 2023 | E2: 2024 | F2: 2025 | G2: 2026 | H2: 2027 | I2: 2028 | J2: 2029 | K2: 2030 | L2: 2031 | M2: 2032 | N2: 2033 | O2: 2034 | P2: 2035 | Q2: 2036 | R2: 2037 | S2: 2038 | T2: 2039 | U2: 2040 | V2: 2041 | W2: 2042 | X2: 2043 | Y2: 2044 | Z2: 2045 | AA2: 2046 | AB2: 2047 | AC2: 2048 | AD2: 2049 | AE2: 2050
A3: 2b | B3: =SUMIFS($E$22:$E$372,$B$22:$B$372,B$2)+SUMIFS($F$22:$F$372,$B$22:$B$372,B$2) -> 89367047258 | C3: =SUMIFS($E$22:$E$372,$B$22:$B$372,C$2)+SUMIFS($F$22:$F$372,$B$22:$B$372,C$2) -> 95977015103 | D3: =SUMIFS($E$22:$E$372,$B$22:$B$372,D$2)+SUMIFS($F$22:$F$372,$B$22:$B$372,D$2) -> 98812825093 | E3: =SUMIFS($E$22:$E$372,$B$22:$B$372,E$2)+SUMIFS($F$22:$F$372,$B$22:$B$372,E$2) -> 100094998262 | F3: =SUMIFS($E$22:$E$372,$B$22:$B$372,F$2)+SUMIFS($F$22:$F$372,$B$22:$B$372,F$2) -> 100480428369 | G3: =SUMIFS($E$22:$E$372,$B$22:$B$372,G$2)+SUMIFS($F$22:$F$372,$B$22:$B$372,G$2) -> 101424489851 | H3: =SUMIFS($E$22:$E$372,$B$22:$B$372,H$2)+SUMIFS($F$22:$F$372,$B$22:$B$372,H$2) -> 102816579379 | I3: =SUMIFS($E$22:$E$372,$B$22:$B$372,I$2)+SUMIFS($F$22:$F$372,$B$22:$B$372,I$2) -> 104230371474 | ... AE3: =SUMIFS($E$22:$E$372,$B$22:$B$372,AE$2)+SUMIFS($F$22:$F$372,$B$22:$B$372,AE$2) -> 130641797616
A4: 3 | B4: =SUMIFS($G$22:$G$372,$B$22:$B$372,B$2)+SUMIFS($H$22:$H$372,$B$22:$B$372,B$2) -> 73491209528 | C4: =SUMIFS($G$22:$G$372,$B$22:$B$372,C$2)+SUMIFS($H$22:$H$372,$B$22:$B$372,C$2) -> 75058850216 | D4: =SUMIFS($G$22:$G$372,$B$22:$B$372,D$2)+SUMIFS($H$22:$H$372,$B$22:$B$372,D$2) -> 74732068170 | E4: =SUMIFS($G$22:$G$372,$B$22:$B$372,E$2)+SUMIFS($H$22:$H$372,$B$22:$B$372,E$2) -> 75056362035 | F4: =SUMIFS($G$22:$G$372,$B$22:$B$372,F$2)+SUMIFS($H$22:$H$372,$B$22:$B$372,F$2) -> 76161660589 | G4: =SUMIFS($G$22:$G$372,$B$22:$B$372,G$2)+SUMIFS($H$22:$H$372,$B$22:$B$372,G$2) -> 77621935152 | H4: =SUMIFS($G$22:$G$372,$B$22:$B$372,H$2)+SUMIFS($H$22:$H$372,$B$22:$B$372,H$2) -> 78824143867 | I4: =SUMIFS($G$22:$G$372,$B$22:$B$372,I$2)+SUMIFS($H$22:$H$372,$B$22:$B$372,I$2) -> 79954302377 | ... AE4: =SUMIFS($G$22:$G$372,$B$22:$B$372,AE$2)+SUMIFS($H$22:$H$372,$B$22:$B$372,AE$2) -> 123324758518
A5: 4 | B5: =SUMIFS($I$22:$I$372,$B$22:$B$372,B$2) -> 16520378018 | C5: =SUMIFS($I$22:$I$372,$B$22:$B$372,C$2) -> 16751666086 | D5: =SUMIFS($I$22:$I$372,$B$22:$B$372,D$2) -> 16583323470 | E5: =SUMIFS($I$22:$I$372,$B$22:$B$372,E$2) -> 16511942220 | F5: =SUMIFS($I$22:$I$372,$B$22:$B$372,F$2) -> 16557685158 | G5: =SUMIFS($I$22:$I$372,$B$22:$B$372,G$2) -> 16722257362 | H5: =SUMIFS($I$22:$I$372,$B$22:$B$372,H$2) -> 16890767928 | I5: =SUMIFS($I$22:$I$372,$B$22:$B$372,I$2) -> 17088339593 | ... AE5: =SUMIFS($I$22:$I$372,$B$22:$B$372,AE$2) -> 22481978241
A6: 5 | B6: =SUMIFS($J$22:$J$372,$B$22:$B$372,B$2) -> 21162307201 | C6: =SUMIFS($J$22:$J$372,$B$22:$B$372,C$2) -> 21781207474 | D6: =SUMIFS($J$22:$J$372,$B$22:$B$372,D$2) -> 21876699449 | E6: =SUMIFS($J$22:$J$372,$B$22:$B$372,E$2) -> 22056979412 | F6: =SUMIFS($J$22:$J$372,$B$22:$B$372,F$2) -> 22392723421 | G6: =SUMIFS($J$22:$J$372,$B$22:$B$372,G$2) -> 22851304902 | H6: =SUMIFS($J$22:$J$372,$B$22:$B$372,H$2) -> 23305101083 | I6: =SUMIFS($J$22:$J$372,$B$22:$B$372,I$2) -> 23762269052 | ... AE6: =SUMIFS($J$22:$J$372,$B$22:$B$372,AE$2) -> 34590984593
A7: 6 | B7: =SUMIFS($K$22:$K$372,$B$22:$B$372,B$2) -> 21091781567 | C7: =SUMIFS($K$22:$K$372,$B$22:$B$372,C$2) -> 21163519149 | D7: =SUMIFS($K$22:$K$372,$B$22:$B$372,D$2) -> 20772978430 | E7: =SUMIFS($K$22:$K$372,$B$22:$B$372,E$2) -> 20535995156 | F7: =SUMIFS($K$22:$K$372,$B$22:$B$372,F$2) -> 20494574836 | G7: =SUMIFS($K$22:$K$372,$B$22:$B$372,G$2) -> 20605713318 | H7: =SUMIFS($K$22:$K$372,$B$22:$B$372,H$2) -> 20747433204 | I7: =SUMIFS($K$22:$K$372,$B$22:$B$372,I$2) -> 20918246976 | ... AE7: =SUMIFS($K$22:$K$372,$B$22:$B$372,AE$2) -> 27570635908
A8: 7 | B8: =SUMIFS($M$22:$M$372,$B$22:$B$372,B$2)+SUMIFS($N$22:$N$372,$B$22:$B$372,B$2)+SUMIFS($O$22:$O$372,$B$22:$B$372,B$2)+SUMIFS($L$22:$L$372,$B$22:$B$372,B$2) -> 21507671116 | C8: =SUMIFS($M$22:$M$372,$B$22:$B$372,C$2)+SUMIFS($N$22:$N$372,$B$22:$B$372,C$2)+SUMIFS($O$22:$O$372,$B$22:$B$372,C$2)+SUMIFS($L$22:$L$372,$B$22:$B$372,C$2) -> 21357975768 | D8: =SUMIFS($M$22:$M$372,$B$22:$B$372,D$2)+SUMIFS($N$22:$N$372,$B$22:$B$372,D$2)+SUMIFS($O$22:$O$372,$B$22:$B$372,D$2)+SUMIFS($L$22:$L$372,$B$22:$B$372,D$2) -> 20783058567 | E8: =SUMIFS($M$22:$M$372,$B$22:$B$372,E$2)+SUMIFS($N$22:$N$372,$B$22:$B$372,E$2)+SUMIFS($O$22:$O$372,$B$22:$B$372,E$2)+SUMIFS($L$22:$L$372,$B$22:$B$372,E$2) -> 20374639585 | F8: =SUMIFS($M$22:$M$372,$B$22:$B$372,F$2)+SUMIFS($N$22:$N$372,$B$22:$B$372,F$2)+SUMIFS($O$22:$O$372,$B$22:$B$372,F$2)+SUMIFS($L$22:$L$372,$B$22:$B$372,F$2) -> 20181540051 | G8: =SUMIFS($M$22:$M$372,$B$22:$B$372,G$2)+SUMIFS($N$22:$N$372,$B$22:$B$372,G$2)+SUMIFS($O$22:$O$372,$B$22:$B$372,G$2)+SUMIFS($L$22:$L$372,$B$22:$B$372,G$2) -> 20133620176 | H8: =SUMIFS($M$22:$M$372,$B$22:$B$372,H$2)+SUMIFS($N$22:$N$372,$B$22:$B$372,H$2)+SUMIFS($O$22:$O$372,$B$22:$B$372,H$2)+SUMIFS($L$22:$L$372,$B$22:$B$372,H$2) -> 20087106886 | I8: =SUMIFS($M$22:$M$372,$B$22:$B$372,I$2)+SUMIFS($N$22:$N$372,$B$22:$B$372,I$2)+SUMIFS($O$22:$O$372,$B$22:$B$372,I$2)+SUMIFS($L$22:$L$372,$B$22:$B$372,I$2) -> 20038635908 | ... AE8: =SUMIFS($M$22:$M$372,$B$22:$B$372,AE$2)+SUMIFS($N$22:$N$372,$B$22:$B$372,AE$2)+SUMIFS($O$22:$O$372,$B$22:$B$372,AE$2)+SUMIFS($L$22:$L$372,$B$22:$B$372,AE$2) -> 19474802616
A9: 8 | B9: =SUMIFS($P$22:$P$372,$B$22:$B$372,B$2)+SUMIFS($Q$22:$Q$372,$B$22:$B$372,B$2)+SUMIFS($R$22:$R$372,$B$22:$B$372,B$2)+SUMIFS($S$22:$S$372,$B$22:$B$372,B$2)+SUMIFS($T$22:$T$372,$B$22:$B$372,B$2)+SUMIFS($U$22:$U$372,$B$22:$B$372,B$2)+SUMIFS($V$22:$V$372,$B$22:$B$372,B$2)+SUMIFS($W$22:$W$372,$B$22:$B$372,B$2) -> 161513165543 | C9: =SUMIFS($P$22:$P$372,$B$22:$B$372,C$2)+SUMIFS($Q$22:$Q$372,$B$22:$B$372,C$2)+SUMIFS($R$22:$R$372,$B$22:$B$372,C$2)+SUMIFS($S$22:$S$372,$B$22:$B$372,C$2)+SUMIFS($T$22:$T$372,$B$22:$B$372,C$2)+SUMIFS($U$22:$U$372,$B$22:$B$372,C$2)+SUMIFS($V$22:$V$372,$B$22:$B$372,C$2)+SUMIFS($W$22:$W$372,$B$22:$B$372,C$2) -> 165833835900 | D9: =SUMIFS($P$22:$P$372,$B$22:$B$372,D$2)+SUMIFS($Q$22:$Q$372,$B$22:$B$372,D$2)+SUMIFS($R$22:$R$372,$B$22:$B$372,D$2)+SUMIFS($S$22:$S$372,$B$22:$B$372,D$2)+SUMIFS($T$22:$T$372,$B$22:$B$372,D$2)+SUMIFS($U$22:$U$372,$B$22:$B$372,D$2)+SUMIFS($V$22:$V$372,$B$22:$B$372,D$2)+SUMIFS($W$22:$W$372,$B$22:$B$372,D$2) -> 165951663770 | E9: =SUMIFS($P$22:$P$372,$B$22:$B$372,E$2)+SUMIFS($Q$22:$Q$372,$B$22:$B$372,E$2)+SUMIFS($R$22:$R$372,$B$22:$B$372,E$2)+SUMIFS($S$22:$S$372,$B$22:$B$372,E$2)+SUMIFS($T$22:$T$372,$B$22:$B$372,E$2)+SUMIFS($U$22:$U$372,$B$22:$B$372,E$2)+SUMIFS($V$22:$V$372,$B$22:$B$372,E$2)+SUMIFS($W$22:$W$372,$B$22:$B$372,E$2) -> 166563777972 | F9: =SUMIFS($P$22:$P$372,$B$22:$B$372,F$2)+SUMIFS($Q$22:$Q$372,$B$22:$B$372,F$2)+SUMIFS($R$22:$R$372,$B$22:$B$372,F$2)+SUMIFS($S$22:$S$372,$B$22:$B$372,F$2)+SUMIFS($T$22:$T$372,$B$22:$B$372,F$2)+SUMIFS($U$22:$U$372,$B$22:$B$372,F$2)+SUMIFS($V$22:$V$372,$B$22:$B$372,F$2)+SUMIFS($W$22:$W$372,$B$22:$B$372,F$2) -> 168228600747 | G9: =SUMIFS($P$22:$P$372,$B$22:$B$372,G$2)+SUMIFS($Q$22:$Q$372,$B$22:$B$372,G$2)+SUMIFS($R$22:$R$372,$B$22:$B$372,G$2)+SUMIFS($S$22:$S$372,$B$22:$B$372,G$2)+SUMIFS($T$22:$T$372,$B$22:$B$372,G$2)+SUMIFS($U$22:$U$372,$B$22:$B$372,G$2)+SUMIFS($V$22:$V$372,$B$22:$B$372,G$2)+SUMIFS($W$22:$W$372,$B$22:$B$372,G$2) -> 170541530605 | H9: =SUMIFS($P$22:$P$372,$B$22:$B$372,H$2)+SUMIFS($Q$22:$Q$372,$B$22:$B$372,H$2)+SUMIFS($R$22:$R$372,$B$22:$B$372,H$2)+SUMIFS($S$22:$S$372,$B$22:$B$372,H$2)+SUMIFS($T$22:$T$372,$B$22:$B$372,H$2)+SUMIFS($U$22:$U$372,$B$22:$B$372,H$2)+SUMIFS($V$22:$V$372,$B$22:$B$372,H$2)+SUMIFS($W$22:$W$372,$B$22:$B$372,H$2) -> 172436733111 | I9: =SUMIFS($P$22:$P$372,$B$22:$B$372,I$2)+SUMIFS($Q$22:$Q$372,$B$22:$B$372,I$2)+SUMIFS($R$22:$R$372,$B$22:$B$372,I$2)+SUMIFS($S$22:$S$372,$B$22:$B$372,I$2)+SUMIFS($T$22:$T$372,$B$22:$B$372,I$2)+SUMIFS($U$22:$U$372,$B$22:$B$372,I$2)+SUMIFS($V$22:$V$372,$B$22:$B$372,I$2)+SUMIFS($W$22:$W$372,$B$22:$B$372,I$2) -> 173990397454 | ... AE9: =SUMIFS($P$22:$P$372,$B$22:$B$372,AE$2)+SUMIFS($Q$22:$Q$372,$B$22:$B$372,AE$2)+SUMIFS($R$22:$R$372,$B$22:$B$372,AE$2)+SUMIFS($S$22:$S$372,$B$22:$B$372,AE$2)+SUMIFS($T$22:$T$372,$B$22:$B$372,AE$2)+SUMIFS($U$22:$U$372,$B$22:$B$372,AE$2)+SUMIFS($V$22:$V$372,$B$22:$B$372,AE$2)+SUMIFS($W$22:$W$372,$B$22:$B$372,AE$2) -> 185700776885
A11: Total VMT by Class
B12: 2021 | C12: 2022 | D12: 2023 | E12: 2024 | F12: 2025 | G12: 2026 | H12: 2027 | I12: 2028 | J12: 2029 | K12: 2030 | L12: 2031 | M12: 2032 | N12: 2033 | O12: 2034 | P12: 2035 | Q12: 2036 | R12: 2037 | S12: 2038 | T12: 2039 | U12: 2040 | V12: 2041 | W12: 2042 | X12: 2043 | Y12: 2044 | Z12: 2045 | AA12: 2046 | AB12: 2047 | AC12: 2048 | AD12: 2049 | AE12: 2050
A13: Percentage of class 6/7 VMT from class 6 | B13: =B7/SUM(B7:B8) -> 0.4951186 | C13: =C7/SUM(C7:C8) -> 0.49771343 | D13: =D7/SUM(D7:D8) -> 0.49987872 | E13: =E7/SUM(E7:E8) -> 0.50197205 | F13: =F7/SUM(F7:F8) -> 0.50384789 | G13: =G7/SUM(G7:G8) -> 0.50579407 | H13: =H7/SUM(H7:H8) -> 0.50808539 | I13: =I7/SUM(I7:I8) -> 0.51073826 | ... AE13: =AE7/SUM(AE7:AE8) -> 0.5860427
A14: Percentage of AEO HDV from class 7 | B14: =B8/SUM(B$8:B$9) -> 0.11751488 | C14: =C8/SUM(C$8:C$9) -> 0.11409674 | D14: =D8/SUM(D$8:D$9) -> 0.11129724 | E14: =E8/SUM(E$8:E$9) -> 0.10899118 | F14: =F8/SUM(F$8:F$9) -> 0.10711494 | G14: =G8/SUM(G$8:G$9) -> 0.10559121 | H14: =H8/SUM(H$8:H$9) -> 0.10433569 | I14: =I8/SUM(I$8:I$9) -> 0.10327648 | ... AE14: =AE8/SUM(AE$8:AE$9) -> 0.094917741
A15: Percentage of AEO HDV from class 8 | B15: =B9/SUM(B$8:B$9) -> 0.88248512 | C15: =C9/SUM(C$8:C$9) -> 0.88590326 | D15: =D9/SUM(D$8:D$9) -> 0.88870276 | E15: =E9/SUM(E$8:E$9) -> 0.89100882 | F15: =F9/SUM(F$8:F$9) -> 0.89288506 | G15: =G9/SUM(G$8:G$9) -> 0.89440879 | H15: =H9/SUM(H$8:H$9) -> 0.89566431 | I15: =I9/SUM(I$8:I$9) -> 0.89672352 | ... AE15: =AE9/SUM(AE$8:AE$9) -> 0.90508226
A17: Freight truck VMT (Class 2b-8) by fuel and market class
A18: AEO2023 Reference case
H20: Vocational | M20: Class 7 tractor | P20: Class 8
B21: Year | D21: Powertrain | E21: Class 2 pickup and van | F21: Class 2 vocational | G21: Class 3 pickup and van | H21: 3 | I21: 4 | J21: 5 | K21: 6 | L21: 7 | M21: Day low | N21: day mid | O21: day high | P21: voc | Q21: day low | R21: day mid | S21: day high | T21: sleeper low | U21: sleeper mid | V21: sleeper high | W21: heavy-haul | AA21: Light-Medium | AB21: Medium-Heavy | AC21: Heavy-heavy
B22: 2012 | C22: Diesel | D22: 1 | E22: 1440254464 | F22: 5322017 | G22: 35961749504 | H22: 3098777600 | I22: 10600532992 | J22: 10702599168 | K22: 16254921728 | L22: 16212148224 | M22: 1825904512 | N22: 1825904512 | O22: 5477713920 | P22: 22833444864 | Q22: 10201739264 | R22: 10201739264 | S22: 30717327360 | T22: 12219665408 | U22: 12219665408 | V22: 36546887680 | W22: 2016466 | Z22: 2012 | AA22: {=SUM(($G$22:$H$372)*($B$22:$B$372=$Z22))/1000000} -> 53357.496 | AB22: {=SUM(($I$22:$K$372)*($B$22:$B$372=$Z22))/1000000} -> 54962.399 | AC22: {=SUM(($L$22:$W$372)*($B$22:$B$372=$Z22))/1000000} -> 160885.03 | AD22: =SUM(AA22:AC22) -> 269204.93
B23: 2012 | C23: Gasoline | D23: 2 | E23: 2212064768 | F23: 595231552 | G23: 7394046976 | H23: 5169382400 | I23: 8645104640 | J23: 3212722688 | K23: 5412267008 | L23: 339667136 | M23: 0 | N23: 0 | O23: 0 | P23: 38699320 | Q23: 0 | R23: 0 | S23: 0 | T23: 0 | U23: 0 | V23: 0 | W23: 0 | Z23: 2013 | AA23: {=SUM(($G$22:$H$372)*($B$22:$B$372=$Z23))/1000000} -> 54849.001 | AB23: {=SUM(($I$22:$K$372)*($B$22:$B$372=$Z23))/1000000} -> 55016.168 | AC23: {=SUM(($L$22:$W$372)*($B$22:$B$372=$Z23))/1000000} -> 165149.1 | AD23: =SUM(AA23:AC23) -> 275014.27
B24: 2012 | C24: LPG | D24: 3 | E24: 0 | F24: 0 | G24: 2868664 | H24: 1669 | I24: 4813934 | J24: 3126864 | K24: 14819426 | L24: 17589540 | M24: 0 | N24: 0 | O24: 0 | P24: 166131 | Q24: 0 | R24: 0 | S24: 0 | T24: 0 | U24: 0 | V24: 0 | W24: 0 | Z24: 2014 | AA24: {=SUM(($G$22:$H$372)*($B$22:$B$372=$Z24))/1000000} -> 56369.293 | AB24: {=SUM(($I$22:$K$372)*($B$22:$B$372=$Z24))/1000000} -> 54763.222 | AC24: {=SUM(($L$22:$W$372)*($B$22:$B$372=$Z24))/1000000} -> 167996.19 | AD24: =SUM(AA24:AC24) -> 279128.7
B25: 2012 | C25: CNG | D25: 4 | E25: 1938696 | F25: 496 | G25: 0 | H25: 0 | I25: 16868926 | J25: 1779335 | K25: 20459338 | L25: 3961454 | M25: 646493 | N25: 646493 | O25: 1939480 | P25: 128548256 | Q25: 6280110 | R25: 6280110 | S25: 18909346 | T25: 7522331 | U25: 7522331 | V25: 22497980 | W25: 0 | Z25: 2015 | AA25: {=SUM(($G$22:$H$372)*($B$22:$B$372=$Z25))/1000000} -> 58042.053 | AB25: {=SUM(($I$22:$K$372)*($B$22:$B$372=$Z25))/1000000} -> 54072.603 | AC25: {=SUM(($L$22:$W$372)*($B$22:$B$372=$Z25))/1000000} -> 167723.9 | AD25: =SUM(AA25:AC25) -> 279838.55
B26: 2012 | C26: Flex | D26: 5 | E26: 1526867200 | F26: 15506088 | G26: 1261574912 | H26: 467267328 | I26: 72383440 | J26: 0 | K26: 0 | L26: 0 | M26: 0 | N26: 0 | O26: 0 | P26: 0 | Q26: 0 | R26: 0 | S26: 0 | T26: 0 | U26: 0 | V26: 0 | W26: 0 | Z26: 2016 | AA26: {=SUM(($G$22:$H$372)*($B$22:$B$372=$Z26))/1000000} -> 59349.005 | AB26: {=SUM(($I$22:$K$372)*($B$22:$B$372=$Z26))/1000000} -> 54712.408 | AC26: {=SUM(($L$22:$W$372)*($B$22:$B$372=$Z26))/1000000} -> 173828.55 | AD26: =SUM(AA26:AC26) -> 287889.96
B27: 2012 | C27: BEV | D27: 6 | E27: 0 | F27: 0 | G27: 0 | H27: 1827002 | I27: 0 | J27: 0 | K27: 0 | L27: 0 | M27: 0 | N27: 0 | O27: 0 | P27: 0 | Q27: 0 | R27: 0 | S27: 0 | T27: 0 | U27: 0 | V27: 0 | W27: 0 | Z27: 2017 | AA27: {=SUM(($G$22:$H$372)*($B$22:$B$372=$Z27))/1000000} -> 63513.358 | AB27: {=SUM(($I$22:$K$372)*($B$22:$B$372=$Z27))/1000000} -> 57567.424 | AC27: {=SUM(($L$22:$W$372)*($B$22:$B$372=$Z27))/1000000} -> 176504.52 | AD27: =SUM(AA27:AC27) -> 297585.3
B28: 2012 | C28: PHEV diesel | D28: 7 | E28: 0 | F28: 0 | G28: 0 | H28: 0 | I28: 0 | J28: 0 | K28: 0 | L28: 0 | M28: 0 | N28: 0 | O28: 0 | P28: 0 | Q28: 0 | R28: 0 | S28: 0 | T28: 0 | U28: 0 | V28: 0 | W28: 0 | Z28: 2018 | AA28: {=SUM(($G$22:$H$372)*($B$22:$B$372=$Z28))/1000000} -> 65749.611 | AB28: {=SUM(($I$22:$K$372)*($B$22:$B$372=$Z28))/1000000} -> 58713.445 | AC28: {=SUM(($L$22:$W$372)*($B$22:$B$372=$Z28))/1000000} -> 180393.99 | AD28: =SUM(AA28:AC28) -> 304857.04
B29: 2012 | C29: PHEV gasoline | D29: 8 | E29: 0 | F29: 0 | G29: 0 | H29: 0 | I29: 0 | J29: 0 | K29: 0 | L29: 0 | M29: 0 | N29: 0 | O29: 0 | P29: 0 | Q29: 0 | R29: 0 | S29: 0 | T29: 0 | U29: 0 | V29: 0 | W29: 0 | Z29: 2019 | AA29: {=SUM(($G$22:$H$372)*($B$22:$B$372=$Z29))/1000000} -> 64032.876 | AB29: {=SUM(($I$22:$K$372)*($B$22:$B$372=$Z29))/1000000} -> 57753.082 | AC29: {=SUM(($L$22:$W$372)*($B$22:$B$372=$Z29))/1000000} -> 178258.79 | AD29: =SUM(AA29:AC29) -> 300044.75
B30: 2012 | C30: Fuel cell | D30: 9 | E30: 0 | F30: 0 | G30: 0 | H30: 0 | I30: 0 | J30: 0 | K30: 0 | L30: 0 | M30: 0 | N30: 0 | O30: 0 | P30: 0 | Q30: 0 | R30: 0 | S30: 0 | T30: 0 | U30: 0 | V30: 0 | W30: 0 | Z30: 2020 | AA30: {=SUM(($G$22:$H$372)*($B$22:$B$372=$Z30))/1000000} -> 66392.729 | AB30: {=SUM(($I$22:$K$372)*($B$22:$B$372=$Z30))/1000000} -> 56565.216 | AC30: {=SUM(($L$22:$W$372)*($B$22:$B$372=$Z30))/1000000} -> 179177.29 | AD30: =SUM(AA30:AC30) -> 302135.24
B31: 2013 | C31: =C22 -> Diesel | D31: 1 | E31: 30803937280 | F31: 113826472 | G31: 37116588032 | H31: 2996025344 | I31: 10001015808 | J31: 11095851008 | K31: 16266354688 | L31: 15772302336 | M31: 1837885568 | N31: 1837885568 | O31: 5513656832 | P31: 22739668992 | Q31: 10591882240 | R31: 10591882240 | S31: 31892043776 | T31: 12686980096 | U31: 12686980096 | V31: 37944545280 | W31: 2940154 | Z31: 2021 | AA31: {=SUM(($G$22:$H$372)*($B$22:$B$372=$Z31))/1000000} -> 73491.21 | AB31: {=SUM(($I$22:$K$372)*($B$22:$B$372=$Z31))/1000000} -> 58774.467 | AC31: {=SUM(($L$22:$W$372)*($B$22:$B$372=$Z31))/1000000} -> 183020.84 | AD31: =SUM(AA31:AC31) -> 315286.51
B32: 2013 | C32: =C23 -> Gasoline | D32: 2 | E32: 40669630464 | F32: 10943552512 | G32: 7747261440 | H32: 5148895232 | I32: 8775163904 | J32: 3338966272 | K32: 5325068288 | L32: 316361344 | M32: 0 | N32: 0 | O32: 0 | P32: 37404796 | Q32: 0 | R32: 0 | S32: 0 | T32: 0 | U32: 0 | V32: 0 | W32: 0 | Z32: 2022 | AA32: {=SUM(($G$22:$H$372)*($B$22:$B$372=$Z32))/1000000} -> 75058.85 | AB32: {=SUM(($I$22:$K$372)*($B$22:$B$372=$Z32))/1000000} -> 59696.393 | AC32: {=SUM(($L$22:$W$372)*($B$22:$B$372=$Z32))/1000000} -> 187191.81 | AD32: =SUM(AA32:AC32) -> 321947.05
B33: 2013 | C33: =C24 -> LPG | D33: 3 | E33: 185391 | F33: 24 | G33: 2577511 | H33: 1674 | I33: 4126762 | J33: 2774236 | K33: 13745288 | L33: 14937902 | M33: 0 | N33: 0 | O33: 0 | P33: 205250 | Q33: 0 | R33: 0 | S33: 0 | T33: 0 | U33: 0 | V33: 0 | W33: 0 | Z33: 2023 | AA33: {=SUM(($G$22:$H$372)*($B$22:$B$372=$Z33))/1000000} -> 74732.068 | AB33: {=SUM(($I$22:$K$372)*($B$22:$B$372=$Z33))/1000000} -> 59233.001 | AC33: {=SUM(($L$22:$W$372)*($B$22:$B$372=$Z33))/1000000} -> 186734.72 | AD33: =SUM(AA33:AC33) -> 320699.79
B34: 2013 | C34: =C25 -> CNG | D34: 4 | E34: 52313188 | F34: 7134 | G34: 0 | H34: 0 | I34: 20689670 | J34: 1538102 | K34: 19159026 | L34: 12698769 | M34: 2153647 | N34: 2153647 | O34: 6460942 | P34: 424092032 | Q34: 21292082 | R34: 21292082 | S34: 64110228 | T34: 25503706 | U34: 25503706 | V34: 76277136 | W34: 0 | Z34: 2024 | AA34: {=SUM(($G$22:$H$372)*($B$22:$B$372=$Z34))/1000000} -> 75056.362 | AB34: {=SUM(($I$22:$K$372)*($B$22:$B$372=$Z34))/1000000} -> 59104.917 | AC34: {=SUM(($L$22:$W$372)*($B$22:$B$372=$Z34))/1000000} -> 186938.42 | AD34: =SUM(AA34:AC34) -> 321099.7
B35: 2013 | C35: =C26 -> Flex | D35: 5 | E35: 5602993664 | F35: 77389656 | G35: 1203051136 | H35: 632725120 | I35: 128952440 | J35: 0 | K35: 22762426 | L35: 0 | M35: 0 | N35: 0 | O35: 0 | P35: 0 | Q35: 0 | R35: 0 | S35: 0 | T35: 0 | U35: 0 | V35: 0 | W35: 0 | Z35: 2025 | AA35: {=SUM(($G$22:$H$372)*($B$22:$B$372=$Z35))/1000000} -> 76161.661 | AB35: {=SUM(($I$22:$K$372)*($B$22:$B$372=$Z35))/1000000} -> 59444.983 | AC35: {=SUM(($L$22:$W$372)*($B$22:$B$372=$Z35))/1000000} -> 188410.14 | AD35: =SUM(AA35:AC35) -> 324016.78
B36: 2013 | C36: =C27 -> BEV | D36: 6 | E36: 0 | F36: 0 | G36: 0 | H36: 1875744 | I36: 0 | J36: 0 | K36: 0 | L36: 0 | M36: 0 | N36: 0 | O36: 0 | P36: 0 | Q36: 0 | R36: 0 | S36: 0 | T36: 0 | U36: 0 | V36: 0 | W36: 0 | Z36: 2026 | AA36: {=SUM(($G$22:$H$372)*($B$22:$B$372=$Z36))/1000000} -> 77621.935 | AB36: {=SUM(($I$22:$K$372)*($B$22:$B$372=$Z36))/1000000} -> 60179.276 | AC36: {=SUM(($L$22:$W$372)*($B$22:$B$372=$Z36))/1000000} -> 190675.15 | AD36: =SUM(AA36:AC36) -> 328476.36
B37: 2013 | C37: =C28 -> PHEV diesel | D37: 7 | E37: 0 | F37: 0 | G37: 0 | H37: 0 | I37: 0 | J37: 0 | K37: 0 | L37: 0 | M37: 0 | N37: 0 | O37: 0 | P37: 0 | Q37: 0 | R37: 0 | S37: 0 | T37: 0 | U37: 0 | V37: 0 | W37: 0 | Z37: 2027 | AA37: {=SUM(($G$22:$H$372)*($B$22:$B$372=$Z37))/1000000} -> 78824.144 | AB37: {=SUM(($I$22:$K$372)*($B$22:$B$372=$Z37))/1000000} -> 60943.302 | AC37: {=SUM(($L$22:$W$372)*($B$22:$B$372=$Z37))/1000000} -> 192523.84 | AD37: =SUM(AA37:AC37) -> 332291.29
B38: 2013 | C38: =C29 -> PHEV gasoline | D38: 8 | E38: 0 | F38: 0 | G38: 0 | H38: 0 | I38: 0 | J38: 0 | K38: 0 | L38: 0 | M38: 0 | N38: 0 | O38: 0 | P38: 0 | Q38: 0 | R38: 0 | S38: 0 | T38: 0 | U38: 0 | V38: 0 | W38: 0 | Z38: 2028 | AA38: {=SUM(($G$22:$H$372)*($B$22:$B$372=$Z38))/1000000} -> 79954.302 | AB38: {=SUM(($I$22:$K$372)*($B$22:$B$372=$Z38))/1000000} -> 61768.856 | AC38: {=SUM(($L$22:$W$372)*($B$22:$B$372=$Z38))/1000000} -> 194029.03 | AD38: =SUM(AA38:AC38) -> 335752.19
B39: 2013 | C39: =C30 -> Fuel cell | D39: 9 | E39: 0 | F39: 0 | G39: 0 | H39: 0 | I39: 0 | J39: 0 | K39: 0 | L39: 0 | M39: 0 | N39: 0 | O39: 0 | P39: 0 | Q39: 0 | R39: 0 | S39: 0 | T39: 0 | U39: 0 | V39: 0 | W39: 0 | Z39: 2029 | AA39: {=SUM(($G$22:$H$372)*($B$22:$B$372=$Z39))/1000000} -> 81126.438 | AB39: {=SUM(($I$22:$K$372)*($B$22:$B$372=$Z39))/1000000} -> 62522.915 | AC39: {=SUM(($L$22:$W$372)*($B$22:$B$372=$Z39))/1000000} -> 194919.58 | AD39: =SUM(AA39:AC39) -> 338568.93
B40: 2014 | C40: =C31 -> Diesel | D40: 1 | E40: 31470921728 | F40: 73441176 | G40: 37866586112 | H40: 2775675904 | I40: 9478882304 | J40: 11652484096 | K40: 15905961984 | L40: 15311998976 | M40: 1816530688 | N40: 1816530688 | O40: 5449592320 | P40: 22719107072 | Q40: 10872541184 | R40: 10872541184 | S40: 32737095680 | T40: 13023152128 | U40: 13023152128 | V40: 38949990400 | W40: 3021042 | Z40: 2030 | AA40: {=SUM(($G$22:$H$372)*($B$22:$B$372=$Z40))/1000000} -> 82515.568 | AB40: {=SUM(($I$22:$K$372)*($B$22:$B$372=$Z40))/1000000} -> 63231.207 | AC40: {=SUM(($L$22:$W$372)*($B$22:$B$372=$Z40))/1000000} -> 195347.26 | AD40: =SUM(AA40:AC40) -> 341094.03
B41: 2014 | C41: =C32 -> Gasoline | D41: 2 | E41: 50104815616 | F41: 1981181184 | G41: 8467652608 | H41: 5142343680 | I41: 8770002944 | J41: 3432117504 | K41: 5204172800 | L41: 292320064 | M41: 0 | N41: 0 | O41: 0 | P41: 37042424 | Q41: 0 | R41: 0 | S41: 0 | T41: 0 | U41: 0 | V41: 0 | W41: 0 | Z41: 2031 | AA41: {=SUM(($G$22:$H$372)*($B$22:$B$372=$Z41))/1000000} -> 84225.81 | AB41: {=SUM(($I$22:$K$372)*($B$22:$B$372=$Z41))/1000000} -> 64039.528 | AC41: {=SUM(($L$22:$W$372)*($B$22:$B$372=$Z41))/1000000} -> 195864.9 | AD41: =SUM(AA41:AC41) -> 344130.23
B42: 2014 | C42: =C33 -> LPG | D42: 3 | E42: 190928 | F42: 318 | G42: 2210096 | H42: 0 | I42: 3378688 | J42: 2267157 | K42: 11943307 | L42: 13006248 | M42: 0 | N42: 0 | O42: 0 | P42: 148184 | Q42: 0 | R42: 0 | S42: 0 | T42: 0 | U42: 0 | V42: 0 | W42: 0 | Z42: 2032 | AA42: {=SUM(($G$22:$H$372)*($B$22:$B$372=$Z42))/1000000} -> 86247.875 | AB42: {=SUM(($I$22:$K$372)*($B$22:$B$372=$Z42))/1000000} -> 65124.282 | AC42: {=SUM(($L$22:$W$372)*($B$22:$B$372=$Z42))/1000000} -> 196870.93 | AD42: =SUM(AA42:AC42) -> 348243.09
... B60: 2016 | C60: =C51 -> LPG | D60: 3 | E60: 154088 | F60: 322 | G60: 1419799 | H60: 0 | I60: 6546392 | J60: 22589896 | K60: 22562494 | L60: 21641836 | M60: 0 | N60: 0 | O60: 0 | P60: 219438 | Q60: 0 | R60: 0 | S60: 0 | T60: 0 | U60: 0 | V60: 0 | W60: 0 | Z60: 2050 | AA60: {=SUM(($G$22:$H$372)*($B$22:$B$372=$Z60))/1000000} -> 123324.76 | AB60: {=SUM(($I$22:$K$372)*($B$22:$B$372=$Z60))/1000000} -> 84643.599 | AC60: {=SUM(($L$22:$W$372)*($B$22:$B$372=$Z60))/1000000} -> 205175.58 | AD60: =SUM(AA60:AC60) -> 413143.94
B61: 2016 | C61: =C52 -> CNG | D61: 4 | E61: 110351456 | F61: 986910 | G61: 85947 | H61: 0 | I61: 19862614 | J61: 964208 | K61: 15353000 | L61: 33596404 | M61: 6550681 | N61: 6550681 | O61: 19652042 | P61: 823382016 | Q61: 72834912 | R61: 72834912 | S61: 219305152 | T61: 87241824 | U61: 87241824 | V61: 260925088 | W61: 0
B62: 2016 | C62: =C53 -> Flex | D62: 5 | E62: 8964489216 | F62: 498212064 | G62: 1649950592 | H62: 1203981952 | I62: 310605120 | J62: 0 | K62: 35030368 | L62: 0 | M62: 0 | N62: 0 | O62: 0 | P62: 0 | Q62: 0 | R62: 0 | S62: 0 | T62: 0 | U62: 0 | V62: 0 | W62: 0
B63: 2016 | C63: =C54 -> BEV | D63: 6 | E63: 0 | F63: 0 | G63: 0 | H63: 1557606 | I63: 0 | J63: 90575 | K63: 0 | L63: 0 | M63: 0 | N63: 0 | O63: 0 | P63: 0 | Q63: 0 | R63: 0 | S63: 0 | T63: 0 | U63: 0 | V63: 0 | W63: 0
B64: 2016 | C64: =C55 -> PHEV diesel | D64: 7 | E64: 0 | F64: 0 | G64: 0 | H64: 0 | I64: 0 | J64: 0 | K64: 0 | L64: 0 | M64: 0 | N64: 0 | O64: 0 | P64: 0 | Q64: 0 | R64: 0 | S64: 0 | T64: 0 | U64: 0 | V64: 0 | W64: 0
B65: 2016 | C65: =C56 -> PHEV gasoline | D65: 8 | E65: 0 | F65: 0 | G65: 0 | H65: 0 | I65: 0 | J65: 0 | K65: 0 | L65: 0 | M65: 0 | N65: 0 | O65: 0 | P65: 0 | Q65: 0 | R65: 0 | S65: 0 | T65: 0 | U65: 0 | V65: 0 | W65: 0
B66: 2016 | C66: =C57 -> Fuel cell | D66: 9 | E66: 0 | F66: 0 | G66: 0 | H66: 0 | I66: 0 | J66: 0 | K66: 0 | L66: 0 | M66: 0 | N66: 0 | O66: 0 | P66: 0 | Q66: 0 | R66: 0 | S66: 0 | T66: 0 | U66: 0 | V66: 0 | W66: 0
B67: 2017 | C67: =C58 -> Diesel | D67: 1 | E67: 32811651072 | F67: 76569928 | G67: 44304506880 | H67: 2348114688 | I67: 7977647616 | J67: 14176344064 | K67: 15916547072 | L67: 14482820096 | M67: 1729491584 | N67: 1729491584 | O67: 5188474880 | P67: 24610936832 | Q67: 11524892672 | R67: 11524892672 | S67: 34701320192 | T67: 13804542976 | U67: 13804542976 | V67: 41286979584 | W67: 6775192
B68: 2017 | C68: =C59 -> Gasoline | D68: 2 | E68: 44827734016 | F68: 1772521472 | G68: 8299080192 | H68: 5030804480 | I68: 9519837184 | J68: 4231507968 | K68: 5212124672 | L68: 236199856 | M68: 0 | N68: 0 | O68: 0 | P68: 23693550 | Q68: 0 | R68: 0 | S68: 0 | T68: 0 | U68: 0 | V68: 0 | W68: 0
B69: 2017 | C69: =C60 -> LPG | D69: 3 | E69: 119304 | F69: 0 | G69: 1312560 | H69: 0 | I69: 6280723 | J69: 21992162 | K69: 22127978 | L69: 24295132 | M69: 0 | N69: 0 | O69: 0 | P69: 202920 | Q69: 0 | R69: 0 | S69: 0 | T69: 0 | U69: 0 | V69: 0 | W69: 0
B70: 2017 | C70: =C61 -> CNG | D70: 4 | E70: 103158128 | F70: 933739 | G70: 173018 | H70: 0 | I70: 19791424 | J70: 914222 | K70: 15320760 | L70: 38967536 | M70: 6478567 | N70: 6478567 | O70: 19435702 | P70: 900560192 | Q70: 77612960 | R70: 77612960 | S70: 233691776 | T70: 92964984 | U70: 92964984 | V70: 278042048 | W70: 0
B71: 2017 | C71: =C62 -> Flex | D71: 5 | E71: 11672904704 | F71: 615768064 | G71: 2047377536 | H71: 1480517888 | I71: 429228384 | J71: 0 | K71: 16629244 | L71: 0 | M71: 0 | N71: 0 | O71: 0 | P71: 0 | Q71: 0 | R71: 0 | S71: 0 | T71: 0 | U71: 0 | V71: 0 | W71: 0
B72: 2017 | C72: =C63 -> BEV | D72: 6 | E72: 0 | F72: 0 | G72: 0 | H72: 1471106 | I72: 0 | J72: 864351 | K72: 266143 | L72: 0 | M72: 0 | N72: 0 | O72: 0 | P72: 22648 | Q72: 27178 | R72: 27178 | S72: 81533 | T72: 0 | U72: 0 | V72: 0 | W72: 0
... B77: 2018 | C77: =C68 -> Gasoline | D77: 2 | E77: 42223857664 | F77: 1669562240 | G77: 8370083840 | H77: 5039817216 | I77: 9712958464 | J77: 4440967680 | K77: 5254778880 | L77: 222187568 | M77: 0 | N77: 0 | O77: 0 | P77: 19375528 | Q77: 0 | R77: 0 | S77: 0 | T77: 0 | U77: 0 | V77: 0 | W77: 0
B78: 2018 | C78: =C69 -> LPG | D78: 3 | E78: 113881 | G78: 1161003 | H78: 0 | I78: 5952121 | J78: 21607650 | K78: 21097912 | L78: 27790504 | M78: 0 | N78: 0 | O78: 0 | P78: 158901 | Q78: 0 | R78: 0 | S78: 0 | T78: 0 | U78: 0 | V78: 0 | W78: 0
B79: 2018 | C79: =C70 -> CNG | D79: 4 | E79: 93512280 | F79: 850391 | G79: 564296 | H79: 289035 | I79: 21994280 | J79: 816488 | K79: 14963066 | L79: 43009028 | M79: 6113100 | N79: 6113100 | O79: 18339300 | P79: 1011967360 | Q79: 81013112 | R79: 81013112 | S79: 243929616 | T79: 97037704 | U79: 97037704 | V79: 290222848 | W79: 0
B80: 2018 | C80: =C71 -> Flex | D80: 5 | E80: 13995052032 | F80: 634162880 | G80: 2365078528 | H80: 1622540032 | I80: 473028704 | J80: 0 | K80: 0 | L80: 0 | M80: 0 | N80: 0 | O80: 0 | P80: 0 | Q80: 0 | R80: 0 | S80: 0 | T80: 0 | U80: 0 | V80: 0 | W80: 0
B81: 2018 | C81: =C72 -> BEV | D81: 6 | E81: 0 | F81: 0 | G81: 0 | H81: 1284285 | I81: 1067053 | J81: 1012080 | K81: 251295 | L81: 0 | M81: 0 | N81: 0 | O81: 0 | P81: 22148 | Q81: 26577 | R81: 26577 | S81: 79732 | T81: 0 | U81: 0 | V81: 0 | W81: 0
B82: 2018 | C82: =C73 -> PHEV diesel | D82: 7 | E82: 0 | F82: 0 | G82: 0 | H82: 0 | I82: 0 | J82: 0 | K82: 0 | L82: 0 | M82: 0 | N82: 0 | O82: 0 | P82: 0 | Q82: 0 | R82: 0 | S82: 0 | T82: 0 | U82: 0 | V82: 0 | W82: 0
B83: 2018 | C83: =C74 -> PHEV gasoline | D83: 8 | E83: 0 | F83: 0 | G83: 0 | H83: 0 | I83: 0 | J83: 0 | K83: 0 | L83: 0 | M83: 0 | N83: 0 | O83: 0 | P83: 0 | Q83: 0 | R83: 0 | S83: 0 | T83: 0 | U83: 0 | V83: 0 | W83: 0
B84: 2018 | C84: =C75 -> Fuel cell | D84: 9 | E84: 0 | F84: 0 | G84: 0 | H84: 0 | I84: 0 | J84: 0 | K84: 0 | L84: 0 | M84: 0 | N84: 0 | O84: 0 | P84: 0 | Q84: 0 | R84: 0 | S84: 0 | T84: 0 | U84: 0 | V84: 0 | W84: 0
B85: 2019 | C85: =C76 -> Diesel | D85: 1 | E85: 34442088448 | F85: 80374744 | G85: 44970164224 | H85: 2173359104 | I85: 6967507968 | J85: 15091208192 | K85: 16094333952 | L85: 13942651904 | M85: 1648101248 | N85: 1648101248 | O85: 4944304640 | P85: 25693448192 | Q85: 11665829888 | R85: 11665829888 | S85: 35125694464 | T85: 13973356544 | U85: 13973356544 | V85: 41791873024 | W85: 6500376
B86: 2019 | C86: =C77 -> Gasoline | D86: 2 | E86: 40873254912 | F86: 1616158976 | G86: 8078728192 | H86: 4712576512 | I86: 9558893568 | J86: 4451668480 | K86: 5003247616 | L86: 195892096 | M86: 0 | N86: 0 | O86: 0 | P86: 14536650 | Q86: 0 | R86: 0 | S86: 0 | T86: 0 | U86: 0 | V86: 0 | W86: 0
B87: 2019 | C87: =C78 -> LPG | D87: 3 | E87: 97511 | F87: 0 | G87: 1012323 | H87: 0 | I87: 5407472 | J87: 18948460 | K87: 17721782 | L87: 25093482 | M87: 0 | N87: 0 | O87: 0 | P87: 139982 | Q87: 0 | R87: 0 | S87: 0 | T87: 0 | U87: 0 | V87: 0 | W87: 0
B88: 2019 | C88: =C79 -> CNG | D88: 4 | E88: 94042832 | F88: 978979 | G88: 1322314 | H88: 16894024 | I88: 21718650 | J88: 705719 | K88: 13523449 | L88: 39026000 | M88: 5323211 | N88: 5323211 | O88: 15969634 | P88: 1024812032 | Q88: 77649360 | R88: 77649360 | S88: 233801376 | T88: 93008592 | U88: 93008592 | V88: 278172480 | W88: 0
B89: 2019 | C89: =C80 -> Flex | D89: 5 | E89: 15781909504 | F89: 683440704 | G89: 2395916544 | H89: 1681821440 | I89: 506052704 | J89: 0 | K89: 0 | L89: 0 | M89: 0 | N89: 0 | O89: 0 | P89: 0 | Q89: 0 | R89: 0 | S89: 0 | T89: 0 | U89: 0 | V89: 0 | W89: 0
B90: 2019 | C90: =C81 -> BEV | D90: 6 | E90: 0 | F90: 0 | G90: 0 | H90: 1081127 | I90: 984846 | J90: 936411 | K90: 222334 | L90: 0 | M90: 0 | N90: 0 | O90: 0 | P90: 20567 | Q90: 62975 | R90: 62975 | S90: 188924 | T90: 0 | U90: 0 | V90: 0 | W90: 0
... B372: 2050 | C372: =C363 -> Fuel cell | D372: 9 | E372: 0 | F372: 0 | G372: 0 | H372: 26557 | I372: 67647448 | J372: 104134440 | K372: 82685296 | L372: 9386373 | M372: 1217271 | N372: 1217305 | O372: 3651839 | P372: 25195466 | Q372: 10909962 | R372: 10888471 | S372: 32789802 | T372: 13073003 | U372: 13035101 | V372: 39102420 | W372: 0

Sheet Freight LDVs + HDVs
A1: Average Battery Pack Size | B1: 2020 | C1: 2021 | D1: 2022 | E1: 2023 | F1: 2024 | G1: 2025 | H1: 2026 | I1: 2027 | J1: 2028 | K1: 2029 | L1: 2030 | M1: 2031 | N1: 2032 | O1: 2033 | P1: 2034 | Q1: 2035 | R1: 2036 | S1: 2037 | T1: 2038 | U1: 2039 | V1: 2040 | W1: 2041 | X1: 2042 | Y1: 2043 | Z1: 2044 | AA1: 2045 | AB1: 2046 | AC1: 2047 | AD1: 2048 | AE1: 2049 | AF1: 2050
A2: Rigid truck, 4-5 | B2: {=TREND($D2:$H2,$D$1:$H$1,B$1)} -> 140.5 | C2: {=TREND($D2:$H2,$D$1:$H$1,C$1)} -> 137.75 | D2: 135 | E2: 132.25 | F2: 129.5 | G2: 126.75 | H2: 124 | I2: 121.25 | J2: 118.5 | K2: 115.75 | L2: 113 | M2: 113 | N2: 113 | O2: 113 | P2: 113 | Q2: 113 | R2: 113 | S2: 113 | T2: 113 | U2: 113 | V2: 113 | W2: 113 | X2: 113 | Y2: 113 | Z2: 113 | AA2: 113 | AB2: 113 | AC2: 113 | AD2: 113 | AE2: 113 | AF2: 113
A3: Rigid truck, 6-7 | B3: {=TREND($D3:$H3,$D$1:$H$1,B$1)} -> 213.5 | C3: {=TREND($D3:$H3,$D$1:$H$1,C$1)} -> 209.25 | D3: 205 | E3: 200.75 | F3: 196.5 | G3: 192.25 | H3: 188 | I3: 183.75 | J3: 179.5 | K3: 175.25 | L3: 171 | M3: 171 | N3: 171 | O3: 171 | P3: 171 | Q3: 171 | R3: 171 | S3: 171 | T3: 171 | U3: 171 | V3: 171 | W3: 171 | X3: 171 | Y3: 171 | Z3: 171 | AA3: 171 | AB3: 171 | AC3: 171 | AD3: 171 | AE3: 171 | AF3: 171
A4: Rigid truck, 8 | B4: {=TREND($D4:$H4,$D$1:$H$1,B$1)} -> 425 | C4: {=TREND($D4:$H4,$D$1:$H$1,C$1)} -> 412.5 | D4: 400 | E4: 387.5 | F4: 375 | G4: 362.5 | H4: 350 | I4: 337.5 | J4: 325 | K4: 312.5 | L4: 300 | M4: 300 | N4: 300 | O4: 300 | P4: 300 | Q4: 300 | R4: 300 | S4: 300 | T4: 300 | U4: 300 | V4: 300 | W4: 300 | X4: 300 | Y4: 300 | Z4: 300 | AA4: 300 | AB4: 300 | AC4: 300 | AD4: 300 | AE4: 300 | AF4: 300
A5: Tractor truck, short-haul | B5: {=TREND($D5:$H5,$D$1:$H$1,B$1)} -> 485.5 | C5: {=TREND($D5:$H5,$D$1:$H$1,C$1)} -> 470.25 | D5: 455 | E5: 439.75 | F5: 424.5 | G5: 409.25 | H5: 394 | I5: 378.75 | J5: 363.5 | K5: 348.25 | L5: 333 | M5: 333 | N5: 333 | O5: 333 | P5: 333 | Q5: 333 | R5: 333 | S5: 333 | T5: 333 | U5: 333 | V5: 333 | W5: 333 | X5: 333 | Y5: 333 | Z5: 333 | AA5: 333 | AB5: 333 | AC5: 333 | AD5: 333 | AE5: 333 | AF5: 333
A6: Tractor truck, long-haul | B6: {=TREND($D6:$H6,$D$1:$H$1,B$1)} -> 984.25 | C6: {=TREND($D6:$H6,$D$1:$H$1,C$1)} -> 952.125 | D6: 920 | E6: 887.875 | F6: 855.75 | G6: 823.625 | H6: 791.5 | I6: 759.375 | J6: 727.25 | K6: 695.125 | L6: 663 | M6: 663 | N6: 663 | O6: 663 | P6: 663 | Q6: 663 | R6: 663 | S6: 663 | T6: 663 | U6: 663 | V6: 663 | W6: 663 | X6: 663 | Y6: 663 | Z6: 663 | AA6: 663 | AB6: 663 | AC6: 663 | AD6: 663 | AE6: 663 | AF6: 663
A7: Refuse truck | B7: {=TREND($D7:$H7,$D$1:$H$1,B$1)} -> 428.25 | C7: {=TREND($D7:$H7,$D$1:$H$1,C$1)} -> 416.625 | D7: 405 | E7: 393.375 | F7: 381.75 | G7: 370.125 | H7: 358.5 | I7: 346.875 | J7: 335.25 | K7: 323.625 | L7: 312 | M7: 312 | N7: 312 | O7: 312 | P7: 312 | Q7: 312 | R7: 312 | S7: 312 | T7: 312 | U7: 312 | V7: 312 | W7: 312 | X7: 312 | Y7: 312 | Z7: 312 | AA7: 312 | AB7: 312 | AC7: 312 | AD7: 312 | AE7: 312 | AF7: 312
A8: Small bus, 4-5 | B8: {=TREND($D8:$H8,$D$1:$H$1,B$1)} -> 121.25 | C8: {=TREND($D8:$H8,$D$1:$H$1,C$1)} -> 120.625 | D8: 120 | E8: 119.375 | F8: 118.75 | G8: 118.125 | H8: 117.5 | I8: 116.875 | J8: 116.25 | K8: 115.625 | L8: 115 | M8: 115 | N8: 115 | O8: 115 | P8: 115 | Q8: 115 | R8: 115 | S8: 115 | T8: 115 | U8: 115 | V8: 115 | W8: 115 | X8: 115 | Y8: 115 | Z8: 115 | AA8: 115 | AB8: 115 | AC8: 115 | AD8: 115 | AE8: 115 | AF8: 115
A9: Transit bus, 6-8 | B9: {=TREND($D9:$H9,$D$1:$H$1,B$1)} -> 455 | C9: {=TREND($D9:$H9,$D$1:$H$1,C$1)} -> 452.5 | D9: 450 | E9: 447.5 | F9: 445 | G9: 442.5 | H9: 440 | I9: 437.5 | J9: 435 | K9: 432.5 | L9: 430 | M9: 430 | N9: 430 | O9: 430 | P9: 430 | Q9: 430 | R9: 430 | S9: 430 | T9: 430 | U9: 430 | V9: 430 | W9: 430 | X9: 430 | Y9: 430 | Z9: 430 | AA9: 430 | AB9: 430 | AC9: 430 | AD9: 430 | AE9: 430 | AF9: 430
A10: School bus, 6-8 | B10: {=TREND($D10:$H10,$D$1:$H$1,B$1)} -> 182 | C10: {=TREND($D10:$H10,$D$1:$H$1,C$1)} -> 181 | D10: 180 | E10: 179 | F10: 178 | G10: 177 | H10: 176 | I10: 175 | J10: 174 | K10: 173 | L10: 172 | M10: 172 | N10: 172 | O10: 172 | P10: 172 | Q10: 172 | R10: 172 | S10: 172 | T10: 172 | U10: 172 | V10: 172 | W10: 172 | X10: 172 | Y10: 172 | Z10: 172 | AA10: 172 | AB10: 172 | AC10: 172 | AD10: 172 | AE10: 172 | AF10: 172
A11: Other bus, 6-8 | B11: {=TREND($D11:$H11,$D$1:$H$1,B$1)} -> 683.5 | C11: {=TREND($D11:$H11,$D$1:$H$1,C$1)} -> 679.75 | D11: 676 | E11: 672.25 | F11: 668.5 | G11: 664.75 | H11: 661 | I11: 657.25 | J11: 653.5 | K11: 649.75 | L11: 646 | M11: 646 | N11: 646 | O11: 646 | P11: 646 | Q11: 646 | R11: 646 | S11: 646 | T11: 646 | U11: 646 | V11: 646 | W11: 646 | X11: 646 | Y11: 646 | Z11: 646 | AA11: 646 | AB11: 646 | AC11: 646 | AD11: 646 | AE11: 646 | AF11: 646
A14: Total vehicle sales - historical data and projections
B15: 2020 | C15: 2021 | D15: 2022 | E15: 2023 | F15: 2024 | G15: 2025 | H15: 2026 | I15: 2027 | J15: 2028 | K15: 2029 | L15: 2030 | M15: 2031 | N15: 2032 | O15: 2033 | P15: 2034 | Q15: 2035 | R15: 2036 | S15: 2037 | T15: 2038 | U15: 2039 | V15: 2040 | W15: 2041 | X15: 2042 | Y15: 2043 | Z15: 2044 | AA15: 2045 | AB15: 2046 | AC15: 2047 | AD15: 2048 | AE15: 2049 | AF15: 2050 | AG15: 2051 | AH15: 2052 | AI15: 2053 | AJ15: EPS Category
A16: Annual sales
A17: Rigid truck, 4-5 | B17: 116537.59 | C17: =($G17-$B17)/5+B17 -> 117344.41 | D17: =($G17-$B17)/5+C17 -> 118151.24 | E17: =($G17-$B17)/5+D17 -> 118958.06 | F17: =($G17-$B17)/5+E17 -> 119764.89 | G17: 120571.71 | H17: =($L17-$G17)/5+G17 -> 122325.78 | I17: =($L17-$G17)/5+H17 -> 124079.86 | J17: =($L17-$G17)/5+I17 -> 125833.93 | K17: =($L17-$G17)/5+J17 -> 127588.01 | L17: 129342.08 | M17: =($Q17-$L17)/5+L17 -> 132498.09 | N17: =($Q17-$L17)/5+M17 -> 135654.1 | O17: =($Q17-$L17)/5+N17 -> 138810.12 | P17: =($Q17-$L17)/5+O17 -> 141966.13 | Q17: 145122.14 | R17: =($V17-$Q17)/5+Q17 -> 148198.99 | S17: =($V17-$Q17)/5+R17 -> 151275.84 | T17: =($V17-$Q17)/5+S17 -> 154352.7 | U17: =($V17-$Q17)/5+T17 -> 157429.55 | V17: 160506.4 | W17: {=TREND($M17:$V17,$M$15:$V$15,W$15)} -> 163688.8 | X17: {=TREND($M17:$V17,$M$15:$V$15,X$15)} -> 166799.23 | Y17: {=TREND($M17:$V17,$M$15:$V$15,Y$15)} -> 169909.67 | Z17: {=TREND($M17:$V17,$M$15:$V$15,Z$15)} -> 173020.1 | AA17: {=TREND($M17:$V17,$M$15:$V$15,AA$15)} -> 176130.54 | AB17: {=TREND($M17:$V17,$M$15:$V$15,AB$15)} -> 179240.97 | AC17: {=TREND($M17:$V17,$M$15:$V$15,AC$15)} -> 182351.41 | AD17: {=TREND($M17:$V17,$M$15:$V$15,AD$15)} -> 185461.84 | ... AI17: {=TREND($M17:$V17,$M$15:$V$15,AI$15)} -> 201014.02 | AJ17: Freight LDV
A18: Rigid truck, 6-7 | B18: 118399.01 | C18: =($G18-$B18)/5+B18 -> 119218.7 | D18: =($G18-$B18)/5+C18 -> 120038.39 | E18: =($G18-$B18)/5+D18 -> 120858.07 | F18: =($G18-$B18)/5+E18 -> 121677.76 | G18: 122497.45 | H18: =($L18-$G18)/5+G18 -> 124279.49 | I18: =($L18-$G18)/5+H18 -> 126061.52 | J18: =($L18-$G18)/5+I18 -> 127843.56 | K18: =($L18-$G18)/5+J18 -> 129625.6 | L18: 131407.63 | M18: =($Q18-$L18)/5+L18 -> 134614.11 | N18: =($Q18-$L18)/5+M18 -> 137820.6 | O18: =($Q18-$L18)/5+N18 -> 141027.08 | P18: =($Q18-$L18)/5+O18 -> 144233.56 | Q18: 147440.04 | R18: =($V18-$Q18)/5+Q18 -> 150566.05 | S18: =($V18-$Q18)/5+R18 -> 153692.05 | T18: =($V18-$Q18)/5+S18 -> 156818.06 | U18: =($V18-$Q18)/5+T18 -> 159944.06 | V18: 163070.07 | W18: {=TREND($M18:$V18,$M$15:$V$15,W$15)} -> 166303.38 | X18: {=TREND($M18:$V18,$M$15:$V$15,X$15)} -> 169463.52 | Y18: {=TREND($M18:$V18,$M$15:$V$15,Y$15)} -> 172623.67 | Z18: {=TREND($M18:$V18,$M$15:$V$15,Z$15)} -> 175783.82 | AA18: {=TREND($M18:$V18,$M$15:$V$15,AA$15)} -> 178943.97 | AB18: {=TREND($M18:$V18,$M$15:$V$15,AB$15)} -> 182104.11 | AC18: {=TREND($M18:$V18,$M$15:$V$15,AC$15)} -> 185264.26 | AD18: {=TREND($M18:$V18,$M$15:$V$15,AD$15)} -> 188424.41 | ... AI18: {=TREND($M18:$V18,$M$15:$V$15,AI$15)} -> 204225.14 | AJ18: Freight LDV
A19: Rigid truck, 8 | B19: 95647.28 | C19: =($G19-$B19)/5+B19 -> 96309.492 | D19: =($G19-$B19)/5+C19 -> 96971.704 | E19: =($G19-$B19)/5+D19 -> 97633.915 | F19: =($G19-$B19)/5+E19 -> 98296.127 | G19: 98958.339 | H19: =($L19-$G19)/5+G19 -> 100397.96 | I19: =($L19-$G19)/5+H19 -> 101837.59 | J19: =($L19-$G19)/5+I19 -> 103277.21 | K19: =($L19-$G19)/5+J19 -> 104716.83 | L19: 106156.46 | M19: =($Q19-$L19)/5+L19 -> 108746.77 | N19: =($Q19-$L19)/5+M19 -> 111337.08 | O19: =($Q19-$L19)/5+N19 -> 113927.39 | P19: =($Q19-$L19)/5+O19 -> 116517.71 | Q19: 119108.02 | R19: =($V19-$Q19)/5+Q19 -> 121633.36 | S19: =($V19-$Q19)/5+R19 -> 124158.69 | T19: =($V19-$Q19)/5+S19 -> 126684.03 | U19: =($V19-$Q19)/5+T19 -> 129209.37 | V19: 131734.7 | W19: {=TREND($M19:$V19,$M$15:$V$15,W$15)} -> 134346.68 | X19: {=TREND($M19:$V19,$M$15:$V$15,X$15)} -> 136899.58 | Y19: {=TREND($M19:$V19,$M$15:$V$15,Y$15)} -> 139452.48 | Z19: {=TREND($M19:$V19,$M$15:$V$15,Z$15)} -> 142005.38 | AA19: {=TREND($M19:$V19,$M$15:$V$15,AA$15)} -> 144558.29 | AB19: {=TREND($M19:$V19,$M$15:$V$15,AB$15)} -> 147111.19 | AC19: {=TREND($M19:$V19,$M$15:$V$15,AC$15)} -> 149664.09 | AD19: {=TREND($M19:$V19,$M$15:$V$15,AD$15)} -> 152216.99 | ... AI19: {=TREND($M19:$V19,$M$15:$V$15,AI$15)} -> 164981.51 | AJ19: Freight HDV
A20: Tractor truck, short-haul | B20: 55945.25 | C20: =($G20-$B20)/5+B20 -> 55322.91 | D20: =($G20-$B20)/5+C20 -> 54700.57 | E20: =($G20-$B20)/5+D20 -> 54078.23 | F20: =($G20-$B20)/5+E20 -> 53455.89 | G20: 52833.55 | H20: =($L20-$G20)/5+G20 -> 52462.84 | I20: =($L20-$G20)/5+H20 -> 52092.13 | J20: =($L20-$G20)/5+I20 -> 51721.42 | K20: =($L20-$G20)/5+J20 -> 51350.71 | L20: 50980 | M20: =($Q20-$L20)/5+L20 -> 51194.304 | N20: =($Q20-$L20)/5+M20 -> 51408.608 | O20: =($Q20-$L20)/5+N20 -> 51622.912 | P20: =($Q20-$L20)/5+O20 -> 51837.216 | Q20: 52051.52 | R20: =($V20-$Q20)/5+Q20 -> 52259.394 | S20: =($V20-$Q20)/5+R20 -> 52467.268 | T20: =($V20-$Q20)/5+S20 -> 52675.142 | U20: =($V20-$Q20)/5+T20 -> 52883.016 | V20: 53090.89 | W20: {=TREND($M20:$V20,$M$15:$V$15,W$15)} -> 53307.337 | X20: {=TREND($M20:$V20,$M$15:$V$15,X$15)} -> 53517.939 | Y20: {=TREND($M20:$V20,$M$15:$V$15,Y$15)} -> 53728.541 | Z20: {=TREND($M20:$V20,$M$15:$V$15,Z$15)} -> 53939.143 | AA20: {=TREND($M20:$V20,$M$15:$V$15,AA$15)} -> 54149.745 | AB20: {=TREND($M20:$V20,$M$15:$V$15,AB$15)} -> 54360.347 | AC20: {=TREND($M20:$V20,$M$15:$V$15,AC$15)} -> 54570.949 | AD20: {=TREND($M20:$V20,$M$15:$V$15,AD$15)} -> 54781.55 | ... AI20: {=TREND($M20:$V20,$M$15:$V$15,AI$15)} -> 55834.56 | AJ20: Freight HDV
A21: Tractor truck, long-haul | B21: 92843.9 | C21: =($G21-$B21)/5+B21 -> 91811.12 | D21: =($G21-$B21)/5+C21 -> 90778.34 | E21: =($G21-$B21)/5+D21 -> 89745.56 | F21: =($G21-$B21)/5+E21 -> 88712.78 | G21: 87680 | H21: =($L21-$G21)/5+G21 -> 87064.76 | I21: =($L21-$G21)/5+H21 -> 86449.52 | J21: =($L21-$G21)/5+I21 -> 85834.28 | K21: =($L21-$G21)/5+J21 -> 85219.04 | L21: 84603.8 | M21: =($Q21-$L21)/5+L21 -> 84959.44 | N21: =($Q21-$L21)/5+M21 -> 85315.08 | O21: =($Q21-$L21)/5+N21 -> 85670.72 | P21: =($Q21-$L21)/5+O21 -> 86026.36 | Q21: 86382 | R21: =($V21-$Q21)/5+Q21 -> 86726.98 | S21: =($V21-$Q21)/5+R21 -> 87071.96 | T21: =($V21-$Q21)/5+S21 -> 87416.94 | U21: =($V21-$Q21)/5+T21 -> 87761.92 | V21: 88106.9 | W21: {=TREND($M21:$V21,$M$15:$V$15,W$15)} -> 88466.093 | X21: {=TREND($M21:$V21,$M$15:$V$15,X$15)} -> 88815.596 | Y21: {=TREND($M21:$V21,$M$15:$V$15,Y$15)} -> 89165.098 | Z21: {=TREND($M21:$V21,$M$15:$V$15,Z$15)} -> 89514.601 | AA21: {=TREND($M21:$V21,$M$15:$V$15,AA$15)} -> 89864.103 | AB21: {=TREND($M21:$V21,$M$15:$V$15,AB$15)} -> 90213.605 | AC21: {=TREND($M21:$V21,$M$15:$V$15,AC$15)} -> 90563.108 | AD21: {=TREND($M21:$V21,$M$15:$V$15,AD$15)} -> 90912.61 | ... AI21: {=TREND($M21:$V21,$M$15:$V$15,AI$15)} -> 92660.122 | AJ21: Freight HDV
A22: Refuse truck | B22: 3614 | C22: =($G22-$B22)/5+B22 -> 3639 | D22: =($G22-$B22)/5+C22 -> 3664 | E22: =($G22-$B22)/5+D22 -> 3689 | F22: =($G22-$B22)/5+E22 -> 3714 | G22: 3739 | H22: =($L22-$G22)/5+G22 -> 3793.4 | I22: =($L22-$G22)/5+H22 -> 3847.8 | J22: =($L22-$G22)/5+I22 -> 3902.2 | K22: =($L22-$G22)/5+J22 -> 3956.6 | L22: 4011 | M22: =($Q22-$L22)/5+L22 -> 4108.8 | N22: =($Q22-$L22)/5+M22 -> 4206.6 | O22: =($Q22-$L22)/5+N22 -> 4304.4 | P22: =($Q22-$L22)/5+O22 -> 4402.2 | Q22: 4500 | R22: =($V22-$Q22)/5+Q22 -> 4595.4 | S22: =($V22-$Q22)/5+R22 -> 4690.8 | T22: =($V22-$Q22)/5+S22 -> 4786.2 | U22: =($V22-$Q22)/5+T22 -> 4881.6 | V22: 4977 | W22: {=TREND($M22:$V22,$M$15:$V$15,W$15)} -> 5075.6 | X22: {=TREND($M22:$V22,$M$15:$V$15,X$15)} -> 5172.0182 | Y22: {=TREND($M22:$V22,$M$15:$V$15,Y$15)} -> 5268.4364 | Z22: {=TREND($M22:$V22,$M$15:$V$15,Z$15)} -> 5364.8545 | AA22: {=TREND($M22:$V22,$M$15:$V$15,AA$15)} -> 5461.2727 | AB22: {=TREND($M22:$V22,$M$15:$V$15,AB$15)} -> 5557.6909 | AC22: {=TREND($M22:$V22,$M$15:$V$15,AC$15)} -> 5654.1091 | AD22: {=TREND($M22:$V22,$M$15:$V$15,AD$15)} -> 5750.5273 | ... AI22: {=TREND($M22:$V22,$M$15:$V$15,AI$15)} -> 6232.6182 | AJ22: Freight HDV
A23: Overall HDT | B23: =SUM(B17:B22) -> 482987.03 | G23: =SUM(G17:G22) -> 486280.05 | L23: =SUM(L17:L22) -> 506500.97 | Q23: =SUM(Q17:Q22) -> 554603.72 | V23: =SUM(V17:V22) -> 601485.96
A24: Small bus, 4-5 | B24: 4754.011 | C24: =($G24-$B24)/5+B24 -> 4754.1696 | D24: =($G24-$B24)/5+C24 -> 4754.3282 | E24: =($G24-$B24)/5+D24 -> 4754.4868 | F24: =($G24-$B24)/5+E24 -> 4754.6454 | G24: 4754.804 | H24: =($L24-$G24)/5+G24 -> 4784.2998 | I24: =($L24-$G24)/5+H24 -> 4813.7956 | J24: =($L24-$G24)/5+I24 -> 4843.2914 | K24: =($L24-$G24)/5+J24 -> 4872.7872 | L24: 4902.283 | M24: =($Q24-$L24)/5+L24 -> 4986.5684 | N24: =($Q24-$L24)/5+M24 -> 5070.8538 | O24: =($Q24-$L24)/5+N24 -> 5155.1392 | P24: =($Q24-$L24)/5+O24 -> 5239.4246 | Q24: 5323.71 | R24: =($V24-$Q24)/5+Q24 -> 5405.7774 | S24: =($V24-$Q24)/5+R24 -> 5487.8448 | T24: =($V24-$Q24)/5+S24 -> 5569.9122 | U24: =($V24-$Q24)/5+T24 -> 5651.9796 | V24: 5734.047 | W24: {=TREND($M24:$V24,$M$15:$V$15,W$15)} -> 5819.0717 | X24: {=TREND($M24:$V24,$M$15:$V$15,X$15)} -> 5902.0801 | Y24: {=TREND($M24:$V24,$M$15:$V$15,Y$15)} -> 5985.0885 | Z24: {=TREND($M24:$V24,$M$15:$V$15,Z$15)} -> 6068.0968 | AA24: {=TREND($M24:$V24,$M$15:$V$15,AA$15)} -> 6151.1052 | AB24: {=TREND($M24:$V24,$M$15:$V$15,AB$15)} -> 6234.1136 | AC24: {=TREND($M24:$V24,$M$15:$V$15,AC$15)} -> 6317.122 | AD24: {=TREND($M24:$V24,$M$15:$V$15,AD$15)} -> 6400.1303 | ... AI24: {=TREND($M24:$V24,$M$15:$V$15,AI$15)} -> 6815.1722 | AJ24: Passenger HDV
A25: Transit bus, 6-8 | B25: 5282.984 | C25: =($G25-$B25)/5+B25 -> 5283.158 | D25: =($G25-$B25)/5+C25 -> 5283.332 | E25: =($G25-$B25)/5+D25 -> 5283.506 | F25: =($G25-$B25)/5+E25 -> 5283.68 | G25: 5283.854 | H25: =($L25-$G25)/5+G25 -> 5316.6318 | I25: =($L25-$G25)/5+H25 -> 5349.4096 | J25: =($L25-$G25)/5+I25 -> 5382.1874 | K25: =($L25-$G25)/5+J25 -> 5414.9652 | L25: 5447.743 | M25: =($Q25-$L25)/5+L25 -> 5541.4026 | N25: =($Q25-$L25)/5+M25 -> 5635.0622 | O25: =($Q25-$L25)/5+N25 -> 5728.7218 | P25: =($Q25-$L25)/5+O25 -> 5822.3814 | Q25: 5916.041 | R25: =($V25-$Q25)/5+Q25 -> 6007.242 | S25: =($V25-$Q25)/5+R25 -> 6098.443 | T25: =($V25-$Q25)/5+S25 -> 6189.644 | U25: =($V25-$Q25)/5+T25 -> 6280.845 | V25: 6372.046 | W25: {=TREND($M25:$V25,$M$15:$V$15,W$15)} -> 6466.5251 | X25: {=TREND($M25:$V25,$M$15:$V$15,X$15)} -> 6558.7692 | Y25: {=TREND($M25:$V25,$M$15:$V$15,Y$15)} -> 6651.0132 | Z25: {=TREND($M25:$V25,$M$15:$V$15,Z$15)} -> 6743.2573 | AA25: {=TREND($M25:$V25,$M$15:$V$15,AA$15)} -> 6835.5013 | AB25: {=TREND($M25:$V25,$M$15:$V$15,AB$15)} -> 6927.7453 | AC25: {=TREND($M25:$V25,$M$15:$V$15,AC$15)} -> 7019.9894 | AD25: {=TREND($M25:$V25,$M$15:$V$15,AD$15)} -> 7112.2334 | ... AI25: {=TREND($M25:$V25,$M$15:$V$15,AI$15)} -> 7573.4536 | AJ25: Passenger HDV
A26: School bus, 6-8 | B26: 27044.907 | C26: =($G26-$B26)/5+B26 -> 27045.802 | D26: =($G26-$B26)/5+C26 -> 27046.698 | E26: =($G26-$B26)/5+D26 -> 27047.593 | F26: =($G26-$B26)/5+E26 -> 27048.489 | G26: 27049.384 | H26: =($L26-$G26)/5+G26 -> 27217.202 | I26: =($L26-$G26)/5+H26 -> 27385.02 | J26: =($L26-$G26)/5+I26 -> 27552.837 | K26: =($L26-$G26)/5+J26 -> 27720.655 | L26: 27888.473 | M26: =($Q26-$L26)/5+L26 -> 28367.96 | N26: =($Q26-$L26)/5+M26 -> 28847.447 | O26: =($Q26-$L26)/5+N26 -> 29326.934 | P26: =($Q26-$L26)/5+O26 -> 29806.421 | Q26: 30285.908 | R26: =($V26-$Q26)/5+Q26 -> 30752.794 | S26: =($V26-$Q26)/5+R26 -> 31219.68 | T26: =($V26-$Q26)/5+S26 -> 31686.566 | U26: =($V26-$Q26)/5+T26 -> 32153.452 | V26: 32620.338 | W26: {=TREND($M26:$V26,$M$15:$V$15,W$15)} -> 33104.025 | X26: {=TREND($M26:$V26,$M$15:$V$15,X$15)} -> 33576.257 | Y26: {=TREND($M26:$V26,$M$15:$V$15,Y$15)} -> 34048.489 | Z26: {=TREND($M26:$V26,$M$15:$V$15,Z$15)} -> 34520.721 | AA26: {=TREND($M26:$V26,$M$15:$V$15,AA$15)} -> 34992.953 | AB26: {=TREND($M26:$V26,$M$15:$V$15,AB$15)} -> 35465.185 | AC26: {=TREND($M26:$V26,$M$15:$V$15,AC$15)} -> 35937.417 | AD26: {=TREND($M26:$V26,$M$15:$V$15,AD$15)} -> 36409.648 | ... AI26: {=TREND($M26:$V26,$M$15:$V$15,AI$15)} -> 38770.808 | AJ26: Passenger HDV
A27: Other bus, 6-8 | B27: 16228.913 | C27: =($G27-$B27)/5+B27 -> 16229.455 | D27: =($G27-$B27)/5+C27 -> 16229.997 | E27: =($G27-$B27)/5+D27 -> 16230.539 | F27: =($G27-$B27)/5+E27 -> 16231.081 | G27: 16231.623 | H27: =($L27-$G27)/5+G27 -> 16332.309 | I27: =($L27-$G27)/5+H27 -> 16432.996 | J27: =($L27-$G27)/5+I27 -> 16533.682 | K27: =($L27-$G27)/5+J27 -> 16634.369 | L27: 16735.055 | M27: =($Q27-$L27)/5+L27 -> 17022.792 | N27: =($Q27-$L27)/5+M27 -> 17310.528 | O27: =($Q27-$L27)/5+N27 -> 17598.265 | P27: =($Q27-$L27)/5+O27 -> 17886.001 | Q27: 18173.738 | R27: =($V27-$Q27)/5+Q27 -> 18453.896 | S27: =($V27-$Q27)/5+R27 -> 18734.054 | T27: =($V27-$Q27)/5+S27 -> 19014.212 | U27: =($V27-$Q27)/5+T27 -> 19294.37 | V27: 19574.528 | W27: {=TREND($M27:$V27,$M$15:$V$15,W$15)} -> 19864.791 | X27: {=TREND($M27:$V27,$M$15:$V$15,X$15)} -> 20148.164 | Y27: {=TREND($M27:$V27,$M$15:$V$15,Y$15)} -> 20431.537 | Z27: {=TREND($M27:$V27,$M$15:$V$15,Z$15)} -> 20714.91 | AA27: {=TREND($M27:$V27,$M$15:$V$15,AA$15)} -> 20998.283 | AB27: {=TREND($M27:$V27,$M$15:$V$15,AB$15)} -> 21281.657 | AC27: {=TREND($M27:$V27,$M$15:$V$15,AC$15)} -> 21565.03 | AD27: {=TREND($M27:$V27,$M$15:$V$15,AD$15)} -> 21848.403 | ... AI27: {=TREND($M27:$V27,$M$15:$V$15,AI$15)} -> 23265.269 | AJ27: Passenger HDV
A28: Overall Bus | B28: =SUM(B24:B27) -> 53310.815 | G28: =SUM(G24:G27) -> 53319.665 | L28: =SUM(L24:L27) -> 54973.554 | Q28: =SUM(Q24:Q27) -> 59699.397 | V28: =SUM(V24:V27) -> 64300.959
B31: VKT per vehicle
B32: Average of VKTpVeh
B33: Row Labels | C33: 2020 | D33: 2021 | E33: 2022 | F33: 2023 | G33: 2024 | H33: 2025 | I33: 2026 | J33: 2027 | K33: 2028 | L33: 2029 | M33: 2030 | N33: 2031 | O33: 2032 | P33: 2033 | Q33: 2034 | R33: 2035 | S33: 2036 | T33: 2037 | U33: 2038 | V33: 2039 | W33: 2040 | X33: 2041 | Y33: 2042 | Z33: 2043 | AA33: 2044 | AB33: 2045 | AC33: 2046 | AD33: 2047 | AE33: 2048 | AF33: 2049 | AG33: 2050 | AH33: 2051 | AI33: 2052 | AJ33: 2053 | AK33: 2054 | AL33: 2055 | AM33: 2056 | AN33: 2057 | AO33: 2058 | AP33: 2059 | AQ33: 2060 | AR33: 2061 | AS33: 2062 | AT33: 2063 | AU33: 2064 | AV33: 2065 | AW33: 2066 | AX33: 2067 | AY33: 2068 | AZ33: 2069 | BA33: 2070 | BB33: (blank) | BC33: Grand Total
A34: bus | B34: Motor Home_4_5 | C34: 7282.1417 | D34: 7350.0019 | E34: 7417.8622 | F34: 7485.7225 | G34: 7553.5827 | H34: 7621.443 | I34: 7849.9524 | J34: 8078.4619 | K34: 8306.9713 | L34: 8535.4807 | M34: 8763.9902 | N34: 8847.3833 | O34: 8930.7764 | P34: 9014.1695 | Q34: 9097.5626 | R34: 9180.9557 | S34: 9222.1208 | T34: 9263.2859 | U34: 9304.451 | V34: 9345.6161 | W34: 9386.7812 | X34: 9369.1215 | Y34: 9351.4619 | Z34: 9333.8022 | AA34: 9316.1426 | AB34: 9298.4829 | AC34: 9319.9004 | AD34: 9341.3179 | AE34: 9362.7354 | AF34: 9384.1529 | AG34: 9405.5704 | AH34: 9452.4188 | AI34: 9499.2673 | AJ34: 9546.1157 | AK34: 9592.9642 | AL34: 9639.8126 | AM34: 9681.9088 | AN34: 9724.0049 | AO34: 9766.1011 | AP34: 9808.1972 | AQ34: 9850.2934 | AR34: 9850.2934 | AS34: 9850.2934 | AT34: 9850.2934 | AU34: 9850.2934 | AV34: 9850.2934 | AW34: 9850.2934 | AX34: 9850.2934 | AY34: 9850.2934 | AZ34: 9850.2934 | BA34: 9850.2934 | BC34: 8941.1253
A35: bus | B35: Motor Home_6_7 | C35: 8136.7393 | D35: 8129.8981 | E35: 8123.057 | F35: 8116.2159 | G35: 8109.3747 | H35: 8102.5336 | I35: 8172.6773 | J35: 8242.821 | K35: 8312.9647 | L35: 8383.1085 | M35: 8453.2522 | N35: 8557.9387 | O35: 8662.6252 | P35: 8767.3116 | Q35: 8871.9981 | R35: 8976.6846 | S35: 9033.8404 | T35: 9090.9962 | U35: 9148.1519 | V35: 9205.3077 | W35: 9262.4635 | X35: 9269.6668 | Y35: 9276.8702 | Z35: 9284.0736 | AA35: 9291.2769 | AB35: 9298.4803 | AC35: 9319.8974 | AD35: 9341.3146 | AE35: 9362.7317 | AF35: 9384.1488 | AG35: 9405.5659 | AH35: 9452.4154 | AI35: 9499.2649 | AJ35: 9546.1145 | AK35: 9592.964 | AL35: 9639.8135 | AM35: 9681.9107 | AN35: 9724.0079 | AO35: 9766.1051 | AP35: 9808.2023 | AQ35: 9850.2995 | AR35: 9850.2995 | AS35: 9850.2995 | AT35: 9850.2995 | AU35: 9850.2995 | AV35: 9850.2995 | AW35: 9850.2995 | AX35: 9850.2995 | AY35: 9850.2995 | AZ35: 9850.2995 | BA35: 9850.2995 | BC35: 9335.2229
A36: bus | B36: Motor Home_8 | C36: 8719.9367 | D36: 8710.9262 | E36: 8701.9157 | F36: 8692.9052 | G36: 8683.8947 | H36: 8674.8843 | I36: 8710.6316 | J36: 8746.3789 | K36: 8782.1261 | L36: 8817.8734 | M36: 8853.6207 | N36: 8903.4736 | O36: 8953.3264 | P36: 9003.1792 | Q36: 9053.032 | R36: 9102.8849 | S36: 9139.2061 | T36: 9175.5272 | U36: 9211.8484 | V36: 9248.1696 | W36: 9284.4908 | X36: 9287.2934 | Y36: 9290.0959 | Z36: 9292.8985 | AA36: 9295.701 | AB36: 9298.5036 | AC36: 9319.9193 | AD36: 9341.335 | AE36: 9362.7507 | AF36: 9384.1664 | AG36: 9405.582 | AH36: 9452.4314 | AI36: 9499.2808 | AJ36: 9546.1301 | AK36: 9592.9795 | AL36: 9639.8288 | AM36: 9681.927 | AN36: 9724.0251 | AO36: 9766.1233 | AP36: 9808.2214 | AQ36: 9850.3195 | AR36: 9850.3195 | AS36: 9850.3195 | AT36: 9850.3195 | AU36: 9850.3195 | AV36: 9850.3195 | AW36: 9850.3195 | AX36: 9850.3195 | AY36: 9850.3195 | AZ36: 9850.3195 | BA36: 9850.3195 | BC36: 9449.9949
A37: bus | B37: Other Buses_4_5 | C37: 47403.343 | D37: 47370.819 | E37: 47338.296 | F37: 47305.773 | G37: 47273.25 | H37: 47240.726 | I37: 47313.685 | J37: 47386.644 | K37: 47459.602 | L37: 47532.561 | M37: 47605.52 | N37: 47813.84 | O37: 48022.161 | P37: 48230.482 | Q37: 48438.802 | R37: 48647.123 | S37: 49000.983 | T37: 49354.842 | U37: 49708.702 | V37: 50062.561 | W37: 50416.421 | X37: 50436.532 | Y37: 50456.643 | Z37: 50476.753 | AA37: 50496.864 | AB37: 50516.975 | AC37: 50482.109 | AD37: 50447.243 | AE37: 50412.377 | AF37: 50377.511 | AG37: 50342.645 | AH37: 50354.082 | AI37: 50365.519 | AJ37: 50376.956 | AK37: 50388.393 | AL37: 50399.83 | AM37: 50409.758 | AN37: 50419.687 | AO37: 50429.615 | AP37: 50439.543 | AQ37: 50449.472 | AR37: 50449.472 | AS37: 50449.472 | AT37: 50449.472 | AU37: 50449.472 | AV37: 50449.472 | AW37: 50449.472 | AX37: 50449.472 | AY37: 50449.472 | AZ37: 50449.472 | BA37: 50449.472 | BC37: 49876.036
A38: Other bus, 6-8 | B38: Other Buses_6_7 | C38: 46342.195 | D38: 46524.8 | E38: 46707.405 | F38: 46890.011 | G38: 47072.616 | H38: 47255.221 | I38: 47488.017 | J38: 47720.814 | K38: 47953.61 | L38: 48186.406 | M38: 48419.202 | N38: 48697.121 | O38: 48975.039 | P38: 49252.958 | Q38: 49530.877 | R38: 49808.796 | S38: 50037.092 | T38: 50265.388 | U38: 50493.684 | V38: 50721.98 | W38: 50950.276 | X38: 50863.641 | Y38: 50777.005 | Z38: 50690.369 | AA38: 50603.734 | AB38: 50517.098 | AC38: 50482.235 | AD38: 50447.372 | AE38: 50412.509 | AF38: 50377.646 | AG38: 50342.783 | AH38: 50354.218 | AI38: 50365.652 | AJ38: 50377.086 | AK38: 50388.521 | AL38: 50399.955 | AM38: 50409.891 | AN38: 50419.827 | AO38: 50429.764 | AP38: 50439.7 | AQ38: 50449.636 | AR38: 50449.636 | AS38: 50449.636 | AT38: 50449.636 | AU38: 50449.636 | AV38: 50449.636 | AW38: 50449.636 | AX38: 50449.636 | AY38: 50449.636 | AZ38: 50449.636 | BA38: 50449.636 | BC38: 48998.777
A39: Other bus, 6-8 | B39: Other Buses_8 | C39: 47278.158 | D39: 47569.074 | E39: 47859.99 | F39: 48150.905 | G39: 48441.821 | H39: 48732.737 | I39: 48956.527 | J39: 49180.316 | K39: 49404.106 | L39: 49627.896 | M39: 49851.686 | N39: 49992.598 | O39: 50133.51 | P39: 50274.421 | Q39: 50415.333 | R39: 50556.245 | S39: 50632.373 | T39: 50708.5 | U39: 50784.627 | V39: 50860.755 | W39: 50936.882 | X39: 50852.921 | Y39: 50768.96 | Z39: 50684.999 | AA39: 50601.038 | AB39: 50517.077 | AC39: 50482.206 | AD39: 50447.336 | AE39: 50412.466 | AF39: 50377.595 | AG39: 50342.725 | AH39: 50354.163 | AI39: 50365.601 | AJ39: 50377.038 | AK39: 50388.476 | AL39: 50399.914 | AM39: 50409.856 | AN39: 50419.798 | AO39: 50429.739 | AP39: 50439.681 | AQ39: 50449.623 | AR39: 50449.623 | AS39: 50449.623 | AT39: 50449.623 | AU39: 50449.623 | AV39: 50449.623 | AW39: 50449.623 | AX39: 50449.623 | AY39: 50449.623 | AZ39: 50449.623 | BA39: 50449.623 | BC39: 48193.856
A40: Small bus, 4-5 | B40: School Bus_4_5 | C40: 16553.996 | D40: 16490.021 | E40: 16426.045 | F40: 16362.07 | G40: 16298.094 | H40: 16234.119 | I40: 16231.142 | J40: 16228.165 | K40: 16225.188 | L40: 16222.21 | M40: 16219.233 | N40: 16279.774 | O40: 16340.315 | P40: 16400.857 | Q40: 16461.398 | R40: 16521.939 | S40: 16649.081 | T40: 16776.224 | U40: 16903.366 | V40: 17030.509 | W40: 17157.652 | X40: 17212.593 | Y40: 17267.535 | Z40: 17322.477 | AA40: 17377.419 | AB40: 17432.361 | AC40: 17419.188 | AD40: 17406.014 | AE40: 17392.841 | AF40: 17379.668 | AG40: 17366.495 | AH40: 17369.149 | AI40: 17371.803 | AJ40: 17374.456 | AK40: 17377.11 | AL40: 17379.764 | AM40: 17382.863 | AN40: 17385.963 | AO40: 17389.062 | AP40: 17392.161 | AQ40: 17395.26 | AR40: 17395.26 | AS40: 17395.26 | AT40: 17395.26 | AU40: 17395.26 | AV40: 17395.26 | AW40: 17395.26 | AX40: 17395.26 | AY40: 17395.26 | AZ40: 17395.26 | BA40: 17395.26 | BC40: 16842.3
A41: School bus, 6-8 | B41: School Bus_6_7 | C41: 16570.755 | D41: 16622.415 | E41: 16674.076 | F41: 16725.737 | G41: 16777.397 | H41: 16829.058 | I41: 16868.764 | J41: 16908.47 | K41: 16948.176 | L41: 16987.882 | M41: 17027.588 | N41: 17080.18 | O41: 17132.772 | P41: 17185.364 | Q41: 17237.957 | R41: 17290.549 | S41: 17338.471 | T41: 17386.392 | U41: 17434.314 | V41: 17482.236 | W41: 17530.157 | X41: 17510.594 | Y41: 17491.03 | Z41: 17471.466 | AA41: 17451.902 | AB41: 17432.339 | AC41: 17419.165 | AD41: 17405.992 | AE41: 17392.818 | AF41: 17379.645 | AG41: 17366.472 | AH41: 17369.128 | AI41: 17371.784 | AJ41: 17374.441 | AK41: 17377.097 | AL41: 17379.754 | AM41: 17382.852 | AN41: 17385.951 | AO41: 17389.049 | AP41: 17392.148 | AQ41: 17395.246 | AR41: 17395.246 | AS41: 17395.246 | AT41: 17395.246 | AU41: 17395.246 | AV41: 17395.246 | AW41: 17395.246 | AX41: 17395.246 | AY41: 17395.246 | AZ41: 17395.246 | BA41: 17395.246 | BC41: 16665.306
A42: School bus, 6-8 | B42: School Bus_8 | C42: 16704.542 | D42: 16744.325 | E42: 16784.109 | F42: 16823.892 | G42: 16863.675 | H42: 16903.458 | I42: 16930.018 | J42: 16956.578 | K42: 16983.137 | L42: 17009.697 | M42: 17036.256 | N42: 17092.803 | O42: 17149.349 | P42: 17205.895 | Q42: 17262.441 | R42: 17318.987 | S42: 17364.258 | T42: 17409.529 | U42: 17454.8 | V42: 17500.072 | W42: 17545.343 | X42: 17522.743 | Y42: 17500.144 | Z42: 17477.544 | AA42: 17454.944 | AB42: 17432.345 | AC42: 17419.171 | AD42: 17405.996 | AE42: 17392.822 | AF42: 17379.648 | AG42: 17366.474 | AH42: 17369.128 | AI42: 17371.782 | AJ42: 17374.436 | AK42: 17377.091 | AL42: 17379.745 | AM42: 17382.843 | AN42: 17385.941 | AO42: 17389.038 | AP42: 17392.136 | AQ42: 17395.234 | AR42: 17395.234 | AS42: 17395.234 | AT42: 17395.234 | AU42: 17395.234 | AV42: 17395.234 | AW42: 17395.234 | AX42: 17395.234 | AY42: 17395.234 | AZ42: 17395.234 | BA42: 17395.234 | BC42: 16757.077
A43: Small bus, 4-5 | B43: Transit Bus_4_5 | C43: 48680.059 | D43: 48531.565 | E43: 48383.072 | F43: 48234.578 | G43: 48086.084 | H43: 47937.59 | I43: 47927.116 | J43: 47916.641 | K43: 47906.167 | L43: 47895.692 | M43: 47885.217 | N43: 47968.701 | O43: 48052.184 | P43: 48135.667 | Q43: 48219.151 | R43: 48302.634 | S43: 48572.494 | T43: 48842.354 | U43: 49112.213 | V43: 49382.073 | W43: 49651.933 | X43: 49714.263 | Y43: 49776.593 | Z43: 49838.923 | AA43: 49901.253 | AB43: 49963.584 | AC43: 49892.911 | AD43: 49822.238 | AE43: 49751.565 | AF43: 49680.892 | AG43: 49610.219 | AH43: 49619.684 | AI43: 49629.149 | AJ43: 49638.614 | AK43: 49648.078 | AL43: 49657.543 | AM43: 49669.802 | AN43: 49682.062 | AO43: 49694.321 | AP43: 49706.58 | AQ43: 49718.84 | AR43: 49718.84 | AS43: 49718.84 | AT43: 49718.84 | AU43: 49718.84 | AV43: 49718.84 | AW43: 49718.84 | AX43: 49718.84 | AY43: 49718.84 | AZ43: 49718.84 | BA43: 49718.84 | BC43: 49997.894
A44: Transit bus, 6-8 | B44: Transit Bus_6_7 | C44: 48928.255 | D44: 48905.951 | E44: 48883.647 | F44: 48861.343 | G44: 48839.039 | H44: 48816.735 | I44: 48853.19 | J44: 48889.644 | K44: 48926.098 | L44: 48962.553 | M44: 48999.007 | N44: 49142.052 | O44: 49285.097 | P44: 49428.142 | Q44: 49571.187 | R44: 49714.232 | S44: 49870.382 | T44: 50026.531 | U44: 50182.68 | V44: 50338.829 | W44: 50494.979 | X44: 50388.725 | Y44: 50282.472 | Z44: 50176.219 | AA44: 50069.966 | AB44: 49963.713 | AC44: 49893.036 | AD44: 49822.36 | AE44: 49751.684 | AF44: 49681.007 | AG44: 49610.331 | AH44: 49619.804 | AI44: 49629.276 | AJ44: 49638.749 | AK44: 49648.222 | AL44: 49657.695 | AM44: 49669.953 | AN44: 49682.211 | AO44: 49694.469 | AP44: 49706.726 | AQ44: 49718.984 | AR44: 49718.984 | AS44: 49718.984 | AT44: 49718.984 | AU44: 49718.984 | AV44: 49718.984 | AW44: 49718.984 | AX44: 49718.984 | AY44: 49718.984 | AZ44: 49718.984 | BA44: 49718.984 | BC44: 49806.33
A45: Transit bus, 6-8 | B45: Transit Bus_8 | C45: 41840.804 | D45: 40833.384 | E45: 39825.965 | F45: 38818.545 | G45: 37811.126 | H45: 36803.706 | I45: 35882.536 | J45: 34961.366 | K45: 34040.196 | L45: 33119.026 | M45: 32197.856 | N45: 31358.835 | O45: 30519.814 | P45: 29680.793 | Q45: 28841.773 | R45: 28002.752 | S45: 28002.752 | T45: 28002.752 | U45: 28002.752 | V45: 28002.752 | W45: 28002.752 | X45: 28002.752 | Y45: 28002.752 | Z45: 28002.752 | AA45: 28002.752 | AB45: 28002.752 | AC45: 28002.752 | AD45: 28002.752 | AE45: 28002.752 | AF45: 28002.752 | AG45: 28002.752 | AH45: 28002.752 | AI45: 28002.752 | AJ45: 28002.752 | AK45: 28002.752 | AL45: 28002.752 | AM45: 28002.752 | AN45: 28002.752 | AO45: 28002.752 | AP45: 28002.752 | AQ45: 28002.752 | AR45: 28002.752 | AS45: 28002.752 | AT45: 28002.752 | AU45: 28002.752 | AV45: 28002.752 | AW45: 28002.752 | AX45: 28002.752 | AY45: 28002.752 | AZ45: 28002.752 | BA45: 28002.752 | BC45: 32848.683
... A71: Rigid truck, 8 | B71: Single Unit Short-haul Truck_8 | C71: 22089.612 | D71: 22254.831 | E71: 22420.049 | F71: 22585.267 | G71: 22750.485 | H71: 22915.703 | I71: 22961.06 | J71: 23006.417 | K71: 23051.774 | L71: 23097.132 | M71: 23142.489 | N71: 23237.179 | O71: 23331.869 | P71: 23426.559 | Q71: 23521.249 | R71: 23615.939 | S71: 23667.042 | T71: 23718.146 | U71: 23769.249 | V71: 23820.353 | W71: 23871.456 | X71: 23825.96 | Y71: 23780.463 | Z71: 23734.966 | AA71: 23689.47 | AB71: 23643.973 | AC71: 23696.146 | AD71: 23748.318 | AE71: 23800.49 | AF71: 23852.663 | AG71: 23904.835 | AH71: 23991.658 | AI71: 24078.481 | AJ71: 24165.304 | AK71: 24252.126 | AL71: 24338.949 | AM71: 24427.753 | AN71: 24516.557 | AO71: 24605.361 | AP71: 24694.164 | AQ71: 24782.968 | AR71: 24782.968 | AS71: 24782.968 | AT71: 24782.968 | AU71: 24782.968 | AV71: 24782.968 | AW71: 24782.968 | AX71: 24782.968 | AY71: 24782.968 | AZ71: 24782.968 | BA71: 24782.968 | BC71: 23473.478
B72: (blank)
B73: Grand Total | C73: 36212.918 | D73: 35995.436 | E73: 35777.955 | F73: 35560.474 | G73: 35342.993 | H73: 35125.512 | I73: 35092.616 | J73: 35059.721 | K73: 35026.826 | L73: 34993.93 | M73: 34961.035 | N73: 35044.534 | O73: 35128.033 | P73: 35211.532 | Q73: 35295.032 | R73: 35378.531 | S73: 35519.507 | T73: 35660.484 | U73: 35801.46 | V73: 35942.437 | W73: 36083.413 | X73: 36110.468 | Y73: 36137.523 | Z73: 36164.578 | AA73: 36191.633 | AB73: 36218.688 | AC73: 36304.421 | AD73: 36390.153 | AE73: 36475.886 | AF73: 36561.618 | AG73: 36647.351 | AH73: 36746.835 | AI73: 36846.32 | AJ73: 36945.804 | AK73: 37045.289 | AL73: 37144.773 | AM73: 37248.896 | AN73: 37353.018 | AO73: 37457.141 | AP73: 37561.263 | AQ73: 37665.385 | AR73: 37665.385 | AS73: 37665.385 | AT73: 37665.385 | AU73: 37665.385 | AV73: 37665.385 | AW73: 37665.385 | AX73: 37665.385 | AY73: 37665.385 | AZ73: 37665.385 | BA73: 37665.385 | BC73: 36810.263
A76: Total Vehicle Kilometers by Vehicle Type | B76: EPS Vehicle Type | C76: 2020 | D76: 2021 | E76: 2022 | F76: 2023 | G76: 2024 | H76: 2025 | I76: 2026 | J76: 2027 | K76: 2028 | L76: 2029 | M76: 2030 | N76: 2031 | O76: 2032 | P76: 2033 | Q76: 2034 | R76: 2035 | S76: 2036 | T76: 2037 | U76: 2038 | V76: 2039 | W76: 2040 | X76: 2041 | Y76: 2042 | Z76: 2043 | AA76: 2044 | AB76: 2045 | AC76: 2046 | AD76: 2047 | AE76: 2048 | AF76: 2049 | AG76: 2050
A77: Rigid truck, 4-5 | B77: =INDEX($AJ$17:$AJ$28,MATCH(A77,$A$17:$A$28,0),1) -> Freight LDV | C77: {=SUMPRODUCT(IF($A$34:$A$71=$A77,C$34:C$71),IF($A$34:$A$71=$A77,C$34:C$71))/SUMIF($A$34:$A$71,$A77,C$34:C$71)} -> 28710.322 | D77: {=SUMPRODUCT(IF($A$34:$A$71=$A77,D$34:D$71),IF($A$34:$A$71=$A77,D$34:D$71))/SUMIF($A$34:$A$71,$A77,D$34:D$71)} -> 28740.361 | E77: {=SUMPRODUCT(IF($A$34:$A$71=$A77,E$34:E$71),IF($A$34:$A$71=$A77,E$34:E$71))/SUMIF($A$34:$A$71,$A77,E$34:E$71)} -> 28770.64 | F77: {=SUMPRODUCT(IF($A$34:$A$71=$A77,F$34:F$71),IF($A$34:$A$71=$A77,F$34:F$71))/SUMIF($A$34:$A$71,$A77,F$34:F$71)} -> 28801.159 | G77: {=SUMPRODUCT(IF($A$34:$A$71=$A77,G$34:G$71),IF($A$34:$A$71=$A77,G$34:G$71))/SUMIF($A$34:$A$71,$A77,G$34:G$71)} -> 28831.917 | H77: {=SUMPRODUCT(IF($A$34:$A$71=$A77,H$34:H$71),IF($A$34:$A$71=$A77,H$34:H$71))/SUMIF($A$34:$A$71,$A77,H$34:H$71)} -> 28862.915 | I77: {=SUMPRODUCT(IF($A$34:$A$71=$A77,I$34:I$71),IF($A$34:$A$71=$A77,I$34:I$71))/SUMIF($A$34:$A$71,$A77,I$34:I$71)} -> 28717.2 | J77: {=SUMPRODUCT(IF($A$34:$A$71=$A77,J$34:J$71),IF($A$34:$A$71=$A77,J$34:J$71))/SUMIF($A$34:$A$71,$A77,J$34:J$71)} -> 28573.838 | ... AG77: {=SUMPRODUCT(IF($A$34:$A$71=$A77,AG$34:AG$71),IF($A$34:$A$71=$A77,AG$34:AG$71))/SUMIF($A$34:$A$71,$A77,AG$34:AG$71)} -> 31285.333
A78: Rigid truck, 6-7 | B78: =INDEX($AJ$17:$AJ$28,MATCH(A78,$A$17:$A$28,0),1) -> Freight LDV | C78: {=SUMPRODUCT(IF($A$34:$A$71=$A78,C$34:C$71),IF($A$34:$A$71=$A78,C$34:C$71))/SUMIF($A$34:$A$71,$A78,C$34:C$71)} -> 28744.398 | D78: {=SUMPRODUCT(IF($A$34:$A$71=$A78,D$34:D$71),IF($A$34:$A$71=$A78,D$34:D$71))/SUMIF($A$34:$A$71,$A78,D$34:D$71)} -> 28676.968 | E78: {=SUMPRODUCT(IF($A$34:$A$71=$A78,E$34:E$71),IF($A$34:$A$71=$A78,E$34:E$71))/SUMIF($A$34:$A$71,$A78,E$34:E$71)} -> 28610.936 | F78: {=SUMPRODUCT(IF($A$34:$A$71=$A78,F$34:F$71),IF($A$34:$A$71=$A78,F$34:F$71))/SUMIF($A$34:$A$71,$A78,F$34:F$71)} -> 28546.303 | G78: {=SUMPRODUCT(IF($A$34:$A$71=$A78,G$34:G$71),IF($A$34:$A$71=$A78,G$34:G$71))/SUMIF($A$34:$A$71,$A78,G$34:G$71)} -> 28483.071 | H78: {=SUMPRODUCT(IF($A$34:$A$71=$A78,H$34:H$71),IF($A$34:$A$71=$A78,H$34:H$71))/SUMIF($A$34:$A$71,$A78,H$34:H$71)} -> 28421.24 | I78: {=SUMPRODUCT(IF($A$34:$A$71=$A78,I$34:I$71),IF($A$34:$A$71=$A78,I$34:I$71))/SUMIF($A$34:$A$71,$A78,I$34:I$71)} -> 28580.672 | J78: {=SUMPRODUCT(IF($A$34:$A$71=$A78,J$34:J$71),IF($A$34:$A$71=$A78,J$34:J$71))/SUMIF($A$34:$A$71,$A78,J$34:J$71)} -> 28740.916 | ... AG78: {=SUMPRODUCT(IF($A$34:$A$71=$A78,AG$34:AG$71),IF($A$34:$A$71=$A78,AG$34:AG$71))/SUMIF($A$34:$A$71,$A78,AG$34:AG$71)} -> 31285.315
A79: Rigid truck, 8 | B79: =INDEX($AJ$17:$AJ$28,MATCH(A79,$A$17:$A$28,0),1) -> Freight HDV | C79: {=SUMPRODUCT(IF($A$34:$A$71=$A79,C$34:C$71),IF($A$34:$A$71=$A79,C$34:C$71))/SUMIF($A$34:$A$71,$A79,C$34:C$71)} -> 29842.882 | D79: {=SUMPRODUCT(IF($A$34:$A$71=$A79,D$34:D$71),IF($A$34:$A$71=$A79,D$34:D$71))/SUMIF($A$34:$A$71,$A79,D$34:D$71)} -> 29958.388 | E79: {=SUMPRODUCT(IF($A$34:$A$71=$A79,E$34:E$71),IF($A$34:$A$71=$A79,E$34:E$71))/SUMIF($A$34:$A$71,$A79,E$34:E$71)} -> 30074.143 | F79: {=SUMPRODUCT(IF($A$34:$A$71=$A79,F$34:F$71),IF($A$34:$A$71=$A79,F$34:F$71))/SUMIF($A$34:$A$71,$A79,F$34:F$71)} -> 30190.144 | G79: {=SUMPRODUCT(IF($A$34:$A$71=$A79,G$34:G$71),IF($A$34:$A$71=$A79,G$34:G$71))/SUMIF($A$34:$A$71,$A79,G$34:G$71)} -> 30306.388 | H79: {=SUMPRODUCT(IF($A$34:$A$71=$A79,H$34:H$71),IF($A$34:$A$71=$A79,H$34:H$71))/SUMIF($A$34:$A$71,$A79,H$34:H$71)} -> 30422.871 | I79: {=SUMPRODUCT(IF($A$34:$A$71=$A79,I$34:I$71),IF($A$34:$A$71=$A79,I$34:I$71))/SUMIF($A$34:$A$71,$A79,I$34:I$71)} -> 30408.455 | J79: {=SUMPRODUCT(IF($A$34:$A$71=$A79,J$34:J$71),IF($A$34:$A$71=$A79,J$34:J$71))/SUMIF($A$34:$A$71,$A79,J$34:J$71)} -> 30394.163 | ... AG79: {=SUMPRODUCT(IF($A$34:$A$71=$A79,AG$34:AG$71),IF($A$34:$A$71=$A79,AG$34:AG$71))/SUMIF($A$34:$A$71,$A79,AG$34:AG$71)} -> 31285.351
A80: Tractor truck, short-haul | B80: =INDEX($AJ$17:$AJ$28,MATCH(A80,$A$17:$A$28,0),1) -> Freight HDV | C80: {=SUMPRODUCT(IF($A$34:$A$71=$A80,C$34:C$71),IF($A$34:$A$71=$A80,C$34:C$71))/SUMIF($A$34:$A$71,$A80,C$34:C$71)} -> 75846.447 | D80: {=SUMPRODUCT(IF($A$34:$A$71=$A80,D$34:D$71),IF($A$34:$A$71=$A80,D$34:D$71))/SUMIF($A$34:$A$71,$A80,D$34:D$71)} -> 74745.588 | E80: {=SUMPRODUCT(IF($A$34:$A$71=$A80,E$34:E$71),IF($A$34:$A$71=$A80,E$34:E$71))/SUMIF($A$34:$A$71,$A80,E$34:E$71)} -> 73758.185 | F80: {=SUMPRODUCT(IF($A$34:$A$71=$A80,F$34:F$71),IF($A$34:$A$71=$A80,F$34:F$71))/SUMIF($A$34:$A$71,$A80,F$34:F$71)} -> 72884.635 | G80: {=SUMPRODUCT(IF($A$34:$A$71=$A80,G$34:G$71),IF($A$34:$A$71=$A80,G$34:G$71))/SUMIF($A$34:$A$71,$A80,G$34:G$71)} -> 72125.337 | H80: {=SUMPRODUCT(IF($A$34:$A$71=$A80,H$34:H$71),IF($A$34:$A$71=$A80,H$34:H$71))/SUMIF($A$34:$A$71,$A80,H$34:H$71)} -> 71480.694 | I80: {=SUMPRODUCT(IF($A$34:$A$71=$A80,I$34:I$71),IF($A$34:$A$71=$A80,I$34:I$71))/SUMIF($A$34:$A$71,$A80,I$34:I$71)} -> 70922.611 | J80: {=SUMPRODUCT(IF($A$34:$A$71=$A80,J$34:J$71),IF($A$34:$A$71=$A80,J$34:J$71))/SUMIF($A$34:$A$71,$A80,J$34:J$71)} -> 70413.121 | ... AG80: {=SUMPRODUCT(IF($A$34:$A$71=$A80,AG$34:AG$71),IF($A$34:$A$71=$A80,AG$34:AG$71))/SUMIF($A$34:$A$71,$A80,AG$34:AG$71)} -> 72626.878
A81: Tractor truck, long-haul | B81: =INDEX($AJ$17:$AJ$28,MATCH(A81,$A$17:$A$28,0),1) -> Freight HDV | C81: {=SUMPRODUCT(IF($A$34:$A$71=$A81,C$34:C$71),IF($A$34:$A$71=$A81,C$34:C$71))/SUMIF($A$34:$A$71,$A81,C$34:C$71)} -> 157391.05 | D81: {=SUMPRODUCT(IF($A$34:$A$71=$A81,D$34:D$71),IF($A$34:$A$71=$A81,D$34:D$71))/SUMIF($A$34:$A$71,$A81,D$34:D$71)} -> 155345.29 | E81: {=SUMPRODUCT(IF($A$34:$A$71=$A81,E$34:E$71),IF($A$34:$A$71=$A81,E$34:E$71))/SUMIF($A$34:$A$71,$A81,E$34:E$71)} -> 153379.8 | F81: {=SUMPRODUCT(IF($A$34:$A$71=$A81,F$34:F$71),IF($A$34:$A$71=$A81,F$34:F$71))/SUMIF($A$34:$A$71,$A81,F$34:F$71)} -> 151498.63 | G81: {=SUMPRODUCT(IF($A$34:$A$71=$A81,G$34:G$71),IF($A$34:$A$71=$A81,G$34:G$71))/SUMIF($A$34:$A$71,$A81,G$34:G$71)} -> 149706.09 | H81: {=SUMPRODUCT(IF($A$34:$A$71=$A81,H$34:H$71),IF($A$34:$A$71=$A81,H$34:H$71))/SUMIF($A$34:$A$71,$A81,H$34:H$71)} -> 148006.79 | I81: {=SUMPRODUCT(IF($A$34:$A$71=$A81,I$34:I$71),IF($A$34:$A$71=$A81,I$34:I$71))/SUMIF($A$34:$A$71,$A81,I$34:I$71)} -> 146843.95 | J81: {=SUMPRODUCT(IF($A$34:$A$71=$A81,J$34:J$71),IF($A$34:$A$71=$A81,J$34:J$71))/SUMIF($A$34:$A$71,$A81,J$34:J$71)} -> 145721.67 | ... AG81: {=SUMPRODUCT(IF($A$34:$A$71=$A81,AG$34:AG$71),IF($A$34:$A$71=$A81,AG$34:AG$71))/SUMIF($A$34:$A$71,$A81,AG$34:AG$71)} -> 151273.58
A82: Refuse truck | B82: =INDEX($AJ$17:$AJ$28,MATCH(A82,$A$17:$A$28,0),1) -> Freight HDV | C82: {=SUMPRODUCT(IF($A$34:$A$71=$A82,C$34:C$71),IF($A$34:$A$71=$A82,C$34:C$71))/SUMIF($A$34:$A$71,$A82,C$34:C$71)} -> 26260.099 | D82: {=SUMPRODUCT(IF($A$34:$A$71=$A82,D$34:D$71),IF($A$34:$A$71=$A82,D$34:D$71))/SUMIF($A$34:$A$71,$A82,D$34:D$71)} -> 26546.403 | E82: {=SUMPRODUCT(IF($A$34:$A$71=$A82,E$34:E$71),IF($A$34:$A$71=$A82,E$34:E$71))/SUMIF($A$34:$A$71,$A82,E$34:E$71)} -> 26863.984 | F82: {=SUMPRODUCT(IF($A$34:$A$71=$A82,F$34:F$71),IF($A$34:$A$71=$A82,F$34:F$71))/SUMIF($A$34:$A$71,$A82,F$34:F$71)} -> 27213.576 | G82: {=SUMPRODUCT(IF($A$34:$A$71=$A82,G$34:G$71),IF($A$34:$A$71=$A82,G$34:G$71))/SUMIF($A$34:$A$71,$A82,G$34:G$71)} -> 27595.935 | H82: {=SUMPRODUCT(IF($A$34:$A$71=$A82,H$34:H$71),IF($A$34:$A$71=$A82,H$34:H$71))/SUMIF($A$34:$A$71,$A82,H$34:H$71)} -> 28011.843 | I82: {=SUMPRODUCT(IF($A$34:$A$71=$A82,I$34:I$71),IF($A$34:$A$71=$A82,I$34:I$71))/SUMIF($A$34:$A$71,$A82,I$34:I$71)} -> 28396.124 | J82: {=SUMPRODUCT(IF($A$34:$A$71=$A82,J$34:J$71),IF($A$34:$A$71=$A82,J$34:J$71))/SUMIF($A$34:$A$71,$A82,J$34:J$71)} -> 28780.696 | ... AG82: {=SUMPRODUCT(IF($A$34:$A$71=$A82,AG$34:AG$71),IF($A$34:$A$71=$A82,AG$34:AG$71))/SUMIF($A$34:$A$71,$A82,AG$34:AG$71)} -> 34069.905
A83: Small bus, 4-5 | B83: =INDEX($AJ$17:$AJ$28,MATCH(A83,$A$17:$A$28,0),1) -> Passenger HDV | C83: {=SUMPRODUCT(IF($A$34:$A$71=$A83,C$34:C$71),IF($A$34:$A$71=$A83,C$34:C$71))/SUMIF($A$34:$A$71,$A83,C$34:C$71)} -> 40527.65 | D83: {=SUMPRODUCT(IF($A$34:$A$71=$A83,D$34:D$71),IF($A$34:$A$71=$A83,D$34:D$71))/SUMIF($A$34:$A$71,$A83,D$34:D$71)} -> 40405.56 | E83: {=SUMPRODUCT(IF($A$34:$A$71=$A83,E$34:E$71),IF($A$34:$A$71=$A83,E$34:E$71))/SUMIF($A$34:$A$71,$A83,E$34:E$71)} -> 40283.477 | F83: {=SUMPRODUCT(IF($A$34:$A$71=$A83,F$34:F$71),IF($A$34:$A$71=$A83,F$34:F$71))/SUMIF($A$34:$A$71,$A83,F$34:F$71)} -> 40161.4 | G83: {=SUMPRODUCT(IF($A$34:$A$71=$A83,G$34:G$71),IF($A$34:$A$71=$A83,G$34:G$71))/SUMIF($A$34:$A$71,$A83,G$34:G$71)} -> 40039.33 | H83: {=SUMPRODUCT(IF($A$34:$A$71=$A83,H$34:H$71),IF($A$34:$A$71=$A83,H$34:H$71))/SUMIF($A$34:$A$71,$A83,H$34:H$71)} -> 39917.266 | I83: {=SUMPRODUCT(IF($A$34:$A$71=$A83,I$34:I$71),IF($A$34:$A$71=$A83,I$34:I$71))/SUMIF($A$34:$A$71,$A83,I$34:I$71)} -> 39908.478 | J83: {=SUMPRODUCT(IF($A$34:$A$71=$A83,J$34:J$71),IF($A$34:$A$71=$A83,J$34:J$71))/SUMIF($A$34:$A$71,$A83,J$34:J$71)} -> 39899.689 | ... AG83: {=SUMPRODUCT(IF($A$34:$A$71=$A83,AG$34:AG$71),IF($A$34:$A$71=$A83,AG$34:AG$71))/SUMIF($A$34:$A$71,$A83,AG$34:AG$71)} -> 41249.695
A84: Transit bus, 6-8 | B84: =INDEX($AJ$17:$AJ$28,MATCH(A84,$A$17:$A$28,0),1) -> Passenger HDV | C84: {=SUMPRODUCT(IF($A$34:$A$71=$A84,C$34:C$71),IF($A$34:$A$71=$A84,C$34:C$71))/SUMIF($A$34:$A$71,$A84,C$34:C$71)} -> 45661.232 | D84: {=SUMPRODUCT(IF($A$34:$A$71=$A84,D$34:D$71),IF($A$34:$A$71=$A84,D$34:D$71))/SUMIF($A$34:$A$71,$A84,D$34:D$71)} -> 45232.755 | E84: {=SUMPRODUCT(IF($A$34:$A$71=$A84,E$34:E$71),IF($A$34:$A$71=$A84,E$34:E$71))/SUMIF($A$34:$A$71,$A84,E$34:E$71)} -> 44817.223 | F84: {=SUMPRODUCT(IF($A$34:$A$71=$A84,F$34:F$71),IF($A$34:$A$71=$A84,F$34:F$71))/SUMIF($A$34:$A$71,$A84,F$34:F$71)} -> 44415.092 | G84: {=SUMPRODUCT(IF($A$34:$A$71=$A84,G$34:G$71),IF($A$34:$A$71=$A84,G$34:G$71))/SUMIF($A$34:$A$71,$A84,G$34:G$71)} -> 44026.841 | H84: {=SUMPRODUCT(IF($A$34:$A$71=$A84,H$34:H$71),IF($A$34:$A$71=$A84,H$34:H$71))/SUMIF($A$34:$A$71,$A84,H$34:H$71)} -> 43652.969 | I84: {=SUMPRODUCT(IF($A$34:$A$71=$A84,I$34:I$71),IF($A$34:$A$71=$A84,I$34:I$71))/SUMIF($A$34:$A$71,$A84,I$34:I$71)} -> 43360.584 | J84: {=SUMPRODUCT(IF($A$34:$A$71=$A84,J$34:J$71),IF($A$34:$A$71=$A84,J$34:J$71))/SUMIF($A$34:$A$71,$A84,J$34:J$71)} -> 43082.3 | ... AG84: {=SUMPRODUCT(IF($A$34:$A$71=$A84,AG$34:AG$71),IF($A$34:$A$71=$A84,AG$34:AG$71))/SUMIF($A$34:$A$71,$A84,AG$34:AG$71)} -> 41814.33
A85: School bus, 6-8 | B85: =INDEX($AJ$17:$AJ$28,MATCH(A85,$A$17:$A$28,0),1) -> Passenger HDV | C85: {=SUMPRODUCT(IF($A$34:$A$71=$A85,C$34:C$71),IF($A$34:$A$71=$A85,C$34:C$71))/SUMIF($A$34:$A$71,$A85,C$34:C$71)} -> 16637.917 | D85: {=SUMPRODUCT(IF($A$34:$A$71=$A85,D$34:D$71),IF($A$34:$A$71=$A85,D$34:D$71))/SUMIF($A$34:$A$71,$A85,D$34:D$71)} -> 16683.593 | E85: {=SUMPRODUCT(IF($A$34:$A$71=$A85,E$34:E$71),IF($A$34:$A$71=$A85,E$34:E$71))/SUMIF($A$34:$A$71,$A85,E$34:E$71)} -> 16729.273 | F85: {=SUMPRODUCT(IF($A$34:$A$71=$A85,F$34:F$71),IF($A$34:$A$71=$A85,F$34:F$71))/SUMIF($A$34:$A$71,$A85,F$34:F$71)} -> 16774.958 | G85: {=SUMPRODUCT(IF($A$34:$A$71=$A85,G$34:G$71),IF($A$34:$A$71=$A85,G$34:G$71))/SUMIF($A$34:$A$71,$A85,G$34:G$71)} -> 16820.647 | H85: {=SUMPRODUCT(IF($A$34:$A$71=$A85,H$34:H$71),IF($A$34:$A$71=$A85,H$34:H$71))/SUMIF($A$34:$A$71,$A85,H$34:H$71)} -> 16866.34 | I85: {=SUMPRODUCT(IF($A$34:$A$71=$A85,I$34:I$71),IF($A$34:$A$71=$A85,I$34:I$71))/SUMIF($A$34:$A$71,$A85,I$34:I$71)} -> 16899.446 | J85: {=SUMPRODUCT(IF($A$34:$A$71=$A85,J$34:J$71),IF($A$34:$A$71=$A85,J$34:J$71))/SUMIF($A$34:$A$71,$A85,J$34:J$71)} -> 16932.558 | ... AG85: {=SUMPRODUCT(IF($A$34:$A$71=$A85,AG$34:AG$71),IF($A$34:$A$71=$A85,AG$34:AG$71))/SUMIF($A$34:$A$71,$A85,AG$34:AG$71)} -> 17366.473
A86: Other bus, 6-8 | B86: =INDEX($AJ$17:$AJ$28,MATCH(A86,$A$17:$A$28,0),1) -> Passenger HDV | C86: {=SUMPRODUCT(IF($A$34:$A$71=$A86,C$34:C$71),IF($A$34:$A$71=$A86,C$34:C$71))/SUMIF($A$34:$A$71,$A86,C$34:C$71)} -> 46814.855 | D86: {=SUMPRODUCT(IF($A$34:$A$71=$A86,D$34:D$71),IF($A$34:$A$71=$A86,D$34:D$71))/SUMIF($A$34:$A$71,$A86,D$34:D$71)} -> 47052.732 | E86: {=SUMPRODUCT(IF($A$34:$A$71=$A86,E$34:E$71),IF($A$34:$A$71=$A86,E$34:E$71))/SUMIF($A$34:$A$71,$A86,E$34:E$71)} -> 47290.721 | F86: {=SUMPRODUCT(IF($A$34:$A$71=$A86,F$34:F$71),IF($A$34:$A$71=$A86,F$34:F$71))/SUMIF($A$34:$A$71,$A86,F$34:F$71)} -> 47528.822 | G86: {=SUMPRODUCT(IF($A$34:$A$71=$A86,G$34:G$71),IF($A$34:$A$71=$A86,G$34:G$71))/SUMIF($A$34:$A$71,$A86,G$34:G$71)} -> 47767.032 | H86: {=SUMPRODUCT(IF($A$34:$A$71=$A86,H$34:H$71),IF($A$34:$A$71=$A86,H$34:H$71))/SUMIF($A$34:$A$71,$A86,H$34:H$71)} -> 48005.351 | I86: {=SUMPRODUCT(IF($A$34:$A$71=$A86,I$34:I$71),IF($A$34:$A$71=$A86,I$34:I$71))/SUMIF($A$34:$A$71,$A86,I$34:I$71)} -> 48233.452 | J86: {=SUMPRODUCT(IF($A$34:$A$71=$A86,J$34:J$71),IF($A$34:$A$71=$A86,J$34:J$71))/SUMIF($A$34:$A$71,$A86,J$34:J$71)} -> 48461.556 | ... AG86: {=SUMPRODUCT(IF($A$34:$A$71=$A86,AG$34:AG$71),IF($A$34:$A$71=$A86,AG$34:AG$71))/SUMIF($A$34:$A$71,$A86,AG$34:AG$71)} -> 50342.754
A88: Total New Vehicle Miles | B88: EPS Vehicle Type | C88: 2020 | D88: 2021 | E88: 2022 | F88: 2023 | G88: 2024 | H88: 2025 | I88: 2026 | J88: 2027 | K88: 2028 | L88: 2029 | M88: 2030 | N88: 2031 | O88: 2032 | P88: 2033 | Q88: 2034 | R88: 2035 | S88: 2036 | T88: 2037 | U88: 2038 | V88: 2039 | W88: 2040 | X88: 2041 | Y88: 2042 | Z88: 2043 | AA88: 2044 | AB88: 2045 | AC88: 2046 | AD88: 2047 | AE88: 2048 | AF88: 2049 | AG88: 2050
A89: Rigid truck, 4-5 | B89: =INDEX($AJ$17:$AJ$28,MATCH(A89,$A$17:$A$28,0),1) -> Freight LDV | C89: =C77*INDEX(B$17:B$28,MATCH($A89,$A$17:$A$28,0),1) -> 3.3458317e+09 | D89: =D77*INDEX(C$17:C$28,MATCH($A89,$A$17:$A$28,0),1) -> 3.3725209e+09 | E89: =E77*INDEX(D$17:D$28,MATCH($A89,$A$17:$A$28,0),1) -> 3.3992868e+09 | F89: =F77*INDEX(E$17:E$28,MATCH($A89,$A$17:$A$28,0),1) -> 3.42613e+09 | G89: =G77*INDEX(F$17:F$28,MATCH($A89,$A$17:$A$28,0),1) -> 3.4530513e+09 | H89: =H77*INDEX(G$17:G$28,MATCH($A89,$A$17:$A$28,0),1) -> 3.480051e+09 | I89: =I77*INDEX(H$17:H$28,MATCH($A89,$A$17:$A$28,0),1) -> 3.512854e+09 | J89: =J77*INDEX(I$17:I$28,MATCH($A89,$A$17:$A$28,0),1) -> 3.5454378e+09 | ... AG89: =AG77*INDEX(AF$17:AF$28,MATCH($A89,$A$17:$A$28,0),1) -> 5.9968575e+09
A90: Rigid truck, 6-7 | B90: =INDEX($AJ$17:$AJ$28,MATCH(A90,$A$17:$A$28,0),1) -> Freight LDV | C90: =C78*INDEX(B$17:B$28,MATCH($A90,$A$17:$A$28,0),1) -> 3.4033083e+09 | D90: =D78*INDEX(C$17:C$28,MATCH($A90,$A$17:$A$28,0),1) -> 3.4188308e+09 | E90: =E78*INDEX(D$17:D$28,MATCH($A90,$A$17:$A$28,0),1) -> 3.4344106e+09 | F90: =F78*INDEX(E$17:E$28,MATCH($A90,$A$17:$A$28,0),1) -> 3.4500512e+09 | G90: =G78*INDEX(F$17:F$28,MATCH($A90,$A$17:$A$28,0),1) -> 3.4657563e+09 | H90: =H78*INDEX(G$17:G$28,MATCH($A90,$A$17:$A$28,0),1) -> 3.4815294e+09 | I90: =I78*INDEX(H$17:H$28,MATCH($A90,$A$17:$A$28,0),1) -> 3.5519913e+09 | J90: =J78*INDEX(I$17:I$28,MATCH($A90,$A$17:$A$28,0),1) -> 3.6231236e+09 | ... AG90: =AG78*INDEX(AF$17:AF$28,MATCH($A90,$A$17:$A$28,0),1) -> 6.0926494e+09
A91: Rigid truck, 8 | B91: =INDEX($AJ$17:$AJ$28,MATCH(A91,$A$17:$A$28,0),1) -> Freight HDV | C91: =C79*INDEX(B$17:B$28,MATCH($A91,$A$17:$A$28,0),1) -> 2.8543905e+09 | D91: =D79*INDEX(C$17:C$28,MATCH($A91,$A$17:$A$28,0),1) -> 2.8852771e+09 | E91: =E79*INDEX(D$17:D$28,MATCH($A91,$A$17:$A$28,0),1) -> 2.9163408e+09 | F91: =F79*INDEX(E$17:E$28,MATCH($A91,$A$17:$A$28,0),1) -> 2.9475819e+09 | G91: =G79*INDEX(F$17:F$28,MATCH($A91,$A$17:$A$28,0),1) -> 2.9790005e+09 | H91: =H79*INDEX(G$17:G$28,MATCH($A91,$A$17:$A$28,0),1) -> 3.0105968e+09 | I91: =I79*INDEX(H$17:H$28,MATCH($A91,$A$17:$A$28,0),1) -> 3.0529469e+09 | J91: =J79*INDEX(I$17:I$28,MATCH($A91,$A$17:$A$28,0),1) -> 3.0952682e+09 | ... AG91: =AG79*INDEX(AF$17:AF$28,MATCH($A91,$A$17:$A$28,0),1) -> 4.921899e+09
A92: Tractor truck, short-haul | B92: =INDEX($AJ$17:$AJ$28,MATCH(A92,$A$17:$A$28,0),1) -> Freight HDV | C92: =C80*INDEX(B$17:B$28,MATCH($A92,$A$17:$A$28,0),1) -> 4.2432484e+09 | D92: =D80*INDEX(C$17:C$28,MATCH($A92,$A$17:$A$28,0),1) -> 4.1351434e+09 | E92: =E80*INDEX(D$17:D$28,MATCH($A92,$A$17:$A$28,0),1) -> 4.0346148e+09 | F92: =F80*INDEX(E$17:E$28,MATCH($A92,$A$17:$A$28,0),1) -> 3.941472e+09 | G92: =G80*INDEX(F$17:F$28,MATCH($A92,$A$17:$A$28,0),1) -> 3.8555241e+09 | H92: =H80*INDEX(G$17:G$28,MATCH($A92,$A$17:$A$28,0),1) -> 3.7765788e+09 | I92: =I80*INDEX(H$17:H$28,MATCH($A92,$A$17:$A$28,0),1) -> 3.7208016e+09 | J92: =J80*INDEX(I$17:I$28,MATCH($A92,$A$17:$A$28,0),1) -> 3.6679694e+09 | ... AG92: =AG80*INDEX(AF$17:AF$28,MATCH($A92,$A$17:$A$28,0),1) -> 4.0092037e+09
A93: Tractor truck, long-haul | B93: =INDEX($AJ$17:$AJ$28,MATCH(A93,$A$17:$A$28,0),1) -> Freight HDV | C93: =C81*INDEX(B$17:B$28,MATCH($A93,$A$17:$A$28,0),1) -> 1.4612799e+10 | D93: =D81*INDEX(C$17:C$28,MATCH($A93,$A$17:$A$28,0),1) -> 1.4262425e+10 | E93: =E81*INDEX(D$17:D$28,MATCH($A93,$A$17:$A$28,0),1) -> 1.3923564e+10 | F93: =F81*INDEX(E$17:E$28,MATCH($A93,$A$17:$A$28,0),1) -> 1.3596329e+10 | G93: =G81*INDEX(F$17:F$28,MATCH($A93,$A$17:$A$28,0),1) -> 1.3280843e+10 | H93: =H81*INDEX(G$17:G$28,MATCH($A93,$A$17:$A$28,0),1) -> 1.2977235e+10 | I93: =I81*INDEX(H$17:H$28,MATCH($A93,$A$17:$A$28,0),1) -> 1.2784934e+10 | J93: =J81*INDEX(I$17:I$28,MATCH($A93,$A$17:$A$28,0),1) -> 1.2597569e+10 | ... AG93: =AG81*INDEX(AF$17:AF$28,MATCH($A93,$A$17:$A$28,0),1) -> 1.3858417e+10
A94: Refuse truck | B94: =INDEX($AJ$17:$AJ$28,MATCH(A94,$A$17:$A$28,0),1) -> Freight HDV | C94: =C82*INDEX(B$17:B$28,MATCH($A94,$A$17:$A$28,0),1) -> 94903997 | D94: =D82*INDEX(C$17:C$28,MATCH($A94,$A$17:$A$28,0),1) -> 96602362 | E94: =E82*INDEX(D$17:D$28,MATCH($A94,$A$17:$A$28,0),1) -> 98429639 | F94: =F82*INDEX(E$17:E$28,MATCH($A94,$A$17:$A$28,0),1) -> 1.0039088e+08 | G94: =G82*INDEX(F$17:F$28,MATCH($A94,$A$17:$A$28,0),1) -> 1.024913e+08 | H94: =H82*INDEX(G$17:G$28,MATCH($A94,$A$17:$A$28,0),1) -> 1.0473628e+08 | I94: =I82*INDEX(H$17:H$28,MATCH($A94,$A$17:$A$28,0),1) -> 1.0771786e+08 | J94: =J82*INDEX(I$17:I$28,MATCH($A94,$A$17:$A$28,0),1) -> 1.1074236e+08 | ... AG94: =AG82*INDEX(AF$17:AF$28,MATCH($A94,$A$17:$A$28,0),1) -> 2.0248984e+08
A95: Small bus, 4-5 | B95: =INDEX($AJ$17:$AJ$28,MATCH(A95,$A$17:$A$28,0),1) -> Passenger HDV | C95: =C83*INDEX(B$17:B$28,MATCH($A95,$A$17:$A$28,0),1) -> 1.9266889e+08 | D95: =D83*INDEX(C$17:C$28,MATCH($A95,$A$17:$A$28,0),1) -> 1.9209489e+08 | E95: =E83*INDEX(D$17:D$28,MATCH($A95,$A$17:$A$28,0),1) -> 1.9152087e+08 | F95: =F83*INDEX(E$17:E$28,MATCH($A95,$A$17:$A$28,0),1) -> 1.9094685e+08 | G95: =G83*INDEX(F$17:F$28,MATCH($A95,$A$17:$A$28,0),1) -> 1.9037282e+08 | H95: =H83*INDEX(G$17:G$28,MATCH($A95,$A$17:$A$28,0),1) -> 1.8979878e+08 | I95: =I83*INDEX(H$17:H$28,MATCH($A95,$A$17:$A$28,0),1) -> 1.9093412e+08 | J95: =J83*INDEX(I$17:I$28,MATCH($A95,$A$17:$A$28,0),1) -> 1.9206895e+08 | ... AG95: =AG83*INDEX(AF$17:AF$28,MATCH($A95,$A$17:$A$28,0),1) -> 2.7085156e+08
A96: Transit bus, 6-8 | B96: =INDEX($AJ$17:$AJ$28,MATCH(A96,$A$17:$A$28,0),1) -> Passenger HDV | C96: =C84*INDEX(B$17:B$28,MATCH($A96,$A$17:$A$28,0),1) -> 2.4122756e+08 | D96: =D84*INDEX(C$17:C$28,MATCH($A96,$A$17:$A$28,0),1) -> 2.3897179e+08 | E96: =E84*INDEX(D$17:D$28,MATCH($A96,$A$17:$A$28,0),1) -> 2.3678427e+08 | F96: =F84*INDEX(E$17:E$28,MATCH($A96,$A$17:$A$28,0),1) -> 2.3466741e+08 | G96: =G84*INDEX(F$17:F$28,MATCH($A96,$A$17:$A$28,0),1) -> 2.3262374e+08 | H96: =H84*INDEX(G$17:G$28,MATCH($A96,$A$17:$A$28,0),1) -> 2.3065591e+08 | I96: =I84*INDEX(H$17:H$28,MATCH($A96,$A$17:$A$28,0),1) -> 2.3053226e+08 | J96: =J84*INDEX(I$17:I$28,MATCH($A96,$A$17:$A$28,0),1) -> 2.3046487e+08 | ... AG96: =AG84*INDEX(AF$17:AF$28,MATCH($A96,$A$17:$A$28,0),1) -> 3.0510752e+08
A97: School bus, 6-8 | B97: =INDEX($AJ$17:$AJ$28,MATCH(A97,$A$17:$A$28,0),1) -> Passenger HDV | C97: =C85*INDEX(B$17:B$28,MATCH($A97,$A$17:$A$28,0),1) -> 4.4997093e+08 | D97: =D85*INDEX(C$17:C$28,MATCH($A97,$A$17:$A$28,0),1) -> 4.5122116e+08 | E97: =E85*INDEX(D$17:D$28,MATCH($A97,$A$17:$A$28,0),1) -> 4.524716e+08 | F97: =F85*INDEX(E$17:E$28,MATCH($A97,$A$17:$A$28,0),1) -> 4.5372223e+08 | G97: =G85*INDEX(F$17:F$28,MATCH($A97,$A$17:$A$28,0),1) -> 4.5497307e+08 | H97: =H85*INDEX(G$17:G$28,MATCH($A97,$A$17:$A$28,0),1) -> 4.5622411e+08 | I97: =I85*INDEX(H$17:H$28,MATCH($A97,$A$17:$A$28,0),1) -> 4.5995564e+08 | J97: =J85*INDEX(I$17:I$28,MATCH($A97,$A$17:$A$28,0),1) -> 4.6369843e+08 | ... AG97: =AG85*INDEX(AF$17:AF$28,MATCH($A97,$A$17:$A$28,0),1) -> 6.4870917e+08
A98: Other bus, 6-8 | B98: =INDEX($AJ$17:$AJ$28,MATCH(A98,$A$17:$A$28,0),1) -> Passenger HDV | C98: =C86*INDEX(B$17:B$28,MATCH($A98,$A$17:$A$28,0),1) -> 7.5975421e+08 | D98: =D86*INDEX(C$17:C$28,MATCH($A98,$A$17:$A$28,0),1) -> 7.6364019e+08 | E98: =E86*INDEX(D$17:D$28,MATCH($A98,$A$17:$A$28,0),1) -> 7.6752827e+08 | F98: =F86*INDEX(E$17:E$28,MATCH($A98,$A$17:$A$28,0),1) -> 7.714184e+08 | G98: =G86*INDEX(F$17:F$28,MATCH($A98,$A$17:$A$28,0),1) -> 7.7531057e+08 | H98: =H86*INDEX(G$17:G$28,MATCH($A98,$A$17:$A$28,0),1) -> 7.7920475e+08 | I98: =I86*INDEX(H$17:H$28,MATCH($A98,$A$17:$A$28,0),1) -> 7.8776366e+08 | J98: =J86*INDEX(I$17:I$28,MATCH($A98,$A$17:$A$28,0),1) -> 7.9636855e+08 | ... AG98: =AG86*INDEX(AF$17:AF$28,MATCH($A98,$A$17:$A$28,0),1) -> 1.1284404e+09
A100: Share New Vehicle Miles by EPS Vehicle Type | B100: EPS Vehicle Type | C100: 2020 | D100: 2021 | E100: 2022 | F100: 2023 | G100: 2024 | H100: 2025 | I100: 2026 | J100: 2027 | K100: 2028 | L100: 2029 | M100: 2030 | N100: 2031 | O100: 2032 | P100: 2033 | Q100: 2034 | R100: 2035 | S100: 2036 | T100: 2037 | U100: 2038 | V100: 2039 | W100: 2040 | X100: 2041 | Y100: 2042 | Z100: 2043 | AA100: 2044 | AB100: 2045 | AC100: 2046 | AD100: 2047 | AE100: 2048 | AF100: 2049 | AG100: 2050
A101: Rigid truck, 4-5 | B101: =INDEX($AJ$17:$AJ$28,MATCH(A101,$A$17:$A$28,0),1) -> Freight LDV | C101: =C89/SUMIFS(C$89:C$98,$B$89:$B$98,$B101) -> 0.49574193 | D101: =D89/SUMIFS(D$89:D$98,$B$89:$B$98,$B101) -> 0.49659052 | E101: =E89/SUMIFS(E$89:E$98,$B$89:$B$98,$B101) -> 0.4974301 | F101: =F89/SUMIFS(F$89:F$98,$B$89:$B$98,$B101) -> 0.49826058 | G101: =G89/SUMIFS(G$89:G$98,$B$89:$B$98,$B101) -> 0.49908185 | H101: =H89/SUMIFS(H$89:H$98,$B$89:$B$98,$B101) -> 0.49989382 | I101: =I89/SUMIFS(I$89:I$98,$B$89:$B$98,$B101) -> 0.49723014 | J101: =J89/SUMIFS(J$89:J$98,$B$89:$B$98,$B101) -> 0.49458149 | ... AG101: =AG89/SUMIFS(AG$89:AG$98,$B$89:$B$98,$B101) -> 0.49603822
A102: Rigid truck, 6-7 | B102: =INDEX($AJ$17:$AJ$28,MATCH(A102,$A$17:$A$28,0),1) -> Freight LDV | C102: =C90/SUMIFS(C$89:C$98,$B$89:$B$98,$B102) -> 0.50425807 | D102: =D90/SUMIFS(D$89:D$98,$B$89:$B$98,$B102) -> 0.50340948 | E102: =E90/SUMIFS(E$89:E$98,$B$89:$B$98,$B102) -> 0.5025699 | F102: =F90/SUMIFS(F$89:F$98,$B$89:$B$98,$B102) -> 0.50173942 | G102: =G90/SUMIFS(G$89:G$98,$B$89:$B$98,$B102) -> 0.50091815 | H102: =H90/SUMIFS(H$89:H$98,$B$89:$B$98,$B102) -> 0.50010618 | I102: =I90/SUMIFS(I$89:I$98,$B$89:$B$98,$B102) -> 0.50276986 | J102: =J90/SUMIFS(J$89:J$98,$B$89:$B$98,$B102) -> 0.50541851 | ... AG102: =AG90/SUMIFS(AG$89:AG$98,$B$89:$B$98,$B102) -> 0.50396178
A103: Rigid truck, 8 | B103: =INDEX($AJ$17:$AJ$28,MATCH(A103,$A$17:$A$28,0),1) -> Freight HDV | C103: =C91/SUMIFS(C$89:C$98,$B$89:$B$98,$B103) -> 0.13090327 | D103: =D91/SUMIFS(D$89:D$98,$B$89:$B$98,$B103) -> 0.13495564 | E103: =E91/SUMIFS(E$89:E$98,$B$89:$B$98,$B103) -> 0.13905249 | F103: =F91/SUMIFS(F$89:F$98,$B$89:$B$98,$B103) -> 0.14318538 | G103: =G91/SUMIFS(G$89:G$98,$B$89:$B$98,$B103) -> 0.147345 | H103: =H91/SUMIFS(H$89:H$98,$B$89:$B$98,$B103) -> 0.15152119 | I103: =I91/SUMIFS(I$89:I$98,$B$89:$B$98,$B103) -> 0.15523669 | J103: =J91/SUMIFS(J$89:J$98,$B$89:$B$98,$B103) -> 0.15896364 | ... AG103: =AG91/SUMIFS(AG$89:AG$98,$B$89:$B$98,$B103) -> 0.21406998
A104: Tractor truck, short-haul | B104: =INDEX($AJ$17:$AJ$28,MATCH(A104,$A$17:$A$28,0),1) -> Freight HDV | C104: =C92/SUMIFS(C$89:C$98,$B$89:$B$98,$B104) -> 0.19459674 | D104: =D92/SUMIFS(D$89:D$98,$B$89:$B$98,$B104) -> 0.19341676 | E104: =E92/SUMIFS(E$89:E$98,$B$89:$B$98,$B104) -> 0.19237232 | F104: =F92/SUMIFS(F$89:F$98,$B$89:$B$98,$B104) -> 0.19146581 | G104: =G92/SUMIFS(G$89:G$98,$B$89:$B$98,$B104) -> 0.19069893 | H104: =H92/SUMIFS(H$89:H$98,$B$89:$B$98,$B104) -> 0.19007252 | I104: =I92/SUMIFS(I$89:I$98,$B$89:$B$98,$B104) -> 0.18919587 | J104: =J92/SUMIFS(J$89:J$98,$B$89:$B$98,$B104) -> 0.18837585 | ... AG104: =AG92/SUMIFS(AG$89:AG$98,$B$89:$B$98,$B104) -> 0.17437378
A105: Tractor truck, long-haul | B105: =INDEX($AJ$17:$AJ$28,MATCH(A105,$A$17:$A$28,0),1) -> Freight HDV | C105: =C93/SUMIFS(C$89:C$98,$B$89:$B$98,$B105) -> 0.67014767 | D105: =D93/SUMIFS(D$89:D$98,$B$89:$B$98,$B105) -> 0.66710913 | E105: =E93/SUMIFS(E$89:E$98,$B$89:$B$98,$B105) -> 0.66388202 | F105: =F93/SUMIFS(F$89:F$98,$B$89:$B$98,$B105) -> 0.66047209 | G105: =G93/SUMIFS(G$89:G$98,$B$89:$B$98,$B105) -> 0.65688672 | H105: =H93/SUMIFS(H$89:H$98,$B$89:$B$98,$B105) -> 0.65313499 | I105: =I93/SUMIFS(I$89:I$98,$B$89:$B$98,$B105) -> 0.65009018 | J105: =J93/SUMIFS(J$89:J$98,$B$89:$B$98,$B105) -> 0.64697312 | ... AG105: =AG93/SUMIFS(AG$89:AG$98,$B$89:$B$98,$B105) -> 0.60274927
A106: Refuse truck | B106: =INDEX($AJ$17:$AJ$28,MATCH(A106,$A$17:$A$28,0),1) -> Freight HDV | C106: =C94/SUMIFS(C$89:C$98,$B$89:$B$98,$B106) -> 0.0043523278 | D106: =D94/SUMIFS(D$89:D$98,$B$89:$B$98,$B106) -> 0.0045184686 | E106: =E94/SUMIFS(E$89:E$98,$B$89:$B$98,$B106) -> 0.0046931712 | F106: =F94/SUMIFS(F$89:F$98,$B$89:$B$98,$B106) -> 0.0048767114 | G106: =G94/SUMIFS(G$89:G$98,$B$89:$B$98,$B106) -> 0.0050693449 | H106: =H94/SUMIFS(H$89:H$98,$B$89:$B$98,$B106) -> 0.0052713024 | I106: =I94/SUMIFS(I$89:I$98,$B$89:$B$98,$B106) -> 0.0054772535 | J106: =J94/SUMIFS(J$89:J$98,$B$89:$B$98,$B106) -> 0.0056873937 | ... AG106: =AG94/SUMIFS(AG$89:AG$98,$B$89:$B$98,$B106) -> 0.0088069657
A107: Small bus, 4-5 | B107: =INDEX($AJ$17:$AJ$28,MATCH(A107,$A$17:$A$28,0),1) -> Passenger HDV | C107: =C95/SUMIFS(C$89:C$98,$B$89:$B$98,$B107) -> 0.11722217 | D107: =D95/SUMIFS(D$89:D$98,$B$89:$B$98,$B107) -> 0.11670917 | E107: =E95/SUMIFS(E$89:E$98,$B$89:$B$98,$B107) -> 0.11619262 | F107: =F95/SUMIFS(F$89:F$98,$B$89:$B$98,$B107) -> 0.11567244 | G107: =G95/SUMIFS(G$89:G$98,$B$89:$B$98,$B107) -> 0.11514855 | H107: =H95/SUMIFS(H$89:H$98,$B$89:$B$98,$B107) -> 0.11462085 | I107: =I95/SUMIFS(I$89:I$98,$B$89:$B$98,$B107) -> 0.11438759 | J107: =J95/SUMIFS(J$89:J$98,$B$89:$B$98,$B107) -> 0.11415004 | ... AG107: =AG95/SUMIFS(AG$89:AG$98,$B$89:$B$98,$B107) -> 0.11510372
A108: Transit bus, 6-8 | B108: =INDEX($AJ$17:$AJ$28,MATCH(A108,$A$17:$A$28,0),1) -> Passenger HDV | C108: =C96/SUMIFS(C$89:C$98,$B$89:$B$98,$B108) -> 0.14676587 | D108: =D96/SUMIFS(D$89:D$98,$B$89:$B$98,$B108) -> 0.1451897 | E108: =E96/SUMIFS(E$89:E$98,$B$89:$B$98,$B108) -> 0.14365319 | F108: =F96/SUMIFS(F$89:F$98,$B$89:$B$98,$B108) -> 0.14215763 | G108: =G96/SUMIFS(G$89:G$98,$B$89:$B$98,$B108) -> 0.14070436 | H108: =H96/SUMIFS(H$89:H$98,$B$89:$B$98,$B108) -> 0.13929477 | I108: =I96/SUMIFS(I$89:I$98,$B$89:$B$98,$B108) -> 0.13811061 | J108: =J96/SUMIFS(J$89:J$98,$B$89:$B$98,$B108) -> 0.13696943 | ... AG108: =AG96/SUMIFS(AG$89:AG$98,$B$89:$B$98,$B108) -> 0.12966147
A109: School bus, 6-8 | B109: =INDEX($AJ$17:$AJ$28,MATCH(A109,$A$17:$A$28,0),1) -> Passenger HDV | C109: =C97/SUMIFS(C$89:C$98,$B$89:$B$98,$B109) -> 0.27376796 | D109: =D97/SUMIFS(D$89:D$98,$B$89:$B$98,$B109) -> 0.27414392 | E109: =E97/SUMIFS(E$89:E$98,$B$89:$B$98,$B109) -> 0.2745072 | F109: =F97/SUMIFS(F$89:F$98,$B$89:$B$98,$B109) -> 0.27485742 | G109: =G97/SUMIFS(G$89:G$98,$B$89:$B$98,$B109) -> 0.27519417 | H109: =H97/SUMIFS(H$89:H$98,$B$89:$B$98,$B109) -> 0.27551702 | I109: =I97/SUMIFS(I$89:I$98,$B$89:$B$98,$B109) -> 0.2755569 | J109: =J97/SUMIFS(J$89:J$98,$B$89:$B$98,$B109) -> 0.27558434 | ... AG109: =AG97/SUMIFS(AG$89:AG$98,$B$89:$B$98,$B109) -> 0.27568178
A110: Other bus, 6-8 | B110: =INDEX($AJ$17:$AJ$28,MATCH(A110,$A$17:$A$28,0),1) -> Passenger HDV | C110: =C98/SUMIFS(C$89:C$98,$B$89:$B$98,$B110) -> 0.462244 | D110: =D98/SUMIFS(D$89:D$98,$B$89:$B$98,$B110) -> 0.46395722 | E110: =E98/SUMIFS(E$89:E$98,$B$89:$B$98,$B110) -> 0.46564699 | F110: =F98/SUMIFS(F$89:F$98,$B$89:$B$98,$B110) -> 0.4673125 | G110: =G98/SUMIFS(G$89:G$98,$B$89:$B$98,$B110) -> 0.46895292 | H110: =H98/SUMIFS(H$89:H$98,$B$89:$B$98,$B110) -> 0.47056736 | I110: =I98/SUMIFS(I$89:I$98,$B$89:$B$98,$B110) -> 0.4719449 | J110: =J98/SUMIFS(J$89:J$98,$B$89:$B$98,$B110) -> 0.47329619 | ... AG110: =AG98/SUMIFS(AG$89:AG$98,$B$89:$B$98,$B110) -> 0.47955303
A112: Percentage of Rigid truck, 6-7 in freight LDV | C112: =D112 -> 0.4951186 | D112: ='AEO by Class'!B13 -> 0.4951186 | E112: ='AEO by Class'!C13 -> 0.49771343 | F112: ='AEO by Class'!D13 -> 0.49987872 | G112: ='AEO by Class'!E13 -> 0.50197205 | H112: ='AEO by Class'!F13 -> 0.50384789 | I112: ='AEO by Class'!G13 -> 0.50579407 | J112: ='AEO by Class'!H13 -> 0.50808539 | K112: ='AEO by Class'!I13 -> 0.51073826 | ... AG112: ='AEO by Class'!AE13 -> 0.5860427
A113: Percentage of Rigid truck, 6-7 in freight HDV | C113: =D113 -> 0.5048814 | D113: =1-D112 -> 0.5048814 | E113: =1-E112 -> 0.50228657 | F113: =1-F112 -> 0.50012128 | G113: =1-G112 -> 0.49802795 | H113: =1-H112 -> 0.49615211 | I113: =1-I112 -> 0.49420593 | J113: =1-J112 -> 0.49191461 | K113: =1-K112 -> 0.48926174 | ... AG113: =1-AG112 -> 0.4139573
A116: Weighted New BEV Size | B116: EPS Vehicle Type | C116: 2020 | D116: 2021 | E116: 2022 | F116: 2023 | G116: 2024 | H116: 2025 | I116: 2026 | J116: 2027 | K116: 2028 | L116: 2029 | M116: 2030 | N116: 2031 | O116: 2032 | P116: 2033 | Q116: 2034 | R116: 2035 | S116: 2036 | T116: 2037 | U116: 2038 | V116: 2039 | W116: 2040 | X116: 2041 | Y116: 2042 | Z116: 2043 | AA116: 2044 | AB116: 2045 | AC116: 2046 | AD116: 2047 | AE116: 2048 | AF116: 2049 | AG116: 2050
A117: Rigid truck, 4-5 | B117: =INDEX($AJ$17:$AJ$28,MATCH(A117,$A$17:$A$28,0),1) -> Freight LDV | C117: =C101*B2 -> 69.651742 | D117: =D101*C2 -> 68.405344 | E117: =E101*D2 -> 67.153063 | F117: =F101*E2 -> 65.894961 | G117: =G101*F2 -> 64.631099 | H117: =H101*G2 -> 63.361541 | I117: =I101*H2 -> 61.656538 | J117: =J101*I2 -> 59.968006 | ... AG117: =AG101*AF2 -> 56.052319
A118: Weighted Rigid truck, 6 | B118: Freight LDV | C118: =B3*C102*C112 -> 53.304022 | D118: =C3*D102*D112 -> 52.155018 | E118: =D3*E102*E112 -> 51.277837 | F118: =E3*F102*F112 -> 50.349878 | G118: =F3*G102*G112 -> 49.409318 | H118: =G3*H102*H112 -> 48.442664 | I118: =H3*I102*I112 -> 47.808026 | J118: =I3*J102*J112 -> 47.186221 | ... AG118: =AF3*AG102*AG112 -> 50.503674
A119: Weighted Rigid truck, 7 | B119: Freight HDV | C119: =B3*C102*C113 -> 54.355075 | D119: =C3*D102*D113 -> 53.183416 | E119: =D3*E102*E113 -> 51.748993 | F119: =E3*F102*F113 -> 50.374311 | G119: =F3*G102*G113 -> 49.021099 | H119: =G3*H102*H113 -> 47.70275 | I119: =H3*I102*I113 -> 46.712707 | J119: =I3*J102*J113 -> 45.68443 | ... AG119: =AF3*AG102*AG113 -> 35.67379
A120: Rigid truck, 8 | B120: =INDEX($AJ$17:$AJ$28,MATCH(A120,$A$17:$A$28,0),1) -> Freight HDV | C120: =C103*B4 -> 55.633888 | D120: =D103*C4 -> 55.669202 | E120: =E103*D4 -> 55.620997 | F120: =F103*E4 -> 55.484335 | G120: =G103*F4 -> 55.254376 | H120: =H103*G4 -> 54.926431 | I120: =I103*H4 -> 54.332843 | J120: =J103*I4 -> 53.650228 | ... AG120: =AG103*AF4 -> 64.220995
A121: Tractor truck, short-haul | B121: =INDEX($AJ$17:$AJ$28,MATCH(A121,$A$17:$A$28,0),1) -> Freight HDV | C121: =C104*B5 -> 94.476715 | D121: =D104*C5 -> 90.95423 | E121: =E104*D5 -> 87.529404 | F121: =F104*E5 -> 84.197092 | G121: =G104*F5 -> 80.951695 | H121: =H104*G5 -> 77.787178 | I121: =I104*H5 -> 74.543172 | J121: =J104*I5 -> 71.347352 | ... AG121: =AG104*AF5 -> 58.06647
A122: Tractor truck, long-haul | B122: =INDEX($AJ$17:$AJ$28,MATCH(A122,$A$17:$A$28,0),1) -> Freight HDV | C122: =C105*B6 -> 659.59284 | D122: =D105*C6 -> 635.17128 | E122: =E105*D6 -> 610.77146 | F122: =F105*E6 -> 586.41666 | G122: =G105*F6 -> 562.13081 | H122: =H105*G6 -> 537.93831 | I122: =I105*H6 -> 514.54638 | J122: =J105*I6 -> 491.29521 | ... AG122: =AG105*AF6 -> 399.62276
A123: Refuse truck | B123: =INDEX($AJ$17:$AJ$28,MATCH(A123,$A$17:$A$28,0),1) -> Freight HDV | C123: =C106*B7 -> 1.8638844 | D123: =D106*C7 -> 1.882507 | E123: =E106*D7 -> 1.9007343 | F123: =F106*E7 -> 1.9183764 | G123: =G106*F7 -> 1.9352224 | H123: =H106*G7 -> 1.9510408 | I123: =I106*H7 -> 1.9635954 | J123: =J106*I7 -> 1.9728147 | ... AG123: =AG106*AF7 -> 2.7477733
A124: Small bus, 4-5 | B124: =INDEX($AJ$17:$AJ$28,MATCH(A124,$A$17:$A$28,0),1) -> Passenger HDV | C124: =C107*B8 -> 14.213188 | D124: =D107*C8 -> 14.078043 | E124: =E107*D8 -> 13.943114 | F124: =F107*E8 -> 13.808398 | G124: =G107*F8 -> 13.67389 | H124: =H107*G8 -> 13.539588 | I124: =I107*H8 -> 13.440541 | J124: =J107*I8 -> 13.341286 | ... AG124: =AG107*AF8 -> 13.236928
A125: Transit bus, 6-8 | B125: =INDEX($AJ$17:$AJ$28,MATCH(A125,$A$17:$A$28,0),1) -> Passenger HDV | C125: =C108*B9 -> 66.778472 | D125: =D108*C9 -> 65.698337 | E125: =E108*D9 -> 64.643934 | F125: =F108*E9 -> 63.61554 | G125: =G108*F9 -> 62.613441 | H125: =H108*G9 -> 61.637934 | I125: =I108*H9 -> 60.76867 | J125: =J108*I9 -> 59.924125 | ... AG125: =AG108*AF9 -> 55.754432
A126: School bus, 6-8 | B126: =INDEX($AJ$17:$AJ$28,MATCH(A126,$A$17:$A$28,0),1) -> Passenger HDV | C126: =C109*B10 -> 49.825769 | D126: =D109*C10 -> 49.620049 | E126: =E109*D10 -> 49.411297 | F126: =F109*E10 -> 49.199479 | G126: =G109*F10 -> 48.984562 | H126: =H109*G10 -> 48.766513 | I126: =I109*H10 -> 48.498015 | J126: =J109*I10 -> 48.227259 | ... AG126: =AG109*AF10 -> 47.417266
A127: Other bus, 6-8 | B127: =INDEX($AJ$17:$AJ$28,MATCH(A127,$A$17:$A$28,0),1) -> Passenger HDV | C127: =C110*B11 -> 315.94377 | D127: =D110*C11 -> 315.37492 | E127: =E110*D11 -> 314.77737 | F127: =F110*E11 -> 314.15083 | G127: =G110*F11 -> 313.49503 | H127: =H110*G11 -> 312.80965 | I127: =I110*H11 -> 311.95558 | J127: =J110*I11 -> 311.07392 | ... AG127: =AG110*AF11 -> 309.79126
A129: New BEV Battery Size by EPS Vehicle Type | C129: 2020 | D129: 2021 | E129: 2022 | F129: 2023 | G129: 2024 | H129: 2025 | I129: 2026 | J129: 2027 | K129: 2028 | L129: 2029 | M129: 2030 | N129: 2031 | O129: 2032 | P129: 2033 | Q129: 2034 | R129: 2035 | S129: 2036 | T129: 2037 | U129: 2038 | V129: 2039 | W129: 2040 | X129: 2041 | Y129: 2042 | Z129: 2043 | AA129: 2044 | AB129: 2045 | AC129: 2046 | AD129: 2047 | AE129: 2048 | AF129: 2049 | AG129: 2050
A130: Freight LDV | C130: =SUMIFS(C$117:C$127,$B$117:$B$127,$A130) -> 122.95576 | D130: =SUMIFS(D$117:D$127,$B$117:$B$127,$A130) -> 120.56036 | E130: =SUMIFS(E$117:E$127,$B$117:$B$127,$A130) -> 118.4309 | F130: =SUMIFS(F$117:F$127,$B$117:$B$127,$A130) -> 116.24484 | G130: =SUMIFS(G$117:G$127,$B$117:$B$127,$A130) -> 114.04042 | H130: =SUMIFS(H$117:H$127,$B$117:$B$127,$A130) -> 111.80421 | I130: =SUMIFS(I$117:I$127,$B$117:$B$127,$A130) -> 109.46456 | J130: =SUMIFS(J$117:J$127,$B$117:$B$127,$A130) -> 107.15423 | ... AG130: =SUMIFS(AG$117:AG$127,$B$117:$B$127,$A130) -> 106.55599
A131: Freight HDV | C131: =SUMIFS(C$117:C$127,$B$117:$B$127,$A131) -> 865.92241 | D131: =SUMIFS(D$117:D$127,$B$117:$B$127,$A131) -> 836.86064 | E131: =SUMIFS(E$117:E$127,$B$117:$B$127,$A131) -> 807.57159 | F131: =SUMIFS(F$117:F$127,$B$117:$B$127,$A131) -> 778.39077 | G131: =SUMIFS(G$117:G$127,$B$117:$B$127,$A131) -> 749.29321 | H131: =SUMIFS(H$117:H$127,$B$117:$B$127,$A131) -> 720.30571 | I131: =SUMIFS(I$117:I$127,$B$117:$B$127,$A131) -> 692.0987 | J131: =SUMIFS(J$117:J$127,$B$117:$B$127,$A131) -> 663.95004 | ... AG131: =SUMIFS(AG$117:AG$127,$B$117:$B$127,$A131) -> 560.33179
A132: Passenger HDV | C132: =SUMIFS(C$117:C$127,$B$117:$B$127,$A132) -> 446.7612 | D132: =SUMIFS(D$117:D$127,$B$117:$B$127,$A132) -> 444.77135 | E132: =SUMIFS(E$117:E$127,$B$117:$B$127,$A132) -> 442.77571 | F132: =SUMIFS(F$117:F$127,$B$117:$B$127,$A132) -> 440.77425 | G132: =SUMIFS(G$117:G$127,$B$117:$B$127,$A132) -> 438.76692 | H132: =SUMIFS(H$117:H$127,$B$117:$B$127,$A132) -> 436.75369 | I132: =SUMIFS(I$117:I$127,$B$117:$B$127,$A132) -> 434.6628 | J132: =SUMIFS(J$117:J$127,$B$117:$B$127,$A132) -> 432.56659 | ... AG132: =SUMIFS(AG$117:AG$127,$B$117:$B$127,$A132) -> 426.19988
A134: Annual Percent Improvement in Battery Size by Vehicle Type | C134: 2020 | D134: 2021 | E134: 2022 | F134: 2023 | G134: 2024 | H134: 2025 | I134: 2026 | J134: 2027 | K134: 2028 | L134: 2029 | M134: 2030 | N134: 2031 | O134: 2032 | P134: 2033 | Q134: 2034 | R134: 2035 | S134: 2036 | T134: 2037 | U134: 2038 | V134: 2039 | W134: 2040 | X134: 2041 | Y134: 2042 | Z134: 2043 | AA134: 2044 | AB134: 2045 | AC134: 2046 | AD134: 2047 | AE134: 2048 | AF134: 2049 | AG134: 2050
A135: Freight LDV | C135: 0 | D135: =1-(D130/C130) -> 0.019481814 | E135: =1-(E130/D130) -> 0.017663036 | F135: =1-(F130/E130) -> 0.018458533 | G135: =1-(G130/F130) -> 0.018963614 | H135: =1-(H130/G130) -> 0.019608942 | I135: =1-(I130/H130) -> 0.020926238 | J135: =1-(J130/I130) -> 0.021105802 | K135: =1-(K130/J130) -> 0.021291081 | ... AG135: =1-(AG130/AF130) -> -0.0027263053
A136: Freight HDV | C136: 0 | D136: =1-(D131/C131) -> 0.033561633 | E136: =1-(E131/D131) -> 0.03499872 | F136: =1-(F131/E131) -> 0.036134025 | G136: =1-(G131/F131) -> 0.037381696 | H136: =1-(H131/G131) -> 0.038686459 | I136: =1-(I131/H131) -> 0.039159774 | J136: =1-(J131/I131) -> 0.040671452 | K136: =1-(K131/J131) -> 0.042299925 | ... AG136: =1-(AG131/AF131) -> 0.0012829793
A137: Passenger HDV | C137: 0 | D137: =1-(D132/C132) -> 0.004453946 | E137: =1-(E132/D132) -> 0.0044868858 | F137: =1-(F132/E132) -> 0.004520266 | G137: =1-(G132/F132) -> 0.0045540956 | H137: =1-(H132/G132) -> 0.0045883837 | I137: =1-(I132/H132) -> 0.0047873348 | J137: =1-(J132/I132) -> 0.0048226108 | K137: =1-(K132/J132) -> 0.0048583291 | ... AG137: =1-(AG132/AF132) -> -7.3978938e-05

Sheet SYBCbVT-passenger
A1: Battery Capacity (MW*hr/vehicle | B1: battery electric vehicle | C1: natural gas vehicle | D1: gasoline vehicle | E1: diesel vehicle | F1: plugin hybrid vehicle | G1: LPG vehicle | H1: hydrogen vehicle | I1: nonroad vehicle
A2: LDVs | B2: ='Pass LDVs'!B181/1000 -> 0.095525493 | C2: 0 | D2: 0 | E2: 0 | F2: ='Pass LDVs'!B182/1000 -> 0.016635207 | G2: 0 | H2: 0 | I2: 0
A3: HDVs | B3: ='Freight LDVs + HDVs'!C132/1000 -> 0.4467612 | C3: 0 | D3: 0 | E3: 0 | F3: 0 | G3: 0 | H3: 0 | I3: 0
A4: aircraft | B4: 0 | C4: 0 | D4: 0 | E4: 0 | F4: 0 | G4: 0 | H4: 0 | I4: 0
A5: rail | B5: 0 | C5: 0 | D5: 0 | E5: 0 | F5: 0 | G5: 0 | H5: 0 | I5: 0
A6: ships | B6: 0 | C6: 0 | D6: 0 | E6: 0 | F6: 0 | G6: 0 | H6: 0 | I6: 0
A7: motorbikes | B7: =Data!A3 -> 0.0007 | C7: 0 | D7: 0 | E7: 0 | F7: 0 | G7: 0 | H7: 0 | I7: 0

Sheet SYBCbVT-freight
A1: Battery Capacity (MW*hr/vehicle | B1: battery electric vehicle | C1: natural gas vehicle | D1: gasoline vehicle | E1: diesel vehicle | F1: plugin hybrid vehicle | G1: LPG vehicle | H1: hydrogen vehicle | I1: nonroad vehicle
A2: LDVs | B2: ='Freight LDVs + HDVs'!C130/1000 -> 0.12295576 | C2: 0 | D2: 0 | E2: 0 | F2: ='SYBCbVT-passenger'!F2*B2/'SYBCbVT-passenger'!B2 -> 0.021412028 | G2: 0 | H2: 0 | I2: 0
A3: HDVs | B3: ='Freight LDVs + HDVs'!C131/1000 -> 0.86592241 | C3: 0 | D3: 0 | E3: 0 | F3: 0 | G3: 0 | H3: 0 | I3: 0
A4: aircraft | B4: 0 | C4: 0 | D4: 0 | E4: 0 | F4: 0 | G4: 0 | H4: 0 | I4: 0
A5: rail | B5: 0 | C5: 0 | D5: 0 | E5: 0 | F5: 0 | G5: 0 | H5: 0 | I5: 0
A6: ships | B6: 0 | C6: 0 | D6: 0 | E6: 0 | F6: 0 | G6: 0 | H6: 0 | I6: 0
A7: motorbikes | B7: =Data!A3 -> 0.0007 | C7: 0 | D7: 0 | E7: 0 | F7: 0 | G7: 0 | H7: 0 | I7: 0
